package com.sleepycat.b.i.b;

import com.sleepycat.b.i.c.b.aa;

public final class a
  extends c
{
  private final aa e;
  private s f = null;
  private ai g = null;
  private final b h;
  
  public a(x paramx, aa paramaa, b paramb)
  {
    super(paramaa, paramx, "Acceptor Thread " + paramaa.a.a);
    this.e = paramaa;
    this.h = paramb;
  }
  
  /* Error */
  public final void run()
  {
    // Byte code:
    //   0: aload_0
    //   1: getfield 49	com/sleepycat/b/i/b/a:e	Lcom/sleepycat/b/i/c/b/aa;
    //   4: getfield 64	com/sleepycat/b/i/c/b/aa:c	Lcom/sleepycat/b/i/h/x;
    //   7: astore 8
    //   9: aload 8
    //   11: ldc 66
    //   13: aload_0
    //   14: getfield 70	com/sleepycat/b/i/b/a:d	Ljava/util/concurrent/BlockingQueue;
    //   17: invokevirtual 75	com/sleepycat/b/i/h/x:a	(Ljava/lang/String;Ljava/util/concurrent/BlockingQueue;)V
    //   20: aload_0
    //   21: getfield 79	com/sleepycat/b/i/b/a:b	Ljava/util/logging/Logger;
    //   24: aload_0
    //   25: getfield 83	com/sleepycat/b/i/b/a:D	Lcom/sleepycat/b/c/ad;
    //   28: aload_0
    //   29: getfield 86	com/sleepycat/b/i/b/a:c	Ljava/util/logging/Formatter;
    //   32: getstatic 92	java/util/logging/Level:FINE	Ljava/util/logging/Level;
    //   35: ldc 94
    //   37: invokestatic 99	com/sleepycat/b/p/w:a	(Ljava/util/logging/Logger;Lcom/sleepycat/b/c/ad;Ljava/util/logging/Formatter;Ljava/util/logging/Level;Ljava/lang/String;)V
    //   40: aload 8
    //   42: ldc 66
    //   44: aload_0
    //   45: getfield 102	com/sleepycat/b/i/b/a:a	Lcom/sleepycat/b/i/b/x;
    //   48: getfield 108	com/sleepycat/b/i/c/ap:m	I
    //   51: invokevirtual 111	com/sleepycat/b/i/h/x:a	(Ljava/lang/String;I)Ljava/nio/channels/SocketChannel;
    //   54: astore_1
    //   55: aload_1
    //   56: ifnonnull +11 -> 67
    //   59: aload 8
    //   61: ldc 66
    //   63: invokevirtual 113	com/sleepycat/b/i/h/x:a	(Ljava/lang/String;)V
    //   66: return
    //   67: aload_1
    //   68: invokevirtual 119	java/nio/channels/SocketChannel:socket	()Ljava/net/Socket;
    //   71: astore 9
    //   73: aconst_null
    //   74: astore_2
    //   75: aconst_null
    //   76: astore 7
    //   78: aconst_null
    //   79: astore 6
    //   81: aconst_null
    //   82: astore_3
    //   83: aconst_null
    //   84: astore 5
    //   86: new 121	java/io/BufferedReader
    //   89: dup
    //   90: new 123	java/io/InputStreamReader
    //   93: dup
    //   94: aload 9
    //   96: invokevirtual 129	java/net/Socket:getInputStream	()Ljava/io/InputStream;
    //   99: invokespecial 132	java/io/InputStreamReader:<init>	(Ljava/io/InputStream;)V
    //   102: invokespecial 135	java/io/BufferedReader:<init>	(Ljava/io/Reader;)V
    //   105: astore_1
    //   106: new 137	java/io/PrintWriter
    //   109: dup
    //   110: aload 9
    //   112: invokevirtual 141	java/net/Socket:getOutputStream	()Ljava/io/OutputStream;
    //   115: iconst_1
    //   116: invokespecial 144	java/io/PrintWriter:<init>	(Ljava/io/OutputStream;Z)V
    //   119: astore_3
    //   120: aload_1
    //   121: invokevirtual 147	java/io/BufferedReader:readLine	()Ljava/lang/String;
    //   124: astore_2
    //   125: aload_2
    //   126: ifnonnull +63 -> 189
    //   129: aload_0
    //   130: getfield 79	com/sleepycat/b/i/b/a:b	Ljava/util/logging/Logger;
    //   133: aload_0
    //   134: getfield 83	com/sleepycat/b/i/b/a:D	Lcom/sleepycat/b/c/ad;
    //   137: aload_0
    //   138: getfield 86	com/sleepycat/b/i/b/a:c	Ljava/util/logging/Formatter;
    //   141: getstatic 92	java/util/logging/Level:FINE	Ljava/util/logging/Level;
    //   144: ldc -107
    //   146: invokestatic 99	com/sleepycat/b/p/w:a	(Ljava/util/logging/Logger;Lcom/sleepycat/b/c/ad;Ljava/util/logging/Formatter;Ljava/util/logging/Level;Ljava/lang/String;)V
    //   149: aload_0
    //   150: getfield 79	com/sleepycat/b/i/b/a:b	Ljava/util/logging/Logger;
    //   153: aload_0
    //   154: getfield 83	com/sleepycat/b/i/b/a:D	Lcom/sleepycat/b/c/ad;
    //   157: aload_0
    //   158: getfield 86	com/sleepycat/b/i/b/a:c	Ljava/util/logging/Formatter;
    //   161: aload 9
    //   163: aload_1
    //   164: aload_3
    //   165: invokestatic 154	com/sleepycat/b/i/b/ao:a	(Ljava/util/logging/Logger;Lcom/sleepycat/b/c/ad;Ljava/util/logging/Formatter;Ljava/net/Socket;Ljava/io/BufferedReader;Ljava/io/PrintWriter;)V
    //   168: goto -128 -> 40
    //   171: astore_1
    //   172: aload_0
    //   173: getfield 160	com/sleepycat/b/p/aj:E	Ljava/util/concurrent/atomic/AtomicBoolean;
    //   176: invokevirtual 166	java/util/concurrent/atomic/AtomicBoolean:get	()Z
    //   179: istore 16
    //   181: iload 16
    //   183: ifeq +905 -> 1088
    //   186: goto -127 -> 59
    //   189: aload_0
    //   190: getfield 102	com/sleepycat/b/i/b/a:a	Lcom/sleepycat/b/i/b/x;
    //   193: aload_2
    //   194: invokevirtual 171	com/sleepycat/b/i/b/x:c	(Ljava/lang/String;)Lcom/sleepycat/b/i/c/ay;
    //   197: astore 4
    //   199: aload 4
    //   201: invokevirtual 176	com/sleepycat/b/i/c/ay:a	()Lcom/sleepycat/b/i/c/av;
    //   204: aload_0
    //   205: getfield 102	com/sleepycat/b/i/b/a:a	Lcom/sleepycat/b/i/b/x;
    //   208: getfield 179	com/sleepycat/b/i/b/x:a	Lcom/sleepycat/b/i/c/av;
    //   211: if_acmpne +530 -> 741
    //   214: aload 4
    //   216: checkcast 181	com/sleepycat/b/i/b/ad
    //   219: astore_2
    //   220: aload_0
    //   221: getfield 45	com/sleepycat/b/i/b/a:f	Lcom/sleepycat/b/i/b/s;
    //   224: ifnull +229 -> 453
    //   227: aload_0
    //   228: getfield 45	com/sleepycat/b/i/b/a:f	Lcom/sleepycat/b/i/b/s;
    //   231: aload_2
    //   232: invokevirtual 184	com/sleepycat/b/i/b/ad:d	()Lcom/sleepycat/b/i/b/s;
    //   235: invokeinterface 190 2 0
    //   240: ifle +213 -> 453
    //   243: aload_0
    //   244: getfield 79	com/sleepycat/b/i/b/a:b	Ljava/util/logging/Logger;
    //   247: aload_0
    //   248: getfield 83	com/sleepycat/b/i/b/a:D	Lcom/sleepycat/b/c/ad;
    //   251: aload_0
    //   252: getfield 86	com/sleepycat/b/i/b/a:c	Ljava/util/logging/Formatter;
    //   255: getstatic 92	java/util/logging/Level:FINE	Ljava/util/logging/Level;
    //   258: new 16	java/lang/StringBuilder
    //   261: dup
    //   262: ldc -64
    //   264: invokespecial 21	java/lang/StringBuilder:<init>	(Ljava/lang/String;)V
    //   267: aload_2
    //   268: invokevirtual 184	com/sleepycat/b/i/b/ad:d	()Lcom/sleepycat/b/i/b/s;
    //   271: invokevirtual 195	java/lang/StringBuilder:append	(Ljava/lang/Object;)Ljava/lang/StringBuilder;
    //   274: ldc -59
    //   276: invokevirtual 36	java/lang/StringBuilder:append	(Ljava/lang/String;)Ljava/lang/StringBuilder;
    //   279: aload_0
    //   280: getfield 45	com/sleepycat/b/i/b/a:f	Lcom/sleepycat/b/i/b/s;
    //   283: invokevirtual 195	java/lang/StringBuilder:append	(Ljava/lang/Object;)Ljava/lang/StringBuilder;
    //   286: invokevirtual 40	java/lang/StringBuilder:toString	()Ljava/lang/String;
    //   289: invokestatic 99	com/sleepycat/b/p/w:a	(Ljava/util/logging/Logger;Lcom/sleepycat/b/c/ad;Ljava/util/logging/Formatter;Ljava/util/logging/Level;Ljava/lang/String;)V
    //   292: aload_0
    //   293: getfield 102	com/sleepycat/b/i/b/a:a	Lcom/sleepycat/b/i/b/x;
    //   296: astore_2
    //   297: aload_2
    //   298: invokevirtual 203	java/lang/Object:getClass	()Ljava/lang/Class;
    //   301: pop
    //   302: new 205	com/sleepycat/b/i/b/ae
    //   305: dup
    //   306: aload_2
    //   307: aload_0
    //   308: getfield 45	com/sleepycat/b/i/b/a:f	Lcom/sleepycat/b/i/b/s;
    //   311: invokespecial 208	com/sleepycat/b/i/b/ae:<init>	(Lcom/sleepycat/b/i/b/x;Lcom/sleepycat/b/i/b/s;)V
    //   314: astore_2
    //   315: aload_2
    //   316: aload 4
    //   318: getfield 213	com/sleepycat/b/i/c/as:i	Ljava/lang/String;
    //   321: invokevirtual 216	com/sleepycat/b/i/c/az:a	(Ljava/lang/String;)V
    //   324: aload_3
    //   325: aload_2
    //   326: invokevirtual 218	com/sleepycat/b/i/c/az:b	()Ljava/lang/String;
    //   329: invokevirtual 221	java/io/PrintWriter:println	(Ljava/lang/String;)V
    //   332: aload_0
    //   333: getfield 79	com/sleepycat/b/i/b/a:b	Ljava/util/logging/Logger;
    //   336: aload_0
    //   337: getfield 83	com/sleepycat/b/i/b/a:D	Lcom/sleepycat/b/c/ad;
    //   340: aload_0
    //   341: getfield 86	com/sleepycat/b/i/b/a:c	Ljava/util/logging/Formatter;
    //   344: aload 9
    //   346: aload_1
    //   347: aload_3
    //   348: invokestatic 154	com/sleepycat/b/i/b/ao:a	(Ljava/util/logging/Logger;Lcom/sleepycat/b/c/ad;Ljava/util/logging/Formatter;Ljava/net/Socket;Ljava/io/BufferedReader;Ljava/io/PrintWriter;)V
    //   351: goto -311 -> 40
    //   354: astore_1
    //   355: aload 8
    //   357: ldc 66
    //   359: invokevirtual 113	com/sleepycat/b/i/h/x:a	(Ljava/lang/String;)V
    //   362: aload_1
    //   363: athrow
    //   364: astore_2
    //   365: aload_0
    //   366: getfield 79	com/sleepycat/b/i/b/a:b	Ljava/util/logging/Logger;
    //   369: aload_0
    //   370: getfield 83	com/sleepycat/b/i/b/a:D	Lcom/sleepycat/b/c/ad;
    //   373: aload_0
    //   374: getfield 86	com/sleepycat/b/i/b/a:c	Ljava/util/logging/Formatter;
    //   377: getstatic 224	java/util/logging/Level:WARNING	Ljava/util/logging/Level;
    //   380: new 16	java/lang/StringBuilder
    //   383: dup
    //   384: ldc -30
    //   386: invokespecial 21	java/lang/StringBuilder:<init>	(Ljava/lang/String;)V
    //   389: aload_2
    //   390: invokevirtual 229	com/sleepycat/b/i/c/ar:getMessage	()Ljava/lang/String;
    //   393: invokevirtual 36	java/lang/StringBuilder:append	(Ljava/lang/String;)Ljava/lang/StringBuilder;
    //   396: invokevirtual 40	java/lang/StringBuilder:toString	()Ljava/lang/String;
    //   399: invokestatic 99	com/sleepycat/b/p/w:a	(Ljava/util/logging/Logger;Lcom/sleepycat/b/c/ad;Ljava/util/logging/Formatter;Ljava/util/logging/Level;Ljava/lang/String;)V
    //   402: aload_0
    //   403: getfield 102	com/sleepycat/b/i/b/a:a	Lcom/sleepycat/b/i/b/x;
    //   406: astore 4
    //   408: aload 4
    //   410: invokevirtual 203	java/lang/Object:getClass	()Ljava/lang/Class;
    //   413: pop
    //   414: aload_3
    //   415: new 231	com/sleepycat/b/i/c/ax
    //   418: dup
    //   419: aload 4
    //   421: aload_2
    //   422: invokespecial 234	com/sleepycat/b/i/c/ax:<init>	(Lcom/sleepycat/b/i/c/ap;Lcom/sleepycat/b/i/c/ar;)V
    //   425: invokevirtual 235	com/sleepycat/b/i/c/ax:b	()Ljava/lang/String;
    //   428: invokevirtual 221	java/io/PrintWriter:println	(Ljava/lang/String;)V
    //   431: aload_0
    //   432: getfield 79	com/sleepycat/b/i/b/a:b	Ljava/util/logging/Logger;
    //   435: aload_0
    //   436: getfield 83	com/sleepycat/b/i/b/a:D	Lcom/sleepycat/b/c/ad;
    //   439: aload_0
    //   440: getfield 86	com/sleepycat/b/i/b/a:c	Ljava/util/logging/Formatter;
    //   443: aload 9
    //   445: aload_1
    //   446: aload_3
    //   447: invokestatic 154	com/sleepycat/b/i/b/ao:a	(Ljava/util/logging/Logger;Lcom/sleepycat/b/c/ad;Ljava/util/logging/Formatter;Ljava/net/Socket;Ljava/io/BufferedReader;Ljava/io/PrintWriter;)V
    //   450: goto -410 -> 40
    //   453: aload_0
    //   454: aload_2
    //   455: invokevirtual 184	com/sleepycat/b/i/b/ad:d	()Lcom/sleepycat/b/i/b/s;
    //   458: putfield 45	com/sleepycat/b/i/b/a:f	Lcom/sleepycat/b/i/b/s;
    //   461: aload_0
    //   462: getfield 51	com/sleepycat/b/i/b/a:h	Lcom/sleepycat/b/i/b/b;
    //   465: invokeinterface 240 1 0
    //   470: astore_2
    //   471: aload_0
    //   472: getfield 51	com/sleepycat/b/i/b/a:h	Lcom/sleepycat/b/i/b/b;
    //   475: aload_0
    //   476: getfield 45	com/sleepycat/b/i/b/a:f	Lcom/sleepycat/b/i/b/s;
    //   479: invokeinterface 243 2 0
    //   484: lstore 14
    //   486: aload_0
    //   487: getfield 79	com/sleepycat/b/i/b/a:b	Ljava/util/logging/Logger;
    //   490: aload_0
    //   491: getfield 83	com/sleepycat/b/i/b/a:D	Lcom/sleepycat/b/c/ad;
    //   494: aload_0
    //   495: getfield 86	com/sleepycat/b/i/b/a:c	Ljava/util/logging/Formatter;
    //   498: getstatic 92	java/util/logging/Level:FINE	Ljava/util/logging/Level;
    //   501: new 16	java/lang/StringBuilder
    //   504: dup
    //   505: ldc -11
    //   507: invokespecial 21	java/lang/StringBuilder:<init>	(Ljava/lang/String;)V
    //   510: aload_0
    //   511: getfield 45	com/sleepycat/b/i/b/a:f	Lcom/sleepycat/b/i/b/s;
    //   514: invokevirtual 195	java/lang/StringBuilder:append	(Ljava/lang/Object;)Ljava/lang/StringBuilder;
    //   517: ldc -9
    //   519: invokevirtual 36	java/lang/StringBuilder:append	(Ljava/lang/String;)Ljava/lang/StringBuilder;
    //   522: aload_2
    //   523: invokevirtual 195	java/lang/StringBuilder:append	(Ljava/lang/Object;)Ljava/lang/StringBuilder;
    //   526: ldc -7
    //   528: invokevirtual 36	java/lang/StringBuilder:append	(Ljava/lang/String;)Ljava/lang/StringBuilder;
    //   531: lload 14
    //   533: invokevirtual 252	java/lang/StringBuilder:append	(J)Ljava/lang/StringBuilder;
    //   536: invokevirtual 40	java/lang/StringBuilder:toString	()Ljava/lang/String;
    //   539: invokestatic 99	com/sleepycat/b/p/w:a	(Ljava/util/logging/Logger;Lcom/sleepycat/b/c/ad;Ljava/util/logging/Formatter;Ljava/util/logging/Level;Ljava/lang/String;)V
    //   542: aload_0
    //   543: getfield 102	com/sleepycat/b/i/b/a:a	Lcom/sleepycat/b/i/b/x;
    //   546: astore 5
    //   548: aload 5
    //   550: invokevirtual 203	java/lang/Object:getClass	()Ljava/lang/Class;
    //   553: pop
    //   554: aload_0
    //   555: getfield 45	com/sleepycat/b/i/b/a:f	Lcom/sleepycat/b/i/b/s;
    //   558: astore 6
    //   560: aload_0
    //   561: getfield 47	com/sleepycat/b/i/b/a:g	Lcom/sleepycat/b/i/b/ai;
    //   564: astore 7
    //   566: aload_0
    //   567: getfield 49	com/sleepycat/b/i/b/a:e	Lcom/sleepycat/b/i/c/b/aa;
    //   570: astore 10
    //   572: aload 10
    //   574: getfield 255	com/sleepycat/b/i/c/b/aa:i	Lcom/sleepycat/b/i/c/aj;
    //   577: getfield 261	com/sleepycat/b/c/ad:u	Lcom/sleepycat/b/c/m;
    //   580: getstatic 267	com/sleepycat/b/i/c/an:r	Lcom/sleepycat/b/b/e;
    //   583: invokevirtual 272	com/sleepycat/b/c/m:a	(Lcom/sleepycat/b/b/e;)I
    //   586: istore 12
    //   588: getstatic 267	com/sleepycat/b/i/c/an:r	Lcom/sleepycat/b/b/e;
    //   591: getfield 276	com/sleepycat/b/b/b:b	Ljava/lang/String;
    //   594: invokestatic 282	java/lang/Integer:parseInt	(Ljava/lang/String;)I
    //   597: istore 13
    //   599: iload 12
    //   601: istore 11
    //   603: aload 10
    //   605: getfield 255	com/sleepycat/b/i/c/b/aa:i	Lcom/sleepycat/b/i/c/aj;
    //   608: getfield 261	com/sleepycat/b/c/ad:u	Lcom/sleepycat/b/c/m;
    //   611: getstatic 286	com/sleepycat/b/i/c/an:s	Lcom/sleepycat/b/b/a;
    //   614: invokevirtual 289	com/sleepycat/b/c/m:a	(Lcom/sleepycat/b/b/a;)Z
    //   617: ifeq +20 -> 637
    //   620: iload 12
    //   622: istore 11
    //   624: iload 12
    //   626: iload 13
    //   628: if_icmpne +9 -> 637
    //   631: iload 13
    //   633: iconst_1
    //   634: iadd
    //   635: istore 11
    //   637: new 291	com/sleepycat/b/i/b/ac
    //   640: dup
    //   641: aload 5
    //   643: aload 6
    //   645: aload 7
    //   647: aload_2
    //   648: lload 14
    //   650: iload 11
    //   652: aload_0
    //   653: getfield 49	com/sleepycat/b/i/b/a:e	Lcom/sleepycat/b/i/c/b/aa;
    //   656: getfield 294	com/sleepycat/b/i/c/b/aa:B	I
    //   659: getstatic 299	com/sleepycat/b/am:a	Lcom/sleepycat/b/am;
    //   662: invokespecial 302	com/sleepycat/b/i/b/ac:<init>	(Lcom/sleepycat/b/i/b/x;Lcom/sleepycat/b/i/b/s;Lcom/sleepycat/b/i/b/ai;Lcom/sleepycat/b/i/b/ai;JIILcom/sleepycat/b/am;)V
    //   665: astore_2
    //   666: goto -351 -> 315
    //   669: astore 4
    //   671: aload_3
    //   672: astore 5
    //   674: aload_1
    //   675: astore_2
    //   676: aload 5
    //   678: astore_3
    //   679: aload_0
    //   680: getfield 79	com/sleepycat/b/i/b/a:b	Ljava/util/logging/Logger;
    //   683: aload_0
    //   684: getfield 83	com/sleepycat/b/i/b/a:D	Lcom/sleepycat/b/c/ad;
    //   687: aload_0
    //   688: getfield 86	com/sleepycat/b/i/b/a:c	Ljava/util/logging/Formatter;
    //   691: getstatic 224	java/util/logging/Level:WARNING	Ljava/util/logging/Level;
    //   694: new 16	java/lang/StringBuilder
    //   697: dup
    //   698: ldc_w 304
    //   701: invokespecial 21	java/lang/StringBuilder:<init>	(Ljava/lang/String;)V
    //   704: aload 4
    //   706: invokevirtual 305	java/io/IOException:getMessage	()Ljava/lang/String;
    //   709: invokevirtual 36	java/lang/StringBuilder:append	(Ljava/lang/String;)Ljava/lang/StringBuilder;
    //   712: invokevirtual 40	java/lang/StringBuilder:toString	()Ljava/lang/String;
    //   715: invokestatic 99	com/sleepycat/b/p/w:a	(Ljava/util/logging/Logger;Lcom/sleepycat/b/c/ad;Ljava/util/logging/Formatter;Ljava/util/logging/Level;Ljava/lang/String;)V
    //   718: aload_0
    //   719: getfield 79	com/sleepycat/b/i/b/a:b	Ljava/util/logging/Logger;
    //   722: aload_0
    //   723: getfield 83	com/sleepycat/b/i/b/a:D	Lcom/sleepycat/b/c/ad;
    //   726: aload_0
    //   727: getfield 86	com/sleepycat/b/i/b/a:c	Ljava/util/logging/Formatter;
    //   730: aload 9
    //   732: aload_1
    //   733: aload 5
    //   735: invokestatic 154	com/sleepycat/b/i/b/ao:a	(Ljava/util/logging/Logger;Lcom/sleepycat/b/c/ad;Ljava/util/logging/Formatter;Ljava/net/Socket;Ljava/io/BufferedReader;Ljava/io/PrintWriter;)V
    //   738: goto -698 -> 40
    //   741: aload 4
    //   743: invokevirtual 176	com/sleepycat/b/i/c/ay:a	()Lcom/sleepycat/b/i/c/av;
    //   746: aload_0
    //   747: getfield 102	com/sleepycat/b/i/b/a:a	Lcom/sleepycat/b/i/b/x;
    //   750: getfield 307	com/sleepycat/b/i/b/x:b	Lcom/sleepycat/b/i/c/av;
    //   753: if_acmpne +212 -> 965
    //   756: aload 4
    //   758: checkcast 309	com/sleepycat/b/i/b/y
    //   761: astore_2
    //   762: aload_0
    //   763: getfield 45	com/sleepycat/b/i/b/a:f	Lcom/sleepycat/b/i/b/s;
    //   766: ifnull +95 -> 861
    //   769: aload_0
    //   770: getfield 45	com/sleepycat/b/i/b/a:f	Lcom/sleepycat/b/i/b/s;
    //   773: aload_2
    //   774: invokevirtual 310	com/sleepycat/b/i/b/y:d	()Lcom/sleepycat/b/i/b/s;
    //   777: invokeinterface 190 2 0
    //   782: ifeq +79 -> 861
    //   785: aload_0
    //   786: getfield 79	com/sleepycat/b/i/b/a:b	Ljava/util/logging/Logger;
    //   789: aload_0
    //   790: getfield 83	com/sleepycat/b/i/b/a:D	Lcom/sleepycat/b/c/ad;
    //   793: aload_0
    //   794: getfield 86	com/sleepycat/b/i/b/a:c	Ljava/util/logging/Formatter;
    //   797: getstatic 92	java/util/logging/Level:FINE	Ljava/util/logging/Level;
    //   800: new 16	java/lang/StringBuilder
    //   803: dup
    //   804: ldc_w 312
    //   807: invokespecial 21	java/lang/StringBuilder:<init>	(Ljava/lang/String;)V
    //   810: aload_2
    //   811: invokevirtual 310	com/sleepycat/b/i/b/y:d	()Lcom/sleepycat/b/i/b/s;
    //   814: invokevirtual 195	java/lang/StringBuilder:append	(Ljava/lang/Object;)Ljava/lang/StringBuilder;
    //   817: ldc -59
    //   819: invokevirtual 36	java/lang/StringBuilder:append	(Ljava/lang/String;)Ljava/lang/StringBuilder;
    //   822: aload_0
    //   823: getfield 45	com/sleepycat/b/i/b/a:f	Lcom/sleepycat/b/i/b/s;
    //   826: invokevirtual 195	java/lang/StringBuilder:append	(Ljava/lang/Object;)Ljava/lang/StringBuilder;
    //   829: invokevirtual 40	java/lang/StringBuilder:toString	()Ljava/lang/String;
    //   832: invokestatic 99	com/sleepycat/b/p/w:a	(Ljava/util/logging/Logger;Lcom/sleepycat/b/c/ad;Ljava/util/logging/Formatter;Ljava/util/logging/Level;Ljava/lang/String;)V
    //   835: aload_0
    //   836: getfield 102	com/sleepycat/b/i/b/a:a	Lcom/sleepycat/b/i/b/x;
    //   839: astore_2
    //   840: aload_2
    //   841: invokevirtual 203	java/lang/Object:getClass	()Ljava/lang/Class;
    //   844: pop
    //   845: new 205	com/sleepycat/b/i/b/ae
    //   848: dup
    //   849: aload_2
    //   850: aload_0
    //   851: getfield 45	com/sleepycat/b/i/b/a:f	Lcom/sleepycat/b/i/b/s;
    //   854: invokespecial 208	com/sleepycat/b/i/b/ae:<init>	(Lcom/sleepycat/b/i/b/x;Lcom/sleepycat/b/i/b/s;)V
    //   857: astore_2
    //   858: goto +292 -> 1150
    //   861: aload_0
    //   862: aload_2
    //   863: getfield 314	com/sleepycat/b/i/b/y:a	Lcom/sleepycat/b/i/b/ai;
    //   866: putfield 47	com/sleepycat/b/i/b/a:g	Lcom/sleepycat/b/i/b/ai;
    //   869: aload_0
    //   870: getfield 79	com/sleepycat/b/i/b/a:b	Ljava/util/logging/Logger;
    //   873: aload_0
    //   874: getfield 83	com/sleepycat/b/i/b/a:D	Lcom/sleepycat/b/c/ad;
    //   877: aload_0
    //   878: getfield 86	com/sleepycat/b/i/b/a:c	Ljava/util/logging/Formatter;
    //   881: getstatic 92	java/util/logging/Level:FINE	Ljava/util/logging/Level;
    //   884: new 16	java/lang/StringBuilder
    //   887: dup
    //   888: ldc -11
    //   890: invokespecial 21	java/lang/StringBuilder:<init>	(Ljava/lang/String;)V
    //   893: aload_0
    //   894: getfield 45	com/sleepycat/b/i/b/a:f	Lcom/sleepycat/b/i/b/s;
    //   897: invokevirtual 195	java/lang/StringBuilder:append	(Ljava/lang/Object;)Ljava/lang/StringBuilder;
    //   900: ldc_w 316
    //   903: invokevirtual 36	java/lang/StringBuilder:append	(Ljava/lang/String;)Ljava/lang/StringBuilder;
    //   906: aload_2
    //   907: invokevirtual 310	com/sleepycat/b/i/b/y:d	()Lcom/sleepycat/b/i/b/s;
    //   910: invokevirtual 195	java/lang/StringBuilder:append	(Ljava/lang/Object;)Ljava/lang/StringBuilder;
    //   913: ldc_w 318
    //   916: invokevirtual 36	java/lang/StringBuilder:append	(Ljava/lang/String;)Ljava/lang/StringBuilder;
    //   919: aload_0
    //   920: getfield 47	com/sleepycat/b/i/b/a:g	Lcom/sleepycat/b/i/b/ai;
    //   923: invokevirtual 195	java/lang/StringBuilder:append	(Ljava/lang/Object;)Ljava/lang/StringBuilder;
    //   926: invokevirtual 40	java/lang/StringBuilder:toString	()Ljava/lang/String;
    //   929: invokestatic 99	com/sleepycat/b/p/w:a	(Ljava/util/logging/Logger;Lcom/sleepycat/b/c/ad;Ljava/util/logging/Formatter;Ljava/util/logging/Level;Ljava/lang/String;)V
    //   932: aload_0
    //   933: getfield 102	com/sleepycat/b/i/b/a:a	Lcom/sleepycat/b/i/b/x;
    //   936: astore 5
    //   938: aload 5
    //   940: invokevirtual 203	java/lang/Object:getClass	()Ljava/lang/Class;
    //   943: pop
    //   944: new 320	com/sleepycat/b/i/b/z
    //   947: dup
    //   948: aload 5
    //   950: aload_2
    //   951: invokevirtual 310	com/sleepycat/b/i/b/y:d	()Lcom/sleepycat/b/i/b/s;
    //   954: aload_0
    //   955: getfield 47	com/sleepycat/b/i/b/a:g	Lcom/sleepycat/b/i/b/ai;
    //   958: invokespecial 323	com/sleepycat/b/i/b/z:<init>	(Lcom/sleepycat/b/i/b/x;Lcom/sleepycat/b/i/b/s;Lcom/sleepycat/b/i/b/ai;)V
    //   961: astore_2
    //   962: goto +188 -> 1150
    //   965: aload 4
    //   967: invokevirtual 176	com/sleepycat/b/i/c/ay:a	()Lcom/sleepycat/b/i/c/av;
    //   970: astore 4
    //   972: aload_0
    //   973: getfield 102	com/sleepycat/b/i/b/a:a	Lcom/sleepycat/b/i/b/x;
    //   976: getfield 325	com/sleepycat/b/i/b/x:e	Lcom/sleepycat/b/i/c/av;
    //   979: astore 5
    //   981: aload 4
    //   983: aload 5
    //   985: if_acmpne +25 -> 1010
    //   988: aload_0
    //   989: getfield 79	com/sleepycat/b/i/b/a:b	Ljava/util/logging/Logger;
    //   992: aload_0
    //   993: getfield 83	com/sleepycat/b/i/b/a:D	Lcom/sleepycat/b/c/ad;
    //   996: aload_0
    //   997: getfield 86	com/sleepycat/b/i/b/a:c	Ljava/util/logging/Formatter;
    //   1000: aload 9
    //   1002: aload_1
    //   1003: aload_3
    //   1004: invokestatic 154	com/sleepycat/b/i/b/ao:a	(Ljava/util/logging/Logger;Lcom/sleepycat/b/c/ad;Ljava/util/logging/Formatter;Ljava/net/Socket;Ljava/io/BufferedReader;Ljava/io/PrintWriter;)V
    //   1007: goto -948 -> 59
    //   1010: aload_0
    //   1011: getfield 79	com/sleepycat/b/i/b/a:b	Ljava/util/logging/Logger;
    //   1014: aload_0
    //   1015: getfield 83	com/sleepycat/b/i/b/a:D	Lcom/sleepycat/b/c/ad;
    //   1018: aload_0
    //   1019: getfield 86	com/sleepycat/b/i/b/a:c	Ljava/util/logging/Formatter;
    //   1022: getstatic 328	java/util/logging/Level:SEVERE	Ljava/util/logging/Level;
    //   1025: new 16	java/lang/StringBuilder
    //   1028: dup
    //   1029: ldc_w 330
    //   1032: invokespecial 21	java/lang/StringBuilder:<init>	(Ljava/lang/String;)V
    //   1035: aload_2
    //   1036: invokevirtual 36	java/lang/StringBuilder:append	(Ljava/lang/String;)Ljava/lang/StringBuilder;
    //   1039: invokevirtual 40	java/lang/StringBuilder:toString	()Ljava/lang/String;
    //   1042: invokestatic 99	com/sleepycat/b/p/w:a	(Ljava/util/logging/Logger;Lcom/sleepycat/b/c/ad;Ljava/util/logging/Formatter;Ljava/util/logging/Level;Ljava/lang/String;)V
    //   1045: aload_0
    //   1046: getfield 79	com/sleepycat/b/i/b/a:b	Ljava/util/logging/Logger;
    //   1049: aload_0
    //   1050: getfield 83	com/sleepycat/b/i/b/a:D	Lcom/sleepycat/b/c/ad;
    //   1053: aload_0
    //   1054: getfield 86	com/sleepycat/b/i/b/a:c	Ljava/util/logging/Formatter;
    //   1057: aload 9
    //   1059: aload_1
    //   1060: aload_3
    //   1061: invokestatic 154	com/sleepycat/b/i/b/ao:a	(Ljava/util/logging/Logger;Lcom/sleepycat/b/c/ad;Ljava/util/logging/Formatter;Ljava/net/Socket;Ljava/io/BufferedReader;Ljava/io/PrintWriter;)V
    //   1064: goto -1024 -> 40
    //   1067: aload_0
    //   1068: getfield 79	com/sleepycat/b/i/b/a:b	Ljava/util/logging/Logger;
    //   1071: aload_0
    //   1072: getfield 83	com/sleepycat/b/i/b/a:D	Lcom/sleepycat/b/c/ad;
    //   1075: aload_0
    //   1076: getfield 86	com/sleepycat/b/i/b/a:c	Ljava/util/logging/Formatter;
    //   1079: aload 9
    //   1081: aload_2
    //   1082: aload_3
    //   1083: invokestatic 154	com/sleepycat/b/i/b/ao:a	(Ljava/util/logging/Logger;Lcom/sleepycat/b/c/ad;Ljava/util/logging/Formatter;Ljava/net/Socket;Ljava/io/BufferedReader;Ljava/io/PrintWriter;)V
    //   1086: aload_1
    //   1087: athrow
    //   1088: aload_0
    //   1089: getfield 79	com/sleepycat/b/i/b/a:b	Ljava/util/logging/Logger;
    //   1092: aload_0
    //   1093: getfield 83	com/sleepycat/b/i/b/a:D	Lcom/sleepycat/b/c/ad;
    //   1096: aload_0
    //   1097: getfield 86	com/sleepycat/b/i/b/a:c	Ljava/util/logging/Formatter;
    //   1100: getstatic 224	java/util/logging/Level:WARNING	Ljava/util/logging/Level;
    //   1103: ldc_w 332
    //   1106: invokestatic 99	com/sleepycat/b/p/w:a	(Ljava/util/logging/Logger;Lcom/sleepycat/b/c/ad;Ljava/util/logging/Formatter;Ljava/util/logging/Level;Ljava/lang/String;)V
    //   1109: aload_1
    //   1110: invokestatic 337	com/sleepycat/b/aa:a	(Ljava/lang/Exception;)Lcom/sleepycat/b/aa;
    //   1113: athrow
    //   1114: astore 4
    //   1116: aload_1
    //   1117: astore_2
    //   1118: aload 6
    //   1120: astore_3
    //   1121: aload 4
    //   1123: astore_1
    //   1124: goto -57 -> 1067
    //   1127: astore 4
    //   1129: aload_1
    //   1130: astore_2
    //   1131: aload 4
    //   1133: astore_1
    //   1134: goto -67 -> 1067
    //   1137: astore 4
    //   1139: aload 7
    //   1141: astore_1
    //   1142: goto -468 -> 674
    //   1145: astore 4
    //   1147: goto -473 -> 674
    //   1150: goto -835 -> 315
    //   1153: astore_1
    //   1154: goto -87 -> 1067
    // Local variable table:
    //   start	length	slot	name	signature
    //   0	1157	0	this	a
    //   54	110	1	localObject1	Object
    //   171	176	1	localInterruptedException	InterruptedException
    //   354	763	1	localBufferedReader	java.io.BufferedReader
    //   1123	19	1	localObject2	Object
    //   1153	1	1	localObject3	Object
    //   74	252	2	localObject4	Object
    //   364	91	2	localar	com.sleepycat.b.i.c.ar
    //   470	661	2	localObject5	Object
    //   82	1039	3	localObject6	Object
    //   197	223	4	localObject7	Object
    //   669	297	4	localIOException1	java.io.IOException
    //   970	12	4	localav	com.sleepycat.b.i.c.av
    //   1114	8	4	localObject8	Object
    //   1127	5	4	localObject9	Object
    //   1137	1	4	localIOException2	java.io.IOException
    //   1145	1	4	localIOException3	java.io.IOException
    //   84	900	5	localObject10	Object
    //   79	1040	6	locals	s
    //   76	1064	7	localai	ai
    //   7	349	8	localx	com.sleepycat.b.i.h.x
    //   71	1009	9	localSocket	java.net.Socket
    //   570	34	10	localaa	aa
    //   601	50	11	i	int
    //   586	43	12	j	int
    //   597	38	13	k	int
    //   484	165	14	l	long
    //   179	3	16	bool	boolean
    // Exception table:
    //   from	to	target	type
    //   40	55	171	java/lang/InterruptedException
    //   67	73	171	java/lang/InterruptedException
    //   149	168	171	java/lang/InterruptedException
    //   332	351	171	java/lang/InterruptedException
    //   431	450	171	java/lang/InterruptedException
    //   718	738	171	java/lang/InterruptedException
    //   988	1007	171	java/lang/InterruptedException
    //   1045	1064	171	java/lang/InterruptedException
    //   1067	1088	171	java/lang/InterruptedException
    //   40	55	354	finally
    //   67	73	354	finally
    //   149	168	354	finally
    //   172	181	354	finally
    //   332	351	354	finally
    //   431	450	354	finally
    //   718	738	354	finally
    //   988	1007	354	finally
    //   1045	1064	354	finally
    //   1067	1088	354	finally
    //   1088	1114	354	finally
    //   189	199	364	com/sleepycat/b/i/c/ar
    //   120	125	669	java/io/IOException
    //   129	149	669	java/io/IOException
    //   189	199	669	java/io/IOException
    //   199	315	669	java/io/IOException
    //   315	332	669	java/io/IOException
    //   365	431	669	java/io/IOException
    //   453	599	669	java/io/IOException
    //   603	620	669	java/io/IOException
    //   637	666	669	java/io/IOException
    //   741	858	669	java/io/IOException
    //   861	962	669	java/io/IOException
    //   965	981	669	java/io/IOException
    //   1010	1045	669	java/io/IOException
    //   106	120	1114	finally
    //   120	125	1127	finally
    //   129	149	1127	finally
    //   189	199	1127	finally
    //   199	315	1127	finally
    //   315	332	1127	finally
    //   365	431	1127	finally
    //   453	599	1127	finally
    //   603	620	1127	finally
    //   637	666	1127	finally
    //   741	858	1127	finally
    //   861	962	1127	finally
    //   965	981	1127	finally
    //   1010	1045	1127	finally
    //   86	106	1137	java/io/IOException
    //   106	120	1145	java/io/IOException
    //   86	106	1153	finally
    //   679	718	1153	finally
  }
}


/* Location:              E:\apk\xueqiu2\classes-dex2jar.jar!\com\sleepycat\b\i\b\a.class
 * Java compiler version: 6 (50.0)
 * JD-Core Version:       0.7.1
 */