package com.sleepycat.b.i.b;

import com.sleepycat.b.i.c.aj;
import com.sleepycat.b.i.c.au;
import com.sleepycat.b.i.c.ay;
import com.sleepycat.b.i.c.az;
import com.sleepycat.b.p.al;
import com.sleepycat.b.p.w;
import java.net.InetSocketAddress;
import java.util.Iterator;
import java.util.LinkedList;
import java.util.List;
import java.util.Set;
import java.util.concurrent.ExecutionException;
import java.util.concurrent.ExecutorService;
import java.util.concurrent.Executors;
import java.util.concurrent.Future;
import java.util.logging.Formatter;
import java.util.logging.Level;
import java.util.logging.Logger;

public final class j
  extends c
{
  private final com.sleepycat.b.i.h.x e;
  private final List<k> f = new LinkedList();
  private s g = null;
  private ai h = null;
  
  public j(x paramx, com.sleepycat.b.i.c.b.aa paramaa)
  {
    this(paramaa, paramx, paramaa.c);
  }
  
  private j(com.sleepycat.b.i.c.b.aa paramaa, x paramx, com.sleepycat.b.i.h.x paramx1)
  {
    super(paramaa, paramx, "Learner Thread " + paramx.k.a);
    this.e = paramx1;
    a(new k()
    {
      public final void a(s paramAnonymouss, ai paramAnonymousai)
      {
        w.a(j.this.b, j.a(j.this), j.this.c, Level.FINE, "Learner notified. Proposal:" + paramAnonymouss + " Value: " + paramAnonymousai);
      }
    });
  }
  
  /* Error */
  private void a(java.net.Socket paramSocket, ay paramay)
  {
    // Byte code:
    //   0: aload_0
    //   1: monitorenter
    //   2: aload_0
    //   3: getfield 67	com/sleepycat/b/i/b/j:g	Lcom/sleepycat/b/i/b/s;
    //   6: ifnull +12 -> 18
    //   9: aload_0
    //   10: getfield 69	com/sleepycat/b/i/b/j:h	Lcom/sleepycat/b/i/b/ai;
    //   13: astore_3
    //   14: aload_3
    //   15: ifnonnull +6 -> 21
    //   18: aload_0
    //   19: monitorexit
    //   20: return
    //   21: aload_0
    //   22: getfield 82	com/sleepycat/b/i/b/j:D	Lcom/sleepycat/b/c/ad;
    //   25: ifnull -7 -> 18
    //   28: aload_0
    //   29: getfield 82	com/sleepycat/b/i/b/j:D	Lcom/sleepycat/b/c/ad;
    //   32: checkcast 85	com/sleepycat/b/i/c/aj
    //   35: getfield 89	com/sleepycat/b/i/c/aj:ap	Lcom/sleepycat/b/i/c/b/z;
    //   38: invokevirtual 94	com/sleepycat/b/i/c/b/z:a	()Lcom/sleepycat/b/i/u;
    //   41: astore_3
    //   42: aload_3
    //   43: getstatic 99	com/sleepycat/b/i/u:c	Lcom/sleepycat/b/i/u;
    //   46: if_acmpeq +14 -> 60
    //   49: getstatic 102	com/sleepycat/b/i/u:d	Lcom/sleepycat/b/i/u;
    //   52: astore 4
    //   54: aload_3
    //   55: aload 4
    //   57: if_acmpne +83 -> 140
    //   60: iconst_1
    //   61: istore 5
    //   63: iload 5
    //   65: ifeq -47 -> 18
    //   68: new 104	java/io/PrintWriter
    //   71: dup
    //   72: aload_1
    //   73: invokevirtual 110	java/net/Socket:getOutputStream	()Ljava/io/OutputStream;
    //   76: iconst_1
    //   77: invokespecial 113	java/io/PrintWriter:<init>	(Ljava/io/OutputStream;Z)V
    //   80: astore_3
    //   81: aload_0
    //   82: getfield 116	com/sleepycat/b/i/b/j:a	Lcom/sleepycat/b/i/b/x;
    //   85: astore_1
    //   86: aload_1
    //   87: invokevirtual 122	java/lang/Object:getClass	()Ljava/lang/Class;
    //   90: pop
    //   91: new 124	com/sleepycat/b/i/b/ab
    //   94: dup
    //   95: aload_1
    //   96: aload_0
    //   97: getfield 67	com/sleepycat/b/i/b/j:g	Lcom/sleepycat/b/i/b/s;
    //   100: aload_0
    //   101: getfield 69	com/sleepycat/b/i/b/j:h	Lcom/sleepycat/b/i/b/ai;
    //   104: invokespecial 127	com/sleepycat/b/i/b/ab:<init>	(Lcom/sleepycat/b/i/b/x;Lcom/sleepycat/b/i/b/s;Lcom/sleepycat/b/i/b/ai;)V
    //   107: astore_1
    //   108: aload_1
    //   109: aload_2
    //   110: getfield 132	com/sleepycat/b/i/c/as:i	Ljava/lang/String;
    //   113: invokevirtual 134	com/sleepycat/b/i/b/ab:a	(Ljava/lang/String;)V
    //   116: aload_3
    //   117: aload_1
    //   118: invokevirtual 137	com/sleepycat/b/i/b/ab:b	()Ljava/lang/String;
    //   121: invokevirtual 140	java/io/PrintWriter:println	(Ljava/lang/String;)V
    //   124: aload_3
    //   125: ifnull -107 -> 18
    //   128: aload_3
    //   129: invokevirtual 143	java/io/PrintWriter:close	()V
    //   132: goto -114 -> 18
    //   135: astore_1
    //   136: aload_0
    //   137: monitorexit
    //   138: aload_1
    //   139: athrow
    //   140: iconst_0
    //   141: istore 5
    //   143: goto -80 -> 63
    //   146: astore_1
    //   147: aconst_null
    //   148: astore_2
    //   149: aload_2
    //   150: ifnull +7 -> 157
    //   153: aload_2
    //   154: invokevirtual 143	java/io/PrintWriter:close	()V
    //   157: aload_1
    //   158: athrow
    //   159: astore_1
    //   160: aload_3
    //   161: astore_2
    //   162: goto -13 -> 149
    // Local variable table:
    //   start	length	slot	name	signature
    //   0	165	0	this	j
    //   0	165	1	paramSocket	java.net.Socket
    //   0	165	2	paramay	ay
    //   13	148	3	localObject	Object
    //   52	4	4	localu	com.sleepycat.b.i.u
    //   61	81	5	i	int
    // Exception table:
    //   from	to	target	type
    //   2	14	135	finally
    //   21	54	135	finally
    //   128	132	135	finally
    //   153	157	135	finally
    //   157	159	135	finally
    //   68	81	146	finally
    //   81	124	159	finally
  }
  
  public static void a(Set<InetSocketAddress> paramSet, v paramv, x paramx, ExecutorService paramExecutorService, Logger paramLogger, aj paramaj, Formatter paramFormatter)
  {
    if ((paramSet == null) || (paramSet.size() == 0)) {
      throw com.sleepycat.b.aa.c("There must be at least one learner");
    }
    w.a(paramLogger, paramaj, paramFormatter, Level.FINE, "Informing " + paramSet.size() + " learners.");
    paramx.getClass();
    paramv = ao.a(paramSet, "Learner", new af(paramx, paramv.a, paramv.b), paramExecutorService).iterator();
    int i = 0;
    while (paramv.hasNext())
    {
      paramx = (Future)paramv.next();
      try
      {
        paramx = (au)paramx.get();
        if (paramx.a() == null) {
          w.a(paramLogger, paramaj, paramFormatter, Level.FINE, "No response from: " + paramx.a + " reason: " + paramx.b);
        }
      }
      catch (InterruptedException paramx)
      {
        w.a(paramLogger, paramaj, paramFormatter, Level.FINE, "informLearners: interrupted while informing ");
        i += 1;
      }
      catch (ExecutionException paramx)
      {
        w.a(paramLogger, paramaj, paramFormatter, Level.FINE, "informLearners: exception while informing " + paramx.getMessage());
        i += 1;
      }
    }
    w.a(paramLogger, paramaj, paramFormatter, Level.FINE, "Informed learners: " + (paramSet.size() - i));
  }
  
  protected final Logger a()
  {
    return this.b;
  }
  
  public final void a(k paramk)
  {
    synchronized (this.f)
    {
      if (!this.f.contains(paramk)) {
        this.f.add(paramk);
      }
      return;
    }
  }
  
  public final void a(s arg1, ai paramai)
  {
    for (;;)
    {
      try
      {
        if ((this.g != null) && (???.compareTo(this.g) < 0))
        {
          w.a(this.b, this.D, this.c, Level.FINE, "Ignoring obsolete winner: " + ???);
          return;
        }
        this.g = ???;
        this.h = paramai;
        synchronized (this.f)
        {
          paramai = this.f.iterator();
          if (paramai.hasNext())
          {
            k localk = (k)paramai.next();
            try
            {
              localk.a(this.g, this.h);
            }
            catch (Exception localException)
            {
              localException.printStackTrace();
              w.a(this.b, this.D, this.c, Level.SEVERE, "Exception in Learner Listener: " + localException.getMessage());
            }
          }
        }
      }
      finally {}
    }
  }
  
  public final void a(Set<InetSocketAddress> paramSet)
  {
    if (paramSet.size() <= 0) {
      return;
    }
    ExecutorService localExecutorService = Executors.newFixedThreadPool(Math.min(paramSet.size(), 10), new al("JE Learner", this.b));
    try
    {
      Object localObject = this.a;
      localObject.getClass();
      localObject = new aa((x)localObject);
      List localList = ao.a(paramSet, "Learner", (ay)localObject, localExecutorService);
      w.a(this.b, this.D, this.c, Level.FINE, "Sent master request " + localObject + " to " + paramSet);
      paramSet = localList.iterator();
      while (paramSet.hasNext()) {
        new ap()
        {
          protected final void a()
          {
            Object localObject = (au)this.a.get();
            if (((au)localObject).a() == null) {}
            l locall;
            do
            {
              do
              {
                return;
              } while (((au)localObject).a().a() != j.this.a.i);
              localObject = (ab)((au)localObject).a();
              locall = (l)((z)localObject).b;
            } while ((locall != null) && (locall.c.equals(j.this.a.k)));
            j.this.a(((z)localObject).a, locall);
          }
        }.a(this.b, this.D, this.c);
      }
    }
    finally
    {
      localExecutorService.shutdown();
    }
  }
  
  public final void a(Set<InetSocketAddress> paramSet, ExecutorService paramExecutorService)
  {
    try
    {
      if ((this.g == null) || (this.h == null)) {
        return;
      }
      v localv = new v(this.g, this.h, null);
      aj localaj = (aj)this.D;
      if (localaj != null)
      {
        a(paramSet, localv, this.a, paramExecutorService, this.b, localaj, this.c);
        return;
      }
    }
    finally {}
  }
  
  /* Error */
  public final void run()
  {
    // Byte code:
    //   0: aconst_null
    //   1: astore 6
    //   3: aload_0
    //   4: getfield 71	com/sleepycat/b/i/b/j:e	Lcom/sleepycat/b/i/h/x;
    //   7: ldc -75
    //   9: aload_0
    //   10: getfield 339	com/sleepycat/b/i/b/j:d	Ljava/util/concurrent/BlockingQueue;
    //   13: invokevirtual 344	com/sleepycat/b/i/h/x:a	(Ljava/lang/String;Ljava/util/concurrent/BlockingQueue;)V
    //   16: aload_0
    //   17: getfield 249	com/sleepycat/b/i/b/j:b	Ljava/util/logging/Logger;
    //   20: aload_0
    //   21: getfield 82	com/sleepycat/b/i/b/j:D	Lcom/sleepycat/b/c/ad;
    //   24: aload_0
    //   25: getfield 268	com/sleepycat/b/i/b/j:c	Ljava/util/logging/Formatter;
    //   28: getstatic 167	java/util/logging/Level:FINE	Ljava/util/logging/Level;
    //   31: ldc_w 346
    //   34: invokestatic 179	com/sleepycat/b/p/w:a	(Ljava/util/logging/Logger;Lcom/sleepycat/b/c/ad;Ljava/util/logging/Formatter;Ljava/util/logging/Level;Ljava/lang/String;)V
    //   37: aload_0
    //   38: getfield 71	com/sleepycat/b/i/b/j:e	Lcom/sleepycat/b/i/h/x;
    //   41: ldc -75
    //   43: aload_0
    //   44: getfield 116	com/sleepycat/b/i/b/j:a	Lcom/sleepycat/b/i/b/x;
    //   47: getfield 350	com/sleepycat/b/i/c/ap:m	I
    //   50: invokevirtual 353	com/sleepycat/b/i/h/x:a	(Ljava/lang/String;I)Ljava/nio/channels/SocketChannel;
    //   53: astore_1
    //   54: aload_1
    //   55: ifnonnull +15 -> 70
    //   58: aload_0
    //   59: getfield 71	com/sleepycat/b/i/b/j:e	Lcom/sleepycat/b/i/h/x;
    //   62: astore_1
    //   63: aload_1
    //   64: ldc -75
    //   66: invokevirtual 354	com/sleepycat/b/i/h/x:a	(Ljava/lang/String;)V
    //   69: return
    //   70: aload_1
    //   71: invokevirtual 360	java/nio/channels/SocketChannel:socket	()Ljava/net/Socket;
    //   74: astore 7
    //   76: new 362	java/io/BufferedReader
    //   79: dup
    //   80: new 364	java/io/InputStreamReader
    //   83: dup
    //   84: aload 7
    //   86: invokevirtual 368	java/net/Socket:getInputStream	()Ljava/io/InputStream;
    //   89: invokespecial 371	java/io/InputStreamReader:<init>	(Ljava/io/InputStream;)V
    //   92: invokespecial 374	java/io/BufferedReader:<init>	(Ljava/io/Reader;)V
    //   95: astore_1
    //   96: aload_1
    //   97: invokevirtual 377	java/io/BufferedReader:readLine	()Ljava/lang/String;
    //   100: astore_2
    //   101: aload_2
    //   102: ifnonnull +48 -> 150
    //   105: aload_0
    //   106: getfield 249	com/sleepycat/b/i/b/j:b	Ljava/util/logging/Logger;
    //   109: aload_0
    //   110: getfield 82	com/sleepycat/b/i/b/j:D	Lcom/sleepycat/b/c/ad;
    //   113: aload_0
    //   114: getfield 268	com/sleepycat/b/i/b/j:c	Ljava/util/logging/Formatter;
    //   117: aload 7
    //   119: aload_1
    //   120: aconst_null
    //   121: invokestatic 380	com/sleepycat/b/i/b/ao:a	(Ljava/util/logging/Logger;Lcom/sleepycat/b/c/ad;Ljava/util/logging/Formatter;Ljava/net/Socket;Ljava/io/BufferedReader;Ljava/io/PrintWriter;)V
    //   124: goto -87 -> 37
    //   127: astore_1
    //   128: aload_0
    //   129: getfield 386	com/sleepycat/b/p/aj:E	Ljava/util/concurrent/atomic/AtomicBoolean;
    //   132: invokevirtual 390	java/util/concurrent/atomic/AtomicBoolean:get	()Z
    //   135: istore 9
    //   137: iload 9
    //   139: ifeq +472 -> 611
    //   142: aload_0
    //   143: getfield 71	com/sleepycat/b/i/b/j:e	Lcom/sleepycat/b/i/h/x;
    //   146: astore_1
    //   147: goto -84 -> 63
    //   150: aload_0
    //   151: getfield 116	com/sleepycat/b/i/b/j:a	Lcom/sleepycat/b/i/b/x;
    //   154: aload_2
    //   155: invokevirtual 395	com/sleepycat/b/i/b/x:c	(Ljava/lang/String;)Lcom/sleepycat/b/i/c/ay;
    //   158: astore_3
    //   159: aload_0
    //   160: getfield 249	com/sleepycat/b/i/b/j:b	Ljava/util/logging/Logger;
    //   163: aload_0
    //   164: getfield 82	com/sleepycat/b/i/b/j:D	Lcom/sleepycat/b/c/ad;
    //   167: aload_0
    //   168: getfield 268	com/sleepycat/b/i/b/j:c	Ljava/util/logging/Formatter;
    //   171: getstatic 398	java/util/logging/Level:FINEST	Ljava/util/logging/Level;
    //   174: new 30	java/lang/StringBuilder
    //   177: dup
    //   178: ldc_w 400
    //   181: invokespecial 35	java/lang/StringBuilder:<init>	(Ljava/lang/String;)V
    //   184: aload_3
    //   185: invokevirtual 405	com/sleepycat/b/i/c/ay:a	()Lcom/sleepycat/b/i/c/av;
    //   188: invokevirtual 229	java/lang/StringBuilder:append	(Ljava/lang/Object;)Ljava/lang/StringBuilder;
    //   191: ldc_w 407
    //   194: invokevirtual 51	java/lang/StringBuilder:append	(Ljava/lang/String;)Ljava/lang/StringBuilder;
    //   197: aload_3
    //   198: getfield 409	com/sleepycat/b/i/c/as:h	I
    //   201: invokevirtual 172	java/lang/StringBuilder:append	(I)Ljava/lang/StringBuilder;
    //   204: invokevirtual 55	java/lang/StringBuilder:toString	()Ljava/lang/String;
    //   207: invokestatic 179	com/sleepycat/b/p/w:a	(Ljava/util/logging/Logger;Lcom/sleepycat/b/c/ad;Ljava/util/logging/Formatter;Ljava/util/logging/Level;Ljava/lang/String;)V
    //   210: aload_3
    //   211: invokevirtual 405	com/sleepycat/b/i/c/ay:a	()Lcom/sleepycat/b/i/c/av;
    //   214: aload_0
    //   215: getfield 116	com/sleepycat/b/i/b/j:a	Lcom/sleepycat/b/i/b/x;
    //   218: getfield 412	com/sleepycat/b/i/b/x:c	Lcom/sleepycat/b/i/c/av;
    //   221: if_acmpne +176 -> 397
    //   224: aload_3
    //   225: checkcast 183	com/sleepycat/b/i/b/af
    //   228: astore_2
    //   229: aload_0
    //   230: aload_2
    //   231: invokevirtual 415	com/sleepycat/b/i/b/af:d	()Lcom/sleepycat/b/i/b/s;
    //   234: aload_2
    //   235: getfield 419	com/sleepycat/b/i/b/y:a	Lcom/sleepycat/b/i/b/ai;
    //   238: invokevirtual 420	com/sleepycat/b/i/b/j:a	(Lcom/sleepycat/b/i/b/s;Lcom/sleepycat/b/i/b/ai;)V
    //   241: aload_0
    //   242: getfield 249	com/sleepycat/b/i/b/j:b	Ljava/util/logging/Logger;
    //   245: aload_0
    //   246: getfield 82	com/sleepycat/b/i/b/j:D	Lcom/sleepycat/b/c/ad;
    //   249: aload_0
    //   250: getfield 268	com/sleepycat/b/i/b/j:c	Ljava/util/logging/Formatter;
    //   253: aload 7
    //   255: aload_1
    //   256: aconst_null
    //   257: invokestatic 380	com/sleepycat/b/i/b/ao:a	(Ljava/util/logging/Logger;Lcom/sleepycat/b/c/ad;Ljava/util/logging/Formatter;Ljava/net/Socket;Ljava/io/BufferedReader;Ljava/io/PrintWriter;)V
    //   260: goto -223 -> 37
    //   263: astore_1
    //   264: aload_0
    //   265: getfield 71	com/sleepycat/b/i/b/j:e	Lcom/sleepycat/b/i/h/x;
    //   268: ldc -75
    //   270: invokevirtual 354	com/sleepycat/b/i/h/x:a	(Ljava/lang/String;)V
    //   273: aload_1
    //   274: athrow
    //   275: astore 5
    //   277: aload_0
    //   278: getfield 249	com/sleepycat/b/i/b/j:b	Ljava/util/logging/Logger;
    //   281: aload_0
    //   282: getfield 82	com/sleepycat/b/i/b/j:D	Lcom/sleepycat/b/c/ad;
    //   285: aload_0
    //   286: getfield 268	com/sleepycat/b/i/b/j:c	Ljava/util/logging/Formatter;
    //   289: getstatic 423	java/util/logging/Level:WARNING	Ljava/util/logging/Level;
    //   292: new 30	java/lang/StringBuilder
    //   295: dup
    //   296: ldc_w 425
    //   299: invokespecial 35	java/lang/StringBuilder:<init>	(Ljava/lang/String;)V
    //   302: aload 5
    //   304: invokevirtual 426	com/sleepycat/b/i/c/ar:getMessage	()Ljava/lang/String;
    //   307: invokevirtual 51	java/lang/StringBuilder:append	(Ljava/lang/String;)Ljava/lang/StringBuilder;
    //   310: invokevirtual 55	java/lang/StringBuilder:toString	()Ljava/lang/String;
    //   313: invokestatic 179	com/sleepycat/b/p/w:a	(Ljava/util/logging/Logger;Lcom/sleepycat/b/c/ad;Ljava/util/logging/Formatter;Ljava/util/logging/Level;Ljava/lang/String;)V
    //   316: new 104	java/io/PrintWriter
    //   319: dup
    //   320: aload 7
    //   322: invokevirtual 110	java/net/Socket:getOutputStream	()Ljava/io/OutputStream;
    //   325: iconst_1
    //   326: invokespecial 113	java/io/PrintWriter:<init>	(Ljava/io/OutputStream;Z)V
    //   329: astore_2
    //   330: aload_1
    //   331: astore 4
    //   333: aload_2
    //   334: astore_3
    //   335: aload_0
    //   336: getfield 116	com/sleepycat/b/i/b/j:a	Lcom/sleepycat/b/i/b/x;
    //   339: astore 8
    //   341: aload_1
    //   342: astore 4
    //   344: aload_2
    //   345: astore_3
    //   346: aload 8
    //   348: invokevirtual 122	java/lang/Object:getClass	()Ljava/lang/Class;
    //   351: pop
    //   352: aload_1
    //   353: astore 4
    //   355: aload_2
    //   356: astore_3
    //   357: aload_2
    //   358: new 428	com/sleepycat/b/i/c/ax
    //   361: dup
    //   362: aload 8
    //   364: aload 5
    //   366: invokespecial 431	com/sleepycat/b/i/c/ax:<init>	(Lcom/sleepycat/b/i/c/ap;Lcom/sleepycat/b/i/c/ar;)V
    //   369: invokevirtual 432	com/sleepycat/b/i/c/ax:b	()Ljava/lang/String;
    //   372: invokevirtual 140	java/io/PrintWriter:println	(Ljava/lang/String;)V
    //   375: aload_0
    //   376: getfield 249	com/sleepycat/b/i/b/j:b	Ljava/util/logging/Logger;
    //   379: aload_0
    //   380: getfield 82	com/sleepycat/b/i/b/j:D	Lcom/sleepycat/b/c/ad;
    //   383: aload_0
    //   384: getfield 268	com/sleepycat/b/i/b/j:c	Ljava/util/logging/Formatter;
    //   387: aload 7
    //   389: aload_1
    //   390: aload_2
    //   391: invokestatic 380	com/sleepycat/b/i/b/ao:a	(Ljava/util/logging/Logger;Lcom/sleepycat/b/c/ad;Ljava/util/logging/Formatter;Ljava/net/Socket;Ljava/io/BufferedReader;Ljava/io/PrintWriter;)V
    //   394: goto -357 -> 37
    //   397: aload_3
    //   398: invokevirtual 405	com/sleepycat/b/i/c/ay:a	()Lcom/sleepycat/b/i/c/av;
    //   401: aload_0
    //   402: getfield 116	com/sleepycat/b/i/b/j:a	Lcom/sleepycat/b/i/b/x;
    //   405: getfield 434	com/sleepycat/b/i/b/x:d	Lcom/sleepycat/b/i/c/av;
    //   408: if_acmpne +83 -> 491
    //   411: aload_0
    //   412: aload 7
    //   414: aload_3
    //   415: invokespecial 436	com/sleepycat/b/i/b/j:a	(Ljava/net/Socket;Lcom/sleepycat/b/i/c/ay;)V
    //   418: goto -177 -> 241
    //   421: astore 5
    //   423: aconst_null
    //   424: astore_2
    //   425: aload_1
    //   426: astore 4
    //   428: aload_2
    //   429: astore_3
    //   430: aload_0
    //   431: getfield 249	com/sleepycat/b/i/b/j:b	Ljava/util/logging/Logger;
    //   434: aload_0
    //   435: getfield 82	com/sleepycat/b/i/b/j:D	Lcom/sleepycat/b/c/ad;
    //   438: aload_0
    //   439: getfield 268	com/sleepycat/b/i/b/j:c	Ljava/util/logging/Formatter;
    //   442: getstatic 423	java/util/logging/Level:WARNING	Ljava/util/logging/Level;
    //   445: new 30	java/lang/StringBuilder
    //   448: dup
    //   449: ldc_w 438
    //   452: invokespecial 35	java/lang/StringBuilder:<init>	(Ljava/lang/String;)V
    //   455: aload 5
    //   457: invokevirtual 439	java/io/IOException:getMessage	()Ljava/lang/String;
    //   460: invokevirtual 51	java/lang/StringBuilder:append	(Ljava/lang/String;)Ljava/lang/StringBuilder;
    //   463: invokevirtual 55	java/lang/StringBuilder:toString	()Ljava/lang/String;
    //   466: invokestatic 179	com/sleepycat/b/p/w:a	(Ljava/util/logging/Logger;Lcom/sleepycat/b/c/ad;Ljava/util/logging/Formatter;Ljava/util/logging/Level;Ljava/lang/String;)V
    //   469: aload_0
    //   470: getfield 249	com/sleepycat/b/i/b/j:b	Ljava/util/logging/Logger;
    //   473: aload_0
    //   474: getfield 82	com/sleepycat/b/i/b/j:D	Lcom/sleepycat/b/c/ad;
    //   477: aload_0
    //   478: getfield 268	com/sleepycat/b/i/b/j:c	Ljava/util/logging/Formatter;
    //   481: aload 7
    //   483: aload_1
    //   484: aload_2
    //   485: invokestatic 380	com/sleepycat/b/i/b/ao:a	(Ljava/util/logging/Logger;Lcom/sleepycat/b/c/ad;Ljava/util/logging/Formatter;Ljava/net/Socket;Ljava/io/BufferedReader;Ljava/io/PrintWriter;)V
    //   488: goto -451 -> 37
    //   491: aload_3
    //   492: invokevirtual 405	com/sleepycat/b/i/c/ay:a	()Lcom/sleepycat/b/i/c/av;
    //   495: aload_0
    //   496: getfield 116	com/sleepycat/b/i/b/j:a	Lcom/sleepycat/b/i/b/x;
    //   499: getfield 441	com/sleepycat/b/i/b/x:e	Lcom/sleepycat/b/i/c/av;
    //   502: if_acmpne +51 -> 553
    //   505: aload_0
    //   506: getfield 249	com/sleepycat/b/i/b/j:b	Ljava/util/logging/Logger;
    //   509: aload_0
    //   510: getfield 82	com/sleepycat/b/i/b/j:D	Lcom/sleepycat/b/c/ad;
    //   513: aload_0
    //   514: getfield 268	com/sleepycat/b/i/b/j:c	Ljava/util/logging/Formatter;
    //   517: getstatic 167	java/util/logging/Level:FINE	Ljava/util/logging/Level;
    //   520: ldc_w 443
    //   523: invokestatic 179	com/sleepycat/b/p/w:a	(Ljava/util/logging/Logger;Lcom/sleepycat/b/c/ad;Ljava/util/logging/Formatter;Ljava/util/logging/Level;Ljava/lang/String;)V
    //   526: aload_0
    //   527: getfield 249	com/sleepycat/b/i/b/j:b	Ljava/util/logging/Logger;
    //   530: aload_0
    //   531: getfield 82	com/sleepycat/b/i/b/j:D	Lcom/sleepycat/b/c/ad;
    //   534: aload_0
    //   535: getfield 268	com/sleepycat/b/i/b/j:c	Ljava/util/logging/Formatter;
    //   538: aload 7
    //   540: aload_1
    //   541: aconst_null
    //   542: invokestatic 380	com/sleepycat/b/i/b/ao:a	(Ljava/util/logging/Logger;Lcom/sleepycat/b/c/ad;Ljava/util/logging/Formatter;Ljava/net/Socket;Ljava/io/BufferedReader;Ljava/io/PrintWriter;)V
    //   545: aload_0
    //   546: getfield 71	com/sleepycat/b/i/b/j:e	Lcom/sleepycat/b/i/h/x;
    //   549: astore_1
    //   550: goto -487 -> 63
    //   553: new 30	java/lang/StringBuilder
    //   556: dup
    //   557: ldc_w 445
    //   560: invokespecial 35	java/lang/StringBuilder:<init>	(Ljava/lang/String;)V
    //   563: aload_2
    //   564: invokevirtual 51	java/lang/StringBuilder:append	(Ljava/lang/String;)Ljava/lang/StringBuilder;
    //   567: invokevirtual 55	java/lang/StringBuilder:toString	()Ljava/lang/String;
    //   570: invokestatic 161	com/sleepycat/b/aa:c	(Ljava/lang/String;)Lcom/sleepycat/b/aa;
    //   573: athrow
    //   574: astore_2
    //   575: aload 6
    //   577: astore_3
    //   578: aload_2
    //   579: invokestatic 448	com/sleepycat/b/aa:a	(Ljava/lang/Exception;)Lcom/sleepycat/b/aa;
    //   582: athrow
    //   583: astore 4
    //   585: aload_3
    //   586: astore_2
    //   587: aload 4
    //   589: astore_3
    //   590: aload_0
    //   591: getfield 249	com/sleepycat/b/i/b/j:b	Ljava/util/logging/Logger;
    //   594: aload_0
    //   595: getfield 82	com/sleepycat/b/i/b/j:D	Lcom/sleepycat/b/c/ad;
    //   598: aload_0
    //   599: getfield 268	com/sleepycat/b/i/b/j:c	Ljava/util/logging/Formatter;
    //   602: aload 7
    //   604: aload_1
    //   605: aload_2
    //   606: invokestatic 380	com/sleepycat/b/i/b/ao:a	(Ljava/util/logging/Logger;Lcom/sleepycat/b/c/ad;Ljava/util/logging/Formatter;Ljava/net/Socket;Ljava/io/BufferedReader;Ljava/io/PrintWriter;)V
    //   609: aload_3
    //   610: athrow
    //   611: aload_0
    //   612: getfield 249	com/sleepycat/b/i/b/j:b	Ljava/util/logging/Logger;
    //   615: aload_0
    //   616: getfield 82	com/sleepycat/b/i/b/j:D	Lcom/sleepycat/b/c/ad;
    //   619: aload_0
    //   620: getfield 268	com/sleepycat/b/i/b/j:c	Ljava/util/logging/Formatter;
    //   623: getstatic 423	java/util/logging/Level:WARNING	Ljava/util/logging/Level;
    //   626: ldc_w 450
    //   629: invokestatic 179	com/sleepycat/b/p/w:a	(Ljava/util/logging/Logger;Lcom/sleepycat/b/c/ad;Ljava/util/logging/Formatter;Ljava/util/logging/Level;Ljava/lang/String;)V
    //   632: aload_1
    //   633: invokestatic 448	com/sleepycat/b/aa:a	(Ljava/lang/Exception;)Lcom/sleepycat/b/aa;
    //   636: athrow
    //   637: astore_3
    //   638: aconst_null
    //   639: astore_2
    //   640: aconst_null
    //   641: astore_1
    //   642: goto -52 -> 590
    //   645: astore_3
    //   646: aconst_null
    //   647: astore_2
    //   648: goto -58 -> 590
    //   651: astore 5
    //   653: aload 4
    //   655: astore_1
    //   656: aload_3
    //   657: astore_2
    //   658: aload 5
    //   660: astore_3
    //   661: goto -71 -> 590
    //   664: astore_2
    //   665: aconst_null
    //   666: astore_1
    //   667: aload 6
    //   669: astore_3
    //   670: goto -92 -> 578
    //   673: astore 4
    //   675: aload_2
    //   676: astore_3
    //   677: aload 4
    //   679: astore_2
    //   680: goto -102 -> 578
    //   683: astore 5
    //   685: aconst_null
    //   686: astore_2
    //   687: aconst_null
    //   688: astore_1
    //   689: goto -264 -> 425
    //   692: astore 5
    //   694: goto -269 -> 425
    // Local variable table:
    //   start	length	slot	name	signature
    //   0	697	0	this	j
    //   53	67	1	localObject1	Object
    //   127	1	1	localInterruptedException	InterruptedException
    //   146	110	1	localx	com.sleepycat.b.i.h.x
    //   263	278	1	localBufferedReader1	java.io.BufferedReader
    //   549	140	1	localObject2	Object
    //   100	464	2	localObject3	Object
    //   574	5	2	localException1	Exception
    //   586	72	2	localObject4	Object
    //   664	12	2	localException2	Exception
    //   679	8	2	localObject5	Object
    //   158	452	3	localObject6	Object
    //   637	1	3	localObject7	Object
    //   645	12	3	localObject8	Object
    //   660	17	3	localObject9	Object
    //   331	96	4	localBufferedReader2	java.io.BufferedReader
    //   583	71	4	localObject10	Object
    //   673	5	4	localException3	Exception
    //   275	90	5	localar	com.sleepycat.b.i.c.ar
    //   421	35	5	localIOException1	java.io.IOException
    //   651	8	5	localObject11	Object
    //   683	1	5	localIOException2	java.io.IOException
    //   692	1	5	localIOException3	java.io.IOException
    //   1	667	6	localObject12	Object
    //   74	529	7	localSocket	java.net.Socket
    //   339	24	8	localx1	x
    //   135	3	9	bool	boolean
    // Exception table:
    //   from	to	target	type
    //   37	54	127	java/lang/InterruptedException
    //   70	76	127	java/lang/InterruptedException
    //   105	124	127	java/lang/InterruptedException
    //   241	260	127	java/lang/InterruptedException
    //   375	394	127	java/lang/InterruptedException
    //   469	488	127	java/lang/InterruptedException
    //   526	545	127	java/lang/InterruptedException
    //   590	611	127	java/lang/InterruptedException
    //   37	54	263	finally
    //   70	76	263	finally
    //   105	124	263	finally
    //   128	137	263	finally
    //   241	260	263	finally
    //   375	394	263	finally
    //   469	488	263	finally
    //   526	545	263	finally
    //   590	611	263	finally
    //   611	637	263	finally
    //   150	159	275	com/sleepycat/b/i/c/ar
    //   96	101	421	java/io/IOException
    //   150	159	421	java/io/IOException
    //   159	241	421	java/io/IOException
    //   277	330	421	java/io/IOException
    //   397	418	421	java/io/IOException
    //   491	526	421	java/io/IOException
    //   553	574	421	java/io/IOException
    //   96	101	574	java/lang/Exception
    //   150	159	574	java/lang/Exception
    //   159	241	574	java/lang/Exception
    //   277	330	574	java/lang/Exception
    //   397	418	574	java/lang/Exception
    //   491	526	574	java/lang/Exception
    //   553	574	574	java/lang/Exception
    //   578	583	583	finally
    //   76	96	637	finally
    //   96	101	645	finally
    //   150	159	645	finally
    //   159	241	645	finally
    //   277	330	645	finally
    //   397	418	645	finally
    //   491	526	645	finally
    //   553	574	645	finally
    //   335	341	651	finally
    //   346	352	651	finally
    //   357	375	651	finally
    //   430	469	651	finally
    //   76	96	664	java/lang/Exception
    //   335	341	673	java/lang/Exception
    //   346	352	673	java/lang/Exception
    //   357	375	673	java/lang/Exception
    //   76	96	683	java/io/IOException
    //   335	341	692	java/io/IOException
    //   346	352	692	java/io/IOException
    //   357	375	692	java/io/IOException
  }
}


/* Location:              E:\apk\xueqiu2\classes-dex2jar.jar!\com\sleepycat\b\i\b\j.class
 * Java compiler version: 6 (50.0)
 * JD-Core Version:       0.7.1
 */