package com.sleepycat.b.i.g.a;

import com.sleepycat.b.ao;
import com.sleepycat.b.av;
import com.sleepycat.b.c.ad;
import com.sleepycat.b.c.c;
import com.sleepycat.b.g.ae;
import com.sleepycat.b.g.am;
import com.sleepycat.b.g.ay;
import com.sleepycat.b.l;
import com.sleepycat.b.l.a;
import com.sleepycat.b.m;
import com.sleepycat.b.p.au;
import com.sleepycat.b.x;
import java.nio.channels.SocketChannel;
import java.util.HashSet;
import java.util.Iterator;

final class g
  implements Runnable
{
  final SocketChannel a;
  private com.sleepycat.b.i.t c;
  private l d = new l();
  
  g(f paramf, SocketChannel paramSocketChannel)
  {
    this.a = paramSocketChannel;
    this.d.e = true;
    this.d.b = false;
  }
  
  private void a(com.sleepycat.b.e parame, u paramu, i parami)
  {
    HashSet localHashSet;
    try
    {
      Object localObject2 = paramu.a;
      Object localObject1 = paramu.b;
      long l2 = paramu.c;
      localHashSet = new HashSet();
      am localam = parame.a().b.a.w;
      localObject2 = new m((byte[])localObject2);
      m localm = new m((byte[])localObject1);
      if (l2 == -1L) {}
      for (int i = 1;; i = 0)
      {
        paramu = parame.g((m)localObject2, localm, ao.a);
        for (long l1 = 1L; (paramu == av.a) && ((i != 0) || (l1 <= l2)); l1 = 1L + l1)
        {
          byte[] arrayOfByte1 = ((m)localObject2).a;
          byte[] arrayOfByte2 = localm.a;
          paramu = parame.a;
          localObject1 = localam.a(paramu.a.k(paramu.b), true).a.e;
          paramu = (u)localObject1;
          if (localObject1 == null) {
            paramu = au.a;
          }
          localHashSet.add(new w(arrayOfByte1, arrayOfByte2, paramu));
          paramu = parame.c((m)localObject2, localm, ao.a);
        }
      }
      parami.getClass();
    }
    catch (Exception parame)
    {
      parami.getClass();
      parami.a(new t(parami, parame.getMessage()), this.a);
      throw new e(parame.getMessage());
    }
    parami.a(new p(parami), this.a);
    parame = localHashSet.iterator();
    while (parame.hasNext())
    {
      paramu = (w)parame.next();
      parami.getClass();
      parami.a(new v(parami, paramu), this.a);
    }
    parami.getClass();
    parami.a(new o(parami), this.a);
  }
  
  /* Error */
  public final void run()
  {
    // Byte code:
    //   0: aconst_null
    //   1: astore_3
    //   2: aconst_null
    //   3: astore 7
    //   5: aconst_null
    //   6: astore_2
    //   7: aconst_null
    //   8: astore 8
    //   10: aconst_null
    //   11: astore 5
    //   13: aload_0
    //   14: getfield 18	com/sleepycat/b/i/g/a/g:b	Lcom/sleepycat/b/i/g/a/f;
    //   17: getfield 203	com/sleepycat/b/i/g/a/f:b	Lcom/sleepycat/b/i/c/aj;
    //   20: astore_1
    //   21: aload_0
    //   22: new 205	com/sleepycat/b/i/t
    //   25: dup
    //   26: aload_1
    //   27: getfield 208	com/sleepycat/b/c/ad:c	Ljava/io/File;
    //   30: aload_1
    //   31: invokevirtual 214	com/sleepycat/b/i/c/aj:Y	()Lcom/sleepycat/b/i/w;
    //   34: aload_1
    //   35: invokevirtual 218	com/sleepycat/b/i/c/aj:z	()Lcom/sleepycat/b/z;
    //   38: invokespecial 221	com/sleepycat/b/i/t:<init>	(Ljava/io/File;Lcom/sleepycat/b/i/w;Lcom/sleepycat/b/z;)V
    //   41: putfield 223	com/sleepycat/b/i/g/a/g:c	Lcom/sleepycat/b/i/t;
    //   44: new 156	com/sleepycat/b/i/g/a/i
    //   47: dup
    //   48: new 225	com/sleepycat/b/i/c/b/x
    //   51: dup
    //   52: ldc -29
    //   54: iconst_m1
    //   55: invokespecial 230	com/sleepycat/b/i/c/b/x:<init>	(Ljava/lang/String;I)V
    //   58: aload_0
    //   59: getfield 18	com/sleepycat/b/i/g/a/g:b	Lcom/sleepycat/b/i/g/a/f;
    //   62: getfield 203	com/sleepycat/b/i/g/a/f:b	Lcom/sleepycat/b/i/c/aj;
    //   65: invokespecial 233	com/sleepycat/b/i/g/a/i:<init>	(Lcom/sleepycat/b/i/c/b/x;Lcom/sleepycat/b/c/ad;)V
    //   68: astore 9
    //   70: aload_0
    //   71: getfield 28	com/sleepycat/b/i/g/a/g:a	Ljava/nio/channels/SocketChannel;
    //   74: iconst_1
    //   75: invokevirtual 239	java/nio/channels/SocketChannel:configureBlocking	(Z)Ljava/nio/channels/SelectableChannel;
    //   78: pop
    //   79: aload 9
    //   81: aload_0
    //   82: getfield 28	com/sleepycat/b/i/g/a/g:a	Ljava/nio/channels/SocketChannel;
    //   85: invokevirtual 242	com/sleepycat/b/i/g/a/i:a	(Ljava/nio/channels/ReadableByteChannel;)Lcom/sleepycat/b/i/h/d;
    //   88: astore_1
    //   89: aload_1
    //   90: invokevirtual 247	com/sleepycat/b/i/h/d:a	()Lcom/sleepycat/b/i/h/e;
    //   93: getstatic 250	com/sleepycat/b/i/g/a/i:a	Lcom/sleepycat/b/i/h/e;
    //   96: if_acmpne +881 -> 977
    //   99: aload_1
    //   100: checkcast 252	com/sleepycat/b/i/g/a/m
    //   103: astore 6
    //   105: aload_0
    //   106: getfield 223	com/sleepycat/b/i/g/a/g:c	Lcom/sleepycat/b/i/t;
    //   109: aconst_null
    //   110: aload 6
    //   112: getfield 255	com/sleepycat/b/i/g/a/m:a	Ljava/lang/String;
    //   115: aload_0
    //   116: getfield 26	com/sleepycat/b/i/g/a/g:d	Lcom/sleepycat/b/l;
    //   119: invokevirtual 258	com/sleepycat/b/i/t:a	(Lcom/sleepycat/b/bp;Ljava/lang/String;Lcom/sleepycat/b/l;)Lcom/sleepycat/b/i;
    //   122: astore 4
    //   124: aload 5
    //   126: astore_3
    //   127: aload 7
    //   129: astore_1
    //   130: aload 4
    //   132: astore_2
    //   133: aload 9
    //   135: invokevirtual 145	java/lang/Object:getClass	()Ljava/lang/Class;
    //   138: pop
    //   139: aload 5
    //   141: astore_3
    //   142: aload 7
    //   144: astore_1
    //   145: aload 4
    //   147: astore_2
    //   148: aload 9
    //   150: new 260	com/sleepycat/b/i/g/a/l
    //   153: dup
    //   154: aload 9
    //   156: invokespecial 261	com/sleepycat/b/i/g/a/l:<init>	(Lcom/sleepycat/b/i/g/a/i;)V
    //   159: aload_0
    //   160: getfield 28	com/sleepycat/b/i/g/a/g:a	Ljava/nio/channels/SocketChannel;
    //   163: invokevirtual 159	com/sleepycat/b/i/g/a/i:a	(Lcom/sleepycat/b/i/h/d;Ljava/nio/channels/WritableByteChannel;)V
    //   166: aload 5
    //   168: astore_3
    //   169: aload 7
    //   171: astore_1
    //   172: aload 4
    //   174: astore_2
    //   175: new 263	com/sleepycat/b/i/g/a/d
    //   178: dup
    //   179: invokespecial 264	com/sleepycat/b/i/g/a/d:<init>	()V
    //   182: astore 10
    //   184: aload 5
    //   186: astore_3
    //   187: aload 7
    //   189: astore_1
    //   190: aload 4
    //   192: astore_2
    //   193: aload 10
    //   195: aload 6
    //   197: getfield 265	com/sleepycat/b/i/g/a/m:b	I
    //   200: putfield 267	com/sleepycat/b/i/g/a/d:a	I
    //   203: aload 5
    //   205: astore_3
    //   206: aload 7
    //   208: astore_1
    //   209: aload 4
    //   211: astore_2
    //   212: new 269	com/sleepycat/b/i/g/a/c
    //   215: dup
    //   216: new 271	com/sleepycat/b/i/g/a/b
    //   219: dup
    //   220: aload 10
    //   222: invokespecial 274	com/sleepycat/b/i/g/a/b:<init>	(Lcom/sleepycat/b/i/g/a/d;)V
    //   225: aload 4
    //   227: invokespecial 277	com/sleepycat/b/i/g/a/c:<init>	(Lcom/sleepycat/b/i/g/a/b;Lcom/sleepycat/b/i;)V
    //   230: astore 6
    //   232: aload 5
    //   234: astore_3
    //   235: aload 7
    //   237: astore_1
    //   238: aload 4
    //   240: astore_2
    //   241: aload 6
    //   243: invokeinterface 179 1 0
    //   248: ifeq +170 -> 418
    //   251: aload 5
    //   253: astore_3
    //   254: aload 7
    //   256: astore_1
    //   257: aload 4
    //   259: astore_2
    //   260: aload 9
    //   262: invokevirtual 145	java/lang/Object:getClass	()Ljava/lang/Class;
    //   265: pop
    //   266: aload 5
    //   268: astore_3
    //   269: aload 7
    //   271: astore_1
    //   272: aload 4
    //   274: astore_2
    //   275: aload 9
    //   277: new 279	com/sleepycat/b/i/g/a/j
    //   280: dup
    //   281: aload 9
    //   283: aload 6
    //   285: invokeinterface 183 1 0
    //   290: checkcast 281	com/sleepycat/b/i/g/a/a
    //   293: invokespecial 284	com/sleepycat/b/i/g/a/j:<init>	(Lcom/sleepycat/b/i/g/a/i;Lcom/sleepycat/b/i/g/a/a;)V
    //   296: aload_0
    //   297: getfield 28	com/sleepycat/b/i/g/a/g:a	Ljava/nio/channels/SocketChannel;
    //   300: invokevirtual 159	com/sleepycat/b/i/g/a/i:a	(Lcom/sleepycat/b/i/h/d;Ljava/nio/channels/WritableByteChannel;)V
    //   303: goto -71 -> 232
    //   306: astore 5
    //   308: aload_3
    //   309: astore_1
    //   310: aload 4
    //   312: astore_2
    //   313: aload 9
    //   315: invokevirtual 145	java/lang/Object:getClass	()Ljava/lang/Class;
    //   318: pop
    //   319: aload_3
    //   320: astore_1
    //   321: aload 4
    //   323: astore_2
    //   324: aload 9
    //   326: new 286	com/sleepycat/b/i/g/a/n
    //   329: dup
    //   330: aload 9
    //   332: aload 5
    //   334: invokevirtual 287	com/sleepycat/b/p:getMessage	()Ljava/lang/String;
    //   337: invokespecial 288	com/sleepycat/b/i/g/a/n:<init>	(Lcom/sleepycat/b/i/g/a/i;Ljava/lang/String;)V
    //   340: aload_0
    //   341: getfield 28	com/sleepycat/b/i/g/a/g:a	Ljava/nio/channels/SocketChannel;
    //   344: invokevirtual 159	com/sleepycat/b/i/g/a/i:a	(Lcom/sleepycat/b/i/h/d;Ljava/nio/channels/WritableByteChannel;)V
    //   347: aload_3
    //   348: ifnull +7 -> 355
    //   351: aload_3
    //   352: invokevirtual 291	com/sleepycat/b/e:close	()V
    //   355: aload 4
    //   357: ifnull +8 -> 365
    //   360: aload 4
    //   362: invokevirtual 292	com/sleepycat/b/i:close	()V
    //   365: aload_0
    //   366: getfield 28	com/sleepycat/b/i/g/a/g:a	Ljava/nio/channels/SocketChannel;
    //   369: invokevirtual 295	java/nio/channels/SocketChannel:isOpen	()Z
    //   372: ifeq +10 -> 382
    //   375: aload_0
    //   376: getfield 28	com/sleepycat/b/i/g/a/g:a	Ljava/nio/channels/SocketChannel;
    //   379: invokevirtual 296	java/nio/channels/SocketChannel:close	()V
    //   382: aload_0
    //   383: getfield 223	com/sleepycat/b/i/g/a/g:c	Lcom/sleepycat/b/i/t;
    //   386: ifnull +10 -> 396
    //   389: aload_0
    //   390: getfield 223	com/sleepycat/b/i/g/a/g:c	Lcom/sleepycat/b/i/t;
    //   393: invokevirtual 297	com/sleepycat/b/i/t:close	()V
    //   396: aload_0
    //   397: getfield 18	com/sleepycat/b/i/g/a/g:b	Lcom/sleepycat/b/i/g/a/f;
    //   400: getfield 300	com/sleepycat/b/i/g/a/f:a	Ljava/util/concurrent/atomic/AtomicBoolean;
    //   403: iconst_1
    //   404: iconst_0
    //   405: invokevirtual 306	java/util/concurrent/atomic/AtomicBoolean:compareAndSet	(ZZ)Z
    //   408: ifne +620 -> 1028
    //   411: ldc_w 308
    //   414: invokestatic 313	com/sleepycat/b/aa:c	(Ljava/lang/String;)Lcom/sleepycat/b/aa;
    //   417: athrow
    //   418: aload 5
    //   420: astore_3
    //   421: aload 7
    //   423: astore_1
    //   424: aload 4
    //   426: astore_2
    //   427: aload 9
    //   429: invokevirtual 145	java/lang/Object:getClass	()Ljava/lang/Class;
    //   432: pop
    //   433: aload 5
    //   435: astore_3
    //   436: aload 7
    //   438: astore_1
    //   439: aload 4
    //   441: astore_2
    //   442: aload 9
    //   444: new 315	com/sleepycat/b/i/g/a/k
    //   447: dup
    //   448: aload 9
    //   450: invokespecial 316	com/sleepycat/b/i/g/a/k:<init>	(Lcom/sleepycat/b/i/g/a/i;)V
    //   453: aload_0
    //   454: getfield 28	com/sleepycat/b/i/g/a/g:a	Ljava/nio/channels/SocketChannel;
    //   457: invokevirtual 159	com/sleepycat/b/i/g/a/i:a	(Lcom/sleepycat/b/i/h/d;Ljava/nio/channels/WritableByteChannel;)V
    //   460: aload 5
    //   462: astore_3
    //   463: aload 7
    //   465: astore_1
    //   466: aload 4
    //   468: astore_2
    //   469: aload 9
    //   471: aload_0
    //   472: getfield 28	com/sleepycat/b/i/g/a/g:a	Ljava/nio/channels/SocketChannel;
    //   475: invokevirtual 242	com/sleepycat/b/i/g/a/i:a	(Ljava/nio/channels/ReadableByteChannel;)Lcom/sleepycat/b/i/h/d;
    //   478: astore 10
    //   480: aload 5
    //   482: astore_3
    //   483: aload 7
    //   485: astore_1
    //   486: aload 4
    //   488: astore_2
    //   489: aload 10
    //   491: invokevirtual 247	com/sleepycat/b/i/h/d:a	()Lcom/sleepycat/b/i/h/e;
    //   494: getstatic 319	com/sleepycat/b/i/g/a/i:h	Lcom/sleepycat/b/i/h/e;
    //   497: if_acmpne +389 -> 886
    //   500: aload 5
    //   502: astore_3
    //   503: aload 7
    //   505: astore_1
    //   506: aload 4
    //   508: astore_2
    //   509: aload 4
    //   511: aconst_null
    //   512: aconst_null
    //   513: invokevirtual 322	com/sleepycat/b/i:a	(Lcom/sleepycat/b/bp;Lcom/sleepycat/b/g;)Lcom/sleepycat/b/e;
    //   516: astore 5
    //   518: aload 5
    //   520: astore_3
    //   521: aload 5
    //   523: astore_1
    //   524: aload 4
    //   526: astore_2
    //   527: aload_0
    //   528: aload 5
    //   530: aload 10
    //   532: checkcast 40	com/sleepycat/b/i/g/a/u
    //   535: aload 9
    //   537: invokespecial 324	com/sleepycat/b/i/g/a/g:a	(Lcom/sleepycat/b/e;Lcom/sleepycat/b/i/g/a/u;Lcom/sleepycat/b/i/g/a/i;)V
    //   540: aload 5
    //   542: astore_3
    //   543: aload 5
    //   545: astore_1
    //   546: aload 4
    //   548: astore_2
    //   549: aload 9
    //   551: aload_0
    //   552: getfield 28	com/sleepycat/b/i/g/a/g:a	Ljava/nio/channels/SocketChannel;
    //   555: invokevirtual 242	com/sleepycat/b/i/g/a/i:a	(Ljava/nio/channels/ReadableByteChannel;)Lcom/sleepycat/b/i/h/d;
    //   558: astore 7
    //   560: aload 5
    //   562: astore_3
    //   563: aload 5
    //   565: astore_1
    //   566: aload 4
    //   568: astore_2
    //   569: aload 7
    //   571: invokevirtual 247	com/sleepycat/b/i/h/d:a	()Lcom/sleepycat/b/i/h/e;
    //   574: getstatic 319	com/sleepycat/b/i/g/a/i:h	Lcom/sleepycat/b/i/h/e;
    //   577: if_acmpne +141 -> 718
    //   580: aload 5
    //   582: astore_3
    //   583: aload 5
    //   585: astore_1
    //   586: aload 4
    //   588: astore_2
    //   589: aload_0
    //   590: aload 5
    //   592: aload 7
    //   594: checkcast 40	com/sleepycat/b/i/g/a/u
    //   597: aload 9
    //   599: invokespecial 324	com/sleepycat/b/i/g/a/g:a	(Lcom/sleepycat/b/e;Lcom/sleepycat/b/i/g/a/u;Lcom/sleepycat/b/i/g/a/i;)V
    //   602: goto -62 -> 540
    //   605: astore 4
    //   607: aload_2
    //   608: astore_3
    //   609: aload_1
    //   610: astore_2
    //   611: aload 4
    //   613: astore_1
    //   614: aload_2
    //   615: ifnull +7 -> 622
    //   618: aload_2
    //   619: invokevirtual 291	com/sleepycat/b/e:close	()V
    //   622: aload_3
    //   623: ifnull +7 -> 630
    //   626: aload_3
    //   627: invokevirtual 292	com/sleepycat/b/i:close	()V
    //   630: aload_1
    //   631: athrow
    //   632: astore_1
    //   633: aload 9
    //   635: invokevirtual 145	java/lang/Object:getClass	()Ljava/lang/Class;
    //   638: pop
    //   639: aload 9
    //   641: new 326	com/sleepycat/b/i/h/f
    //   644: dup
    //   645: aload 9
    //   647: aload_1
    //   648: invokevirtual 327	com/sleepycat/b/i/h/g:getMessage	()Ljava/lang/String;
    //   651: invokespecial 330	com/sleepycat/b/i/h/f:<init>	(Lcom/sleepycat/b/i/h/a;Ljava/lang/String;)V
    //   654: aload_0
    //   655: getfield 28	com/sleepycat/b/i/g/a/g:a	Ljava/nio/channels/SocketChannel;
    //   658: invokevirtual 159	com/sleepycat/b/i/g/a/i:a	(Lcom/sleepycat/b/i/h/d;Ljava/nio/channels/WritableByteChannel;)V
    //   661: aload_0
    //   662: getfield 28	com/sleepycat/b/i/g/a/g:a	Ljava/nio/channels/SocketChannel;
    //   665: invokevirtual 295	java/nio/channels/SocketChannel:isOpen	()Z
    //   668: ifeq -286 -> 382
    //   671: aload_0
    //   672: getfield 28	com/sleepycat/b/i/g/a/g:a	Ljava/nio/channels/SocketChannel;
    //   675: invokevirtual 296	java/nio/channels/SocketChannel:close	()V
    //   678: goto -296 -> 382
    //   681: astore_1
    //   682: aload_0
    //   683: getfield 223	com/sleepycat/b/i/g/a/g:c	Lcom/sleepycat/b/i/t;
    //   686: ifnull +10 -> 696
    //   689: aload_0
    //   690: getfield 223	com/sleepycat/b/i/g/a/g:c	Lcom/sleepycat/b/i/t;
    //   693: invokevirtual 297	com/sleepycat/b/i/t:close	()V
    //   696: aload_0
    //   697: getfield 18	com/sleepycat/b/i/g/a/g:b	Lcom/sleepycat/b/i/g/a/f;
    //   700: getfield 300	com/sleepycat/b/i/g/a/f:a	Ljava/util/concurrent/atomic/AtomicBoolean;
    //   703: iconst_1
    //   704: iconst_0
    //   705: invokevirtual 306	java/util/concurrent/atomic/AtomicBoolean:compareAndSet	(ZZ)Z
    //   708: ifne +320 -> 1028
    //   711: ldc_w 308
    //   714: invokestatic 313	com/sleepycat/b/aa:c	(Ljava/lang/String;)Lcom/sleepycat/b/aa;
    //   717: athrow
    //   718: aload 5
    //   720: astore_3
    //   721: aload 5
    //   723: astore_1
    //   724: aload 4
    //   726: astore_2
    //   727: aload 5
    //   729: astore 6
    //   731: aload 7
    //   733: invokevirtual 247	com/sleepycat/b/i/h/d:a	()Lcom/sleepycat/b/i/h/e;
    //   736: getstatic 333	com/sleepycat/b/i/g/a/i:l	Lcom/sleepycat/b/i/h/e;
    //   739: if_acmpeq +67 -> 806
    //   742: aload 5
    //   744: astore_3
    //   745: aload 5
    //   747: astore_1
    //   748: aload 4
    //   750: astore_2
    //   751: aload 9
    //   753: invokevirtual 145	java/lang/Object:getClass	()Ljava/lang/Class;
    //   756: pop
    //   757: aload 5
    //   759: astore_3
    //   760: aload 5
    //   762: astore_1
    //   763: aload 4
    //   765: astore_2
    //   766: aload 9
    //   768: new 326	com/sleepycat/b/i/h/f
    //   771: dup
    //   772: aload 9
    //   774: new 335	java/lang/StringBuilder
    //   777: dup
    //   778: ldc_w 337
    //   781: invokespecial 338	java/lang/StringBuilder:<init>	(Ljava/lang/String;)V
    //   784: aload 7
    //   786: invokevirtual 342	java/lang/StringBuilder:append	(Ljava/lang/Object;)Ljava/lang/StringBuilder;
    //   789: invokevirtual 345	java/lang/StringBuilder:toString	()Ljava/lang/String;
    //   792: invokespecial 330	com/sleepycat/b/i/h/f:<init>	(Lcom/sleepycat/b/i/h/a;Ljava/lang/String;)V
    //   795: aload_0
    //   796: getfield 28	com/sleepycat/b/i/g/a/g:a	Ljava/nio/channels/SocketChannel;
    //   799: invokevirtual 159	com/sleepycat/b/i/g/a/i:a	(Lcom/sleepycat/b/i/h/d;Ljava/nio/channels/WritableByteChannel;)V
    //   802: aload 5
    //   804: astore 6
    //   806: aload 6
    //   808: ifnull +8 -> 816
    //   811: aload 6
    //   813: invokevirtual 291	com/sleepycat/b/e:close	()V
    //   816: aload 4
    //   818: ifnull -453 -> 365
    //   821: aload 4
    //   823: invokevirtual 292	com/sleepycat/b/i:close	()V
    //   826: goto -461 -> 365
    //   829: astore_1
    //   830: aload_0
    //   831: getfield 28	com/sleepycat/b/i/g/a/g:a	Ljava/nio/channels/SocketChannel;
    //   834: invokevirtual 295	java/nio/channels/SocketChannel:isOpen	()Z
    //   837: ifeq +10 -> 847
    //   840: aload_0
    //   841: getfield 28	com/sleepycat/b/i/g/a/g:a	Ljava/nio/channels/SocketChannel;
    //   844: invokevirtual 296	java/nio/channels/SocketChannel:close	()V
    //   847: aload_1
    //   848: athrow
    //   849: astore_1
    //   850: aload_0
    //   851: getfield 223	com/sleepycat/b/i/g/a/g:c	Lcom/sleepycat/b/i/t;
    //   854: ifnull +10 -> 864
    //   857: aload_0
    //   858: getfield 223	com/sleepycat/b/i/g/a/g:c	Lcom/sleepycat/b/i/t;
    //   861: invokevirtual 297	com/sleepycat/b/i/t:close	()V
    //   864: aload_0
    //   865: getfield 18	com/sleepycat/b/i/g/a/g:b	Lcom/sleepycat/b/i/g/a/f;
    //   868: getfield 300	com/sleepycat/b/i/g/a/f:a	Ljava/util/concurrent/atomic/AtomicBoolean;
    //   871: iconst_1
    //   872: iconst_0
    //   873: invokevirtual 306	java/util/concurrent/atomic/AtomicBoolean:compareAndSet	(ZZ)Z
    //   876: ifne +150 -> 1026
    //   879: ldc_w 308
    //   882: invokestatic 313	com/sleepycat/b/aa:c	(Ljava/lang/String;)Lcom/sleepycat/b/aa;
    //   885: athrow
    //   886: aload 5
    //   888: astore_3
    //   889: aload 7
    //   891: astore_1
    //   892: aload 4
    //   894: astore_2
    //   895: aload 8
    //   897: astore 6
    //   899: aload 10
    //   901: invokevirtual 247	com/sleepycat/b/i/h/d:a	()Lcom/sleepycat/b/i/h/e;
    //   904: getstatic 333	com/sleepycat/b/i/g/a/i:l	Lcom/sleepycat/b/i/h/e;
    //   907: if_acmpeq -101 -> 806
    //   910: aload 5
    //   912: astore_3
    //   913: aload 7
    //   915: astore_1
    //   916: aload 4
    //   918: astore_2
    //   919: aload 9
    //   921: invokevirtual 145	java/lang/Object:getClass	()Ljava/lang/Class;
    //   924: pop
    //   925: aload 5
    //   927: astore_3
    //   928: aload 7
    //   930: astore_1
    //   931: aload 4
    //   933: astore_2
    //   934: aload 9
    //   936: new 326	com/sleepycat/b/i/h/f
    //   939: dup
    //   940: aload 9
    //   942: new 335	java/lang/StringBuilder
    //   945: dup
    //   946: ldc_w 337
    //   949: invokespecial 338	java/lang/StringBuilder:<init>	(Ljava/lang/String;)V
    //   952: aload 10
    //   954: invokevirtual 342	java/lang/StringBuilder:append	(Ljava/lang/Object;)Ljava/lang/StringBuilder;
    //   957: invokevirtual 345	java/lang/StringBuilder:toString	()Ljava/lang/String;
    //   960: invokespecial 330	com/sleepycat/b/i/h/f:<init>	(Lcom/sleepycat/b/i/h/a;Ljava/lang/String;)V
    //   963: aload_0
    //   964: getfield 28	com/sleepycat/b/i/g/a/g:a	Ljava/nio/channels/SocketChannel;
    //   967: invokevirtual 159	com/sleepycat/b/i/g/a/i:a	(Lcom/sleepycat/b/i/h/d;Ljava/nio/channels/WritableByteChannel;)V
    //   970: aload 8
    //   972: astore 6
    //   974: goto -168 -> 806
    //   977: aload_1
    //   978: invokevirtual 247	com/sleepycat/b/i/h/d:a	()Lcom/sleepycat/b/i/h/e;
    //   981: getstatic 348	com/sleepycat/b/i/g/a/i:f	Lcom/sleepycat/b/i/h/e;
    //   984: if_acmpne -619 -> 365
    //   987: aload 9
    //   989: invokevirtual 145	java/lang/Object:getClass	()Ljava/lang/Class;
    //   992: pop
    //   993: aload 9
    //   995: new 350	com/sleepycat/b/i/g/a/s
    //   998: dup
    //   999: aload 9
    //   1001: aload_0
    //   1002: getfield 223	com/sleepycat/b/i/g/a/g:c	Lcom/sleepycat/b/i/t;
    //   1005: invokevirtual 353	com/sleepycat/b/i/t:c	()Ljava/util/List;
    //   1008: invokeinterface 359 1 0
    //   1013: invokespecial 362	com/sleepycat/b/i/g/a/s:<init>	(Lcom/sleepycat/b/i/g/a/i;I)V
    //   1016: aload_0
    //   1017: getfield 28	com/sleepycat/b/i/g/a/g:a	Ljava/nio/channels/SocketChannel;
    //   1020: invokevirtual 159	com/sleepycat/b/i/g/a/i:a	(Lcom/sleepycat/b/i/h/d;Ljava/nio/channels/WritableByteChannel;)V
    //   1023: goto -658 -> 365
    //   1026: aload_1
    //   1027: athrow
    //   1028: return
    //   1029: astore_1
    //   1030: aconst_null
    //   1031: astore_3
    //   1032: goto -418 -> 614
    //   1035: astore 5
    //   1037: aconst_null
    //   1038: astore 4
    //   1040: goto -732 -> 308
    // Local variable table:
    //   start	length	slot	name	signature
    //   0	1043	0	this	g
    //   20	611	1	localObject1	Object
    //   632	16	1	localg	com.sleepycat.b.i.h.g
    //   681	1	1	localIOException	java.io.IOException
    //   723	40	1	locale1	com.sleepycat.b.e
    //   829	19	1	localObject2	Object
    //   849	1	1	localObject3	Object
    //   891	136	1	locald1	com.sleepycat.b.i.h.d
    //   1029	1	1	localObject4	Object
    //   6	928	2	localObject5	Object
    //   1	1031	3	localObject6	Object
    //   122	465	4	locali	com.sleepycat.b.i
    //   605	327	4	localObject7	Object
    //   1038	1	4	localObject8	Object
    //   11	256	5	localObject9	Object
    //   306	195	5	localp1	com.sleepycat.b.p
    //   516	410	5	locale2	com.sleepycat.b.e
    //   1035	1	5	localp2	com.sleepycat.b.p
    //   103	870	6	localObject10	Object
    //   3	926	7	locald2	com.sleepycat.b.i.h.d
    //   8	963	8	localObject11	Object
    //   68	932	9	locali1	i
    //   182	771	10	localObject12	Object
    // Exception table:
    //   from	to	target	type
    //   133	139	306	com/sleepycat/b/p
    //   148	166	306	com/sleepycat/b/p
    //   175	184	306	com/sleepycat/b/p
    //   193	203	306	com/sleepycat/b/p
    //   212	232	306	com/sleepycat/b/p
    //   241	251	306	com/sleepycat/b/p
    //   260	266	306	com/sleepycat/b/p
    //   275	303	306	com/sleepycat/b/p
    //   427	433	306	com/sleepycat/b/p
    //   442	460	306	com/sleepycat/b/p
    //   469	480	306	com/sleepycat/b/p
    //   489	500	306	com/sleepycat/b/p
    //   509	518	306	com/sleepycat/b/p
    //   527	540	306	com/sleepycat/b/p
    //   549	560	306	com/sleepycat/b/p
    //   569	580	306	com/sleepycat/b/p
    //   589	602	306	com/sleepycat/b/p
    //   731	742	306	com/sleepycat/b/p
    //   751	757	306	com/sleepycat/b/p
    //   766	802	306	com/sleepycat/b/p
    //   899	910	306	com/sleepycat/b/p
    //   919	925	306	com/sleepycat/b/p
    //   934	970	306	com/sleepycat/b/p
    //   133	139	605	finally
    //   148	166	605	finally
    //   175	184	605	finally
    //   193	203	605	finally
    //   212	232	605	finally
    //   241	251	605	finally
    //   260	266	605	finally
    //   275	303	605	finally
    //   313	319	605	finally
    //   324	347	605	finally
    //   427	433	605	finally
    //   442	460	605	finally
    //   469	480	605	finally
    //   489	500	605	finally
    //   509	518	605	finally
    //   527	540	605	finally
    //   549	560	605	finally
    //   569	580	605	finally
    //   589	602	605	finally
    //   731	742	605	finally
    //   751	757	605	finally
    //   766	802	605	finally
    //   899	910	605	finally
    //   919	925	605	finally
    //   934	970	605	finally
    //   70	105	632	com/sleepycat/b/i/h/g
    //   351	355	632	com/sleepycat/b/i/h/g
    //   360	365	632	com/sleepycat/b/i/h/g
    //   618	622	632	com/sleepycat/b/i/h/g
    //   626	630	632	com/sleepycat/b/i/h/g
    //   630	632	632	com/sleepycat/b/i/h/g
    //   811	816	632	com/sleepycat/b/i/h/g
    //   821	826	632	com/sleepycat/b/i/h/g
    //   977	1023	632	com/sleepycat/b/i/h/g
    //   13	70	681	java/io/IOException
    //   365	382	681	java/io/IOException
    //   661	678	681	java/io/IOException
    //   830	847	681	java/io/IOException
    //   847	849	681	java/io/IOException
    //   70	105	829	finally
    //   351	355	829	finally
    //   360	365	829	finally
    //   618	622	829	finally
    //   626	630	829	finally
    //   630	632	829	finally
    //   633	661	829	finally
    //   811	816	829	finally
    //   821	826	829	finally
    //   977	1023	829	finally
    //   13	70	849	finally
    //   365	382	849	finally
    //   661	678	849	finally
    //   830	847	849	finally
    //   847	849	849	finally
    //   105	124	1029	finally
    //   105	124	1035	com/sleepycat/b/p
  }
}


/* Location:              E:\apk\xueqiu2\classes-dex2jar.jar!\com\sleepycat\b\i\g\a\g.class
 * Java compiler version: 6 (50.0)
 * JD-Core Version:       0.7.1
 */