package com.sleepycat.b.i.c;

import com.sleepycat.b.aa;
import com.sleepycat.b.p.w;
import java.net.InetSocketAddress;
import java.util.logging.Level;

public final class au
  implements Runnable
{
  public final InetSocketAddress a;
  public Exception b;
  private final ay d;
  private final String e;
  private az f;
  
  public au(ap paramap, InetSocketAddress paramInetSocketAddress, String paramString, ay paramay)
  {
    this.a = paramInetSocketAddress;
    this.e = paramString;
    this.d = paramay;
  }
  
  /* Error */
  private void b()
  {
    // Byte code:
    //   0: aconst_null
    //   1: astore_2
    //   2: new 46	java/net/Socket
    //   5: dup
    //   6: invokespecial 47	java/net/Socket:<init>	()V
    //   9: astore 6
    //   11: aload 6
    //   13: aload_0
    //   14: getfield 22	com/sleepycat/b/i/c/au:c	Lcom/sleepycat/b/i/c/ap;
    //   17: invokestatic 52	com/sleepycat/b/i/c/ap:d	(Lcom/sleepycat/b/i/c/ap;)I
    //   20: invokevirtual 56	java/net/Socket:setSoTimeout	(I)V
    //   23: aload 6
    //   25: iconst_1
    //   26: invokevirtual 60	java/net/Socket:setTcpNoDelay	(Z)V
    //   29: aload 6
    //   31: iconst_1
    //   32: invokevirtual 63	java/net/Socket:setReuseAddress	(Z)V
    //   35: aload 6
    //   37: aload_0
    //   38: getfield 27	com/sleepycat/b/i/c/au:a	Ljava/net/InetSocketAddress;
    //   41: aload_0
    //   42: getfield 22	com/sleepycat/b/i/c/au:c	Lcom/sleepycat/b/i/c/ap;
    //   45: invokestatic 65	com/sleepycat/b/i/c/ap:e	(Lcom/sleepycat/b/i/c/ap;)I
    //   48: invokevirtual 69	java/net/Socket:connect	(Ljava/net/SocketAddress;I)V
    //   51: new 71	java/io/PrintWriter
    //   54: dup
    //   55: aload 6
    //   57: aload_0
    //   58: getfield 29	com/sleepycat/b/i/c/au:e	Ljava/lang/String;
    //   61: invokestatic 76	com/sleepycat/b/i/h/x:a	(Ljava/net/Socket;Ljava/lang/String;)Ljava/io/OutputStream;
    //   64: iconst_1
    //   65: invokespecial 79	java/io/PrintWriter:<init>	(Ljava/io/OutputStream;Z)V
    //   68: astore_1
    //   69: aload_1
    //   70: aload_0
    //   71: getfield 31	com/sleepycat/b/i/c/au:d	Lcom/sleepycat/b/i/c/ay;
    //   74: invokevirtual 84	com/sleepycat/b/i/c/ay:b	()Ljava/lang/String;
    //   77: invokevirtual 88	java/io/PrintWriter:println	(Ljava/lang/String;)V
    //   80: aload_1
    //   81: invokevirtual 91	java/io/PrintWriter:flush	()V
    //   84: new 93	java/io/BufferedReader
    //   87: dup
    //   88: new 95	java/io/InputStreamReader
    //   91: dup
    //   92: aload 6
    //   94: invokevirtual 99	java/net/Socket:getInputStream	()Ljava/io/InputStream;
    //   97: invokespecial 102	java/io/InputStreamReader:<init>	(Ljava/io/InputStream;)V
    //   100: invokespecial 105	java/io/BufferedReader:<init>	(Ljava/io/Reader;)V
    //   103: astore 4
    //   105: aload 4
    //   107: astore_3
    //   108: aload_1
    //   109: astore_2
    //   110: aload 4
    //   112: invokevirtual 108	java/io/BufferedReader:readLine	()Ljava/lang/String;
    //   115: astore 5
    //   117: aload 5
    //   119: ifnonnull +78 -> 197
    //   122: aload 4
    //   124: astore_3
    //   125: aload_1
    //   126: astore_2
    //   127: aload_0
    //   128: new 110	com/sleepycat/b/i/c/ax
    //   131: dup
    //   132: aload_0
    //   133: getfield 22	com/sleepycat/b/i/c/au:c	Lcom/sleepycat/b/i/c/ap;
    //   136: getstatic 115	com/sleepycat/b/i/c/at:a	Lcom/sleepycat/b/i/c/at;
    //   139: new 117	java/lang/StringBuilder
    //   142: dup
    //   143: ldc 119
    //   145: invokespecial 121	java/lang/StringBuilder:<init>	(Ljava/lang/String;)V
    //   148: aload_0
    //   149: getfield 31	com/sleepycat/b/i/c/au:d	Lcom/sleepycat/b/i/c/ay;
    //   152: invokevirtual 84	com/sleepycat/b/i/c/ay:b	()Ljava/lang/String;
    //   155: invokevirtual 125	java/lang/StringBuilder:append	(Ljava/lang/String;)Ljava/lang/StringBuilder;
    //   158: invokevirtual 128	java/lang/StringBuilder:toString	()Ljava/lang/String;
    //   161: invokespecial 131	com/sleepycat/b/i/c/ax:<init>	(Lcom/sleepycat/b/i/c/ap;Lcom/sleepycat/b/i/c/at;Ljava/lang/String;)V
    //   164: putfield 133	com/sleepycat/b/i/c/au:f	Lcom/sleepycat/b/i/c/az;
    //   167: aload_0
    //   168: getfield 22	com/sleepycat/b/i/c/au:c	Lcom/sleepycat/b/i/c/ap;
    //   171: getfield 137	com/sleepycat/b/i/c/ap:q	Ljava/util/logging/Logger;
    //   174: aload_0
    //   175: getfield 22	com/sleepycat/b/i/c/au:c	Lcom/sleepycat/b/i/c/ap;
    //   178: getfield 141	com/sleepycat/b/i/c/ap:s	Lcom/sleepycat/b/c/ad;
    //   181: aload_0
    //   182: getfield 22	com/sleepycat/b/i/c/au:c	Lcom/sleepycat/b/i/c/ap;
    //   185: getfield 145	com/sleepycat/b/i/c/ap:r	Ljava/util/logging/Formatter;
    //   188: aload 6
    //   190: aload 4
    //   192: aload_1
    //   193: invokestatic 150	com/sleepycat/b/i/b/ao:a	(Ljava/util/logging/Logger;Lcom/sleepycat/b/c/ad;Ljava/util/logging/Formatter;Ljava/net/Socket;Ljava/io/BufferedReader;Ljava/io/PrintWriter;)V
    //   196: return
    //   197: aload 4
    //   199: astore_3
    //   200: aload_1
    //   201: astore_2
    //   202: aload_0
    //   203: aload_0
    //   204: getfield 22	com/sleepycat/b/i/c/au:c	Lcom/sleepycat/b/i/c/ap;
    //   207: aload 5
    //   209: invokevirtual 153	com/sleepycat/b/i/c/ap:b	(Ljava/lang/String;)Lcom/sleepycat/b/i/c/as;
    //   212: checkcast 155	com/sleepycat/b/i/c/az
    //   215: putfield 133	com/sleepycat/b/i/c/au:f	Lcom/sleepycat/b/i/c/az;
    //   218: goto -51 -> 167
    //   221: astore 5
    //   223: aload 4
    //   225: astore_3
    //   226: aload_1
    //   227: astore_2
    //   228: aload_0
    //   229: aload 5
    //   231: putfield 157	com/sleepycat/b/i/c/au:b	Ljava/lang/Exception;
    //   234: aload_0
    //   235: getfield 22	com/sleepycat/b/i/c/au:c	Lcom/sleepycat/b/i/c/ap;
    //   238: getfield 137	com/sleepycat/b/i/c/ap:q	Ljava/util/logging/Logger;
    //   241: aload_0
    //   242: getfield 22	com/sleepycat/b/i/c/au:c	Lcom/sleepycat/b/i/c/ap;
    //   245: getfield 141	com/sleepycat/b/i/c/ap:s	Lcom/sleepycat/b/c/ad;
    //   248: aload_0
    //   249: getfield 22	com/sleepycat/b/i/c/au:c	Lcom/sleepycat/b/i/c/ap;
    //   252: getfield 145	com/sleepycat/b/i/c/ap:r	Ljava/util/logging/Formatter;
    //   255: aload 6
    //   257: aload 4
    //   259: aload_1
    //   260: invokestatic 150	com/sleepycat/b/i/b/ao:a	(Ljava/util/logging/Logger;Lcom/sleepycat/b/c/ad;Ljava/util/logging/Formatter;Ljava/net/Socket;Ljava/io/BufferedReader;Ljava/io/PrintWriter;)V
    //   263: return
    //   264: astore 5
    //   266: aconst_null
    //   267: astore_1
    //   268: aconst_null
    //   269: astore 4
    //   271: aload 4
    //   273: astore_3
    //   274: aload_1
    //   275: astore_2
    //   276: aload_0
    //   277: aload 5
    //   279: putfield 157	com/sleepycat/b/i/c/au:b	Ljava/lang/Exception;
    //   282: aload_0
    //   283: getfield 22	com/sleepycat/b/i/c/au:c	Lcom/sleepycat/b/i/c/ap;
    //   286: getfield 137	com/sleepycat/b/i/c/ap:q	Ljava/util/logging/Logger;
    //   289: aload_0
    //   290: getfield 22	com/sleepycat/b/i/c/au:c	Lcom/sleepycat/b/i/c/ap;
    //   293: getfield 141	com/sleepycat/b/i/c/ap:s	Lcom/sleepycat/b/c/ad;
    //   296: aload_0
    //   297: getfield 22	com/sleepycat/b/i/c/au:c	Lcom/sleepycat/b/i/c/ap;
    //   300: getfield 145	com/sleepycat/b/i/c/ap:r	Ljava/util/logging/Formatter;
    //   303: aload 6
    //   305: aload 4
    //   307: aload_1
    //   308: invokestatic 150	com/sleepycat/b/i/b/ao:a	(Ljava/util/logging/Logger;Lcom/sleepycat/b/c/ad;Ljava/util/logging/Formatter;Ljava/net/Socket;Ljava/io/BufferedReader;Ljava/io/PrintWriter;)V
    //   311: return
    //   312: astore 5
    //   314: aconst_null
    //   315: astore_1
    //   316: aconst_null
    //   317: astore 4
    //   319: aload 4
    //   321: astore_3
    //   322: aload_1
    //   323: astore_2
    //   324: aload_0
    //   325: aload 5
    //   327: putfield 157	com/sleepycat/b/i/c/au:b	Ljava/lang/Exception;
    //   330: aload_0
    //   331: getfield 22	com/sleepycat/b/i/c/au:c	Lcom/sleepycat/b/i/c/ap;
    //   334: getfield 137	com/sleepycat/b/i/c/ap:q	Ljava/util/logging/Logger;
    //   337: aload_0
    //   338: getfield 22	com/sleepycat/b/i/c/au:c	Lcom/sleepycat/b/i/c/ap;
    //   341: getfield 141	com/sleepycat/b/i/c/ap:s	Lcom/sleepycat/b/c/ad;
    //   344: aload_0
    //   345: getfield 22	com/sleepycat/b/i/c/au:c	Lcom/sleepycat/b/i/c/ap;
    //   348: getfield 145	com/sleepycat/b/i/c/ap:r	Ljava/util/logging/Formatter;
    //   351: aload 6
    //   353: aload 4
    //   355: aload_1
    //   356: invokestatic 150	com/sleepycat/b/i/b/ao:a	(Ljava/util/logging/Logger;Lcom/sleepycat/b/c/ad;Ljava/util/logging/Formatter;Ljava/net/Socket;Ljava/io/BufferedReader;Ljava/io/PrintWriter;)V
    //   359: return
    //   360: astore 5
    //   362: aconst_null
    //   363: astore_1
    //   364: aconst_null
    //   365: astore 4
    //   367: aload 4
    //   369: astore_3
    //   370: aload_1
    //   371: astore_2
    //   372: aload_0
    //   373: aload 5
    //   375: putfield 157	com/sleepycat/b/i/c/au:b	Ljava/lang/Exception;
    //   378: aload_0
    //   379: getfield 22	com/sleepycat/b/i/c/au:c	Lcom/sleepycat/b/i/c/ap;
    //   382: getfield 137	com/sleepycat/b/i/c/ap:q	Ljava/util/logging/Logger;
    //   385: aload_0
    //   386: getfield 22	com/sleepycat/b/i/c/au:c	Lcom/sleepycat/b/i/c/ap;
    //   389: getfield 141	com/sleepycat/b/i/c/ap:s	Lcom/sleepycat/b/c/ad;
    //   392: aload_0
    //   393: getfield 22	com/sleepycat/b/i/c/au:c	Lcom/sleepycat/b/i/c/ap;
    //   396: getfield 145	com/sleepycat/b/i/c/ap:r	Ljava/util/logging/Formatter;
    //   399: aload 6
    //   401: aload 4
    //   403: aload_1
    //   404: invokestatic 150	com/sleepycat/b/i/b/ao:a	(Ljava/util/logging/Logger;Lcom/sleepycat/b/c/ad;Ljava/util/logging/Formatter;Ljava/net/Socket;Ljava/io/BufferedReader;Ljava/io/PrintWriter;)V
    //   407: return
    //   408: astore 5
    //   410: aconst_null
    //   411: astore_1
    //   412: aconst_null
    //   413: astore 4
    //   415: aload 4
    //   417: astore_3
    //   418: aload_1
    //   419: astore_2
    //   420: aload_0
    //   421: aload 5
    //   423: putfield 157	com/sleepycat/b/i/c/au:b	Ljava/lang/Exception;
    //   426: aload_0
    //   427: getfield 22	com/sleepycat/b/i/c/au:c	Lcom/sleepycat/b/i/c/ap;
    //   430: getfield 137	com/sleepycat/b/i/c/ap:q	Ljava/util/logging/Logger;
    //   433: aload_0
    //   434: getfield 22	com/sleepycat/b/i/c/au:c	Lcom/sleepycat/b/i/c/ap;
    //   437: getfield 141	com/sleepycat/b/i/c/ap:s	Lcom/sleepycat/b/c/ad;
    //   440: aload_0
    //   441: getfield 22	com/sleepycat/b/i/c/au:c	Lcom/sleepycat/b/i/c/ap;
    //   444: getfield 145	com/sleepycat/b/i/c/ap:r	Ljava/util/logging/Formatter;
    //   447: aload 6
    //   449: aload 4
    //   451: aload_1
    //   452: invokestatic 150	com/sleepycat/b/i/b/ao:a	(Ljava/util/logging/Logger;Lcom/sleepycat/b/c/ad;Ljava/util/logging/Formatter;Ljava/net/Socket;Ljava/io/BufferedReader;Ljava/io/PrintWriter;)V
    //   455: return
    //   456: astore_3
    //   457: aconst_null
    //   458: astore_1
    //   459: aload_0
    //   460: aload_3
    //   461: putfield 157	com/sleepycat/b/i/c/au:b	Ljava/lang/Exception;
    //   464: aload_0
    //   465: getfield 22	com/sleepycat/b/i/c/au:c	Lcom/sleepycat/b/i/c/ap;
    //   468: getfield 137	com/sleepycat/b/i/c/ap:q	Ljava/util/logging/Logger;
    //   471: aload_0
    //   472: getfield 22	com/sleepycat/b/i/c/au:c	Lcom/sleepycat/b/i/c/ap;
    //   475: getfield 141	com/sleepycat/b/i/c/ap:s	Lcom/sleepycat/b/c/ad;
    //   478: aload_0
    //   479: getfield 22	com/sleepycat/b/i/c/au:c	Lcom/sleepycat/b/i/c/ap;
    //   482: getfield 145	com/sleepycat/b/i/c/ap:r	Ljava/util/logging/Formatter;
    //   485: getstatic 163	java/util/logging/Level:SEVERE	Ljava/util/logging/Level;
    //   488: new 117	java/lang/StringBuilder
    //   491: dup
    //   492: ldc -91
    //   494: invokespecial 121	java/lang/StringBuilder:<init>	(Ljava/lang/String;)V
    //   497: aload_3
    //   498: invokestatic 170	com/sleepycat/b/p/w:a	(Ljava/lang/Exception;)Ljava/lang/String;
    //   501: invokevirtual 125	java/lang/StringBuilder:append	(Ljava/lang/String;)Ljava/lang/StringBuilder;
    //   504: invokevirtual 128	java/lang/StringBuilder:toString	()Ljava/lang/String;
    //   507: invokestatic 173	com/sleepycat/b/p/w:a	(Ljava/util/logging/Logger;Lcom/sleepycat/b/c/ad;Ljava/util/logging/Formatter;Ljava/util/logging/Level;Ljava/lang/String;)V
    //   510: new 117	java/lang/StringBuilder
    //   513: dup
    //   514: ldc -81
    //   516: invokespecial 121	java/lang/StringBuilder:<init>	(Ljava/lang/String;)V
    //   519: aload_0
    //   520: getfield 29	com/sleepycat/b/i/c/au:e	Ljava/lang/String;
    //   523: invokevirtual 125	java/lang/StringBuilder:append	(Ljava/lang/String;)Ljava/lang/StringBuilder;
    //   526: ldc -79
    //   528: invokevirtual 125	java/lang/StringBuilder:append	(Ljava/lang/String;)Ljava/lang/StringBuilder;
    //   531: aload_0
    //   532: getfield 31	com/sleepycat/b/i/c/au:d	Lcom/sleepycat/b/i/c/ay;
    //   535: invokevirtual 180	com/sleepycat/b/i/c/ay:a	()Lcom/sleepycat/b/i/c/av;
    //   538: invokevirtual 183	java/lang/StringBuilder:append	(Ljava/lang/Object;)Ljava/lang/StringBuilder;
    //   541: invokevirtual 128	java/lang/StringBuilder:toString	()Ljava/lang/String;
    //   544: aload_3
    //   545: invokestatic 188	com/sleepycat/b/aa:a	(Ljava/lang/String;Ljava/lang/Exception;)Lcom/sleepycat/b/aa;
    //   548: athrow
    //   549: astore 4
    //   551: aload_2
    //   552: astore_3
    //   553: aload 4
    //   555: astore_2
    //   556: aload_0
    //   557: getfield 22	com/sleepycat/b/i/c/au:c	Lcom/sleepycat/b/i/c/ap;
    //   560: getfield 137	com/sleepycat/b/i/c/ap:q	Ljava/util/logging/Logger;
    //   563: aload_0
    //   564: getfield 22	com/sleepycat/b/i/c/au:c	Lcom/sleepycat/b/i/c/ap;
    //   567: getfield 141	com/sleepycat/b/i/c/ap:s	Lcom/sleepycat/b/c/ad;
    //   570: aload_0
    //   571: getfield 22	com/sleepycat/b/i/c/au:c	Lcom/sleepycat/b/i/c/ap;
    //   574: getfield 145	com/sleepycat/b/i/c/ap:r	Ljava/util/logging/Formatter;
    //   577: aload 6
    //   579: aload_3
    //   580: aload_1
    //   581: invokestatic 150	com/sleepycat/b/i/b/ao:a	(Ljava/util/logging/Logger;Lcom/sleepycat/b/c/ad;Ljava/util/logging/Formatter;Ljava/net/Socket;Ljava/io/BufferedReader;Ljava/io/PrintWriter;)V
    //   584: aload_2
    //   585: athrow
    //   586: astore_2
    //   587: aconst_null
    //   588: astore_1
    //   589: aconst_null
    //   590: astore_3
    //   591: goto -35 -> 556
    //   594: astore_2
    //   595: aconst_null
    //   596: astore_3
    //   597: goto -41 -> 556
    //   600: astore 4
    //   602: aload_2
    //   603: astore_1
    //   604: aload 4
    //   606: astore_2
    //   607: goto -51 -> 556
    //   610: astore_3
    //   611: goto -152 -> 459
    //   614: astore_3
    //   615: aload 4
    //   617: astore_2
    //   618: goto -159 -> 459
    //   621: astore 5
    //   623: aconst_null
    //   624: astore 4
    //   626: goto -211 -> 415
    //   629: astore 5
    //   631: goto -216 -> 415
    //   634: astore 5
    //   636: aconst_null
    //   637: astore 4
    //   639: goto -272 -> 367
    //   642: astore 5
    //   644: goto -277 -> 367
    //   647: astore 5
    //   649: aconst_null
    //   650: astore 4
    //   652: goto -333 -> 319
    //   655: astore 5
    //   657: goto -338 -> 319
    //   660: astore 5
    //   662: aconst_null
    //   663: astore 4
    //   665: goto -394 -> 271
    //   668: astore 5
    //   670: goto -399 -> 271
    //   673: astore 5
    //   675: aconst_null
    //   676: astore_1
    //   677: aconst_null
    //   678: astore 4
    //   680: goto -457 -> 223
    //   683: astore 5
    //   685: aconst_null
    //   686: astore 4
    //   688: goto -465 -> 223
    // Local variable table:
    //   start	length	slot	name	signature
    //   0	691	0	this	au
    //   68	609	1	localObject1	Object
    //   1	584	2	localObject2	Object
    //   586	1	2	localObject3	Object
    //   594	9	2	localObject4	Object
    //   606	12	2	localObject5	Object
    //   107	311	3	localBufferedReader1	java.io.BufferedReader
    //   456	89	3	localException1	Exception
    //   552	45	3	localObject6	Object
    //   610	1	3	localException2	Exception
    //   614	1	3	localException3	Exception
    //   103	347	4	localBufferedReader2	java.io.BufferedReader
    //   549	5	4	localObject7	Object
    //   600	16	4	localObject8	Object
    //   624	63	4	localObject9	Object
    //   115	93	5	str	String
    //   221	9	5	localSocketTimeoutException1	java.net.SocketTimeoutException
    //   264	14	5	localSocketException1	java.net.SocketException
    //   312	14	5	localIOException1	java.io.IOException
    //   360	14	5	localar1	ar
    //   408	14	5	localae1	com.sleepycat.b.i.h.ae
    //   621	1	5	localae2	com.sleepycat.b.i.h.ae
    //   629	1	5	localae3	com.sleepycat.b.i.h.ae
    //   634	1	5	localar2	ar
    //   642	1	5	localar3	ar
    //   647	1	5	localIOException2	java.io.IOException
    //   655	1	5	localIOException3	java.io.IOException
    //   660	1	5	localSocketException2	java.net.SocketException
    //   668	1	5	localSocketException3	java.net.SocketException
    //   673	1	5	localSocketTimeoutException2	java.net.SocketTimeoutException
    //   683	1	5	localSocketTimeoutException3	java.net.SocketTimeoutException
    //   9	569	6	localSocket	java.net.Socket
    // Exception table:
    //   from	to	target	type
    //   110	117	221	java/net/SocketTimeoutException
    //   127	167	221	java/net/SocketTimeoutException
    //   202	218	221	java/net/SocketTimeoutException
    //   11	69	264	java/net/SocketException
    //   11	69	312	java/io/IOException
    //   11	69	360	com/sleepycat/b/i/c/ar
    //   11	69	408	com/sleepycat/b/i/h/ae
    //   11	69	456	java/lang/Exception
    //   459	549	549	finally
    //   11	69	586	finally
    //   69	105	594	finally
    //   110	117	600	finally
    //   127	167	600	finally
    //   202	218	600	finally
    //   228	234	600	finally
    //   276	282	600	finally
    //   324	330	600	finally
    //   372	378	600	finally
    //   420	426	600	finally
    //   69	105	610	java/lang/Exception
    //   110	117	614	java/lang/Exception
    //   127	167	614	java/lang/Exception
    //   202	218	614	java/lang/Exception
    //   69	105	621	com/sleepycat/b/i/h/ae
    //   110	117	629	com/sleepycat/b/i/h/ae
    //   127	167	629	com/sleepycat/b/i/h/ae
    //   202	218	629	com/sleepycat/b/i/h/ae
    //   69	105	634	com/sleepycat/b/i/c/ar
    //   110	117	642	com/sleepycat/b/i/c/ar
    //   127	167	642	com/sleepycat/b/i/c/ar
    //   202	218	642	com/sleepycat/b/i/c/ar
    //   69	105	647	java/io/IOException
    //   110	117	655	java/io/IOException
    //   127	167	655	java/io/IOException
    //   202	218	655	java/io/IOException
    //   69	105	660	java/net/SocketException
    //   110	117	668	java/net/SocketException
    //   127	167	668	java/net/SocketException
    //   202	218	668	java/net/SocketException
    //   11	69	673	java/net/SocketTimeoutException
    //   69	105	683	java/net/SocketTimeoutException
  }
  
  public final az a()
  {
    if (((this.b instanceof ar)) && (((ar)this.b).a == at.c))
    {
      if (this.c.s == null) {
        throw aa.c("Incurred " + this.b + " because of group mismatch ");
      }
      throw aa.a(this.c.s, this.b.getMessage());
    }
    return this.f;
  }
  
  public final void run()
  {
    b();
    if ((this.f != null) && (this.f.a() == this.c.n))
    {
      ax localax = (ax)this.f;
      if (localax.b == at.b)
      {
        this.d.a(localax.i);
        b();
        w.a(this.c.q, this.c.s, this.c.r, Level.INFO, "Resend message: " + this.d.toString() + " in version: " + this.d.i + " while protocol version is: " + ap.a(this.c) + " because of the version mismatch, the returned response message is: " + this.f);
      }
    }
  }
}


/* Location:              E:\apk\xueqiu2\classes-dex2jar.jar!\com\sleepycat\b\i\c\au.class
 * Java compiler version: 6 (50.0)
 * JD-Core Version:       0.7.1
 */