package com.sleepycat.b.i.c;

import java.nio.channels.SocketChannel;

final class e
  implements Runnable
{
  private SocketChannel b;
  
  e(d paramd, SocketChannel paramSocketChannel)
  {
    this.b = paramSocketChannel;
  }
  
  /* Error */
  public final void run()
  {
    // Byte code:
    //   0: new 29	com/sleepycat/b/i/c/a
    //   3: dup
    //   4: getstatic 35	com/sleepycat/b/i/c/b/x:d	Lcom/sleepycat/b/i/c/b/x;
    //   7: aload_0
    //   8: getfield 14	com/sleepycat/b/i/c/e:a	Lcom/sleepycat/b/i/c/d;
    //   11: getfield 40	com/sleepycat/b/i/c/d:a	Lcom/sleepycat/b/i/c/b/aa;
    //   14: getfield 46	com/sleepycat/b/i/c/b/aa:i	Lcom/sleepycat/b/i/c/aj;
    //   17: invokespecial 49	com/sleepycat/b/i/c/a:<init>	(Lcom/sleepycat/b/i/c/b/x;Lcom/sleepycat/b/i/c/aj;)V
    //   20: astore_2
    //   21: aload_0
    //   22: getfield 19	com/sleepycat/b/i/c/e:b	Ljava/nio/channels/SocketChannel;
    //   25: iconst_1
    //   26: invokevirtual 55	java/nio/channels/SocketChannel:configureBlocking	(Z)Ljava/nio/channels/SelectableChannel;
    //   29: pop
    //   30: aload_2
    //   31: aload_0
    //   32: getfield 19	com/sleepycat/b/i/c/e:b	Ljava/nio/channels/SocketChannel;
    //   35: ldc 57
    //   37: invokevirtual 60	com/sleepycat/b/i/c/a:a	(Ljava/nio/channels/ReadableByteChannel;Ljava/lang/Class;)Lcom/sleepycat/b/i/h/d;
    //   40: checkcast 57	com/sleepycat/b/i/c/b
    //   43: astore_1
    //   44: aload_1
    //   45: getfield 63	com/sleepycat/b/i/c/b:b	Ljava/lang/String;
    //   48: astore_3
    //   49: aload_0
    //   50: getfield 14	com/sleepycat/b/i/c/e:a	Lcom/sleepycat/b/i/c/d;
    //   53: getfield 40	com/sleepycat/b/i/c/d:a	Lcom/sleepycat/b/i/c/b/aa;
    //   56: getfield 67	com/sleepycat/b/i/c/b/aa:m	Lcom/sleepycat/b/i/c/t;
    //   59: getfield 71	com/sleepycat/b/i/c/t:a	Ljava/lang/String;
    //   62: aload_3
    //   63: invokevirtual 77	java/lang/String:equals	(Ljava/lang/Object;)Z
    //   66: ifeq +26 -> 92
    //   69: aload_0
    //   70: getfield 14	com/sleepycat/b/i/c/e:a	Lcom/sleepycat/b/i/c/d;
    //   73: getfield 40	com/sleepycat/b/i/c/d:a	Lcom/sleepycat/b/i/c/b/aa;
    //   76: getfield 79	com/sleepycat/b/i/c/b/aa:a	Lcom/sleepycat/b/i/c/b/x;
    //   79: getfield 80	com/sleepycat/b/i/c/b/x:a	Ljava/lang/String;
    //   82: aload_1
    //   83: getfield 81	com/sleepycat/b/i/c/b:a	Ljava/lang/String;
    //   86: invokevirtual 77	java/lang/String:equals	(Ljava/lang/Object;)Z
    //   89: ifne +101 -> 190
    //   92: new 25	com/sleepycat/b/i/h/g
    //   95: dup
    //   96: ldc 83
    //   98: invokespecial 86	com/sleepycat/b/i/h/g:<init>	(Ljava/lang/String;)V
    //   101: athrow
    //   102: astore_1
    //   103: aload_0
    //   104: getfield 14	com/sleepycat/b/i/c/e:a	Lcom/sleepycat/b/i/c/d;
    //   107: getfield 90	com/sleepycat/b/i/c/d:c	Ljava/util/logging/Logger;
    //   110: aload_0
    //   111: getfield 14	com/sleepycat/b/i/c/e:a	Lcom/sleepycat/b/i/c/d;
    //   114: getfield 40	com/sleepycat/b/i/c/d:a	Lcom/sleepycat/b/i/c/b/aa;
    //   117: getfield 46	com/sleepycat/b/i/c/b/aa:i	Lcom/sleepycat/b/i/c/aj;
    //   120: new 92	java/lang/StringBuilder
    //   123: dup
    //   124: ldc 94
    //   126: invokespecial 95	java/lang/StringBuilder:<init>	(Ljava/lang/String;)V
    //   129: aload_1
    //   130: invokestatic 100	com/sleepycat/b/p/w:a	(Ljava/lang/Exception;)Ljava/lang/String;
    //   133: invokevirtual 104	java/lang/StringBuilder:append	(Ljava/lang/String;)Ljava/lang/StringBuilder;
    //   136: ldc 106
    //   138: invokevirtual 104	java/lang/StringBuilder:append	(Ljava/lang/String;)Ljava/lang/StringBuilder;
    //   141: invokevirtual 110	java/lang/StringBuilder:toString	()Ljava/lang/String;
    //   144: invokestatic 113	com/sleepycat/b/p/w:c	(Ljava/util/logging/Logger;Lcom/sleepycat/b/c/ad;Ljava/lang/String;)V
    //   147: aload_2
    //   148: invokevirtual 117	java/lang/Object:getClass	()Ljava/lang/Class;
    //   151: pop
    //   152: aload_2
    //   153: new 119	com/sleepycat/b/i/h/f
    //   156: dup
    //   157: aload_2
    //   158: aload_1
    //   159: invokevirtual 122	com/sleepycat/b/i/h/g:getMessage	()Ljava/lang/String;
    //   162: invokespecial 125	com/sleepycat/b/i/h/f:<init>	(Lcom/sleepycat/b/i/h/a;Ljava/lang/String;)V
    //   165: aload_0
    //   166: getfield 19	com/sleepycat/b/i/c/e:b	Ljava/nio/channels/SocketChannel;
    //   169: invokevirtual 128	com/sleepycat/b/i/c/a:a	(Lcom/sleepycat/b/i/h/d;Ljava/nio/channels/WritableByteChannel;)V
    //   172: aload_0
    //   173: getfield 19	com/sleepycat/b/i/c/e:b	Ljava/nio/channels/SocketChannel;
    //   176: invokevirtual 132	java/nio/channels/SocketChannel:isOpen	()Z
    //   179: ifeq +10 -> 189
    //   182: aload_0
    //   183: getfield 19	com/sleepycat/b/i/c/e:b	Ljava/nio/channels/SocketChannel;
    //   186: invokevirtual 135	java/nio/channels/SocketChannel:close	()V
    //   189: return
    //   190: aload_0
    //   191: getfield 14	com/sleepycat/b/i/c/e:a	Lcom/sleepycat/b/i/c/d;
    //   194: getfield 40	com/sleepycat/b/i/c/d:a	Lcom/sleepycat/b/i/c/b/aa;
    //   197: getfield 139	com/sleepycat/b/i/c/b/aa:t	Lcom/sleepycat/b/i/c/b/w;
    //   200: getfield 144	com/sleepycat/b/i/c/b/w:a	J
    //   203: lstore 11
    //   205: aload_0
    //   206: getfield 14	com/sleepycat/b/i/c/e:a	Lcom/sleepycat/b/i/c/d;
    //   209: getfield 40	com/sleepycat/b/i/c/d:a	Lcom/sleepycat/b/i/c/b/aa;
    //   212: invokevirtual 148	com/sleepycat/b/i/c/b/aa:g	()Lcom/sleepycat/b/p/au;
    //   215: ifnonnull +220 -> 435
    //   218: lconst_0
    //   219: lstore 9
    //   221: aload_0
    //   222: getfield 14	com/sleepycat/b/i/c/e:a	Lcom/sleepycat/b/i/c/d;
    //   225: getfield 40	com/sleepycat/b/i/c/d:a	Lcom/sleepycat/b/i/c/b/aa;
    //   228: getfield 152	com/sleepycat/b/i/c/b/aa:e	Lcom/sleepycat/b/i/c/b/ag;
    //   231: getfield 157	com/sleepycat/b/i/c/b/ag:d	Lcom/sleepycat/b/i/c/b/ai;
    //   234: getfield 161	com/sleepycat/b/i/c/b/ai:d	J
    //   237: lstore 13
    //   239: aload_0
    //   240: getfield 14	com/sleepycat/b/i/c/e:a	Lcom/sleepycat/b/i/c/d;
    //   243: getfield 40	com/sleepycat/b/i/c/d:a	Lcom/sleepycat/b/i/c/b/aa;
    //   246: getfield 165	com/sleepycat/b/i/c/b/aa:f	Lcom/sleepycat/b/i/c/b/m;
    //   249: getfield 170	com/sleepycat/b/i/c/b/m:c	Lcom/sleepycat/b/i/h/af;
    //   252: invokevirtual 176	com/sleepycat/b/i/h/af:size	()I
    //   255: istore 8
    //   257: aload_2
    //   258: invokevirtual 117	java/lang/Object:getClass	()Ljava/lang/Class;
    //   261: pop
    //   262: aload_0
    //   263: getfield 14	com/sleepycat/b/i/c/e:a	Lcom/sleepycat/b/i/c/d;
    //   266: getfield 40	com/sleepycat/b/i/c/d:a	Lcom/sleepycat/b/i/c/b/aa;
    //   269: getfield 79	com/sleepycat/b/i/c/b/aa:a	Lcom/sleepycat/b/i/c/b/x;
    //   272: getfield 80	com/sleepycat/b/i/c/b/x:a	Ljava/lang/String;
    //   275: astore_3
    //   276: aload_0
    //   277: getfield 14	com/sleepycat/b/i/c/e:a	Lcom/sleepycat/b/i/c/d;
    //   280: getfield 40	com/sleepycat/b/i/c/d:a	Lcom/sleepycat/b/i/c/b/aa;
    //   283: getfield 67	com/sleepycat/b/i/c/b/aa:m	Lcom/sleepycat/b/i/c/t;
    //   286: getfield 71	com/sleepycat/b/i/c/t:a	Ljava/lang/String;
    //   289: astore 4
    //   291: aload_0
    //   292: getfield 14	com/sleepycat/b/i/c/e:a	Lcom/sleepycat/b/i/c/d;
    //   295: getfield 40	com/sleepycat/b/i/c/d:a	Lcom/sleepycat/b/i/c/b/aa;
    //   298: invokevirtual 178	com/sleepycat/b/i/c/b/aa:f	()Ljava/lang/String;
    //   301: astore 5
    //   303: getstatic 183	com/sleepycat/b/am:a	Lcom/sleepycat/b/am;
    //   306: astore 6
    //   308: aload_0
    //   309: getfield 14	com/sleepycat/b/i/c/e:a	Lcom/sleepycat/b/i/c/d;
    //   312: getfield 40	com/sleepycat/b/i/c/d:a	Lcom/sleepycat/b/i/c/b/aa;
    //   315: getfield 46	com/sleepycat/b/i/c/b/aa:i	Lcom/sleepycat/b/i/c/aj;
    //   318: getfield 189	com/sleepycat/b/i/c/aj:ap	Lcom/sleepycat/b/i/c/b/z;
    //   321: invokevirtual 194	com/sleepycat/b/i/c/b/z:a	()Lcom/sleepycat/b/i/u;
    //   324: astore 7
    //   326: aload_0
    //   327: getfield 14	com/sleepycat/b/i/c/e:a	Lcom/sleepycat/b/i/c/d;
    //   330: getfield 40	com/sleepycat/b/i/c/d:a	Lcom/sleepycat/b/i/c/b/aa;
    //   333: astore_1
    //   334: aload_1
    //   335: getfield 198	com/sleepycat/b/i/c/b/aa:u	Lcom/sleepycat/b/i/a;
    //   338: ifnull +254 -> 592
    //   341: aload_1
    //   342: getfield 198	com/sleepycat/b/i/c/b/aa:u	Lcom/sleepycat/b/i/a;
    //   345: invokeinterface 203 1 0
    //   350: ifnonnull +103 -> 453
    //   353: goto +239 -> 592
    //   356: aload_2
    //   357: new 205	com/sleepycat/b/i/c/c
    //   360: dup
    //   361: aload_2
    //   362: aload_3
    //   363: aload 4
    //   365: aload 5
    //   367: aload 6
    //   369: lload 11
    //   371: aload 7
    //   373: lload 9
    //   375: lload 13
    //   377: iload 8
    //   379: aload_1
    //   380: invokestatic 210	com/sleepycat/b/p/s:a	()D
    //   383: invokespecial 213	com/sleepycat/b/i/c/c:<init>	(Lcom/sleepycat/b/i/c/a;Ljava/lang/String;Ljava/lang/String;Ljava/lang/String;Lcom/sleepycat/b/am;JLcom/sleepycat/b/i/u;JJI[BD)V
    //   386: aload_0
    //   387: getfield 19	com/sleepycat/b/i/c/e:b	Ljava/nio/channels/SocketChannel;
    //   390: invokevirtual 128	com/sleepycat/b/i/c/a:a	(Lcom/sleepycat/b/i/h/d;Ljava/nio/channels/WritableByteChannel;)V
    //   393: aload_0
    //   394: getfield 14	com/sleepycat/b/i/c/e:a	Lcom/sleepycat/b/i/c/d;
    //   397: getfield 90	com/sleepycat/b/i/c/d:c	Ljava/util/logging/Logger;
    //   400: aload_0
    //   401: getfield 14	com/sleepycat/b/i/c/e:a	Lcom/sleepycat/b/i/c/d;
    //   404: getfield 40	com/sleepycat/b/i/c/d:a	Lcom/sleepycat/b/i/c/b/aa;
    //   407: getfield 46	com/sleepycat/b/i/c/b/aa:i	Lcom/sleepycat/b/i/c/aj;
    //   410: ldc -41
    //   412: invokestatic 217	com/sleepycat/b/p/w:e	(Ljava/util/logging/Logger;Lcom/sleepycat/b/c/ad;Ljava/lang/String;)V
    //   415: aload_0
    //   416: getfield 19	com/sleepycat/b/i/c/e:b	Ljava/nio/channels/SocketChannel;
    //   419: invokevirtual 132	java/nio/channels/SocketChannel:isOpen	()Z
    //   422: ifeq -233 -> 189
    //   425: aload_0
    //   426: getfield 19	com/sleepycat/b/i/c/e:b	Ljava/nio/channels/SocketChannel;
    //   429: invokevirtual 135	java/nio/channels/SocketChannel:close	()V
    //   432: return
    //   433: astore_1
    //   434: return
    //   435: aload_0
    //   436: getfield 14	com/sleepycat/b/i/c/e:a	Lcom/sleepycat/b/i/c/d;
    //   439: getfield 40	com/sleepycat/b/i/c/d:a	Lcom/sleepycat/b/i/c/b/aa;
    //   442: invokevirtual 148	com/sleepycat/b/i/c/b/aa:g	()Lcom/sleepycat/b/p/au;
    //   445: getfield 221	com/sleepycat/b/p/au:c	J
    //   448: lstore 9
    //   450: goto -229 -> 221
    //   453: aload_1
    //   454: getfield 198	com/sleepycat/b/i/c/b/aa:u	Lcom/sleepycat/b/i/a;
    //   457: invokeinterface 203 1 0
    //   462: arraylength
    //   463: ifne +96 -> 559
    //   466: new 223	java/lang/IllegalStateException
    //   469: dup
    //   470: ldc -31
    //   472: invokespecial 226	java/lang/IllegalStateException:<init>	(Ljava/lang/String;)V
    //   475: athrow
    //   476: astore_1
    //   477: aload_0
    //   478: getfield 14	com/sleepycat/b/i/c/e:a	Lcom/sleepycat/b/i/c/d;
    //   481: getfield 90	com/sleepycat/b/i/c/d:c	Ljava/util/logging/Logger;
    //   484: aload_0
    //   485: getfield 14	com/sleepycat/b/i/c/e:a	Lcom/sleepycat/b/i/c/d;
    //   488: getfield 40	com/sleepycat/b/i/c/d:a	Lcom/sleepycat/b/i/c/b/aa;
    //   491: getfield 46	com/sleepycat/b/i/c/b/aa:i	Lcom/sleepycat/b/i/c/aj;
    //   494: new 92	java/lang/StringBuilder
    //   497: dup
    //   498: ldc -28
    //   500: invokespecial 95	java/lang/StringBuilder:<init>	(Ljava/lang/String;)V
    //   503: aload_1
    //   504: invokestatic 100	com/sleepycat/b/p/w:a	(Ljava/lang/Exception;)Ljava/lang/String;
    //   507: invokevirtual 104	java/lang/StringBuilder:append	(Ljava/lang/String;)Ljava/lang/StringBuilder;
    //   510: invokevirtual 110	java/lang/StringBuilder:toString	()Ljava/lang/String;
    //   513: invokestatic 113	com/sleepycat/b/p/w:c	(Ljava/util/logging/Logger;Lcom/sleepycat/b/c/ad;Ljava/lang/String;)V
    //   516: aload_2
    //   517: invokevirtual 117	java/lang/Object:getClass	()Ljava/lang/Class;
    //   520: pop
    //   521: aload_2
    //   522: new 119	com/sleepycat/b/i/h/f
    //   525: dup
    //   526: aload_2
    //   527: aload_1
    //   528: invokevirtual 229	java/lang/Exception:getMessage	()Ljava/lang/String;
    //   531: invokespecial 125	com/sleepycat/b/i/h/f:<init>	(Lcom/sleepycat/b/i/h/a;Ljava/lang/String;)V
    //   534: aload_0
    //   535: getfield 19	com/sleepycat/b/i/c/e:b	Ljava/nio/channels/SocketChannel;
    //   538: invokevirtual 128	com/sleepycat/b/i/c/a:a	(Lcom/sleepycat/b/i/h/d;Ljava/nio/channels/WritableByteChannel;)V
    //   541: aload_0
    //   542: getfield 19	com/sleepycat/b/i/c/e:b	Ljava/nio/channels/SocketChannel;
    //   545: invokevirtual 132	java/nio/channels/SocketChannel:isOpen	()Z
    //   548: ifeq -359 -> 189
    //   551: aload_0
    //   552: getfield 19	com/sleepycat/b/i/c/e:b	Ljava/nio/channels/SocketChannel;
    //   555: invokevirtual 135	java/nio/channels/SocketChannel:close	()V
    //   558: return
    //   559: aload_1
    //   560: getfield 198	com/sleepycat/b/i/c/b/aa:u	Lcom/sleepycat/b/i/a;
    //   563: invokeinterface 203 1 0
    //   568: astore_1
    //   569: goto -213 -> 356
    //   572: astore_1
    //   573: aload_0
    //   574: getfield 19	com/sleepycat/b/i/c/e:b	Ljava/nio/channels/SocketChannel;
    //   577: invokevirtual 132	java/nio/channels/SocketChannel:isOpen	()Z
    //   580: ifeq +10 -> 590
    //   583: aload_0
    //   584: getfield 19	com/sleepycat/b/i/c/e:b	Ljava/nio/channels/SocketChannel;
    //   587: invokevirtual 135	java/nio/channels/SocketChannel:close	()V
    //   590: aload_1
    //   591: athrow
    //   592: aconst_null
    //   593: astore_1
    //   594: goto -238 -> 356
    // Local variable table:
    //   start	length	slot	name	signature
    //   0	597	0	this	e
    //   43	40	1	localb	b
    //   102	57	1	localg	com.sleepycat.b.i.h.g
    //   333	47	1	localaa	com.sleepycat.b.i.c.b.aa
    //   433	21	1	localIOException	java.io.IOException
    //   476	84	1	localException	Exception
    //   568	1	1	arrayOfByte	byte[]
    //   572	19	1	localObject1	Object
    //   593	1	1	localObject2	Object
    //   20	507	2	locala	a
    //   48	315	3	str1	String
    //   289	75	4	str2	String
    //   301	65	5	str3	String
    //   306	62	6	localam	com.sleepycat.b.am
    //   324	48	7	localu	com.sleepycat.b.i.u
    //   255	123	8	i	int
    //   219	230	9	l1	long
    //   203	167	11	l2	long
    //   237	139	13	l3	long
    // Exception table:
    //   from	to	target	type
    //   21	92	102	com/sleepycat/b/i/h/g
    //   92	102	102	com/sleepycat/b/i/h/g
    //   190	218	102	com/sleepycat/b/i/h/g
    //   221	353	102	com/sleepycat/b/i/h/g
    //   356	415	102	com/sleepycat/b/i/h/g
    //   435	450	102	com/sleepycat/b/i/h/g
    //   453	476	102	com/sleepycat/b/i/h/g
    //   559	569	102	com/sleepycat/b/i/h/g
    //   0	21	433	java/io/IOException
    //   172	189	433	java/io/IOException
    //   415	432	433	java/io/IOException
    //   541	558	433	java/io/IOException
    //   573	590	433	java/io/IOException
    //   590	592	433	java/io/IOException
    //   21	92	476	java/lang/Exception
    //   92	102	476	java/lang/Exception
    //   190	218	476	java/lang/Exception
    //   221	353	476	java/lang/Exception
    //   356	415	476	java/lang/Exception
    //   435	450	476	java/lang/Exception
    //   453	476	476	java/lang/Exception
    //   559	569	476	java/lang/Exception
    //   21	92	572	finally
    //   92	102	572	finally
    //   103	172	572	finally
    //   190	218	572	finally
    //   221	353	572	finally
    //   356	415	572	finally
    //   435	450	572	finally
    //   453	476	572	finally
    //   477	541	572	finally
    //   559	569	572	finally
  }
}


/* Location:              E:\apk\xueqiu2\classes-dex2jar.jar!\com\sleepycat\b\i\c\e.class
 * Java compiler version: 6 (50.0)
 * JD-Core Version:       0.7.1
 */