package com.alipay.sdk.f;

public final class d
{
  /* Error */
  public static g a(c paramc)
  {
    // Byte code:
    //   0: aload_0
    //   1: getfield 18	com/alipay/sdk/f/c:a	Lcom/alipay/sdk/b/e;
    //   4: astore_2
    //   5: aload_0
    //   6: getfield 22	com/alipay/sdk/f/c:b	Lcom/alipay/sdk/b/f;
    //   9: astore_3
    //   10: aload_0
    //   11: getfield 26	com/alipay/sdk/f/c:c	Lorg/json/JSONObject;
    //   14: astore_1
    //   15: aload_1
    //   16: ldc 28
    //   18: invokevirtual 34	org/json/JSONObject:has	(Ljava/lang/String;)Z
    //   21: ifeq +23 -> 44
    //   24: new 36	com/alipay/sdk/f/g
    //   27: dup
    //   28: aload_2
    //   29: aload_3
    //   30: invokespecial 39	com/alipay/sdk/f/g:<init>	(Lcom/alipay/sdk/b/e;Lcom/alipay/sdk/b/f;)V
    //   33: astore_1
    //   34: aload_1
    //   35: aload_0
    //   36: getfield 26	com/alipay/sdk/f/c:c	Lorg/json/JSONObject;
    //   39: invokevirtual 42	com/alipay/sdk/f/g:a	(Lorg/json/JSONObject;)V
    //   42: aload_1
    //   43: areturn
    //   44: aload_1
    //   45: ldc 44
    //   47: invokevirtual 34	org/json/JSONObject:has	(Ljava/lang/String;)Z
    //   50: ifeq +50 -> 100
    //   53: aload_1
    //   54: ldc 44
    //   56: invokevirtual 48	org/json/JSONObject:optString	(Ljava/lang/String;)Ljava/lang/String;
    //   59: invokestatic 53	com/alipay/sdk/f/f:a	(Ljava/lang/String;)Lcom/alipay/sdk/f/f;
    //   62: astore_0
    //   63: getstatic 58	com/alipay/sdk/f/e:a	[I
    //   66: aload_0
    //   67: invokevirtual 62	com/alipay/sdk/f/f:ordinal	()I
    //   70: iaload
    //   71: tableswitch	default:+29->100, 1:+31->102, 2:+31->102, 3:+31->102, 4:+48->119
    //   100: aconst_null
    //   101: areturn
    //   102: new 36	com/alipay/sdk/f/g
    //   105: dup
    //   106: aload_2
    //   107: aload_3
    //   108: invokespecial 39	com/alipay/sdk/f/g:<init>	(Lcom/alipay/sdk/b/e;Lcom/alipay/sdk/b/f;)V
    //   111: astore_0
    //   112: aload_0
    //   113: aload_1
    //   114: invokevirtual 42	com/alipay/sdk/f/g:a	(Lorg/json/JSONObject;)V
    //   117: aload_0
    //   118: areturn
    //   119: invokestatic 67	com/alipay/sdk/g/a:a	()Lcom/alipay/sdk/g/a;
    //   122: getfield 70	com/alipay/sdk/g/a:a	Landroid/content/Context;
    //   125: astore_0
    //   126: aload_0
    //   127: invokestatic 75	com/alipay/sdk/i/b:a	(Landroid/content/Context;)Lcom/alipay/sdk/i/b;
    //   130: invokevirtual 78	com/alipay/sdk/i/b:a	()Ljava/lang/String;
    //   133: astore_2
    //   134: aload_0
    //   135: invokestatic 75	com/alipay/sdk/i/b:a	(Landroid/content/Context;)Lcom/alipay/sdk/i/b;
    //   138: invokevirtual 80	com/alipay/sdk/i/b:b	()Ljava/lang/String;
    //   141: astore_3
    //   142: new 82	com/alipay/sdk/h/a
    //   145: dup
    //   146: aload_0
    //   147: invokespecial 85	com/alipay/sdk/h/a:<init>	(Landroid/content/Context;)V
    //   150: astore_1
    //   151: aload_1
    //   152: invokevirtual 89	com/alipay/sdk/h/a:getWritableDatabase	()Landroid/database/sqlite/SQLiteDatabase;
    //   155: astore_0
    //   156: aload_1
    //   157: aload_0
    //   158: aload_2
    //   159: aload_3
    //   160: ldc 91
    //   162: ldc 91
    //   164: invokevirtual 94	com/alipay/sdk/h/a:a	(Landroid/database/sqlite/SQLiteDatabase;Ljava/lang/String;Ljava/lang/String;Ljava/lang/String;Ljava/lang/String;)V
    //   167: aload_0
    //   168: aload_2
    //   169: aload_3
    //   170: invokestatic 97	com/alipay/sdk/h/a:c	(Ljava/lang/String;Ljava/lang/String;)Ljava/lang/String;
    //   173: invokestatic 100	com/alipay/sdk/h/a:a	(Landroid/database/sqlite/SQLiteDatabase;Ljava/lang/String;)V
    //   176: aload_0
    //   177: ifnull +14 -> 191
    //   180: aload_0
    //   181: invokevirtual 106	android/database/sqlite/SQLiteDatabase:isOpen	()Z
    //   184: ifeq +7 -> 191
    //   187: aload_0
    //   188: invokevirtual 109	android/database/sqlite/SQLiteDatabase:close	()V
    //   191: aload_1
    //   192: invokevirtual 110	com/alipay/sdk/h/a:close	()V
    //   195: goto -95 -> 100
    //   198: astore_0
    //   199: aconst_null
    //   200: astore_0
    //   201: aload_0
    //   202: ifnull -11 -> 191
    //   205: aload_0
    //   206: invokevirtual 106	android/database/sqlite/SQLiteDatabase:isOpen	()Z
    //   209: ifeq -18 -> 191
    //   212: aload_0
    //   213: invokevirtual 109	android/database/sqlite/SQLiteDatabase:close	()V
    //   216: goto -25 -> 191
    //   219: astore_1
    //   220: aconst_null
    //   221: astore_0
    //   222: aload_0
    //   223: ifnull +14 -> 237
    //   226: aload_0
    //   227: invokevirtual 106	android/database/sqlite/SQLiteDatabase:isOpen	()Z
    //   230: ifeq +7 -> 237
    //   233: aload_0
    //   234: invokevirtual 109	android/database/sqlite/SQLiteDatabase:close	()V
    //   237: aload_1
    //   238: athrow
    //   239: astore_1
    //   240: goto -18 -> 222
    //   243: astore_2
    //   244: goto -43 -> 201
    // Local variable table:
    //   start	length	slot	name	signature
    //   0	247	0	paramc	c
    //   14	178	1	localObject1	Object
    //   219	19	1	localObject2	Object
    //   239	1	1	localObject3	Object
    //   4	165	2	localObject4	Object
    //   243	1	2	localException	Exception
    //   9	161	3	localObject5	Object
    // Exception table:
    //   from	to	target	type
    //   151	156	198	java/lang/Exception
    //   151	156	219	finally
    //   156	176	239	finally
    //   156	176	243	java/lang/Exception
  }
}


/* Location:              E:\apk\xueqiu2\classes-dex2jar.jar!\com\alipay\sdk\f\d.class
 * Java compiler version: 6 (50.0)
 * JD-Core Version:       0.7.1
 */