package com.sleepycat.b.a;

import com.sleepycat.b.c.ac;
import com.sleepycat.b.c.ao;
import com.sleepycat.b.c.p;
import com.sleepycat.b.g.a.b;
import com.sleepycat.b.g.af;
import com.sleepycat.b.g.am;
import com.sleepycat.b.g.av;
import com.sleepycat.b.g.e;
import com.sleepycat.b.g.l;
import com.sleepycat.b.g.s;
import com.sleepycat.b.g.u;
import com.sleepycat.b.l.ae;
import com.sleepycat.b.l.ah;
import com.sleepycat.b.l.aj;
import com.sleepycat.b.l.al;
import com.sleepycat.b.l.g;
import com.sleepycat.b.l.y;
import com.sleepycat.b.p.z;
import java.util.ArrayList;
import java.util.HashMap;
import java.util.HashSet;
import java.util.Iterator;
import java.util.Map;
import java.util.Set;
import java.util.SortedMap;

public class h
  extends com.sleepycat.b.p.h
{
  private int A = 0;
  private int B = 0;
  private int C = 0;
  private int D = 0;
  private int E;
  private long F;
  public com.sleepycat.b.c.ad a;
  public c b;
  public k c;
  public ad d;
  public aa e;
  private int g;
  private int h = 0;
  private int i = 0;
  private int j = 0;
  private int k = 0;
  private int t = 0;
  private int u = 0;
  private int v = 0;
  private int w = 0;
  private int x = 0;
  private int y = 0;
  private int z = 0;
  
  static
  {
    if (!h.class.desiredAssertionStatus()) {}
    for (boolean bool = true;; bool = false)
    {
      f = bool;
      return;
    }
  }
  
  h(String paramString, com.sleepycat.b.c.ad paramad, c paramc, ad paramad1, aa paramaa, k paramk)
  {
    super(0L, paramString, paramad);
    this.a = paramad;
    this.b = paramc;
    this.c = paramk;
    this.d = paramad1;
    this.e = paramaa;
  }
  
  private static com.sleepycat.b.l.j a(ah paramah, com.sleepycat.b.c.i parami, com.sleepycat.b.l.j paramj, long paramLong)
  {
    com.sleepycat.b.l.j localj = null;
    if (paramj.J())
    {
      paramah = paramah.b(new j(parami, paramj, paramLong));
      parami = paramah;
      if (paramah == null) {
        parami = null;
      }
      label33:
      return parami;
    }
    paramj.a(c.a);
    try
    {
      localae = paramah.a(paramj, true, c.a, paramj.j, null);
    }
    finally
    {
      try
      {
        boolean bool = localae.a;
        if (!bool)
        {
          if ((localae != null) && (localae.a)) {
            localae.d.C();
          }
          return null;
        }
        long l = localae.d.k(localae.e);
        if (l == -1L)
        {
          if ((localae != null) && (localae.a)) {
            localae.d.C();
          }
          return null;
        }
        if (l == paramLong)
        {
          localj = (com.sleepycat.b.l.j)localae.d.j(localae.e);
          paramah = localj;
          if (localj == null)
          {
            paramj.a(parami, paramLong);
            localae.d.a(localae.e, paramj, null);
            paramah = paramj;
          }
          paramah.a(c.a);
          parami = paramah;
          if (localae == null) {
            break label33;
          }
          parami = paramah;
          if (!localae.a) {
            break label33;
          }
        }
        for (parami = localae.d;; parami = localae.d)
        {
          parami.C();
          return paramah;
          if (paramj.f()) {
            l = ((com.sleepycat.b.l.j)localae.d.q(localae.e)).m;
          }
          int m = com.sleepycat.b.p.j.b(l, paramLong);
          if (m > 0)
          {
            if ((localae != null) && (localae.a)) {
              localae.d.C();
            }
            return null;
          }
          paramah = (com.sleepycat.b.l.j)localae.d.q(localae.e);
          paramah.a(c.a);
          parami = paramah;
          if (localae == null) {
            break;
          }
          parami = paramah;
          if (!localae.a) {
            break;
          }
        }
        paramah = finally;
        parami = localj;
      }
      finally
      {
        for (;;)
        {
          ae localae;
          parami = localae;
        }
      }
      if ((parami != null) && (parami.a)) {
        parami.d.C();
      }
      throw paramah;
    }
  }
  
  private void a(r paramr, long paramLong1, long paramLong2, com.sleepycat.b.l.a parama, int paramInt)
  {
    y localy = paramr.a;
    byte[] arrayOfByte = paramr.c;
    com.sleepycat.b.c.i locali = parama.i;
    boolean bool3 = locali.e();
    boolean bool2 = false;
    Object localObject1 = null;
    Object localObject2 = null;
    com.sleepycat.b.n.a locala = null;
    paramr = locala;
    boolean bool1 = bool2;
    try
    {
      ah localah = locali.b;
      paramr = locala;
      bool1 = bool2;
      if ((f) || (localah != null)) {
        break label115;
      }
      paramr = locala;
      bool1 = bool2;
      throw new AssertionError();
    }
    finally {}
    if (paramr != null) {
      paramr.a_(true);
    }
    this.b.a("CleanLN:", localy, paramLong1, false, bool1, false);
    throw parama;
    label115:
    paramr = locala;
    bool1 = bool2;
    int m;
    if ((localy.i()) && (paramLong2 == paramLong1))
    {
      paramr = locala;
      bool1 = bool2;
      if (this.g <= 2)
      {
        bool2 = true;
        paramr = locala;
        bool1 = bool2;
        this.z += 1;
        paramr = locala;
        bool1 = bool2;
        parama.m(paramInt);
        m = 0;
        bool1 = true;
        paramr = (r)localObject1;
      }
    }
    for (;;)
    {
      if ((!bool1) && (m == 0))
      {
        try
        {
          if ((f) || (paramLong2 == paramLong1)) {
            break label458;
          }
          throw new AssertionError();
        }
        finally {}
        break;
        if (paramLong2 == -1L)
        {
          m = 0;
          bool1 = true;
          paramr = (r)localObject1;
          continue;
        }
        if ((paramLong2 != paramLong1) && (bool3))
        {
          paramr = locala;
          bool1 = bool2;
          this.z += 1;
          m = 0;
          bool1 = true;
          paramr = (r)localObject1;
          continue;
        }
        if (paramLong2 == paramLong1)
        {
          paramr = locala;
          bool1 = bool2;
          localObject1 = localObject2;
          if (this.b.P) {
            break label748;
          }
        }
        localObject1 = localObject2;
        if (bool3) {
          break label748;
        }
        paramr = locala;
        bool1 = bool2;
        locala = com.sleepycat.b.n.a.a(this.a, false);
        paramr = locala;
        bool1 = bool2;
        locala.r = false;
        paramr = locala;
        bool1 = bool2;
        if (locala.b(paramLong2, com.sleepycat.b.n.o.a, false, locali).a == com.sleepycat.b.n.h.f)
        {
          paramr = locala;
          bool1 = bool2;
          this.A += 1;
          m = 1;
          bool1 = false;
          paramr = locala;
          continue;
        }
        localObject1 = locala;
        if (paramLong2 == paramLong1) {
          break label748;
        }
        paramr = locala;
        bool1 = bool2;
        this.z += 1;
        m = 0;
        bool1 = true;
        paramr = locala;
        continue;
        label458:
        if (parama.j(paramInt) == null)
        {
          localy.a(locali, paramLong1);
          parama.a(paramInt, localy, arrayOfByte);
        }
        if (bool3)
        {
          ((y)parama.j(paramInt)).l();
          parama.a(true);
          this.C += 1;
          parama.d(com.sleepycat.b.a.a);
        }
      }
      for (bool2 = true;; bool2 = false)
      {
        if (paramr != null) {
          paramr.a_(true);
        }
        if (m != 0)
        {
          if ((!f) && (bool3))
          {
            throw new AssertionError();
            if (this.b.P)
            {
              parama.b(paramInt, true);
              parama.a(true);
              this.C += 1;
              break;
            }
            localObject1 = (y)parama.j(paramInt);
            if ((!f) && (localObject1 == null)) {
              throw new AssertionError();
            }
            long l = ((y)localObject1).a(this.a, locali, parama.h(paramInt), paramLong1, true, c.a((y)localObject1));
            parama.c(paramInt, l);
            if (localy == localObject1) {
              parama.e(paramInt);
            }
            com.sleepycat.b.c.c.a(locali, paramLong1, l, paramr);
            this.B += 1;
            break;
          }
          this.c.a(paramLong2, localy, locali.a, arrayOfByte);
        }
        this.b.a("CleanLN:", localy, paramLong1, true, bool1, bool2);
        return;
      }
      label748:
      m = 0;
      bool1 = false;
      paramr = (r)localObject1;
    }
  }
  
  /* Error */
  private void a(Long paramLong, al paramal, i parami, Map<com.sleepycat.b.c.h, com.sleepycat.b.c.i> paramMap, Set<com.sleepycat.b.c.h> paramSet)
  {
    // Byte code:
    //   0: aload_0
    //   1: aload_0
    //   2: getfield 72	com/sleepycat/b/a/h:y	I
    //   5: iconst_1
    //   6: iadd
    //   7: putfield 72	com/sleepycat/b/a/h:y	I
    //   10: aload_3
    //   11: getfield 279	com/sleepycat/b/a/i:a	Ljava/util/SortedMap;
    //   14: invokeinterface 285 1 0
    //   19: checkcast 287	java/lang/Long
    //   22: astore 9
    //   24: aload_3
    //   25: aload 9
    //   27: invokevirtual 290	com/sleepycat/b/a/i:a	(Ljava/lang/Long;)Lcom/sleepycat/b/a/r;
    //   30: astore 7
    //   32: aload 7
    //   34: getfield 163	com/sleepycat/b/a/r:a	Lcom/sleepycat/b/l/y;
    //   37: astore 6
    //   39: aload 7
    //   41: getfield 166	com/sleepycat/b/a/r:c	[B
    //   44: astore 8
    //   46: aload_1
    //   47: invokevirtual 294	java/lang/Long:longValue	()J
    //   50: aload 9
    //   52: invokevirtual 294	java/lang/Long:longValue	()J
    //   55: invokestatic 297	com/sleepycat/b/p/j:a	(JJ)J
    //   58: lstore 12
    //   60: aload 7
    //   62: getfield 299	com/sleepycat/b/a/r:b	Lcom/sleepycat/b/c/h;
    //   65: astore 9
    //   67: aload_0
    //   68: getfield 84	com/sleepycat/b/a/h:a	Lcom/sleepycat/b/c/ad;
    //   71: getfield 304	com/sleepycat/b/c/ad:q	Lcom/sleepycat/b/c/p;
    //   74: aload 9
    //   76: aload_0
    //   77: getfield 86	com/sleepycat/b/a/h:b	Lcom/sleepycat/b/a/c;
    //   80: getfield 306	com/sleepycat/b/a/c:E	J
    //   83: aload 4
    //   85: invokevirtual 311	com/sleepycat/b/c/p:a	(Lcom/sleepycat/b/c/h;JLjava/util/Map;)Lcom/sleepycat/b/c/i;
    //   88: astore 4
    //   90: aload 4
    //   92: ifnull +11 -> 103
    //   95: aload 4
    //   97: invokevirtual 313	com/sleepycat/b/c/i:z	()Z
    //   100: ifeq +29 -> 129
    //   103: aload_0
    //   104: aload_0
    //   105: getfield 70	com/sleepycat/b/a/h:x	I
    //   108: iconst_1
    //   109: iadd
    //   110: putfield 70	com/sleepycat/b/a/h:x	I
    //   113: aload 5
    //   115: ifnull +13 -> 128
    //   118: aload 5
    //   120: aload 9
    //   122: invokeinterface 319 2 0
    //   127: pop
    //   128: return
    //   129: aload 4
    //   131: getfield 176	com/sleepycat/b/c/i:b	Lcom/sleepycat/b/l/ah;
    //   134: astore 4
    //   136: getstatic 46	com/sleepycat/b/a/h:f	Z
    //   139: ifne +57 -> 196
    //   142: aload 4
    //   144: ifnonnull +52 -> 196
    //   147: new 178	java/lang/AssertionError
    //   150: dup
    //   151: invokespecial 180	java/lang/AssertionError:<init>	()V
    //   154: athrow
    //   155: astore_1
    //   156: aconst_null
    //   157: astore_2
    //   158: iconst_1
    //   159: istore 10
    //   161: iconst_0
    //   162: istore 16
    //   164: aload_2
    //   165: ifnull +7 -> 172
    //   168: aload_2
    //   169: invokevirtual 320	com/sleepycat/b/l/a:C	()V
    //   172: iload 10
    //   174: ifeq +20 -> 194
    //   177: aload_0
    //   178: getfield 86	com/sleepycat/b/a/h:b	Lcom/sleepycat/b/a/c;
    //   181: ldc -68
    //   183: aload 6
    //   185: lload 12
    //   187: iload 16
    //   189: iconst_0
    //   190: iconst_0
    //   191: invokevirtual 191	com/sleepycat/b/a/c:a	(Ljava/lang/String;Lcom/sleepycat/b/l/ac;JZZZ)V
    //   194: aload_1
    //   195: athrow
    //   196: aload 4
    //   198: aload_2
    //   199: aload 8
    //   201: iconst_0
    //   202: iconst_1
    //   203: getstatic 112	com/sleepycat/b/a/c:a	Lcom/sleepycat/b/a;
    //   206: invokevirtual 323	com/sleepycat/b/l/ah:a	(Lcom/sleepycat/b/l/al;[BZZLcom/sleepycat/b/a;)Z
    //   209: istore 16
    //   211: aload_2
    //   212: getfield 328	com/sleepycat/b/l/al:a	Lcom/sleepycat/b/l/a;
    //   215: astore 4
    //   217: aload_2
    //   218: getfield 330	com/sleepycat/b/l/al:b	I
    //   221: istore 11
    //   223: iload 16
    //   225: ifne +42 -> 267
    //   228: aload_0
    //   229: aload_0
    //   230: getfield 74	com/sleepycat/b/a/h:z	I
    //   233: iconst_1
    //   234: iadd
    //   235: putfield 74	com/sleepycat/b/a/h:z	I
    //   238: aload 4
    //   240: ifnull +8 -> 248
    //   243: aload 4
    //   245: invokevirtual 320	com/sleepycat/b/l/a:C	()V
    //   248: aload_0
    //   249: getfield 86	com/sleepycat/b/a/h:b	Lcom/sleepycat/b/a/c;
    //   252: astore_1
    //   253: aload_1
    //   254: ldc -68
    //   256: aload 6
    //   258: lload 12
    //   260: iconst_1
    //   261: iconst_1
    //   262: iconst_0
    //   263: invokevirtual 191	com/sleepycat/b/a/c:a	(Ljava/lang/String;Lcom/sleepycat/b/l/ac;JZZZ)V
    //   266: return
    //   267: aload 4
    //   269: iload 11
    //   271: invokevirtual 334	com/sleepycat/b/l/a:o	(I)Z
    //   274: ifeq +31 -> 305
    //   277: aload_0
    //   278: aload_0
    //   279: getfield 74	com/sleepycat/b/a/h:z	I
    //   282: iconst_1
    //   283: iadd
    //   284: putfield 74	com/sleepycat/b/a/h:z	I
    //   287: aload 4
    //   289: ifnull +8 -> 297
    //   292: aload 4
    //   294: invokevirtual 320	com/sleepycat/b/l/a:C	()V
    //   297: aload_0
    //   298: getfield 86	com/sleepycat/b/a/h:b	Lcom/sleepycat/b/a/c;
    //   301: astore_1
    //   302: goto -49 -> 253
    //   305: aload_0
    //   306: aload 7
    //   308: lload 12
    //   310: aload 4
    //   312: iload 11
    //   314: invokevirtual 335	com/sleepycat/b/l/a:k	(I)J
    //   317: aload 4
    //   319: iload 11
    //   321: invokespecial 337	com/sleepycat/b/a/h:a	(Lcom/sleepycat/b/a/r;JJLcom/sleepycat/b/l/a;I)V
    //   324: iconst_0
    //   325: istore 10
    //   327: iload 10
    //   329: aload 4
    //   331: getfield 339	com/sleepycat/b/l/j:f	I
    //   334: if_icmpge +111 -> 445
    //   337: aload 4
    //   339: iload 10
    //   341: invokevirtual 335	com/sleepycat/b/l/a:k	(I)J
    //   344: lstore 14
    //   346: iload 10
    //   348: iload 11
    //   350: if_icmpeq +86 -> 436
    //   353: aload 4
    //   355: iload 10
    //   357: invokevirtual 334	com/sleepycat/b/l/a:o	(I)Z
    //   360: ifne +76 -> 436
    //   363: aload 4
    //   365: iload 10
    //   367: invokevirtual 341	com/sleepycat/b/l/a:l	(I)Z
    //   370: ifne +66 -> 436
    //   373: lload 14
    //   375: invokestatic 344	com/sleepycat/b/p/j:d	(J)J
    //   378: aload_1
    //   379: invokevirtual 294	java/lang/Long:longValue	()J
    //   382: lcmp
    //   383: ifne +53 -> 436
    //   386: aload_3
    //   387: lload 14
    //   389: invokestatic 346	com/sleepycat/b/p/j:e	(J)J
    //   392: invokestatic 350	java/lang/Long:valueOf	(J)Ljava/lang/Long;
    //   395: invokevirtual 290	com/sleepycat/b/a/i:a	(Ljava/lang/Long;)Lcom/sleepycat/b/a/r;
    //   398: astore_2
    //   399: aload_2
    //   400: ifnull +36 -> 436
    //   403: aload_0
    //   404: aload_0
    //   405: getfield 82	com/sleepycat/b/a/h:D	I
    //   408: iconst_1
    //   409: iadd
    //   410: putfield 82	com/sleepycat/b/a/h:D	I
    //   413: aload_0
    //   414: aload_0
    //   415: getfield 72	com/sleepycat/b/a/h:y	I
    //   418: iconst_1
    //   419: iadd
    //   420: putfield 72	com/sleepycat/b/a/h:y	I
    //   423: aload_0
    //   424: aload_2
    //   425: lload 14
    //   427: lload 14
    //   429: aload 4
    //   431: iload 10
    //   433: invokespecial 337	com/sleepycat/b/a/h:a	(Lcom/sleepycat/b/a/r;JJLcom/sleepycat/b/l/a;I)V
    //   436: iload 10
    //   438: iconst_1
    //   439: iadd
    //   440: istore 10
    //   442: goto -115 -> 327
    //   445: aload 4
    //   447: ifnull -319 -> 128
    //   450: aload 4
    //   452: invokevirtual 320	com/sleepycat/b/l/a:C	()V
    //   455: return
    //   456: astore_1
    //   457: aload 4
    //   459: astore_2
    //   460: iconst_1
    //   461: istore 10
    //   463: iconst_0
    //   464: istore 16
    //   466: goto -302 -> 164
    //   469: astore_1
    //   470: aload 4
    //   472: astore_2
    //   473: iconst_0
    //   474: istore 10
    //   476: iconst_0
    //   477: istore 16
    //   479: goto -315 -> 164
    //   482: astore_1
    //   483: iconst_0
    //   484: istore 10
    //   486: aload 4
    //   488: astore_2
    //   489: iconst_1
    //   490: istore 16
    //   492: goto -328 -> 164
    // Local variable table:
    //   start	length	slot	name	signature
    //   0	495	0	this	h
    //   0	495	1	paramLong	Long
    //   0	495	2	paramal	al
    //   0	495	3	parami	i
    //   0	495	4	paramMap	Map<com.sleepycat.b.c.h, com.sleepycat.b.c.i>
    //   0	495	5	paramSet	Set<com.sleepycat.b.c.h>
    //   37	220	6	localy	y
    //   30	277	7	localr	r
    //   44	156	8	arrayOfByte	byte[]
    //   22	99	9	localObject	Object
    //   159	326	10	m	int
    //   221	130	11	n	int
    //   58	251	12	l1	long
    //   344	84	14	l2	long
    //   162	329	16	bool	boolean
    // Exception table:
    //   from	to	target	type
    //   129	142	155	finally
    //   147	155	155	finally
    //   196	217	155	finally
    //   217	223	456	finally
    //   228	238	456	finally
    //   267	287	456	finally
    //   305	324	469	finally
    //   327	346	482	finally
    //   353	399	482	finally
    //   403	436	482	finally
  }
  
  private boolean a(Long paramLong, o paramo, q paramq, boolean paramBoolean)
  {
    Object localObject1 = this.d.b(paramLong);
    x localx = ((w)localObject1).c();
    int n = this.b.F;
    int m;
    int i7;
    ao localao;
    label82:
    HashSet localHashSet1;
    label90:
    HashMap localHashMap;
    p localp;
    HashSet localHashSet2;
    e locale;
    if (paramBoolean)
    {
      m = 0;
      i7 = ((w)localObject1).a() + n * 2 + m;
      localao = this.a.n;
      localao.e(i7);
      this.a.b(true);
      if (!paramBoolean) {
        break label432;
      }
      localObject1 = null;
      if (!paramBoolean) {
        break label446;
      }
      localHashSet1 = null;
      localHashMap = new HashMap();
      localp = this.a.q;
      localHashSet2 = new HashSet();
      locale = new e(this.a, n, com.sleepycat.b.p.j.a(paramLong.longValue(), 0), paramLong, paramo, paramq);
      locale.q = true;
    }
    al localal;
    long l1;
    long l3;
    int i3;
    int i4;
    int i5;
    int i6;
    label277:
    label347:
    int i1;
    for (;;)
    {
      int i2;
      long l2;
      label359:
      boolean bool1;
      try
      {
        localal = new al();
        m = 0;
        i2 = 0;
        l1 = -1L;
        if (!locale.f()) {
          break label1815;
        }
        this.b.z.f();
        m += 1;
        l2 = locale.c();
        l3 = com.sleepycat.b.p.j.e(l2);
        if (locale.b == 0)
        {
          i3 = 1;
          if (locale.b != 1) {
            continue;
          }
          i4 = 1;
          if (locale.b != 2) {
            continue;
          }
          i5 = 1;
          if (locale.b != 3) {
            continue;
          }
          i6 = 1;
          n = 0;
          if (locale.b != 0) {
            continue;
          }
          paramo = ((com.sleepycat.b.g.a.k)locale.a).d;
          if (paramo == null) {
            break label1715;
          }
          localHashSet2.add(paramo);
          if (m % this.b.Q == 0)
          {
            localp.a(localHashMap);
            localHashMap.clear();
          }
          paramq = localp.a(paramo, this.b.E, localHashMap);
          if (paramq == null) {
            break label1720;
          }
          if (!paramq.z()) {
            break label1712;
          }
          break label1720;
          if (locale.b != 4) {
            break label1731;
          }
          i1 = 1;
          if (i1 != 0) {
            this.g = ((l)locale.a.h()).c;
          }
          bool1 = this.a.b;
          if (!bool1) {
            continue;
          }
          return false;
          m = this.b.G;
          break;
          label432:
          localObject1 = new i(m);
          break label82;
          label446:
          localHashSet1 = new HashSet();
          break label90;
        }
        i3 = 0;
        continue;
        i4 = 0;
        continue;
        i5 = 0;
        continue;
        i6 = 0;
        continue;
        if (locale.b == 1)
        {
          paramo = ((com.sleepycat.b.g.a.j)locale.a).d;
          continue;
        }
        if (locale.b != 2) {
          break label1726;
        }
        paramo = ((b)locale.a).a();
        continue;
        ??? = locale.g;
        i1 = ((u)???).h;
        ((u)???).h = 0;
        if (i1 > 0)
        {
          com.sleepycat.b.c.ad localad = this.a;
          int i8 = localad.M;
          if (i8 > 0) {
            synchronized (localad.Q)
            {
              localad.O = (i1 + localad.O);
              if (localad.O >= i8)
              {
                localad.L += 1;
                localad.O -= i8;
                if ((!com.sleepycat.b.c.ad.ai) && (localad.O < 0)) {
                  throw new AssertionError();
                }
              }
            }
          }
        }
      }
      catch (com.sleepycat.b.g.c paramLong)
      {
        throw new com.sleepycat.b.aa(this.a, ac.j, paramLong);
      }
      finally
      {
        localao.e(0 - i7);
        localp.a(localHashMap);
      }
      this.a.g();
      while ((l1 < l3) && (localx.a())) {
        l1 = localx.b();
      }
      label732:
      i1 = n;
      if (n == 0)
      {
        i1 = n;
        if (i5 != 0)
        {
          i1 = n;
          if (this.g < 8) {
            i1 = 1;
          }
        }
      }
      n = i1;
      if (i1 == 0)
      {
        n = i1;
        if (i4 != 0)
        {
          n = i1;
          if (paramq.h())
          {
            n = i1;
            if (this.g < 8) {
              n = 1;
            }
          }
        }
      }
      if ((n != 0) || (i3 == 0) || (!((com.sleepycat.b.g.a.k)locale.a).f()) || (this.g <= 2)) {
        break label1709;
      }
      n = 1;
      label846:
      if (n != 0)
      {
        if (!paramBoolean)
        {
          if (i3 == 0) {
            break label897;
          }
          this.x += 1;
        }
        for (;;)
        {
          if ((localHashSet1 != null) && (paramo != null)) {
            localHashSet1.add(paramo);
          }
          locale.b();
          break;
          label897:
          if (i5 != 0) {
            this.t += 1;
          } else if (i4 != 0) {
            this.h += 1;
          }
        }
      }
      if (paramBoolean) {
        break label1706;
      }
      this.a.b(true);
      if (i3 != 0)
      {
        ??? = (com.sleepycat.b.g.a.k)locale.a;
        ((com.sleepycat.b.g.a.k)???).c(paramq);
        paramq = ((com.sleepycat.b.g.a.k)???).j();
        ??? = ((com.sleepycat.b.g.a.k)???).k();
        l2 = com.sleepycat.b.p.j.e(l2);
        paramo = new r(paramq, paramo, (byte[])???);
        ((i)localObject1).a.put(Long.valueOf(l2), paramo);
        ((i)localObject1).c += paramo.a();
        ((i)localObject1).c += ao.r;
        if (((i)localObject1).c < ((i)localObject1).b) {
          break label1806;
        }
        n = 1;
        label1061:
        if (n != 0) {
          a(paramLong, localal, (i)localObject1, localHashMap, localHashSet1);
        }
        i2 += 1;
        if (i2 % 100 != 0) {
          break label1803;
        }
        this.b.e();
        break label1803;
      }
      if (i4 != 0)
      {
        paramo = ((com.sleepycat.b.g.a.j)locale.a).c;
        paramo.i = paramq;
        try
        {
          this.i += 1;
          ??? = paramq.b;
          if ((!f) && (??? == null)) {
            throw new AssertionError();
          }
        }
        finally
        {
          this.b.a("CleanIN:", paramo, l2, false, false, false);
        }
        paramq = a((ah)???, paramq, paramo, l2);
        boolean bool2;
        if (paramq == null)
        {
          this.j += 1;
          bool1 = true;
          bool2 = false;
        }
        for (;;)
        {
          this.b.a("CleanIN:", paramo, l2, true, bool1, bool2);
          break;
          this.k += 1;
          paramq.a(true);
          paramq.i();
          paramq.C();
          bool2 = true;
          bool1 = false;
        }
      }
      if (i5 != 0)
      {
        paramo = (com.sleepycat.b.l.c)((b)locale.a).c;
        this.u += 1;
        if ((!com.sleepycat.b.l.c.e) && (paramo.d.size() <= 0)) {
          throw new AssertionError();
        }
        paramo = ((g)paramo.d.get(0)).a;
        paramo = (com.sleepycat.b.l.a)paramq.b.a(paramo, aj.a, null, c.a, null);
        if (paramo == null) {
          this.v += 1;
        } else {
          try
          {
            l3 = paramo.g();
            if (l3 == -1L)
            {
              this.v += 1;
              paramo.C();
              continue;
            }
            if (com.sleepycat.b.p.j.b(l3, l2) > 0)
            {
              this.v += 1;
              paramo.C();
              continue;
            }
            paramo.a(true);
            this.w += 1;
            paramo.C();
            continue;
          }
          finally
          {
            paramo.C();
          }
        }
      }
      else
      {
        if (i6 != 0)
        {
          paramo = this.a;
          paramo.s.a();
        }
        try
        {
          if (com.sleepycat.b.p.j.b(l2, paramo.r) == 0) {
            paramo.r = paramo.w.b(com.sleepycat.b.g.a.q.a(af.p, paramo.q), av.g);
          }
          paramo.s.c();
        }
        finally
        {
          paramo.s.c();
        }
      }
    }
    throw new AssertionError();
    for (;;)
    {
      if (!((i)localObject1).a.isEmpty())
      {
        this.a.b(true);
        a(paramLong, localal, (i)localObject1, localHashMap, localHashSet1);
        this.a.g();
      }
      else
      {
        label1706:
        label1709:
        label1712:
        label1715:
        label1720:
        label1726:
        label1731:
        label1803:
        label1806:
        label1815:
        do
        {
          if (localHashSet1 != null)
          {
            paramo = localHashSet1.iterator();
            while (paramo.hasNext())
            {
              paramq = localp.a((com.sleepycat.b.c.h)paramo.next(), this.b.E, localHashMap);
              this.b.a(paramq);
            }
          }
          this.E = locale.j;
          this.F = locale.g.g;
          localao.e(0 - i7);
          localp.a(localHashMap);
          if (!paramBoolean) {
            this.c.a(paramLong, localHashSet2, locale.c, localao);
          }
          return true;
          break;
          break label846;
          break label347;
          paramq = null;
          break label347;
          n = 1;
          break label347;
          paramo = null;
          break label277;
          i1 = 0;
          break label359;
          i1 = n;
          if (l1 == l3) {
            i1 = 1;
          }
          n = i1;
          if (i1 != 0) {
            break label732;
          }
          n = i1;
          if (i3 != 0) {
            break label732;
          }
          n = i1;
          if (i4 != 0) {
            break label732;
          }
          n = i1;
          if (i5 != 0) {
            break label732;
          }
          n = i1;
          if (i6 != 0) {
            break label732;
          }
          n = 1;
          break label732;
          break;
          n = 0;
          break label1061;
          break;
        } while (localObject1 == null);
      }
    }
  }
  
  /* Error */
  private int c()
  {
    // Byte code:
    //   0: aload_0
    //   1: monitorenter
    //   2: aload_0
    //   3: getfield 84	com/sleepycat/b/a/h:a	Lcom/sleepycat/b/c/ad;
    //   6: invokevirtual 640	com/sleepycat/b/c/ad:l	()Z
    //   9: istore 19
    //   11: iload 19
    //   13: ifeq +11 -> 24
    //   16: iconst_0
    //   17: istore 10
    //   19: aload_0
    //   20: monitorexit
    //   21: iload 10
    //   23: ireturn
    //   24: getstatic 46	com/sleepycat/b/a/h:f	Z
    //   27: ifne +26 -> 53
    //   30: aload_0
    //   31: getfield 84	com/sleepycat/b/a/h:a	Lcom/sleepycat/b/c/ad;
    //   34: getfield 644	com/sleepycat/b/c/ad:ag	Lcom/sleepycat/b/k/a/c;
    //   37: ifnonnull +16 -> 53
    //   40: new 178	java/lang/AssertionError
    //   43: dup
    //   44: invokespecial 180	java/lang/AssertionError:<init>	()V
    //   47: athrow
    //   48: astore_2
    //   49: aload_0
    //   50: monitorexit
    //   51: aload_2
    //   52: athrow
    //   53: aload_0
    //   54: getfield 90	com/sleepycat/b/a/h:d	Lcom/sleepycat/b/a/ad;
    //   57: invokevirtual 647	com/sleepycat/b/a/ad:b	()Ljava/util/SortedMap;
    //   60: astore_2
    //   61: aload_2
    //   62: invokeinterface 648 1 0
    //   67: istore 13
    //   69: iconst_0
    //   70: istore 10
    //   72: iload 10
    //   74: iload 13
    //   76: if_icmplt +40 -> 116
    //   79: aload_0
    //   80: getfield 651	com/sleepycat/b/a/h:r	Ljava/util/logging/Logger;
    //   83: aload_0
    //   84: getfield 84	com/sleepycat/b/a/h:a	Lcom/sleepycat/b/c/ad;
    //   87: getstatic 657	java/util/logging/Level:INFO	Ljava/util/logging/Level;
    //   90: new 659	java/lang/StringBuilder
    //   93: dup
    //   94: ldc_w 661
    //   97: invokespecial 664	java/lang/StringBuilder:<init>	(Ljava/lang/String;)V
    //   100: aload_0
    //   101: getfield 88	com/sleepycat/b/a/h:c	Lcom/sleepycat/b/a/k;
    //   104: invokevirtual 668	java/lang/StringBuilder:append	(Ljava/lang/Object;)Ljava/lang/StringBuilder;
    //   107: invokevirtual 672	java/lang/StringBuilder:toString	()Ljava/lang/String;
    //   110: invokestatic 677	com/sleepycat/b/p/w:a	(Ljava/util/logging/Logger;Lcom/sleepycat/b/c/ad;Ljava/util/logging/Level;Ljava/lang/String;)V
    //   113: goto +2458 -> 2571
    //   116: aload_0
    //   117: getfield 679	com/sleepycat/b/p/h:o	Z
    //   120: ifne +2451 -> 2571
    //   123: aload_0
    //   124: getfield 84	com/sleepycat/b/a/h:a	Lcom/sleepycat/b/c/ad;
    //   127: getfield 440	com/sleepycat/b/c/ad:b	Z
    //   130: ifne +2441 -> 2571
    //   133: aload_0
    //   134: getfield 86	com/sleepycat/b/a/h:b	Lcom/sleepycat/b/a/c;
    //   137: invokevirtual 522	com/sleepycat/b/a/c:e	()V
    //   140: aload_0
    //   141: getfield 86	com/sleepycat/b/a/h:b	Lcom/sleepycat/b/a/c;
    //   144: getfield 681	com/sleepycat/b/a/c:J	Z
    //   147: ifne +2427 -> 2574
    //   150: aload_0
    //   151: getfield 86	com/sleepycat/b/a/h:b	Lcom/sleepycat/b/a/c;
    //   154: getfield 684	com/sleepycat/b/a/c:K	Z
    //   157: ifeq +1194 -> 1351
    //   160: goto +2414 -> 2574
    //   163: aload_0
    //   164: getfield 88	com/sleepycat/b/a/h:c	Lcom/sleepycat/b/a/k;
    //   167: aload_0
    //   168: getfield 92	com/sleepycat/b/a/h:e	Lcom/sleepycat/b/a/aa;
    //   171: aload_2
    //   172: iload 19
    //   174: aload_0
    //   175: getfield 86	com/sleepycat/b/a/h:b	Lcom/sleepycat/b/a/c;
    //   178: getfield 685	com/sleepycat/b/a/c:L	I
    //   181: invokevirtual 688	com/sleepycat/b/a/k:a	(Lcom/sleepycat/b/a/aa;Ljava/util/SortedMap;ZI)Ljava/lang/Long;
    //   184: astore 4
    //   186: aload_0
    //   187: getfield 86	com/sleepycat/b/a/h:b	Lcom/sleepycat/b/a/c;
    //   190: invokevirtual 690	com/sleepycat/b/a/c:d	()V
    //   193: aload 4
    //   195: ifnonnull +2370 -> 2565
    //   198: aload_0
    //   199: getfield 88	com/sleepycat/b/a/h:c	Lcom/sleepycat/b/a/k;
    //   202: aload_0
    //   203: getfield 92	com/sleepycat/b/a/h:e	Lcom/sleepycat/b/a/aa;
    //   206: aload_2
    //   207: invokevirtual 693	com/sleepycat/b/a/k:a	(Lcom/sleepycat/b/a/aa;Ljava/util/SortedMap;)Ljava/lang/Long;
    //   210: astore 4
    //   212: iconst_1
    //   213: istore 21
    //   215: aload 4
    //   217: ifnull +2354 -> 2571
    //   220: aload_2
    //   221: aload 4
    //   223: invokeinterface 696 2 0
    //   228: ifeq +1129 -> 1357
    //   231: aload_2
    //   232: aload 4
    //   234: invokeinterface 699 2 0
    //   239: checkcast 701	com/sleepycat/b/a/o
    //   242: invokevirtual 704	com/sleepycat/b/a/o:c	()Lcom/sleepycat/b/a/o;
    //   245: astore_3
    //   246: new 701	com/sleepycat/b/a/o
    //   249: dup
    //   250: invokespecial 705	com/sleepycat/b/a/o:<init>	()V
    //   253: astore 5
    //   255: new 707	com/sleepycat/b/a/q
    //   258: dup
    //   259: invokespecial 708	com/sleepycat/b/a/q:<init>	()V
    //   262: astore 6
    //   264: aload_0
    //   265: getfield 86	com/sleepycat/b/a/h:b	Lcom/sleepycat/b/a/c;
    //   268: getfield 711	com/sleepycat/b/a/c:ac	Lcom/sleepycat/b/a/aa;
    //   271: astore 7
    //   273: aload 7
    //   275: getfield 715	com/sleepycat/b/a/aa:a	F
    //   278: fstore_1
    //   279: aload_0
    //   280: iconst_0
    //   281: putfield 54	com/sleepycat/b/a/h:h	I
    //   284: aload_0
    //   285: iconst_0
    //   286: putfield 56	com/sleepycat/b/a/h:i	I
    //   289: aload_0
    //   290: iconst_0
    //   291: putfield 58	com/sleepycat/b/a/h:j	I
    //   294: aload_0
    //   295: iconst_0
    //   296: putfield 60	com/sleepycat/b/a/h:k	I
    //   299: aload_0
    //   300: iconst_0
    //   301: putfield 62	com/sleepycat/b/a/h:t	I
    //   304: aload_0
    //   305: iconst_0
    //   306: putfield 64	com/sleepycat/b/a/h:u	I
    //   309: aload_0
    //   310: iconst_0
    //   311: putfield 66	com/sleepycat/b/a/h:v	I
    //   314: aload_0
    //   315: iconst_0
    //   316: putfield 68	com/sleepycat/b/a/h:w	I
    //   319: aload_0
    //   320: iconst_0
    //   321: putfield 70	com/sleepycat/b/a/h:x	I
    //   324: aload_0
    //   325: iconst_0
    //   326: putfield 72	com/sleepycat/b/a/h:y	I
    //   329: aload_0
    //   330: iconst_0
    //   331: putfield 74	com/sleepycat/b/a/h:z	I
    //   334: aload_0
    //   335: iconst_0
    //   336: putfield 78	com/sleepycat/b/a/h:B	I
    //   339: aload_0
    //   340: iconst_0
    //   341: putfield 80	com/sleepycat/b/a/h:C	I
    //   344: aload_0
    //   345: iconst_0
    //   346: putfield 82	com/sleepycat/b/a/h:D	I
    //   349: aload_0
    //   350: iconst_0
    //   351: putfield 76	com/sleepycat/b/a/h:A	I
    //   354: aload_0
    //   355: iconst_0
    //   356: putfield 622	com/sleepycat/b/a/h:E	I
    //   359: aload_0
    //   360: lconst_0
    //   361: putfield 626	com/sleepycat/b/a/h:F	J
    //   364: iconst_0
    //   365: istore 19
    //   367: aload 4
    //   369: invokevirtual 294	java/lang/Long:longValue	()J
    //   372: lstore 15
    //   374: aload_0
    //   375: getfield 86	com/sleepycat/b/a/h:b	Lcom/sleepycat/b/a/c;
    //   378: getfield 717	com/sleepycat/b/a/c:c	Lcom/sleepycat/b/p/z;
    //   381: invokevirtual 408	com/sleepycat/b/p/z:f	()V
    //   384: iload 21
    //   386: ifeq +13 -> 399
    //   389: aload_0
    //   390: getfield 86	com/sleepycat/b/a/h:b	Lcom/sleepycat/b/a/c;
    //   393: getfield 719	com/sleepycat/b/a/c:d	Lcom/sleepycat/b/p/z;
    //   396: invokevirtual 408	com/sleepycat/b/p/z:f	()V
    //   399: aload_0
    //   400: getfield 86	com/sleepycat/b/a/h:b	Lcom/sleepycat/b/a/c;
    //   403: getfield 723	com/sleepycat/b/a/c:af	Ljava/util/concurrent/atomic/AtomicLong;
    //   406: invokevirtual 728	java/util/concurrent/atomic/AtomicLong:incrementAndGet	()J
    //   409: lstore 17
    //   411: aload_0
    //   412: getfield 84	com/sleepycat/b/a/h:a	Lcom/sleepycat/b/c/ad;
    //   415: getfield 374	com/sleepycat/b/c/ad:n	Lcom/sleepycat/b/c/ao;
    //   418: astore 8
    //   420: aload_0
    //   421: getfield 86	com/sleepycat/b/a/h:b	Lcom/sleepycat/b/a/c;
    //   424: getfield 731	com/sleepycat/b/a/c:ag	Lcom/sleepycat/b/p/ao;
    //   427: astore 9
    //   429: new 659	java/lang/StringBuilder
    //   432: dup
    //   433: ldc_w 733
    //   436: invokespecial 664	java/lang/StringBuilder:<init>	(Ljava/lang/String;)V
    //   439: lload 17
    //   441: invokevirtual 736	java/lang/StringBuilder:append	(J)Ljava/lang/StringBuilder;
    //   444: ldc_w 738
    //   447: invokevirtual 741	java/lang/StringBuilder:append	(Ljava/lang/String;)Ljava/lang/StringBuilder;
    //   450: lload 15
    //   452: invokestatic 745	java/lang/Long:toHexString	(J)Ljava/lang/String;
    //   455: invokevirtual 741	java/lang/StringBuilder:append	(Ljava/lang/String;)Ljava/lang/StringBuilder;
    //   458: ldc_w 747
    //   461: invokevirtual 741	java/lang/StringBuilder:append	(Ljava/lang/String;)Ljava/lang/StringBuilder;
    //   464: iload 21
    //   466: invokevirtual 750	java/lang/StringBuilder:append	(Z)Ljava/lang/StringBuilder;
    //   469: ldc_w 752
    //   472: invokevirtual 741	java/lang/StringBuilder:append	(Ljava/lang/String;)Ljava/lang/StringBuilder;
    //   475: aload_0
    //   476: getfield 88	com/sleepycat/b/a/h:c	Lcom/sleepycat/b/a/k;
    //   479: getstatic 757	com/sleepycat/b/a/n:a	Lcom/sleepycat/b/a/n;
    //   482: invokevirtual 760	com/sleepycat/b/a/k:a	(Lcom/sleepycat/b/a/n;)I
    //   485: invokevirtual 763	java/lang/StringBuilder:append	(I)Ljava/lang/StringBuilder;
    //   488: invokevirtual 672	java/lang/StringBuilder:toString	()Ljava/lang/String;
    //   491: astore 9
    //   493: aload_0
    //   494: getfield 765	com/sleepycat/b/a/h:q	Lcom/sleepycat/b/c/ad;
    //   497: aload 9
    //   499: invokestatic 770	com/sleepycat/b/g/aw:a	(Lcom/sleepycat/b/c/ad;Ljava/lang/String;)V
    //   502: aload_0
    //   503: getfield 651	com/sleepycat/b/a/h:r	Ljava/util/logging/Logger;
    //   506: aload_0
    //   507: getfield 84	com/sleepycat/b/a/h:a	Lcom/sleepycat/b/c/ad;
    //   510: getstatic 773	java/util/logging/Level:FINE	Ljava/util/logging/Level;
    //   513: aload 9
    //   515: invokestatic 677	com/sleepycat/b/p/w:a	(Ljava/util/logging/Logger;Lcom/sleepycat/b/c/ad;Ljava/util/logging/Level;Ljava/lang/String;)V
    //   518: aload_0
    //   519: aload 4
    //   521: aload 5
    //   523: aload 6
    //   525: iload 21
    //   527: invokespecial 775	com/sleepycat/b/a/h:a	(Ljava/lang/Long;Lcom/sleepycat/b/a/o;Lcom/sleepycat/b/a/q;Z)Z
    //   530: istore 20
    //   532: iload 20
    //   534: ifeq +2022 -> 2556
    //   537: iload 10
    //   539: iconst_1
    //   540: iadd
    //   541: istore 10
    //   543: aload_0
    //   544: getfield 86	com/sleepycat/b/a/h:b	Lcom/sleepycat/b/a/c;
    //   547: getfield 777	com/sleepycat/b/a/c:f	Lcom/sleepycat/b/p/z;
    //   550: aload_0
    //   551: getfield 54	com/sleepycat/b/a/h:h	I
    //   554: i2l
    //   555: invokevirtual 779	com/sleepycat/b/p/z:b	(J)V
    //   558: aload_0
    //   559: getfield 86	com/sleepycat/b/a/h:b	Lcom/sleepycat/b/a/c;
    //   562: getfield 781	com/sleepycat/b/a/c:g	Lcom/sleepycat/b/p/z;
    //   565: aload_0
    //   566: getfield 56	com/sleepycat/b/a/h:i	I
    //   569: i2l
    //   570: invokevirtual 779	com/sleepycat/b/p/z:b	(J)V
    //   573: aload_0
    //   574: getfield 86	com/sleepycat/b/a/h:b	Lcom/sleepycat/b/a/c;
    //   577: getfield 783	com/sleepycat/b/a/c:h	Lcom/sleepycat/b/p/z;
    //   580: aload_0
    //   581: getfield 58	com/sleepycat/b/a/h:j	I
    //   584: i2l
    //   585: invokevirtual 779	com/sleepycat/b/p/z:b	(J)V
    //   588: aload_0
    //   589: getfield 86	com/sleepycat/b/a/h:b	Lcom/sleepycat/b/a/c;
    //   592: getfield 785	com/sleepycat/b/a/c:i	Lcom/sleepycat/b/p/z;
    //   595: aload_0
    //   596: getfield 60	com/sleepycat/b/a/h:k	I
    //   599: i2l
    //   600: invokevirtual 779	com/sleepycat/b/p/z:b	(J)V
    //   603: aload_0
    //   604: getfield 86	com/sleepycat/b/a/h:b	Lcom/sleepycat/b/a/c;
    //   607: getfield 787	com/sleepycat/b/a/c:j	Lcom/sleepycat/b/p/z;
    //   610: aload_0
    //   611: getfield 62	com/sleepycat/b/a/h:t	I
    //   614: i2l
    //   615: invokevirtual 779	com/sleepycat/b/p/z:b	(J)V
    //   618: aload_0
    //   619: getfield 86	com/sleepycat/b/a/h:b	Lcom/sleepycat/b/a/c;
    //   622: getfield 789	com/sleepycat/b/a/c:k	Lcom/sleepycat/b/p/z;
    //   625: aload_0
    //   626: getfield 64	com/sleepycat/b/a/h:u	I
    //   629: i2l
    //   630: invokevirtual 779	com/sleepycat/b/p/z:b	(J)V
    //   633: aload_0
    //   634: getfield 86	com/sleepycat/b/a/h:b	Lcom/sleepycat/b/a/c;
    //   637: getfield 791	com/sleepycat/b/a/c:l	Lcom/sleepycat/b/p/z;
    //   640: aload_0
    //   641: getfield 66	com/sleepycat/b/a/h:v	I
    //   644: i2l
    //   645: invokevirtual 779	com/sleepycat/b/p/z:b	(J)V
    //   648: aload_0
    //   649: getfield 86	com/sleepycat/b/a/h:b	Lcom/sleepycat/b/a/c;
    //   652: getfield 793	com/sleepycat/b/a/c:m	Lcom/sleepycat/b/p/z;
    //   655: aload_0
    //   656: getfield 68	com/sleepycat/b/a/h:w	I
    //   659: i2l
    //   660: invokevirtual 779	com/sleepycat/b/p/z:b	(J)V
    //   663: aload_0
    //   664: getfield 86	com/sleepycat/b/a/h:b	Lcom/sleepycat/b/a/c;
    //   667: getfield 795	com/sleepycat/b/a/c:n	Lcom/sleepycat/b/p/z;
    //   670: aload_0
    //   671: getfield 70	com/sleepycat/b/a/h:x	I
    //   674: i2l
    //   675: invokevirtual 779	com/sleepycat/b/p/z:b	(J)V
    //   678: aload_0
    //   679: getfield 86	com/sleepycat/b/a/h:b	Lcom/sleepycat/b/a/c;
    //   682: getfield 797	com/sleepycat/b/a/c:o	Lcom/sleepycat/b/p/z;
    //   685: aload_0
    //   686: getfield 72	com/sleepycat/b/a/h:y	I
    //   689: i2l
    //   690: invokevirtual 779	com/sleepycat/b/p/z:b	(J)V
    //   693: aload_0
    //   694: getfield 86	com/sleepycat/b/a/h:b	Lcom/sleepycat/b/a/c;
    //   697: getfield 799	com/sleepycat/b/a/c:p	Lcom/sleepycat/b/p/z;
    //   700: aload_0
    //   701: getfield 74	com/sleepycat/b/a/h:z	I
    //   704: i2l
    //   705: invokevirtual 779	com/sleepycat/b/p/z:b	(J)V
    //   708: aload_0
    //   709: getfield 86	com/sleepycat/b/a/h:b	Lcom/sleepycat/b/a/c;
    //   712: getfield 801	com/sleepycat/b/a/c:r	Lcom/sleepycat/b/p/z;
    //   715: aload_0
    //   716: getfield 78	com/sleepycat/b/a/h:B	I
    //   719: i2l
    //   720: invokevirtual 779	com/sleepycat/b/p/z:b	(J)V
    //   723: aload_0
    //   724: getfield 86	com/sleepycat/b/a/h:b	Lcom/sleepycat/b/a/c;
    //   727: getfield 803	com/sleepycat/b/a/c:s	Lcom/sleepycat/b/p/z;
    //   730: aload_0
    //   731: getfield 80	com/sleepycat/b/a/h:C	I
    //   734: i2l
    //   735: invokevirtual 779	com/sleepycat/b/p/z:b	(J)V
    //   738: aload_0
    //   739: getfield 86	com/sleepycat/b/a/h:b	Lcom/sleepycat/b/a/c;
    //   742: getfield 805	com/sleepycat/b/a/c:t	Lcom/sleepycat/b/p/z;
    //   745: aload_0
    //   746: getfield 82	com/sleepycat/b/a/h:D	I
    //   749: i2l
    //   750: invokevirtual 779	com/sleepycat/b/p/z:b	(J)V
    //   753: aload_0
    //   754: getfield 86	com/sleepycat/b/a/h:b	Lcom/sleepycat/b/a/c;
    //   757: getfield 807	com/sleepycat/b/a/c:q	Lcom/sleepycat/b/p/z;
    //   760: aload_0
    //   761: getfield 76	com/sleepycat/b/a/h:A	I
    //   764: i2l
    //   765: invokevirtual 779	com/sleepycat/b/p/z:b	(J)V
    //   768: aload_0
    //   769: getfield 86	com/sleepycat/b/a/h:b	Lcom/sleepycat/b/a/c;
    //   772: getfield 809	com/sleepycat/b/a/c:A	Lcom/sleepycat/b/p/z;
    //   775: aload_0
    //   776: getfield 626	com/sleepycat/b/a/h:F	J
    //   779: invokevirtual 779	com/sleepycat/b/p/z:b	(J)V
    //   782: iconst_1
    //   783: istore 22
    //   785: iconst_1
    //   786: istore 19
    //   788: iconst_1
    //   789: istore 23
    //   791: iconst_1
    //   792: istore 20
    //   794: aload_3
    //   795: ifnull +1755 -> 2550
    //   798: aload 7
    //   800: aload 4
    //   802: invokevirtual 294	java/lang/Long:longValue	()J
    //   805: aload_2
    //   806: invokeinterface 812 1 0
    //   811: checkcast 287	java/lang/Long
    //   814: invokevirtual 294	java/lang/Long:longValue	()J
    //   817: aload_3
    //   818: aload 5
    //   820: invokevirtual 815	com/sleepycat/b/a/aa:a	(JJLcom/sleepycat/b/a/o;Lcom/sleepycat/b/a/o;)Z
    //   823: istore 24
    //   825: iload 24
    //   827: ifne +1723 -> 2550
    //   830: iconst_1
    //   831: istore 19
    //   833: iload 20
    //   835: ifne +17 -> 852
    //   838: iload 21
    //   840: ifne +12 -> 852
    //   843: aload_0
    //   844: getfield 88	com/sleepycat/b/a/h:c	Lcom/sleepycat/b/a/k;
    //   847: aload 4
    //   849: invokevirtual 818	com/sleepycat/b/a/k:b	(Ljava/lang/Long;)V
    //   852: new 659	java/lang/StringBuilder
    //   855: dup
    //   856: ldc_w 733
    //   859: invokespecial 664	java/lang/StringBuilder:<init>	(Ljava/lang/String;)V
    //   862: lload 17
    //   864: invokevirtual 736	java/lang/StringBuilder:append	(J)Ljava/lang/StringBuilder;
    //   867: ldc_w 820
    //   870: invokevirtual 741	java/lang/StringBuilder:append	(Ljava/lang/String;)Ljava/lang/StringBuilder;
    //   873: lload 15
    //   875: invokestatic 745	java/lang/Long:toHexString	(J)Ljava/lang/String;
    //   878: invokevirtual 741	java/lang/StringBuilder:append	(Ljava/lang/String;)Ljava/lang/StringBuilder;
    //   881: ldc_w 822
    //   884: invokevirtual 741	java/lang/StringBuilder:append	(Ljava/lang/String;)Ljava/lang/StringBuilder;
    //   887: iload 21
    //   889: invokevirtual 750	java/lang/StringBuilder:append	(Z)Ljava/lang/StringBuilder;
    //   892: ldc_w 824
    //   895: invokevirtual 741	java/lang/StringBuilder:append	(Ljava/lang/String;)Ljava/lang/StringBuilder;
    //   898: iload 20
    //   900: invokevirtual 750	java/lang/StringBuilder:append	(Z)Ljava/lang/StringBuilder;
    //   903: ldc_w 826
    //   906: invokevirtual 741	java/lang/StringBuilder:append	(Ljava/lang/String;)Ljava/lang/StringBuilder;
    //   909: iconst_0
    //   910: invokevirtual 750	java/lang/StringBuilder:append	(Z)Ljava/lang/StringBuilder;
    //   913: ldc_w 828
    //   916: invokevirtual 741	java/lang/StringBuilder:append	(Ljava/lang/String;)Ljava/lang/StringBuilder;
    //   919: aload_0
    //   920: getfield 622	com/sleepycat/b/a/h:E	I
    //   923: invokevirtual 763	java/lang/StringBuilder:append	(I)Ljava/lang/StringBuilder;
    //   926: ldc_w 830
    //   929: invokevirtual 741	java/lang/StringBuilder:append	(Ljava/lang/String;)Ljava/lang/StringBuilder;
    //   932: aload_0
    //   933: getfield 54	com/sleepycat/b/a/h:h	I
    //   936: invokevirtual 763	java/lang/StringBuilder:append	(I)Ljava/lang/StringBuilder;
    //   939: ldc_w 832
    //   942: invokevirtual 741	java/lang/StringBuilder:append	(Ljava/lang/String;)Ljava/lang/StringBuilder;
    //   945: aload_0
    //   946: getfield 56	com/sleepycat/b/a/h:i	I
    //   949: invokevirtual 763	java/lang/StringBuilder:append	(I)Ljava/lang/StringBuilder;
    //   952: ldc_w 834
    //   955: invokevirtual 741	java/lang/StringBuilder:append	(Ljava/lang/String;)Ljava/lang/StringBuilder;
    //   958: aload_0
    //   959: getfield 58	com/sleepycat/b/a/h:j	I
    //   962: invokevirtual 763	java/lang/StringBuilder:append	(I)Ljava/lang/StringBuilder;
    //   965: ldc_w 836
    //   968: invokevirtual 741	java/lang/StringBuilder:append	(Ljava/lang/String;)Ljava/lang/StringBuilder;
    //   971: aload_0
    //   972: getfield 60	com/sleepycat/b/a/h:k	I
    //   975: invokevirtual 763	java/lang/StringBuilder:append	(I)Ljava/lang/StringBuilder;
    //   978: ldc_w 838
    //   981: invokevirtual 741	java/lang/StringBuilder:append	(Ljava/lang/String;)Ljava/lang/StringBuilder;
    //   984: aload_0
    //   985: getfield 62	com/sleepycat/b/a/h:t	I
    //   988: invokevirtual 763	java/lang/StringBuilder:append	(I)Ljava/lang/StringBuilder;
    //   991: ldc_w 840
    //   994: invokevirtual 741	java/lang/StringBuilder:append	(Ljava/lang/String;)Ljava/lang/StringBuilder;
    //   997: aload_0
    //   998: getfield 64	com/sleepycat/b/a/h:u	I
    //   1001: invokevirtual 763	java/lang/StringBuilder:append	(I)Ljava/lang/StringBuilder;
    //   1004: ldc_w 842
    //   1007: invokevirtual 741	java/lang/StringBuilder:append	(Ljava/lang/String;)Ljava/lang/StringBuilder;
    //   1010: aload_0
    //   1011: getfield 66	com/sleepycat/b/a/h:v	I
    //   1014: invokevirtual 763	java/lang/StringBuilder:append	(I)Ljava/lang/StringBuilder;
    //   1017: ldc_w 844
    //   1020: invokevirtual 741	java/lang/StringBuilder:append	(Ljava/lang/String;)Ljava/lang/StringBuilder;
    //   1023: aload_0
    //   1024: getfield 68	com/sleepycat/b/a/h:w	I
    //   1027: invokevirtual 763	java/lang/StringBuilder:append	(I)Ljava/lang/StringBuilder;
    //   1030: ldc_w 846
    //   1033: invokevirtual 741	java/lang/StringBuilder:append	(Ljava/lang/String;)Ljava/lang/StringBuilder;
    //   1036: aload_0
    //   1037: getfield 70	com/sleepycat/b/a/h:x	I
    //   1040: invokevirtual 763	java/lang/StringBuilder:append	(I)Ljava/lang/StringBuilder;
    //   1043: ldc_w 848
    //   1046: invokevirtual 741	java/lang/StringBuilder:append	(Ljava/lang/String;)Ljava/lang/StringBuilder;
    //   1049: aload_0
    //   1050: getfield 72	com/sleepycat/b/a/h:y	I
    //   1053: invokevirtual 763	java/lang/StringBuilder:append	(I)Ljava/lang/StringBuilder;
    //   1056: ldc_w 850
    //   1059: invokevirtual 741	java/lang/StringBuilder:append	(Ljava/lang/String;)Ljava/lang/StringBuilder;
    //   1062: aload_0
    //   1063: getfield 74	com/sleepycat/b/a/h:z	I
    //   1066: invokevirtual 763	java/lang/StringBuilder:append	(I)Ljava/lang/StringBuilder;
    //   1069: ldc_w 852
    //   1072: invokevirtual 741	java/lang/StringBuilder:append	(Ljava/lang/String;)Ljava/lang/StringBuilder;
    //   1075: aload_0
    //   1076: getfield 78	com/sleepycat/b/a/h:B	I
    //   1079: invokevirtual 763	java/lang/StringBuilder:append	(I)Ljava/lang/StringBuilder;
    //   1082: ldc_w 854
    //   1085: invokevirtual 741	java/lang/StringBuilder:append	(Ljava/lang/String;)Ljava/lang/StringBuilder;
    //   1088: aload_0
    //   1089: getfield 80	com/sleepycat/b/a/h:C	I
    //   1092: invokevirtual 763	java/lang/StringBuilder:append	(I)Ljava/lang/StringBuilder;
    //   1095: ldc_w 856
    //   1098: invokevirtual 741	java/lang/StringBuilder:append	(Ljava/lang/String;)Ljava/lang/StringBuilder;
    //   1101: aload_0
    //   1102: getfield 82	com/sleepycat/b/a/h:D	I
    //   1105: invokevirtual 763	java/lang/StringBuilder:append	(I)Ljava/lang/StringBuilder;
    //   1108: ldc_w 858
    //   1111: invokevirtual 741	java/lang/StringBuilder:append	(Ljava/lang/String;)Ljava/lang/StringBuilder;
    //   1114: aload_0
    //   1115: getfield 76	com/sleepycat/b/a/h:A	I
    //   1118: invokevirtual 763	java/lang/StringBuilder:append	(I)Ljava/lang/StringBuilder;
    //   1121: invokevirtual 672	java/lang/StringBuilder:toString	()Ljava/lang/String;
    //   1124: astore_2
    //   1125: aload_0
    //   1126: getfield 765	com/sleepycat/b/a/h:q	Lcom/sleepycat/b/c/ad;
    //   1129: aload_2
    //   1130: invokestatic 770	com/sleepycat/b/g/aw:a	(Lcom/sleepycat/b/c/ad;Ljava/lang/String;)V
    //   1133: iload 10
    //   1135: istore 11
    //   1137: aload_0
    //   1138: getfield 651	com/sleepycat/b/a/h:r	Ljava/util/logging/Logger;
    //   1141: getstatic 657	java/util/logging/Level:INFO	Ljava/util/logging/Level;
    //   1144: invokevirtual 864	java/util/logging/Logger:isLoggable	(Ljava/util/logging/Level;)Z
    //   1147: ifeq +189 -> 1336
    //   1150: aload_3
    //   1151: ifnull +1342 -> 2493
    //   1154: aload_3
    //   1155: invokevirtual 866	com/sleepycat/b/a/o:h	()I
    //   1158: istore 12
    //   1160: aload_3
    //   1161: fload_1
    //   1162: invokevirtual 869	com/sleepycat/b/a/o:a	(F)I
    //   1165: i2l
    //   1166: aload_3
    //   1167: getfield 870	com/sleepycat/b/a/o:b	I
    //   1170: i2l
    //   1171: invokestatic 872	com/sleepycat/b/a/o:a	(JJ)I
    //   1174: istore 11
    //   1176: aload 5
    //   1178: invokevirtual 866	com/sleepycat/b/a/o:h	()I
    //   1181: istore 14
    //   1183: new 659	java/lang/StringBuilder
    //   1186: dup
    //   1187: invokespecial 873	java/lang/StringBuilder:<init>	()V
    //   1190: aload_2
    //   1191: invokevirtual 741	java/lang/StringBuilder:append	(Ljava/lang/String;)Ljava/lang/StringBuilder;
    //   1194: ldc_w 875
    //   1197: invokevirtual 741	java/lang/StringBuilder:append	(Ljava/lang/String;)Ljava/lang/StringBuilder;
    //   1200: aload_0
    //   1201: getfield 86	com/sleepycat/b/a/h:b	Lcom/sleepycat/b/a/c;
    //   1204: getfield 711	com/sleepycat/b/a/c:ac	Lcom/sleepycat/b/a/aa;
    //   1207: invokevirtual 878	com/sleepycat/b/a/aa:a	()Lcom/sleepycat/b/a/d;
    //   1210: invokevirtual 668	java/lang/StringBuilder:append	(Ljava/lang/Object;)Ljava/lang/StringBuilder;
    //   1213: ldc_w 880
    //   1216: invokevirtual 741	java/lang/StringBuilder:append	(Ljava/lang/String;)Ljava/lang/StringBuilder;
    //   1219: aload 6
    //   1221: invokevirtual 668	java/lang/StringBuilder:append	(Ljava/lang/Object;)Ljava/lang/StringBuilder;
    //   1224: ldc_w 882
    //   1227: invokevirtual 741	java/lang/StringBuilder:append	(Ljava/lang/String;)Ljava/lang/StringBuilder;
    //   1230: aload_3
    //   1231: invokevirtual 668	java/lang/StringBuilder:append	(Ljava/lang/Object;)Ljava/lang/StringBuilder;
    //   1234: ldc_w 884
    //   1237: invokevirtual 741	java/lang/StringBuilder:append	(Ljava/lang/String;)Ljava/lang/StringBuilder;
    //   1240: aload 5
    //   1242: invokevirtual 668	java/lang/StringBuilder:append	(Ljava/lang/Object;)Ljava/lang/StringBuilder;
    //   1245: ldc_w 886
    //   1248: invokevirtual 741	java/lang/StringBuilder:append	(Ljava/lang/String;)Ljava/lang/StringBuilder;
    //   1251: fload_1
    //   1252: invokevirtual 889	java/lang/StringBuilder:append	(F)Ljava/lang/StringBuilder;
    //   1255: ldc_w 891
    //   1258: invokevirtual 741	java/lang/StringBuilder:append	(Ljava/lang/String;)Ljava/lang/StringBuilder;
    //   1261: aload 7
    //   1263: getfield 715	com/sleepycat/b/a/aa:a	F
    //   1266: invokevirtual 889	java/lang/StringBuilder:append	(F)Ljava/lang/StringBuilder;
    //   1269: ldc_w 893
    //   1272: invokevirtual 741	java/lang/StringBuilder:append	(Ljava/lang/String;)Ljava/lang/StringBuilder;
    //   1275: iload 12
    //   1277: invokevirtual 763	java/lang/StringBuilder:append	(I)Ljava/lang/StringBuilder;
    //   1280: ldc_w 895
    //   1283: invokevirtual 741	java/lang/StringBuilder:append	(Ljava/lang/String;)Ljava/lang/StringBuilder;
    //   1286: iload 11
    //   1288: invokevirtual 763	java/lang/StringBuilder:append	(I)Ljava/lang/StringBuilder;
    //   1291: ldc_w 897
    //   1294: invokevirtual 741	java/lang/StringBuilder:append	(Ljava/lang/String;)Ljava/lang/StringBuilder;
    //   1297: iload 14
    //   1299: invokevirtual 763	java/lang/StringBuilder:append	(I)Ljava/lang/StringBuilder;
    //   1302: ldc_w 899
    //   1305: invokevirtual 741	java/lang/StringBuilder:append	(Ljava/lang/String;)Ljava/lang/StringBuilder;
    //   1308: iload 19
    //   1310: invokevirtual 750	java/lang/StringBuilder:append	(Z)Ljava/lang/StringBuilder;
    //   1313: invokevirtual 672	java/lang/StringBuilder:toString	()Ljava/lang/String;
    //   1316: astore_2
    //   1317: aload_0
    //   1318: getfield 651	com/sleepycat/b/a/h:r	Ljava/util/logging/Logger;
    //   1321: aload_0
    //   1322: getfield 84	com/sleepycat/b/a/h:a	Lcom/sleepycat/b/c/ad;
    //   1325: getstatic 657	java/util/logging/Level:INFO	Ljava/util/logging/Level;
    //   1328: aload_2
    //   1329: invokestatic 677	com/sleepycat/b/p/w:a	(Ljava/util/logging/Logger;Lcom/sleepycat/b/c/ad;Ljava/util/logging/Level;Ljava/lang/String;)V
    //   1332: iload 10
    //   1334: istore 11
    //   1336: aload_0
    //   1337: getfield 90	com/sleepycat/b/a/h:d	Lcom/sleepycat/b/a/ad;
    //   1340: invokevirtual 647	com/sleepycat/b/a/ad:b	()Ljava/util/SortedMap;
    //   1343: astore_2
    //   1344: iload 11
    //   1346: istore 10
    //   1348: goto -1276 -> 72
    //   1351: iconst_0
    //   1352: istore 19
    //   1354: goto -1191 -> 163
    //   1357: aconst_null
    //   1358: astore_3
    //   1359: goto -1113 -> 246
    //   1362: astore_2
    //   1363: aload_0
    //   1364: getfield 90	com/sleepycat/b/a/h:d	Lcom/sleepycat/b/a/ad;
    //   1367: astore_2
    //   1368: aload_2
    //   1369: aload 4
    //   1371: invokestatic 905	java/util/Collections:singleton	(Ljava/lang/Object;)Ljava/util/Set;
    //   1374: aconst_null
    //   1375: invokevirtual 908	com/sleepycat/b/a/ad:a	(Ljava/util/Collection;Ljava/util/Set;)V
    //   1378: aload_2
    //   1379: aload 4
    //   1381: invokevirtual 910	com/sleepycat/b/a/ad:a	(Ljava/lang/Long;)V
    //   1384: aload_0
    //   1385: getfield 88	com/sleepycat/b/a/h:c	Lcom/sleepycat/b/a/k;
    //   1388: aload 4
    //   1390: aload 8
    //   1392: invokevirtual 913	com/sleepycat/b/a/k:a	(Ljava/lang/Long;Lcom/sleepycat/b/c/ao;)V
    //   1395: iload 19
    //   1397: ifne +3 -> 1400
    //   1400: new 659	java/lang/StringBuilder
    //   1403: dup
    //   1404: ldc_w 733
    //   1407: invokespecial 664	java/lang/StringBuilder:<init>	(Ljava/lang/String;)V
    //   1410: lload 17
    //   1412: invokevirtual 736	java/lang/StringBuilder:append	(J)Ljava/lang/StringBuilder;
    //   1415: ldc_w 820
    //   1418: invokevirtual 741	java/lang/StringBuilder:append	(Ljava/lang/String;)Ljava/lang/StringBuilder;
    //   1421: lload 15
    //   1423: invokestatic 745	java/lang/Long:toHexString	(J)Ljava/lang/String;
    //   1426: invokevirtual 741	java/lang/StringBuilder:append	(Ljava/lang/String;)Ljava/lang/StringBuilder;
    //   1429: ldc_w 822
    //   1432: invokevirtual 741	java/lang/StringBuilder:append	(Ljava/lang/String;)Ljava/lang/StringBuilder;
    //   1435: iload 21
    //   1437: invokevirtual 750	java/lang/StringBuilder:append	(Z)Ljava/lang/StringBuilder;
    //   1440: ldc_w 824
    //   1443: invokevirtual 741	java/lang/StringBuilder:append	(Ljava/lang/String;)Ljava/lang/StringBuilder;
    //   1446: iload 19
    //   1448: invokevirtual 750	java/lang/StringBuilder:append	(Z)Ljava/lang/StringBuilder;
    //   1451: ldc_w 826
    //   1454: invokevirtual 741	java/lang/StringBuilder:append	(Ljava/lang/String;)Ljava/lang/StringBuilder;
    //   1457: iconst_1
    //   1458: invokevirtual 750	java/lang/StringBuilder:append	(Z)Ljava/lang/StringBuilder;
    //   1461: ldc_w 828
    //   1464: invokevirtual 741	java/lang/StringBuilder:append	(Ljava/lang/String;)Ljava/lang/StringBuilder;
    //   1467: aload_0
    //   1468: getfield 622	com/sleepycat/b/a/h:E	I
    //   1471: invokevirtual 763	java/lang/StringBuilder:append	(I)Ljava/lang/StringBuilder;
    //   1474: ldc_w 830
    //   1477: invokevirtual 741	java/lang/StringBuilder:append	(Ljava/lang/String;)Ljava/lang/StringBuilder;
    //   1480: aload_0
    //   1481: getfield 54	com/sleepycat/b/a/h:h	I
    //   1484: invokevirtual 763	java/lang/StringBuilder:append	(I)Ljava/lang/StringBuilder;
    //   1487: ldc_w 832
    //   1490: invokevirtual 741	java/lang/StringBuilder:append	(Ljava/lang/String;)Ljava/lang/StringBuilder;
    //   1493: aload_0
    //   1494: getfield 56	com/sleepycat/b/a/h:i	I
    //   1497: invokevirtual 763	java/lang/StringBuilder:append	(I)Ljava/lang/StringBuilder;
    //   1500: ldc_w 834
    //   1503: invokevirtual 741	java/lang/StringBuilder:append	(Ljava/lang/String;)Ljava/lang/StringBuilder;
    //   1506: aload_0
    //   1507: getfield 58	com/sleepycat/b/a/h:j	I
    //   1510: invokevirtual 763	java/lang/StringBuilder:append	(I)Ljava/lang/StringBuilder;
    //   1513: ldc_w 836
    //   1516: invokevirtual 741	java/lang/StringBuilder:append	(Ljava/lang/String;)Ljava/lang/StringBuilder;
    //   1519: aload_0
    //   1520: getfield 60	com/sleepycat/b/a/h:k	I
    //   1523: invokevirtual 763	java/lang/StringBuilder:append	(I)Ljava/lang/StringBuilder;
    //   1526: ldc_w 838
    //   1529: invokevirtual 741	java/lang/StringBuilder:append	(Ljava/lang/String;)Ljava/lang/StringBuilder;
    //   1532: aload_0
    //   1533: getfield 62	com/sleepycat/b/a/h:t	I
    //   1536: invokevirtual 763	java/lang/StringBuilder:append	(I)Ljava/lang/StringBuilder;
    //   1539: ldc_w 840
    //   1542: invokevirtual 741	java/lang/StringBuilder:append	(Ljava/lang/String;)Ljava/lang/StringBuilder;
    //   1545: aload_0
    //   1546: getfield 64	com/sleepycat/b/a/h:u	I
    //   1549: invokevirtual 763	java/lang/StringBuilder:append	(I)Ljava/lang/StringBuilder;
    //   1552: ldc_w 842
    //   1555: invokevirtual 741	java/lang/StringBuilder:append	(Ljava/lang/String;)Ljava/lang/StringBuilder;
    //   1558: aload_0
    //   1559: getfield 66	com/sleepycat/b/a/h:v	I
    //   1562: invokevirtual 763	java/lang/StringBuilder:append	(I)Ljava/lang/StringBuilder;
    //   1565: ldc_w 844
    //   1568: invokevirtual 741	java/lang/StringBuilder:append	(Ljava/lang/String;)Ljava/lang/StringBuilder;
    //   1571: aload_0
    //   1572: getfield 68	com/sleepycat/b/a/h:w	I
    //   1575: invokevirtual 763	java/lang/StringBuilder:append	(I)Ljava/lang/StringBuilder;
    //   1578: ldc_w 846
    //   1581: invokevirtual 741	java/lang/StringBuilder:append	(Ljava/lang/String;)Ljava/lang/StringBuilder;
    //   1584: aload_0
    //   1585: getfield 70	com/sleepycat/b/a/h:x	I
    //   1588: invokevirtual 763	java/lang/StringBuilder:append	(I)Ljava/lang/StringBuilder;
    //   1591: ldc_w 848
    //   1594: invokevirtual 741	java/lang/StringBuilder:append	(Ljava/lang/String;)Ljava/lang/StringBuilder;
    //   1597: aload_0
    //   1598: getfield 72	com/sleepycat/b/a/h:y	I
    //   1601: invokevirtual 763	java/lang/StringBuilder:append	(I)Ljava/lang/StringBuilder;
    //   1604: ldc_w 850
    //   1607: invokevirtual 741	java/lang/StringBuilder:append	(Ljava/lang/String;)Ljava/lang/StringBuilder;
    //   1610: aload_0
    //   1611: getfield 74	com/sleepycat/b/a/h:z	I
    //   1614: invokevirtual 763	java/lang/StringBuilder:append	(I)Ljava/lang/StringBuilder;
    //   1617: ldc_w 852
    //   1620: invokevirtual 741	java/lang/StringBuilder:append	(Ljava/lang/String;)Ljava/lang/StringBuilder;
    //   1623: aload_0
    //   1624: getfield 78	com/sleepycat/b/a/h:B	I
    //   1627: invokevirtual 763	java/lang/StringBuilder:append	(I)Ljava/lang/StringBuilder;
    //   1630: ldc_w 854
    //   1633: invokevirtual 741	java/lang/StringBuilder:append	(Ljava/lang/String;)Ljava/lang/StringBuilder;
    //   1636: aload_0
    //   1637: getfield 80	com/sleepycat/b/a/h:C	I
    //   1640: invokevirtual 763	java/lang/StringBuilder:append	(I)Ljava/lang/StringBuilder;
    //   1643: ldc_w 856
    //   1646: invokevirtual 741	java/lang/StringBuilder:append	(Ljava/lang/String;)Ljava/lang/StringBuilder;
    //   1649: aload_0
    //   1650: getfield 82	com/sleepycat/b/a/h:D	I
    //   1653: invokevirtual 763	java/lang/StringBuilder:append	(I)Ljava/lang/StringBuilder;
    //   1656: ldc_w 858
    //   1659: invokevirtual 741	java/lang/StringBuilder:append	(Ljava/lang/String;)Ljava/lang/StringBuilder;
    //   1662: aload_0
    //   1663: getfield 76	com/sleepycat/b/a/h:A	I
    //   1666: invokevirtual 763	java/lang/StringBuilder:append	(I)Ljava/lang/StringBuilder;
    //   1669: invokevirtual 672	java/lang/StringBuilder:toString	()Ljava/lang/String;
    //   1672: astore_2
    //   1673: aload_0
    //   1674: getfield 765	com/sleepycat/b/a/h:q	Lcom/sleepycat/b/c/ad;
    //   1677: aload_2
    //   1678: invokestatic 770	com/sleepycat/b/g/aw:a	(Lcom/sleepycat/b/c/ad;Ljava/lang/String;)V
    //   1681: aload_0
    //   1682: getfield 651	com/sleepycat/b/a/h:r	Ljava/util/logging/Logger;
    //   1685: getstatic 657	java/util/logging/Level:INFO	Ljava/util/logging/Level;
    //   1688: invokevirtual 864	java/util/logging/Logger:isLoggable	(Ljava/util/logging/Level;)Z
    //   1691: ifeq +184 -> 1875
    //   1694: aload_3
    //   1695: ifnull +789 -> 2484
    //   1698: aload_3
    //   1699: invokevirtual 866	com/sleepycat/b/a/o:h	()I
    //   1702: istore 12
    //   1704: aload_3
    //   1705: fload_1
    //   1706: invokevirtual 869	com/sleepycat/b/a/o:a	(F)I
    //   1709: i2l
    //   1710: aload_3
    //   1711: getfield 870	com/sleepycat/b/a/o:b	I
    //   1714: i2l
    //   1715: invokestatic 872	com/sleepycat/b/a/o:a	(JJ)I
    //   1718: istore 11
    //   1720: aload 5
    //   1722: invokevirtual 866	com/sleepycat/b/a/o:h	()I
    //   1725: istore 14
    //   1727: new 659	java/lang/StringBuilder
    //   1730: dup
    //   1731: invokespecial 873	java/lang/StringBuilder:<init>	()V
    //   1734: aload_2
    //   1735: invokevirtual 741	java/lang/StringBuilder:append	(Ljava/lang/String;)Ljava/lang/StringBuilder;
    //   1738: ldc_w 875
    //   1741: invokevirtual 741	java/lang/StringBuilder:append	(Ljava/lang/String;)Ljava/lang/StringBuilder;
    //   1744: aload_0
    //   1745: getfield 86	com/sleepycat/b/a/h:b	Lcom/sleepycat/b/a/c;
    //   1748: getfield 711	com/sleepycat/b/a/c:ac	Lcom/sleepycat/b/a/aa;
    //   1751: invokevirtual 878	com/sleepycat/b/a/aa:a	()Lcom/sleepycat/b/a/d;
    //   1754: invokevirtual 668	java/lang/StringBuilder:append	(Ljava/lang/Object;)Ljava/lang/StringBuilder;
    //   1757: ldc_w 880
    //   1760: invokevirtual 741	java/lang/StringBuilder:append	(Ljava/lang/String;)Ljava/lang/StringBuilder;
    //   1763: aload 6
    //   1765: invokevirtual 668	java/lang/StringBuilder:append	(Ljava/lang/Object;)Ljava/lang/StringBuilder;
    //   1768: ldc_w 882
    //   1771: invokevirtual 741	java/lang/StringBuilder:append	(Ljava/lang/String;)Ljava/lang/StringBuilder;
    //   1774: aload_3
    //   1775: invokevirtual 668	java/lang/StringBuilder:append	(Ljava/lang/Object;)Ljava/lang/StringBuilder;
    //   1778: ldc_w 884
    //   1781: invokevirtual 741	java/lang/StringBuilder:append	(Ljava/lang/String;)Ljava/lang/StringBuilder;
    //   1784: aload 5
    //   1786: invokevirtual 668	java/lang/StringBuilder:append	(Ljava/lang/Object;)Ljava/lang/StringBuilder;
    //   1789: ldc_w 886
    //   1792: invokevirtual 741	java/lang/StringBuilder:append	(Ljava/lang/String;)Ljava/lang/StringBuilder;
    //   1795: fload_1
    //   1796: invokevirtual 889	java/lang/StringBuilder:append	(F)Ljava/lang/StringBuilder;
    //   1799: ldc_w 891
    //   1802: invokevirtual 741	java/lang/StringBuilder:append	(Ljava/lang/String;)Ljava/lang/StringBuilder;
    //   1805: aload 7
    //   1807: getfield 715	com/sleepycat/b/a/aa:a	F
    //   1810: invokevirtual 889	java/lang/StringBuilder:append	(F)Ljava/lang/StringBuilder;
    //   1813: ldc_w 893
    //   1816: invokevirtual 741	java/lang/StringBuilder:append	(Ljava/lang/String;)Ljava/lang/StringBuilder;
    //   1819: iload 12
    //   1821: invokevirtual 763	java/lang/StringBuilder:append	(I)Ljava/lang/StringBuilder;
    //   1824: ldc_w 895
    //   1827: invokevirtual 741	java/lang/StringBuilder:append	(Ljava/lang/String;)Ljava/lang/StringBuilder;
    //   1830: iload 11
    //   1832: invokevirtual 763	java/lang/StringBuilder:append	(I)Ljava/lang/StringBuilder;
    //   1835: ldc_w 897
    //   1838: invokevirtual 741	java/lang/StringBuilder:append	(Ljava/lang/String;)Ljava/lang/StringBuilder;
    //   1841: iload 14
    //   1843: invokevirtual 763	java/lang/StringBuilder:append	(I)Ljava/lang/StringBuilder;
    //   1846: ldc_w 899
    //   1849: invokevirtual 741	java/lang/StringBuilder:append	(Ljava/lang/String;)Ljava/lang/StringBuilder;
    //   1852: iconst_0
    //   1853: invokevirtual 750	java/lang/StringBuilder:append	(Z)Ljava/lang/StringBuilder;
    //   1856: invokevirtual 672	java/lang/StringBuilder:toString	()Ljava/lang/String;
    //   1859: astore_2
    //   1860: aload_0
    //   1861: getfield 651	com/sleepycat/b/a/h:r	Ljava/util/logging/Logger;
    //   1864: aload_0
    //   1865: getfield 84	com/sleepycat/b/a/h:a	Lcom/sleepycat/b/c/ad;
    //   1868: getstatic 657	java/util/logging/Level:INFO	Ljava/util/logging/Level;
    //   1871: aload_2
    //   1872: invokestatic 677	com/sleepycat/b/p/w:a	(Ljava/util/logging/Logger;Lcom/sleepycat/b/c/ad;Ljava/util/logging/Level;Ljava/lang/String;)V
    //   1875: iload 10
    //   1877: istore 11
    //   1879: goto -543 -> 1336
    //   1882: astore_2
    //   1883: iconst_0
    //   1884: istore 20
    //   1886: iload 20
    //   1888: istore 19
    //   1890: aload_0
    //   1891: getfield 84	com/sleepycat/b/a/h:a	Lcom/sleepycat/b/c/ad;
    //   1894: ldc_w 915
    //   1897: ldc_w 917
    //   1900: ldc_w 919
    //   1903: aload_2
    //   1904: invokestatic 922	com/sleepycat/b/p/w:a	(Lcom/sleepycat/b/c/ad;Ljava/lang/String;Ljava/lang/String;Ljava/lang/String;Ljava/lang/Throwable;)V
    //   1907: iload 20
    //   1909: istore 19
    //   1911: new 476	com/sleepycat/b/aa
    //   1914: dup
    //   1915: aload_0
    //   1916: getfield 84	com/sleepycat/b/a/h:a	Lcom/sleepycat/b/c/ad;
    //   1919: getstatic 924	com/sleepycat/b/c/ac:m	Lcom/sleepycat/b/c/ac;
    //   1922: aload_2
    //   1923: invokespecial 484	com/sleepycat/b/aa:<init>	(Lcom/sleepycat/b/c/ad;Lcom/sleepycat/b/c/ac;Ljava/lang/Throwable;)V
    //   1926: athrow
    //   1927: astore_2
    //   1928: iconst_0
    //   1929: istore 22
    //   1931: iload 19
    //   1933: istore 20
    //   1935: iload 22
    //   1937: istore 19
    //   1939: iload 20
    //   1941: ifne +22 -> 1963
    //   1944: iload 19
    //   1946: ifne +17 -> 1963
    //   1949: iload 21
    //   1951: ifne +12 -> 1963
    //   1954: aload_0
    //   1955: getfield 88	com/sleepycat/b/a/h:c	Lcom/sleepycat/b/a/k;
    //   1958: aload 4
    //   1960: invokevirtual 818	com/sleepycat/b/a/k:b	(Ljava/lang/Long;)V
    //   1963: new 659	java/lang/StringBuilder
    //   1966: dup
    //   1967: ldc_w 733
    //   1970: invokespecial 664	java/lang/StringBuilder:<init>	(Ljava/lang/String;)V
    //   1973: lload 17
    //   1975: invokevirtual 736	java/lang/StringBuilder:append	(J)Ljava/lang/StringBuilder;
    //   1978: ldc_w 820
    //   1981: invokevirtual 741	java/lang/StringBuilder:append	(Ljava/lang/String;)Ljava/lang/StringBuilder;
    //   1984: lload 15
    //   1986: invokestatic 745	java/lang/Long:toHexString	(J)Ljava/lang/String;
    //   1989: invokevirtual 741	java/lang/StringBuilder:append	(Ljava/lang/String;)Ljava/lang/StringBuilder;
    //   1992: ldc_w 822
    //   1995: invokevirtual 741	java/lang/StringBuilder:append	(Ljava/lang/String;)Ljava/lang/StringBuilder;
    //   1998: iload 21
    //   2000: invokevirtual 750	java/lang/StringBuilder:append	(Z)Ljava/lang/StringBuilder;
    //   2003: ldc_w 824
    //   2006: invokevirtual 741	java/lang/StringBuilder:append	(Ljava/lang/String;)Ljava/lang/StringBuilder;
    //   2009: iload 20
    //   2011: invokevirtual 750	java/lang/StringBuilder:append	(Z)Ljava/lang/StringBuilder;
    //   2014: ldc_w 826
    //   2017: invokevirtual 741	java/lang/StringBuilder:append	(Ljava/lang/String;)Ljava/lang/StringBuilder;
    //   2020: iload 19
    //   2022: invokevirtual 750	java/lang/StringBuilder:append	(Z)Ljava/lang/StringBuilder;
    //   2025: ldc_w 828
    //   2028: invokevirtual 741	java/lang/StringBuilder:append	(Ljava/lang/String;)Ljava/lang/StringBuilder;
    //   2031: aload_0
    //   2032: getfield 622	com/sleepycat/b/a/h:E	I
    //   2035: invokevirtual 763	java/lang/StringBuilder:append	(I)Ljava/lang/StringBuilder;
    //   2038: ldc_w 830
    //   2041: invokevirtual 741	java/lang/StringBuilder:append	(Ljava/lang/String;)Ljava/lang/StringBuilder;
    //   2044: aload_0
    //   2045: getfield 54	com/sleepycat/b/a/h:h	I
    //   2048: invokevirtual 763	java/lang/StringBuilder:append	(I)Ljava/lang/StringBuilder;
    //   2051: ldc_w 832
    //   2054: invokevirtual 741	java/lang/StringBuilder:append	(Ljava/lang/String;)Ljava/lang/StringBuilder;
    //   2057: aload_0
    //   2058: getfield 56	com/sleepycat/b/a/h:i	I
    //   2061: invokevirtual 763	java/lang/StringBuilder:append	(I)Ljava/lang/StringBuilder;
    //   2064: ldc_w 834
    //   2067: invokevirtual 741	java/lang/StringBuilder:append	(Ljava/lang/String;)Ljava/lang/StringBuilder;
    //   2070: aload_0
    //   2071: getfield 58	com/sleepycat/b/a/h:j	I
    //   2074: invokevirtual 763	java/lang/StringBuilder:append	(I)Ljava/lang/StringBuilder;
    //   2077: ldc_w 836
    //   2080: invokevirtual 741	java/lang/StringBuilder:append	(Ljava/lang/String;)Ljava/lang/StringBuilder;
    //   2083: aload_0
    //   2084: getfield 60	com/sleepycat/b/a/h:k	I
    //   2087: invokevirtual 763	java/lang/StringBuilder:append	(I)Ljava/lang/StringBuilder;
    //   2090: ldc_w 838
    //   2093: invokevirtual 741	java/lang/StringBuilder:append	(Ljava/lang/String;)Ljava/lang/StringBuilder;
    //   2096: aload_0
    //   2097: getfield 62	com/sleepycat/b/a/h:t	I
    //   2100: invokevirtual 763	java/lang/StringBuilder:append	(I)Ljava/lang/StringBuilder;
    //   2103: ldc_w 840
    //   2106: invokevirtual 741	java/lang/StringBuilder:append	(Ljava/lang/String;)Ljava/lang/StringBuilder;
    //   2109: aload_0
    //   2110: getfield 64	com/sleepycat/b/a/h:u	I
    //   2113: invokevirtual 763	java/lang/StringBuilder:append	(I)Ljava/lang/StringBuilder;
    //   2116: ldc_w 842
    //   2119: invokevirtual 741	java/lang/StringBuilder:append	(Ljava/lang/String;)Ljava/lang/StringBuilder;
    //   2122: aload_0
    //   2123: getfield 66	com/sleepycat/b/a/h:v	I
    //   2126: invokevirtual 763	java/lang/StringBuilder:append	(I)Ljava/lang/StringBuilder;
    //   2129: ldc_w 844
    //   2132: invokevirtual 741	java/lang/StringBuilder:append	(Ljava/lang/String;)Ljava/lang/StringBuilder;
    //   2135: aload_0
    //   2136: getfield 68	com/sleepycat/b/a/h:w	I
    //   2139: invokevirtual 763	java/lang/StringBuilder:append	(I)Ljava/lang/StringBuilder;
    //   2142: ldc_w 846
    //   2145: invokevirtual 741	java/lang/StringBuilder:append	(Ljava/lang/String;)Ljava/lang/StringBuilder;
    //   2148: aload_0
    //   2149: getfield 70	com/sleepycat/b/a/h:x	I
    //   2152: invokevirtual 763	java/lang/StringBuilder:append	(I)Ljava/lang/StringBuilder;
    //   2155: ldc_w 848
    //   2158: invokevirtual 741	java/lang/StringBuilder:append	(Ljava/lang/String;)Ljava/lang/StringBuilder;
    //   2161: aload_0
    //   2162: getfield 72	com/sleepycat/b/a/h:y	I
    //   2165: invokevirtual 763	java/lang/StringBuilder:append	(I)Ljava/lang/StringBuilder;
    //   2168: ldc_w 850
    //   2171: invokevirtual 741	java/lang/StringBuilder:append	(Ljava/lang/String;)Ljava/lang/StringBuilder;
    //   2174: aload_0
    //   2175: getfield 74	com/sleepycat/b/a/h:z	I
    //   2178: invokevirtual 763	java/lang/StringBuilder:append	(I)Ljava/lang/StringBuilder;
    //   2181: ldc_w 852
    //   2184: invokevirtual 741	java/lang/StringBuilder:append	(Ljava/lang/String;)Ljava/lang/StringBuilder;
    //   2187: aload_0
    //   2188: getfield 78	com/sleepycat/b/a/h:B	I
    //   2191: invokevirtual 763	java/lang/StringBuilder:append	(I)Ljava/lang/StringBuilder;
    //   2194: ldc_w 854
    //   2197: invokevirtual 741	java/lang/StringBuilder:append	(Ljava/lang/String;)Ljava/lang/StringBuilder;
    //   2200: aload_0
    //   2201: getfield 80	com/sleepycat/b/a/h:C	I
    //   2204: invokevirtual 763	java/lang/StringBuilder:append	(I)Ljava/lang/StringBuilder;
    //   2207: ldc_w 856
    //   2210: invokevirtual 741	java/lang/StringBuilder:append	(Ljava/lang/String;)Ljava/lang/StringBuilder;
    //   2213: aload_0
    //   2214: getfield 82	com/sleepycat/b/a/h:D	I
    //   2217: invokevirtual 763	java/lang/StringBuilder:append	(I)Ljava/lang/StringBuilder;
    //   2220: ldc_w 858
    //   2223: invokevirtual 741	java/lang/StringBuilder:append	(Ljava/lang/String;)Ljava/lang/StringBuilder;
    //   2226: aload_0
    //   2227: getfield 76	com/sleepycat/b/a/h:A	I
    //   2230: invokevirtual 763	java/lang/StringBuilder:append	(I)Ljava/lang/StringBuilder;
    //   2233: invokevirtual 672	java/lang/StringBuilder:toString	()Ljava/lang/String;
    //   2236: astore 4
    //   2238: aload_0
    //   2239: getfield 765	com/sleepycat/b/a/h:q	Lcom/sleepycat/b/c/ad;
    //   2242: aload 4
    //   2244: invokestatic 770	com/sleepycat/b/g/aw:a	(Lcom/sleepycat/b/c/ad;Ljava/lang/String;)V
    //   2247: aload_0
    //   2248: getfield 651	com/sleepycat/b/a/h:r	Ljava/util/logging/Logger;
    //   2251: getstatic 657	java/util/logging/Level:INFO	Ljava/util/logging/Level;
    //   2254: invokevirtual 864	java/util/logging/Logger:isLoggable	(Ljava/util/logging/Level;)Z
    //   2257: ifeq +185 -> 2442
    //   2260: aload_3
    //   2261: ifnull +214 -> 2475
    //   2264: aload_3
    //   2265: invokevirtual 866	com/sleepycat/b/a/o:h	()I
    //   2268: istore 11
    //   2270: aload_3
    //   2271: fload_1
    //   2272: invokevirtual 869	com/sleepycat/b/a/o:a	(F)I
    //   2275: i2l
    //   2276: aload_3
    //   2277: getfield 870	com/sleepycat/b/a/o:b	I
    //   2280: i2l
    //   2281: invokestatic 872	com/sleepycat/b/a/o:a	(JJ)I
    //   2284: istore 10
    //   2286: aload 5
    //   2288: invokevirtual 866	com/sleepycat/b/a/o:h	()I
    //   2291: istore 12
    //   2293: new 659	java/lang/StringBuilder
    //   2296: dup
    //   2297: invokespecial 873	java/lang/StringBuilder:<init>	()V
    //   2300: aload 4
    //   2302: invokevirtual 741	java/lang/StringBuilder:append	(Ljava/lang/String;)Ljava/lang/StringBuilder;
    //   2305: ldc_w 875
    //   2308: invokevirtual 741	java/lang/StringBuilder:append	(Ljava/lang/String;)Ljava/lang/StringBuilder;
    //   2311: aload_0
    //   2312: getfield 86	com/sleepycat/b/a/h:b	Lcom/sleepycat/b/a/c;
    //   2315: getfield 711	com/sleepycat/b/a/c:ac	Lcom/sleepycat/b/a/aa;
    //   2318: invokevirtual 878	com/sleepycat/b/a/aa:a	()Lcom/sleepycat/b/a/d;
    //   2321: invokevirtual 668	java/lang/StringBuilder:append	(Ljava/lang/Object;)Ljava/lang/StringBuilder;
    //   2324: ldc_w 880
    //   2327: invokevirtual 741	java/lang/StringBuilder:append	(Ljava/lang/String;)Ljava/lang/StringBuilder;
    //   2330: aload 6
    //   2332: invokevirtual 668	java/lang/StringBuilder:append	(Ljava/lang/Object;)Ljava/lang/StringBuilder;
    //   2335: ldc_w 882
    //   2338: invokevirtual 741	java/lang/StringBuilder:append	(Ljava/lang/String;)Ljava/lang/StringBuilder;
    //   2341: aload_3
    //   2342: invokevirtual 668	java/lang/StringBuilder:append	(Ljava/lang/Object;)Ljava/lang/StringBuilder;
    //   2345: ldc_w 884
    //   2348: invokevirtual 741	java/lang/StringBuilder:append	(Ljava/lang/String;)Ljava/lang/StringBuilder;
    //   2351: aload 5
    //   2353: invokevirtual 668	java/lang/StringBuilder:append	(Ljava/lang/Object;)Ljava/lang/StringBuilder;
    //   2356: ldc_w 886
    //   2359: invokevirtual 741	java/lang/StringBuilder:append	(Ljava/lang/String;)Ljava/lang/StringBuilder;
    //   2362: fload_1
    //   2363: invokevirtual 889	java/lang/StringBuilder:append	(F)Ljava/lang/StringBuilder;
    //   2366: ldc_w 891
    //   2369: invokevirtual 741	java/lang/StringBuilder:append	(Ljava/lang/String;)Ljava/lang/StringBuilder;
    //   2372: aload 7
    //   2374: getfield 715	com/sleepycat/b/a/aa:a	F
    //   2377: invokevirtual 889	java/lang/StringBuilder:append	(F)Ljava/lang/StringBuilder;
    //   2380: ldc_w 893
    //   2383: invokevirtual 741	java/lang/StringBuilder:append	(Ljava/lang/String;)Ljava/lang/StringBuilder;
    //   2386: iload 11
    //   2388: invokevirtual 763	java/lang/StringBuilder:append	(I)Ljava/lang/StringBuilder;
    //   2391: ldc_w 895
    //   2394: invokevirtual 741	java/lang/StringBuilder:append	(Ljava/lang/String;)Ljava/lang/StringBuilder;
    //   2397: iload 10
    //   2399: invokevirtual 763	java/lang/StringBuilder:append	(I)Ljava/lang/StringBuilder;
    //   2402: ldc_w 897
    //   2405: invokevirtual 741	java/lang/StringBuilder:append	(Ljava/lang/String;)Ljava/lang/StringBuilder;
    //   2408: iload 12
    //   2410: invokevirtual 763	java/lang/StringBuilder:append	(I)Ljava/lang/StringBuilder;
    //   2413: ldc_w 899
    //   2416: invokevirtual 741	java/lang/StringBuilder:append	(Ljava/lang/String;)Ljava/lang/StringBuilder;
    //   2419: iconst_0
    //   2420: invokevirtual 750	java/lang/StringBuilder:append	(Z)Ljava/lang/StringBuilder;
    //   2423: invokevirtual 672	java/lang/StringBuilder:toString	()Ljava/lang/String;
    //   2426: astore_3
    //   2427: aload_0
    //   2428: getfield 651	com/sleepycat/b/a/h:r	Ljava/util/logging/Logger;
    //   2431: aload_0
    //   2432: getfield 84	com/sleepycat/b/a/h:a	Lcom/sleepycat/b/c/ad;
    //   2435: getstatic 657	java/util/logging/Level:INFO	Ljava/util/logging/Level;
    //   2438: aload_3
    //   2439: invokestatic 677	com/sleepycat/b/p/w:a	(Ljava/util/logging/Logger;Lcom/sleepycat/b/c/ad;Ljava/util/logging/Level;Ljava/lang/String;)V
    //   2442: aload_2
    //   2443: athrow
    //   2444: astore_2
    //   2445: iconst_0
    //   2446: istore 20
    //   2448: iload 20
    //   2450: istore 19
    //   2452: aload_0
    //   2453: getfield 84	com/sleepycat/b/a/h:a	Lcom/sleepycat/b/c/ad;
    //   2456: ldc_w 915
    //   2459: ldc_w 917
    //   2462: ldc_w 919
    //   2465: aload_2
    //   2466: invokestatic 922	com/sleepycat/b/p/w:a	(Lcom/sleepycat/b/c/ad;Ljava/lang/String;Ljava/lang/String;Ljava/lang/String;Ljava/lang/Throwable;)V
    //   2469: iload 20
    //   2471: istore 19
    //   2473: aload_2
    //   2474: athrow
    //   2475: iconst_m1
    //   2476: istore 11
    //   2478: iconst_m1
    //   2479: istore 10
    //   2481: goto -195 -> 2286
    //   2484: iconst_m1
    //   2485: istore 12
    //   2487: iconst_m1
    //   2488: istore 11
    //   2490: goto -770 -> 1720
    //   2493: iconst_m1
    //   2494: istore 12
    //   2496: iconst_m1
    //   2497: istore 11
    //   2499: goto -1323 -> 1176
    //   2502: astore_2
    //   2503: iconst_0
    //   2504: istore 20
    //   2506: iconst_0
    //   2507: istore 19
    //   2509: goto -570 -> 1939
    //   2512: astore_2
    //   2513: iload 19
    //   2515: istore 20
    //   2517: iconst_1
    //   2518: istore 19
    //   2520: goto -581 -> 1939
    //   2523: astore_2
    //   2524: iload 23
    //   2526: istore 20
    //   2528: goto -80 -> 2448
    //   2531: astore_2
    //   2532: iload 22
    //   2534: istore 20
    //   2536: goto -650 -> 1886
    //   2539: astore_2
    //   2540: goto -1177 -> 1363
    //   2543: astore_2
    //   2544: iconst_1
    //   2545: istore 19
    //   2547: goto -1184 -> 1363
    //   2550: iconst_0
    //   2551: istore 19
    //   2553: goto -1720 -> 833
    //   2556: iconst_0
    //   2557: istore 20
    //   2559: iconst_0
    //   2560: istore 19
    //   2562: goto -1729 -> 833
    //   2565: iconst_0
    //   2566: istore 21
    //   2568: goto -2353 -> 215
    //   2571: goto -2552 -> 19
    //   2574: iconst_1
    //   2575: istore 19
    //   2577: goto -2414 -> 163
    // Local variable table:
    //   start	length	slot	name	signature
    //   0	2580	0	this	h
    //   278	2085	1	f1	float
    //   48	4	2	localObject1	Object
    //   60	1284	2	localObject2	Object
    //   1362	1	2	localFileNotFoundException1	java.io.FileNotFoundException
    //   1367	505	2	localObject3	Object
    //   1882	41	2	localIOException1	java.io.IOException
    //   1927	516	2	localObject4	Object
    //   2444	30	2	localRuntimeException1	RuntimeException
    //   2502	1	2	localObject5	Object
    //   2512	1	2	localObject6	Object
    //   2523	1	2	localRuntimeException2	RuntimeException
    //   2531	1	2	localIOException2	java.io.IOException
    //   2539	1	2	localFileNotFoundException2	java.io.FileNotFoundException
    //   2543	1	2	localFileNotFoundException3	java.io.FileNotFoundException
    //   245	2194	3	localObject7	Object
    //   184	2117	4	localObject8	Object
    //   253	2099	5	localo	o
    //   262	2069	6	localq	q
    //   271	2102	7	localaa	aa
    //   418	973	8	localao	ao
    //   427	87	9	localObject9	Object
    //   17	2463	10	m	int
    //   1135	1363	11	n	int
    //   1158	1337	12	i1	int
    //   67	10	13	i2	int
    //   1181	661	14	i3	int
    //   372	1613	15	l1	long
    //   409	1565	17	l2	long
    //   9	2567	19	bool1	boolean
    //   530	2028	20	bool2	boolean
    //   213	2354	21	bool3	boolean
    //   783	1750	22	bool4	boolean
    //   789	1736	23	bool5	boolean
    //   823	3	24	bool6	boolean
    // Exception table:
    //   from	to	target	type
    //   2	11	48	finally
    //   24	48	48	finally
    //   53	69	48	finally
    //   79	113	48	finally
    //   116	160	48	finally
    //   163	193	48	finally
    //   198	212	48	finally
    //   220	246	48	finally
    //   246	364	48	finally
    //   367	384	48	finally
    //   389	399	48	finally
    //   399	420	48	finally
    //   843	852	48	finally
    //   852	1133	48	finally
    //   1137	1150	48	finally
    //   1154	1176	48	finally
    //   1176	1332	48	finally
    //   1336	1344	48	finally
    //   1400	1694	48	finally
    //   1698	1720	48	finally
    //   1720	1875	48	finally
    //   1954	1963	48	finally
    //   1963	2260	48	finally
    //   2264	2286	48	finally
    //   2286	2442	48	finally
    //   2442	2444	48	finally
    //   420	532	1362	java/io/FileNotFoundException
    //   420	532	1882	java/io/IOException
    //   543	782	1882	java/io/IOException
    //   798	825	1927	finally
    //   1890	1907	1927	finally
    //   1911	1927	1927	finally
    //   2452	2469	1927	finally
    //   2473	2475	1927	finally
    //   420	532	2444	java/lang/RuntimeException
    //   543	782	2444	java/lang/RuntimeException
    //   420	532	2502	finally
    //   543	782	2502	finally
    //   1363	1395	2512	finally
    //   798	825	2523	java/lang/RuntimeException
    //   798	825	2531	java/io/IOException
    //   543	782	2539	java/io/FileNotFoundException
    //   798	825	2543	java/io/FileNotFoundException
  }
  
  protected final long a()
  {
    return this.b.H;
  }
  
  public final void b()
  {
    c();
  }
}


/* Location:              E:\apk\xueqiu2\classes-dex2jar.jar!\com\sleepycat\b\a\h.class
 * Java compiler version: 6 (50.0)
 * JD-Core Version:       0.7.1
 */