package com.sleepycat.b.i.e;

import com.sleepycat.b.i.b.ai;
import com.sleepycat.b.i.b.k;
import com.sleepycat.b.i.c.b.aa;
import com.sleepycat.b.p.w;
import java.util.logging.Logger;

public final class l
  implements k
{
  private ai a = null;
  private final aa b;
  private final Logger c;
  
  public l(aa paramaa)
  {
    this.b = paramaa;
    this.c = w.a(getClass());
  }
  
  /* Error */
  public final void a(com.sleepycat.b.i.b.s params, ai paramai)
  {
    // Byte code:
    //   0: aload_0
    //   1: getfield 21	com/sleepycat/b/i/e/l:b	Lcom/sleepycat/b/i/c/b/aa;
    //   4: getfield 40	com/sleepycat/b/i/c/b/aa:l	Lcom/sleepycat/b/i/c/b/b;
    //   7: aload_1
    //   8: invokevirtual 45	com/sleepycat/b/i/c/b/b:b	(Lcom/sleepycat/b/i/b/s;)V
    //   11: aload_2
    //   12: aload_0
    //   13: getfield 19	com/sleepycat/b/i/e/l:a	Lcom/sleepycat/b/i/b/ai;
    //   16: invokevirtual 49	java/lang/Object:equals	(Ljava/lang/Object;)Z
    //   19: ifeq +48 -> 67
    //   22: aload_0
    //   23: getfield 32	com/sleepycat/b/i/e/l:c	Ljava/util/logging/Logger;
    //   26: aload_0
    //   27: getfield 21	com/sleepycat/b/i/e/l:b	Lcom/sleepycat/b/i/c/b/aa;
    //   30: getfield 53	com/sleepycat/b/i/c/b/aa:i	Lcom/sleepycat/b/i/c/aj;
    //   33: new 55	java/lang/StringBuilder
    //   36: dup
    //   37: ldc 57
    //   39: invokespecial 60	java/lang/StringBuilder:<init>	(Ljava/lang/String;)V
    //   42: aload_1
    //   43: invokevirtual 64	java/lang/StringBuilder:append	(Ljava/lang/Object;)Ljava/lang/StringBuilder;
    //   46: ldc 66
    //   48: invokevirtual 69	java/lang/StringBuilder:append	(Ljava/lang/String;)Ljava/lang/StringBuilder;
    //   51: aload_2
    //   52: invokevirtual 64	java/lang/StringBuilder:append	(Ljava/lang/Object;)Ljava/lang/StringBuilder;
    //   55: invokevirtual 73	java/lang/StringBuilder:toString	()Ljava/lang/String;
    //   58: invokestatic 77	com/sleepycat/b/p/w:d	(Ljava/util/logging/Logger;Lcom/sleepycat/b/c/ad;Ljava/lang/String;)V
    //   61: aload_0
    //   62: aload_2
    //   63: putfield 19	com/sleepycat/b/i/e/l:a	Lcom/sleepycat/b/i/b/ai;
    //   66: return
    //   67: aload_2
    //   68: checkcast 79	com/sleepycat/b/i/b/l
    //   71: astore_3
    //   72: aload_0
    //   73: getfield 32	com/sleepycat/b/i/e/l:c	Ljava/util/logging/Logger;
    //   76: aload_0
    //   77: getfield 21	com/sleepycat/b/i/e/l:b	Lcom/sleepycat/b/i/c/b/aa;
    //   80: getfield 53	com/sleepycat/b/i/c/b/aa:i	Lcom/sleepycat/b/i/c/aj;
    //   83: new 55	java/lang/StringBuilder
    //   86: dup
    //   87: ldc 81
    //   89: invokespecial 60	java/lang/StringBuilder:<init>	(Ljava/lang/String;)V
    //   92: aload_1
    //   93: invokevirtual 64	java/lang/StringBuilder:append	(Ljava/lang/Object;)Ljava/lang/StringBuilder;
    //   96: ldc 66
    //   98: invokevirtual 69	java/lang/StringBuilder:append	(Ljava/lang/String;)Ljava/lang/StringBuilder;
    //   101: aload_2
    //   102: invokevirtual 64	java/lang/StringBuilder:append	(Ljava/lang/Object;)Ljava/lang/StringBuilder;
    //   105: invokevirtual 73	java/lang/StringBuilder:toString	()Ljava/lang/String;
    //   108: invokestatic 77	com/sleepycat/b/p/w:d	(Ljava/util/logging/Logger;Lcom/sleepycat/b/c/ad;Ljava/lang/String;)V
    //   111: aload_0
    //   112: getfield 32	com/sleepycat/b/i/e/l:c	Ljava/util/logging/Logger;
    //   115: aload_0
    //   116: getfield 21	com/sleepycat/b/i/e/l:b	Lcom/sleepycat/b/i/c/b/aa;
    //   119: getfield 53	com/sleepycat/b/i/c/b/aa:i	Lcom/sleepycat/b/i/c/aj;
    //   122: new 55	java/lang/StringBuilder
    //   125: dup
    //   126: ldc 83
    //   128: invokespecial 60	java/lang/StringBuilder:<init>	(Ljava/lang/String;)V
    //   131: aload_3
    //   132: getfield 86	com/sleepycat/b/i/b/l:c	Lcom/sleepycat/b/i/c/b/x;
    //   135: getfield 91	com/sleepycat/b/i/c/b/x:a	Ljava/lang/String;
    //   138: invokevirtual 69	java/lang/StringBuilder:append	(Ljava/lang/String;)Ljava/lang/StringBuilder;
    //   141: invokevirtual 73	java/lang/StringBuilder:toString	()Ljava/lang/String;
    //   144: invokestatic 93	com/sleepycat/b/p/w:c	(Ljava/util/logging/Logger;Lcom/sleepycat/b/c/ad;Ljava/lang/String;)V
    //   147: aload_0
    //   148: getfield 21	com/sleepycat/b/i/e/l:b	Lcom/sleepycat/b/i/c/b/aa;
    //   151: getfield 97	com/sleepycat/b/i/c/b/aa:g	Lcom/sleepycat/b/i/e/n;
    //   154: new 99	java/net/InetSocketAddress
    //   157: dup
    //   158: aload_3
    //   159: getfield 100	com/sleepycat/b/i/b/l:a	Ljava/lang/String;
    //   162: aload_3
    //   163: getfield 103	com/sleepycat/b/i/b/l:b	I
    //   166: invokespecial 106	java/net/InetSocketAddress:<init>	(Ljava/lang/String;I)V
    //   169: aload_3
    //   170: getfield 86	com/sleepycat/b/i/b/l:c	Lcom/sleepycat/b/i/c/b/x;
    //   173: invokevirtual 111	com/sleepycat/b/i/e/n:a	(Ljava/net/InetSocketAddress;Lcom/sleepycat/b/i/c/b/x;)V
    //   176: aload_0
    //   177: getfield 21	com/sleepycat/b/i/e/l:b	Lcom/sleepycat/b/i/c/b/aa;
    //   180: getfield 114	com/sleepycat/b/i/c/b/aa:d	Lcom/sleepycat/b/i/b/d;
    //   183: astore_3
    //   184: aload_3
    //   185: getfield 119	com/sleepycat/b/i/b/d:a	Lcom/sleepycat/b/i/c/t;
    //   188: invokevirtual 124	com/sleepycat/b/i/c/t:g	()Ljava/util/Set;
    //   191: astore 4
    //   193: aload 4
    //   195: invokeinterface 130 1 0
    //   200: ifeq -139 -> 61
    //   203: aload_3
    //   204: getfield 133	com/sleepycat/b/i/b/d:k	Ljava/util/logging/Logger;
    //   207: aload_3
    //   208: getfield 135	com/sleepycat/b/i/b/d:d	Lcom/sleepycat/b/i/c/aj;
    //   211: aload_3
    //   212: getfield 138	com/sleepycat/b/i/b/d:l	Ljava/util/logging/Formatter;
    //   215: getstatic 144	java/util/logging/Level:INFO	Ljava/util/logging/Level;
    //   218: ldc -110
    //   220: iconst_1
    //   221: anewarray 4	java/lang/Object
    //   224: dup
    //   225: iconst_0
    //   226: aload 4
    //   228: invokeinterface 130 1 0
    //   233: invokestatic 152	java/lang/Integer:valueOf	(I)Ljava/lang/Integer;
    //   236: aastore
    //   237: invokestatic 158	java/lang/String:format	(Ljava/lang/String;[Ljava/lang/Object;)Ljava/lang/String;
    //   240: invokestatic 161	com/sleepycat/b/p/w:a	(Ljava/util/logging/Logger;Lcom/sleepycat/b/c/ad;Ljava/util/logging/Formatter;Ljava/util/logging/Level;Ljava/lang/String;)V
    //   243: aload_3
    //   244: getfield 165	com/sleepycat/b/i/b/d:h	Ljava/util/concurrent/ExecutorService;
    //   247: new 167	com/sleepycat/b/i/b/g
    //   250: dup
    //   251: aload_3
    //   252: aload 4
    //   254: new 169	com/sleepycat/b/i/b/v
    //   257: dup
    //   258: aload_1
    //   259: aload_2
    //   260: aconst_null
    //   261: invokespecial 172	com/sleepycat/b/i/b/v:<init>	(Lcom/sleepycat/b/i/b/s;Lcom/sleepycat/b/i/b/ai;Lcom/sleepycat/b/p/ai;)V
    //   264: invokespecial 175	com/sleepycat/b/i/b/g:<init>	(Lcom/sleepycat/b/i/b/d;Ljava/util/Set;Lcom/sleepycat/b/i/b/v;)V
    //   267: invokeinterface 181 2 0
    //   272: goto -211 -> 61
    //   275: astore_1
    //   276: aload_0
    //   277: aload_2
    //   278: putfield 19	com/sleepycat/b/i/e/l:a	Lcom/sleepycat/b/i/b/ai;
    //   281: aload_1
    //   282: athrow
    // Local variable table:
    //   start	length	slot	name	signature
    //   0	283	0	this	l
    //   0	283	1	params	com.sleepycat.b.i.b.s
    //   0	283	2	paramai	ai
    //   71	181	3	localObject	Object
    //   191	62	4	localSet	java.util.Set
    // Exception table:
    //   from	to	target	type
    //   0	61	275	finally
    //   67	272	275	finally
  }
}


/* Location:              E:\apk\xueqiu2\classes-dex2jar.jar!\com\sleepycat\b\i\e\l.class
 * Java compiler version: 6 (50.0)
 * JD-Core Version:       0.7.1
 */