package com.flurry.sdk;

public final class iu
{
  private int a;
  private long b;
  private String c;
  private String d;
  private String e;
  private Throwable f;
  
  public iu(int paramInt, long paramLong, String paramString1, String paramString2, String paramString3, Throwable paramThrowable)
  {
    this.a = paramInt;
    this.b = paramLong;
    this.c = paramString1;
    this.d = paramString2;
    this.e = paramString3;
    this.f = paramThrowable;
  }
  
  public final int a()
  {
    return b().length;
  }
  
  /* Error */
  public final byte[] b()
  {
    // Byte code:
    //   0: new 40	java/io/ByteArrayOutputStream
    //   3: dup
    //   4: invokespecial 41	java/io/ByteArrayOutputStream:<init>	()V
    //   7: astore_3
    //   8: new 43	java/io/DataOutputStream
    //   11: dup
    //   12: aload_3
    //   13: invokespecial 46	java/io/DataOutputStream:<init>	(Ljava/io/OutputStream;)V
    //   16: astore_1
    //   17: aload_1
    //   18: astore_2
    //   19: aload_1
    //   20: aload_0
    //   21: getfield 21	com/flurry/sdk/iu:a	I
    //   24: invokevirtual 50	java/io/DataOutputStream:writeShort	(I)V
    //   27: aload_1
    //   28: astore_2
    //   29: aload_1
    //   30: aload_0
    //   31: getfield 23	com/flurry/sdk/iu:b	J
    //   34: invokevirtual 54	java/io/DataOutputStream:writeLong	(J)V
    //   37: aload_1
    //   38: astore_2
    //   39: aload_1
    //   40: aload_0
    //   41: getfield 25	com/flurry/sdk/iu:c	Ljava/lang/String;
    //   44: invokevirtual 58	java/io/DataOutputStream:writeUTF	(Ljava/lang/String;)V
    //   47: aload_1
    //   48: astore_2
    //   49: aload_1
    //   50: aload_0
    //   51: getfield 27	com/flurry/sdk/iu:d	Ljava/lang/String;
    //   54: invokevirtual 58	java/io/DataOutputStream:writeUTF	(Ljava/lang/String;)V
    //   57: aload_1
    //   58: astore_2
    //   59: aload_1
    //   60: aload_0
    //   61: getfield 29	com/flurry/sdk/iu:e	Ljava/lang/String;
    //   64: invokevirtual 58	java/io/DataOutputStream:writeUTF	(Ljava/lang/String;)V
    //   67: aload_1
    //   68: astore_2
    //   69: aload_0
    //   70: getfield 31	com/flurry/sdk/iu:f	Ljava/lang/Throwable;
    //   73: ifnull +275 -> 348
    //   76: aload_1
    //   77: astore_2
    //   78: ldc 60
    //   80: aload_0
    //   81: getfield 25	com/flurry/sdk/iu:c	Ljava/lang/String;
    //   84: invokevirtual 66	java/lang/String:equals	(Ljava/lang/Object;)Z
    //   87: ifeq +99 -> 186
    //   90: aload_1
    //   91: astore_2
    //   92: aload_1
    //   93: iconst_3
    //   94: invokevirtual 69	java/io/DataOutputStream:writeByte	(I)V
    //   97: aload_1
    //   98: astore_2
    //   99: aload_1
    //   100: iconst_2
    //   101: invokevirtual 69	java/io/DataOutputStream:writeByte	(I)V
    //   104: aload_1
    //   105: astore_2
    //   106: new 71	java/lang/StringBuilder
    //   109: dup
    //   110: ldc 73
    //   112: invokespecial 75	java/lang/StringBuilder:<init>	(Ljava/lang/String;)V
    //   115: astore 4
    //   117: aload_1
    //   118: astore_2
    //   119: ldc 77
    //   121: invokestatic 83	java/lang/System:getProperty	(Ljava/lang/String;)Ljava/lang/String;
    //   124: astore 5
    //   126: aload_1
    //   127: astore_2
    //   128: aload_0
    //   129: getfield 31	com/flurry/sdk/iu:f	Ljava/lang/Throwable;
    //   132: invokevirtual 89	java/lang/Throwable:getStackTrace	()[Ljava/lang/StackTraceElement;
    //   135: astore 6
    //   137: aload_1
    //   138: astore_2
    //   139: aload 6
    //   141: arraylength
    //   142: istore 8
    //   144: iconst_0
    //   145: istore 7
    //   147: iload 7
    //   149: iload 8
    //   151: if_icmpge +54 -> 205
    //   154: aload_1
    //   155: astore_2
    //   156: aload 4
    //   158: aload 6
    //   160: iload 7
    //   162: aaload
    //   163: invokevirtual 93	java/lang/StringBuilder:append	(Ljava/lang/Object;)Ljava/lang/StringBuilder;
    //   166: pop
    //   167: aload_1
    //   168: astore_2
    //   169: aload 4
    //   171: aload 5
    //   173: invokevirtual 96	java/lang/StringBuilder:append	(Ljava/lang/String;)Ljava/lang/StringBuilder;
    //   176: pop
    //   177: iload 7
    //   179: iconst_1
    //   180: iadd
    //   181: istore 7
    //   183: goto -36 -> 147
    //   186: aload_1
    //   187: astore_2
    //   188: aload_1
    //   189: iconst_2
    //   190: invokevirtual 69	java/io/DataOutputStream:writeByte	(I)V
    //   193: goto -96 -> 97
    //   196: astore_2
    //   197: aload_1
    //   198: invokestatic 101	com/flurry/sdk/lt:a	(Ljava/io/Closeable;)V
    //   201: iconst_0
    //   202: newarray <illegal type>
    //   204: areturn
    //   205: aload_1
    //   206: astore_2
    //   207: aload_0
    //   208: getfield 31	com/flurry/sdk/iu:f	Ljava/lang/Throwable;
    //   211: invokevirtual 105	java/lang/Throwable:getCause	()Ljava/lang/Throwable;
    //   214: ifnull +86 -> 300
    //   217: aload_1
    //   218: astore_2
    //   219: aload 4
    //   221: aload 5
    //   223: invokevirtual 96	java/lang/StringBuilder:append	(Ljava/lang/String;)Ljava/lang/StringBuilder;
    //   226: pop
    //   227: aload_1
    //   228: astore_2
    //   229: aload 4
    //   231: ldc 107
    //   233: invokevirtual 96	java/lang/StringBuilder:append	(Ljava/lang/String;)Ljava/lang/StringBuilder;
    //   236: pop
    //   237: aload_1
    //   238: astore_2
    //   239: aload_0
    //   240: getfield 31	com/flurry/sdk/iu:f	Ljava/lang/Throwable;
    //   243: invokevirtual 105	java/lang/Throwable:getCause	()Ljava/lang/Throwable;
    //   246: invokevirtual 89	java/lang/Throwable:getStackTrace	()[Ljava/lang/StackTraceElement;
    //   249: astore 6
    //   251: aload_1
    //   252: astore_2
    //   253: aload 6
    //   255: arraylength
    //   256: istore 8
    //   258: iconst_0
    //   259: istore 7
    //   261: iload 7
    //   263: iload 8
    //   265: if_icmpge +35 -> 300
    //   268: aload_1
    //   269: astore_2
    //   270: aload 4
    //   272: aload 6
    //   274: iload 7
    //   276: aaload
    //   277: invokevirtual 93	java/lang/StringBuilder:append	(Ljava/lang/Object;)Ljava/lang/StringBuilder;
    //   280: pop
    //   281: aload_1
    //   282: astore_2
    //   283: aload 4
    //   285: aload 5
    //   287: invokevirtual 96	java/lang/StringBuilder:append	(Ljava/lang/String;)Ljava/lang/StringBuilder;
    //   290: pop
    //   291: iload 7
    //   293: iconst_1
    //   294: iadd
    //   295: istore 7
    //   297: goto -36 -> 261
    //   300: aload_1
    //   301: astore_2
    //   302: aload 4
    //   304: invokevirtual 111	java/lang/StringBuilder:toString	()Ljava/lang/String;
    //   307: invokevirtual 114	java/lang/String:getBytes	()[B
    //   310: astore 4
    //   312: aload_1
    //   313: astore_2
    //   314: aload_1
    //   315: aload 4
    //   317: arraylength
    //   318: invokevirtual 117	java/io/DataOutputStream:writeInt	(I)V
    //   321: aload_1
    //   322: astore_2
    //   323: aload_1
    //   324: aload 4
    //   326: invokevirtual 121	java/io/DataOutputStream:write	([B)V
    //   329: aload_1
    //   330: astore_2
    //   331: aload_1
    //   332: invokevirtual 124	java/io/DataOutputStream:flush	()V
    //   335: aload_1
    //   336: astore_2
    //   337: aload_3
    //   338: invokevirtual 127	java/io/ByteArrayOutputStream:toByteArray	()[B
    //   341: astore_3
    //   342: aload_1
    //   343: invokestatic 101	com/flurry/sdk/lt:a	(Ljava/io/Closeable;)V
    //   346: aload_3
    //   347: areturn
    //   348: aload_1
    //   349: astore_2
    //   350: aload_1
    //   351: iconst_1
    //   352: invokevirtual 69	java/io/DataOutputStream:writeByte	(I)V
    //   355: aload_1
    //   356: astore_2
    //   357: aload_1
    //   358: iconst_0
    //   359: invokevirtual 69	java/io/DataOutputStream:writeByte	(I)V
    //   362: goto -33 -> 329
    //   365: astore_1
    //   366: aload_2
    //   367: invokestatic 101	com/flurry/sdk/lt:a	(Ljava/io/Closeable;)V
    //   370: aload_1
    //   371: athrow
    //   372: astore_1
    //   373: aconst_null
    //   374: astore_2
    //   375: goto -9 -> 366
    //   378: astore_1
    //   379: aconst_null
    //   380: astore_1
    //   381: goto -184 -> 197
    // Local variable table:
    //   start	length	slot	name	signature
    //   0	384	0	this	iu
    //   16	342	1	localDataOutputStream1	java.io.DataOutputStream
    //   365	6	1	localObject1	Object
    //   372	1	1	localObject2	Object
    //   378	1	1	localIOException1	java.io.IOException
    //   380	1	1	localObject3	Object
    //   18	170	2	localDataOutputStream2	java.io.DataOutputStream
    //   196	1	2	localIOException2	java.io.IOException
    //   206	169	2	localDataOutputStream3	java.io.DataOutputStream
    //   7	340	3	localObject4	Object
    //   115	210	4	localObject5	Object
    //   124	162	5	str	String
    //   135	138	6	arrayOfStackTraceElement	StackTraceElement[]
    //   145	151	7	i	int
    //   142	124	8	j	int
    // Exception table:
    //   from	to	target	type
    //   19	27	196	java/io/IOException
    //   29	37	196	java/io/IOException
    //   39	47	196	java/io/IOException
    //   49	57	196	java/io/IOException
    //   59	67	196	java/io/IOException
    //   69	76	196	java/io/IOException
    //   78	90	196	java/io/IOException
    //   92	97	196	java/io/IOException
    //   99	104	196	java/io/IOException
    //   106	117	196	java/io/IOException
    //   119	126	196	java/io/IOException
    //   128	137	196	java/io/IOException
    //   139	144	196	java/io/IOException
    //   156	167	196	java/io/IOException
    //   169	177	196	java/io/IOException
    //   188	193	196	java/io/IOException
    //   207	217	196	java/io/IOException
    //   219	227	196	java/io/IOException
    //   229	237	196	java/io/IOException
    //   239	251	196	java/io/IOException
    //   253	258	196	java/io/IOException
    //   270	281	196	java/io/IOException
    //   283	291	196	java/io/IOException
    //   302	312	196	java/io/IOException
    //   314	321	196	java/io/IOException
    //   323	329	196	java/io/IOException
    //   331	335	196	java/io/IOException
    //   337	342	196	java/io/IOException
    //   350	355	196	java/io/IOException
    //   357	362	196	java/io/IOException
    //   19	27	365	finally
    //   29	37	365	finally
    //   39	47	365	finally
    //   49	57	365	finally
    //   59	67	365	finally
    //   69	76	365	finally
    //   78	90	365	finally
    //   92	97	365	finally
    //   99	104	365	finally
    //   106	117	365	finally
    //   119	126	365	finally
    //   128	137	365	finally
    //   139	144	365	finally
    //   156	167	365	finally
    //   169	177	365	finally
    //   188	193	365	finally
    //   207	217	365	finally
    //   219	227	365	finally
    //   229	237	365	finally
    //   239	251	365	finally
    //   253	258	365	finally
    //   270	281	365	finally
    //   283	291	365	finally
    //   302	312	365	finally
    //   314	321	365	finally
    //   323	329	365	finally
    //   331	335	365	finally
    //   337	342	365	finally
    //   350	355	365	finally
    //   357	362	365	finally
    //   0	17	372	finally
    //   0	17	378	java/io/IOException
  }
  
  public final String c()
  {
    return this.c;
  }
}


/* Location:              E:\apk\xueqiu2\classes-dex2jar.jar!\com\flurry\sdk\iu.class
 * Java compiler version: 6 (50.0)
 * JD-Core Version:       0.7.1
 */