package com.flurry.sdk;

public class iz
{
  private static final String b = iz.class.getSimpleName();
  byte[] a;
  
  private iz() {}
  
  /* Error */
  public iz(ja paramja)
  {
    // Byte code:
    //   0: aload_0
    //   1: invokespecial 24	java/lang/Object:<init>	()V
    //   4: aconst_null
    //   5: astore_3
    //   6: new 31	java/io/ByteArrayOutputStream
    //   9: dup
    //   10: invokespecial 32	java/io/ByteArrayOutputStream:<init>	()V
    //   13: astore 4
    //   15: new 34	java/io/DataOutputStream
    //   18: dup
    //   19: aload 4
    //   21: invokespecial 37	java/io/DataOutputStream:<init>	(Ljava/io/OutputStream;)V
    //   24: astore_2
    //   25: aload_2
    //   26: bipush 7
    //   28: invokevirtual 41	java/io/DataOutputStream:writeShort	(I)V
    //   31: aload_2
    //   32: aload_1
    //   33: invokevirtual 45	com/flurry/sdk/ja:a	()Ljava/lang/String;
    //   36: invokevirtual 49	java/io/DataOutputStream:writeUTF	(Ljava/lang/String;)V
    //   39: aload_2
    //   40: aload_1
    //   41: invokevirtual 52	com/flurry/sdk/ja:b	()J
    //   44: invokevirtual 56	java/io/DataOutputStream:writeLong	(J)V
    //   47: aload_2
    //   48: aload_1
    //   49: invokevirtual 59	com/flurry/sdk/ja:c	()J
    //   52: invokevirtual 56	java/io/DataOutputStream:writeLong	(J)V
    //   55: aload_2
    //   56: aload_1
    //   57: invokevirtual 62	com/flurry/sdk/ja:d	()J
    //   60: invokevirtual 56	java/io/DataOutputStream:writeLong	(J)V
    //   63: aload_2
    //   64: iconst_1
    //   65: invokevirtual 66	java/io/DataOutputStream:writeBoolean	(Z)V
    //   68: aload_2
    //   69: iconst_m1
    //   70: invokevirtual 69	java/io/DataOutputStream:writeByte	(I)V
    //   73: aload_1
    //   74: invokevirtual 72	com/flurry/sdk/ja:f	()Ljava/lang/String;
    //   77: invokestatic 78	android/text/TextUtils:isEmpty	(Ljava/lang/CharSequence;)Z
    //   80: ifne +308 -> 388
    //   83: aload_2
    //   84: iconst_1
    //   85: invokevirtual 66	java/io/DataOutputStream:writeBoolean	(Z)V
    //   88: aload_2
    //   89: aload_1
    //   90: invokevirtual 72	com/flurry/sdk/ja:f	()Ljava/lang/String;
    //   93: invokevirtual 49	java/io/DataOutputStream:writeUTF	(Ljava/lang/String;)V
    //   96: aload_1
    //   97: invokevirtual 81	com/flurry/sdk/ja:g	()Ljava/lang/String;
    //   100: invokestatic 78	android/text/TextUtils:isEmpty	(Ljava/lang/CharSequence;)Z
    //   103: ifne +322 -> 425
    //   106: aload_2
    //   107: iconst_1
    //   108: invokevirtual 66	java/io/DataOutputStream:writeBoolean	(Z)V
    //   111: aload_2
    //   112: aload_1
    //   113: invokevirtual 81	com/flurry/sdk/ja:g	()Ljava/lang/String;
    //   116: invokevirtual 49	java/io/DataOutputStream:writeUTF	(Ljava/lang/String;)V
    //   119: aload_1
    //   120: invokevirtual 85	com/flurry/sdk/ja:h	()Ljava/util/Map;
    //   123: astore_3
    //   124: aload_3
    //   125: ifnonnull +308 -> 433
    //   128: aload_2
    //   129: iconst_0
    //   130: invokevirtual 41	java/io/DataOutputStream:writeShort	(I)V
    //   133: aload_1
    //   134: invokevirtual 88	com/flurry/sdk/ja:e	()Ljava/util/Map;
    //   137: astore_3
    //   138: aload_3
    //   139: ifnonnull +367 -> 506
    //   142: aload_2
    //   143: iconst_0
    //   144: invokevirtual 41	java/io/DataOutputStream:writeShort	(I)V
    //   147: aload_2
    //   148: aload_1
    //   149: invokevirtual 91	com/flurry/sdk/ja:i	()Ljava/lang/String;
    //   152: invokevirtual 49	java/io/DataOutputStream:writeUTF	(Ljava/lang/String;)V
    //   155: aload_2
    //   156: aload_1
    //   157: invokevirtual 94	com/flurry/sdk/ja:j	()Ljava/lang/String;
    //   160: invokevirtual 49	java/io/DataOutputStream:writeUTF	(Ljava/lang/String;)V
    //   163: aload_2
    //   164: aload_1
    //   165: invokevirtual 98	com/flurry/sdk/ja:k	()I
    //   168: invokevirtual 69	java/io/DataOutputStream:writeByte	(I)V
    //   171: aload_2
    //   172: aload_1
    //   173: invokevirtual 101	com/flurry/sdk/ja:l	()I
    //   176: invokevirtual 69	java/io/DataOutputStream:writeByte	(I)V
    //   179: aload_2
    //   180: aload_1
    //   181: invokevirtual 104	com/flurry/sdk/ja:m	()Ljava/lang/String;
    //   184: invokevirtual 49	java/io/DataOutputStream:writeUTF	(Ljava/lang/String;)V
    //   187: aload_1
    //   188: invokevirtual 108	com/flurry/sdk/ja:n	()Landroid/location/Location;
    //   191: ifnonnull +393 -> 584
    //   194: aload_2
    //   195: iconst_0
    //   196: invokevirtual 66	java/io/DataOutputStream:writeBoolean	(Z)V
    //   199: aload_2
    //   200: aload_1
    //   201: invokevirtual 111	com/flurry/sdk/ja:o	()I
    //   204: invokevirtual 114	java/io/DataOutputStream:writeInt	(I)V
    //   207: aload_2
    //   208: iconst_m1
    //   209: invokevirtual 69	java/io/DataOutputStream:writeByte	(I)V
    //   212: aload_2
    //   213: iconst_m1
    //   214: invokevirtual 69	java/io/DataOutputStream:writeByte	(I)V
    //   217: aload_2
    //   218: aload_1
    //   219: invokevirtual 118	com/flurry/sdk/ja:p	()B
    //   222: invokevirtual 69	java/io/DataOutputStream:writeByte	(I)V
    //   225: aload_1
    //   226: invokevirtual 122	com/flurry/sdk/ja:q	()Ljava/lang/Long;
    //   229: ifnonnull +404 -> 633
    //   232: aload_2
    //   233: iconst_0
    //   234: invokevirtual 66	java/io/DataOutputStream:writeBoolean	(Z)V
    //   237: aload_1
    //   238: invokevirtual 125	com/flurry/sdk/ja:r	()Ljava/util/Map;
    //   241: astore_3
    //   242: aload_3
    //   243: ifnonnull +409 -> 652
    //   246: aload_2
    //   247: iconst_0
    //   248: invokevirtual 41	java/io/DataOutputStream:writeShort	(I)V
    //   251: aload_1
    //   252: invokevirtual 129	com/flurry/sdk/ja:s	()Ljava/util/List;
    //   255: astore_3
    //   256: aload_3
    //   257: ifnonnull +471 -> 728
    //   260: aload_2
    //   261: iconst_0
    //   262: invokevirtual 41	java/io/DataOutputStream:writeShort	(I)V
    //   265: aload_2
    //   266: aload_1
    //   267: invokevirtual 133	com/flurry/sdk/ja:t	()Z
    //   270: invokevirtual 66	java/io/DataOutputStream:writeBoolean	(Z)V
    //   273: aload_1
    //   274: invokevirtual 136	com/flurry/sdk/ja:v	()Ljava/util/List;
    //   277: astore_3
    //   278: aload_3
    //   279: ifnull +543 -> 822
    //   282: iconst_0
    //   283: istore 7
    //   285: iconst_0
    //   286: istore 6
    //   288: iconst_0
    //   289: istore 8
    //   291: iload 7
    //   293: aload_3
    //   294: invokeinterface 141 1 0
    //   299: if_icmpge +520 -> 819
    //   302: iload 8
    //   304: aload_3
    //   305: iload 7
    //   307: invokeinterface 145 2 0
    //   312: checkcast 147	com/flurry/sdk/iu
    //   315: invokevirtual 149	com/flurry/sdk/iu:a	()I
    //   318: iadd
    //   319: istore 8
    //   321: iload 8
    //   323: ldc -106
    //   325: if_icmple +507 -> 832
    //   328: iconst_5
    //   329: getstatic 20	com/flurry/sdk/iz:b	Ljava/lang/String;
    //   332: ldc -104
    //   334: invokestatic 157	com/flurry/sdk/kg:a	(ILjava/lang/String;Ljava/lang/String;)V
    //   337: aload_2
    //   338: aload_1
    //   339: invokevirtual 160	com/flurry/sdk/ja:u	()I
    //   342: invokevirtual 114	java/io/DataOutputStream:writeInt	(I)V
    //   345: aload_2
    //   346: iload 6
    //   348: invokevirtual 41	java/io/DataOutputStream:writeShort	(I)V
    //   351: iconst_0
    //   352: istore 7
    //   354: iload 7
    //   356: iload 6
    //   358: if_icmpge +415 -> 773
    //   361: aload_2
    //   362: aload_3
    //   363: iload 7
    //   365: invokeinterface 145 2 0
    //   370: checkcast 147	com/flurry/sdk/iu
    //   373: invokevirtual 163	com/flurry/sdk/iu:b	()[B
    //   376: invokevirtual 167	java/io/DataOutputStream:write	([B)V
    //   379: iload 7
    //   381: iconst_1
    //   382: iadd
    //   383: istore 7
    //   385: goto -31 -> 354
    //   388: aload_2
    //   389: iconst_0
    //   390: invokevirtual 66	java/io/DataOutputStream:writeBoolean	(Z)V
    //   393: goto -297 -> 96
    //   396: astore_3
    //   397: aload_2
    //   398: astore_1
    //   399: aload_3
    //   400: astore_2
    //   401: bipush 6
    //   403: getstatic 20	com/flurry/sdk/iz:b	Ljava/lang/String;
    //   406: ldc -87
    //   408: aload_2
    //   409: invokestatic 172	com/flurry/sdk/kg:a	(ILjava/lang/String;Ljava/lang/String;Ljava/lang/Throwable;)V
    //   412: aload_2
    //   413: athrow
    //   414: astore_3
    //   415: aload_1
    //   416: astore_2
    //   417: aload_3
    //   418: astore_1
    //   419: aload_2
    //   420: invokestatic 177	com/flurry/sdk/lt:a	(Ljava/io/Closeable;)V
    //   423: aload_1
    //   424: athrow
    //   425: aload_2
    //   426: iconst_0
    //   427: invokevirtual 66	java/io/DataOutputStream:writeBoolean	(Z)V
    //   430: goto -311 -> 119
    //   433: aload_2
    //   434: aload_3
    //   435: invokeinterface 180 1 0
    //   440: invokevirtual 41	java/io/DataOutputStream:writeShort	(I)V
    //   443: aload_3
    //   444: invokeinterface 184 1 0
    //   449: invokeinterface 190 1 0
    //   454: astore_3
    //   455: aload_3
    //   456: invokeinterface 195 1 0
    //   461: ifeq -328 -> 133
    //   464: aload_3
    //   465: invokeinterface 199 1 0
    //   470: checkcast 201	java/util/Map$Entry
    //   473: astore 5
    //   475: aload_2
    //   476: aload 5
    //   478: invokeinterface 204 1 0
    //   483: checkcast 206	java/lang/String
    //   486: invokevirtual 49	java/io/DataOutputStream:writeUTF	(Ljava/lang/String;)V
    //   489: aload_2
    //   490: aload 5
    //   492: invokeinterface 209 1 0
    //   497: checkcast 206	java/lang/String
    //   500: invokevirtual 49	java/io/DataOutputStream:writeUTF	(Ljava/lang/String;)V
    //   503: goto -48 -> 455
    //   506: aload_2
    //   507: aload_3
    //   508: invokeinterface 180 1 0
    //   513: invokevirtual 41	java/io/DataOutputStream:writeShort	(I)V
    //   516: aload_3
    //   517: invokeinterface 184 1 0
    //   522: invokeinterface 190 1 0
    //   527: astore_3
    //   528: aload_3
    //   529: invokeinterface 195 1 0
    //   534: ifeq -387 -> 147
    //   537: aload_3
    //   538: invokeinterface 199 1 0
    //   543: checkcast 201	java/util/Map$Entry
    //   546: astore 5
    //   548: aload_2
    //   549: aload 5
    //   551: invokeinterface 204 1 0
    //   556: checkcast 206	java/lang/String
    //   559: invokevirtual 49	java/io/DataOutputStream:writeUTF	(Ljava/lang/String;)V
    //   562: aload_2
    //   563: aload 5
    //   565: invokeinterface 209 1 0
    //   570: checkcast 206	java/lang/String
    //   573: invokevirtual 49	java/io/DataOutputStream:writeUTF	(Ljava/lang/String;)V
    //   576: aload_2
    //   577: iconst_0
    //   578: invokevirtual 69	java/io/DataOutputStream:writeByte	(I)V
    //   581: goto -53 -> 528
    //   584: aload_2
    //   585: iconst_1
    //   586: invokevirtual 66	java/io/DataOutputStream:writeBoolean	(Z)V
    //   589: aload_2
    //   590: aload_1
    //   591: invokevirtual 108	com/flurry/sdk/ja:n	()Landroid/location/Location;
    //   594: invokevirtual 215	android/location/Location:getLatitude	()D
    //   597: iconst_3
    //   598: invokestatic 218	com/flurry/sdk/lt:a	(DI)D
    //   601: invokevirtual 222	java/io/DataOutputStream:writeDouble	(D)V
    //   604: aload_2
    //   605: aload_1
    //   606: invokevirtual 108	com/flurry/sdk/ja:n	()Landroid/location/Location;
    //   609: invokevirtual 225	android/location/Location:getLongitude	()D
    //   612: iconst_3
    //   613: invokestatic 218	com/flurry/sdk/lt:a	(DI)D
    //   616: invokevirtual 222	java/io/DataOutputStream:writeDouble	(D)V
    //   619: aload_2
    //   620: aload_1
    //   621: invokevirtual 108	com/flurry/sdk/ja:n	()Landroid/location/Location;
    //   624: invokevirtual 229	android/location/Location:getAccuracy	()F
    //   627: invokevirtual 233	java/io/DataOutputStream:writeFloat	(F)V
    //   630: goto -431 -> 199
    //   633: aload_2
    //   634: iconst_1
    //   635: invokevirtual 66	java/io/DataOutputStream:writeBoolean	(Z)V
    //   638: aload_2
    //   639: aload_1
    //   640: invokevirtual 122	com/flurry/sdk/ja:q	()Ljava/lang/Long;
    //   643: invokevirtual 238	java/lang/Long:longValue	()J
    //   646: invokevirtual 56	java/io/DataOutputStream:writeLong	(J)V
    //   649: goto -412 -> 237
    //   652: aload_2
    //   653: aload_3
    //   654: invokeinterface 180 1 0
    //   659: invokevirtual 41	java/io/DataOutputStream:writeShort	(I)V
    //   662: aload_3
    //   663: invokeinterface 184 1 0
    //   668: invokeinterface 190 1 0
    //   673: astore_3
    //   674: aload_3
    //   675: invokeinterface 195 1 0
    //   680: ifeq -429 -> 251
    //   683: aload_3
    //   684: invokeinterface 199 1 0
    //   689: checkcast 201	java/util/Map$Entry
    //   692: astore 5
    //   694: aload_2
    //   695: aload 5
    //   697: invokeinterface 204 1 0
    //   702: checkcast 206	java/lang/String
    //   705: invokevirtual 49	java/io/DataOutputStream:writeUTF	(Ljava/lang/String;)V
    //   708: aload_2
    //   709: aload 5
    //   711: invokeinterface 209 1 0
    //   716: checkcast 240	com/flurry/sdk/iv
    //   719: getfield 243	com/flurry/sdk/iv:a	I
    //   722: invokevirtual 114	java/io/DataOutputStream:writeInt	(I)V
    //   725: goto -51 -> 674
    //   728: aload_2
    //   729: aload_3
    //   730: invokeinterface 141 1 0
    //   735: invokevirtual 41	java/io/DataOutputStream:writeShort	(I)V
    //   738: aload_3
    //   739: invokeinterface 244 1 0
    //   744: astore_3
    //   745: aload_3
    //   746: invokeinterface 195 1 0
    //   751: ifeq -486 -> 265
    //   754: aload_2
    //   755: aload_3
    //   756: invokeinterface 199 1 0
    //   761: checkcast 246	com/flurry/sdk/iw
    //   764: invokevirtual 248	com/flurry/sdk/iw:e	()[B
    //   767: invokevirtual 167	java/io/DataOutputStream:write	([B)V
    //   770: goto -25 -> 745
    //   773: aload_2
    //   774: iconst_m1
    //   775: invokevirtual 114	java/io/DataOutputStream:writeInt	(I)V
    //   778: aload_2
    //   779: iconst_0
    //   780: invokevirtual 41	java/io/DataOutputStream:writeShort	(I)V
    //   783: aload_2
    //   784: iconst_0
    //   785: invokevirtual 41	java/io/DataOutputStream:writeShort	(I)V
    //   788: aload_2
    //   789: iconst_0
    //   790: invokevirtual 41	java/io/DataOutputStream:writeShort	(I)V
    //   793: aload_0
    //   794: aload 4
    //   796: invokevirtual 251	java/io/ByteArrayOutputStream:toByteArray	()[B
    //   799: putfield 253	com/flurry/sdk/iz:a	[B
    //   802: aload_2
    //   803: invokestatic 177	com/flurry/sdk/lt:a	(Ljava/io/Closeable;)V
    //   806: return
    //   807: astore_1
    //   808: aconst_null
    //   809: astore_2
    //   810: goto -391 -> 419
    //   813: astore_2
    //   814: aload_3
    //   815: astore_1
    //   816: goto -415 -> 401
    //   819: goto -482 -> 337
    //   822: iconst_0
    //   823: istore 6
    //   825: goto -488 -> 337
    //   828: astore_1
    //   829: goto -410 -> 419
    //   832: iload 6
    //   834: iconst_1
    //   835: iadd
    //   836: istore 6
    //   838: iload 7
    //   840: iconst_1
    //   841: iadd
    //   842: istore 7
    //   844: goto -553 -> 291
    // Local variable table:
    //   start	length	slot	name	signature
    //   0	847	0	this	iz
    //   0	847	1	paramja	ja
    //   24	786	2	localObject1	Object
    //   813	1	2	localIOException1	java.io.IOException
    //   5	358	3	localObject2	Object
    //   396	4	3	localIOException2	java.io.IOException
    //   414	30	3	localObject3	Object
    //   454	361	3	localIterator	java.util.Iterator
    //   13	782	4	localByteArrayOutputStream	java.io.ByteArrayOutputStream
    //   473	237	5	localEntry	java.util.Map.Entry
    //   286	551	6	i	int
    //   283	560	7	j	int
    //   289	37	8	k	int
    // Exception table:
    //   from	to	target	type
    //   25	96	396	java/io/IOException
    //   96	119	396	java/io/IOException
    //   119	124	396	java/io/IOException
    //   128	133	396	java/io/IOException
    //   133	138	396	java/io/IOException
    //   142	147	396	java/io/IOException
    //   147	199	396	java/io/IOException
    //   199	237	396	java/io/IOException
    //   237	242	396	java/io/IOException
    //   246	251	396	java/io/IOException
    //   251	256	396	java/io/IOException
    //   260	265	396	java/io/IOException
    //   265	278	396	java/io/IOException
    //   291	321	396	java/io/IOException
    //   328	337	396	java/io/IOException
    //   337	351	396	java/io/IOException
    //   361	379	396	java/io/IOException
    //   388	393	396	java/io/IOException
    //   425	430	396	java/io/IOException
    //   433	455	396	java/io/IOException
    //   455	503	396	java/io/IOException
    //   506	528	396	java/io/IOException
    //   528	581	396	java/io/IOException
    //   584	630	396	java/io/IOException
    //   633	649	396	java/io/IOException
    //   652	674	396	java/io/IOException
    //   674	725	396	java/io/IOException
    //   728	745	396	java/io/IOException
    //   745	770	396	java/io/IOException
    //   773	802	396	java/io/IOException
    //   401	414	414	finally
    //   6	25	807	finally
    //   6	25	813	java/io/IOException
    //   25	96	828	finally
    //   96	119	828	finally
    //   119	124	828	finally
    //   128	133	828	finally
    //   133	138	828	finally
    //   142	147	828	finally
    //   147	199	828	finally
    //   199	237	828	finally
    //   237	242	828	finally
    //   246	251	828	finally
    //   251	256	828	finally
    //   260	265	828	finally
    //   265	278	828	finally
    //   291	321	828	finally
    //   328	337	828	finally
    //   337	351	828	finally
    //   361	379	828	finally
    //   388	393	828	finally
    //   425	430	828	finally
    //   433	455	828	finally
    //   455	503	828	finally
    //   506	528	828	finally
    //   528	581	828	finally
    //   584	630	828	finally
    //   633	649	828	finally
    //   652	674	828	finally
    //   674	725	828	finally
    //   728	745	828	finally
    //   745	770	828	finally
    //   773	802	828	finally
  }
  
  public iz(byte[] paramArrayOfByte)
  {
    this.a = paramArrayOfByte;
  }
  
  public byte[] a()
  {
    return this.a;
  }
}


/* Location:              E:\apk\xueqiu2\classes-dex2jar.jar!\com\flurry\sdk\iz.class
 * Java compiler version: 6 (50.0)
 * JD-Core Version:       0.7.1
 */