package com.sleepycat.b.i.c.b;

import com.sleepycat.b.i.b.j;
import com.sleepycat.b.i.c.ae;
import com.sleepycat.b.i.c.al;
import com.sleepycat.b.i.c.am;
import com.sleepycat.b.i.c.an;
import com.sleepycat.b.i.c.az;
import com.sleepycat.b.k.a.c;
import java.net.InetAddress;
import java.net.InetSocketAddress;
import java.util.Collection;
import java.util.HashSet;
import java.util.Iterator;
import java.util.Set;
import java.util.Timer;
import java.util.UUID;
import java.util.concurrent.BlockingQueue;
import java.util.concurrent.atomic.AtomicBoolean;
import java.util.logging.Logger;

public class aa
  extends com.sleepycat.b.p.aj
{
  public final com.sleepycat.b.i.a.a A;
  public int B = 8;
  private final com.sleepycat.b.i.e.l G;
  private final com.sleepycat.b.i.e.p H;
  private com.sleepycat.b.i.p I = com.sleepycat.b.i.p.b;
  private com.sleepycat.b.i.g.a.f J;
  private com.sleepycat.b.i.c.l K;
  private com.sleepycat.b.i.c.d L;
  private com.sleepycat.b.i.c.g M;
  private s N;
  private Set<com.sleepycat.b.p.ao<Integer>> O;
  public final x a;
  public final InetSocketAddress b;
  public final com.sleepycat.b.i.h.x c;
  public com.sleepycat.b.i.b.d d;
  public final ag e;
  public m f;
  public final com.sleepycat.b.i.e.n g;
  final z h;
  public final com.sleepycat.b.i.c.aj i;
  public final com.sleepycat.b.i.c.p j;
  volatile com.sleepycat.b.i.h.t k = null;
  public final b l = new b();
  public volatile com.sleepycat.b.i.c.t m;
  public final ab n;
  com.sleepycat.b.i.c.a.a o;
  public final q p;
  u q;
  public final o r;
  long s = -1L;
  public w t;
  public com.sleepycat.b.i.a u;
  public final Timer v;
  public final a w;
  public final Logger x;
  public final g y;
  public final f z;
  
  static
  {
    if (!aa.class.desiredAssertionStatus()) {}
    for (boolean bool = true;; bool = false)
    {
      C = bool;
      return;
    }
  }
  
  public aa()
  {
    this(x.c);
  }
  
  public aa(com.sleepycat.b.i.c.aj paramaj, ac paramac, z paramz)
  {
    super(paramaj, "RepNode " + paramaj.ao);
    this.i = paramaj;
    this.k = new com.sleepycat.b.i.h.t(paramaj);
    this.a = paramaj.ao;
    this.x = com.sleepycat.b.p.w.a(getClass());
    this.b = paramaj.ad();
    this.c = new com.sleepycat.b.i.h.x(this.b, paramaj);
    this.c.start();
    this.n = new ab(com.sleepycat.b.i.c.aj.aa(), (byte)0);
    this.j = new com.sleepycat.b.i.c.p(paramaj);
    this.g = new com.sleepycat.b.i.e.n(this.a);
    this.e = ao.a(this, paramac);
    this.f = new m(this);
    this.G = new com.sleepycat.b.i.e.l(this);
    this.H = new com.sleepycat.b.i.e.p(this);
    this.h = paramz;
    this.y = new g(paramaj);
    this.z = new f(paramaj);
    this.J = new com.sleepycat.b.i.g.a.f(this.c, this.i);
    this.o = new com.sleepycat.b.i.c.a.a(this.c, this.i, this.a);
    this.K = new com.sleepycat.b.i.c.l(this.c, this);
    this.c.a(this.K);
    this.L = new com.sleepycat.b.i.c.d(this.c, this);
    this.M = new com.sleepycat.b.i.c.g(this.c, this);
    this.c.a(this.M);
    this.p = new q(this);
    this.r = new o(this);
    this.t = new w(this);
    this.v = new Timer(true);
    this.w = new a(this.v);
    paramac = this.i.u;
    boolean bool = paramac.a(an.aa);
    int i1 = paramac.a(an.ab);
    if (!bool) {
      if (this.N != null) {
        this.N.a();
      }
    }
    for (;;)
    {
      this.A = new com.sleepycat.b.i.a.a(paramaj);
      return;
      if (this.N == null) {
        this.N = new s(this, this.v);
      }
      paramac = this.N;
      if ((paramac.c != i1) || (paramac.d == null))
      {
        paramac.c = i1;
        paramac.a();
        paramac.d = new t(paramac.a);
        paramac.b.schedule(paramac.d, 0L, paramac.c);
      }
    }
  }
  
  private aa(x paramx)
  {
    this(paramx, (byte)0);
  }
  
  private aa(x paramx, byte paramByte)
  {
    super("RepNode " + paramx);
    this.i = null;
    this.n = new ab(0, (byte)0);
    this.a = paramx;
    this.b = null;
    this.c = null;
    this.j = null;
    this.g = new com.sleepycat.b.i.e.n(x.c);
    this.e = null;
    this.f = null;
    this.G = null;
    this.H = null;
    this.h = null;
    this.p = null;
    this.r = null;
    this.x = null;
    this.v = null;
    this.w = null;
    this.y = null;
    this.z = null;
    this.A = null;
  }
  
  public static String a(Set<Long> paramSet)
  {
    StringBuilder localStringBuilder = new StringBuilder();
    paramSet = paramSet.iterator();
    while (paramSet.hasNext())
    {
      Long localLong = (Long)paramSet.next();
      localStringBuilder.append(" 0x").append(Long.toHexString(localLong.longValue()));
    }
    return localStringBuilder.toString();
  }
  
  /* Error */
  private boolean a(x paramx)
  {
    // Byte code:
    //   0: aconst_null
    //   1: astore 5
    //   3: aconst_null
    //   4: astore 4
    //   6: aload 4
    //   8: astore_3
    //   9: aload 5
    //   11: astore_2
    //   12: aload_0
    //   13: getfield 205	com/sleepycat/b/i/c/b/aa:g	Lcom/sleepycat/b/i/e/n;
    //   16: invokevirtual 402	com/sleepycat/b/i/e/n:i	()Ljava/net/InetSocketAddress;
    //   19: astore 7
    //   21: aload 4
    //   23: astore_3
    //   24: aload 5
    //   26: astore_2
    //   27: new 404	com/sleepycat/b/i/c/a
    //   30: dup
    //   31: getstatic 406	com/sleepycat/b/i/c/b/x:d	Lcom/sleepycat/b/i/c/b/x;
    //   34: aconst_null
    //   35: invokespecial 409	com/sleepycat/b/i/c/a:<init>	(Lcom/sleepycat/b/i/c/b/x;Lcom/sleepycat/b/i/c/aj;)V
    //   38: astore 6
    //   40: aload 4
    //   42: astore_3
    //   43: aload 5
    //   45: astore_2
    //   46: aload 7
    //   48: invokestatic 414	com/sleepycat/b/i/h/q:a	(Ljava/net/InetSocketAddress;)Ljava/nio/channels/SocketChannel;
    //   51: astore 4
    //   53: aload 4
    //   55: astore_3
    //   56: aload 4
    //   58: astore_2
    //   59: aload 4
    //   61: ldc_w 416
    //   64: invokestatic 419	com/sleepycat/b/i/h/x:a	(Ljava/nio/channels/SocketChannel;Ljava/lang/String;)V
    //   67: aload 4
    //   69: astore_3
    //   70: aload 4
    //   72: astore_2
    //   73: aload 6
    //   75: invokevirtual 159	java/lang/Object:getClass	()Ljava/lang/Class;
    //   78: pop
    //   79: aload 4
    //   81: astore_3
    //   82: aload 4
    //   84: astore_2
    //   85: aload 6
    //   87: new 421	com/sleepycat/b/i/c/b
    //   90: dup
    //   91: aload 6
    //   93: aload_1
    //   94: getfield 424	com/sleepycat/b/i/c/b/x:a	Ljava/lang/String;
    //   97: aload_0
    //   98: getfield 426	com/sleepycat/b/i/c/b/aa:m	Lcom/sleepycat/b/i/c/t;
    //   101: getfield 429	com/sleepycat/b/i/c/t:a	Ljava/lang/String;
    //   104: invokespecial 432	com/sleepycat/b/i/c/b:<init>	(Lcom/sleepycat/b/i/c/a;Ljava/lang/String;Ljava/lang/String;)V
    //   107: aload 4
    //   109: invokevirtual 435	com/sleepycat/b/i/c/a:a	(Lcom/sleepycat/b/i/h/d;Ljava/nio/channels/WritableByteChannel;)V
    //   112: aload 4
    //   114: astore_3
    //   115: aload 4
    //   117: astore_2
    //   118: aload 6
    //   120: aload 4
    //   122: ldc_w 437
    //   125: invokevirtual 440	com/sleepycat/b/i/c/a:a	(Ljava/nio/channels/ReadableByteChannel;Ljava/lang/Class;)Lcom/sleepycat/b/i/h/d;
    //   128: checkcast 437	com/sleepycat/b/i/c/c
    //   131: getfield 443	com/sleepycat/b/i/c/c:a	Lcom/sleepycat/b/i/u;
    //   134: astore 5
    //   136: aload 5
    //   138: ifnull +37 -> 175
    //   141: aload 4
    //   143: astore_3
    //   144: aload 4
    //   146: astore_2
    //   147: aload 5
    //   149: invokevirtual 447	com/sleepycat/b/i/u:a	()Z
    //   152: istore 8
    //   154: iload 8
    //   156: ifeq +19 -> 175
    //   159: iconst_1
    //   160: istore 8
    //   162: aload 4
    //   164: ifnull +8 -> 172
    //   167: aload 4
    //   169: invokevirtual 452	java/nio/channels/SocketChannel:close	()V
    //   172: iload 8
    //   174: ireturn
    //   175: iconst_0
    //   176: istore 8
    //   178: goto -16 -> 162
    //   181: astore 4
    //   183: aload_3
    //   184: astore_2
    //   185: aload_0
    //   186: getfield 166	com/sleepycat/b/i/c/b/aa:x	Ljava/util/logging/Logger;
    //   189: aload_0
    //   190: getfield 146	com/sleepycat/b/i/c/b/aa:i	Lcom/sleepycat/b/i/c/aj;
    //   193: new 103	java/lang/StringBuilder
    //   196: dup
    //   197: ldc_w 454
    //   200: invokespecial 108	java/lang/StringBuilder:<init>	(Ljava/lang/String;)V
    //   203: aload_1
    //   204: invokevirtual 117	java/lang/StringBuilder:append	(Ljava/lang/Object;)Ljava/lang/StringBuilder;
    //   207: ldc_w 456
    //   210: invokevirtual 385	java/lang/StringBuilder:append	(Ljava/lang/String;)Ljava/lang/StringBuilder;
    //   213: aload 4
    //   215: invokevirtual 117	java/lang/StringBuilder:append	(Ljava/lang/Object;)Ljava/lang/StringBuilder;
    //   218: invokevirtual 121	java/lang/StringBuilder:toString	()Ljava/lang/String;
    //   221: invokestatic 459	com/sleepycat/b/p/w:c	(Ljava/util/logging/Logger;Lcom/sleepycat/b/c/ad;Ljava/lang/String;)V
    //   224: aload_3
    //   225: ifnull +7 -> 232
    //   228: aload_3
    //   229: invokevirtual 452	java/nio/channels/SocketChannel:close	()V
    //   232: iconst_0
    //   233: ireturn
    //   234: astore_1
    //   235: aload_2
    //   236: ifnull +7 -> 243
    //   239: aload_2
    //   240: invokevirtual 452	java/nio/channels/SocketChannel:close	()V
    //   243: aload_1
    //   244: athrow
    //   245: astore_1
    //   246: iload 8
    //   248: ireturn
    //   249: astore_1
    //   250: goto -18 -> 232
    //   253: astore_2
    //   254: goto -11 -> 243
    // Local variable table:
    //   start	length	slot	name	signature
    //   0	257	0	this	aa
    //   0	257	1	paramx	x
    //   11	229	2	localObject	Object
    //   253	1	2	localIOException	java.io.IOException
    //   8	221	3	localSocketChannel1	java.nio.channels.SocketChannel
    //   4	164	4	localSocketChannel2	java.nio.channels.SocketChannel
    //   181	33	4	localException	Exception
    //   1	147	5	localu	com.sleepycat.b.i.u
    //   38	81	6	locala	com.sleepycat.b.i.c.a
    //   19	28	7	localInetSocketAddress	InetSocketAddress
    //   152	95	8	bool	boolean
    // Exception table:
    //   from	to	target	type
    //   12	21	181	java/lang/Exception
    //   27	40	181	java/lang/Exception
    //   46	53	181	java/lang/Exception
    //   59	67	181	java/lang/Exception
    //   73	79	181	java/lang/Exception
    //   85	112	181	java/lang/Exception
    //   118	136	181	java/lang/Exception
    //   147	154	181	java/lang/Exception
    //   12	21	234	finally
    //   27	40	234	finally
    //   46	53	234	finally
    //   59	67	234	finally
    //   73	79	234	finally
    //   85	112	234	finally
    //   118	136	234	finally
    //   147	154	234	finally
    //   185	224	234	finally
    //   167	172	245	java/io/IOException
    //   228	232	249	java/io/IOException
    //   239	243	253	java/io/IOException
  }
  
  private void b(Set<InetSocketAddress> paramSet)
  {
    HashSet localHashSet = new HashSet();
    com.sleepycat.b.i.c.x localx = new com.sleepycat.b.i.c.x(this.m.a, this.a, this.i);
    paramSet = paramSet.iterator();
    while (paramSet.hasNext())
    {
      Object localObject1 = (InetSocketAddress)paramSet.next();
      localx.getClass();
      localx.getClass();
      Object localObject2 = new com.sleepycat.b.i.c.au(localx, (InetSocketAddress)localObject1, "Group", new com.sleepycat.b.i.c.ad(localx));
      ((com.sleepycat.b.i.c.au)localObject2).run();
      localObject2 = ((com.sleepycat.b.i.c.au)localObject2).a();
      if ((localObject2 != null) && (!localx.f.equals(((az)localObject2).a())))
      {
        localObject2 = ((ae)localObject2).a;
        am localam = ((com.sleepycat.b.i.c.t)localObject2).b(this.a.a);
        if ((localam != null) && (!localam.d) && (localam.c))
        {
          localObject1 = ((com.sleepycat.b.i.c.t)localObject2).a((InetSocketAddress)localObject1);
          if (localObject1 != null) {
            localHashSet.add(localObject1);
          }
        }
      }
    }
    if (localHashSet.isEmpty()) {
      return;
    }
    throw new com.sleepycat.b.i.f(this, com.sleepycat.b.p.au.a, localHashSet);
  }
  
  private void o()
  {
    Object localObject1 = this.i.ae();
    boolean bool = this.b.getAddress().isLoopbackAddress();
    Object localObject3 = ((Set)localObject1).iterator();
    Object localObject2;
    while (((Iterator)localObject3).hasNext())
    {
      localObject2 = (InetSocketAddress)((Iterator)localObject3).next();
      if (((InetSocketAddress)localObject2).getAddress().isLoopbackAddress() != bool)
      {
        localObject3 = new StringBuilder().append(this.b).append(" the address associated with this node, ");
        if (bool)
        {
          localObject1 = "is ";
          localObject2 = ((StringBuilder)localObject3).append((String)localObject1).append("a loopback address. It conflicts with an existing use, by a different node  of the address:").append(localObject2);
          if (bool) {
            break label142;
          }
        }
        label142:
        for (localObject1 = " which is a loopback address.";; localObject1 = " which is not a loopback address.")
        {
          throw new IllegalArgumentException((String)localObject1 + " Such mixing of addresses within a group is not allowed, since the nodes will not be able to communicate with each other.");
          localObject1 = "is not ";
          break;
        }
      }
    }
    localObject1 = new HashSet((Collection)localObject1);
    ((Set)localObject1).addAll(this.m.f());
    if (((Set)localObject1).size() == 0) {
      throw com.sleepycat.b.aa.c("Need a helper to add a new node into the group");
    }
    for (;;)
    {
      this.d.g.a((Set)localObject1);
      localObject2 = this.g.j();
      if (!((x)localObject2).a())
      {
        if ((this.a.a()) && (((x)localObject2).a.equals(this.a.a))) {
          try
          {
            Thread.sleep(10000L);
          }
          catch (InterruptedException localInterruptedException1)
          {
            throw com.sleepycat.b.aa.a(localInterruptedException1);
          }
        }
        if (a((x)localObject2)) {
          break;
        }
      }
      else
      {
        b(localInterruptedException1);
        try
        {
          Thread.sleep(10000L);
        }
        catch (InterruptedException localInterruptedException2)
        {
          throw com.sleepycat.b.aa.a(localInterruptedException2);
        }
      }
    }
    com.sleepycat.b.p.w.c(this.x, this.i, "New node " + this.a.a + " located master: " + localObject2);
  }
  
  private boolean p()
  {
    if (this.O == null) {}
    for (;;)
    {
      return true;
      Iterator localIterator = this.O.iterator();
      while (localIterator.hasNext())
      {
        localIterator.next();
        if (C) {}
      }
    }
  }
  
  /* Error */
  public final com.sleepycat.b.i.u a(com.sleepycat.b.bc parambc, com.sleepycat.b.i.p paramp)
  {
    // Byte code:
    //   0: aconst_null
    //   1: astore_3
    //   2: new 632	com/sleepycat/b/i/c/b/p
    //   5: dup
    //   6: aload_0
    //   7: getfield 146	com/sleepycat/b/i/c/b/aa:i	Lcom/sleepycat/b/i/c/aj;
    //   10: getfield 309	com/sleepycat/b/c/ad:u	Lcom/sleepycat/b/c/m;
    //   13: invokespecial 635	com/sleepycat/b/i/c/b/p:<init>	(Lcom/sleepycat/b/c/m;)V
    //   16: astore 5
    //   18: aload_0
    //   19: invokevirtual 638	com/sleepycat/b/i/c/b/aa:isAlive	()Z
    //   22: ifne +325 -> 347
    //   25: aload_0
    //   26: getfield 231	com/sleepycat/b/i/c/b/aa:h	Lcom/sleepycat/b/i/c/b/z;
    //   29: invokevirtual 643	com/sleepycat/b/i/c/b/z:a	()Lcom/sleepycat/b/i/u;
    //   32: invokevirtual 645	com/sleepycat/b/i/u:c	()Z
    //   35: ifeq +16 -> 51
    //   38: aload_0
    //   39: getfield 231	com/sleepycat/b/i/c/b/aa:h	Lcom/sleepycat/b/i/c/b/z;
    //   42: getstatic 647	com/sleepycat/b/i/u:b	Lcom/sleepycat/b/i/u;
    //   45: getstatic 97	com/sleepycat/b/i/c/b/x:c	Lcom/sleepycat/b/i/c/b/x;
    //   48: invokevirtual 650	com/sleepycat/b/i/c/b/z:a	(Lcom/sleepycat/b/i/u;Lcom/sleepycat/b/i/c/b/x;)V
    //   51: aload_0
    //   52: new 588	com/sleepycat/b/i/b/d
    //   55: dup
    //   56: aload_0
    //   57: aload_0
    //   58: getfield 224	com/sleepycat/b/i/c/b/aa:G	Lcom/sleepycat/b/i/e/l;
    //   61: aload_0
    //   62: getfield 229	com/sleepycat/b/i/c/b/aa:H	Lcom/sleepycat/b/i/e/p;
    //   65: invokespecial 653	com/sleepycat/b/i/b/d:<init>	(Lcom/sleepycat/b/i/c/b/aa;Lcom/sleepycat/b/i/b/k;Lcom/sleepycat/b/i/b/b;)V
    //   68: putfield 586	com/sleepycat/b/i/c/b/aa:d	Lcom/sleepycat/b/i/b/d;
    //   71: aload_0
    //   72: getfield 146	com/sleepycat/b/i/c/b/aa:i	Lcom/sleepycat/b/i/c/aj;
    //   75: getfield 657	com/sleepycat/b/c/ad:E	Lcom/sleepycat/b/c/bd;
    //   78: getstatic 662	com/sleepycat/b/c/bg:r	Lcom/sleepycat/b/c/bg;
    //   81: invokevirtual 667	com/sleepycat/b/c/bd:a	(Lcom/sleepycat/b/c/bg;)V
    //   84: aload_0
    //   85: getfield 146	com/sleepycat/b/i/c/b/aa:i	Lcom/sleepycat/b/i/c/aj;
    //   88: getfield 309	com/sleepycat/b/c/ad:u	Lcom/sleepycat/b/c/m;
    //   91: getstatic 669	com/sleepycat/b/i/c/an:v	Lcom/sleepycat/b/b/a;
    //   94: invokevirtual 319	com/sleepycat/b/c/m:a	(Lcom/sleepycat/b/b/a;)Z
    //   97: ifeq +395 -> 492
    //   100: aload_0
    //   101: aload_0
    //   102: getfield 200	com/sleepycat/b/i/c/b/aa:j	Lcom/sleepycat/b/i/c/p;
    //   105: getfield 671	com/sleepycat/b/i/c/p:b	Lcom/sleepycat/b/i/c/t;
    //   108: putfield 426	com/sleepycat/b/i/c/b/aa:m	Lcom/sleepycat/b/i/c/t;
    //   111: aload_0
    //   112: getfield 166	com/sleepycat/b/i/c/b/aa:x	Ljava/util/logging/Logger;
    //   115: aload_0
    //   116: getfield 146	com/sleepycat/b/i/c/b/aa:i	Lcom/sleepycat/b/i/c/aj;
    //   119: new 103	java/lang/StringBuilder
    //   122: dup
    //   123: ldc_w 673
    //   126: invokespecial 108	java/lang/StringBuilder:<init>	(Ljava/lang/String;)V
    //   129: aload_0
    //   130: getfield 153	com/sleepycat/b/i/c/b/aa:a	Lcom/sleepycat/b/i/c/b/x;
    //   133: invokevirtual 117	java/lang/StringBuilder:append	(Ljava/lang/Object;)Ljava/lang/StringBuilder;
    //   136: invokevirtual 121	java/lang/StringBuilder:toString	()Ljava/lang/String;
    //   139: invokestatic 459	com/sleepycat/b/p/w:c	(Ljava/util/logging/Logger;Lcom/sleepycat/b/c/ad;Ljava/lang/String;)V
    //   142: aload_0
    //   143: getfield 231	com/sleepycat/b/i/c/b/aa:h	Lcom/sleepycat/b/i/c/b/z;
    //   146: getstatic 675	com/sleepycat/b/i/u:c	Lcom/sleepycat/b/i/u;
    //   149: aload_0
    //   150: getfield 205	com/sleepycat/b/i/c/b/aa:g	Lcom/sleepycat/b/i/e/n;
    //   153: invokevirtual 677	com/sleepycat/b/i/e/n:h	()Lcom/sleepycat/b/i/c/b/x;
    //   156: invokevirtual 650	com/sleepycat/b/i/c/b/z:a	(Lcom/sleepycat/b/i/u;Lcom/sleepycat/b/i/c/b/x;)V
    //   159: aload_0
    //   160: getfield 146	com/sleepycat/b/i/c/b/aa:i	Lcom/sleepycat/b/i/c/aj;
    //   163: getfield 681	com/sleepycat/b/i/c/aj:aj	Lcom/sleepycat/b/i/i/f;
    //   166: invokevirtual 684	com/sleepycat/b/i/i/f:a	()V
    //   169: aload_0
    //   170: getfield 146	com/sleepycat/b/i/c/b/aa:i	Lcom/sleepycat/b/i/c/aj;
    //   173: invokevirtual 686	com/sleepycat/b/i/c/aj:t	()J
    //   176: pop2
    //   177: new 688	com/sleepycat/b/c
    //   180: dup
    //   181: invokespecial 689	com/sleepycat/b/c:<init>	()V
    //   184: astore_1
    //   185: aload_1
    //   186: iconst_1
    //   187: putfield 691	com/sleepycat/b/c:b	Z
    //   190: aload_0
    //   191: getfield 146	com/sleepycat/b/i/c/b/aa:i	Lcom/sleepycat/b/i/c/aj;
    //   194: getfield 694	com/sleepycat/b/c/ad:C	Lcom/sleepycat/b/h/d;
    //   197: aload_1
    //   198: ldc_w 696
    //   201: invokevirtual 701	com/sleepycat/b/h/d:a	(Lcom/sleepycat/b/c;Ljava/lang/String;)V
    //   204: aload_0
    //   205: getfield 146	com/sleepycat/b/i/c/b/aa:i	Lcom/sleepycat/b/i/c/aj;
    //   208: getfield 681	com/sleepycat/b/i/c/aj:aj	Lcom/sleepycat/b/i/i/f;
    //   211: getfield 704	com/sleepycat/b/i/i/f:h	Lcom/sleepycat/b/i/i/p;
    //   214: invokevirtual 709	com/sleepycat/b/i/i/p:b	()Lcom/sleepycat/b/i/i/m;
    //   217: getfield 713	com/sleepycat/b/i/i/m:c	Lcom/sleepycat/b/p/au;
    //   220: astore_1
    //   221: aload_0
    //   222: getfield 200	com/sleepycat/b/i/c/b/aa:j	Lcom/sleepycat/b/i/c/p;
    //   225: aload_1
    //   226: invokevirtual 716	com/sleepycat/b/i/c/p:a	(Lcom/sleepycat/b/p/au;)V
    //   229: aload_0
    //   230: invokevirtual 719	com/sleepycat/b/i/c/b/aa:h	()Lcom/sleepycat/b/i/c/t;
    //   233: pop
    //   234: aload_0
    //   235: getfield 146	com/sleepycat/b/i/c/b/aa:i	Lcom/sleepycat/b/i/c/aj;
    //   238: getfield 681	com/sleepycat/b/i/c/aj:aj	Lcom/sleepycat/b/i/i/f;
    //   241: aload_1
    //   242: invokevirtual 722	com/sleepycat/b/i/i/f:a	(Lcom/sleepycat/b/p/au;)J
    //   245: lstore 12
    //   247: aload_0
    //   248: getfield 146	com/sleepycat/b/i/c/b/aa:i	Lcom/sleepycat/b/i/c/aj;
    //   251: getfield 681	com/sleepycat/b/i/c/aj:aj	Lcom/sleepycat/b/i/i/f;
    //   254: aload_1
    //   255: lload 12
    //   257: invokevirtual 725	com/sleepycat/b/i/i/f:a	(Lcom/sleepycat/b/p/au;J)V
    //   260: aload_0
    //   261: getfield 586	com/sleepycat/b/i/c/b/aa:d	Lcom/sleepycat/b/i/b/d;
    //   264: invokevirtual 726	com/sleepycat/b/i/b/d:a	()V
    //   267: aload_0
    //   268: getfield 205	com/sleepycat/b/i/c/b/aa:g	Lcom/sleepycat/b/i/e/n;
    //   271: invokevirtual 728	com/sleepycat/b/i/e/n:d	()V
    //   274: aload_0
    //   275: aload_2
    //   276: putfield 138	com/sleepycat/b/i/c/b/aa:I	Lcom/sleepycat/b/i/p;
    //   279: aload_0
    //   280: getfield 586	com/sleepycat/b/i/c/b/aa:d	Lcom/sleepycat/b/i/b/d;
    //   283: astore_1
    //   284: aload_1
    //   285: new 730	com/sleepycat/b/i/b/ak
    //   288: dup
    //   289: aload_1
    //   290: aload_1
    //   291: getfield 732	com/sleepycat/b/i/b/d:b	Lcom/sleepycat/b/i/c/b/x;
    //   294: invokespecial 735	com/sleepycat/b/i/b/ak:<init>	(Lcom/sleepycat/b/i/b/d;Lcom/sleepycat/b/i/c/b/x;)V
    //   297: putfield 738	com/sleepycat/b/i/b/d:e	Lcom/sleepycat/b/i/b/m;
    //   300: aload_1
    //   301: new 740	com/sleepycat/b/i/b/a
    //   304: dup
    //   305: aload_1
    //   306: getfield 743	com/sleepycat/b/i/b/d:j	Lcom/sleepycat/b/i/b/x;
    //   309: aload_1
    //   310: getfield 745	com/sleepycat/b/i/b/d:c	Lcom/sleepycat/b/i/c/b/aa;
    //   313: aload_1
    //   314: getfield 748	com/sleepycat/b/i/b/d:i	Lcom/sleepycat/b/i/b/b;
    //   317: invokespecial 751	com/sleepycat/b/i/b/a:<init>	(Lcom/sleepycat/b/i/b/x;Lcom/sleepycat/b/i/c/b/aa;Lcom/sleepycat/b/i/b/b;)V
    //   320: putfield 754	com/sleepycat/b/i/b/d:f	Lcom/sleepycat/b/i/b/a;
    //   323: aload_1
    //   324: getfield 754	com/sleepycat/b/i/b/d:f	Lcom/sleepycat/b/i/b/a;
    //   327: invokevirtual 755	com/sleepycat/b/i/b/a:start	()V
    //   330: aload_0
    //   331: getfield 146	com/sleepycat/b/i/c/b/aa:i	Lcom/sleepycat/b/i/c/aj;
    //   334: getfield 657	com/sleepycat/b/c/ad:E	Lcom/sleepycat/b/c/bd;
    //   337: getstatic 662	com/sleepycat/b/c/bg:r	Lcom/sleepycat/b/c/bg;
    //   340: invokevirtual 757	com/sleepycat/b/c/bd:b	(Lcom/sleepycat/b/c/bg;)V
    //   343: aload_0
    //   344: invokevirtual 758	com/sleepycat/b/i/c/b/aa:start	()V
    //   347: aload_0
    //   348: getfield 166	com/sleepycat/b/i/c/b/aa:x	Ljava/util/logging/Logger;
    //   351: aload_0
    //   352: getfield 146	com/sleepycat/b/i/c/b/aa:i	Lcom/sleepycat/b/i/c/aj;
    //   355: new 103	java/lang/StringBuilder
    //   358: dup
    //   359: ldc_w 760
    //   362: invokespecial 108	java/lang/StringBuilder:<init>	(Ljava/lang/String;)V
    //   365: aload_0
    //   366: getfield 231	com/sleepycat/b/i/c/b/aa:h	Lcom/sleepycat/b/i/c/b/z;
    //   369: invokevirtual 643	com/sleepycat/b/i/c/b/z:a	()Lcom/sleepycat/b/i/u;
    //   372: invokevirtual 117	java/lang/StringBuilder:append	(Ljava/lang/Object;)Ljava/lang/StringBuilder;
    //   375: invokevirtual 121	java/lang/StringBuilder:toString	()Ljava/lang/String;
    //   378: invokestatic 762	com/sleepycat/b/p/w:e	(Ljava/util/logging/Logger;Lcom/sleepycat/b/c/ad;Ljava/lang/String;)V
    //   381: aload_0
    //   382: getfield 146	com/sleepycat/b/i/c/b/aa:i	Lcom/sleepycat/b/i/c/aj;
    //   385: getfield 657	com/sleepycat/b/c/ad:E	Lcom/sleepycat/b/c/bd;
    //   388: getstatic 764	com/sleepycat/b/c/bg:s	Lcom/sleepycat/b/c/bg;
    //   391: invokevirtual 667	com/sleepycat/b/c/bd:a	(Lcom/sleepycat/b/c/bg;)V
    //   394: aload_0
    //   395: getfield 146	com/sleepycat/b/i/c/b/aa:i	Lcom/sleepycat/b/i/c/aj;
    //   398: getfield 657	com/sleepycat/b/c/ad:E	Lcom/sleepycat/b/c/bd;
    //   401: astore_1
    //   402: getstatic 768	com/sleepycat/b/bb:p	I
    //   405: istore 10
    //   407: aload_1
    //   408: invokevirtual 769	com/sleepycat/b/c/bd:a	()V
    //   411: iconst_0
    //   412: istore 10
    //   414: aconst_null
    //   415: astore_1
    //   416: iload 10
    //   418: bipush 10
    //   420: if_icmpge +1209 -> 1629
    //   423: aload_0
    //   424: getfield 126	com/sleepycat/b/i/c/b/aa:k	Lcom/sleepycat/b/i/h/t;
    //   427: aload 5
    //   429: invokevirtual 771	com/sleepycat/b/i/c/b/p:a	()I
    //   432: i2l
    //   433: getstatic 777	java/util/concurrent/TimeUnit:MILLISECONDS	Ljava/util/concurrent/TimeUnit;
    //   436: invokevirtual 780	com/sleepycat/b/i/h/t:a	(JLjava/util/concurrent/TimeUnit;)Z
    //   439: istore 14
    //   441: aload_0
    //   442: getfield 231	com/sleepycat/b/i/c/b/aa:h	Lcom/sleepycat/b/i/c/b/z;
    //   445: invokevirtual 643	com/sleepycat/b/i/c/b/z:a	()Lcom/sleepycat/b/i/u;
    //   448: astore_3
    //   449: iload 14
    //   451: ifne +841 -> 1292
    //   454: aload_3
    //   455: invokevirtual 782	com/sleepycat/b/i/u:b	()Z
    //   458: ifeq +786 -> 1244
    //   461: aload 5
    //   463: invokevirtual 783	com/sleepycat/b/i/c/b/p:b	()Z
    //   466: ifeq +727 -> 1193
    //   469: aload 5
    //   471: aload 5
    //   473: getfield 785	com/sleepycat/b/i/c/b/p:a	I
    //   476: putfield 787	com/sleepycat/b/i/c/b/p:b	I
    //   479: aload_1
    //   480: astore_2
    //   481: iload 10
    //   483: iconst_1
    //   484: iadd
    //   485: istore 10
    //   487: aload_2
    //   488: astore_1
    //   489: goto -73 -> 416
    //   492: aload_0
    //   493: invokevirtual 719	com/sleepycat/b/i/c/b/aa:h	()Lcom/sleepycat/b/i/c/t;
    //   496: pop
    //   497: aload_0
    //   498: getfield 586	com/sleepycat/b/i/c/b/aa:d	Lcom/sleepycat/b/i/b/d;
    //   501: invokevirtual 726	com/sleepycat/b/i/b/d:a	()V
    //   504: aload_0
    //   505: getfield 166	com/sleepycat/b/i/c/b/aa:x	Ljava/util/logging/Logger;
    //   508: aload_0
    //   509: getfield 146	com/sleepycat/b/i/c/b/aa:i	Lcom/sleepycat/b/i/c/aj;
    //   512: new 103	java/lang/StringBuilder
    //   515: dup
    //   516: ldc_w 789
    //   519: invokespecial 108	java/lang/StringBuilder:<init>	(Ljava/lang/String;)V
    //   522: aload_0
    //   523: getfield 426	com/sleepycat/b/i/c/b/aa:m	Lcom/sleepycat/b/i/c/t;
    //   526: invokevirtual 791	com/sleepycat/b/i/c/t:h	()I
    //   529: invokevirtual 794	java/lang/StringBuilder:append	(I)Ljava/lang/StringBuilder;
    //   532: invokevirtual 121	java/lang/StringBuilder:toString	()Ljava/lang/String;
    //   535: invokestatic 459	com/sleepycat/b/p/w:c	(Ljava/util/logging/Logger;Lcom/sleepycat/b/c/ad;Ljava/lang/String;)V
    //   538: aload_0
    //   539: getfield 426	com/sleepycat/b/i/c/b/aa:m	Lcom/sleepycat/b/i/c/t;
    //   542: aload_0
    //   543: getfield 153	com/sleepycat/b/i/c/b/aa:a	Lcom/sleepycat/b/i/c/b/x;
    //   546: getfield 424	com/sleepycat/b/i/c/b/x:a	Ljava/lang/String;
    //   549: invokevirtual 507	com/sleepycat/b/i/c/t:b	(Ljava/lang/String;)Lcom/sleepycat/b/i/c/am;
    //   552: astore_1
    //   553: aload_1
    //   554: ifnonnull +523 -> 1077
    //   557: aload_0
    //   558: getfield 166	com/sleepycat/b/i/c/b/aa:x	Ljava/util/logging/Logger;
    //   561: aload_0
    //   562: getfield 146	com/sleepycat/b/i/c/b/aa:i	Lcom/sleepycat/b/i/c/aj;
    //   565: new 103	java/lang/StringBuilder
    //   568: dup
    //   569: ldc_w 619
    //   572: invokespecial 108	java/lang/StringBuilder:<init>	(Ljava/lang/String;)V
    //   575: aload_0
    //   576: getfield 153	com/sleepycat/b/i/c/b/aa:a	Lcom/sleepycat/b/i/c/b/x;
    //   579: invokevirtual 117	java/lang/StringBuilder:append	(Ljava/lang/Object;)Ljava/lang/StringBuilder;
    //   582: ldc_w 796
    //   585: invokevirtual 385	java/lang/StringBuilder:append	(Ljava/lang/String;)Ljava/lang/StringBuilder;
    //   588: invokevirtual 121	java/lang/StringBuilder:toString	()Ljava/lang/String;
    //   591: invokestatic 459	com/sleepycat/b/p/w:c	(Ljava/util/logging/Logger;Lcom/sleepycat/b/c/ad;Ljava/lang/String;)V
    //   594: aload_0
    //   595: getfield 146	com/sleepycat/b/i/c/b/aa:i	Lcom/sleepycat/b/i/c/aj;
    //   598: invokevirtual 539	com/sleepycat/b/i/c/aj:ae	()Ljava/util/Set;
    //   601: astore_1
    //   602: aload_0
    //   603: getfield 426	com/sleepycat/b/i/c/b/aa:m	Lcom/sleepycat/b/i/c/t;
    //   606: invokevirtual 791	com/sleepycat/b/i/c/t:h	()I
    //   609: ifne +461 -> 1070
    //   612: aload_1
    //   613: invokeinterface 577 1 0
    //   618: iconst_1
    //   619: if_icmpne +451 -> 1070
    //   622: aload_0
    //   623: getfield 179	com/sleepycat/b/i/c/b/aa:c	Lcom/sleepycat/b/i/h/x;
    //   626: getfield 798	com/sleepycat/b/i/h/x:a	Ljava/net/InetSocketAddress;
    //   629: aload_1
    //   630: invokeinterface 369 1 0
    //   635: invokeinterface 378 1 0
    //   640: invokevirtual 799	java/net/InetSocketAddress:equals	(Ljava/lang/Object;)Z
    //   643: ifeq +427 -> 1070
    //   646: aload_0
    //   647: getfield 153	com/sleepycat/b/i/c/b/aa:a	Lcom/sleepycat/b/i/c/b/x;
    //   650: invokestatic 801	com/sleepycat/b/i/c/t:b	()I
    //   653: invokevirtual 804	com/sleepycat/b/i/c/b/x:a	(I)V
    //   656: new 806	com/sleepycat/b/i/b/am
    //   659: dup
    //   660: invokespecial 807	com/sleepycat/b/i/b/am:<init>	()V
    //   663: invokevirtual 810	com/sleepycat/b/i/b/am:a	()Lcom/sleepycat/b/i/b/s;
    //   666: astore_1
    //   667: aload_0
    //   668: getfield 586	com/sleepycat/b/i/c/b/aa:d	Lcom/sleepycat/b/i/b/d;
    //   671: getfield 591	com/sleepycat/b/i/b/d:g	Lcom/sleepycat/b/i/b/j;
    //   674: aload_1
    //   675: aload_0
    //   676: getfield 229	com/sleepycat/b/i/c/b/aa:H	Lcom/sleepycat/b/i/e/p;
    //   679: invokevirtual 813	com/sleepycat/b/i/e/p:a	()Lcom/sleepycat/b/i/b/ai;
    //   682: invokevirtual 816	com/sleepycat/b/i/b/j:a	(Lcom/sleepycat/b/i/b/s;Lcom/sleepycat/b/i/b/ai;)V
    //   685: aload_0
    //   686: getfield 166	com/sleepycat/b/i/c/b/aa:x	Ljava/util/logging/Logger;
    //   689: aload_0
    //   690: getfield 146	com/sleepycat/b/i/c/b/aa:i	Lcom/sleepycat/b/i/c/aj;
    //   693: new 103	java/lang/StringBuilder
    //   696: dup
    //   697: ldc_w 818
    //   700: invokespecial 108	java/lang/StringBuilder:<init>	(Ljava/lang/String;)V
    //   703: aload_0
    //   704: getfield 153	com/sleepycat/b/i/c/b/aa:a	Lcom/sleepycat/b/i/c/b/x;
    //   707: getfield 424	com/sleepycat/b/i/c/b/x:a	Ljava/lang/String;
    //   710: invokevirtual 385	java/lang/StringBuilder:append	(Ljava/lang/String;)Ljava/lang/StringBuilder;
    //   713: ldc_w 820
    //   716: invokevirtual 385	java/lang/StringBuilder:append	(Ljava/lang/String;)Ljava/lang/StringBuilder;
    //   719: invokevirtual 121	java/lang/StringBuilder:toString	()Ljava/lang/String;
    //   722: invokestatic 459	com/sleepycat/b/p/w:c	(Ljava/util/logging/Logger;Lcom/sleepycat/b/c/ad;Ljava/lang/String;)V
    //   725: aload_0
    //   726: getfield 205	com/sleepycat/b/i/c/b/aa:g	Lcom/sleepycat/b/i/e/n;
    //   729: invokevirtual 822	com/sleepycat/b/i/e/n:f	()V
    //   732: aload_0
    //   733: getfield 231	com/sleepycat/b/i/c/b/aa:h	Lcom/sleepycat/b/i/c/b/z;
    //   736: getstatic 675	com/sleepycat/b/i/u:c	Lcom/sleepycat/b/i/u;
    //   739: aload_0
    //   740: getfield 205	com/sleepycat/b/i/c/b/aa:g	Lcom/sleepycat/b/i/e/n;
    //   743: invokevirtual 677	com/sleepycat/b/i/e/n:h	()Lcom/sleepycat/b/i/c/b/x;
    //   746: invokevirtual 650	com/sleepycat/b/i/c/b/z:a	(Lcom/sleepycat/b/i/u;Lcom/sleepycat/b/i/c/b/x;)V
    //   749: aload_0
    //   750: getfield 146	com/sleepycat/b/i/c/b/aa:i	Lcom/sleepycat/b/i/c/aj;
    //   753: getfield 681	com/sleepycat/b/i/c/aj:aj	Lcom/sleepycat/b/i/i/f;
    //   756: invokevirtual 684	com/sleepycat/b/i/i/f:a	()V
    //   759: aload_0
    //   760: getfield 200	com/sleepycat/b/i/c/b/aa:j	Lcom/sleepycat/b/i/c/p;
    //   763: astore 6
    //   765: aload 6
    //   767: getfield 824	com/sleepycat/b/i/c/p:a	Lcom/sleepycat/b/i/c/aj;
    //   770: getfield 309	com/sleepycat/b/c/ad:u	Lcom/sleepycat/b/c/m;
    //   773: astore_1
    //   774: aload_1
    //   775: getstatic 827	com/sleepycat/b/i/c/an:a	Lcom/sleepycat/b/b/b;
    //   778: invokevirtual 830	com/sleepycat/b/c/m:a	(Lcom/sleepycat/b/b/b;)Ljava/lang/String;
    //   781: astore 8
    //   783: aload_1
    //   784: getstatic 832	com/sleepycat/b/i/c/an:p	Lcom/sleepycat/b/b/b;
    //   787: invokevirtual 830	com/sleepycat/b/c/m:a	(Lcom/sleepycat/b/b/b;)Ljava/lang/String;
    //   790: astore 7
    //   792: aload 6
    //   794: getfield 824	com/sleepycat/b/i/c/p:a	Lcom/sleepycat/b/i/c/aj;
    //   797: invokevirtual 836	com/sleepycat/b/i/c/aj:af	()Lcom/sleepycat/b/c/i;
    //   800: astore 4
    //   802: new 838	com/sleepycat/b/i/c/q
    //   805: dup
    //   806: invokespecial 839	com/sleepycat/b/i/c/q:<init>	()V
    //   809: astore_1
    //   810: new 428	com/sleepycat/b/i/c/t
    //   813: dup
    //   814: aload 8
    //   816: invokespecial 840	com/sleepycat/b/i/c/t:<init>	(Ljava/lang/String;)V
    //   819: astore 9
    //   821: new 842	com/sleepycat/b/m
    //   824: dup
    //   825: invokespecial 843	com/sleepycat/b/m:<init>	()V
    //   828: astore 8
    //   830: aload_1
    //   831: aload 9
    //   833: aload 8
    //   835: invokevirtual 847	com/sleepycat/b/i/c/q:objectToEntry	(Ljava/lang/Object;Lcom/sleepycat/b/m;)V
    //   838: new 849	com/sleepycat/b/br
    //   841: dup
    //   842: invokespecial 850	com/sleepycat/b/br:<init>	()V
    //   845: astore_1
    //   846: aload_1
    //   847: getstatic 853	com/sleepycat/b/i/c/p:d	Lcom/sleepycat/b/br;
    //   850: getfield 856	com/sleepycat/b/br:e	Lcom/sleepycat/b/u;
    //   853: invokevirtual 859	com/sleepycat/b/br:a	(Lcom/sleepycat/b/u;)Lcom/sleepycat/b/br;
    //   856: pop
    //   857: aload_1
    //   858: getstatic 864	com/sleepycat/b/i/n:a	Lcom/sleepycat/b/i/n;
    //   861: putfield 867	com/sleepycat/b/br:f	Lcom/sleepycat/b/bc;
    //   864: new 869	com/sleepycat/b/i/f/b
    //   867: dup
    //   868: aload 6
    //   870: getfield 824	com/sleepycat/b/i/c/p:a	Lcom/sleepycat/b/i/c/aj;
    //   873: aload_1
    //   874: aload 6
    //   876: getfield 824	com/sleepycat/b/i/c/p:a	Lcom/sleepycat/b/i/c/aj;
    //   879: getfield 113	com/sleepycat/b/i/c/aj:ao	Lcom/sleepycat/b/i/c/b/x;
    //   882: invokespecial 872	com/sleepycat/b/i/f/b:<init>	(Lcom/sleepycat/b/c/ad;Lcom/sleepycat/b/br;Lcom/sleepycat/b/i/c/b/x;)V
    //   885: astore_1
    //   886: aload 4
    //   888: aload_1
    //   889: getstatic 877	com/sleepycat/b/g:a	Lcom/sleepycat/b/g;
    //   892: invokestatic 880	com/sleepycat/b/i/c/p:a	(Lcom/sleepycat/b/c/i;Lcom/sleepycat/b/n/z;Lcom/sleepycat/b/g;)Lcom/sleepycat/b/e;
    //   895: astore 4
    //   897: aload 4
    //   899: getstatic 883	com/sleepycat/b/i/c/p:c	Lcom/sleepycat/b/m;
    //   902: aload 8
    //   904: invokevirtual 888	com/sleepycat/b/e:a	(Lcom/sleepycat/b/m;Lcom/sleepycat/b/m;)Lcom/sleepycat/b/av;
    //   907: astore_3
    //   908: aload_3
    //   909: getstatic 893	com/sleepycat/b/av:a	Lcom/sleepycat/b/av;
    //   912: if_acmpeq +68 -> 980
    //   915: new 103	java/lang/StringBuilder
    //   918: dup
    //   919: ldc_w 895
    //   922: invokespecial 108	java/lang/StringBuilder:<init>	(Ljava/lang/String;)V
    //   925: aload_3
    //   926: invokevirtual 117	java/lang/StringBuilder:append	(Ljava/lang/Object;)Ljava/lang/StringBuilder;
    //   929: invokevirtual 121	java/lang/StringBuilder:toString	()Ljava/lang/String;
    //   932: invokestatic 584	com/sleepycat/b/aa:c	(Ljava/lang/String;)Lcom/sleepycat/b/aa;
    //   935: athrow
    //   936: astore 5
    //   938: aload_1
    //   939: astore_3
    //   940: aload 4
    //   942: astore_2
    //   943: aload 5
    //   945: astore_1
    //   946: aload_2
    //   947: ifnull +7 -> 954
    //   950: aload_2
    //   951: invokevirtual 896	com/sleepycat/b/e:close	()V
    //   954: aload_3
    //   955: ifnull +7 -> 962
    //   958: aload_3
    //   959: invokevirtual 900	com/sleepycat/b/n/z:n	()V
    //   962: aload_1
    //   963: athrow
    //   964: astore_1
    //   965: aload_0
    //   966: getfield 146	com/sleepycat/b/i/c/b/aa:i	Lcom/sleepycat/b/i/c/aj;
    //   969: getfield 657	com/sleepycat/b/c/ad:E	Lcom/sleepycat/b/c/bd;
    //   972: getstatic 662	com/sleepycat/b/c/bg:r	Lcom/sleepycat/b/c/bg;
    //   975: invokevirtual 757	com/sleepycat/b/c/bd:b	(Lcom/sleepycat/b/c/bg;)V
    //   978: aload_1
    //   979: athrow
    //   980: aload 4
    //   982: invokevirtual 896	com/sleepycat/b/e:close	()V
    //   985: aload_1
    //   986: invokevirtual 902	com/sleepycat/b/n/z:m	()J
    //   989: pop2
    //   990: iconst_0
    //   991: ifeq +11 -> 1002
    //   994: new 904	java/lang/NullPointerException
    //   997: dup
    //   998: invokespecial 905	java/lang/NullPointerException:<init>	()V
    //   1001: athrow
    //   1002: iconst_0
    //   1003: ifeq +11 -> 1014
    //   1006: new 904	java/lang/NullPointerException
    //   1009: dup
    //   1010: invokespecial 905	java/lang/NullPointerException:<init>	()V
    //   1013: athrow
    //   1014: aload 6
    //   1016: new 509	com/sleepycat/b/i/c/am
    //   1019: dup
    //   1020: aload 7
    //   1022: aload 6
    //   1024: getfield 824	com/sleepycat/b/i/c/p:a	Lcom/sleepycat/b/i/c/aj;
    //   1027: invokevirtual 907	com/sleepycat/b/i/c/aj:ab	()Ljava/lang/String;
    //   1030: aload 6
    //   1032: getfield 824	com/sleepycat/b/i/c/p:a	Lcom/sleepycat/b/i/c/aj;
    //   1035: invokevirtual 910	com/sleepycat/b/i/c/aj:ac	()I
    //   1038: invokespecial 913	com/sleepycat/b/i/c/am:<init>	(Ljava/lang/String;Ljava/lang/String;I)V
    //   1041: invokevirtual 916	com/sleepycat/b/i/c/p:a	(Lcom/sleepycat/b/i/c/am;)V
    //   1044: aload_0
    //   1045: invokevirtual 719	com/sleepycat/b/i/c/b/aa:h	()Lcom/sleepycat/b/i/c/t;
    //   1048: pop
    //   1049: aload_0
    //   1050: getfield 205	com/sleepycat/b/i/c/b/aa:g	Lcom/sleepycat/b/i/e/n;
    //   1053: invokevirtual 728	com/sleepycat/b/i/e/n:d	()V
    //   1056: aload_0
    //   1057: getfield 586	com/sleepycat/b/i/c/b/aa:d	Lcom/sleepycat/b/i/b/d;
    //   1060: aload_0
    //   1061: getfield 426	com/sleepycat/b/i/c/b/aa:m	Lcom/sleepycat/b/i/c/t;
    //   1064: invokevirtual 919	com/sleepycat/b/i/b/d:a	(Lcom/sleepycat/b/i/c/t;)V
    //   1067: goto -793 -> 274
    //   1070: aload_0
    //   1071: invokespecial 921	com/sleepycat/b/i/c/b/aa:o	()V
    //   1074: goto -800 -> 274
    //   1077: aload_1
    //   1078: getfield 511	com/sleepycat/b/i/c/am:d	Z
    //   1081: ifeq +36 -> 1117
    //   1084: new 103	java/lang/StringBuilder
    //   1087: dup
    //   1088: ldc_w 923
    //   1091: invokespecial 108	java/lang/StringBuilder:<init>	(Ljava/lang/String;)V
    //   1094: aload_0
    //   1095: getfield 153	com/sleepycat/b/i/c/b/aa:a	Lcom/sleepycat/b/i/c/b/x;
    //   1098: getfield 424	com/sleepycat/b/i/c/b/x:a	Ljava/lang/String;
    //   1101: invokevirtual 385	java/lang/StringBuilder:append	(Ljava/lang/String;)Ljava/lang/StringBuilder;
    //   1104: ldc_w 925
    //   1107: invokevirtual 385	java/lang/StringBuilder:append	(Ljava/lang/String;)Ljava/lang/StringBuilder;
    //   1110: invokevirtual 121	java/lang/StringBuilder:toString	()Ljava/lang/String;
    //   1113: invokestatic 584	com/sleepycat/b/aa:c	(Ljava/lang/String;)Lcom/sleepycat/b/aa;
    //   1116: athrow
    //   1117: aload_0
    //   1118: getfield 166	com/sleepycat/b/i/c/b/aa:x	Ljava/util/logging/Logger;
    //   1121: aload_0
    //   1122: getfield 146	com/sleepycat/b/i/c/b/aa:i	Lcom/sleepycat/b/i/c/aj;
    //   1125: new 103	java/lang/StringBuilder
    //   1128: dup
    //   1129: ldc_w 927
    //   1132: invokespecial 108	java/lang/StringBuilder:<init>	(Ljava/lang/String;)V
    //   1135: aload_0
    //   1136: getfield 153	com/sleepycat/b/i/c/b/aa:a	Lcom/sleepycat/b/i/c/b/x;
    //   1139: getfield 424	com/sleepycat/b/i/c/b/x:a	Ljava/lang/String;
    //   1142: invokevirtual 385	java/lang/StringBuilder:append	(Ljava/lang/String;)Ljava/lang/StringBuilder;
    //   1145: ldc_w 929
    //   1148: invokevirtual 385	java/lang/StringBuilder:append	(Ljava/lang/String;)Ljava/lang/StringBuilder;
    //   1151: invokevirtual 121	java/lang/StringBuilder:toString	()Ljava/lang/String;
    //   1154: invokestatic 459	com/sleepycat/b/p/w:c	(Ljava/util/logging/Logger;Lcom/sleepycat/b/c/ad;Ljava/lang/String;)V
    //   1157: aload_0
    //   1158: getfield 146	com/sleepycat/b/i/c/b/aa:i	Lcom/sleepycat/b/i/c/aj;
    //   1161: invokevirtual 539	com/sleepycat/b/i/c/aj:ae	()Ljava/util/Set;
    //   1164: astore_1
    //   1165: aload_1
    //   1166: aload_0
    //   1167: getfield 426	com/sleepycat/b/i/c/b/aa:m	Lcom/sleepycat/b/i/c/t;
    //   1170: invokevirtual 570	com/sleepycat/b/i/c/t:f	()Ljava/util/Set;
    //   1173: invokeinterface 574 2 0
    //   1178: pop
    //   1179: aload_0
    //   1180: getfield 586	com/sleepycat/b/i/c/b/aa:d	Lcom/sleepycat/b/i/b/d;
    //   1183: getfield 591	com/sleepycat/b/i/b/d:g	Lcom/sleepycat/b/i/b/j;
    //   1186: aload_1
    //   1187: invokevirtual 595	com/sleepycat/b/i/b/j:a	(Ljava/util/Set;)V
    //   1190: goto -916 -> 274
    //   1193: new 931	com/sleepycat/b/i/r
    //   1196: dup
    //   1197: ldc_w 933
    //   1200: iconst_1
    //   1201: anewarray 155	java/lang/Object
    //   1204: dup
    //   1205: iconst_0
    //   1206: aload 5
    //   1208: getfield 785	com/sleepycat/b/i/c/b/p:a	I
    //   1211: invokestatic 939	java/lang/Integer:valueOf	(I)Ljava/lang/Integer;
    //   1214: aastore
    //   1215: invokestatic 943	java/lang/String:format	(Ljava/lang/String;[Ljava/lang/Object;)Ljava/lang/String;
    //   1218: invokespecial 944	com/sleepycat/b/i/r:<init>	(Ljava/lang/String;)V
    //   1221: athrow
    //   1222: astore_1
    //   1223: aload_1
    //   1224: invokestatic 613	com/sleepycat/b/aa:a	(Ljava/lang/Exception;)Lcom/sleepycat/b/aa;
    //   1227: athrow
    //   1228: astore_1
    //   1229: aload_0
    //   1230: getfield 146	com/sleepycat/b/i/c/b/aa:i	Lcom/sleepycat/b/i/c/aj;
    //   1233: getfield 657	com/sleepycat/b/c/ad:E	Lcom/sleepycat/b/c/bd;
    //   1236: getstatic 764	com/sleepycat/b/c/bg:s	Lcom/sleepycat/b/c/bg;
    //   1239: invokevirtual 757	com/sleepycat/b/c/bd:b	(Lcom/sleepycat/b/c/bg;)V
    //   1242: aload_1
    //   1243: athrow
    //   1244: aload_3
    //   1245: getstatic 647	com/sleepycat/b/i/u:b	Lcom/sleepycat/b/i/u;
    //   1248: if_acmpne +38 -> 1286
    //   1251: iconst_1
    //   1252: istore 11
    //   1254: iload 11
    //   1256: ifeq +373 -> 1629
    //   1259: aload 5
    //   1261: invokevirtual 783	com/sleepycat/b/i/c/b/p:b	()Z
    //   1264: ifeq +365 -> 1629
    //   1267: getstatic 647	com/sleepycat/b/i/u:b	Lcom/sleepycat/b/i/u;
    //   1270: astore_2
    //   1271: aload_0
    //   1272: getfield 146	com/sleepycat/b/i/c/b/aa:i	Lcom/sleepycat/b/i/c/aj;
    //   1275: getfield 657	com/sleepycat/b/c/ad:E	Lcom/sleepycat/b/c/bd;
    //   1278: getstatic 764	com/sleepycat/b/c/bg:s	Lcom/sleepycat/b/c/bg;
    //   1281: invokevirtual 757	com/sleepycat/b/c/bd:b	(Lcom/sleepycat/b/c/bg;)V
    //   1284: aload_2
    //   1285: areturn
    //   1286: iconst_0
    //   1287: istore 11
    //   1289: goto -35 -> 1254
    //   1292: getstatic 947	com/sleepycat/b/i/c/b/aa$1:a	[I
    //   1295: aload_3
    //   1296: invokevirtual 950	com/sleepycat/b/i/u:ordinal	()I
    //   1299: iaload
    //   1300: istore 11
    //   1302: aload_1
    //   1303: astore_2
    //   1304: iload 11
    //   1306: tableswitch	default:+30->1336, 1:+-825->481, 2:+45->1351, 3:+201->1507, 4:+252->1558
    //   1336: aload_0
    //   1337: getfield 146	com/sleepycat/b/i/c/b/aa:i	Lcom/sleepycat/b/i/c/aj;
    //   1340: getfield 657	com/sleepycat/b/c/ad:E	Lcom/sleepycat/b/c/bd;
    //   1343: getstatic 764	com/sleepycat/b/c/bg:s	Lcom/sleepycat/b/c/bg;
    //   1346: invokevirtual 757	com/sleepycat/b/c/bd:b	(Lcom/sleepycat/b/c/bg;)V
    //   1349: aload_3
    //   1350: areturn
    //   1351: aload_0
    //   1352: getfield 146	com/sleepycat/b/i/c/b/aa:i	Lcom/sleepycat/b/i/c/aj;
    //   1355: getfield 309	com/sleepycat/b/c/ad:u	Lcom/sleepycat/b/c/m;
    //   1358: getstatic 952	com/sleepycat/b/i/c/an:h	Lcom/sleepycat/b/b/c;
    //   1361: invokevirtual 326	com/sleepycat/b/c/m:a	(Lcom/sleepycat/b/b/c;)I
    //   1364: istore 11
    //   1366: new 954	com/sleepycat/b/i/c/n
    //   1369: dup
    //   1370: new 526	com/sleepycat/b/p/au
    //   1373: dup
    //   1374: aload_0
    //   1375: getfield 212	com/sleepycat/b/i/c/b/aa:e	Lcom/sleepycat/b/i/c/b/ag;
    //   1378: getfield 959	com/sleepycat/b/i/c/b/ag:d	Lcom/sleepycat/b/i/c/b/ai;
    //   1381: getfield 963	com/sleepycat/b/i/c/b/ai:d	J
    //   1384: invokespecial 965	com/sleepycat/b/p/au:<init>	(J)V
    //   1387: iload 11
    //   1389: i2l
    //   1390: getstatic 777	java/util/concurrent/TimeUnit:MILLISECONDS	Ljava/util/concurrent/TimeUnit;
    //   1393: invokespecial 968	com/sleepycat/b/i/c/n:<init>	(Lcom/sleepycat/b/p/au;JLjava/util/concurrent/TimeUnit;)V
    //   1396: astore_2
    //   1397: aload_2
    //   1398: aload_0
    //   1399: getfield 146	com/sleepycat/b/i/c/b/aa:i	Lcom/sleepycat/b/i/c/aj;
    //   1402: invokeinterface 972 2 0
    //   1407: aload_0
    //   1408: getfield 146	com/sleepycat/b/i/c/b/aa:i	Lcom/sleepycat/b/i/c/aj;
    //   1411: getfield 975	com/sleepycat/b/c/ad:w	Lcom/sleepycat/b/g/am;
    //   1414: invokevirtual 979	com/sleepycat/b/g/am:b	()V
    //   1417: aload_0
    //   1418: getfield 166	com/sleepycat/b/i/c/b/aa:x	Ljava/util/logging/Logger;
    //   1421: aload_0
    //   1422: getfield 146	com/sleepycat/b/i/c/b/aa:i	Lcom/sleepycat/b/i/c/aj;
    //   1425: new 103	java/lang/StringBuilder
    //   1428: dup
    //   1429: ldc_w 981
    //   1432: invokespecial 108	java/lang/StringBuilder:<init>	(Ljava/lang/String;)V
    //   1435: aload_2
    //   1436: invokevirtual 117	java/lang/StringBuilder:append	(Ljava/lang/Object;)Ljava/lang/StringBuilder;
    //   1439: ldc_w 983
    //   1442: invokevirtual 385	java/lang/StringBuilder:append	(Ljava/lang/String;)Ljava/lang/StringBuilder;
    //   1445: aload_0
    //   1446: getfield 146	com/sleepycat/b/i/c/b/aa:i	Lcom/sleepycat/b/i/c/aj;
    //   1449: getfield 681	com/sleepycat/b/i/c/aj:aj	Lcom/sleepycat/b/i/i/f;
    //   1452: getfield 704	com/sleepycat/b/i/i/f:h	Lcom/sleepycat/b/i/i/p;
    //   1455: invokevirtual 709	com/sleepycat/b/i/i/p:b	()Lcom/sleepycat/b/i/i/m;
    //   1458: invokevirtual 117	java/lang/StringBuilder:append	(Ljava/lang/Object;)Ljava/lang/StringBuilder;
    //   1461: invokevirtual 121	java/lang/StringBuilder:toString	()Ljava/lang/String;
    //   1464: invokestatic 459	com/sleepycat/b/p/w:c	(Ljava/util/logging/Logger;Lcom/sleepycat/b/c/ad;Ljava/lang/String;)V
    //   1467: goto -131 -> 1336
    //   1470: astore_2
    //   1471: aload_0
    //   1472: getfield 166	com/sleepycat/b/i/c/b/aa:x	Ljava/util/logging/Logger;
    //   1475: aload_0
    //   1476: getfield 146	com/sleepycat/b/i/c/b/aa:i	Lcom/sleepycat/b/i/c/aj;
    //   1479: new 103	java/lang/StringBuilder
    //   1482: dup
    //   1483: ldc_w 985
    //   1486: invokespecial 108	java/lang/StringBuilder:<init>	(Ljava/lang/String;)V
    //   1489: aload_2
    //   1490: invokevirtual 988	com/sleepycat/b/i/k:getMessage	()Ljava/lang/String;
    //   1493: invokevirtual 385	java/lang/StringBuilder:append	(Ljava/lang/String;)Ljava/lang/StringBuilder;
    //   1496: invokevirtual 121	java/lang/StringBuilder:toString	()Ljava/lang/String;
    //   1499: invokestatic 990	com/sleepycat/b/p/w:b	(Ljava/util/logging/Logger;Lcom/sleepycat/b/c/ad;Ljava/lang/String;)V
    //   1502: aload_1
    //   1503: astore_2
    //   1504: goto -1023 -> 481
    //   1507: aload_0
    //   1508: getfield 166	com/sleepycat/b/i/c/b/aa:x	Ljava/util/logging/Logger;
    //   1511: aload_0
    //   1512: getfield 146	com/sleepycat/b/i/c/b/aa:i	Lcom/sleepycat/b/i/c/aj;
    //   1515: ldc_w 992
    //   1518: invokestatic 459	com/sleepycat/b/p/w:c	(Ljava/util/logging/Logger;Lcom/sleepycat/b/c/ad;Ljava/lang/String;)V
    //   1521: goto -185 -> 1336
    //   1524: astore_1
    //   1525: aload_0
    //   1526: getfield 166	com/sleepycat/b/i/c/b/aa:x	Ljava/util/logging/Logger;
    //   1529: aload_0
    //   1530: getfield 146	com/sleepycat/b/i/c/b/aa:i	Lcom/sleepycat/b/i/c/aj;
    //   1533: new 103	java/lang/StringBuilder
    //   1536: dup
    //   1537: ldc_w 994
    //   1540: invokespecial 108	java/lang/StringBuilder:<init>	(Ljava/lang/String;)V
    //   1543: aload_1
    //   1544: invokevirtual 995	com/sleepycat/b/i/y:getMessage	()Ljava/lang/String;
    //   1547: invokevirtual 385	java/lang/StringBuilder:append	(Ljava/lang/String;)Ljava/lang/StringBuilder;
    //   1550: invokevirtual 121	java/lang/StringBuilder:toString	()Ljava/lang/String;
    //   1553: invokestatic 990	com/sleepycat/b/p/w:b	(Ljava/util/logging/Logger;Lcom/sleepycat/b/c/ad;Ljava/lang/String;)V
    //   1556: aload_1
    //   1557: athrow
    //   1558: ldc_w 997
    //   1561: invokestatic 584	com/sleepycat/b/aa:c	(Ljava/lang/String;)Lcom/sleepycat/b/aa;
    //   1564: athrow
    //   1565: astore_2
    //   1566: aload_2
    //   1567: invokevirtual 1001	com/sleepycat/b/n:getCause	()Ljava/lang/Throwable;
    //   1570: astore_1
    //   1571: aload_1
    //   1572: ifnull +55 -> 1627
    //   1575: aload_1
    //   1576: invokevirtual 159	java/lang/Object:getClass	()Ljava/lang/Class;
    //   1579: ldc_w 1003
    //   1582: if_acmpne +45 -> 1627
    //   1585: aload 5
    //   1587: invokevirtual 771	com/sleepycat/b/i/c/b/p:a	()I
    //   1590: ifle +37 -> 1627
    //   1593: aload_0
    //   1594: getfield 166	com/sleepycat/b/i/c/b/aa:x	Ljava/util/logging/Logger;
    //   1597: aload_0
    //   1598: getfield 146	com/sleepycat/b/i/c/b/aa:i	Lcom/sleepycat/b/i/c/aj;
    //   1601: new 103	java/lang/StringBuilder
    //   1604: dup
    //   1605: ldc_w 1005
    //   1608: invokespecial 108	java/lang/StringBuilder:<init>	(Ljava/lang/String;)V
    //   1611: aload_1
    //   1612: invokevirtual 1008	java/lang/Throwable:getMessage	()Ljava/lang/String;
    //   1615: invokevirtual 385	java/lang/StringBuilder:append	(Ljava/lang/String;)Ljava/lang/StringBuilder;
    //   1618: invokevirtual 121	java/lang/StringBuilder:toString	()Ljava/lang/String;
    //   1621: invokestatic 990	com/sleepycat/b/p/w:b	(Ljava/util/logging/Logger;Lcom/sleepycat/b/c/ad;Ljava/lang/String;)V
    //   1624: goto -1143 -> 481
    //   1627: aload_2
    //   1628: athrow
    //   1629: aload_0
    //   1630: getfield 146	com/sleepycat/b/i/c/b/aa:i	Lcom/sleepycat/b/i/c/aj;
    //   1633: getfield 657	com/sleepycat/b/c/ad:E	Lcom/sleepycat/b/c/bd;
    //   1636: getstatic 764	com/sleepycat/b/c/bg:s	Lcom/sleepycat/b/c/bg;
    //   1639: invokevirtual 757	com/sleepycat/b/c/bd:b	(Lcom/sleepycat/b/c/bg;)V
    //   1642: aload_1
    //   1643: ifnull +44 -> 1687
    //   1646: aload_0
    //   1647: getfield 166	com/sleepycat/b/i/c/b/aa:x	Ljava/util/logging/Logger;
    //   1650: aload_0
    //   1651: getfield 146	com/sleepycat/b/i/c/b/aa:i	Lcom/sleepycat/b/i/c/aj;
    //   1654: new 103	java/lang/StringBuilder
    //   1657: dup
    //   1658: ldc_w 1010
    //   1661: invokespecial 108	java/lang/StringBuilder:<init>	(Ljava/lang/String;)V
    //   1664: iload 10
    //   1666: invokevirtual 794	java/lang/StringBuilder:append	(I)Ljava/lang/StringBuilder;
    //   1669: ldc_w 1012
    //   1672: invokevirtual 385	java/lang/StringBuilder:append	(Ljava/lang/String;)Ljava/lang/StringBuilder;
    //   1675: aload_1
    //   1676: invokevirtual 117	java/lang/StringBuilder:append	(Ljava/lang/Object;)Ljava/lang/StringBuilder;
    //   1679: invokevirtual 121	java/lang/StringBuilder:toString	()Ljava/lang/String;
    //   1682: invokestatic 990	com/sleepycat/b/p/w:b	(Ljava/util/logging/Logger;Lcom/sleepycat/b/c/ad;Ljava/lang/String;)V
    //   1685: aload_1
    //   1686: athrow
    //   1687: new 1014	com/sleepycat/b/i/af
    //   1690: dup
    //   1691: aconst_null
    //   1692: aload_0
    //   1693: getfield 146	com/sleepycat/b/i/c/b/aa:i	Lcom/sleepycat/b/i/c/aj;
    //   1696: getfield 1017	com/sleepycat/b/i/c/aj:ap	Lcom/sleepycat/b/i/c/b/z;
    //   1699: invokevirtual 1020	com/sleepycat/b/i/c/b/z:b	()Lcom/sleepycat/b/i/ab;
    //   1702: invokespecial 1023	com/sleepycat/b/i/af:<init>	(Lcom/sleepycat/b/n/q;Lcom/sleepycat/b/i/ab;)V
    //   1705: athrow
    //   1706: astore_1
    //   1707: aconst_null
    //   1708: astore_2
    //   1709: goto -763 -> 946
    //   1712: astore 4
    //   1714: aconst_null
    //   1715: astore_2
    //   1716: aload_1
    //   1717: astore_3
    //   1718: aload 4
    //   1720: astore_1
    //   1721: goto -775 -> 946
    // Local variable table:
    //   start	length	slot	name	signature
    //   0	1724	0	this	aa
    //   0	1724	1	parambc	com.sleepycat.b.bc
    //   0	1724	2	paramp	com.sleepycat.b.i.p
    //   1	1717	3	localObject1	Object
    //   800	181	4	localObject2	Object
    //   1712	7	4	localObject3	Object
    //   16	456	5	localp	p
    //   936	650	5	localObject4	Object
    //   763	268	6	localp1	com.sleepycat.b.i.c.p
    //   790	231	7	str	String
    //   781	122	8	localObject5	Object
    //   819	13	9	localt	com.sleepycat.b.i.c.t
    //   405	1260	10	i1	int
    //   1252	136	11	i2	int
    //   245	11	12	l1	long
    //   439	11	14	bool	boolean
    // Exception table:
    //   from	to	target	type
    //   897	936	936	finally
    //   980	985	936	finally
    //   84	274	964	finally
    //   274	330	964	finally
    //   492	553	964	finally
    //   557	864	964	finally
    //   950	954	964	finally
    //   958	962	964	finally
    //   962	964	964	finally
    //   994	1002	964	finally
    //   1006	1014	964	finally
    //   1014	1067	964	finally
    //   1070	1074	964	finally
    //   1077	1117	964	finally
    //   1117	1190	964	finally
    //   423	449	1222	java/lang/InterruptedException
    //   454	479	1222	java/lang/InterruptedException
    //   1193	1222	1222	java/lang/InterruptedException
    //   1244	1251	1222	java/lang/InterruptedException
    //   1259	1271	1222	java/lang/InterruptedException
    //   1292	1302	1222	java/lang/InterruptedException
    //   1351	1467	1222	java/lang/InterruptedException
    //   1507	1521	1222	java/lang/InterruptedException
    //   1558	1565	1222	java/lang/InterruptedException
    //   423	449	1228	finally
    //   454	479	1228	finally
    //   1193	1222	1228	finally
    //   1223	1228	1228	finally
    //   1244	1251	1228	finally
    //   1259	1271	1228	finally
    //   1292	1302	1228	finally
    //   1351	1467	1228	finally
    //   1471	1502	1228	finally
    //   1507	1521	1228	finally
    //   1525	1558	1228	finally
    //   1558	1565	1228	finally
    //   1566	1571	1228	finally
    //   1575	1624	1228	finally
    //   1627	1629	1228	finally
    //   423	449	1470	com/sleepycat/b/i/k
    //   454	479	1470	com/sleepycat/b/i/k
    //   1193	1222	1470	com/sleepycat/b/i/k
    //   1244	1251	1470	com/sleepycat/b/i/k
    //   1259	1271	1470	com/sleepycat/b/i/k
    //   1292	1302	1470	com/sleepycat/b/i/k
    //   1351	1467	1470	com/sleepycat/b/i/k
    //   1507	1521	1470	com/sleepycat/b/i/k
    //   1558	1565	1470	com/sleepycat/b/i/k
    //   423	449	1524	com/sleepycat/b/i/y
    //   454	479	1524	com/sleepycat/b/i/y
    //   1193	1222	1524	com/sleepycat/b/i/y
    //   1244	1251	1524	com/sleepycat/b/i/y
    //   1259	1271	1524	com/sleepycat/b/i/y
    //   1292	1302	1524	com/sleepycat/b/i/y
    //   1351	1467	1524	com/sleepycat/b/i/y
    //   1507	1521	1524	com/sleepycat/b/i/y
    //   1558	1565	1524	com/sleepycat/b/i/y
    //   423	449	1565	com/sleepycat/b/n
    //   454	479	1565	com/sleepycat/b/n
    //   1193	1222	1565	com/sleepycat/b/n
    //   1244	1251	1565	com/sleepycat/b/n
    //   1259	1271	1565	com/sleepycat/b/n
    //   1292	1302	1565	com/sleepycat/b/n
    //   1351	1467	1565	com/sleepycat/b/n
    //   1507	1521	1565	com/sleepycat/b/n
    //   1558	1565	1565	com/sleepycat/b/n
    //   864	886	1706	finally
    //   886	897	1712	finally
    //   985	990	1712	finally
  }
  
  public final Logger a()
  {
    return this.x;
  }
  
  public final void a(Exception paramException)
  {
    com.sleepycat.b.i.h.t localt = this.k;
    this.k = new com.sleepycat.b.i.h.t(this.i);
    if (localt.getCount() != 0L) {
      localt.a(paramException);
    }
  }
  
  public final UUID b()
  {
    if (this.m == null) {
      throw com.sleepycat.b.aa.c("Group info is not available");
    }
    return this.m.b;
  }
  
  protected final int c()
  {
    return d() * 4;
  }
  
  public final int d()
  {
    return this.i.u.a(an.y);
  }
  
  public final am[] e()
  {
    Object localObject = this.m.d();
    am[] arrayOfam = new am[((Set)localObject).size()];
    localObject = ((Set)localObject).iterator();
    int i1 = 0;
    while (((Iterator)localObject).hasNext())
    {
      arrayOfam[i1] = ((am)((Iterator)localObject).next());
      i1 += 1;
    }
    return arrayOfam;
  }
  
  public final String f()
  {
    if (this.g.j().b == -1) {
      return null;
    }
    return this.g.j().a;
  }
  
  public final com.sleepycat.b.p.au g()
  {
    return this.i.ak.a();
  }
  
  public final com.sleepycat.b.i.c.t h()
  {
    Object localObject = this.j;
    com.sleepycat.b.i.n localn = new com.sleepycat.b.i.n();
    this.m = com.sleepycat.b.i.c.p.a(((com.sleepycat.b.i.c.p)localObject).a, ((com.sleepycat.b.i.c.p)localObject).a.u.a(an.a), localn);
    this.d.a(this.m);
    if (this.a.a())
    {
      localObject = this.m.a(this.a.a);
      if (localObject != null) {
        this.a.a(((am)localObject).a);
      }
    }
    return this.m;
  }
  
  public final void i()
  {
    try
    {
      this.q = null;
      return;
    }
    finally
    {
      localObject = finally;
      throw ((Throwable)localObject);
    }
  }
  
  final void j()
  {
    this.r.a(this.m);
  }
  
  public final boolean k()
  {
    if (this.E.get()) {
      return true;
    }
    com.sleepycat.b.i.c.aj localaj = this.i;
    if ((localaj.a == com.sleepycat.b.c.o.d) || ((localaj.a == com.sleepycat.b.c.o.c) && (localaj.F != null))) {}
    for (int i1 = 1; i1 != 0; i1 = 0)
    {
      this.F = this.i.F;
      return true;
    }
    return false;
  }
  
  public final void l()
  {
    if (n()) {
      return;
    }
    com.sleepycat.b.p.w.c(this.x, this.i, "Shutting down node " + this.a);
    if (this.i.j())
    {
      localObject2 = this.t;
      localObject1 = this.F;
      if (localObject1 != null) {
        break label119;
      }
      localObject1 = com.sleepycat.b.i.d.d.a;
    }
    for (;;)
    {
      ((w)localObject2).a((com.sleepycat.b.i.d.d)localObject1);
      this.c.b = false;
      if (this.d != null) {
        this.d.c();
      }
      localObject1 = this.f;
      if (((m)localObject1).a.E.get()) {
        break;
      }
      throw com.sleepycat.b.aa.c("Rep node is still active");
      label119:
      if ((localObject1 instanceof com.sleepycat.b.i.d)) {
        localObject1 = com.sleepycat.b.i.d.d.c;
      } else {
        localObject1 = com.sleepycat.b.i.d.d.b;
      }
    }
    ((m)localObject1).b.clear();
    ((m)localObject1).b.add(com.sleepycat.b.i.h.q.a);
    if ((this.s >= 0L) && (this.h.a().a())) {
      join();
    }
    Object localObject2 = this.e;
    if (!((ag)localObject2).a.E.get()) {
      throw com.sleepycat.b.aa.c("Rep node must have initiated the shutdown.");
    }
    Object localObject3 = ((ag)localObject2).d;
    Object localObject1 = ag.a(((ai)localObject3).k).F;
    if ((localObject1 instanceof com.sleepycat.b.aa)) {}
    for (localObject1 = (com.sleepycat.b.aa)localObject1;; localObject1 = com.sleepycat.b.aa.a("Node: " + ag.a(((ai)localObject3).k).a + " was shut down.", (Exception)localObject1))
    {
      ((ai)localObject3).a((com.sleepycat.b.n)localObject1);
      if (Thread.currentThread() != ((ag)localObject2).a)
      {
        com.sleepycat.b.i.h.q.a(((ag)localObject2).c);
        ((ag)localObject2).a.l.a();
      }
      a(this.x);
      com.sleepycat.b.p.w.c(this.x, this.i, "RepNode main thread: " + getName() + " exited.");
      if (this.J != null) {
        this.J.c.a("LDiff");
      }
      if (this.o != null) {
        this.o.b();
      }
      if (this.L != null) {
        this.L.b.a("BinaryNodeState");
      }
      if (this.K != null) {
        this.c.a("NodeState");
      }
      if (this.M != null) {
        this.c.a("Group");
      }
      localObject3 = this.q;
      if (localObject3 != null)
      {
        localObject2 = this.F;
        localObject1 = localObject2;
        if (localObject2 == null) {
          localObject1 = new com.sleepycat.b.i.l("shutting down");
        }
        ((u)localObject3).a((Exception)localObject1);
      }
      this.c.b();
      com.sleepycat.b.p.w.c(this.x, this.i, this.a + " shutdown completed.");
      this.g.a(null, x.c);
      this.k.a(this.F);
      this.w.cancel();
      if (this.N != null) {
        this.N.a();
      }
      this.v.cancel();
      return;
    }
  }
  
  public final long m()
  {
    long l1 = this.i.ag.a();
    if (l1 != 0L)
    {
      com.sleepycat.b.p.au localau = new com.sleepycat.b.p.au(l1);
      if (localau.b(this.r.a) < 0) {
        return this.i.aj.a(localau);
      }
    }
    return this.r.c();
  }
  
  /* Error */
  public void run()
  {
    // Byte code:
    //   0: aconst_null
    //   1: astore_2
    //   2: aload_0
    //   3: getfield 166	com/sleepycat/b/i/c/b/aa:x	Ljava/util/logging/Logger;
    //   6: aload_0
    //   7: getfield 146	com/sleepycat/b/i/c/b/aa:i	Lcom/sleepycat/b/i/c/aj;
    //   10: new 103	java/lang/StringBuilder
    //   13: dup
    //   14: ldc_w 1222
    //   17: invokespecial 108	java/lang/StringBuilder:<init>	(Ljava/lang/String;)V
    //   20: aload_0
    //   21: getfield 153	com/sleepycat/b/i/c/b/aa:a	Lcom/sleepycat/b/i/c/b/x;
    //   24: getfield 424	com/sleepycat/b/i/c/b/x:a	Ljava/lang/String;
    //   27: invokevirtual 385	java/lang/StringBuilder:append	(Ljava/lang/String;)Ljava/lang/StringBuilder;
    //   30: ldc_w 1224
    //   33: invokevirtual 385	java/lang/StringBuilder:append	(Ljava/lang/String;)Ljava/lang/StringBuilder;
    //   36: invokevirtual 121	java/lang/StringBuilder:toString	()Ljava/lang/String;
    //   39: invokestatic 459	com/sleepycat/b/p/w:c	(Ljava/util/logging/Logger;Lcom/sleepycat/b/c/ad;Ljava/lang/String;)V
    //   42: aload_0
    //   43: invokevirtual 1226	com/sleepycat/b/i/c/b/aa:k	()Z
    //   46: ifne +1610 -> 1656
    //   49: aload_0
    //   50: getfield 231	com/sleepycat/b/i/c/b/aa:h	Lcom/sleepycat/b/i/c/b/z;
    //   53: invokevirtual 643	com/sleepycat/b/i/c/b/z:a	()Lcom/sleepycat/b/i/u;
    //   56: getstatic 647	com/sleepycat/b/i/u:b	Lcom/sleepycat/b/i/u;
    //   59: if_acmpeq +16 -> 75
    //   62: aload_0
    //   63: getfield 231	com/sleepycat/b/i/c/b/aa:h	Lcom/sleepycat/b/i/c/b/z;
    //   66: getstatic 647	com/sleepycat/b/i/u:b	Lcom/sleepycat/b/i/u;
    //   69: getstatic 97	com/sleepycat/b/i/c/b/x:c	Lcom/sleepycat/b/i/c/b/x;
    //   72: invokevirtual 650	com/sleepycat/b/i/c/b/z:a	(Lcom/sleepycat/b/i/u;Lcom/sleepycat/b/i/c/b/x;)V
    //   75: aload_0
    //   76: getfield 205	com/sleepycat/b/i/c/b/aa:g	Lcom/sleepycat/b/i/e/n;
    //   79: invokevirtual 598	com/sleepycat/b/i/e/n:j	()Lcom/sleepycat/b/i/c/b/x;
    //   82: invokevirtual 599	com/sleepycat/b/i/c/b/x:a	()Z
    //   85: ifne +13 -> 98
    //   88: aload_0
    //   89: getfield 205	com/sleepycat/b/i/c/b/aa:g	Lcom/sleepycat/b/i/e/n;
    //   92: invokevirtual 1227	com/sleepycat/b/i/e/n:c	()Z
    //   95: ifeq +214 -> 309
    //   98: aload_0
    //   99: getfield 153	com/sleepycat/b/i/c/b/aa:a	Lcom/sleepycat/b/i/c/b/x;
    //   102: invokevirtual 599	com/sleepycat/b/i/c/b/x:a	()Z
    //   105: ifeq +93 -> 198
    //   108: aload_0
    //   109: invokespecial 921	com/sleepycat/b/i/c/b/aa:o	()V
    //   112: aload_0
    //   113: invokevirtual 1226	com/sleepycat/b/i/c/b/aa:k	()Z
    //   116: istore 4
    //   118: iload 4
    //   120: ifeq +189 -> 309
    //   123: aload_0
    //   124: getfield 166	com/sleepycat/b/i/c/b/aa:x	Ljava/util/logging/Logger;
    //   127: aload_0
    //   128: getfield 146	com/sleepycat/b/i/c/b/aa:i	Lcom/sleepycat/b/i/c/aj;
    //   131: ldc_w 1229
    //   134: invokestatic 459	com/sleepycat/b/p/w:c	(Ljava/util/logging/Logger;Lcom/sleepycat/b/c/ad;Ljava/lang/String;)V
    //   137: iconst_0
    //   138: ifeq +1387 -> 1525
    //   141: aload_0
    //   142: getfield 166	com/sleepycat/b/i/c/b/aa:x	Ljava/util/logging/Logger;
    //   145: aload_0
    //   146: getfield 146	com/sleepycat/b/i/c/b/aa:i	Lcom/sleepycat/b/i/c/aj;
    //   149: new 103	java/lang/StringBuilder
    //   152: dup
    //   153: ldc_w 1231
    //   156: invokespecial 108	java/lang/StringBuilder:<init>	(Ljava/lang/String;)V
    //   159: aload_0
    //   160: getfield 146	com/sleepycat/b/i/c/b/aa:i	Lcom/sleepycat/b/i/c/aj;
    //   163: invokevirtual 1234	com/sleepycat/b/i/c/aj:ai	()Ljava/lang/String;
    //   166: invokevirtual 385	java/lang/StringBuilder:append	(Ljava/lang/String;)Ljava/lang/StringBuilder;
    //   169: invokevirtual 121	java/lang/StringBuilder:toString	()Ljava/lang/String;
    //   172: invokestatic 459	com/sleepycat/b/p/w:c	(Ljava/util/logging/Logger;Lcom/sleepycat/b/c/ad;Ljava/lang/String;)V
    //   175: aconst_null
    //   176: athrow
    //   177: astore_1
    //   178: aload_0
    //   179: getfield 231	com/sleepycat/b/i/c/b/aa:h	Lcom/sleepycat/b/i/c/b/z;
    //   182: astore_1
    //   183: getstatic 1235	com/sleepycat/b/i/u:a	Lcom/sleepycat/b/i/u;
    //   186: astore_2
    //   187: getstatic 97	com/sleepycat/b/i/c/b/x:c	Lcom/sleepycat/b/i/c/b/x;
    //   190: astore_3
    //   191: aload_1
    //   192: aload_2
    //   193: aload_3
    //   194: invokevirtual 650	com/sleepycat/b/i/c/b/z:a	(Lcom/sleepycat/b/i/u;Lcom/sleepycat/b/i/c/b/x;)V
    //   197: return
    //   198: aload_0
    //   199: getfield 586	com/sleepycat/b/i/c/b/aa:d	Lcom/sleepycat/b/i/b/d;
    //   202: aload_0
    //   203: getfield 426	com/sleepycat/b/i/c/b/aa:m	Lcom/sleepycat/b/i/c/t;
    //   206: aload_0
    //   207: getfield 138	com/sleepycat/b/i/c/b/aa:I	Lcom/sleepycat/b/i/p;
    //   210: invokevirtual 1238	com/sleepycat/b/i/b/d:a	(Lcom/sleepycat/b/i/c/t;Lcom/sleepycat/b/i/p;)V
    //   213: aload_0
    //   214: getstatic 136	com/sleepycat/b/i/p:b	Lcom/sleepycat/b/i/p;
    //   217: putfield 138	com/sleepycat/b/i/c/b/aa:I	Lcom/sleepycat/b/i/p;
    //   220: goto -108 -> 112
    //   223: astore_1
    //   224: aload_0
    //   225: getfield 166	com/sleepycat/b/i/c/b/aa:x	Ljava/util/logging/Logger;
    //   228: aload_0
    //   229: getfield 146	com/sleepycat/b/i/c/b/aa:i	Lcom/sleepycat/b/i/c/aj;
    //   232: ldc_w 1240
    //   235: invokestatic 1242	com/sleepycat/b/p/w:d	(Ljava/util/logging/Logger;Lcom/sleepycat/b/c/ad;Ljava/lang/String;)V
    //   238: aload_0
    //   239: getfield 166	com/sleepycat/b/i/c/b/aa:x	Ljava/util/logging/Logger;
    //   242: aload_0
    //   243: getfield 146	com/sleepycat/b/i/c/b/aa:i	Lcom/sleepycat/b/i/c/aj;
    //   246: ldc_w 1229
    //   249: invokestatic 459	com/sleepycat/b/p/w:c	(Ljava/util/logging/Logger;Lcom/sleepycat/b/c/ad;Ljava/lang/String;)V
    //   252: iconst_0
    //   253: ifeq +748 -> 1001
    //   256: aload_0
    //   257: getfield 166	com/sleepycat/b/i/c/b/aa:x	Ljava/util/logging/Logger;
    //   260: aload_0
    //   261: getfield 146	com/sleepycat/b/i/c/b/aa:i	Lcom/sleepycat/b/i/c/aj;
    //   264: new 103	java/lang/StringBuilder
    //   267: dup
    //   268: ldc_w 1231
    //   271: invokespecial 108	java/lang/StringBuilder:<init>	(Ljava/lang/String;)V
    //   274: aload_0
    //   275: getfield 146	com/sleepycat/b/i/c/b/aa:i	Lcom/sleepycat/b/i/c/aj;
    //   278: invokevirtual 1234	com/sleepycat/b/i/c/aj:ai	()Ljava/lang/String;
    //   281: invokevirtual 385	java/lang/StringBuilder:append	(Ljava/lang/String;)Ljava/lang/StringBuilder;
    //   284: invokevirtual 121	java/lang/StringBuilder:toString	()Ljava/lang/String;
    //   287: invokestatic 459	com/sleepycat/b/p/w:c	(Ljava/util/logging/Logger;Lcom/sleepycat/b/c/ad;Ljava/lang/String;)V
    //   290: aconst_null
    //   291: athrow
    //   292: astore_1
    //   293: aload_0
    //   294: getfield 231	com/sleepycat/b/i/c/b/aa:h	Lcom/sleepycat/b/i/c/b/z;
    //   297: astore_1
    //   298: getstatic 1235	com/sleepycat/b/i/u:a	Lcom/sleepycat/b/i/u;
    //   301: astore_2
    //   302: getstatic 97	com/sleepycat/b/i/c/b/x:c	Lcom/sleepycat/b/i/c/b/x;
    //   305: astore_3
    //   306: goto -115 -> 191
    //   309: aload_0
    //   310: getfield 205	com/sleepycat/b/i/c/b/aa:g	Lcom/sleepycat/b/i/e/n;
    //   313: invokevirtual 822	com/sleepycat/b/i/e/n:f	()V
    //   316: aload_0
    //   317: getfield 205	com/sleepycat/b/i/c/b/aa:g	Lcom/sleepycat/b/i/e/n;
    //   320: invokevirtual 1243	com/sleepycat/b/i/e/n:b	()Z
    //   323: ifeq +235 -> 558
    //   326: aload_0
    //   327: getfield 146	com/sleepycat/b/i/c/b/aa:i	Lcom/sleepycat/b/i/c/aj;
    //   330: getfield 681	com/sleepycat/b/i/c/aj:aj	Lcom/sleepycat/b/i/i/f;
    //   333: invokevirtual 684	com/sleepycat/b/i/i/f:a	()V
    //   336: aload_0
    //   337: getfield 212	com/sleepycat/b/i/c/b/aa:e	Lcom/sleepycat/b/i/c/b/ag;
    //   340: astore_1
    //   341: aload_1
    //   342: aconst_null
    //   343: putfield 1246	com/sleepycat/b/i/c/b/ag:g	Lcom/sleepycat/b/i/c/b/aj;
    //   346: aload_1
    //   347: getfield 1249	com/sleepycat/b/i/c/b/ag:b	Lcom/sleepycat/b/i/c/b/ac;
    //   350: invokevirtual 1252	com/sleepycat/b/i/c/b/ac:a	()V
    //   353: aload_1
    //   354: getfield 959	com/sleepycat/b/i/c/b/ag:d	Lcom/sleepycat/b/i/c/b/ai;
    //   357: new 626	com/sleepycat/b/i/k
    //   360: dup
    //   361: aload_1
    //   362: getfield 1135	com/sleepycat/b/i/c/b/ag:a	Lcom/sleepycat/b/i/c/b/aa;
    //   365: getfield 146	com/sleepycat/b/i/c/b/aa:i	Lcom/sleepycat/b/i/c/aj;
    //   368: getfield 1017	com/sleepycat/b/i/c/aj:ap	Lcom/sleepycat/b/i/c/b/z;
    //   371: invokevirtual 1020	com/sleepycat/b/i/c/b/z:b	()Lcom/sleepycat/b/i/ab;
    //   374: invokespecial 1255	com/sleepycat/b/i/k:<init>	(Lcom/sleepycat/b/i/ab;)V
    //   377: invokevirtual 1145	com/sleepycat/b/i/c/b/ai:a	(Lcom/sleepycat/b/n;)V
    //   380: aload_0
    //   381: getfield 231	com/sleepycat/b/i/c/b/aa:h	Lcom/sleepycat/b/i/c/b/z;
    //   384: getstatic 675	com/sleepycat/b/i/u:c	Lcom/sleepycat/b/i/u;
    //   387: aload_0
    //   388: getfield 205	com/sleepycat/b/i/c/b/aa:g	Lcom/sleepycat/b/i/e/n;
    //   391: invokevirtual 677	com/sleepycat/b/i/e/n:h	()Lcom/sleepycat/b/i/c/b/x;
    //   394: invokevirtual 650	com/sleepycat/b/i/c/b/z:a	(Lcom/sleepycat/b/i/u;Lcom/sleepycat/b/i/c/b/x;)V
    //   397: aload_0
    //   398: getfield 219	com/sleepycat/b/i/c/b/aa:f	Lcom/sleepycat/b/i/c/b/m;
    //   401: invokevirtual 1256	com/sleepycat/b/i/c/b/m:b	()V
    //   404: aload_0
    //   405: getfield 231	com/sleepycat/b/i/c/b/aa:h	Lcom/sleepycat/b/i/c/b/z;
    //   408: getstatic 647	com/sleepycat/b/i/u:b	Lcom/sleepycat/b/i/u;
    //   411: getstatic 97	com/sleepycat/b/i/c/b/x:c	Lcom/sleepycat/b/i/c/b/x;
    //   414: invokevirtual 650	com/sleepycat/b/i/c/b/z:a	(Lcom/sleepycat/b/i/u;Lcom/sleepycat/b/i/c/b/x;)V
    //   417: aload_0
    //   418: getfield 146	com/sleepycat/b/i/c/b/aa:i	Lcom/sleepycat/b/i/c/aj;
    //   421: getfield 681	com/sleepycat/b/i/c/aj:aj	Lcom/sleepycat/b/i/i/f;
    //   424: invokevirtual 1257	com/sleepycat/b/i/i/f:b	()V
    //   427: getstatic 91	com/sleepycat/b/i/c/b/aa:C	Z
    //   430: ifne +8 -> 438
    //   433: aload_0
    //   434: invokespecial 1259	com/sleepycat/b/i/c/b/aa:p	()Z
    //   437: pop
    //   438: aload_0
    //   439: new 214	com/sleepycat/b/i/c/b/m
    //   442: dup
    //   443: aload_0
    //   444: invokespecial 217	com/sleepycat/b/i/c/b/m:<init>	(Lcom/sleepycat/b/i/c/b/aa;)V
    //   447: putfield 219	com/sleepycat/b/i/c/b/aa:f	Lcom/sleepycat/b/i/c/b/m;
    //   450: goto -408 -> 42
    //   453: astore_1
    //   454: aload_0
    //   455: aload_1
    //   456: putfield 1093	com/sleepycat/b/p/aj:F	Ljava/lang/Exception;
    //   459: aload_0
    //   460: getfield 166	com/sleepycat/b/i/c/b/aa:x	Ljava/util/logging/Logger;
    //   463: aload_0
    //   464: getfield 146	com/sleepycat/b/i/c/b/aa:i	Lcom/sleepycat/b/i/c/aj;
    //   467: new 103	java/lang/StringBuilder
    //   470: dup
    //   471: ldc_w 1261
    //   474: invokespecial 108	java/lang/StringBuilder:<init>	(Ljava/lang/String;)V
    //   477: aload_1
    //   478: invokevirtual 117	java/lang/StringBuilder:append	(Ljava/lang/Object;)Ljava/lang/StringBuilder;
    //   481: invokevirtual 121	java/lang/StringBuilder:toString	()Ljava/lang/String;
    //   484: invokestatic 1242	com/sleepycat/b/p/w:d	(Ljava/util/logging/Logger;Lcom/sleepycat/b/c/ad;Ljava/lang/String;)V
    //   487: aload_0
    //   488: getfield 166	com/sleepycat/b/i/c/b/aa:x	Ljava/util/logging/Logger;
    //   491: aload_0
    //   492: getfield 146	com/sleepycat/b/i/c/b/aa:i	Lcom/sleepycat/b/i/c/aj;
    //   495: ldc_w 1229
    //   498: invokestatic 459	com/sleepycat/b/p/w:c	(Ljava/util/logging/Logger;Lcom/sleepycat/b/c/ad;Ljava/lang/String;)V
    //   501: iconst_0
    //   502: ifeq +630 -> 1132
    //   505: aload_0
    //   506: getfield 166	com/sleepycat/b/i/c/b/aa:x	Ljava/util/logging/Logger;
    //   509: aload_0
    //   510: getfield 146	com/sleepycat/b/i/c/b/aa:i	Lcom/sleepycat/b/i/c/aj;
    //   513: new 103	java/lang/StringBuilder
    //   516: dup
    //   517: ldc_w 1231
    //   520: invokespecial 108	java/lang/StringBuilder:<init>	(Ljava/lang/String;)V
    //   523: aload_0
    //   524: getfield 146	com/sleepycat/b/i/c/b/aa:i	Lcom/sleepycat/b/i/c/aj;
    //   527: invokevirtual 1234	com/sleepycat/b/i/c/aj:ai	()Ljava/lang/String;
    //   530: invokevirtual 385	java/lang/StringBuilder:append	(Ljava/lang/String;)Ljava/lang/StringBuilder;
    //   533: invokevirtual 121	java/lang/StringBuilder:toString	()Ljava/lang/String;
    //   536: invokestatic 459	com/sleepycat/b/p/w:c	(Ljava/util/logging/Logger;Lcom/sleepycat/b/c/ad;Ljava/lang/String;)V
    //   539: aconst_null
    //   540: athrow
    //   541: astore_1
    //   542: aload_0
    //   543: getfield 231	com/sleepycat/b/i/c/b/aa:h	Lcom/sleepycat/b/i/c/b/z;
    //   546: astore_1
    //   547: getstatic 1235	com/sleepycat/b/i/u:a	Lcom/sleepycat/b/i/u;
    //   550: astore_2
    //   551: getstatic 97	com/sleepycat/b/i/c/b/x:c	Lcom/sleepycat/b/i/c/b/x;
    //   554: astore_3
    //   555: goto -364 -> 191
    //   558: aload_0
    //   559: getfield 212	com/sleepycat/b/i/c/b/aa:e	Lcom/sleepycat/b/i/c/b/ag;
    //   562: invokevirtual 1262	com/sleepycat/b/i/c/b/ag:d	()V
    //   565: aload_0
    //   566: getfield 212	com/sleepycat/b/i/c/b/aa:e	Lcom/sleepycat/b/i/c/b/ag;
    //   569: invokevirtual 1263	com/sleepycat/b/i/c/b/ag:a	()V
    //   572: goto -530 -> 42
    //   575: astore_1
    //   576: aload_0
    //   577: aload_1
    //   578: putfield 1093	com/sleepycat/b/p/aj:F	Ljava/lang/Exception;
    //   581: aload_0
    //   582: getfield 166	com/sleepycat/b/i/c/b/aa:x	Ljava/util/logging/Logger;
    //   585: aload_0
    //   586: getfield 146	com/sleepycat/b/i/c/b/aa:i	Lcom/sleepycat/b/i/c/aj;
    //   589: ldc_w 1229
    //   592: invokestatic 459	com/sleepycat/b/p/w:c	(Ljava/util/logging/Logger;Lcom/sleepycat/b/c/ad;Ljava/lang/String;)V
    //   595: iconst_0
    //   596: ifeq +667 -> 1263
    //   599: aload_0
    //   600: getfield 166	com/sleepycat/b/i/c/b/aa:x	Ljava/util/logging/Logger;
    //   603: aload_0
    //   604: getfield 146	com/sleepycat/b/i/c/b/aa:i	Lcom/sleepycat/b/i/c/aj;
    //   607: new 103	java/lang/StringBuilder
    //   610: dup
    //   611: ldc_w 1231
    //   614: invokespecial 108	java/lang/StringBuilder:<init>	(Ljava/lang/String;)V
    //   617: aload_0
    //   618: getfield 146	com/sleepycat/b/i/c/b/aa:i	Lcom/sleepycat/b/i/c/aj;
    //   621: invokevirtual 1234	com/sleepycat/b/i/c/aj:ai	()Ljava/lang/String;
    //   624: invokevirtual 385	java/lang/StringBuilder:append	(Ljava/lang/String;)Ljava/lang/StringBuilder;
    //   627: invokevirtual 121	java/lang/StringBuilder:toString	()Ljava/lang/String;
    //   630: invokestatic 459	com/sleepycat/b/p/w:c	(Ljava/util/logging/Logger;Lcom/sleepycat/b/c/ad;Ljava/lang/String;)V
    //   633: aconst_null
    //   634: athrow
    //   635: astore_1
    //   636: aload_0
    //   637: getfield 231	com/sleepycat/b/i/c/b/aa:h	Lcom/sleepycat/b/i/c/b/z;
    //   640: astore_1
    //   641: getstatic 1235	com/sleepycat/b/i/u:a	Lcom/sleepycat/b/i/u;
    //   644: astore_2
    //   645: getstatic 97	com/sleepycat/b/i/c/b/x:c	Lcom/sleepycat/b/i/c/b/x;
    //   648: astore_3
    //   649: goto -458 -> 191
    //   652: astore_1
    //   653: aload_0
    //   654: getfield 166	com/sleepycat/b/i/c/b/aa:x	Ljava/util/logging/Logger;
    //   657: aload_0
    //   658: getfield 146	com/sleepycat/b/i/c/b/aa:i	Lcom/sleepycat/b/i/c/aj;
    //   661: new 103	java/lang/StringBuilder
    //   664: dup
    //   665: ldc_w 1265
    //   668: invokespecial 108	java/lang/StringBuilder:<init>	(Ljava/lang/String;)V
    //   671: aload_1
    //   672: invokevirtual 117	java/lang/StringBuilder:append	(Ljava/lang/Object;)Ljava/lang/StringBuilder;
    //   675: invokevirtual 121	java/lang/StringBuilder:toString	()Ljava/lang/String;
    //   678: invokestatic 1242	com/sleepycat/b/p/w:d	(Ljava/util/logging/Logger;Lcom/sleepycat/b/c/ad;Ljava/lang/String;)V
    //   681: aload_0
    //   682: aload_1
    //   683: putfield 1093	com/sleepycat/b/p/aj:F	Ljava/lang/Exception;
    //   686: aload_1
    //   687: athrow
    //   688: astore_1
    //   689: aload_0
    //   690: getfield 166	com/sleepycat/b/i/c/b/aa:x	Ljava/util/logging/Logger;
    //   693: aload_0
    //   694: getfield 146	com/sleepycat/b/i/c/b/aa:i	Lcom/sleepycat/b/i/c/aj;
    //   697: ldc_w 1229
    //   700: invokestatic 459	com/sleepycat/b/p/w:c	(Ljava/util/logging/Logger;Lcom/sleepycat/b/c/ad;Ljava/lang/String;)V
    //   703: aload_2
    //   704: ifnull +166 -> 870
    //   707: aload_0
    //   708: getfield 166	com/sleepycat/b/i/c/b/aa:x	Ljava/util/logging/Logger;
    //   711: aload_0
    //   712: getfield 146	com/sleepycat/b/i/c/b/aa:i	Lcom/sleepycat/b/i/c/aj;
    //   715: new 103	java/lang/StringBuilder
    //   718: dup
    //   719: ldc_w 1231
    //   722: invokespecial 108	java/lang/StringBuilder:<init>	(Ljava/lang/String;)V
    //   725: aload_0
    //   726: getfield 146	com/sleepycat/b/i/c/b/aa:i	Lcom/sleepycat/b/i/c/aj;
    //   729: invokevirtual 1234	com/sleepycat/b/i/c/aj:ai	()Ljava/lang/String;
    //   732: invokevirtual 385	java/lang/StringBuilder:append	(Ljava/lang/String;)Ljava/lang/StringBuilder;
    //   735: invokevirtual 121	java/lang/StringBuilder:toString	()Ljava/lang/String;
    //   738: invokestatic 459	com/sleepycat/b/p/w:c	(Ljava/util/logging/Logger;Lcom/sleepycat/b/c/ad;Ljava/lang/String;)V
    //   741: aload_2
    //   742: athrow
    //   743: astore_2
    //   744: aload_0
    //   745: getfield 231	com/sleepycat/b/i/c/b/aa:h	Lcom/sleepycat/b/i/c/b/z;
    //   748: getstatic 1235	com/sleepycat/b/i/u:a	Lcom/sleepycat/b/i/u;
    //   751: getstatic 97	com/sleepycat/b/i/c/b/x:c	Lcom/sleepycat/b/i/c/b/x;
    //   754: invokevirtual 650	com/sleepycat/b/i/c/b/z:a	(Lcom/sleepycat/b/i/u;Lcom/sleepycat/b/i/c/b/x;)V
    //   757: aload_1
    //   758: athrow
    //   759: astore_1
    //   760: aload_0
    //   761: getfield 166	com/sleepycat/b/i/c/b/aa:x	Ljava/util/logging/Logger;
    //   764: aload_0
    //   765: getfield 146	com/sleepycat/b/i/c/b/aa:i	Lcom/sleepycat/b/i/c/aj;
    //   768: new 103	java/lang/StringBuilder
    //   771: dup
    //   772: invokespecial 363	java/lang/StringBuilder:<init>	()V
    //   775: aload_1
    //   776: invokevirtual 117	java/lang/StringBuilder:append	(Ljava/lang/Object;)Ljava/lang/StringBuilder;
    //   779: ldc_w 1267
    //   782: invokevirtual 385	java/lang/StringBuilder:append	(Ljava/lang/String;)Ljava/lang/StringBuilder;
    //   785: invokevirtual 121	java/lang/StringBuilder:toString	()Ljava/lang/String;
    //   788: invokestatic 1242	com/sleepycat/b/p/w:d	(Ljava/util/logging/Logger;Lcom/sleepycat/b/c/ad;Ljava/lang/String;)V
    //   791: aload_0
    //   792: getfield 146	com/sleepycat/b/i/c/b/aa:i	Lcom/sleepycat/b/i/c/aj;
    //   795: aload_1
    //   796: invokevirtual 1270	com/sleepycat/b/i/c/aj:a	(Ljava/lang/Error;)V
    //   799: aload_0
    //   800: getfield 166	com/sleepycat/b/i/c/b/aa:x	Ljava/util/logging/Logger;
    //   803: aload_0
    //   804: getfield 146	com/sleepycat/b/i/c/b/aa:i	Lcom/sleepycat/b/i/c/aj;
    //   807: ldc_w 1229
    //   810: invokestatic 459	com/sleepycat/b/p/w:c	(Ljava/util/logging/Logger;Lcom/sleepycat/b/c/ad;Ljava/lang/String;)V
    //   813: aload_1
    //   814: ifnull +580 -> 1394
    //   817: aload_0
    //   818: getfield 166	com/sleepycat/b/i/c/b/aa:x	Ljava/util/logging/Logger;
    //   821: aload_0
    //   822: getfield 146	com/sleepycat/b/i/c/b/aa:i	Lcom/sleepycat/b/i/c/aj;
    //   825: new 103	java/lang/StringBuilder
    //   828: dup
    //   829: ldc_w 1231
    //   832: invokespecial 108	java/lang/StringBuilder:<init>	(Ljava/lang/String;)V
    //   835: aload_0
    //   836: getfield 146	com/sleepycat/b/i/c/b/aa:i	Lcom/sleepycat/b/i/c/aj;
    //   839: invokevirtual 1234	com/sleepycat/b/i/c/aj:ai	()Ljava/lang/String;
    //   842: invokevirtual 385	java/lang/StringBuilder:append	(Ljava/lang/String;)Ljava/lang/StringBuilder;
    //   845: invokevirtual 121	java/lang/StringBuilder:toString	()Ljava/lang/String;
    //   848: invokestatic 459	com/sleepycat/b/p/w:c	(Ljava/util/logging/Logger;Lcom/sleepycat/b/c/ad;Ljava/lang/String;)V
    //   851: aload_1
    //   852: athrow
    //   853: astore_1
    //   854: aload_0
    //   855: getfield 231	com/sleepycat/b/i/c/b/aa:h	Lcom/sleepycat/b/i/c/b/z;
    //   858: astore_1
    //   859: getstatic 1235	com/sleepycat/b/i/u:a	Lcom/sleepycat/b/i/u;
    //   862: astore_2
    //   863: getstatic 97	com/sleepycat/b/i/c/b/x:c	Lcom/sleepycat/b/i/c/b/x;
    //   866: astore_3
    //   867: goto -676 -> 191
    //   870: aload_0
    //   871: getfield 1093	com/sleepycat/b/p/aj:F	Ljava/lang/Exception;
    //   874: astore_2
    //   875: aload_2
    //   876: ifnonnull +81 -> 957
    //   879: aload_0
    //   880: getfield 166	com/sleepycat/b/i/c/b/aa:x	Ljava/util/logging/Logger;
    //   883: aload_0
    //   884: getfield 146	com/sleepycat/b/i/c/b/aa:i	Lcom/sleepycat/b/i/c/aj;
    //   887: new 103	java/lang/StringBuilder
    //   890: dup
    //   891: ldc_w 1231
    //   894: invokespecial 108	java/lang/StringBuilder:<init>	(Ljava/lang/String;)V
    //   897: aload_0
    //   898: getfield 146	com/sleepycat/b/i/c/b/aa:i	Lcom/sleepycat/b/i/c/aj;
    //   901: invokevirtual 1234	com/sleepycat/b/i/c/aj:ai	()Ljava/lang/String;
    //   904: invokevirtual 385	java/lang/StringBuilder:append	(Ljava/lang/String;)Ljava/lang/StringBuilder;
    //   907: invokevirtual 121	java/lang/StringBuilder:toString	()Ljava/lang/String;
    //   910: invokestatic 1242	com/sleepycat/b/p/w:d	(Ljava/util/logging/Logger;Lcom/sleepycat/b/c/ad;Ljava/lang/String;)V
    //   913: aload_0
    //   914: invokevirtual 1272	com/sleepycat/b/i/c/b/aa:l	()V
    //   917: goto -173 -> 744
    //   920: astore_3
    //   921: aload_3
    //   922: aload_2
    //   923: invokestatic 1275	com/sleepycat/b/i/h/q:a	(Ljava/lang/Throwable;Ljava/lang/Throwable;)Ljava/lang/Throwable;
    //   926: pop
    //   927: aload_0
    //   928: getfield 166	com/sleepycat/b/i/c/b/aa:x	Ljava/util/logging/Logger;
    //   931: aload_0
    //   932: getfield 146	com/sleepycat/b/i/c/b/aa:i	Lcom/sleepycat/b/i/c/aj;
    //   935: new 103	java/lang/StringBuilder
    //   938: dup
    //   939: ldc_w 1277
    //   942: invokespecial 108	java/lang/StringBuilder:<init>	(Ljava/lang/String;)V
    //   945: aload_3
    //   946: invokevirtual 117	java/lang/StringBuilder:append	(Ljava/lang/Object;)Ljava/lang/StringBuilder;
    //   949: invokevirtual 121	java/lang/StringBuilder:toString	()Ljava/lang/String;
    //   952: invokestatic 1279	com/sleepycat/b/p/w:a	(Ljava/util/logging/Logger;Lcom/sleepycat/b/c/ad;Ljava/lang/String;)V
    //   955: aload_3
    //   956: athrow
    //   957: aload_0
    //   958: getfield 166	com/sleepycat/b/i/c/b/aa:x	Ljava/util/logging/Logger;
    //   961: aload_0
    //   962: getfield 146	com/sleepycat/b/i/c/b/aa:i	Lcom/sleepycat/b/i/c/aj;
    //   965: new 103	java/lang/StringBuilder
    //   968: dup
    //   969: ldc_w 1281
    //   972: invokespecial 108	java/lang/StringBuilder:<init>	(Ljava/lang/String;)V
    //   975: aload_2
    //   976: invokevirtual 1008	java/lang/Throwable:getMessage	()Ljava/lang/String;
    //   979: invokevirtual 385	java/lang/StringBuilder:append	(Ljava/lang/String;)Ljava/lang/StringBuilder;
    //   982: aload_0
    //   983: getfield 146	com/sleepycat/b/i/c/b/aa:i	Lcom/sleepycat/b/i/c/aj;
    //   986: invokevirtual 1234	com/sleepycat/b/i/c/aj:ai	()Ljava/lang/String;
    //   989: invokevirtual 385	java/lang/StringBuilder:append	(Ljava/lang/String;)Ljava/lang/StringBuilder;
    //   992: invokevirtual 121	java/lang/StringBuilder:toString	()Ljava/lang/String;
    //   995: invokestatic 459	com/sleepycat/b/p/w:c	(Ljava/util/logging/Logger;Lcom/sleepycat/b/c/ad;Ljava/lang/String;)V
    //   998: goto -85 -> 913
    //   1001: aload_0
    //   1002: getfield 1093	com/sleepycat/b/p/aj:F	Ljava/lang/Exception;
    //   1005: astore_1
    //   1006: aload_1
    //   1007: ifnonnull +81 -> 1088
    //   1010: aload_0
    //   1011: getfield 166	com/sleepycat/b/i/c/b/aa:x	Ljava/util/logging/Logger;
    //   1014: aload_0
    //   1015: getfield 146	com/sleepycat/b/i/c/b/aa:i	Lcom/sleepycat/b/i/c/aj;
    //   1018: new 103	java/lang/StringBuilder
    //   1021: dup
    //   1022: ldc_w 1231
    //   1025: invokespecial 108	java/lang/StringBuilder:<init>	(Ljava/lang/String;)V
    //   1028: aload_0
    //   1029: getfield 146	com/sleepycat/b/i/c/b/aa:i	Lcom/sleepycat/b/i/c/aj;
    //   1032: invokevirtual 1234	com/sleepycat/b/i/c/aj:ai	()Ljava/lang/String;
    //   1035: invokevirtual 385	java/lang/StringBuilder:append	(Ljava/lang/String;)Ljava/lang/StringBuilder;
    //   1038: invokevirtual 121	java/lang/StringBuilder:toString	()Ljava/lang/String;
    //   1041: invokestatic 1242	com/sleepycat/b/p/w:d	(Ljava/util/logging/Logger;Lcom/sleepycat/b/c/ad;Ljava/lang/String;)V
    //   1044: aload_0
    //   1045: invokevirtual 1272	com/sleepycat/b/i/c/b/aa:l	()V
    //   1048: goto -755 -> 293
    //   1051: astore_2
    //   1052: aload_2
    //   1053: aload_1
    //   1054: invokestatic 1275	com/sleepycat/b/i/h/q:a	(Ljava/lang/Throwable;Ljava/lang/Throwable;)Ljava/lang/Throwable;
    //   1057: pop
    //   1058: aload_0
    //   1059: getfield 166	com/sleepycat/b/i/c/b/aa:x	Ljava/util/logging/Logger;
    //   1062: aload_0
    //   1063: getfield 146	com/sleepycat/b/i/c/b/aa:i	Lcom/sleepycat/b/i/c/aj;
    //   1066: new 103	java/lang/StringBuilder
    //   1069: dup
    //   1070: ldc_w 1277
    //   1073: invokespecial 108	java/lang/StringBuilder:<init>	(Ljava/lang/String;)V
    //   1076: aload_2
    //   1077: invokevirtual 117	java/lang/StringBuilder:append	(Ljava/lang/Object;)Ljava/lang/StringBuilder;
    //   1080: invokevirtual 121	java/lang/StringBuilder:toString	()Ljava/lang/String;
    //   1083: invokestatic 1279	com/sleepycat/b/p/w:a	(Ljava/util/logging/Logger;Lcom/sleepycat/b/c/ad;Ljava/lang/String;)V
    //   1086: aload_2
    //   1087: athrow
    //   1088: aload_0
    //   1089: getfield 166	com/sleepycat/b/i/c/b/aa:x	Ljava/util/logging/Logger;
    //   1092: aload_0
    //   1093: getfield 146	com/sleepycat/b/i/c/b/aa:i	Lcom/sleepycat/b/i/c/aj;
    //   1096: new 103	java/lang/StringBuilder
    //   1099: dup
    //   1100: ldc_w 1281
    //   1103: invokespecial 108	java/lang/StringBuilder:<init>	(Ljava/lang/String;)V
    //   1106: aload_1
    //   1107: invokevirtual 1008	java/lang/Throwable:getMessage	()Ljava/lang/String;
    //   1110: invokevirtual 385	java/lang/StringBuilder:append	(Ljava/lang/String;)Ljava/lang/StringBuilder;
    //   1113: aload_0
    //   1114: getfield 146	com/sleepycat/b/i/c/b/aa:i	Lcom/sleepycat/b/i/c/aj;
    //   1117: invokevirtual 1234	com/sleepycat/b/i/c/aj:ai	()Ljava/lang/String;
    //   1120: invokevirtual 385	java/lang/StringBuilder:append	(Ljava/lang/String;)Ljava/lang/StringBuilder;
    //   1123: invokevirtual 121	java/lang/StringBuilder:toString	()Ljava/lang/String;
    //   1126: invokestatic 459	com/sleepycat/b/p/w:c	(Ljava/util/logging/Logger;Lcom/sleepycat/b/c/ad;Ljava/lang/String;)V
    //   1129: goto -85 -> 1044
    //   1132: aload_0
    //   1133: getfield 1093	com/sleepycat/b/p/aj:F	Ljava/lang/Exception;
    //   1136: astore_1
    //   1137: aload_1
    //   1138: ifnonnull +81 -> 1219
    //   1141: aload_0
    //   1142: getfield 166	com/sleepycat/b/i/c/b/aa:x	Ljava/util/logging/Logger;
    //   1145: aload_0
    //   1146: getfield 146	com/sleepycat/b/i/c/b/aa:i	Lcom/sleepycat/b/i/c/aj;
    //   1149: new 103	java/lang/StringBuilder
    //   1152: dup
    //   1153: ldc_w 1231
    //   1156: invokespecial 108	java/lang/StringBuilder:<init>	(Ljava/lang/String;)V
    //   1159: aload_0
    //   1160: getfield 146	com/sleepycat/b/i/c/b/aa:i	Lcom/sleepycat/b/i/c/aj;
    //   1163: invokevirtual 1234	com/sleepycat/b/i/c/aj:ai	()Ljava/lang/String;
    //   1166: invokevirtual 385	java/lang/StringBuilder:append	(Ljava/lang/String;)Ljava/lang/StringBuilder;
    //   1169: invokevirtual 121	java/lang/StringBuilder:toString	()Ljava/lang/String;
    //   1172: invokestatic 1242	com/sleepycat/b/p/w:d	(Ljava/util/logging/Logger;Lcom/sleepycat/b/c/ad;Ljava/lang/String;)V
    //   1175: aload_0
    //   1176: invokevirtual 1272	com/sleepycat/b/i/c/b/aa:l	()V
    //   1179: goto -637 -> 542
    //   1182: astore_2
    //   1183: aload_2
    //   1184: aload_1
    //   1185: invokestatic 1275	com/sleepycat/b/i/h/q:a	(Ljava/lang/Throwable;Ljava/lang/Throwable;)Ljava/lang/Throwable;
    //   1188: pop
    //   1189: aload_0
    //   1190: getfield 166	com/sleepycat/b/i/c/b/aa:x	Ljava/util/logging/Logger;
    //   1193: aload_0
    //   1194: getfield 146	com/sleepycat/b/i/c/b/aa:i	Lcom/sleepycat/b/i/c/aj;
    //   1197: new 103	java/lang/StringBuilder
    //   1200: dup
    //   1201: ldc_w 1277
    //   1204: invokespecial 108	java/lang/StringBuilder:<init>	(Ljava/lang/String;)V
    //   1207: aload_2
    //   1208: invokevirtual 117	java/lang/StringBuilder:append	(Ljava/lang/Object;)Ljava/lang/StringBuilder;
    //   1211: invokevirtual 121	java/lang/StringBuilder:toString	()Ljava/lang/String;
    //   1214: invokestatic 1279	com/sleepycat/b/p/w:a	(Ljava/util/logging/Logger;Lcom/sleepycat/b/c/ad;Ljava/lang/String;)V
    //   1217: aload_2
    //   1218: athrow
    //   1219: aload_0
    //   1220: getfield 166	com/sleepycat/b/i/c/b/aa:x	Ljava/util/logging/Logger;
    //   1223: aload_0
    //   1224: getfield 146	com/sleepycat/b/i/c/b/aa:i	Lcom/sleepycat/b/i/c/aj;
    //   1227: new 103	java/lang/StringBuilder
    //   1230: dup
    //   1231: ldc_w 1281
    //   1234: invokespecial 108	java/lang/StringBuilder:<init>	(Ljava/lang/String;)V
    //   1237: aload_1
    //   1238: invokevirtual 1008	java/lang/Throwable:getMessage	()Ljava/lang/String;
    //   1241: invokevirtual 385	java/lang/StringBuilder:append	(Ljava/lang/String;)Ljava/lang/StringBuilder;
    //   1244: aload_0
    //   1245: getfield 146	com/sleepycat/b/i/c/b/aa:i	Lcom/sleepycat/b/i/c/aj;
    //   1248: invokevirtual 1234	com/sleepycat/b/i/c/aj:ai	()Ljava/lang/String;
    //   1251: invokevirtual 385	java/lang/StringBuilder:append	(Ljava/lang/String;)Ljava/lang/StringBuilder;
    //   1254: invokevirtual 121	java/lang/StringBuilder:toString	()Ljava/lang/String;
    //   1257: invokestatic 459	com/sleepycat/b/p/w:c	(Ljava/util/logging/Logger;Lcom/sleepycat/b/c/ad;Ljava/lang/String;)V
    //   1260: goto -85 -> 1175
    //   1263: aload_0
    //   1264: getfield 1093	com/sleepycat/b/p/aj:F	Ljava/lang/Exception;
    //   1267: astore_1
    //   1268: aload_1
    //   1269: ifnonnull +81 -> 1350
    //   1272: aload_0
    //   1273: getfield 166	com/sleepycat/b/i/c/b/aa:x	Ljava/util/logging/Logger;
    //   1276: aload_0
    //   1277: getfield 146	com/sleepycat/b/i/c/b/aa:i	Lcom/sleepycat/b/i/c/aj;
    //   1280: new 103	java/lang/StringBuilder
    //   1283: dup
    //   1284: ldc_w 1231
    //   1287: invokespecial 108	java/lang/StringBuilder:<init>	(Ljava/lang/String;)V
    //   1290: aload_0
    //   1291: getfield 146	com/sleepycat/b/i/c/b/aa:i	Lcom/sleepycat/b/i/c/aj;
    //   1294: invokevirtual 1234	com/sleepycat/b/i/c/aj:ai	()Ljava/lang/String;
    //   1297: invokevirtual 385	java/lang/StringBuilder:append	(Ljava/lang/String;)Ljava/lang/StringBuilder;
    //   1300: invokevirtual 121	java/lang/StringBuilder:toString	()Ljava/lang/String;
    //   1303: invokestatic 1242	com/sleepycat/b/p/w:d	(Ljava/util/logging/Logger;Lcom/sleepycat/b/c/ad;Ljava/lang/String;)V
    //   1306: aload_0
    //   1307: invokevirtual 1272	com/sleepycat/b/i/c/b/aa:l	()V
    //   1310: goto -674 -> 636
    //   1313: astore_2
    //   1314: aload_2
    //   1315: aload_1
    //   1316: invokestatic 1275	com/sleepycat/b/i/h/q:a	(Ljava/lang/Throwable;Ljava/lang/Throwable;)Ljava/lang/Throwable;
    //   1319: pop
    //   1320: aload_0
    //   1321: getfield 166	com/sleepycat/b/i/c/b/aa:x	Ljava/util/logging/Logger;
    //   1324: aload_0
    //   1325: getfield 146	com/sleepycat/b/i/c/b/aa:i	Lcom/sleepycat/b/i/c/aj;
    //   1328: new 103	java/lang/StringBuilder
    //   1331: dup
    //   1332: ldc_w 1277
    //   1335: invokespecial 108	java/lang/StringBuilder:<init>	(Ljava/lang/String;)V
    //   1338: aload_2
    //   1339: invokevirtual 117	java/lang/StringBuilder:append	(Ljava/lang/Object;)Ljava/lang/StringBuilder;
    //   1342: invokevirtual 121	java/lang/StringBuilder:toString	()Ljava/lang/String;
    //   1345: invokestatic 1279	com/sleepycat/b/p/w:a	(Ljava/util/logging/Logger;Lcom/sleepycat/b/c/ad;Ljava/lang/String;)V
    //   1348: aload_2
    //   1349: athrow
    //   1350: aload_0
    //   1351: getfield 166	com/sleepycat/b/i/c/b/aa:x	Ljava/util/logging/Logger;
    //   1354: aload_0
    //   1355: getfield 146	com/sleepycat/b/i/c/b/aa:i	Lcom/sleepycat/b/i/c/aj;
    //   1358: new 103	java/lang/StringBuilder
    //   1361: dup
    //   1362: ldc_w 1281
    //   1365: invokespecial 108	java/lang/StringBuilder:<init>	(Ljava/lang/String;)V
    //   1368: aload_1
    //   1369: invokevirtual 1008	java/lang/Throwable:getMessage	()Ljava/lang/String;
    //   1372: invokevirtual 385	java/lang/StringBuilder:append	(Ljava/lang/String;)Ljava/lang/StringBuilder;
    //   1375: aload_0
    //   1376: getfield 146	com/sleepycat/b/i/c/b/aa:i	Lcom/sleepycat/b/i/c/aj;
    //   1379: invokevirtual 1234	com/sleepycat/b/i/c/aj:ai	()Ljava/lang/String;
    //   1382: invokevirtual 385	java/lang/StringBuilder:append	(Ljava/lang/String;)Ljava/lang/StringBuilder;
    //   1385: invokevirtual 121	java/lang/StringBuilder:toString	()Ljava/lang/String;
    //   1388: invokestatic 459	com/sleepycat/b/p/w:c	(Ljava/util/logging/Logger;Lcom/sleepycat/b/c/ad;Ljava/lang/String;)V
    //   1391: goto -85 -> 1306
    //   1394: aload_0
    //   1395: getfield 1093	com/sleepycat/b/p/aj:F	Ljava/lang/Exception;
    //   1398: astore_1
    //   1399: aload_1
    //   1400: ifnonnull +81 -> 1481
    //   1403: aload_0
    //   1404: getfield 166	com/sleepycat/b/i/c/b/aa:x	Ljava/util/logging/Logger;
    //   1407: aload_0
    //   1408: getfield 146	com/sleepycat/b/i/c/b/aa:i	Lcom/sleepycat/b/i/c/aj;
    //   1411: new 103	java/lang/StringBuilder
    //   1414: dup
    //   1415: ldc_w 1231
    //   1418: invokespecial 108	java/lang/StringBuilder:<init>	(Ljava/lang/String;)V
    //   1421: aload_0
    //   1422: getfield 146	com/sleepycat/b/i/c/b/aa:i	Lcom/sleepycat/b/i/c/aj;
    //   1425: invokevirtual 1234	com/sleepycat/b/i/c/aj:ai	()Ljava/lang/String;
    //   1428: invokevirtual 385	java/lang/StringBuilder:append	(Ljava/lang/String;)Ljava/lang/StringBuilder;
    //   1431: invokevirtual 121	java/lang/StringBuilder:toString	()Ljava/lang/String;
    //   1434: invokestatic 1242	com/sleepycat/b/p/w:d	(Ljava/util/logging/Logger;Lcom/sleepycat/b/c/ad;Ljava/lang/String;)V
    //   1437: aload_0
    //   1438: invokevirtual 1272	com/sleepycat/b/i/c/b/aa:l	()V
    //   1441: goto -587 -> 854
    //   1444: astore_2
    //   1445: aload_2
    //   1446: aload_1
    //   1447: invokestatic 1275	com/sleepycat/b/i/h/q:a	(Ljava/lang/Throwable;Ljava/lang/Throwable;)Ljava/lang/Throwable;
    //   1450: pop
    //   1451: aload_0
    //   1452: getfield 166	com/sleepycat/b/i/c/b/aa:x	Ljava/util/logging/Logger;
    //   1455: aload_0
    //   1456: getfield 146	com/sleepycat/b/i/c/b/aa:i	Lcom/sleepycat/b/i/c/aj;
    //   1459: new 103	java/lang/StringBuilder
    //   1462: dup
    //   1463: ldc_w 1277
    //   1466: invokespecial 108	java/lang/StringBuilder:<init>	(Ljava/lang/String;)V
    //   1469: aload_2
    //   1470: invokevirtual 117	java/lang/StringBuilder:append	(Ljava/lang/Object;)Ljava/lang/StringBuilder;
    //   1473: invokevirtual 121	java/lang/StringBuilder:toString	()Ljava/lang/String;
    //   1476: invokestatic 1279	com/sleepycat/b/p/w:a	(Ljava/util/logging/Logger;Lcom/sleepycat/b/c/ad;Ljava/lang/String;)V
    //   1479: aload_2
    //   1480: athrow
    //   1481: aload_0
    //   1482: getfield 166	com/sleepycat/b/i/c/b/aa:x	Ljava/util/logging/Logger;
    //   1485: aload_0
    //   1486: getfield 146	com/sleepycat/b/i/c/b/aa:i	Lcom/sleepycat/b/i/c/aj;
    //   1489: new 103	java/lang/StringBuilder
    //   1492: dup
    //   1493: ldc_w 1281
    //   1496: invokespecial 108	java/lang/StringBuilder:<init>	(Ljava/lang/String;)V
    //   1499: aload_1
    //   1500: invokevirtual 1008	java/lang/Throwable:getMessage	()Ljava/lang/String;
    //   1503: invokevirtual 385	java/lang/StringBuilder:append	(Ljava/lang/String;)Ljava/lang/StringBuilder;
    //   1506: aload_0
    //   1507: getfield 146	com/sleepycat/b/i/c/b/aa:i	Lcom/sleepycat/b/i/c/aj;
    //   1510: invokevirtual 1234	com/sleepycat/b/i/c/aj:ai	()Ljava/lang/String;
    //   1513: invokevirtual 385	java/lang/StringBuilder:append	(Ljava/lang/String;)Ljava/lang/StringBuilder;
    //   1516: invokevirtual 121	java/lang/StringBuilder:toString	()Ljava/lang/String;
    //   1519: invokestatic 459	com/sleepycat/b/p/w:c	(Ljava/util/logging/Logger;Lcom/sleepycat/b/c/ad;Ljava/lang/String;)V
    //   1522: goto -85 -> 1437
    //   1525: aload_0
    //   1526: getfield 1093	com/sleepycat/b/p/aj:F	Ljava/lang/Exception;
    //   1529: astore_1
    //   1530: aload_1
    //   1531: ifnonnull +81 -> 1612
    //   1534: aload_0
    //   1535: getfield 166	com/sleepycat/b/i/c/b/aa:x	Ljava/util/logging/Logger;
    //   1538: aload_0
    //   1539: getfield 146	com/sleepycat/b/i/c/b/aa:i	Lcom/sleepycat/b/i/c/aj;
    //   1542: new 103	java/lang/StringBuilder
    //   1545: dup
    //   1546: ldc_w 1231
    //   1549: invokespecial 108	java/lang/StringBuilder:<init>	(Ljava/lang/String;)V
    //   1552: aload_0
    //   1553: getfield 146	com/sleepycat/b/i/c/b/aa:i	Lcom/sleepycat/b/i/c/aj;
    //   1556: invokevirtual 1234	com/sleepycat/b/i/c/aj:ai	()Ljava/lang/String;
    //   1559: invokevirtual 385	java/lang/StringBuilder:append	(Ljava/lang/String;)Ljava/lang/StringBuilder;
    //   1562: invokevirtual 121	java/lang/StringBuilder:toString	()Ljava/lang/String;
    //   1565: invokestatic 1242	com/sleepycat/b/p/w:d	(Ljava/util/logging/Logger;Lcom/sleepycat/b/c/ad;Ljava/lang/String;)V
    //   1568: aload_0
    //   1569: invokevirtual 1272	com/sleepycat/b/i/c/b/aa:l	()V
    //   1572: goto -1394 -> 178
    //   1575: astore_2
    //   1576: aload_2
    //   1577: aload_1
    //   1578: invokestatic 1275	com/sleepycat/b/i/h/q:a	(Ljava/lang/Throwable;Ljava/lang/Throwable;)Ljava/lang/Throwable;
    //   1581: pop
    //   1582: aload_0
    //   1583: getfield 166	com/sleepycat/b/i/c/b/aa:x	Ljava/util/logging/Logger;
    //   1586: aload_0
    //   1587: getfield 146	com/sleepycat/b/i/c/b/aa:i	Lcom/sleepycat/b/i/c/aj;
    //   1590: new 103	java/lang/StringBuilder
    //   1593: dup
    //   1594: ldc_w 1277
    //   1597: invokespecial 108	java/lang/StringBuilder:<init>	(Ljava/lang/String;)V
    //   1600: aload_2
    //   1601: invokevirtual 117	java/lang/StringBuilder:append	(Ljava/lang/Object;)Ljava/lang/StringBuilder;
    //   1604: invokevirtual 121	java/lang/StringBuilder:toString	()Ljava/lang/String;
    //   1607: invokestatic 1279	com/sleepycat/b/p/w:a	(Ljava/util/logging/Logger;Lcom/sleepycat/b/c/ad;Ljava/lang/String;)V
    //   1610: aload_2
    //   1611: athrow
    //   1612: aload_0
    //   1613: getfield 166	com/sleepycat/b/i/c/b/aa:x	Ljava/util/logging/Logger;
    //   1616: aload_0
    //   1617: getfield 146	com/sleepycat/b/i/c/b/aa:i	Lcom/sleepycat/b/i/c/aj;
    //   1620: new 103	java/lang/StringBuilder
    //   1623: dup
    //   1624: ldc_w 1281
    //   1627: invokespecial 108	java/lang/StringBuilder:<init>	(Ljava/lang/String;)V
    //   1630: aload_1
    //   1631: invokevirtual 1008	java/lang/Throwable:getMessage	()Ljava/lang/String;
    //   1634: invokevirtual 385	java/lang/StringBuilder:append	(Ljava/lang/String;)Ljava/lang/StringBuilder;
    //   1637: aload_0
    //   1638: getfield 146	com/sleepycat/b/i/c/b/aa:i	Lcom/sleepycat/b/i/c/aj;
    //   1641: invokevirtual 1234	com/sleepycat/b/i/c/aj:ai	()Ljava/lang/String;
    //   1644: invokevirtual 385	java/lang/StringBuilder:append	(Ljava/lang/String;)Ljava/lang/StringBuilder;
    //   1647: invokevirtual 121	java/lang/StringBuilder:toString	()Ljava/lang/String;
    //   1650: invokestatic 459	com/sleepycat/b/p/w:c	(Ljava/util/logging/Logger;Lcom/sleepycat/b/c/ad;Ljava/lang/String;)V
    //   1653: goto -85 -> 1568
    //   1656: aload_0
    //   1657: getfield 166	com/sleepycat/b/i/c/b/aa:x	Ljava/util/logging/Logger;
    //   1660: aload_0
    //   1661: getfield 146	com/sleepycat/b/i/c/b/aa:i	Lcom/sleepycat/b/i/c/aj;
    //   1664: ldc_w 1229
    //   1667: invokestatic 459	com/sleepycat/b/p/w:c	(Ljava/util/logging/Logger;Lcom/sleepycat/b/c/ad;Ljava/lang/String;)V
    //   1670: iconst_0
    //   1671: ifeq +56 -> 1727
    //   1674: aload_0
    //   1675: getfield 166	com/sleepycat/b/i/c/b/aa:x	Ljava/util/logging/Logger;
    //   1678: aload_0
    //   1679: getfield 146	com/sleepycat/b/i/c/b/aa:i	Lcom/sleepycat/b/i/c/aj;
    //   1682: new 103	java/lang/StringBuilder
    //   1685: dup
    //   1686: ldc_w 1231
    //   1689: invokespecial 108	java/lang/StringBuilder:<init>	(Ljava/lang/String;)V
    //   1692: aload_0
    //   1693: getfield 146	com/sleepycat/b/i/c/b/aa:i	Lcom/sleepycat/b/i/c/aj;
    //   1696: invokevirtual 1234	com/sleepycat/b/i/c/aj:ai	()Ljava/lang/String;
    //   1699: invokevirtual 385	java/lang/StringBuilder:append	(Ljava/lang/String;)Ljava/lang/StringBuilder;
    //   1702: invokevirtual 121	java/lang/StringBuilder:toString	()Ljava/lang/String;
    //   1705: invokestatic 459	com/sleepycat/b/p/w:c	(Ljava/util/logging/Logger;Lcom/sleepycat/b/c/ad;Ljava/lang/String;)V
    //   1708: aconst_null
    //   1709: athrow
    //   1710: astore_1
    //   1711: aload_0
    //   1712: getfield 231	com/sleepycat/b/i/c/b/aa:h	Lcom/sleepycat/b/i/c/b/z;
    //   1715: astore_1
    //   1716: getstatic 1235	com/sleepycat/b/i/u:a	Lcom/sleepycat/b/i/u;
    //   1719: astore_2
    //   1720: getstatic 97	com/sleepycat/b/i/c/b/x:c	Lcom/sleepycat/b/i/c/b/x;
    //   1723: astore_3
    //   1724: goto -1533 -> 191
    //   1727: aload_0
    //   1728: getfield 1093	com/sleepycat/b/p/aj:F	Ljava/lang/Exception;
    //   1731: astore_1
    //   1732: aload_1
    //   1733: ifnonnull +81 -> 1814
    //   1736: aload_0
    //   1737: getfield 166	com/sleepycat/b/i/c/b/aa:x	Ljava/util/logging/Logger;
    //   1740: aload_0
    //   1741: getfield 146	com/sleepycat/b/i/c/b/aa:i	Lcom/sleepycat/b/i/c/aj;
    //   1744: new 103	java/lang/StringBuilder
    //   1747: dup
    //   1748: ldc_w 1231
    //   1751: invokespecial 108	java/lang/StringBuilder:<init>	(Ljava/lang/String;)V
    //   1754: aload_0
    //   1755: getfield 146	com/sleepycat/b/i/c/b/aa:i	Lcom/sleepycat/b/i/c/aj;
    //   1758: invokevirtual 1234	com/sleepycat/b/i/c/aj:ai	()Ljava/lang/String;
    //   1761: invokevirtual 385	java/lang/StringBuilder:append	(Ljava/lang/String;)Ljava/lang/StringBuilder;
    //   1764: invokevirtual 121	java/lang/StringBuilder:toString	()Ljava/lang/String;
    //   1767: invokestatic 1242	com/sleepycat/b/p/w:d	(Ljava/util/logging/Logger;Lcom/sleepycat/b/c/ad;Ljava/lang/String;)V
    //   1770: aload_0
    //   1771: invokevirtual 1272	com/sleepycat/b/i/c/b/aa:l	()V
    //   1774: goto -63 -> 1711
    //   1777: astore_2
    //   1778: aload_2
    //   1779: aload_1
    //   1780: invokestatic 1275	com/sleepycat/b/i/h/q:a	(Ljava/lang/Throwable;Ljava/lang/Throwable;)Ljava/lang/Throwable;
    //   1783: pop
    //   1784: aload_0
    //   1785: getfield 166	com/sleepycat/b/i/c/b/aa:x	Ljava/util/logging/Logger;
    //   1788: aload_0
    //   1789: getfield 146	com/sleepycat/b/i/c/b/aa:i	Lcom/sleepycat/b/i/c/aj;
    //   1792: new 103	java/lang/StringBuilder
    //   1795: dup
    //   1796: ldc_w 1277
    //   1799: invokespecial 108	java/lang/StringBuilder:<init>	(Ljava/lang/String;)V
    //   1802: aload_2
    //   1803: invokevirtual 117	java/lang/StringBuilder:append	(Ljava/lang/Object;)Ljava/lang/StringBuilder;
    //   1806: invokevirtual 121	java/lang/StringBuilder:toString	()Ljava/lang/String;
    //   1809: invokestatic 1279	com/sleepycat/b/p/w:a	(Ljava/util/logging/Logger;Lcom/sleepycat/b/c/ad;Ljava/lang/String;)V
    //   1812: aload_2
    //   1813: athrow
    //   1814: aload_0
    //   1815: getfield 166	com/sleepycat/b/i/c/b/aa:x	Ljava/util/logging/Logger;
    //   1818: aload_0
    //   1819: getfield 146	com/sleepycat/b/i/c/b/aa:i	Lcom/sleepycat/b/i/c/aj;
    //   1822: new 103	java/lang/StringBuilder
    //   1825: dup
    //   1826: ldc_w 1281
    //   1829: invokespecial 108	java/lang/StringBuilder:<init>	(Ljava/lang/String;)V
    //   1832: aload_1
    //   1833: invokevirtual 1008	java/lang/Throwable:getMessage	()Ljava/lang/String;
    //   1836: invokevirtual 385	java/lang/StringBuilder:append	(Ljava/lang/String;)Ljava/lang/StringBuilder;
    //   1839: aload_0
    //   1840: getfield 146	com/sleepycat/b/i/c/b/aa:i	Lcom/sleepycat/b/i/c/aj;
    //   1843: invokevirtual 1234	com/sleepycat/b/i/c/aj:ai	()Ljava/lang/String;
    //   1846: invokevirtual 385	java/lang/StringBuilder:append	(Ljava/lang/String;)Ljava/lang/StringBuilder;
    //   1849: invokevirtual 121	java/lang/StringBuilder:toString	()Ljava/lang/String;
    //   1852: invokestatic 459	com/sleepycat/b/p/w:c	(Ljava/util/logging/Logger;Lcom/sleepycat/b/c/ad;Ljava/lang/String;)V
    //   1855: goto -85 -> 1770
    //   1858: astore_3
    //   1859: aload_1
    //   1860: astore_2
    //   1861: aload_3
    //   1862: astore_1
    //   1863: goto -1174 -> 689
    // Local variable table:
    //   start	length	slot	name	signature
    //   0	1866	0	this	aa
    //   177	1	1	localInterruptedException1	InterruptedException
    //   182	10	1	localz1	z
    //   223	1	1	localInterruptedException2	InterruptedException
    //   292	1	1	localInterruptedException3	InterruptedException
    //   297	65	1	localObject1	Object
    //   453	25	1	locald	com.sleepycat.b.i.d
    //   541	1	1	localInterruptedException4	InterruptedException
    //   546	1	1	localz2	z
    //   575	3	1	localf	com.sleepycat.b.i.f
    //   635	1	1	localInterruptedException5	InterruptedException
    //   640	1	1	localz3	z
    //   652	35	1	localRuntimeException	RuntimeException
    //   688	70	1	localObject2	Object
    //   759	93	1	localError	Error
    //   853	1	1	localInterruptedException6	InterruptedException
    //   858	773	1	localObject3	Object
    //   1710	1	1	localInterruptedException7	InterruptedException
    //   1715	148	1	localObject4	Object
    //   1	741	2	localu1	com.sleepycat.b.i.u
    //   743	1	2	localInterruptedException8	InterruptedException
    //   862	114	2	localObject5	Object
    //   1051	36	2	localn1	com.sleepycat.b.n
    //   1182	36	2	localn2	com.sleepycat.b.n
    //   1313	36	2	localn3	com.sleepycat.b.n
    //   1444	36	2	localn4	com.sleepycat.b.n
    //   1575	36	2	localn5	com.sleepycat.b.n
    //   1719	1	2	localu2	com.sleepycat.b.i.u
    //   1777	36	2	localn6	com.sleepycat.b.n
    //   1860	1	2	localObject6	Object
    //   190	677	3	localx1	x
    //   920	36	3	localn7	com.sleepycat.b.n
    //   1723	1	3	localx2	x
    //   1858	4	3	localObject7	Object
    //   116	3	4	bool	boolean
    // Exception table:
    //   from	to	target	type
    //   123	137	177	java/lang/InterruptedException
    //   141	177	177	java/lang/InterruptedException
    //   1525	1530	177	java/lang/InterruptedException
    //   1534	1568	177	java/lang/InterruptedException
    //   1568	1572	177	java/lang/InterruptedException
    //   1576	1612	177	java/lang/InterruptedException
    //   1612	1653	177	java/lang/InterruptedException
    //   2	42	223	java/lang/InterruptedException
    //   42	75	223	java/lang/InterruptedException
    //   75	98	223	java/lang/InterruptedException
    //   98	112	223	java/lang/InterruptedException
    //   112	118	223	java/lang/InterruptedException
    //   198	220	223	java/lang/InterruptedException
    //   309	438	223	java/lang/InterruptedException
    //   438	450	223	java/lang/InterruptedException
    //   558	572	223	java/lang/InterruptedException
    //   238	252	292	java/lang/InterruptedException
    //   256	292	292	java/lang/InterruptedException
    //   1001	1006	292	java/lang/InterruptedException
    //   1010	1044	292	java/lang/InterruptedException
    //   1044	1048	292	java/lang/InterruptedException
    //   1052	1088	292	java/lang/InterruptedException
    //   1088	1129	292	java/lang/InterruptedException
    //   2	42	453	com/sleepycat/b/i/d
    //   42	75	453	com/sleepycat/b/i/d
    //   75	98	453	com/sleepycat/b/i/d
    //   98	112	453	com/sleepycat/b/i/d
    //   112	118	453	com/sleepycat/b/i/d
    //   198	220	453	com/sleepycat/b/i/d
    //   309	438	453	com/sleepycat/b/i/d
    //   438	450	453	com/sleepycat/b/i/d
    //   558	572	453	com/sleepycat/b/i/d
    //   487	501	541	java/lang/InterruptedException
    //   505	541	541	java/lang/InterruptedException
    //   1132	1137	541	java/lang/InterruptedException
    //   1141	1175	541	java/lang/InterruptedException
    //   1175	1179	541	java/lang/InterruptedException
    //   1183	1219	541	java/lang/InterruptedException
    //   1219	1260	541	java/lang/InterruptedException
    //   2	42	575	com/sleepycat/b/i/f
    //   42	75	575	com/sleepycat/b/i/f
    //   75	98	575	com/sleepycat/b/i/f
    //   98	112	575	com/sleepycat/b/i/f
    //   112	118	575	com/sleepycat/b/i/f
    //   198	220	575	com/sleepycat/b/i/f
    //   309	438	575	com/sleepycat/b/i/f
    //   438	450	575	com/sleepycat/b/i/f
    //   558	572	575	com/sleepycat/b/i/f
    //   581	595	635	java/lang/InterruptedException
    //   599	635	635	java/lang/InterruptedException
    //   1263	1268	635	java/lang/InterruptedException
    //   1272	1306	635	java/lang/InterruptedException
    //   1306	1310	635	java/lang/InterruptedException
    //   1314	1350	635	java/lang/InterruptedException
    //   1350	1391	635	java/lang/InterruptedException
    //   2	42	652	java/lang/RuntimeException
    //   42	75	652	java/lang/RuntimeException
    //   75	98	652	java/lang/RuntimeException
    //   98	112	652	java/lang/RuntimeException
    //   112	118	652	java/lang/RuntimeException
    //   198	220	652	java/lang/RuntimeException
    //   309	438	652	java/lang/RuntimeException
    //   438	450	652	java/lang/RuntimeException
    //   558	572	652	java/lang/RuntimeException
    //   2	42	688	finally
    //   42	75	688	finally
    //   75	98	688	finally
    //   98	112	688	finally
    //   112	118	688	finally
    //   198	220	688	finally
    //   224	238	688	finally
    //   309	438	688	finally
    //   438	450	688	finally
    //   454	487	688	finally
    //   558	572	688	finally
    //   576	581	688	finally
    //   653	688	688	finally
    //   760	791	688	finally
    //   689	703	743	java/lang/InterruptedException
    //   707	743	743	java/lang/InterruptedException
    //   870	875	743	java/lang/InterruptedException
    //   879	913	743	java/lang/InterruptedException
    //   913	917	743	java/lang/InterruptedException
    //   921	957	743	java/lang/InterruptedException
    //   957	998	743	java/lang/InterruptedException
    //   2	42	759	java/lang/Error
    //   42	75	759	java/lang/Error
    //   75	98	759	java/lang/Error
    //   98	112	759	java/lang/Error
    //   112	118	759	java/lang/Error
    //   198	220	759	java/lang/Error
    //   309	438	759	java/lang/Error
    //   438	450	759	java/lang/Error
    //   558	572	759	java/lang/Error
    //   799	813	853	java/lang/InterruptedException
    //   817	853	853	java/lang/InterruptedException
    //   1394	1399	853	java/lang/InterruptedException
    //   1403	1437	853	java/lang/InterruptedException
    //   1437	1441	853	java/lang/InterruptedException
    //   1445	1481	853	java/lang/InterruptedException
    //   1481	1522	853	java/lang/InterruptedException
    //   913	917	920	com/sleepycat/b/n
    //   1044	1048	1051	com/sleepycat/b/n
    //   1175	1179	1182	com/sleepycat/b/n
    //   1306	1310	1313	com/sleepycat/b/n
    //   1437	1441	1444	com/sleepycat/b/n
    //   1568	1572	1575	com/sleepycat/b/n
    //   1656	1670	1710	java/lang/InterruptedException
    //   1674	1710	1710	java/lang/InterruptedException
    //   1727	1732	1710	java/lang/InterruptedException
    //   1736	1770	1710	java/lang/InterruptedException
    //   1770	1774	1710	java/lang/InterruptedException
    //   1778	1814	1710	java/lang/InterruptedException
    //   1814	1855	1710	java/lang/InterruptedException
    //   1770	1774	1777	com/sleepycat/b/n
    //   791	799	1858	finally
  }
}


/* Location:              E:\apk\xueqiu2\classes-dex2jar.jar!\com\sleepycat\b\i\c\b\aa.class
 * Java compiler version: 6 (50.0)
 * JD-Core Version:       0.7.1
 */