package com.sleepycat.b.i.c.b;

import com.sleepycat.b.c.ad;
import com.sleepycat.b.c.m;
import com.sleepycat.b.i.c.an;
import com.sleepycat.b.i.e.ae;
import com.sleepycat.b.i.e.af;
import com.sleepycat.b.i.e.as;
import com.sleepycat.b.i.e.at;
import com.sleepycat.b.i.e.ay;
import com.sleepycat.b.i.e.t;
import com.sleepycat.b.i.f.b;
import com.sleepycat.b.i.h.o;
import com.sleepycat.b.i.h.p;
import com.sleepycat.b.i.u;
import com.sleepycat.b.p.ao;
import com.sleepycat.b.p.au;
import com.sleepycat.b.p.w;
import java.io.IOException;
import java.util.Collection;
import java.util.HashSet;
import java.util.Iterator;
import java.util.Set;
import java.util.concurrent.BlockingQueue;
import java.util.concurrent.TimeUnit;
import java.util.logging.Logger;

public class ag
{
  private static ao<com.sleepycat.b.i.h.d> p;
  final aa a;
  public final ac b;
  p c = null;
  public final ai d;
  public t e = null;
  public final com.sleepycat.b.p.ai f;
  aj g;
  public ay<Object> h;
  final c i;
  private final com.sleepycat.b.i.c.aj j;
  private Exception k = null;
  private au l;
  private int m = 0;
  private boolean n = false;
  private final ao<com.sleepycat.b.i.h.d> o;
  private final Logger q;
  private final com.sleepycat.b.p.z r;
  
  ag(aa paramaa, ac paramac)
  {
    this.a = paramaa;
    this.j = paramaa.i;
    m localm = paramaa.i.u;
    this.i = new c(this.j.q, localm.a(an.P), localm.a(an.Q));
    this.d = new ai(this);
    this.b = paramac;
    this.q = w.a(getClass());
    this.f = new com.sleepycat.b.p.ai("BinaryProtocol", "Network traffic due to the replication stream.");
    this.r = paramac.x;
    this.m = paramaa.i.u.a(an.D);
    this.o = p;
  }
  
  private com.sleepycat.b.i.d a(as paramas)
  {
    Object localObject = this.e;
    t localt = this.e;
    localt.getClass();
    ((t)localObject).a(new at(localt), this.c);
    this.c.a(Integer.MAX_VALUE);
    this.a.i.v();
    w.c(this.q, this.j, "Checkpoint initiated.");
    localObject = new com.sleepycat.b.c();
    ((com.sleepycat.b.c)localObject).b = true;
    ((com.sleepycat.b.c)localObject).e = true;
    this.a.i.a((com.sleepycat.b.c)localObject, "Group Shutdown");
    this.a.i.w();
    w.c(this.q, this.j, "Checkpoint completed.");
    return new com.sleepycat.b.i.d(this.q, this.a, paramas.a);
  }
  
  private void a(o paramo, ae paramae)
  {
    t localt1 = this.e;
    t localt2 = this.e;
    localt2.getClass();
    localt1.a(new af(localt2, this.a.p.b, this.l), paramo);
    this.d.a(paramae);
  }
  
  /* Error */
  final void a()
  {
    // Byte code:
    //   0: iconst_0
    //   1: istore 8
    //   3: aconst_null
    //   4: astore_1
    //   5: aload_0
    //   6: aconst_null
    //   7: putfield 48	com/sleepycat/b/i/c/b/ag:k	Ljava/lang/Exception;
    //   10: aload_0
    //   11: getfield 118	com/sleepycat/b/i/c/b/ag:q	Ljava/util/logging/Logger;
    //   14: aload_0
    //   15: getfield 64	com/sleepycat/b/i/c/b/ag:j	Lcom/sleepycat/b/i/c/aj;
    //   18: new 255	java/lang/StringBuilder
    //   21: dup
    //   22: ldc_w 257
    //   25: invokespecial 260	java/lang/StringBuilder:<init>	(Ljava/lang/String;)V
    //   28: aload_0
    //   29: getfield 58	com/sleepycat/b/i/c/b/ag:a	Lcom/sleepycat/b/i/c/b/aa;
    //   32: getfield 263	com/sleepycat/b/i/c/b/aa:g	Lcom/sleepycat/b/i/e/n;
    //   35: invokevirtual 268	com/sleepycat/b/i/e/n:h	()Lcom/sleepycat/b/i/c/b/x;
    //   38: invokevirtual 272	java/lang/StringBuilder:append	(Ljava/lang/Object;)Ljava/lang/StringBuilder;
    //   41: invokevirtual 276	java/lang/StringBuilder:toString	()Ljava/lang/String;
    //   44: invokestatic 175	com/sleepycat/b/p/w:c	(Ljava/util/logging/Logger;Lcom/sleepycat/b/c/ad;Ljava/lang/String;)V
    //   47: aload_0
    //   48: getfield 52	com/sleepycat/b/i/c/b/ag:m	I
    //   51: ifle +40 -> 91
    //   54: aload_0
    //   55: getfield 118	com/sleepycat/b/i/c/b/ag:q	Ljava/util/logging/Logger;
    //   58: aload_0
    //   59: getfield 64	com/sleepycat/b/i/c/b/ag:j	Lcom/sleepycat/b/i/c/aj;
    //   62: new 255	java/lang/StringBuilder
    //   65: dup
    //   66: ldc_w 278
    //   69: invokespecial 260	java/lang/StringBuilder:<init>	(Ljava/lang/String;)V
    //   72: aload_0
    //   73: getfield 52	com/sleepycat/b/i/c/b/ag:m	I
    //   76: invokevirtual 281	java/lang/StringBuilder:append	(I)Ljava/lang/StringBuilder;
    //   79: ldc_w 283
    //   82: invokevirtual 286	java/lang/StringBuilder:append	(Ljava/lang/String;)Ljava/lang/StringBuilder;
    //   85: invokevirtual 276	java/lang/StringBuilder:toString	()Ljava/lang/String;
    //   88: invokestatic 175	com/sleepycat/b/p/w:c	(Ljava/util/logging/Logger;Lcom/sleepycat/b/c/ad;Ljava/lang/String;)V
    //   91: invokestatic 292	java/nio/channels/SocketChannel:open	()Ljava/nio/channels/SocketChannel;
    //   94: astore_2
    //   95: aload_0
    //   96: getfield 58	com/sleepycat/b/i/c/b/ag:a	Lcom/sleepycat/b/i/c/b/aa;
    //   99: getfield 62	com/sleepycat/b/i/c/b/aa:i	Lcom/sleepycat/b/i/c/aj;
    //   102: getfield 70	com/sleepycat/b/c/ad:u	Lcom/sleepycat/b/c/m;
    //   105: astore_3
    //   106: aload_3
    //   107: getstatic 295	com/sleepycat/b/i/c/an:Y	Lcom/sleepycat/b/b/c;
    //   110: invokevirtual 93	com/sleepycat/b/c/m:a	(Lcom/sleepycat/b/b/c;)I
    //   113: istore 9
    //   115: aload_0
    //   116: new 162	com/sleepycat/b/i/h/p
    //   119: dup
    //   120: aload_0
    //   121: getfield 58	com/sleepycat/b/i/c/b/ag:a	Lcom/sleepycat/b/i/c/b/aa;
    //   124: aload_2
    //   125: iload 9
    //   127: invokespecial 298	com/sleepycat/b/i/h/p:<init>	(Lcom/sleepycat/b/i/c/b/aa;Ljava/nio/channels/SocketChannel;I)V
    //   130: putfield 50	com/sleepycat/b/i/c/b/ag:c	Lcom/sleepycat/b/i/h/p;
    //   133: aload_2
    //   134: invokevirtual 302	java/nio/channels/SocketChannel:socket	()Ljava/net/Socket;
    //   137: astore 4
    //   139: aload_3
    //   140: getstatic 304	com/sleepycat/b/i/c/an:d	Lcom/sleepycat/b/b/e;
    //   143: invokevirtual 86	com/sleepycat/b/c/m:a	(Lcom/sleepycat/b/b/e;)I
    //   146: istore 9
    //   148: iload 9
    //   150: ifle +10 -> 160
    //   153: aload 4
    //   155: iload 9
    //   157: invokevirtual 309	java/net/Socket:setReceiveBufferSize	(I)V
    //   160: aload_2
    //   161: iconst_1
    //   162: invokevirtual 313	java/nio/channels/SocketChannel:configureBlocking	(Z)Ljava/nio/channels/SelectableChannel;
    //   165: pop
    //   166: aload 4
    //   168: iconst_1
    //   169: invokevirtual 317	java/net/Socket:setTcpNoDelay	(Z)V
    //   172: aload_3
    //   173: getstatic 320	com/sleepycat/b/i/c/an:F	Lcom/sleepycat/b/b/c;
    //   176: invokevirtual 93	com/sleepycat/b/c/m:a	(Lcom/sleepycat/b/b/c;)I
    //   179: istore 9
    //   181: aload 4
    //   183: aload_0
    //   184: getfield 58	com/sleepycat/b/i/c/b/ag:a	Lcom/sleepycat/b/i/c/b/aa;
    //   187: getfield 263	com/sleepycat/b/i/c/b/aa:g	Lcom/sleepycat/b/i/e/n;
    //   190: invokevirtual 323	com/sleepycat/b/i/e/n:g	()Ljava/net/InetSocketAddress;
    //   193: iload 9
    //   195: invokevirtual 327	java/net/Socket:connect	(Ljava/net/SocketAddress;I)V
    //   198: aload_2
    //   199: ldc_w 329
    //   202: invokestatic 334	com/sleepycat/b/i/h/x:a	(Ljava/nio/channels/SocketChannel;Ljava/lang/String;)V
    //   205: new 336	com/sleepycat/b/i/e/aw
    //   208: dup
    //   209: aload_0
    //   210: getfield 58	com/sleepycat/b/i/c/b/ag:a	Lcom/sleepycat/b/i/c/b/aa;
    //   213: aload_0
    //   214: getfield 50	com/sleepycat/b/i/c/b/ag:c	Lcom/sleepycat/b/i/h/p;
    //   217: invokespecial 339	com/sleepycat/b/i/e/aw:<init>	(Lcom/sleepycat/b/i/c/b/aa;Lcom/sleepycat/b/i/h/o;)V
    //   220: astore_2
    //   221: aload_2
    //   222: getfield 341	com/sleepycat/b/i/e/aw:g	Ljava/util/logging/Logger;
    //   225: aload_2
    //   226: getfield 342	com/sleepycat/b/i/e/aw:a	Lcom/sleepycat/b/i/c/b/aa;
    //   229: getfield 62	com/sleepycat/b/i/c/b/aa:i	Lcom/sleepycat/b/i/c/aj;
    //   232: ldc_w 344
    //   235: invokestatic 175	com/sleepycat/b/p/w:c	(Ljava/util/logging/Logger;Lcom/sleepycat/b/c/ad;Ljava/lang/String;)V
    //   238: aload_2
    //   239: getfield 342	com/sleepycat/b/i/e/aw:a	Lcom/sleepycat/b/i/c/b/aa;
    //   242: invokestatic 347	com/sleepycat/b/i/e/t:a	(Lcom/sleepycat/b/i/c/b/aa;)Lcom/sleepycat/b/i/e/t;
    //   245: astore_3
    //   246: aload_3
    //   247: invokevirtual 111	java/lang/Object:getClass	()Ljava/lang/Class;
    //   250: pop
    //   251: aload_3
    //   252: new 349	com/sleepycat/b/i/e/an
    //   255: dup
    //   256: aload_3
    //   257: invokespecial 350	com/sleepycat/b/i/e/an:<init>	(Lcom/sleepycat/b/i/e/t;)V
    //   260: aload_2
    //   261: getfield 353	com/sleepycat/b/i/e/aw:b	Lcom/sleepycat/b/i/h/o;
    //   264: invokevirtual 159	com/sleepycat/b/i/e/t:a	(Lcom/sleepycat/b/i/h/d;Lcom/sleepycat/b/i/h/o;)V
    //   267: aload_3
    //   268: aload_2
    //   269: getfield 353	com/sleepycat/b/i/e/aw:b	Lcom/sleepycat/b/i/h/o;
    //   272: invokevirtual 356	com/sleepycat/b/i/e/t:a	(Ljava/nio/channels/ReadableByteChannel;)Lcom/sleepycat/b/i/h/d;
    //   275: astore 4
    //   277: aload 4
    //   279: instanceof 358
    //   282: ifeq +898 -> 1180
    //   285: new 360	com/sleepycat/b/aa
    //   288: dup
    //   289: aload_2
    //   290: getfield 342	com/sleepycat/b/i/e/aw:a	Lcom/sleepycat/b/i/c/b/aa;
    //   293: getfield 62	com/sleepycat/b/i/c/b/aa:i	Lcom/sleepycat/b/i/c/aj;
    //   296: getstatic 365	com/sleepycat/b/c/ac:d	Lcom/sleepycat/b/c/ac;
    //   299: new 255	java/lang/StringBuilder
    //   302: dup
    //   303: ldc_w 367
    //   306: invokespecial 260	java/lang/StringBuilder:<init>	(Ljava/lang/String;)V
    //   309: aload_2
    //   310: getfield 370	com/sleepycat/b/i/e/aw:c	Lcom/sleepycat/b/i/c/b/x;
    //   313: invokevirtual 272	java/lang/StringBuilder:append	(Ljava/lang/Object;)Ljava/lang/StringBuilder;
    //   316: ldc_w 372
    //   319: invokevirtual 286	java/lang/StringBuilder:append	(Ljava/lang/String;)Ljava/lang/StringBuilder;
    //   322: aload_2
    //   323: getfield 374	com/sleepycat/b/i/e/aw:d	Lcom/sleepycat/b/i/c/b/x;
    //   326: invokevirtual 272	java/lang/StringBuilder:append	(Ljava/lang/Object;)Ljava/lang/StringBuilder;
    //   329: invokevirtual 276	java/lang/StringBuilder:toString	()Ljava/lang/String;
    //   332: invokespecial 377	com/sleepycat/b/aa:<init>	(Lcom/sleepycat/b/c/ad;Lcom/sleepycat/b/c/ac;Ljava/lang/String;)V
    //   335: athrow
    //   336: astore_2
    //   337: aload_0
    //   338: aload_2
    //   339: putfield 48	com/sleepycat/b/i/c/b/ag:k	Ljava/lang/Exception;
    //   342: aload_2
    //   343: athrow
    //   344: astore_2
    //   345: aload_0
    //   346: getfield 48	com/sleepycat/b/i/c/b/ag:k	Ljava/lang/Exception;
    //   349: ifnull +3987 -> 4336
    //   352: aload_0
    //   353: getfield 48	com/sleepycat/b/i/c/b/ag:k	Ljava/lang/Exception;
    //   356: instanceof 235
    //   359: ifeq +3994 -> 4353
    //   362: aload_0
    //   363: getfield 118	com/sleepycat/b/i/c/b/ag:q	Ljava/util/logging/Logger;
    //   366: aload_0
    //   367: getfield 64	com/sleepycat/b/i/c/b/ag:j	Lcom/sleepycat/b/i/c/aj;
    //   370: new 255	java/lang/StringBuilder
    //   373: dup
    //   374: ldc_w 379
    //   377: invokespecial 260	java/lang/StringBuilder:<init>	(Ljava/lang/String;)V
    //   380: aload_0
    //   381: getfield 48	com/sleepycat/b/i/c/b/ag:k	Ljava/lang/Exception;
    //   384: invokevirtual 382	java/lang/Exception:getMessage	()Ljava/lang/String;
    //   387: invokevirtual 286	java/lang/StringBuilder:append	(Ljava/lang/String;)Ljava/lang/StringBuilder;
    //   390: invokevirtual 276	java/lang/StringBuilder:toString	()Ljava/lang/String;
    //   393: invokestatic 175	com/sleepycat/b/p/w:c	(Ljava/util/logging/Logger;Lcom/sleepycat/b/c/ad;Ljava/lang/String;)V
    //   396: aload_0
    //   397: invokevirtual 384	com/sleepycat/b/i/c/b/ag:c	()V
    //   400: aload_0
    //   401: getfield 50	com/sleepycat/b/i/c/b/ag:c	Lcom/sleepycat/b/i/h/p;
    //   404: invokestatic 389	com/sleepycat/b/i/h/q:a	(Lcom/sleepycat/b/i/h/o;)V
    //   407: aload_0
    //   408: getfield 105	com/sleepycat/b/i/c/b/ag:d	Lcom/sleepycat/b/i/c/b/ai;
    //   411: ifnull +118 -> 529
    //   414: aload_0
    //   415: getfield 105	com/sleepycat/b/i/c/b/ag:d	Lcom/sleepycat/b/i/c/b/ai;
    //   418: astore_3
    //   419: aload_3
    //   420: getfield 392	com/sleepycat/b/i/c/b/ai:k	Lcom/sleepycat/b/i/c/b/ag;
    //   423: getfield 118	com/sleepycat/b/i/c/b/ag:q	Ljava/util/logging/Logger;
    //   426: getstatic 398	java/util/logging/Level:INFO	Ljava/util/logging/Level;
    //   429: invokevirtual 404	java/util/logging/Logger:isLoggable	(Ljava/util/logging/Level;)Z
    //   432: ifeq +97 -> 529
    //   435: aload_3
    //   436: getfield 392	com/sleepycat/b/i/c/b/ai:k	Lcom/sleepycat/b/i/c/b/ag;
    //   439: getfield 118	com/sleepycat/b/i/c/b/ag:q	Ljava/util/logging/Logger;
    //   442: aload_3
    //   443: getfield 392	com/sleepycat/b/i/c/b/ai:k	Lcom/sleepycat/b/i/c/b/ag;
    //   446: getfield 64	com/sleepycat/b/i/c/b/ag:j	Lcom/sleepycat/b/i/c/aj;
    //   449: new 255	java/lang/StringBuilder
    //   452: dup
    //   453: ldc_w 406
    //   456: invokespecial 260	java/lang/StringBuilder:<init>	(Ljava/lang/String;)V
    //   459: aload_3
    //   460: getfield 408	com/sleepycat/b/i/c/b/ai:e	Lcom/sleepycat/b/p/z;
    //   463: invokevirtual 413	com/sleepycat/b/p/z:b	()Ljava/lang/Long;
    //   466: invokevirtual 272	java/lang/StringBuilder:append	(Ljava/lang/Object;)Ljava/lang/StringBuilder;
    //   469: ldc_w 415
    //   472: invokevirtual 286	java/lang/StringBuilder:append	(Ljava/lang/String;)Ljava/lang/StringBuilder;
    //   475: aload_3
    //   476: getfield 417	com/sleepycat/b/i/c/b/ai:f	Lcom/sleepycat/b/p/z;
    //   479: invokevirtual 413	com/sleepycat/b/p/z:b	()Ljava/lang/Long;
    //   482: invokevirtual 272	java/lang/StringBuilder:append	(Ljava/lang/Object;)Ljava/lang/StringBuilder;
    //   485: ldc_w 419
    //   488: invokevirtual 286	java/lang/StringBuilder:append	(Ljava/lang/String;)Ljava/lang/StringBuilder;
    //   491: aload_3
    //   492: getfield 421	com/sleepycat/b/i/c/b/ai:g	Lcom/sleepycat/b/p/z;
    //   495: invokevirtual 413	com/sleepycat/b/p/z:b	()Ljava/lang/Long;
    //   498: invokevirtual 272	java/lang/StringBuilder:append	(Ljava/lang/Object;)Ljava/lang/StringBuilder;
    //   501: ldc_w 415
    //   504: invokevirtual 286	java/lang/StringBuilder:append	(Ljava/lang/String;)Ljava/lang/StringBuilder;
    //   507: aload_3
    //   508: getfield 423	com/sleepycat/b/i/c/b/ai:h	Lcom/sleepycat/b/p/z;
    //   511: invokevirtual 413	com/sleepycat/b/p/z:b	()Ljava/lang/Long;
    //   514: invokevirtual 272	java/lang/StringBuilder:append	(Ljava/lang/Object;)Ljava/lang/StringBuilder;
    //   517: ldc_w 425
    //   520: invokevirtual 286	java/lang/StringBuilder:append	(Ljava/lang/String;)Ljava/lang/StringBuilder;
    //   523: invokevirtual 276	java/lang/StringBuilder:toString	()Ljava/lang/String;
    //   526: invokestatic 175	com/sleepycat/b/p/w:c	(Ljava/util/logging/Logger;Lcom/sleepycat/b/c/ad;Ljava/lang/String;)V
    //   529: aload_0
    //   530: getfield 56	com/sleepycat/b/i/c/b/ag:e	Lcom/sleepycat/b/i/e/t;
    //   533: ifnull +20 -> 553
    //   536: aload_0
    //   537: getfield 129	com/sleepycat/b/i/c/b/ag:f	Lcom/sleepycat/b/p/ai;
    //   540: aload_0
    //   541: getfield 56	com/sleepycat/b/i/c/b/ag:e	Lcom/sleepycat/b/i/e/t;
    //   544: getstatic 430	com/sleepycat/b/bn:a	Lcom/sleepycat/b/bn;
    //   547: invokevirtual 433	com/sleepycat/b/i/e/t:a	(Lcom/sleepycat/b/bn;)Lcom/sleepycat/b/p/ai;
    //   550: invokevirtual 436	com/sleepycat/b/p/ai:a	(Lcom/sleepycat/b/p/ai;)V
    //   553: aload_0
    //   554: aconst_null
    //   555: putfield 56	com/sleepycat/b/i/c/b/ag:e	Lcom/sleepycat/b/i/e/t;
    //   558: aload_2
    //   559: athrow
    //   560: astore_2
    //   561: aload_0
    //   562: getfield 58	com/sleepycat/b/i/c/b/ag:a	Lcom/sleepycat/b/i/c/b/aa;
    //   565: getfield 263	com/sleepycat/b/i/c/b/aa:g	Lcom/sleepycat/b/i/e/n;
    //   568: invokevirtual 439	com/sleepycat/b/i/e/n:c	()Z
    //   571: ifne +3578 -> 4149
    //   574: aload_0
    //   575: getfield 118	com/sleepycat/b/i/c/b/ag:q	Ljava/util/logging/Logger;
    //   578: aload_0
    //   579: getfield 64	com/sleepycat/b/i/c/b/ag:j	Lcom/sleepycat/b/i/c/aj;
    //   582: ldc_w 441
    //   585: invokestatic 443	com/sleepycat/b/p/w:d	(Ljava/util/logging/Logger;Lcom/sleepycat/b/c/ad;Ljava/lang/String;)V
    //   588: aload_0
    //   589: getfield 445	com/sleepycat/b/i/c/b/ag:g	Lcom/sleepycat/b/i/c/b/aj;
    //   592: ifnonnull +14 -> 606
    //   595: aload_0
    //   596: getfield 58	com/sleepycat/b/i/c/b/ag:a	Lcom/sleepycat/b/i/c/b/aa;
    //   599: aload_0
    //   600: getfield 48	com/sleepycat/b/i/c/b/ag:k	Ljava/lang/Exception;
    //   603: invokevirtual 448	com/sleepycat/b/i/c/b/aa:a	(Ljava/lang/Exception;)V
    //   606: return
    //   607: astore_2
    //   608: new 450	com/sleepycat/b/i/c/b/ah
    //   611: dup
    //   612: aload_2
    //   613: invokevirtual 451	java/net/ConnectException:getMessage	()Ljava/lang/String;
    //   616: iconst_2
    //   617: invokespecial 454	com/sleepycat/b/i/c/b/ah:<init>	(Ljava/lang/String;I)V
    //   620: athrow
    //   621: astore_2
    //   622: aload_0
    //   623: getfield 58	com/sleepycat/b/i/c/b/ag:a	Lcom/sleepycat/b/i/c/b/aa;
    //   626: getfield 460	com/sleepycat/b/p/aj:E	Ljava/util/concurrent/atomic/AtomicBoolean;
    //   629: invokevirtual 465	java/util/concurrent/atomic/AtomicBoolean:get	()Z
    //   632: ifeq +3491 -> 4123
    //   635: aload_0
    //   636: getfield 118	com/sleepycat/b/i/c/b/ag:q	Ljava/util/logging/Logger;
    //   639: aload_0
    //   640: getfield 64	com/sleepycat/b/i/c/b/ag:j	Lcom/sleepycat/b/i/c/aj;
    //   643: ldc_w 467
    //   646: invokestatic 175	com/sleepycat/b/p/w:c	(Ljava/util/logging/Logger;Lcom/sleepycat/b/c/ad;Ljava/lang/String;)V
    //   649: aload_0
    //   650: getfield 48	com/sleepycat/b/i/c/b/ag:k	Ljava/lang/Exception;
    //   653: ifnull +3777 -> 4430
    //   656: aload_0
    //   657: getfield 48	com/sleepycat/b/i/c/b/ag:k	Ljava/lang/Exception;
    //   660: instanceof 235
    //   663: ifeq +3784 -> 4447
    //   666: aload_0
    //   667: getfield 118	com/sleepycat/b/i/c/b/ag:q	Ljava/util/logging/Logger;
    //   670: aload_0
    //   671: getfield 64	com/sleepycat/b/i/c/b/ag:j	Lcom/sleepycat/b/i/c/aj;
    //   674: new 255	java/lang/StringBuilder
    //   677: dup
    //   678: ldc_w 379
    //   681: invokespecial 260	java/lang/StringBuilder:<init>	(Ljava/lang/String;)V
    //   684: aload_0
    //   685: getfield 48	com/sleepycat/b/i/c/b/ag:k	Ljava/lang/Exception;
    //   688: invokevirtual 382	java/lang/Exception:getMessage	()Ljava/lang/String;
    //   691: invokevirtual 286	java/lang/StringBuilder:append	(Ljava/lang/String;)Ljava/lang/StringBuilder;
    //   694: invokevirtual 276	java/lang/StringBuilder:toString	()Ljava/lang/String;
    //   697: invokestatic 175	com/sleepycat/b/p/w:c	(Ljava/util/logging/Logger;Lcom/sleepycat/b/c/ad;Ljava/lang/String;)V
    //   700: aload_0
    //   701: invokevirtual 384	com/sleepycat/b/i/c/b/ag:c	()V
    //   704: aload_0
    //   705: getfield 50	com/sleepycat/b/i/c/b/ag:c	Lcom/sleepycat/b/i/h/p;
    //   708: invokestatic 389	com/sleepycat/b/i/h/q:a	(Lcom/sleepycat/b/i/h/o;)V
    //   711: aload_0
    //   712: getfield 105	com/sleepycat/b/i/c/b/ag:d	Lcom/sleepycat/b/i/c/b/ai;
    //   715: ifnull +118 -> 833
    //   718: aload_0
    //   719: getfield 105	com/sleepycat/b/i/c/b/ag:d	Lcom/sleepycat/b/i/c/b/ai;
    //   722: astore_2
    //   723: aload_2
    //   724: getfield 392	com/sleepycat/b/i/c/b/ai:k	Lcom/sleepycat/b/i/c/b/ag;
    //   727: getfield 118	com/sleepycat/b/i/c/b/ag:q	Ljava/util/logging/Logger;
    //   730: getstatic 398	java/util/logging/Level:INFO	Ljava/util/logging/Level;
    //   733: invokevirtual 404	java/util/logging/Logger:isLoggable	(Ljava/util/logging/Level;)Z
    //   736: ifeq +97 -> 833
    //   739: aload_2
    //   740: getfield 392	com/sleepycat/b/i/c/b/ai:k	Lcom/sleepycat/b/i/c/b/ag;
    //   743: getfield 118	com/sleepycat/b/i/c/b/ag:q	Ljava/util/logging/Logger;
    //   746: aload_2
    //   747: getfield 392	com/sleepycat/b/i/c/b/ai:k	Lcom/sleepycat/b/i/c/b/ag;
    //   750: getfield 64	com/sleepycat/b/i/c/b/ag:j	Lcom/sleepycat/b/i/c/aj;
    //   753: new 255	java/lang/StringBuilder
    //   756: dup
    //   757: ldc_w 406
    //   760: invokespecial 260	java/lang/StringBuilder:<init>	(Ljava/lang/String;)V
    //   763: aload_2
    //   764: getfield 408	com/sleepycat/b/i/c/b/ai:e	Lcom/sleepycat/b/p/z;
    //   767: invokevirtual 413	com/sleepycat/b/p/z:b	()Ljava/lang/Long;
    //   770: invokevirtual 272	java/lang/StringBuilder:append	(Ljava/lang/Object;)Ljava/lang/StringBuilder;
    //   773: ldc_w 415
    //   776: invokevirtual 286	java/lang/StringBuilder:append	(Ljava/lang/String;)Ljava/lang/StringBuilder;
    //   779: aload_2
    //   780: getfield 417	com/sleepycat/b/i/c/b/ai:f	Lcom/sleepycat/b/p/z;
    //   783: invokevirtual 413	com/sleepycat/b/p/z:b	()Ljava/lang/Long;
    //   786: invokevirtual 272	java/lang/StringBuilder:append	(Ljava/lang/Object;)Ljava/lang/StringBuilder;
    //   789: ldc_w 419
    //   792: invokevirtual 286	java/lang/StringBuilder:append	(Ljava/lang/String;)Ljava/lang/StringBuilder;
    //   795: aload_2
    //   796: getfield 421	com/sleepycat/b/i/c/b/ai:g	Lcom/sleepycat/b/p/z;
    //   799: invokevirtual 413	com/sleepycat/b/p/z:b	()Ljava/lang/Long;
    //   802: invokevirtual 272	java/lang/StringBuilder:append	(Ljava/lang/Object;)Ljava/lang/StringBuilder;
    //   805: ldc_w 415
    //   808: invokevirtual 286	java/lang/StringBuilder:append	(Ljava/lang/String;)Ljava/lang/StringBuilder;
    //   811: aload_2
    //   812: getfield 423	com/sleepycat/b/i/c/b/ai:h	Lcom/sleepycat/b/p/z;
    //   815: invokevirtual 413	com/sleepycat/b/p/z:b	()Ljava/lang/Long;
    //   818: invokevirtual 272	java/lang/StringBuilder:append	(Ljava/lang/Object;)Ljava/lang/StringBuilder;
    //   821: ldc_w 425
    //   824: invokevirtual 286	java/lang/StringBuilder:append	(Ljava/lang/String;)Ljava/lang/StringBuilder;
    //   827: invokevirtual 276	java/lang/StringBuilder:toString	()Ljava/lang/String;
    //   830: invokestatic 175	com/sleepycat/b/p/w:c	(Ljava/util/logging/Logger;Lcom/sleepycat/b/c/ad;Ljava/lang/String;)V
    //   833: aload_0
    //   834: getfield 56	com/sleepycat/b/i/c/b/ag:e	Lcom/sleepycat/b/i/e/t;
    //   837: ifnull +20 -> 857
    //   840: aload_0
    //   841: getfield 129	com/sleepycat/b/i/c/b/ag:f	Lcom/sleepycat/b/p/ai;
    //   844: aload_0
    //   845: getfield 56	com/sleepycat/b/i/c/b/ag:e	Lcom/sleepycat/b/i/e/t;
    //   848: getstatic 430	com/sleepycat/b/bn:a	Lcom/sleepycat/b/bn;
    //   851: invokevirtual 433	com/sleepycat/b/i/e/t:a	(Lcom/sleepycat/b/bn;)Lcom/sleepycat/b/p/ai;
    //   854: invokevirtual 436	com/sleepycat/b/p/ai:a	(Lcom/sleepycat/b/p/ai;)V
    //   857: aload_0
    //   858: aconst_null
    //   859: putfield 56	com/sleepycat/b/i/c/b/ag:e	Lcom/sleepycat/b/i/e/t;
    //   862: goto -274 -> 588
    //   865: astore_1
    //   866: aload_0
    //   867: getfield 445	com/sleepycat/b/i/c/b/ag:g	Lcom/sleepycat/b/i/c/b/aj;
    //   870: ifnonnull +14 -> 884
    //   873: aload_0
    //   874: getfield 58	com/sleepycat/b/i/c/b/ag:a	Lcom/sleepycat/b/i/c/b/aa;
    //   877: aload_0
    //   878: getfield 48	com/sleepycat/b/i/c/b/ag:k	Ljava/lang/Exception;
    //   881: invokevirtual 448	com/sleepycat/b/i/c/b/aa:a	(Ljava/lang/Exception;)V
    //   884: aload_1
    //   885: athrow
    //   886: astore_2
    //   887: aload_2
    //   888: getfield 470	com/sleepycat/b/i/h/ae:a	Lcom/sleepycat/b/i/h/ac;
    //   891: getstatic 474	com/sleepycat/b/i/h/ac:d	Lcom/sleepycat/b/i/h/ac;
    //   894: if_acmpne +278 -> 1172
    //   897: new 450	com/sleepycat/b/i/c/b/ah
    //   900: dup
    //   901: aload_2
    //   902: invokevirtual 475	com/sleepycat/b/i/h/ae:getMessage	()Ljava/lang/String;
    //   905: bipush 10
    //   907: invokespecial 454	com/sleepycat/b/i/c/b/ah:<init>	(Ljava/lang/String;I)V
    //   910: athrow
    //   911: astore_2
    //   912: aload_0
    //   913: getfield 118	com/sleepycat/b/i/c/b/ag:q	Ljava/util/logging/Logger;
    //   916: aload_0
    //   917: getfield 64	com/sleepycat/b/i/c/b/ag:j	Lcom/sleepycat/b/i/c/aj;
    //   920: new 255	java/lang/StringBuilder
    //   923: dup
    //   924: ldc_w 477
    //   927: invokespecial 260	java/lang/StringBuilder:<init>	(Ljava/lang/String;)V
    //   930: aload_2
    //   931: invokevirtual 478	java/io/IOException:getMessage	()Ljava/lang/String;
    //   934: invokevirtual 286	java/lang/StringBuilder:append	(Ljava/lang/String;)Ljava/lang/StringBuilder;
    //   937: ldc_w 480
    //   940: invokevirtual 286	java/lang/StringBuilder:append	(Ljava/lang/String;)Ljava/lang/StringBuilder;
    //   943: aload_2
    //   944: invokestatic 483	com/sleepycat/b/p/w:a	(Ljava/lang/Throwable;)Ljava/lang/String;
    //   947: invokevirtual 286	java/lang/StringBuilder:append	(Ljava/lang/String;)Ljava/lang/StringBuilder;
    //   950: invokevirtual 276	java/lang/StringBuilder:toString	()Ljava/lang/String;
    //   953: invokestatic 175	com/sleepycat/b/p/w:c	(Ljava/util/logging/Logger;Lcom/sleepycat/b/c/ad;Ljava/lang/String;)V
    //   956: aload_0
    //   957: getfield 48	com/sleepycat/b/i/c/b/ag:k	Ljava/lang/Exception;
    //   960: ifnull +3564 -> 4524
    //   963: aload_0
    //   964: getfield 48	com/sleepycat/b/i/c/b/ag:k	Ljava/lang/Exception;
    //   967: instanceof 235
    //   970: ifeq +3571 -> 4541
    //   973: aload_0
    //   974: getfield 118	com/sleepycat/b/i/c/b/ag:q	Ljava/util/logging/Logger;
    //   977: aload_0
    //   978: getfield 64	com/sleepycat/b/i/c/b/ag:j	Lcom/sleepycat/b/i/c/aj;
    //   981: new 255	java/lang/StringBuilder
    //   984: dup
    //   985: ldc_w 379
    //   988: invokespecial 260	java/lang/StringBuilder:<init>	(Ljava/lang/String;)V
    //   991: aload_0
    //   992: getfield 48	com/sleepycat/b/i/c/b/ag:k	Ljava/lang/Exception;
    //   995: invokevirtual 382	java/lang/Exception:getMessage	()Ljava/lang/String;
    //   998: invokevirtual 286	java/lang/StringBuilder:append	(Ljava/lang/String;)Ljava/lang/StringBuilder;
    //   1001: invokevirtual 276	java/lang/StringBuilder:toString	()Ljava/lang/String;
    //   1004: invokestatic 175	com/sleepycat/b/p/w:c	(Ljava/util/logging/Logger;Lcom/sleepycat/b/c/ad;Ljava/lang/String;)V
    //   1007: aload_0
    //   1008: invokevirtual 384	com/sleepycat/b/i/c/b/ag:c	()V
    //   1011: aload_0
    //   1012: getfield 50	com/sleepycat/b/i/c/b/ag:c	Lcom/sleepycat/b/i/h/p;
    //   1015: invokestatic 389	com/sleepycat/b/i/h/q:a	(Lcom/sleepycat/b/i/h/o;)V
    //   1018: aload_0
    //   1019: getfield 105	com/sleepycat/b/i/c/b/ag:d	Lcom/sleepycat/b/i/c/b/ai;
    //   1022: ifnull +118 -> 1140
    //   1025: aload_0
    //   1026: getfield 105	com/sleepycat/b/i/c/b/ag:d	Lcom/sleepycat/b/i/c/b/ai;
    //   1029: astore_2
    //   1030: aload_2
    //   1031: getfield 392	com/sleepycat/b/i/c/b/ai:k	Lcom/sleepycat/b/i/c/b/ag;
    //   1034: getfield 118	com/sleepycat/b/i/c/b/ag:q	Ljava/util/logging/Logger;
    //   1037: getstatic 398	java/util/logging/Level:INFO	Ljava/util/logging/Level;
    //   1040: invokevirtual 404	java/util/logging/Logger:isLoggable	(Ljava/util/logging/Level;)Z
    //   1043: ifeq +97 -> 1140
    //   1046: aload_2
    //   1047: getfield 392	com/sleepycat/b/i/c/b/ai:k	Lcom/sleepycat/b/i/c/b/ag;
    //   1050: getfield 118	com/sleepycat/b/i/c/b/ag:q	Ljava/util/logging/Logger;
    //   1053: aload_2
    //   1054: getfield 392	com/sleepycat/b/i/c/b/ai:k	Lcom/sleepycat/b/i/c/b/ag;
    //   1057: getfield 64	com/sleepycat/b/i/c/b/ag:j	Lcom/sleepycat/b/i/c/aj;
    //   1060: new 255	java/lang/StringBuilder
    //   1063: dup
    //   1064: ldc_w 406
    //   1067: invokespecial 260	java/lang/StringBuilder:<init>	(Ljava/lang/String;)V
    //   1070: aload_2
    //   1071: getfield 408	com/sleepycat/b/i/c/b/ai:e	Lcom/sleepycat/b/p/z;
    //   1074: invokevirtual 413	com/sleepycat/b/p/z:b	()Ljava/lang/Long;
    //   1077: invokevirtual 272	java/lang/StringBuilder:append	(Ljava/lang/Object;)Ljava/lang/StringBuilder;
    //   1080: ldc_w 415
    //   1083: invokevirtual 286	java/lang/StringBuilder:append	(Ljava/lang/String;)Ljava/lang/StringBuilder;
    //   1086: aload_2
    //   1087: getfield 417	com/sleepycat/b/i/c/b/ai:f	Lcom/sleepycat/b/p/z;
    //   1090: invokevirtual 413	com/sleepycat/b/p/z:b	()Ljava/lang/Long;
    //   1093: invokevirtual 272	java/lang/StringBuilder:append	(Ljava/lang/Object;)Ljava/lang/StringBuilder;
    //   1096: ldc_w 419
    //   1099: invokevirtual 286	java/lang/StringBuilder:append	(Ljava/lang/String;)Ljava/lang/StringBuilder;
    //   1102: aload_2
    //   1103: getfield 421	com/sleepycat/b/i/c/b/ai:g	Lcom/sleepycat/b/p/z;
    //   1106: invokevirtual 413	com/sleepycat/b/p/z:b	()Ljava/lang/Long;
    //   1109: invokevirtual 272	java/lang/StringBuilder:append	(Ljava/lang/Object;)Ljava/lang/StringBuilder;
    //   1112: ldc_w 415
    //   1115: invokevirtual 286	java/lang/StringBuilder:append	(Ljava/lang/String;)Ljava/lang/StringBuilder;
    //   1118: aload_2
    //   1119: getfield 423	com/sleepycat/b/i/c/b/ai:h	Lcom/sleepycat/b/p/z;
    //   1122: invokevirtual 413	com/sleepycat/b/p/z:b	()Ljava/lang/Long;
    //   1125: invokevirtual 272	java/lang/StringBuilder:append	(Ljava/lang/Object;)Ljava/lang/StringBuilder;
    //   1128: ldc_w 425
    //   1131: invokevirtual 286	java/lang/StringBuilder:append	(Ljava/lang/String;)Ljava/lang/StringBuilder;
    //   1134: invokevirtual 276	java/lang/StringBuilder:toString	()Ljava/lang/String;
    //   1137: invokestatic 175	com/sleepycat/b/p/w:c	(Ljava/util/logging/Logger;Lcom/sleepycat/b/c/ad;Ljava/lang/String;)V
    //   1140: aload_0
    //   1141: getfield 56	com/sleepycat/b/i/c/b/ag:e	Lcom/sleepycat/b/i/e/t;
    //   1144: ifnull +20 -> 1164
    //   1147: aload_0
    //   1148: getfield 129	com/sleepycat/b/i/c/b/ag:f	Lcom/sleepycat/b/p/ai;
    //   1151: aload_0
    //   1152: getfield 56	com/sleepycat/b/i/c/b/ag:e	Lcom/sleepycat/b/i/e/t;
    //   1155: getstatic 430	com/sleepycat/b/bn:a	Lcom/sleepycat/b/bn;
    //   1158: invokevirtual 433	com/sleepycat/b/i/e/t:a	(Lcom/sleepycat/b/bn;)Lcom/sleepycat/b/p/ai;
    //   1161: invokevirtual 436	com/sleepycat/b/p/ai:a	(Lcom/sleepycat/b/p/ai;)V
    //   1164: aload_0
    //   1165: aconst_null
    //   1166: putfield 56	com/sleepycat/b/i/c/b/ag:e	Lcom/sleepycat/b/i/e/t;
    //   1169: goto -581 -> 588
    //   1172: aload_2
    //   1173: invokestatic 486	com/sleepycat/b/aa:a	(Ljava/lang/Exception;)Lcom/sleepycat/b/aa;
    //   1176: athrow
    //   1177: astore_2
    //   1178: aload_2
    //   1179: athrow
    //   1180: aload 4
    //   1182: checkcast 488	com/sleepycat/b/i/e/ac
    //   1185: astore 4
    //   1187: aload_2
    //   1188: aload 4
    //   1190: getfield 491	com/sleepycat/b/i/e/al:d	Lcom/sleepycat/b/i/c/b/x;
    //   1193: putfield 374	com/sleepycat/b/i/e/aw:d	Lcom/sleepycat/b/i/c/b/x;
    //   1196: aload_2
    //   1197: getfield 342	com/sleepycat/b/i/e/aw:a	Lcom/sleepycat/b/i/c/b/aa;
    //   1200: aload 4
    //   1202: getfield 493	com/sleepycat/b/i/e/al:c	I
    //   1205: invokestatic 496	com/sleepycat/b/i/e/t:a	(Lcom/sleepycat/b/i/c/b/aa;I)Lcom/sleepycat/b/i/e/t;
    //   1208: astore 5
    //   1210: aload_2
    //   1211: getfield 341	com/sleepycat/b/i/e/aw:g	Ljava/util/logging/Logger;
    //   1214: aload_2
    //   1215: getfield 342	com/sleepycat/b/i/e/aw:a	Lcom/sleepycat/b/i/c/b/aa;
    //   1218: getfield 62	com/sleepycat/b/i/c/b/aa:i	Lcom/sleepycat/b/i/c/aj;
    //   1221: new 255	java/lang/StringBuilder
    //   1224: dup
    //   1225: ldc_w 498
    //   1228: invokespecial 260	java/lang/StringBuilder:<init>	(Ljava/lang/String;)V
    //   1231: aload 4
    //   1233: getfield 491	com/sleepycat/b/i/e/al:d	Lcom/sleepycat/b/i/c/b/x;
    //   1236: invokevirtual 272	java/lang/StringBuilder:append	(Ljava/lang/Object;)Ljava/lang/StringBuilder;
    //   1239: ldc_w 500
    //   1242: invokevirtual 286	java/lang/StringBuilder:append	(Ljava/lang/String;)Ljava/lang/StringBuilder;
    //   1245: aload 4
    //   1247: getfield 493	com/sleepycat/b/i/e/al:c	I
    //   1250: invokevirtual 281	java/lang/StringBuilder:append	(I)Ljava/lang/StringBuilder;
    //   1253: invokevirtual 276	java/lang/StringBuilder:toString	()Ljava/lang/String;
    //   1256: invokestatic 443	com/sleepycat/b/p/w:d	(Ljava/util/logging/Logger;Lcom/sleepycat/b/c/ad;Ljava/lang/String;)V
    //   1259: aload_2
    //   1260: getfield 353	com/sleepycat/b/i/e/aw:b	Lcom/sleepycat/b/i/h/o;
    //   1263: aload_2
    //   1264: getfield 374	com/sleepycat/b/i/e/aw:d	Lcom/sleepycat/b/i/c/b/x;
    //   1267: putfield 504	com/sleepycat/b/i/h/o:a	Lcom/sleepycat/b/i/c/b/x;
    //   1270: aload_2
    //   1271: getfield 341	com/sleepycat/b/i/e/aw:g	Ljava/util/logging/Logger;
    //   1274: aload_2
    //   1275: getfield 342	com/sleepycat/b/i/e/aw:a	Lcom/sleepycat/b/i/c/b/aa;
    //   1278: getfield 62	com/sleepycat/b/i/c/b/aa:i	Lcom/sleepycat/b/i/c/aj;
    //   1281: new 255	java/lang/StringBuilder
    //   1284: dup
    //   1285: ldc_w 506
    //   1288: invokespecial 260	java/lang/StringBuilder:<init>	(Ljava/lang/String;)V
    //   1291: aload_2
    //   1292: getfield 374	com/sleepycat/b/i/e/aw:d	Lcom/sleepycat/b/i/c/b/x;
    //   1295: invokevirtual 272	java/lang/StringBuilder:append	(Ljava/lang/Object;)Ljava/lang/StringBuilder;
    //   1298: ldc_w 508
    //   1301: invokevirtual 286	java/lang/StringBuilder:append	(Ljava/lang/String;)Ljava/lang/StringBuilder;
    //   1304: aload_2
    //   1305: getfield 353	com/sleepycat/b/i/e/aw:b	Lcom/sleepycat/b/i/h/o;
    //   1308: invokevirtual 510	com/sleepycat/b/i/h/o:a	()Ljava/nio/channels/SocketChannel;
    //   1311: invokevirtual 272	java/lang/StringBuilder:append	(Ljava/lang/Object;)Ljava/lang/StringBuilder;
    //   1314: invokevirtual 276	java/lang/StringBuilder:toString	()Ljava/lang/String;
    //   1317: invokestatic 443	com/sleepycat/b/p/w:d	(Ljava/util/logging/Logger;Lcom/sleepycat/b/c/ad;Ljava/lang/String;)V
    //   1320: aload 5
    //   1322: ifnonnull +89 -> 1411
    //   1325: new 360	com/sleepycat/b/aa
    //   1328: dup
    //   1329: aload_2
    //   1330: getfield 342	com/sleepycat/b/i/e/aw:a	Lcom/sleepycat/b/i/c/b/aa;
    //   1333: getfield 62	com/sleepycat/b/i/c/b/aa:i	Lcom/sleepycat/b/i/c/aj;
    //   1336: getstatic 513	com/sleepycat/b/c/ac:t	Lcom/sleepycat/b/c/ac;
    //   1339: new 255	java/lang/StringBuilder
    //   1342: dup
    //   1343: ldc_w 515
    //   1346: invokespecial 260	java/lang/StringBuilder:<init>	(Ljava/lang/String;)V
    //   1349: aload 4
    //   1351: getfield 493	com/sleepycat/b/i/e/al:c	I
    //   1354: invokevirtual 281	java/lang/StringBuilder:append	(I)Ljava/lang/StringBuilder;
    //   1357: ldc_w 517
    //   1360: invokevirtual 286	java/lang/StringBuilder:append	(Ljava/lang/String;)Ljava/lang/StringBuilder;
    //   1363: aload_2
    //   1364: getfield 374	com/sleepycat/b/i/e/aw:d	Lcom/sleepycat/b/i/c/b/x;
    //   1367: invokevirtual 272	java/lang/StringBuilder:append	(Ljava/lang/Object;)Ljava/lang/StringBuilder;
    //   1370: ldc_w 519
    //   1373: invokevirtual 286	java/lang/StringBuilder:append	(Ljava/lang/String;)Ljava/lang/StringBuilder;
    //   1376: aload_2
    //   1377: getfield 370	com/sleepycat/b/i/e/aw:c	Lcom/sleepycat/b/i/c/b/x;
    //   1380: invokevirtual 272	java/lang/StringBuilder:append	(Ljava/lang/Object;)Ljava/lang/StringBuilder;
    //   1383: ldc_w 521
    //   1386: invokevirtual 286	java/lang/StringBuilder:append	(Ljava/lang/String;)Ljava/lang/StringBuilder;
    //   1389: aload_3
    //   1390: getfield 526	com/sleepycat/b/i/h/a:B	I
    //   1393: invokevirtual 281	java/lang/StringBuilder:append	(I)Ljava/lang/StringBuilder;
    //   1396: invokevirtual 276	java/lang/StringBuilder:toString	()Ljava/lang/String;
    //   1399: invokespecial 377	com/sleepycat/b/aa:<init>	(Lcom/sleepycat/b/c/ad;Lcom/sleepycat/b/c/ac;Ljava/lang/String;)V
    //   1402: athrow
    //   1403: astore_2
    //   1404: aload_0
    //   1405: aload_2
    //   1406: putfield 48	com/sleepycat/b/i/c/b/ag:k	Ljava/lang/Exception;
    //   1409: aload_2
    //   1410: athrow
    //   1411: aload_2
    //   1412: aload 5
    //   1414: putfield 527	com/sleepycat/b/i/e/aw:e	Lcom/sleepycat/b/i/e/t;
    //   1417: aload_2
    //   1418: getfield 527	com/sleepycat/b/i/e/aw:e	Lcom/sleepycat/b/i/e/t;
    //   1421: astore_3
    //   1422: aload_2
    //   1423: getfield 527	com/sleepycat/b/i/e/aw:e	Lcom/sleepycat/b/i/e/t;
    //   1426: astore 4
    //   1428: aload 4
    //   1430: invokevirtual 111	java/lang/Object:getClass	()Ljava/lang/Class;
    //   1433: pop
    //   1434: aload_3
    //   1435: new 529	com/sleepycat/b/i/e/am
    //   1438: dup
    //   1439: aload 4
    //   1441: getstatic 534	com/sleepycat/b/am:a	Lcom/sleepycat/b/am;
    //   1444: invokestatic 537	com/sleepycat/b/i/e/aw:a	()I
    //   1447: invokespecial 540	com/sleepycat/b/i/e/am:<init>	(Lcom/sleepycat/b/i/e/t;Lcom/sleepycat/b/am;I)V
    //   1450: aload_2
    //   1451: getfield 353	com/sleepycat/b/i/e/aw:b	Lcom/sleepycat/b/i/h/o;
    //   1454: invokevirtual 159	com/sleepycat/b/i/e/t:a	(Lcom/sleepycat/b/i/h/d;Lcom/sleepycat/b/i/h/o;)V
    //   1457: aload_2
    //   1458: getfield 527	com/sleepycat/b/i/e/aw:e	Lcom/sleepycat/b/i/e/t;
    //   1461: aload_2
    //   1462: getfield 353	com/sleepycat/b/i/e/aw:b	Lcom/sleepycat/b/i/h/o;
    //   1465: invokevirtual 356	com/sleepycat/b/i/e/t:a	(Ljava/nio/channels/ReadableByteChannel;)Lcom/sleepycat/b/i/h/d;
    //   1468: astore_3
    //   1469: aload_3
    //   1470: instanceof 542
    //   1473: ifeq +106 -> 1579
    //   1476: new 360	com/sleepycat/b/aa
    //   1479: dup
    //   1480: aload_2
    //   1481: getfield 342	com/sleepycat/b/i/e/aw:a	Lcom/sleepycat/b/i/c/b/aa;
    //   1484: getfield 62	com/sleepycat/b/i/c/b/aa:i	Lcom/sleepycat/b/i/c/aj;
    //   1487: getstatic 365	com/sleepycat/b/c/ac:d	Lcom/sleepycat/b/c/ac;
    //   1490: new 255	java/lang/StringBuilder
    //   1493: dup
    //   1494: ldc_w 544
    //   1497: invokespecial 260	java/lang/StringBuilder:<init>	(Ljava/lang/String;)V
    //   1500: aload_2
    //   1501: getfield 374	com/sleepycat/b/i/e/aw:d	Lcom/sleepycat/b/i/c/b/x;
    //   1504: invokevirtual 272	java/lang/StringBuilder:append	(Ljava/lang/Object;)Ljava/lang/StringBuilder;
    //   1507: ldc_w 546
    //   1510: invokevirtual 286	java/lang/StringBuilder:append	(Ljava/lang/String;)Ljava/lang/StringBuilder;
    //   1513: aload_3
    //   1514: checkcast 542	com/sleepycat/b/i/e/ah
    //   1517: getfield 551	com/sleepycat/b/i/h/i:b	Ljava/lang/String;
    //   1520: invokevirtual 286	java/lang/StringBuilder:append	(Ljava/lang/String;)Ljava/lang/StringBuilder;
    //   1523: invokevirtual 276	java/lang/StringBuilder:toString	()Ljava/lang/String;
    //   1526: invokespecial 377	com/sleepycat/b/aa:<init>	(Lcom/sleepycat/b/c/ad;Lcom/sleepycat/b/c/ac;Ljava/lang/String;)V
    //   1529: athrow
    //   1530: astore_2
    //   1531: aload_0
    //   1532: aload_2
    //   1533: putfield 48	com/sleepycat/b/i/c/b/ag:k	Ljava/lang/Exception;
    //   1536: aload_0
    //   1537: getfield 118	com/sleepycat/b/i/c/b/ag:q	Ljava/util/logging/Logger;
    //   1540: aload_0
    //   1541: getfield 64	com/sleepycat/b/i/c/b/ag:j	Lcom/sleepycat/b/i/c/aj;
    //   1544: new 255	java/lang/StringBuilder
    //   1547: dup
    //   1548: ldc_w 553
    //   1551: invokespecial 260	java/lang/StringBuilder:<init>	(Ljava/lang/String;)V
    //   1554: aload_2
    //   1555: invokevirtual 272	java/lang/StringBuilder:append	(Ljava/lang/Object;)Ljava/lang/StringBuilder;
    //   1558: ldc_w 555
    //   1561: invokevirtual 286	java/lang/StringBuilder:append	(Ljava/lang/String;)Ljava/lang/StringBuilder;
    //   1564: aload_2
    //   1565: invokestatic 483	com/sleepycat/b/p/w:a	(Ljava/lang/Throwable;)Ljava/lang/String;
    //   1568: invokevirtual 286	java/lang/StringBuilder:append	(Ljava/lang/String;)Ljava/lang/StringBuilder;
    //   1571: invokevirtual 276	java/lang/StringBuilder:toString	()Ljava/lang/String;
    //   1574: invokestatic 557	com/sleepycat/b/p/w:a	(Ljava/util/logging/Logger;Lcom/sleepycat/b/c/ad;Ljava/lang/String;)V
    //   1577: aload_2
    //   1578: athrow
    //   1579: aload_2
    //   1580: aload_3
    //   1581: checkcast 559	com/sleepycat/b/i/e/ab
    //   1584: putfield 562	com/sleepycat/b/i/e/aw:f	Lcom/sleepycat/b/i/e/ab;
    //   1587: aload_2
    //   1588: getfield 562	com/sleepycat/b/i/e/aw:f	Lcom/sleepycat/b/i/e/ab;
    //   1591: invokevirtual 565	com/sleepycat/b/i/e/ab:c	()B
    //   1594: invokestatic 537	com/sleepycat/b/i/e/aw:a	()I
    //   1597: if_icmple +301 -> 1898
    //   1600: new 360	com/sleepycat/b/aa
    //   1603: dup
    //   1604: aload_2
    //   1605: getfield 342	com/sleepycat/b/i/e/aw:a	Lcom/sleepycat/b/i/c/b/aa;
    //   1608: getfield 62	com/sleepycat/b/i/c/b/aa:i	Lcom/sleepycat/b/i/c/aj;
    //   1611: getstatic 365	com/sleepycat/b/c/ac:d	Lcom/sleepycat/b/c/ac;
    //   1614: new 255	java/lang/StringBuilder
    //   1617: dup
    //   1618: ldc_w 544
    //   1621: invokespecial 260	java/lang/StringBuilder:<init>	(Ljava/lang/String;)V
    //   1624: aload_2
    //   1625: getfield 374	com/sleepycat/b/i/e/aw:d	Lcom/sleepycat/b/i/c/b/x;
    //   1628: invokevirtual 272	java/lang/StringBuilder:append	(Ljava/lang/Object;)Ljava/lang/StringBuilder;
    //   1631: ldc_w 567
    //   1634: invokevirtual 286	java/lang/StringBuilder:append	(Ljava/lang/String;)Ljava/lang/StringBuilder;
    //   1637: aload_2
    //   1638: getfield 562	com/sleepycat/b/i/e/aw:f	Lcom/sleepycat/b/i/e/ab;
    //   1641: invokevirtual 565	com/sleepycat/b/i/e/ab:c	()B
    //   1644: invokevirtual 281	java/lang/StringBuilder:append	(I)Ljava/lang/StringBuilder;
    //   1647: ldc_w 569
    //   1650: invokevirtual 286	java/lang/StringBuilder:append	(Ljava/lang/String;)Ljava/lang/StringBuilder;
    //   1653: invokestatic 537	com/sleepycat/b/i/e/aw:a	()I
    //   1656: invokevirtual 281	java/lang/StringBuilder:append	(I)Ljava/lang/StringBuilder;
    //   1659: invokevirtual 276	java/lang/StringBuilder:toString	()Ljava/lang/String;
    //   1662: invokespecial 377	com/sleepycat/b/aa:<init>	(Lcom/sleepycat/b/c/ad;Lcom/sleepycat/b/c/ac;Ljava/lang/String;)V
    //   1665: athrow
    //   1666: astore_2
    //   1667: aload_0
    //   1668: getfield 118	com/sleepycat/b/i/c/b/ag:q	Ljava/util/logging/Logger;
    //   1671: aload_0
    //   1672: getfield 64	com/sleepycat/b/i/c/b/ag:j	Lcom/sleepycat/b/i/c/aj;
    //   1675: aload_2
    //   1676: invokevirtual 570	com/sleepycat/b/i/e/o:getMessage	()Ljava/lang/String;
    //   1679: invokestatic 175	com/sleepycat/b/p/w:c	(Ljava/util/logging/Logger;Lcom/sleepycat/b/c/ad;Ljava/lang/String;)V
    //   1682: aload_0
    //   1683: getfield 48	com/sleepycat/b/i/c/b/ag:k	Ljava/lang/Exception;
    //   1686: ifnull +2932 -> 4618
    //   1689: aload_0
    //   1690: getfield 48	com/sleepycat/b/i/c/b/ag:k	Ljava/lang/Exception;
    //   1693: instanceof 235
    //   1696: ifeq +2939 -> 4635
    //   1699: aload_0
    //   1700: getfield 118	com/sleepycat/b/i/c/b/ag:q	Ljava/util/logging/Logger;
    //   1703: aload_0
    //   1704: getfield 64	com/sleepycat/b/i/c/b/ag:j	Lcom/sleepycat/b/i/c/aj;
    //   1707: new 255	java/lang/StringBuilder
    //   1710: dup
    //   1711: ldc_w 379
    //   1714: invokespecial 260	java/lang/StringBuilder:<init>	(Ljava/lang/String;)V
    //   1717: aload_0
    //   1718: getfield 48	com/sleepycat/b/i/c/b/ag:k	Ljava/lang/Exception;
    //   1721: invokevirtual 382	java/lang/Exception:getMessage	()Ljava/lang/String;
    //   1724: invokevirtual 286	java/lang/StringBuilder:append	(Ljava/lang/String;)Ljava/lang/StringBuilder;
    //   1727: invokevirtual 276	java/lang/StringBuilder:toString	()Ljava/lang/String;
    //   1730: invokestatic 175	com/sleepycat/b/p/w:c	(Ljava/util/logging/Logger;Lcom/sleepycat/b/c/ad;Ljava/lang/String;)V
    //   1733: aload_0
    //   1734: invokevirtual 384	com/sleepycat/b/i/c/b/ag:c	()V
    //   1737: aload_0
    //   1738: getfield 50	com/sleepycat/b/i/c/b/ag:c	Lcom/sleepycat/b/i/h/p;
    //   1741: invokestatic 389	com/sleepycat/b/i/h/q:a	(Lcom/sleepycat/b/i/h/o;)V
    //   1744: aload_0
    //   1745: getfield 105	com/sleepycat/b/i/c/b/ag:d	Lcom/sleepycat/b/i/c/b/ai;
    //   1748: ifnull +118 -> 1866
    //   1751: aload_0
    //   1752: getfield 105	com/sleepycat/b/i/c/b/ag:d	Lcom/sleepycat/b/i/c/b/ai;
    //   1755: astore_2
    //   1756: aload_2
    //   1757: getfield 392	com/sleepycat/b/i/c/b/ai:k	Lcom/sleepycat/b/i/c/b/ag;
    //   1760: getfield 118	com/sleepycat/b/i/c/b/ag:q	Ljava/util/logging/Logger;
    //   1763: getstatic 398	java/util/logging/Level:INFO	Ljava/util/logging/Level;
    //   1766: invokevirtual 404	java/util/logging/Logger:isLoggable	(Ljava/util/logging/Level;)Z
    //   1769: ifeq +97 -> 1866
    //   1772: aload_2
    //   1773: getfield 392	com/sleepycat/b/i/c/b/ai:k	Lcom/sleepycat/b/i/c/b/ag;
    //   1776: getfield 118	com/sleepycat/b/i/c/b/ag:q	Ljava/util/logging/Logger;
    //   1779: aload_2
    //   1780: getfield 392	com/sleepycat/b/i/c/b/ai:k	Lcom/sleepycat/b/i/c/b/ag;
    //   1783: getfield 64	com/sleepycat/b/i/c/b/ag:j	Lcom/sleepycat/b/i/c/aj;
    //   1786: new 255	java/lang/StringBuilder
    //   1789: dup
    //   1790: ldc_w 406
    //   1793: invokespecial 260	java/lang/StringBuilder:<init>	(Ljava/lang/String;)V
    //   1796: aload_2
    //   1797: getfield 408	com/sleepycat/b/i/c/b/ai:e	Lcom/sleepycat/b/p/z;
    //   1800: invokevirtual 413	com/sleepycat/b/p/z:b	()Ljava/lang/Long;
    //   1803: invokevirtual 272	java/lang/StringBuilder:append	(Ljava/lang/Object;)Ljava/lang/StringBuilder;
    //   1806: ldc_w 415
    //   1809: invokevirtual 286	java/lang/StringBuilder:append	(Ljava/lang/String;)Ljava/lang/StringBuilder;
    //   1812: aload_2
    //   1813: getfield 417	com/sleepycat/b/i/c/b/ai:f	Lcom/sleepycat/b/p/z;
    //   1816: invokevirtual 413	com/sleepycat/b/p/z:b	()Ljava/lang/Long;
    //   1819: invokevirtual 272	java/lang/StringBuilder:append	(Ljava/lang/Object;)Ljava/lang/StringBuilder;
    //   1822: ldc_w 419
    //   1825: invokevirtual 286	java/lang/StringBuilder:append	(Ljava/lang/String;)Ljava/lang/StringBuilder;
    //   1828: aload_2
    //   1829: getfield 421	com/sleepycat/b/i/c/b/ai:g	Lcom/sleepycat/b/p/z;
    //   1832: invokevirtual 413	com/sleepycat/b/p/z:b	()Ljava/lang/Long;
    //   1835: invokevirtual 272	java/lang/StringBuilder:append	(Ljava/lang/Object;)Ljava/lang/StringBuilder;
    //   1838: ldc_w 415
    //   1841: invokevirtual 286	java/lang/StringBuilder:append	(Ljava/lang/String;)Ljava/lang/StringBuilder;
    //   1844: aload_2
    //   1845: getfield 423	com/sleepycat/b/i/c/b/ai:h	Lcom/sleepycat/b/p/z;
    //   1848: invokevirtual 413	com/sleepycat/b/p/z:b	()Ljava/lang/Long;
    //   1851: invokevirtual 272	java/lang/StringBuilder:append	(Ljava/lang/Object;)Ljava/lang/StringBuilder;
    //   1854: ldc_w 425
    //   1857: invokevirtual 286	java/lang/StringBuilder:append	(Ljava/lang/String;)Ljava/lang/StringBuilder;
    //   1860: invokevirtual 276	java/lang/StringBuilder:toString	()Ljava/lang/String;
    //   1863: invokestatic 175	com/sleepycat/b/p/w:c	(Ljava/util/logging/Logger;Lcom/sleepycat/b/c/ad;Ljava/lang/String;)V
    //   1866: aload_0
    //   1867: getfield 56	com/sleepycat/b/i/c/b/ag:e	Lcom/sleepycat/b/i/e/t;
    //   1870: ifnull +20 -> 1890
    //   1873: aload_0
    //   1874: getfield 129	com/sleepycat/b/i/c/b/ag:f	Lcom/sleepycat/b/p/ai;
    //   1877: aload_0
    //   1878: getfield 56	com/sleepycat/b/i/c/b/ag:e	Lcom/sleepycat/b/i/e/t;
    //   1881: getstatic 430	com/sleepycat/b/bn:a	Lcom/sleepycat/b/bn;
    //   1884: invokevirtual 433	com/sleepycat/b/i/e/t:a	(Lcom/sleepycat/b/bn;)Lcom/sleepycat/b/p/ai;
    //   1887: invokevirtual 436	com/sleepycat/b/p/ai:a	(Lcom/sleepycat/b/p/ai;)V
    //   1890: aload_0
    //   1891: aconst_null
    //   1892: putfield 56	com/sleepycat/b/i/c/b/ag:e	Lcom/sleepycat/b/i/e/t;
    //   1895: goto -1307 -> 588
    //   1898: aload_2
    //   1899: getfield 342	com/sleepycat/b/i/e/aw:a	Lcom/sleepycat/b/i/c/b/aa;
    //   1902: getfield 62	com/sleepycat/b/i/c/b/aa:i	Lcom/sleepycat/b/i/c/aj;
    //   1905: astore_3
    //   1906: aload_3
    //   1907: getfield 70	com/sleepycat/b/c/ad:u	Lcom/sleepycat/b/c/m;
    //   1910: astore 6
    //   1912: aload 6
    //   1914: getstatic 573	com/sleepycat/b/i/c/an:a	Lcom/sleepycat/b/b/b;
    //   1917: invokevirtual 576	com/sleepycat/b/c/m:a	(Lcom/sleepycat/b/b/b;)Ljava/lang/String;
    //   1920: astore 4
    //   1922: getstatic 579	com/sleepycat/b/i/c/an:q	Lcom/sleepycat/b/i/c/f;
    //   1925: astore 5
    //   1927: aload 6
    //   1929: getstatic 579	com/sleepycat/b/i/c/an:q	Lcom/sleepycat/b/i/c/f;
    //   1932: invokevirtual 576	com/sleepycat/b/c/m:a	(Lcom/sleepycat/b/b/b;)Ljava/lang/String;
    //   1935: astore 6
    //   1937: aload 5
    //   1939: getfield 584	com/sleepycat/b/i/c/f:f	Ljava/lang/Class;
    //   1942: aload 6
    //   1944: invokestatic 590	java/lang/Enum:valueOf	(Ljava/lang/Class;Ljava/lang/String;)Ljava/lang/Enum;
    //   1947: checkcast 592	com/sleepycat/b/i/o
    //   1950: astore 5
    //   1952: aload_2
    //   1953: getfield 527	com/sleepycat/b/i/e/aw:e	Lcom/sleepycat/b/i/e/t;
    //   1956: astore 6
    //   1958: aload 6
    //   1960: invokevirtual 111	java/lang/Object:getClass	()Ljava/lang/Class;
    //   1963: pop
    //   1964: new 594	com/sleepycat/b/i/e/ai
    //   1967: dup
    //   1968: aload 6
    //   1970: aload 4
    //   1972: aload_2
    //   1973: getfield 342	com/sleepycat/b/i/e/aw:a	Lcom/sleepycat/b/i/c/b/aa;
    //   1976: getfield 597	com/sleepycat/b/i/c/b/aa:m	Lcom/sleepycat/b/i/c/t;
    //   1979: getfield 602	com/sleepycat/b/i/c/t:b	Ljava/util/UUID;
    //   1982: aload_2
    //   1983: getfield 370	com/sleepycat/b/i/e/aw:c	Lcom/sleepycat/b/i/c/b/x;
    //   1986: aload_3
    //   1987: invokevirtual 605	com/sleepycat/b/i/c/aj:ab	()Ljava/lang/String;
    //   1990: aload_3
    //   1991: invokevirtual 608	com/sleepycat/b/i/c/aj:ac	()I
    //   1994: aload 5
    //   1996: aload_3
    //   1997: invokevirtual 611	com/sleepycat/b/i/c/aj:ah	()Z
    //   2000: invokespecial 614	com/sleepycat/b/i/e/ai:<init>	(Lcom/sleepycat/b/i/e/t;Ljava/lang/String;Ljava/util/UUID;Lcom/sleepycat/b/i/c/b/x;Ljava/lang/String;ILcom/sleepycat/b/i/o;Z)V
    //   2003: astore 4
    //   2005: aload_2
    //   2006: getfield 527	com/sleepycat/b/i/e/aw:e	Lcom/sleepycat/b/i/e/t;
    //   2009: aload 4
    //   2011: aload_2
    //   2012: getfield 353	com/sleepycat/b/i/e/aw:b	Lcom/sleepycat/b/i/h/o;
    //   2015: invokevirtual 159	com/sleepycat/b/i/e/t:a	(Lcom/sleepycat/b/i/h/d;Lcom/sleepycat/b/i/h/o;)V
    //   2018: aload_2
    //   2019: getfield 527	com/sleepycat/b/i/e/aw:e	Lcom/sleepycat/b/i/e/t;
    //   2022: aload_2
    //   2023: getfield 353	com/sleepycat/b/i/e/aw:b	Lcom/sleepycat/b/i/h/o;
    //   2026: invokevirtual 356	com/sleepycat/b/i/e/t:a	(Ljava/nio/channels/ReadableByteChannel;)Lcom/sleepycat/b/i/h/d;
    //   2029: astore 4
    //   2031: aload 4
    //   2033: instanceof 616
    //   2036: ifeq +293 -> 2329
    //   2039: aload 4
    //   2041: checkcast 616	com/sleepycat/b/i/e/ak
    //   2044: astore 4
    //   2046: new 360	com/sleepycat/b/aa
    //   2049: dup
    //   2050: aload_3
    //   2051: getstatic 365	com/sleepycat/b/c/ac:d	Lcom/sleepycat/b/c/ac;
    //   2054: new 255	java/lang/StringBuilder
    //   2057: dup
    //   2058: ldc_w 544
    //   2061: invokespecial 260	java/lang/StringBuilder:<init>	(Ljava/lang/String;)V
    //   2064: aload_2
    //   2065: getfield 374	com/sleepycat/b/i/e/aw:d	Lcom/sleepycat/b/i/c/b/x;
    //   2068: invokevirtual 272	java/lang/StringBuilder:append	(Ljava/lang/Object;)Ljava/lang/StringBuilder;
    //   2071: ldc_w 546
    //   2074: invokevirtual 286	java/lang/StringBuilder:append	(Ljava/lang/String;)Ljava/lang/StringBuilder;
    //   2077: aload 4
    //   2079: getfield 551	com/sleepycat/b/i/h/i:b	Ljava/lang/String;
    //   2082: invokevirtual 286	java/lang/StringBuilder:append	(Ljava/lang/String;)Ljava/lang/StringBuilder;
    //   2085: invokevirtual 276	java/lang/StringBuilder:toString	()Ljava/lang/String;
    //   2088: invokespecial 377	com/sleepycat/b/aa:<init>	(Lcom/sleepycat/b/c/ad;Lcom/sleepycat/b/c/ac;Ljava/lang/String;)V
    //   2091: athrow
    //   2092: astore_2
    //   2093: aload_0
    //   2094: aload_2
    //   2095: putfield 445	com/sleepycat/b/i/c/b/ag:g	Lcom/sleepycat/b/i/c/b/aj;
    //   2098: aload_0
    //   2099: getfield 118	com/sleepycat/b/i/c/b/ag:q	Ljava/util/logging/Logger;
    //   2102: aload_0
    //   2103: getfield 64	com/sleepycat/b/i/c/b/ag:j	Lcom/sleepycat/b/i/c/aj;
    //   2106: aload_2
    //   2107: invokevirtual 617	com/sleepycat/b/i/c/b/aj:getMessage	()Ljava/lang/String;
    //   2110: invokestatic 175	com/sleepycat/b/p/w:c	(Ljava/util/logging/Logger;Lcom/sleepycat/b/c/ad;Ljava/lang/String;)V
    //   2113: aload_0
    //   2114: getfield 48	com/sleepycat/b/i/c/b/ag:k	Ljava/lang/Exception;
    //   2117: ifnull +2595 -> 4712
    //   2120: aload_0
    //   2121: getfield 48	com/sleepycat/b/i/c/b/ag:k	Ljava/lang/Exception;
    //   2124: instanceof 235
    //   2127: ifeq +2602 -> 4729
    //   2130: aload_0
    //   2131: getfield 118	com/sleepycat/b/i/c/b/ag:q	Ljava/util/logging/Logger;
    //   2134: aload_0
    //   2135: getfield 64	com/sleepycat/b/i/c/b/ag:j	Lcom/sleepycat/b/i/c/aj;
    //   2138: new 255	java/lang/StringBuilder
    //   2141: dup
    //   2142: ldc_w 379
    //   2145: invokespecial 260	java/lang/StringBuilder:<init>	(Ljava/lang/String;)V
    //   2148: aload_0
    //   2149: getfield 48	com/sleepycat/b/i/c/b/ag:k	Ljava/lang/Exception;
    //   2152: invokevirtual 382	java/lang/Exception:getMessage	()Ljava/lang/String;
    //   2155: invokevirtual 286	java/lang/StringBuilder:append	(Ljava/lang/String;)Ljava/lang/StringBuilder;
    //   2158: invokevirtual 276	java/lang/StringBuilder:toString	()Ljava/lang/String;
    //   2161: invokestatic 175	com/sleepycat/b/p/w:c	(Ljava/util/logging/Logger;Lcom/sleepycat/b/c/ad;Ljava/lang/String;)V
    //   2164: aload_0
    //   2165: invokevirtual 384	com/sleepycat/b/i/c/b/ag:c	()V
    //   2168: aload_0
    //   2169: getfield 50	com/sleepycat/b/i/c/b/ag:c	Lcom/sleepycat/b/i/h/p;
    //   2172: invokestatic 389	com/sleepycat/b/i/h/q:a	(Lcom/sleepycat/b/i/h/o;)V
    //   2175: aload_0
    //   2176: getfield 105	com/sleepycat/b/i/c/b/ag:d	Lcom/sleepycat/b/i/c/b/ai;
    //   2179: ifnull +118 -> 2297
    //   2182: aload_0
    //   2183: getfield 105	com/sleepycat/b/i/c/b/ag:d	Lcom/sleepycat/b/i/c/b/ai;
    //   2186: astore_2
    //   2187: aload_2
    //   2188: getfield 392	com/sleepycat/b/i/c/b/ai:k	Lcom/sleepycat/b/i/c/b/ag;
    //   2191: getfield 118	com/sleepycat/b/i/c/b/ag:q	Ljava/util/logging/Logger;
    //   2194: getstatic 398	java/util/logging/Level:INFO	Ljava/util/logging/Level;
    //   2197: invokevirtual 404	java/util/logging/Logger:isLoggable	(Ljava/util/logging/Level;)Z
    //   2200: ifeq +97 -> 2297
    //   2203: aload_2
    //   2204: getfield 392	com/sleepycat/b/i/c/b/ai:k	Lcom/sleepycat/b/i/c/b/ag;
    //   2207: getfield 118	com/sleepycat/b/i/c/b/ag:q	Ljava/util/logging/Logger;
    //   2210: aload_2
    //   2211: getfield 392	com/sleepycat/b/i/c/b/ai:k	Lcom/sleepycat/b/i/c/b/ag;
    //   2214: getfield 64	com/sleepycat/b/i/c/b/ag:j	Lcom/sleepycat/b/i/c/aj;
    //   2217: new 255	java/lang/StringBuilder
    //   2220: dup
    //   2221: ldc_w 406
    //   2224: invokespecial 260	java/lang/StringBuilder:<init>	(Ljava/lang/String;)V
    //   2227: aload_2
    //   2228: getfield 408	com/sleepycat/b/i/c/b/ai:e	Lcom/sleepycat/b/p/z;
    //   2231: invokevirtual 413	com/sleepycat/b/p/z:b	()Ljava/lang/Long;
    //   2234: invokevirtual 272	java/lang/StringBuilder:append	(Ljava/lang/Object;)Ljava/lang/StringBuilder;
    //   2237: ldc_w 415
    //   2240: invokevirtual 286	java/lang/StringBuilder:append	(Ljava/lang/String;)Ljava/lang/StringBuilder;
    //   2243: aload_2
    //   2244: getfield 417	com/sleepycat/b/i/c/b/ai:f	Lcom/sleepycat/b/p/z;
    //   2247: invokevirtual 413	com/sleepycat/b/p/z:b	()Ljava/lang/Long;
    //   2250: invokevirtual 272	java/lang/StringBuilder:append	(Ljava/lang/Object;)Ljava/lang/StringBuilder;
    //   2253: ldc_w 419
    //   2256: invokevirtual 286	java/lang/StringBuilder:append	(Ljava/lang/String;)Ljava/lang/StringBuilder;
    //   2259: aload_2
    //   2260: getfield 421	com/sleepycat/b/i/c/b/ai:g	Lcom/sleepycat/b/p/z;
    //   2263: invokevirtual 413	com/sleepycat/b/p/z:b	()Ljava/lang/Long;
    //   2266: invokevirtual 272	java/lang/StringBuilder:append	(Ljava/lang/Object;)Ljava/lang/StringBuilder;
    //   2269: ldc_w 415
    //   2272: invokevirtual 286	java/lang/StringBuilder:append	(Ljava/lang/String;)Ljava/lang/StringBuilder;
    //   2275: aload_2
    //   2276: getfield 423	com/sleepycat/b/i/c/b/ai:h	Lcom/sleepycat/b/p/z;
    //   2279: invokevirtual 413	com/sleepycat/b/p/z:b	()Ljava/lang/Long;
    //   2282: invokevirtual 272	java/lang/StringBuilder:append	(Ljava/lang/Object;)Ljava/lang/StringBuilder;
    //   2285: ldc_w 425
    //   2288: invokevirtual 286	java/lang/StringBuilder:append	(Ljava/lang/String;)Ljava/lang/StringBuilder;
    //   2291: invokevirtual 276	java/lang/StringBuilder:toString	()Ljava/lang/String;
    //   2294: invokestatic 175	com/sleepycat/b/p/w:c	(Ljava/util/logging/Logger;Lcom/sleepycat/b/c/ad;Ljava/lang/String;)V
    //   2297: aload_0
    //   2298: getfield 56	com/sleepycat/b/i/c/b/ag:e	Lcom/sleepycat/b/i/e/t;
    //   2301: ifnull +20 -> 2321
    //   2304: aload_0
    //   2305: getfield 129	com/sleepycat/b/i/c/b/ag:f	Lcom/sleepycat/b/p/ai;
    //   2308: aload_0
    //   2309: getfield 56	com/sleepycat/b/i/c/b/ag:e	Lcom/sleepycat/b/i/e/t;
    //   2312: getstatic 430	com/sleepycat/b/bn:a	Lcom/sleepycat/b/bn;
    //   2315: invokevirtual 433	com/sleepycat/b/i/e/t:a	(Lcom/sleepycat/b/bn;)Lcom/sleepycat/b/p/ai;
    //   2318: invokevirtual 436	com/sleepycat/b/p/ai:a	(Lcom/sleepycat/b/p/ai;)V
    //   2321: aload_0
    //   2322: aconst_null
    //   2323: putfield 56	com/sleepycat/b/i/c/b/ag:e	Lcom/sleepycat/b/i/e/t;
    //   2326: goto -1738 -> 588
    //   2329: aload 4
    //   2331: instanceof 619
    //   2334: ifne +98 -> 2432
    //   2337: new 360	com/sleepycat/b/aa
    //   2340: dup
    //   2341: aload_3
    //   2342: getstatic 365	com/sleepycat/b/c/ac:d	Lcom/sleepycat/b/c/ac;
    //   2345: new 255	java/lang/StringBuilder
    //   2348: dup
    //   2349: ldc_w 544
    //   2352: invokespecial 260	java/lang/StringBuilder:<init>	(Ljava/lang/String;)V
    //   2355: aload_2
    //   2356: getfield 374	com/sleepycat/b/i/e/aw:d	Lcom/sleepycat/b/i/c/b/x;
    //   2359: invokevirtual 272	java/lang/StringBuilder:append	(Ljava/lang/Object;)Ljava/lang/StringBuilder;
    //   2362: ldc_w 621
    //   2365: invokevirtual 286	java/lang/StringBuilder:append	(Ljava/lang/String;)Ljava/lang/StringBuilder;
    //   2368: aload 4
    //   2370: invokevirtual 272	java/lang/StringBuilder:append	(Ljava/lang/Object;)Ljava/lang/StringBuilder;
    //   2373: invokevirtual 276	java/lang/StringBuilder:toString	()Ljava/lang/String;
    //   2376: invokespecial 377	com/sleepycat/b/aa:<init>	(Lcom/sleepycat/b/c/ad;Lcom/sleepycat/b/c/ac;Ljava/lang/String;)V
    //   2379: athrow
    //   2380: astore_2
    //   2381: aload_0
    //   2382: aload_2
    //   2383: putfield 48	com/sleepycat/b/i/c/b/ag:k	Ljava/lang/Exception;
    //   2386: aload_0
    //   2387: getfield 118	com/sleepycat/b/i/c/b/ag:q	Ljava/util/logging/Logger;
    //   2390: aload_0
    //   2391: getfield 64	com/sleepycat/b/i/c/b/ag:j	Lcom/sleepycat/b/i/c/aj;
    //   2394: new 255	java/lang/StringBuilder
    //   2397: dup
    //   2398: ldc_w 553
    //   2401: invokespecial 260	java/lang/StringBuilder:<init>	(Ljava/lang/String;)V
    //   2404: aload_2
    //   2405: invokevirtual 272	java/lang/StringBuilder:append	(Ljava/lang/Object;)Ljava/lang/StringBuilder;
    //   2408: ldc_w 555
    //   2411: invokevirtual 286	java/lang/StringBuilder:append	(Ljava/lang/String;)Ljava/lang/StringBuilder;
    //   2414: aload_2
    //   2415: invokestatic 483	com/sleepycat/b/p/w:a	(Ljava/lang/Throwable;)Ljava/lang/String;
    //   2418: invokevirtual 286	java/lang/StringBuilder:append	(Ljava/lang/String;)Ljava/lang/StringBuilder;
    //   2421: invokevirtual 276	java/lang/StringBuilder:toString	()Ljava/lang/String;
    //   2424: invokestatic 557	com/sleepycat/b/p/w:a	(Ljava/util/logging/Logger;Lcom/sleepycat/b/c/ad;Ljava/lang/String;)V
    //   2427: aload_2
    //   2428: invokestatic 486	com/sleepycat/b/aa:a	(Ljava/lang/Exception;)Lcom/sleepycat/b/aa;
    //   2431: athrow
    //   2432: aload_2
    //   2433: getfield 342	com/sleepycat/b/i/e/aw:a	Lcom/sleepycat/b/i/c/b/aa;
    //   2436: getfield 597	com/sleepycat/b/i/c/b/aa:m	Lcom/sleepycat/b/i/c/t;
    //   2439: invokevirtual 623	com/sleepycat/b/i/c/t:a	()Z
    //   2442: ifeq +56 -> 2498
    //   2445: aload_2
    //   2446: getfield 342	com/sleepycat/b/i/e/aw:a	Lcom/sleepycat/b/i/c/b/aa;
    //   2449: getfield 597	com/sleepycat/b/i/c/b/aa:m	Lcom/sleepycat/b/i/c/t;
    //   2452: astore_3
    //   2453: aload 4
    //   2455: checkcast 619	com/sleepycat/b/i/e/aj
    //   2458: getfield 625	com/sleepycat/b/i/e/aj:a	Ljava/util/UUID;
    //   2461: astore 4
    //   2463: aload_3
    //   2464: invokevirtual 623	com/sleepycat/b/i/c/t:a	()Z
    //   2467: ifne +25 -> 2492
    //   2470: new 255	java/lang/StringBuilder
    //   2473: dup
    //   2474: ldc_w 627
    //   2477: invokespecial 260	java/lang/StringBuilder:<init>	(Ljava/lang/String;)V
    //   2480: aload 4
    //   2482: invokevirtual 272	java/lang/StringBuilder:append	(Ljava/lang/Object;)Ljava/lang/StringBuilder;
    //   2485: invokevirtual 276	java/lang/StringBuilder:toString	()Ljava/lang/String;
    //   2488: invokestatic 630	com/sleepycat/b/aa:c	(Ljava/lang/String;)Lcom/sleepycat/b/aa;
    //   2491: athrow
    //   2492: aload_3
    //   2493: aload 4
    //   2495: putfield 602	com/sleepycat/b/i/c/t:b	Ljava/util/UUID;
    //   2498: aload_2
    //   2499: invokevirtual 632	com/sleepycat/b/i/e/aw:b	()V
    //   2502: aload_2
    //   2503: getfield 341	com/sleepycat/b/i/e/aw:g	Ljava/util/logging/Logger;
    //   2506: aload_2
    //   2507: getfield 342	com/sleepycat/b/i/e/aw:a	Lcom/sleepycat/b/i/c/b/aa;
    //   2510: getfield 62	com/sleepycat/b/i/c/b/aa:i	Lcom/sleepycat/b/i/c/aj;
    //   2513: new 255	java/lang/StringBuilder
    //   2516: dup
    //   2517: ldc_w 634
    //   2520: invokespecial 260	java/lang/StringBuilder:<init>	(Ljava/lang/String;)V
    //   2523: aload_2
    //   2524: getfield 374	com/sleepycat/b/i/e/aw:d	Lcom/sleepycat/b/i/c/b/x;
    //   2527: getfield 638	com/sleepycat/b/i/c/b/x:a	Ljava/lang/String;
    //   2530: invokevirtual 286	java/lang/StringBuilder:append	(Ljava/lang/String;)Ljava/lang/StringBuilder;
    //   2533: ldc_w 640
    //   2536: invokevirtual 286	java/lang/StringBuilder:append	(Ljava/lang/String;)Ljava/lang/StringBuilder;
    //   2539: invokevirtual 276	java/lang/StringBuilder:toString	()Ljava/lang/String;
    //   2542: invokestatic 175	com/sleepycat/b/p/w:c	(Ljava/util/logging/Logger;Lcom/sleepycat/b/c/ad;Ljava/lang/String;)V
    //   2545: aload_0
    //   2546: aload_2
    //   2547: getfield 527	com/sleepycat/b/i/e/aw:e	Lcom/sleepycat/b/i/e/t;
    //   2550: putfield 56	com/sleepycat/b/i/c/b/ag:e	Lcom/sleepycat/b/i/e/t;
    //   2553: aload_0
    //   2554: getfield 58	com/sleepycat/b/i/c/b/ag:a	Lcom/sleepycat/b/i/c/b/aa;
    //   2557: astore_2
    //   2558: aload_2
    //   2559: getfield 643	com/sleepycat/b/i/c/b/aa:h	Lcom/sleepycat/b/i/c/b/z;
    //   2562: getstatic 648	com/sleepycat/b/i/u:d	Lcom/sleepycat/b/i/u;
    //   2565: aload_2
    //   2566: getfield 263	com/sleepycat/b/i/c/b/aa:g	Lcom/sleepycat/b/i/e/n;
    //   2569: invokevirtual 268	com/sleepycat/b/i/e/n:h	()Lcom/sleepycat/b/i/c/b/x;
    //   2572: invokevirtual 653	com/sleepycat/b/i/c/b/z:a	(Lcom/sleepycat/b/i/u;Lcom/sleepycat/b/i/c/b/x;)V
    //   2575: aload_0
    //   2576: getfield 445	com/sleepycat/b/i/c/b/ag:g	Lcom/sleepycat/b/i/c/b/aj;
    //   2579: ifnull +421 -> 3000
    //   2582: aload_0
    //   2583: getfield 118	com/sleepycat/b/i/c/b/ag:q	Ljava/util/logging/Logger;
    //   2586: aload_0
    //   2587: getfield 64	com/sleepycat/b/i/c/b/ag:j	Lcom/sleepycat/b/i/c/aj;
    //   2590: new 255	java/lang/StringBuilder
    //   2593: dup
    //   2594: ldc_w 655
    //   2597: invokespecial 260	java/lang/StringBuilder:<init>	(Ljava/lang/String;)V
    //   2600: aload_0
    //   2601: getfield 445	com/sleepycat/b/i/c/b/ag:g	Lcom/sleepycat/b/i/c/b/aj;
    //   2604: getfield 656	com/sleepycat/b/i/c/b/aj:a	Lcom/sleepycat/b/i/c/b/x;
    //   2607: invokevirtual 272	java/lang/StringBuilder:append	(Ljava/lang/Object;)Ljava/lang/StringBuilder;
    //   2610: ldc_w 658
    //   2613: invokevirtual 286	java/lang/StringBuilder:append	(Ljava/lang/String;)Ljava/lang/StringBuilder;
    //   2616: aload_0
    //   2617: getfield 58	com/sleepycat/b/i/c/b/ag:a	Lcom/sleepycat/b/i/c/b/aa;
    //   2620: getfield 263	com/sleepycat/b/i/c/b/aa:g	Lcom/sleepycat/b/i/e/n;
    //   2623: invokevirtual 268	com/sleepycat/b/i/e/n:h	()Lcom/sleepycat/b/i/c/b/x;
    //   2626: invokevirtual 272	java/lang/StringBuilder:append	(Ljava/lang/Object;)Ljava/lang/StringBuilder;
    //   2629: invokevirtual 276	java/lang/StringBuilder:toString	()Ljava/lang/String;
    //   2632: invokestatic 175	com/sleepycat/b/p/w:c	(Ljava/util/logging/Logger;Lcom/sleepycat/b/c/ad;Ljava/lang/String;)V
    //   2635: iconst_0
    //   2636: istore 14
    //   2638: aload_0
    //   2639: aconst_null
    //   2640: putfield 445	com/sleepycat/b/i/c/b/ag:g	Lcom/sleepycat/b/i/c/b/aj;
    //   2643: new 660	com/sleepycat/b/i/e/ax
    //   2646: dup
    //   2647: aload_0
    //   2648: getfield 58	com/sleepycat/b/i/c/b/ag:a	Lcom/sleepycat/b/i/c/b/aa;
    //   2651: aload_0
    //   2652: getfield 107	com/sleepycat/b/i/c/b/ag:b	Lcom/sleepycat/b/i/c/b/ac;
    //   2655: aload_0
    //   2656: getfield 50	com/sleepycat/b/i/c/b/ag:c	Lcom/sleepycat/b/i/h/p;
    //   2659: aload_0
    //   2660: getfield 56	com/sleepycat/b/i/c/b/ag:e	Lcom/sleepycat/b/i/e/t;
    //   2663: iload 14
    //   2665: invokespecial 663	com/sleepycat/b/i/e/ax:<init>	(Lcom/sleepycat/b/i/c/b/aa;Lcom/sleepycat/b/i/c/b/ac;Lcom/sleepycat/b/i/h/o;Lcom/sleepycat/b/i/e/t;Z)V
    //   2668: astore_2
    //   2669: aload_0
    //   2670: getfield 58	com/sleepycat/b/i/c/b/ag:a	Lcom/sleepycat/b/i/c/b/aa;
    //   2673: getfield 214	com/sleepycat/b/i/c/b/aa:p	Lcom/sleepycat/b/i/c/b/q;
    //   2676: astore 4
    //   2678: invokestatic 669	java/lang/System:currentTimeMillis	()J
    //   2681: lstore 10
    //   2683: aload_2
    //   2684: getfield 670	com/sleepycat/b/i/e/ax:b	Lcom/sleepycat/b/i/h/o;
    //   2687: getfield 504	com/sleepycat/b/i/h/o:a	Lcom/sleepycat/b/i/c/b/x;
    //   2690: getfield 638	com/sleepycat/b/i/c/b/x:a	Ljava/lang/String;
    //   2693: astore_3
    //   2694: aload_2
    //   2695: getfield 672	com/sleepycat/b/i/e/ax:a	Ljava/util/logging/Logger;
    //   2698: aload_2
    //   2699: getfield 674	com/sleepycat/b/i/e/ax:g	Lcom/sleepycat/b/i/c/aj;
    //   2702: new 255	java/lang/StringBuilder
    //   2705: dup
    //   2706: ldc_w 634
    //   2709: invokespecial 260	java/lang/StringBuilder:<init>	(Ljava/lang/String;)V
    //   2712: aload_3
    //   2713: invokevirtual 286	java/lang/StringBuilder:append	(Ljava/lang/String;)Ljava/lang/StringBuilder;
    //   2716: ldc_w 676
    //   2719: invokevirtual 286	java/lang/StringBuilder:append	(Ljava/lang/String;)Ljava/lang/StringBuilder;
    //   2722: aload_2
    //   2723: getfield 678	com/sleepycat/b/i/e/ax:d	Lcom/sleepycat/b/i/c/b/aa;
    //   2726: getfield 62	com/sleepycat/b/i/c/b/aa:i	Lcom/sleepycat/b/i/c/aj;
    //   2729: getfield 682	com/sleepycat/b/i/c/aj:aj	Lcom/sleepycat/b/i/i/f;
    //   2732: getfield 687	com/sleepycat/b/i/i/f:h	Lcom/sleepycat/b/i/i/p;
    //   2735: invokevirtual 692	com/sleepycat/b/i/i/p:b	()Lcom/sleepycat/b/i/i/m;
    //   2738: invokevirtual 272	java/lang/StringBuilder:append	(Ljava/lang/Object;)Ljava/lang/StringBuilder;
    //   2741: invokevirtual 276	java/lang/StringBuilder:toString	()Ljava/lang/String;
    //   2744: invokestatic 175	com/sleepycat/b/p/w:c	(Ljava/util/logging/Logger;Lcom/sleepycat/b/c/ad;Ljava/lang/String;)V
    //   2747: aload_2
    //   2748: getfield 678	com/sleepycat/b/i/e/ax:d	Lcom/sleepycat/b/i/c/b/aa;
    //   2751: getfield 695	com/sleepycat/b/i/c/b/aa:r	Lcom/sleepycat/b/i/c/b/o;
    //   2754: invokevirtual 699	com/sleepycat/b/i/c/b/o:a	()V
    //   2757: aload_2
    //   2758: getfield 701	com/sleepycat/b/i/e/ax:e	Lcom/sleepycat/b/i/i/f;
    //   2761: getfield 687	com/sleepycat/b/i/i/f:h	Lcom/sleepycat/b/i/i/p;
    //   2764: invokevirtual 692	com/sleepycat/b/i/i/p:b	()Lcom/sleepycat/b/i/i/m;
    //   2767: astore 5
    //   2769: aload_2
    //   2770: aload 5
    //   2772: invokevirtual 704	com/sleepycat/b/i/e/ax:a	(Lcom/sleepycat/b/i/i/m;)V
    //   2775: aload_2
    //   2776: getfield 674	com/sleepycat/b/i/e/ax:g	Lcom/sleepycat/b/i/c/aj;
    //   2779: astore 6
    //   2781: getstatic 708	com/sleepycat/b/i/ad:b	I
    //   2784: istore 9
    //   2786: aload 6
    //   2788: invokevirtual 710	com/sleepycat/b/i/c/aj:aj	()V
    //   2791: aload 5
    //   2793: getfield 714	com/sleepycat/b/i/i/m:g	Lcom/sleepycat/b/p/au;
    //   2796: astore 6
    //   2798: aload 5
    //   2800: getfield 716	com/sleepycat/b/i/i/m:f	Lcom/sleepycat/b/p/au;
    //   2803: astore 7
    //   2805: aload_2
    //   2806: getfield 672	com/sleepycat/b/i/e/ax:a	Ljava/util/logging/Logger;
    //   2809: aload_2
    //   2810: getfield 674	com/sleepycat/b/i/e/ax:g	Lcom/sleepycat/b/i/c/aj;
    //   2813: new 255	java/lang/StringBuilder
    //   2816: dup
    //   2817: ldc_w 718
    //   2820: invokespecial 260	java/lang/StringBuilder:<init>	(Ljava/lang/String;)V
    //   2823: aload 5
    //   2825: invokevirtual 272	java/lang/StringBuilder:append	(Ljava/lang/Object;)Ljava/lang/StringBuilder;
    //   2828: ldc_w 720
    //   2831: invokevirtual 286	java/lang/StringBuilder:append	(Ljava/lang/String;)Ljava/lang/StringBuilder;
    //   2834: aload_2
    //   2835: getfield 723	com/sleepycat/b/i/e/ax:k	Lcom/sleepycat/b/i/e/q;
    //   2838: invokevirtual 272	java/lang/StringBuilder:append	(Ljava/lang/Object;)Ljava/lang/StringBuilder;
    //   2841: invokevirtual 276	java/lang/StringBuilder:toString	()Ljava/lang/String;
    //   2844: invokestatic 725	com/sleepycat/b/p/w:e	(Ljava/util/logging/Logger;Lcom/sleepycat/b/c/ad;Ljava/lang/String;)V
    //   2847: aload 6
    //   2849: invokevirtual 728	com/sleepycat/b/p/au:c	()Z
    //   2852: ifeq +777 -> 3629
    //   2855: aload 5
    //   2857: getfield 716	com/sleepycat/b/i/i/m:f	Lcom/sleepycat/b/p/au;
    //   2860: invokevirtual 728	com/sleepycat/b/p/au:c	()Z
    //   2863: ifeq +143 -> 3006
    //   2866: aload_2
    //   2867: getfield 730	com/sleepycat/b/i/e/ax:h	Lcom/sleepycat/b/p/au;
    //   2870: invokevirtual 728	com/sleepycat/b/p/au:c	()Z
    //   2873: ifne +133 -> 3006
    //   2876: aload_2
    //   2877: getfield 678	com/sleepycat/b/i/e/ax:d	Lcom/sleepycat/b/i/c/b/aa;
    //   2880: getfield 62	com/sleepycat/b/i/c/b/aa:i	Lcom/sleepycat/b/i/c/aj;
    //   2883: new 255	java/lang/StringBuilder
    //   2886: dup
    //   2887: ldc_w 732
    //   2890: invokespecial 260	java/lang/StringBuilder:<init>	(Ljava/lang/String;)V
    //   2893: aload_2
    //   2894: getfield 730	com/sleepycat/b/i/e/ax:h	Lcom/sleepycat/b/p/au;
    //   2897: invokevirtual 272	java/lang/StringBuilder:append	(Ljava/lang/Object;)Ljava/lang/StringBuilder;
    //   2900: ldc_w 734
    //   2903: invokevirtual 286	java/lang/StringBuilder:append	(Ljava/lang/String;)Ljava/lang/StringBuilder;
    //   2906: aload 5
    //   2908: invokevirtual 272	java/lang/StringBuilder:append	(Ljava/lang/Object;)Ljava/lang/StringBuilder;
    //   2911: invokevirtual 276	java/lang/StringBuilder:toString	()Ljava/lang/String;
    //   2914: invokestatic 737	com/sleepycat/b/aa:a	(Lcom/sleepycat/b/c/ad;Ljava/lang/String;)Lcom/sleepycat/b/aa;
    //   2917: athrow
    //   2918: astore 4
    //   2920: aload_2
    //   2921: getfield 678	com/sleepycat/b/i/e/ax:d	Lcom/sleepycat/b/i/c/b/aa;
    //   2924: getfield 695	com/sleepycat/b/i/c/b/aa:r	Lcom/sleepycat/b/i/c/b/o;
    //   2927: invokevirtual 738	com/sleepycat/b/i/c/b/o:b	()V
    //   2930: aload_2
    //   2931: getfield 672	com/sleepycat/b/i/e/ax:a	Ljava/util/logging/Logger;
    //   2934: aload_2
    //   2935: getfield 674	com/sleepycat/b/i/e/ax:g	Lcom/sleepycat/b/i/c/aj;
    //   2938: new 255	java/lang/StringBuilder
    //   2941: dup
    //   2942: ldc_w 634
    //   2945: invokespecial 260	java/lang/StringBuilder:<init>	(Ljava/lang/String;)V
    //   2948: aload_3
    //   2949: invokevirtual 286	java/lang/StringBuilder:append	(Ljava/lang/String;)Ljava/lang/StringBuilder;
    //   2952: ldc_w 740
    //   2955: invokevirtual 286	java/lang/StringBuilder:append	(Ljava/lang/String;)Ljava/lang/StringBuilder;
    //   2958: invokevirtual 276	java/lang/StringBuilder:toString	()Ljava/lang/String;
    //   2961: iconst_1
    //   2962: anewarray 4	java/lang/Object
    //   2965: dup
    //   2966: iconst_0
    //   2967: invokestatic 669	java/lang/System:currentTimeMillis	()J
    //   2970: lload 10
    //   2972: lsub
    //   2973: invokestatic 745	java/lang/Long:valueOf	(J)Ljava/lang/Long;
    //   2976: aastore
    //   2977: invokestatic 751	java/lang/String:format	(Ljava/lang/String;[Ljava/lang/Object;)Ljava/lang/String;
    //   2980: invokestatic 175	com/sleepycat/b/p/w:c	(Ljava/util/logging/Logger;Lcom/sleepycat/b/c/ad;Ljava/lang/String;)V
    //   2983: aload_2
    //   2984: getfield 674	com/sleepycat/b/i/e/ax:g	Lcom/sleepycat/b/i/c/aj;
    //   2987: astore_2
    //   2988: getstatic 753	com/sleepycat/b/i/ad:d	I
    //   2991: istore 9
    //   2993: aload_2
    //   2994: invokevirtual 710	com/sleepycat/b/i/c/aj:aj	()V
    //   2997: aload 4
    //   2999: athrow
    //   3000: iconst_1
    //   3001: istore 14
    //   3003: goto -365 -> 2638
    //   3006: aload_2
    //   3007: getfield 672	com/sleepycat/b/i/e/ax:a	Ljava/util/logging/Logger;
    //   3010: aload_2
    //   3011: getfield 674	com/sleepycat/b/i/e/ax:g	Lcom/sleepycat/b/i/c/aj;
    //   3014: ldc_w 755
    //   3017: invokestatic 443	com/sleepycat/b/p/w:d	(Ljava/util/logging/Logger;Lcom/sleepycat/b/c/ad;Ljava/lang/String;)V
    //   3020: aload_2
    //   3021: getfield 757	com/sleepycat/b/i/e/ax:f	Lcom/sleepycat/b/i/c/b/ac;
    //   3024: aload_2
    //   3025: getfield 730	com/sleepycat/b/i/e/ax:h	Lcom/sleepycat/b/p/au;
    //   3028: aload_2
    //   3029: getfield 723	com/sleepycat/b/i/e/ax:k	Lcom/sleepycat/b/i/e/q;
    //   3032: getfield 760	com/sleepycat/b/i/e/q:a	J
    //   3035: invokevirtual 763	com/sleepycat/b/i/c/b/ac:a	(Lcom/sleepycat/b/p/au;J)V
    //   3038: aload_2
    //   3039: getfield 730	com/sleepycat/b/i/e/ax:h	Lcom/sleepycat/b/p/au;
    //   3042: invokevirtual 766	com/sleepycat/b/p/au:d	()Lcom/sleepycat/b/p/au;
    //   3045: astore 5
    //   3047: aload_2
    //   3048: getfield 701	com/sleepycat/b/i/e/ax:e	Lcom/sleepycat/b/i/i/f;
    //   3051: aload 5
    //   3053: aload_2
    //   3054: getfield 723	com/sleepycat/b/i/e/ax:k	Lcom/sleepycat/b/i/e/q;
    //   3057: getfield 760	com/sleepycat/b/i/e/q:a	J
    //   3060: invokevirtual 768	com/sleepycat/b/i/i/f:b	(Lcom/sleepycat/b/p/au;J)V
    //   3063: aload_2
    //   3064: getfield 770	com/sleepycat/b/i/e/ax:c	Lcom/sleepycat/b/i/e/t;
    //   3067: astore 6
    //   3069: aload_2
    //   3070: getfield 770	com/sleepycat/b/i/e/ax:c	Lcom/sleepycat/b/i/e/t;
    //   3073: astore 7
    //   3075: aload 7
    //   3077: invokevirtual 111	java/lang/Object:getClass	()Ljava/lang/Class;
    //   3080: pop
    //   3081: aload 6
    //   3083: new 772	com/sleepycat/b/i/e/au
    //   3086: dup
    //   3087: aload 7
    //   3089: aload 5
    //   3091: invokespecial 775	com/sleepycat/b/i/e/au:<init>	(Lcom/sleepycat/b/i/e/t;Lcom/sleepycat/b/p/au;)V
    //   3094: aload_2
    //   3095: getfield 670	com/sleepycat/b/i/e/ax:b	Lcom/sleepycat/b/i/h/o;
    //   3098: invokevirtual 159	com/sleepycat/b/i/e/t:a	(Lcom/sleepycat/b/i/h/d;Lcom/sleepycat/b/i/h/o;)V
    //   3101: aload_2
    //   3102: getfield 672	com/sleepycat/b/i/e/ax:a	Ljava/util/logging/Logger;
    //   3105: aload_2
    //   3106: getfield 674	com/sleepycat/b/i/e/ax:g	Lcom/sleepycat/b/i/c/aj;
    //   3109: new 255	java/lang/StringBuilder
    //   3112: dup
    //   3113: ldc_w 634
    //   3116: invokespecial 260	java/lang/StringBuilder:<init>	(Ljava/lang/String;)V
    //   3119: aload_3
    //   3120: invokevirtual 286	java/lang/StringBuilder:append	(Ljava/lang/String;)Ljava/lang/StringBuilder;
    //   3123: ldc_w 777
    //   3126: invokevirtual 286	java/lang/StringBuilder:append	(Ljava/lang/String;)Ljava/lang/StringBuilder;
    //   3129: aload 5
    //   3131: invokevirtual 272	java/lang/StringBuilder:append	(Ljava/lang/Object;)Ljava/lang/StringBuilder;
    //   3134: invokevirtual 276	java/lang/StringBuilder:toString	()Ljava/lang/String;
    //   3137: invokestatic 175	com/sleepycat/b/p/w:c	(Ljava/util/logging/Logger;Lcom/sleepycat/b/c/ad;Ljava/lang/String;)V
    //   3140: aload_2
    //   3141: getfield 730	com/sleepycat/b/i/e/ax:h	Lcom/sleepycat/b/p/au;
    //   3144: astore 5
    //   3146: aload 4
    //   3148: aload 5
    //   3150: putfield 218	com/sleepycat/b/i/c/b/q:b	Lcom/sleepycat/b/p/au;
    //   3153: aload 4
    //   3155: aload 5
    //   3157: putfield 779	com/sleepycat/b/i/c/b/q:a	Lcom/sleepycat/b/p/au;
    //   3160: aload_2
    //   3161: getfield 678	com/sleepycat/b/i/e/ax:d	Lcom/sleepycat/b/i/c/b/aa;
    //   3164: getfield 695	com/sleepycat/b/i/c/b/aa:r	Lcom/sleepycat/b/i/c/b/o;
    //   3167: invokevirtual 738	com/sleepycat/b/i/c/b/o:b	()V
    //   3170: aload_2
    //   3171: getfield 672	com/sleepycat/b/i/e/ax:a	Ljava/util/logging/Logger;
    //   3174: aload_2
    //   3175: getfield 674	com/sleepycat/b/i/e/ax:g	Lcom/sleepycat/b/i/c/aj;
    //   3178: new 255	java/lang/StringBuilder
    //   3181: dup
    //   3182: ldc_w 634
    //   3185: invokespecial 260	java/lang/StringBuilder:<init>	(Ljava/lang/String;)V
    //   3188: aload_3
    //   3189: invokevirtual 286	java/lang/StringBuilder:append	(Ljava/lang/String;)Ljava/lang/StringBuilder;
    //   3192: ldc_w 740
    //   3195: invokevirtual 286	java/lang/StringBuilder:append	(Ljava/lang/String;)Ljava/lang/StringBuilder;
    //   3198: invokevirtual 276	java/lang/StringBuilder:toString	()Ljava/lang/String;
    //   3201: iconst_1
    //   3202: anewarray 4	java/lang/Object
    //   3205: dup
    //   3206: iconst_0
    //   3207: invokestatic 669	java/lang/System:currentTimeMillis	()J
    //   3210: lload 10
    //   3212: lsub
    //   3213: invokestatic 745	java/lang/Long:valueOf	(J)Ljava/lang/Long;
    //   3216: aastore
    //   3217: invokestatic 751	java/lang/String:format	(Ljava/lang/String;[Ljava/lang/Object;)Ljava/lang/String;
    //   3220: invokestatic 175	com/sleepycat/b/p/w:c	(Ljava/util/logging/Logger;Lcom/sleepycat/b/c/ad;Ljava/lang/String;)V
    //   3223: aload_2
    //   3224: getfield 674	com/sleepycat/b/i/e/ax:g	Lcom/sleepycat/b/i/c/aj;
    //   3227: astore_3
    //   3228: getstatic 753	com/sleepycat/b/i/ad:d	I
    //   3231: istore 9
    //   3233: aload_3
    //   3234: invokevirtual 710	com/sleepycat/b/i/c/aj:aj	()V
    //   3237: aload_0
    //   3238: aload_2
    //   3239: getfield 730	com/sleepycat/b/i/e/ax:h	Lcom/sleepycat/b/p/au;
    //   3242: putfield 205	com/sleepycat/b/i/c/b/ag:l	Lcom/sleepycat/b/p/au;
    //   3245: aload_2
    //   3246: getfield 782	com/sleepycat/b/i/e/ax:i	Ljava/lang/Long;
    //   3249: invokevirtual 785	java/lang/Long:longValue	()J
    //   3252: lstore 10
    //   3254: aload_0
    //   3255: getfield 105	com/sleepycat/b/i/c/b/ag:d	Lcom/sleepycat/b/i/c/b/ai;
    //   3258: astore_2
    //   3259: aload_0
    //   3260: getfield 205	com/sleepycat/b/i/c/b/ag:l	Lcom/sleepycat/b/p/au;
    //   3263: getfield 787	com/sleepycat/b/p/au:c	J
    //   3266: lstore 12
    //   3268: aload_2
    //   3269: new 727	com/sleepycat/b/p/au
    //   3272: dup
    //   3273: lload 12
    //   3275: invokespecial 790	com/sleepycat/b/p/au:<init>	(J)V
    //   3278: putfield 791	com/sleepycat/b/i/c/b/ai:b	Lcom/sleepycat/b/p/au;
    //   3281: aload_2
    //   3282: lload 12
    //   3284: putfield 792	com/sleepycat/b/i/c/b/ai:a	J
    //   3287: aload_2
    //   3288: lload 10
    //   3290: putfield 793	com/sleepycat/b/i/c/b/ai:c	J
    //   3293: aload_0
    //   3294: getfield 56	com/sleepycat/b/i/c/b/ag:e	Lcom/sleepycat/b/i/e/t;
    //   3297: aload_0
    //   3298: getfield 50	com/sleepycat/b/i/c/b/ag:c	Lcom/sleepycat/b/i/h/p;
    //   3301: invokevirtual 794	com/sleepycat/b/i/h/p:a	()Ljava/nio/channels/SocketChannel;
    //   3304: ldc_w 796
    //   3307: invokevirtual 799	com/sleepycat/b/i/e/t:a	(Ljava/nio/channels/ReadableByteChannel;Ljava/lang/Class;)Lcom/sleepycat/b/i/h/d;
    //   3310: checkcast 796	com/sleepycat/b/i/e/ae
    //   3313: astore_2
    //   3314: aload_0
    //   3315: aload_0
    //   3316: getfield 50	com/sleepycat/b/i/c/b/ag:c	Lcom/sleepycat/b/i/h/p;
    //   3319: aload_2
    //   3320: invokespecial 209	com/sleepycat/b/i/c/b/ag:a	(Lcom/sleepycat/b/i/h/o;Lcom/sleepycat/b/i/e/ae;)V
    //   3323: aload_0
    //   3324: getfield 105	com/sleepycat/b/i/c/b/ag:d	Lcom/sleepycat/b/i/c/b/ai;
    //   3327: getfield 801	com/sleepycat/b/i/c/b/ai:d	J
    //   3330: lstore 10
    //   3332: aload_0
    //   3333: getfield 105	com/sleepycat/b/i/c/b/ag:d	Lcom/sleepycat/b/i/c/b/ai;
    //   3336: invokestatic 804	com/sleepycat/b/i/c/b/ai:a	(Lcom/sleepycat/b/i/c/b/ai;)Lcom/sleepycat/b/p/au;
    //   3339: getfield 787	com/sleepycat/b/p/au:c	J
    //   3342: lstore 12
    //   3344: aload_0
    //   3345: getfield 118	com/sleepycat/b/i/c/b/ag:q	Ljava/util/logging/Logger;
    //   3348: aload_0
    //   3349: getfield 64	com/sleepycat/b/i/c/b/ag:j	Lcom/sleepycat/b/i/c/aj;
    //   3352: ldc_w 806
    //   3355: iconst_3
    //   3356: anewarray 4	java/lang/Object
    //   3359: dup
    //   3360: iconst_0
    //   3361: aload_0
    //   3362: getfield 105	com/sleepycat/b/i/c/b/ag:d	Lcom/sleepycat/b/i/c/b/ai;
    //   3365: invokestatic 804	com/sleepycat/b/i/c/b/ai:a	(Lcom/sleepycat/b/i/c/b/ai;)Lcom/sleepycat/b/p/au;
    //   3368: aastore
    //   3369: dup
    //   3370: iconst_1
    //   3371: aload_0
    //   3372: getfield 105	com/sleepycat/b/i/c/b/ag:d	Lcom/sleepycat/b/i/c/b/ai;
    //   3375: getfield 801	com/sleepycat/b/i/c/b/ai:d	J
    //   3378: invokestatic 745	java/lang/Long:valueOf	(J)Ljava/lang/Long;
    //   3381: aastore
    //   3382: dup
    //   3383: iconst_2
    //   3384: lload 10
    //   3386: lload 12
    //   3388: lsub
    //   3389: invokestatic 745	java/lang/Long:valueOf	(J)Ljava/lang/Long;
    //   3392: aastore
    //   3393: invokestatic 751	java/lang/String:format	(Ljava/lang/String;[Ljava/lang/Object;)Ljava/lang/String;
    //   3396: invokestatic 175	com/sleepycat/b/p/w:c	(Ljava/util/logging/Logger;Lcom/sleepycat/b/c/ad;Ljava/lang/String;)V
    //   3399: aload_0
    //   3400: getfield 58	com/sleepycat/b/i/c/b/ag:a	Lcom/sleepycat/b/i/c/b/aa;
    //   3403: getfield 809	com/sleepycat/b/i/c/b/aa:k	Lcom/sleepycat/b/i/h/t;
    //   3406: invokevirtual 814	com/sleepycat/b/i/h/t:countDown	()V
    //   3409: aload_0
    //   3410: invokevirtual 815	com/sleepycat/b/i/c/b/ag:b	()V
    //   3413: aload_0
    //   3414: getfield 48	com/sleepycat/b/i/c/b/ag:k	Ljava/lang/Exception;
    //   3417: ifnull +1389 -> 4806
    //   3420: aload_0
    //   3421: getfield 48	com/sleepycat/b/i/c/b/ag:k	Ljava/lang/Exception;
    //   3424: instanceof 235
    //   3427: ifeq +1396 -> 4823
    //   3430: aload_0
    //   3431: getfield 118	com/sleepycat/b/i/c/b/ag:q	Ljava/util/logging/Logger;
    //   3434: aload_0
    //   3435: getfield 64	com/sleepycat/b/i/c/b/ag:j	Lcom/sleepycat/b/i/c/aj;
    //   3438: new 255	java/lang/StringBuilder
    //   3441: dup
    //   3442: ldc_w 379
    //   3445: invokespecial 260	java/lang/StringBuilder:<init>	(Ljava/lang/String;)V
    //   3448: aload_0
    //   3449: getfield 48	com/sleepycat/b/i/c/b/ag:k	Ljava/lang/Exception;
    //   3452: invokevirtual 382	java/lang/Exception:getMessage	()Ljava/lang/String;
    //   3455: invokevirtual 286	java/lang/StringBuilder:append	(Ljava/lang/String;)Ljava/lang/StringBuilder;
    //   3458: invokevirtual 276	java/lang/StringBuilder:toString	()Ljava/lang/String;
    //   3461: invokestatic 175	com/sleepycat/b/p/w:c	(Ljava/util/logging/Logger;Lcom/sleepycat/b/c/ad;Ljava/lang/String;)V
    //   3464: aload_0
    //   3465: invokevirtual 384	com/sleepycat/b/i/c/b/ag:c	()V
    //   3468: aload_0
    //   3469: getfield 50	com/sleepycat/b/i/c/b/ag:c	Lcom/sleepycat/b/i/h/p;
    //   3472: invokestatic 389	com/sleepycat/b/i/h/q:a	(Lcom/sleepycat/b/i/h/o;)V
    //   3475: aload_0
    //   3476: getfield 105	com/sleepycat/b/i/c/b/ag:d	Lcom/sleepycat/b/i/c/b/ai;
    //   3479: ifnull +118 -> 3597
    //   3482: aload_0
    //   3483: getfield 105	com/sleepycat/b/i/c/b/ag:d	Lcom/sleepycat/b/i/c/b/ai;
    //   3486: astore_2
    //   3487: aload_2
    //   3488: getfield 392	com/sleepycat/b/i/c/b/ai:k	Lcom/sleepycat/b/i/c/b/ag;
    //   3491: getfield 118	com/sleepycat/b/i/c/b/ag:q	Ljava/util/logging/Logger;
    //   3494: getstatic 398	java/util/logging/Level:INFO	Ljava/util/logging/Level;
    //   3497: invokevirtual 404	java/util/logging/Logger:isLoggable	(Ljava/util/logging/Level;)Z
    //   3500: ifeq +97 -> 3597
    //   3503: aload_2
    //   3504: getfield 392	com/sleepycat/b/i/c/b/ai:k	Lcom/sleepycat/b/i/c/b/ag;
    //   3507: getfield 118	com/sleepycat/b/i/c/b/ag:q	Ljava/util/logging/Logger;
    //   3510: aload_2
    //   3511: getfield 392	com/sleepycat/b/i/c/b/ai:k	Lcom/sleepycat/b/i/c/b/ag;
    //   3514: getfield 64	com/sleepycat/b/i/c/b/ag:j	Lcom/sleepycat/b/i/c/aj;
    //   3517: new 255	java/lang/StringBuilder
    //   3520: dup
    //   3521: ldc_w 406
    //   3524: invokespecial 260	java/lang/StringBuilder:<init>	(Ljava/lang/String;)V
    //   3527: aload_2
    //   3528: getfield 408	com/sleepycat/b/i/c/b/ai:e	Lcom/sleepycat/b/p/z;
    //   3531: invokevirtual 413	com/sleepycat/b/p/z:b	()Ljava/lang/Long;
    //   3534: invokevirtual 272	java/lang/StringBuilder:append	(Ljava/lang/Object;)Ljava/lang/StringBuilder;
    //   3537: ldc_w 415
    //   3540: invokevirtual 286	java/lang/StringBuilder:append	(Ljava/lang/String;)Ljava/lang/StringBuilder;
    //   3543: aload_2
    //   3544: getfield 417	com/sleepycat/b/i/c/b/ai:f	Lcom/sleepycat/b/p/z;
    //   3547: invokevirtual 413	com/sleepycat/b/p/z:b	()Ljava/lang/Long;
    //   3550: invokevirtual 272	java/lang/StringBuilder:append	(Ljava/lang/Object;)Ljava/lang/StringBuilder;
    //   3553: ldc_w 419
    //   3556: invokevirtual 286	java/lang/StringBuilder:append	(Ljava/lang/String;)Ljava/lang/StringBuilder;
    //   3559: aload_2
    //   3560: getfield 421	com/sleepycat/b/i/c/b/ai:g	Lcom/sleepycat/b/p/z;
    //   3563: invokevirtual 413	com/sleepycat/b/p/z:b	()Ljava/lang/Long;
    //   3566: invokevirtual 272	java/lang/StringBuilder:append	(Ljava/lang/Object;)Ljava/lang/StringBuilder;
    //   3569: ldc_w 415
    //   3572: invokevirtual 286	java/lang/StringBuilder:append	(Ljava/lang/String;)Ljava/lang/StringBuilder;
    //   3575: aload_2
    //   3576: getfield 423	com/sleepycat/b/i/c/b/ai:h	Lcom/sleepycat/b/p/z;
    //   3579: invokevirtual 413	com/sleepycat/b/p/z:b	()Ljava/lang/Long;
    //   3582: invokevirtual 272	java/lang/StringBuilder:append	(Ljava/lang/Object;)Ljava/lang/StringBuilder;
    //   3585: ldc_w 425
    //   3588: invokevirtual 286	java/lang/StringBuilder:append	(Ljava/lang/String;)Ljava/lang/StringBuilder;
    //   3591: invokevirtual 276	java/lang/StringBuilder:toString	()Ljava/lang/String;
    //   3594: invokestatic 175	com/sleepycat/b/p/w:c	(Ljava/util/logging/Logger;Lcom/sleepycat/b/c/ad;Ljava/lang/String;)V
    //   3597: aload_0
    //   3598: getfield 56	com/sleepycat/b/i/c/b/ag:e	Lcom/sleepycat/b/i/e/t;
    //   3601: ifnull +20 -> 3621
    //   3604: aload_0
    //   3605: getfield 129	com/sleepycat/b/i/c/b/ag:f	Lcom/sleepycat/b/p/ai;
    //   3608: aload_0
    //   3609: getfield 56	com/sleepycat/b/i/c/b/ag:e	Lcom/sleepycat/b/i/e/t;
    //   3612: getstatic 430	com/sleepycat/b/bn:a	Lcom/sleepycat/b/bn;
    //   3615: invokevirtual 433	com/sleepycat/b/i/e/t:a	(Lcom/sleepycat/b/bn;)Lcom/sleepycat/b/p/ai;
    //   3618: invokevirtual 436	com/sleepycat/b/p/ai:a	(Lcom/sleepycat/b/p/ai;)V
    //   3621: aload_0
    //   3622: aconst_null
    //   3623: putfield 56	com/sleepycat/b/i/c/b/ag:e	Lcom/sleepycat/b/i/e/t;
    //   3626: goto -3038 -> 588
    //   3629: aload 7
    //   3631: invokevirtual 728	com/sleepycat/b/p/au:c	()Z
    //   3634: ifeq +43 -> 3677
    //   3637: aload_2
    //   3638: getfield 678	com/sleepycat/b/i/e/ax:d	Lcom/sleepycat/b/i/c/b/aa;
    //   3641: getfield 62	com/sleepycat/b/i/c/b/aa:i	Lcom/sleepycat/b/i/c/aj;
    //   3644: new 255	java/lang/StringBuilder
    //   3647: dup
    //   3648: ldc_w 817
    //   3651: invokespecial 260	java/lang/StringBuilder:<init>	(Ljava/lang/String;)V
    //   3654: aload 6
    //   3656: invokevirtual 272	java/lang/StringBuilder:append	(Ljava/lang/Object;)Ljava/lang/StringBuilder;
    //   3659: ldc_w 819
    //   3662: invokevirtual 286	java/lang/StringBuilder:append	(Ljava/lang/String;)Ljava/lang/StringBuilder;
    //   3665: aload 5
    //   3667: invokevirtual 272	java/lang/StringBuilder:append	(Ljava/lang/Object;)Ljava/lang/StringBuilder;
    //   3670: invokevirtual 276	java/lang/StringBuilder:toString	()Ljava/lang/String;
    //   3673: invokestatic 737	com/sleepycat/b/aa:a	(Lcom/sleepycat/b/c/ad;Ljava/lang/String;)Lcom/sleepycat/b/aa;
    //   3676: athrow
    //   3677: aload_2
    //   3678: getfield 730	com/sleepycat/b/i/e/ax:h	Lcom/sleepycat/b/p/au;
    //   3681: invokevirtual 728	com/sleepycat/b/p/au:c	()Z
    //   3684: ifeq +47 -> 3731
    //   3687: aload_2
    //   3688: getfield 672	com/sleepycat/b/i/e/ax:a	Ljava/util/logging/Logger;
    //   3691: aload_2
    //   3692: getfield 674	com/sleepycat/b/i/e/ax:g	Lcom/sleepycat/b/i/c/aj;
    //   3695: new 255	java/lang/StringBuilder
    //   3698: dup
    //   3699: ldc_w 821
    //   3702: invokespecial 260	java/lang/StringBuilder:<init>	(Ljava/lang/String;)V
    //   3705: aload 6
    //   3707: invokevirtual 272	java/lang/StringBuilder:append	(Ljava/lang/Object;)Ljava/lang/StringBuilder;
    //   3710: ldc_w 823
    //   3713: invokevirtual 286	java/lang/StringBuilder:append	(Ljava/lang/String;)Ljava/lang/StringBuilder;
    //   3716: invokevirtual 276	java/lang/StringBuilder:toString	()Ljava/lang/String;
    //   3719: invokestatic 175	com/sleepycat/b/p/w:c	(Ljava/util/logging/Logger;Lcom/sleepycat/b/c/ad;Ljava/lang/String;)V
    //   3722: aload_2
    //   3723: aload_2
    //   3724: getfield 730	com/sleepycat/b/i/e/ax:h	Lcom/sleepycat/b/p/au;
    //   3727: invokevirtual 826	com/sleepycat/b/i/e/ax:a	(Lcom/sleepycat/b/p/au;)Lcom/sleepycat/b/i/f;
    //   3730: athrow
    //   3731: aload 6
    //   3733: aload_2
    //   3734: getfield 730	com/sleepycat/b/i/e/ax:h	Lcom/sleepycat/b/p/au;
    //   3737: invokevirtual 829	com/sleepycat/b/p/au:b	(Lcom/sleepycat/b/p/au;)I
    //   3740: ifgt +64 -> 3804
    //   3743: aload_2
    //   3744: getfield 723	com/sleepycat/b/i/e/ax:k	Lcom/sleepycat/b/i/e/q;
    //   3747: getfield 831	com/sleepycat/b/i/e/q:h	I
    //   3750: ifne +54 -> 3804
    //   3753: aload_2
    //   3754: getfield 672	com/sleepycat/b/i/e/ax:a	Ljava/util/logging/Logger;
    //   3757: aload_2
    //   3758: getfield 674	com/sleepycat/b/i/e/ax:g	Lcom/sleepycat/b/i/c/aj;
    //   3761: new 255	java/lang/StringBuilder
    //   3764: dup
    //   3765: ldc_w 833
    //   3768: invokespecial 260	java/lang/StringBuilder:<init>	(Ljava/lang/String;)V
    //   3771: aload 6
    //   3773: invokevirtual 272	java/lang/StringBuilder:append	(Ljava/lang/Object;)Ljava/lang/StringBuilder;
    //   3776: ldc_w 835
    //   3779: invokevirtual 286	java/lang/StringBuilder:append	(Ljava/lang/String;)Ljava/lang/StringBuilder;
    //   3782: aload_2
    //   3783: getfield 730	com/sleepycat/b/i/e/ax:h	Lcom/sleepycat/b/p/au;
    //   3786: invokevirtual 272	java/lang/StringBuilder:append	(Ljava/lang/Object;)Ljava/lang/StringBuilder;
    //   3789: ldc_w 837
    //   3792: invokevirtual 286	java/lang/StringBuilder:append	(Ljava/lang/String;)Ljava/lang/StringBuilder;
    //   3795: invokevirtual 276	java/lang/StringBuilder:toString	()Ljava/lang/String;
    //   3798: invokestatic 443	com/sleepycat/b/p/w:d	(Ljava/util/logging/Logger;Lcom/sleepycat/b/c/ad;Ljava/lang/String;)V
    //   3801: goto -781 -> 3020
    //   3804: aload_2
    //   3805: getfield 839	com/sleepycat/b/i/e/ax:j	Z
    //   3808: ifeq +27 -> 3835
    //   3811: new 247	com/sleepycat/b/i/c/b/aj
    //   3814: dup
    //   3815: aload_2
    //   3816: getfield 678	com/sleepycat/b/i/e/ax:d	Lcom/sleepycat/b/i/c/b/aa;
    //   3819: getfield 263	com/sleepycat/b/i/c/b/aa:g	Lcom/sleepycat/b/i/e/n;
    //   3822: invokevirtual 268	com/sleepycat/b/i/e/n:h	()Lcom/sleepycat/b/i/c/b/x;
    //   3825: aload 6
    //   3827: aload_2
    //   3828: getfield 730	com/sleepycat/b/i/e/ax:h	Lcom/sleepycat/b/p/au;
    //   3831: invokespecial 842	com/sleepycat/b/i/c/b/aj:<init>	(Lcom/sleepycat/b/i/c/b/x;Lcom/sleepycat/b/p/au;Lcom/sleepycat/b/p/au;)V
    //   3834: athrow
    //   3835: aload_2
    //   3836: getfield 723	com/sleepycat/b/i/e/ax:k	Lcom/sleepycat/b/i/e/q;
    //   3839: getfield 843	com/sleepycat/b/i/e/q:b	Z
    //   3842: ifeq +49 -> 3891
    //   3845: aload_2
    //   3846: getfield 672	com/sleepycat/b/i/e/ax:a	Ljava/util/logging/Logger;
    //   3849: aload_2
    //   3850: getfield 674	com/sleepycat/b/i/e/ax:g	Lcom/sleepycat/b/i/c/aj;
    //   3853: new 255	java/lang/StringBuilder
    //   3856: dup
    //   3857: ldc_w 845
    //   3860: invokespecial 260	java/lang/StringBuilder:<init>	(Ljava/lang/String;)V
    //   3863: aload_2
    //   3864: getfield 730	com/sleepycat/b/i/e/ax:h	Lcom/sleepycat/b/p/au;
    //   3867: invokevirtual 272	java/lang/StringBuilder:append	(Ljava/lang/Object;)Ljava/lang/StringBuilder;
    //   3870: ldc_w 847
    //   3873: invokevirtual 286	java/lang/StringBuilder:append	(Ljava/lang/String;)Ljava/lang/StringBuilder;
    //   3876: invokevirtual 276	java/lang/StringBuilder:toString	()Ljava/lang/String;
    //   3879: invokestatic 175	com/sleepycat/b/p/w:c	(Ljava/util/logging/Logger;Lcom/sleepycat/b/c/ad;Ljava/lang/String;)V
    //   3882: aload_2
    //   3883: aload_2
    //   3884: getfield 730	com/sleepycat/b/i/e/ax:h	Lcom/sleepycat/b/p/au;
    //   3887: invokevirtual 826	com/sleepycat/b/i/e/ax:a	(Lcom/sleepycat/b/p/au;)Lcom/sleepycat/b/i/f;
    //   3890: athrow
    //   3891: aload_2
    //   3892: getfield 723	com/sleepycat/b/i/e/ax:k	Lcom/sleepycat/b/i/e/q;
    //   3895: getfield 849	com/sleepycat/b/i/e/q:c	Z
    //   3898: ifeq +49 -> 3947
    //   3901: aload_2
    //   3902: getfield 672	com/sleepycat/b/i/e/ax:a	Ljava/util/logging/Logger;
    //   3905: aload_2
    //   3906: getfield 674	com/sleepycat/b/i/e/ax:g	Lcom/sleepycat/b/i/c/aj;
    //   3909: new 255	java/lang/StringBuilder
    //   3912: dup
    //   3913: ldc_w 845
    //   3916: invokespecial 260	java/lang/StringBuilder:<init>	(Ljava/lang/String;)V
    //   3919: aload_2
    //   3920: getfield 730	com/sleepycat/b/i/e/ax:h	Lcom/sleepycat/b/p/au;
    //   3923: invokevirtual 272	java/lang/StringBuilder:append	(Ljava/lang/Object;)Ljava/lang/StringBuilder;
    //   3926: ldc_w 851
    //   3929: invokevirtual 286	java/lang/StringBuilder:append	(Ljava/lang/String;)Ljava/lang/StringBuilder;
    //   3932: invokevirtual 276	java/lang/StringBuilder:toString	()Ljava/lang/String;
    //   3935: invokestatic 175	com/sleepycat/b/p/w:c	(Ljava/util/logging/Logger;Lcom/sleepycat/b/c/ad;Ljava/lang/String;)V
    //   3938: aload_2
    //   3939: aload_2
    //   3940: getfield 730	com/sleepycat/b/i/e/ax:h	Lcom/sleepycat/b/p/au;
    //   3943: invokevirtual 826	com/sleepycat/b/i/e/ax:a	(Lcom/sleepycat/b/p/au;)Lcom/sleepycat/b/i/f;
    //   3946: athrow
    //   3947: aload_2
    //   3948: getfield 678	com/sleepycat/b/i/e/ax:d	Lcom/sleepycat/b/i/c/b/aa;
    //   3951: getfield 62	com/sleepycat/b/i/c/b/aa:i	Lcom/sleepycat/b/i/c/aj;
    //   3954: getfield 70	com/sleepycat/b/c/ad:u	Lcom/sleepycat/b/c/m;
    //   3957: getstatic 853	com/sleepycat/b/i/c/an:Z	Lcom/sleepycat/b/b/e;
    //   3960: invokevirtual 86	com/sleepycat/b/c/m:a	(Lcom/sleepycat/b/b/e;)I
    //   3963: istore 9
    //   3965: aload_2
    //   3966: getfield 723	com/sleepycat/b/i/e/ax:k	Lcom/sleepycat/b/i/e/q;
    //   3969: getfield 831	com/sleepycat/b/i/e/q:h	I
    //   3972: iload 9
    //   3974: if_icmple +62 -> 4036
    //   3977: aload_2
    //   3978: getfield 672	com/sleepycat/b/i/e/ax:a	Ljava/util/logging/Logger;
    //   3981: aload_2
    //   3982: getfield 674	com/sleepycat/b/i/e/ax:g	Lcom/sleepycat/b/i/c/aj;
    //   3985: new 255	java/lang/StringBuilder
    //   3988: dup
    //   3989: ldc_w 855
    //   3992: invokespecial 260	java/lang/StringBuilder:<init>	(Ljava/lang/String;)V
    //   3995: aload_2
    //   3996: getfield 723	com/sleepycat/b/i/e/ax:k	Lcom/sleepycat/b/i/e/q;
    //   3999: invokevirtual 857	com/sleepycat/b/i/e/q:a	()Ljava/lang/String;
    //   4002: invokevirtual 286	java/lang/StringBuilder:append	(Ljava/lang/String;)Ljava/lang/StringBuilder;
    //   4005: invokevirtual 276	java/lang/StringBuilder:toString	()Ljava/lang/String;
    //   4008: invokestatic 557	com/sleepycat/b/p/w:a	(Ljava/util/logging/Logger;Lcom/sleepycat/b/c/ad;Ljava/lang/String;)V
    //   4011: new 859	com/sleepycat/b/i/aa
    //   4014: dup
    //   4015: aload_2
    //   4016: getfield 678	com/sleepycat/b/i/e/ax:d	Lcom/sleepycat/b/i/c/b/aa;
    //   4019: getfield 62	com/sleepycat/b/i/c/b/aa:i	Lcom/sleepycat/b/i/c/aj;
    //   4022: iload 9
    //   4024: aload_2
    //   4025: getfield 730	com/sleepycat/b/i/e/ax:h	Lcom/sleepycat/b/p/au;
    //   4028: aload_2
    //   4029: getfield 723	com/sleepycat/b/i/e/ax:k	Lcom/sleepycat/b/i/e/q;
    //   4032: invokespecial 862	com/sleepycat/b/i/aa:<init>	(Lcom/sleepycat/b/i/c/aj;ILcom/sleepycat/b/p/au;Lcom/sleepycat/b/i/e/q;)V
    //   4035: athrow
    //   4036: new 864	com/sleepycat/b/i/z
    //   4039: dup
    //   4040: aload_2
    //   4041: getfield 674	com/sleepycat/b/i/e/ax:g	Lcom/sleepycat/b/i/c/aj;
    //   4044: aload_2
    //   4045: getfield 730	com/sleepycat/b/i/e/ax:h	Lcom/sleepycat/b/p/au;
    //   4048: aload_2
    //   4049: getfield 723	com/sleepycat/b/i/e/ax:k	Lcom/sleepycat/b/i/e/q;
    //   4052: invokespecial 867	com/sleepycat/b/i/z:<init>	(Lcom/sleepycat/b/i/c/aj;Lcom/sleepycat/b/p/au;Lcom/sleepycat/b/i/e/q;)V
    //   4055: astore 4
    //   4057: aload_2
    //   4058: getfield 672	com/sleepycat/b/i/e/ax:a	Ljava/util/logging/Logger;
    //   4061: aload_2
    //   4062: getfield 674	com/sleepycat/b/i/e/ax:g	Lcom/sleepycat/b/i/c/aj;
    //   4065: new 255	java/lang/StringBuilder
    //   4068: dup
    //   4069: ldc_w 869
    //   4072: invokespecial 260	java/lang/StringBuilder:<init>	(Ljava/lang/String;)V
    //   4075: aload_2
    //   4076: getfield 723	com/sleepycat/b/i/e/ax:k	Lcom/sleepycat/b/i/e/q;
    //   4079: invokevirtual 857	com/sleepycat/b/i/e/q:a	()Ljava/lang/String;
    //   4082: invokevirtual 286	java/lang/StringBuilder:append	(Ljava/lang/String;)Ljava/lang/StringBuilder;
    //   4085: invokevirtual 276	java/lang/StringBuilder:toString	()Ljava/lang/String;
    //   4088: invokestatic 557	com/sleepycat/b/p/w:a	(Ljava/util/logging/Logger;Lcom/sleepycat/b/c/ad;Ljava/lang/String;)V
    //   4091: aload_2
    //   4092: getfield 723	com/sleepycat/b/i/e/ax:k	Lcom/sleepycat/b/i/e/q;
    //   4095: getfield 760	com/sleepycat/b/i/e/q:a	J
    //   4098: lstore 12
    //   4100: aload_2
    //   4101: getfield 674	com/sleepycat/b/i/e/ax:g	Lcom/sleepycat/b/i/c/aj;
    //   4104: getfield 872	com/sleepycat/b/c/ad:x	Lcom/sleepycat/b/g/m;
    //   4107: lload 12
    //   4109: invokestatic 877	com/sleepycat/b/p/j:d	(J)J
    //   4112: lload 12
    //   4114: invokestatic 879	com/sleepycat/b/p/j:e	(J)J
    //   4117: invokevirtual 884	com/sleepycat/b/g/m:c	(JJ)V
    //   4120: aload 4
    //   4122: athrow
    //   4123: aload_0
    //   4124: getfield 118	com/sleepycat/b/i/c/b/ag:q	Ljava/util/logging/Logger;
    //   4127: aload_0
    //   4128: getfield 64	com/sleepycat/b/i/c/b/ag:j	Lcom/sleepycat/b/i/c/aj;
    //   4131: ldc_w 886
    //   4134: invokestatic 888	com/sleepycat/b/p/w:b	(Ljava/util/logging/Logger;Lcom/sleepycat/b/c/ad;Ljava/lang/String;)V
    //   4137: new 890	java/lang/InterruptedException
    //   4140: dup
    //   4141: aload_2
    //   4142: invokevirtual 891	java/nio/channels/ClosedByInterruptException:getMessage	()Ljava/lang/String;
    //   4145: invokespecial 892	java/lang/InterruptedException:<init>	(Ljava/lang/String;)V
    //   4148: athrow
    //   4149: aload_2
    //   4150: invokevirtual 111	java/lang/Object:getClass	()Ljava/lang/Class;
    //   4153: aload_1
    //   4154: if_acmpeq +10 -> 4164
    //   4157: aload_2
    //   4158: getfield 894	com/sleepycat/b/i/c/b/an:a	I
    //   4161: ifne +78 -> 4239
    //   4164: iload 8
    //   4166: iconst_1
    //   4167: iadd
    //   4168: istore 8
    //   4170: iload 8
    //   4172: aload_2
    //   4173: getfield 894	com/sleepycat/b/i/c/b/an:a	I
    //   4176: if_icmplt +724 -> 4900
    //   4179: aload_0
    //   4180: getfield 118	com/sleepycat/b/i/c/b/ag:q	Ljava/util/logging/Logger;
    //   4183: aload_0
    //   4184: getfield 64	com/sleepycat/b/i/c/b/ag:j	Lcom/sleepycat/b/i/c/aj;
    //   4187: new 255	java/lang/StringBuilder
    //   4190: dup
    //   4191: ldc_w 896
    //   4194: invokespecial 260	java/lang/StringBuilder:<init>	(Ljava/lang/String;)V
    //   4197: aload_2
    //   4198: invokevirtual 897	com/sleepycat/b/i/c/b/an:getMessage	()Ljava/lang/String;
    //   4201: invokevirtual 286	java/lang/StringBuilder:append	(Ljava/lang/String;)Ljava/lang/StringBuilder;
    //   4204: ldc_w 899
    //   4207: invokevirtual 286	java/lang/StringBuilder:append	(Ljava/lang/String;)Ljava/lang/StringBuilder;
    //   4210: aload_2
    //   4211: getfield 894	com/sleepycat/b/i/c/b/an:a	I
    //   4214: invokevirtual 281	java/lang/StringBuilder:append	(I)Ljava/lang/StringBuilder;
    //   4217: ldc_w 901
    //   4220: invokevirtual 286	java/lang/StringBuilder:append	(Ljava/lang/String;)Ljava/lang/StringBuilder;
    //   4223: aload_2
    //   4224: invokestatic 483	com/sleepycat/b/p/w:a	(Ljava/lang/Throwable;)Ljava/lang/String;
    //   4227: invokevirtual 286	java/lang/StringBuilder:append	(Ljava/lang/String;)Ljava/lang/StringBuilder;
    //   4230: invokevirtual 276	java/lang/StringBuilder:toString	()Ljava/lang/String;
    //   4233: invokestatic 175	com/sleepycat/b/p/w:c	(Ljava/util/logging/Logger;Lcom/sleepycat/b/c/ad;Ljava/lang/String;)V
    //   4236: goto -3648 -> 588
    //   4239: iconst_0
    //   4240: istore 8
    //   4242: aload_2
    //   4243: invokevirtual 111	java/lang/Object:getClass	()Ljava/lang/Class;
    //   4246: astore_1
    //   4247: aload_0
    //   4248: getfield 118	com/sleepycat/b/i/c/b/ag:q	Ljava/util/logging/Logger;
    //   4251: aload_0
    //   4252: getfield 64	com/sleepycat/b/i/c/b/ag:j	Lcom/sleepycat/b/i/c/aj;
    //   4255: new 255	java/lang/StringBuilder
    //   4258: dup
    //   4259: ldc_w 903
    //   4262: invokespecial 260	java/lang/StringBuilder:<init>	(Ljava/lang/String;)V
    //   4265: iload 8
    //   4267: invokevirtual 281	java/lang/StringBuilder:append	(I)Ljava/lang/StringBuilder;
    //   4270: ldc_w 905
    //   4273: invokevirtual 286	java/lang/StringBuilder:append	(Ljava/lang/String;)Ljava/lang/StringBuilder;
    //   4276: aload_2
    //   4277: getfield 894	com/sleepycat/b/i/c/b/an:a	I
    //   4280: invokevirtual 281	java/lang/StringBuilder:append	(I)Ljava/lang/StringBuilder;
    //   4283: ldc_w 907
    //   4286: invokevirtual 286	java/lang/StringBuilder:append	(Ljava/lang/String;)Ljava/lang/StringBuilder;
    //   4289: aload_2
    //   4290: getfield 908	com/sleepycat/b/i/c/b/an:b	I
    //   4293: invokevirtual 281	java/lang/StringBuilder:append	(I)Ljava/lang/StringBuilder;
    //   4296: ldc_w 910
    //   4299: invokevirtual 286	java/lang/StringBuilder:append	(Ljava/lang/String;)Ljava/lang/StringBuilder;
    //   4302: invokevirtual 276	java/lang/StringBuilder:toString	()Ljava/lang/String;
    //   4305: invokestatic 175	com/sleepycat/b/p/w:c	(Ljava/util/logging/Logger;Lcom/sleepycat/b/c/ad;Ljava/lang/String;)V
    //   4308: aload_2
    //   4309: getfield 908	com/sleepycat/b/i/c/b/an:b	I
    //   4312: i2l
    //   4313: invokestatic 915	java/lang/Thread:sleep	(J)V
    //   4316: aload_0
    //   4317: getfield 58	com/sleepycat/b/i/c/b/ag:a	Lcom/sleepycat/b/i/c/b/aa;
    //   4320: getfield 263	com/sleepycat/b/i/c/b/aa:g	Lcom/sleepycat/b/i/e/n;
    //   4323: invokevirtual 439	com/sleepycat/b/i/e/n:c	()Z
    //   4326: istore 14
    //   4328: iload 14
    //   4330: ifeq -3742 -> 588
    //   4333: goto -4328 -> 5
    //   4336: aload_0
    //   4337: getfield 118	com/sleepycat/b/i/c/b/ag:q	Ljava/util/logging/Logger;
    //   4340: aload_0
    //   4341: getfield 64	com/sleepycat/b/i/c/b/ag:j	Lcom/sleepycat/b/i/c/aj;
    //   4344: ldc_w 917
    //   4347: invokestatic 175	com/sleepycat/b/p/w:c	(Ljava/util/logging/Logger;Lcom/sleepycat/b/c/ad;Ljava/lang/String;)V
    //   4350: goto -3954 -> 396
    //   4353: aload_0
    //   4354: getfield 48	com/sleepycat/b/i/c/b/ag:k	Ljava/lang/Exception;
    //   4357: instanceof 194
    //   4360: ifeq +20 -> 4380
    //   4363: aload_0
    //   4364: getfield 118	com/sleepycat/b/i/c/b/ag:q	Ljava/util/logging/Logger;
    //   4367: aload_0
    //   4368: getfield 64	com/sleepycat/b/i/c/b/ag:j	Lcom/sleepycat/b/i/c/aj;
    //   4371: ldc_w 919
    //   4374: invokestatic 175	com/sleepycat/b/p/w:c	(Ljava/util/logging/Logger;Lcom/sleepycat/b/c/ad;Ljava/lang/String;)V
    //   4377: goto -3981 -> 396
    //   4380: aload_0
    //   4381: getfield 118	com/sleepycat/b/i/c/b/ag:q	Ljava/util/logging/Logger;
    //   4384: aload_0
    //   4385: getfield 64	com/sleepycat/b/i/c/b/ag:j	Lcom/sleepycat/b/i/c/aj;
    //   4388: new 255	java/lang/StringBuilder
    //   4391: dup
    //   4392: ldc_w 921
    //   4395: invokespecial 260	java/lang/StringBuilder:<init>	(Ljava/lang/String;)V
    //   4398: aload_0
    //   4399: getfield 48	com/sleepycat/b/i/c/b/ag:k	Ljava/lang/Exception;
    //   4402: invokevirtual 272	java/lang/StringBuilder:append	(Ljava/lang/Object;)Ljava/lang/StringBuilder;
    //   4405: ldc_w 480
    //   4408: invokevirtual 286	java/lang/StringBuilder:append	(Ljava/lang/String;)Ljava/lang/StringBuilder;
    //   4411: aload_0
    //   4412: getfield 48	com/sleepycat/b/i/c/b/ag:k	Ljava/lang/Exception;
    //   4415: invokestatic 483	com/sleepycat/b/p/w:a	(Ljava/lang/Throwable;)Ljava/lang/String;
    //   4418: invokevirtual 286	java/lang/StringBuilder:append	(Ljava/lang/String;)Ljava/lang/StringBuilder;
    //   4421: invokevirtual 276	java/lang/StringBuilder:toString	()Ljava/lang/String;
    //   4424: invokestatic 888	com/sleepycat/b/p/w:b	(Ljava/util/logging/Logger;Lcom/sleepycat/b/c/ad;Ljava/lang/String;)V
    //   4427: goto -4031 -> 396
    //   4430: aload_0
    //   4431: getfield 118	com/sleepycat/b/i/c/b/ag:q	Ljava/util/logging/Logger;
    //   4434: aload_0
    //   4435: getfield 64	com/sleepycat/b/i/c/b/ag:j	Lcom/sleepycat/b/i/c/aj;
    //   4438: ldc_w 917
    //   4441: invokestatic 175	com/sleepycat/b/p/w:c	(Ljava/util/logging/Logger;Lcom/sleepycat/b/c/ad;Ljava/lang/String;)V
    //   4444: goto -3744 -> 700
    //   4447: aload_0
    //   4448: getfield 48	com/sleepycat/b/i/c/b/ag:k	Ljava/lang/Exception;
    //   4451: instanceof 194
    //   4454: ifeq +20 -> 4474
    //   4457: aload_0
    //   4458: getfield 118	com/sleepycat/b/i/c/b/ag:q	Ljava/util/logging/Logger;
    //   4461: aload_0
    //   4462: getfield 64	com/sleepycat/b/i/c/b/ag:j	Lcom/sleepycat/b/i/c/aj;
    //   4465: ldc_w 919
    //   4468: invokestatic 175	com/sleepycat/b/p/w:c	(Ljava/util/logging/Logger;Lcom/sleepycat/b/c/ad;Ljava/lang/String;)V
    //   4471: goto -3771 -> 700
    //   4474: aload_0
    //   4475: getfield 118	com/sleepycat/b/i/c/b/ag:q	Ljava/util/logging/Logger;
    //   4478: aload_0
    //   4479: getfield 64	com/sleepycat/b/i/c/b/ag:j	Lcom/sleepycat/b/i/c/aj;
    //   4482: new 255	java/lang/StringBuilder
    //   4485: dup
    //   4486: ldc_w 921
    //   4489: invokespecial 260	java/lang/StringBuilder:<init>	(Ljava/lang/String;)V
    //   4492: aload_0
    //   4493: getfield 48	com/sleepycat/b/i/c/b/ag:k	Ljava/lang/Exception;
    //   4496: invokevirtual 272	java/lang/StringBuilder:append	(Ljava/lang/Object;)Ljava/lang/StringBuilder;
    //   4499: ldc_w 480
    //   4502: invokevirtual 286	java/lang/StringBuilder:append	(Ljava/lang/String;)Ljava/lang/StringBuilder;
    //   4505: aload_0
    //   4506: getfield 48	com/sleepycat/b/i/c/b/ag:k	Ljava/lang/Exception;
    //   4509: invokestatic 483	com/sleepycat/b/p/w:a	(Ljava/lang/Throwable;)Ljava/lang/String;
    //   4512: invokevirtual 286	java/lang/StringBuilder:append	(Ljava/lang/String;)Ljava/lang/StringBuilder;
    //   4515: invokevirtual 276	java/lang/StringBuilder:toString	()Ljava/lang/String;
    //   4518: invokestatic 888	com/sleepycat/b/p/w:b	(Ljava/util/logging/Logger;Lcom/sleepycat/b/c/ad;Ljava/lang/String;)V
    //   4521: goto -3821 -> 700
    //   4524: aload_0
    //   4525: getfield 118	com/sleepycat/b/i/c/b/ag:q	Ljava/util/logging/Logger;
    //   4528: aload_0
    //   4529: getfield 64	com/sleepycat/b/i/c/b/ag:j	Lcom/sleepycat/b/i/c/aj;
    //   4532: ldc_w 917
    //   4535: invokestatic 175	com/sleepycat/b/p/w:c	(Ljava/util/logging/Logger;Lcom/sleepycat/b/c/ad;Ljava/lang/String;)V
    //   4538: goto -3531 -> 1007
    //   4541: aload_0
    //   4542: getfield 48	com/sleepycat/b/i/c/b/ag:k	Ljava/lang/Exception;
    //   4545: instanceof 194
    //   4548: ifeq +20 -> 4568
    //   4551: aload_0
    //   4552: getfield 118	com/sleepycat/b/i/c/b/ag:q	Ljava/util/logging/Logger;
    //   4555: aload_0
    //   4556: getfield 64	com/sleepycat/b/i/c/b/ag:j	Lcom/sleepycat/b/i/c/aj;
    //   4559: ldc_w 919
    //   4562: invokestatic 175	com/sleepycat/b/p/w:c	(Ljava/util/logging/Logger;Lcom/sleepycat/b/c/ad;Ljava/lang/String;)V
    //   4565: goto -3558 -> 1007
    //   4568: aload_0
    //   4569: getfield 118	com/sleepycat/b/i/c/b/ag:q	Ljava/util/logging/Logger;
    //   4572: aload_0
    //   4573: getfield 64	com/sleepycat/b/i/c/b/ag:j	Lcom/sleepycat/b/i/c/aj;
    //   4576: new 255	java/lang/StringBuilder
    //   4579: dup
    //   4580: ldc_w 921
    //   4583: invokespecial 260	java/lang/StringBuilder:<init>	(Ljava/lang/String;)V
    //   4586: aload_0
    //   4587: getfield 48	com/sleepycat/b/i/c/b/ag:k	Ljava/lang/Exception;
    //   4590: invokevirtual 272	java/lang/StringBuilder:append	(Ljava/lang/Object;)Ljava/lang/StringBuilder;
    //   4593: ldc_w 480
    //   4596: invokevirtual 286	java/lang/StringBuilder:append	(Ljava/lang/String;)Ljava/lang/StringBuilder;
    //   4599: aload_0
    //   4600: getfield 48	com/sleepycat/b/i/c/b/ag:k	Ljava/lang/Exception;
    //   4603: invokestatic 483	com/sleepycat/b/p/w:a	(Ljava/lang/Throwable;)Ljava/lang/String;
    //   4606: invokevirtual 286	java/lang/StringBuilder:append	(Ljava/lang/String;)Ljava/lang/StringBuilder;
    //   4609: invokevirtual 276	java/lang/StringBuilder:toString	()Ljava/lang/String;
    //   4612: invokestatic 888	com/sleepycat/b/p/w:b	(Ljava/util/logging/Logger;Lcom/sleepycat/b/c/ad;Ljava/lang/String;)V
    //   4615: goto -3608 -> 1007
    //   4618: aload_0
    //   4619: getfield 118	com/sleepycat/b/i/c/b/ag:q	Ljava/util/logging/Logger;
    //   4622: aload_0
    //   4623: getfield 64	com/sleepycat/b/i/c/b/ag:j	Lcom/sleepycat/b/i/c/aj;
    //   4626: ldc_w 917
    //   4629: invokestatic 175	com/sleepycat/b/p/w:c	(Ljava/util/logging/Logger;Lcom/sleepycat/b/c/ad;Ljava/lang/String;)V
    //   4632: goto -2899 -> 1733
    //   4635: aload_0
    //   4636: getfield 48	com/sleepycat/b/i/c/b/ag:k	Ljava/lang/Exception;
    //   4639: instanceof 194
    //   4642: ifeq +20 -> 4662
    //   4645: aload_0
    //   4646: getfield 118	com/sleepycat/b/i/c/b/ag:q	Ljava/util/logging/Logger;
    //   4649: aload_0
    //   4650: getfield 64	com/sleepycat/b/i/c/b/ag:j	Lcom/sleepycat/b/i/c/aj;
    //   4653: ldc_w 919
    //   4656: invokestatic 175	com/sleepycat/b/p/w:c	(Ljava/util/logging/Logger;Lcom/sleepycat/b/c/ad;Ljava/lang/String;)V
    //   4659: goto -2926 -> 1733
    //   4662: aload_0
    //   4663: getfield 118	com/sleepycat/b/i/c/b/ag:q	Ljava/util/logging/Logger;
    //   4666: aload_0
    //   4667: getfield 64	com/sleepycat/b/i/c/b/ag:j	Lcom/sleepycat/b/i/c/aj;
    //   4670: new 255	java/lang/StringBuilder
    //   4673: dup
    //   4674: ldc_w 921
    //   4677: invokespecial 260	java/lang/StringBuilder:<init>	(Ljava/lang/String;)V
    //   4680: aload_0
    //   4681: getfield 48	com/sleepycat/b/i/c/b/ag:k	Ljava/lang/Exception;
    //   4684: invokevirtual 272	java/lang/StringBuilder:append	(Ljava/lang/Object;)Ljava/lang/StringBuilder;
    //   4687: ldc_w 480
    //   4690: invokevirtual 286	java/lang/StringBuilder:append	(Ljava/lang/String;)Ljava/lang/StringBuilder;
    //   4693: aload_0
    //   4694: getfield 48	com/sleepycat/b/i/c/b/ag:k	Ljava/lang/Exception;
    //   4697: invokestatic 483	com/sleepycat/b/p/w:a	(Ljava/lang/Throwable;)Ljava/lang/String;
    //   4700: invokevirtual 286	java/lang/StringBuilder:append	(Ljava/lang/String;)Ljava/lang/StringBuilder;
    //   4703: invokevirtual 276	java/lang/StringBuilder:toString	()Ljava/lang/String;
    //   4706: invokestatic 888	com/sleepycat/b/p/w:b	(Ljava/util/logging/Logger;Lcom/sleepycat/b/c/ad;Ljava/lang/String;)V
    //   4709: goto -2976 -> 1733
    //   4712: aload_0
    //   4713: getfield 118	com/sleepycat/b/i/c/b/ag:q	Ljava/util/logging/Logger;
    //   4716: aload_0
    //   4717: getfield 64	com/sleepycat/b/i/c/b/ag:j	Lcom/sleepycat/b/i/c/aj;
    //   4720: ldc_w 917
    //   4723: invokestatic 175	com/sleepycat/b/p/w:c	(Ljava/util/logging/Logger;Lcom/sleepycat/b/c/ad;Ljava/lang/String;)V
    //   4726: goto -2562 -> 2164
    //   4729: aload_0
    //   4730: getfield 48	com/sleepycat/b/i/c/b/ag:k	Ljava/lang/Exception;
    //   4733: instanceof 194
    //   4736: ifeq +20 -> 4756
    //   4739: aload_0
    //   4740: getfield 118	com/sleepycat/b/i/c/b/ag:q	Ljava/util/logging/Logger;
    //   4743: aload_0
    //   4744: getfield 64	com/sleepycat/b/i/c/b/ag:j	Lcom/sleepycat/b/i/c/aj;
    //   4747: ldc_w 919
    //   4750: invokestatic 175	com/sleepycat/b/p/w:c	(Ljava/util/logging/Logger;Lcom/sleepycat/b/c/ad;Ljava/lang/String;)V
    //   4753: goto -2589 -> 2164
    //   4756: aload_0
    //   4757: getfield 118	com/sleepycat/b/i/c/b/ag:q	Ljava/util/logging/Logger;
    //   4760: aload_0
    //   4761: getfield 64	com/sleepycat/b/i/c/b/ag:j	Lcom/sleepycat/b/i/c/aj;
    //   4764: new 255	java/lang/StringBuilder
    //   4767: dup
    //   4768: ldc_w 921
    //   4771: invokespecial 260	java/lang/StringBuilder:<init>	(Ljava/lang/String;)V
    //   4774: aload_0
    //   4775: getfield 48	com/sleepycat/b/i/c/b/ag:k	Ljava/lang/Exception;
    //   4778: invokevirtual 272	java/lang/StringBuilder:append	(Ljava/lang/Object;)Ljava/lang/StringBuilder;
    //   4781: ldc_w 480
    //   4784: invokevirtual 286	java/lang/StringBuilder:append	(Ljava/lang/String;)Ljava/lang/StringBuilder;
    //   4787: aload_0
    //   4788: getfield 48	com/sleepycat/b/i/c/b/ag:k	Ljava/lang/Exception;
    //   4791: invokestatic 483	com/sleepycat/b/p/w:a	(Ljava/lang/Throwable;)Ljava/lang/String;
    //   4794: invokevirtual 286	java/lang/StringBuilder:append	(Ljava/lang/String;)Ljava/lang/StringBuilder;
    //   4797: invokevirtual 276	java/lang/StringBuilder:toString	()Ljava/lang/String;
    //   4800: invokestatic 888	com/sleepycat/b/p/w:b	(Ljava/util/logging/Logger;Lcom/sleepycat/b/c/ad;Ljava/lang/String;)V
    //   4803: goto -2639 -> 2164
    //   4806: aload_0
    //   4807: getfield 118	com/sleepycat/b/i/c/b/ag:q	Ljava/util/logging/Logger;
    //   4810: aload_0
    //   4811: getfield 64	com/sleepycat/b/i/c/b/ag:j	Lcom/sleepycat/b/i/c/aj;
    //   4814: ldc_w 917
    //   4817: invokestatic 175	com/sleepycat/b/p/w:c	(Ljava/util/logging/Logger;Lcom/sleepycat/b/c/ad;Ljava/lang/String;)V
    //   4820: goto -1356 -> 3464
    //   4823: aload_0
    //   4824: getfield 48	com/sleepycat/b/i/c/b/ag:k	Ljava/lang/Exception;
    //   4827: instanceof 194
    //   4830: ifeq +20 -> 4850
    //   4833: aload_0
    //   4834: getfield 118	com/sleepycat/b/i/c/b/ag:q	Ljava/util/logging/Logger;
    //   4837: aload_0
    //   4838: getfield 64	com/sleepycat/b/i/c/b/ag:j	Lcom/sleepycat/b/i/c/aj;
    //   4841: ldc_w 919
    //   4844: invokestatic 175	com/sleepycat/b/p/w:c	(Ljava/util/logging/Logger;Lcom/sleepycat/b/c/ad;Ljava/lang/String;)V
    //   4847: goto -1383 -> 3464
    //   4850: aload_0
    //   4851: getfield 118	com/sleepycat/b/i/c/b/ag:q	Ljava/util/logging/Logger;
    //   4854: aload_0
    //   4855: getfield 64	com/sleepycat/b/i/c/b/ag:j	Lcom/sleepycat/b/i/c/aj;
    //   4858: new 255	java/lang/StringBuilder
    //   4861: dup
    //   4862: ldc_w 921
    //   4865: invokespecial 260	java/lang/StringBuilder:<init>	(Ljava/lang/String;)V
    //   4868: aload_0
    //   4869: getfield 48	com/sleepycat/b/i/c/b/ag:k	Ljava/lang/Exception;
    //   4872: invokevirtual 272	java/lang/StringBuilder:append	(Ljava/lang/Object;)Ljava/lang/StringBuilder;
    //   4875: ldc_w 480
    //   4878: invokevirtual 286	java/lang/StringBuilder:append	(Ljava/lang/String;)Ljava/lang/StringBuilder;
    //   4881: aload_0
    //   4882: getfield 48	com/sleepycat/b/i/c/b/ag:k	Ljava/lang/Exception;
    //   4885: invokestatic 483	com/sleepycat/b/p/w:a	(Ljava/lang/Throwable;)Ljava/lang/String;
    //   4888: invokevirtual 286	java/lang/StringBuilder:append	(Ljava/lang/String;)Ljava/lang/StringBuilder;
    //   4891: invokevirtual 276	java/lang/StringBuilder:toString	()Ljava/lang/String;
    //   4894: invokestatic 888	com/sleepycat/b/p/w:b	(Ljava/util/logging/Logger;Lcom/sleepycat/b/c/ad;Ljava/lang/String;)V
    //   4897: goto -1433 -> 3464
    //   4900: goto -653 -> 4247
    // Local variable table:
    //   start	length	slot	name	signature
    //   0	4903	0	this	ag
    //   4	1	1	localObject1	Object
    //   865	3289	1	localObject2	Object
    //   4246	1	1	localClass	Class
    //   94	229	2	localObject3	Object
    //   336	7	2	localy	com.sleepycat.b.i.y
    //   344	215	2	localObject4	Object
    //   560	1	2	localan1	an
    //   607	6	2	localConnectException	java.net.ConnectException
    //   621	1	2	localClosedByInterruptException	java.nio.channels.ClosedByInterruptException
    //   722	90	2	localai1	ai
    //   886	16	2	localae	com.sleepycat.b.i.h.ae
    //   911	33	2	localIOException	IOException
    //   1029	144	2	localai2	ai
    //   1177	200	2	localan2	an
    //   1403	98	2	locald	com.sleepycat.b.i.d
    //   1530	108	2	localRuntimeException	RuntimeException
    //   1666	10	2	localo	com.sleepycat.b.i.e.o
    //   1755	310	2	localai3	ai
    //   2092	15	2	localaj	aj
    //   2186	170	2	localai4	ai
    //   2380	167	2	localException	Exception
    //   2557	1752	2	localObject5	Object
    //   105	3129	3	localObject6	Object
    //   137	2540	4	localObject7	Object
    //   2918	236	4	localObject8	Object
    //   4055	66	4	localz	com.sleepycat.b.i.z
    //   1208	2458	5	localObject9	Object
    //   1910	1916	6	localObject10	Object
    //   2803	827	7	localObject11	Object
    //   1	4265	8	i1	int
    //   113	3910	9	i2	int
    //   2681	704	10	l1	long
    //   3266	847	12	l2	long
    //   2636	1693	14	bool	boolean
    // Exception table:
    //   from	to	target	type
    //   91	148	336	com/sleepycat/b/i/y
    //   153	160	336	com/sleepycat/b/i/y
    //   160	172	336	com/sleepycat/b/i/y
    //   172	205	336	com/sleepycat/b/i/y
    //   205	336	336	com/sleepycat/b/i/y
    //   608	621	336	com/sleepycat/b/i/y
    //   887	911	336	com/sleepycat/b/i/y
    //   1172	1177	336	com/sleepycat/b/i/y
    //   1180	1320	336	com/sleepycat/b/i/y
    //   1325	1403	336	com/sleepycat/b/i/y
    //   1411	1530	336	com/sleepycat/b/i/y
    //   1579	1666	336	com/sleepycat/b/i/y
    //   1898	2092	336	com/sleepycat/b/i/y
    //   2329	2380	336	com/sleepycat/b/i/y
    //   2432	2492	336	com/sleepycat/b/i/y
    //   2492	2498	336	com/sleepycat/b/i/y
    //   2498	2635	336	com/sleepycat/b/i/y
    //   2638	2757	336	com/sleepycat/b/i/y
    //   2920	3000	336	com/sleepycat/b/i/y
    //   3160	3413	336	com/sleepycat/b/i/y
    //   91	148	344	finally
    //   153	160	344	finally
    //   160	172	344	finally
    //   172	205	344	finally
    //   205	336	344	finally
    //   337	344	344	finally
    //   608	621	344	finally
    //   622	649	344	finally
    //   887	911	344	finally
    //   912	956	344	finally
    //   1172	1177	344	finally
    //   1178	1180	344	finally
    //   1180	1320	344	finally
    //   1325	1403	344	finally
    //   1404	1411	344	finally
    //   1411	1530	344	finally
    //   1531	1579	344	finally
    //   1579	1666	344	finally
    //   1667	1682	344	finally
    //   1898	2092	344	finally
    //   2093	2113	344	finally
    //   2329	2380	344	finally
    //   2381	2432	344	finally
    //   2432	2492	344	finally
    //   2492	2498	344	finally
    //   2498	2635	344	finally
    //   2638	2757	344	finally
    //   2920	3000	344	finally
    //   3160	3413	344	finally
    //   4123	4149	344	finally
    //   5	91	560	com/sleepycat/b/i/c/b/an
    //   345	396	560	com/sleepycat/b/i/c/b/an
    //   396	529	560	com/sleepycat/b/i/c/b/an
    //   529	553	560	com/sleepycat/b/i/c/b/an
    //   553	560	560	com/sleepycat/b/i/c/b/an
    //   649	700	560	com/sleepycat/b/i/c/b/an
    //   700	833	560	com/sleepycat/b/i/c/b/an
    //   833	857	560	com/sleepycat/b/i/c/b/an
    //   857	862	560	com/sleepycat/b/i/c/b/an
    //   956	1007	560	com/sleepycat/b/i/c/b/an
    //   1007	1140	560	com/sleepycat/b/i/c/b/an
    //   1140	1164	560	com/sleepycat/b/i/c/b/an
    //   1164	1169	560	com/sleepycat/b/i/c/b/an
    //   1682	1733	560	com/sleepycat/b/i/c/b/an
    //   1733	1866	560	com/sleepycat/b/i/c/b/an
    //   1866	1890	560	com/sleepycat/b/i/c/b/an
    //   1890	1895	560	com/sleepycat/b/i/c/b/an
    //   2113	2164	560	com/sleepycat/b/i/c/b/an
    //   2164	2297	560	com/sleepycat/b/i/c/b/an
    //   2297	2321	560	com/sleepycat/b/i/c/b/an
    //   2321	2326	560	com/sleepycat/b/i/c/b/an
    //   3413	3464	560	com/sleepycat/b/i/c/b/an
    //   3464	3597	560	com/sleepycat/b/i/c/b/an
    //   3597	3621	560	com/sleepycat/b/i/c/b/an
    //   3621	3626	560	com/sleepycat/b/i/c/b/an
    //   4336	4350	560	com/sleepycat/b/i/c/b/an
    //   4353	4377	560	com/sleepycat/b/i/c/b/an
    //   4380	4427	560	com/sleepycat/b/i/c/b/an
    //   4430	4444	560	com/sleepycat/b/i/c/b/an
    //   4447	4471	560	com/sleepycat/b/i/c/b/an
    //   4474	4521	560	com/sleepycat/b/i/c/b/an
    //   4524	4538	560	com/sleepycat/b/i/c/b/an
    //   4541	4565	560	com/sleepycat/b/i/c/b/an
    //   4568	4615	560	com/sleepycat/b/i/c/b/an
    //   4618	4632	560	com/sleepycat/b/i/c/b/an
    //   4635	4659	560	com/sleepycat/b/i/c/b/an
    //   4662	4709	560	com/sleepycat/b/i/c/b/an
    //   4712	4726	560	com/sleepycat/b/i/c/b/an
    //   4729	4753	560	com/sleepycat/b/i/c/b/an
    //   4756	4803	560	com/sleepycat/b/i/c/b/an
    //   4806	4820	560	com/sleepycat/b/i/c/b/an
    //   4823	4847	560	com/sleepycat/b/i/c/b/an
    //   4850	4897	560	com/sleepycat/b/i/c/b/an
    //   172	205	607	java/net/ConnectException
    //   91	148	621	java/nio/channels/ClosedByInterruptException
    //   153	160	621	java/nio/channels/ClosedByInterruptException
    //   160	172	621	java/nio/channels/ClosedByInterruptException
    //   172	205	621	java/nio/channels/ClosedByInterruptException
    //   205	336	621	java/nio/channels/ClosedByInterruptException
    //   608	621	621	java/nio/channels/ClosedByInterruptException
    //   887	911	621	java/nio/channels/ClosedByInterruptException
    //   1172	1177	621	java/nio/channels/ClosedByInterruptException
    //   1180	1320	621	java/nio/channels/ClosedByInterruptException
    //   1325	1403	621	java/nio/channels/ClosedByInterruptException
    //   1411	1530	621	java/nio/channels/ClosedByInterruptException
    //   1579	1666	621	java/nio/channels/ClosedByInterruptException
    //   1898	2092	621	java/nio/channels/ClosedByInterruptException
    //   2329	2380	621	java/nio/channels/ClosedByInterruptException
    //   2432	2492	621	java/nio/channels/ClosedByInterruptException
    //   2492	2498	621	java/nio/channels/ClosedByInterruptException
    //   2498	2635	621	java/nio/channels/ClosedByInterruptException
    //   2638	2757	621	java/nio/channels/ClosedByInterruptException
    //   2920	3000	621	java/nio/channels/ClosedByInterruptException
    //   3160	3413	621	java/nio/channels/ClosedByInterruptException
    //   5	91	865	finally
    //   345	396	865	finally
    //   396	529	865	finally
    //   529	553	865	finally
    //   553	560	865	finally
    //   561	588	865	finally
    //   649	700	865	finally
    //   700	833	865	finally
    //   833	857	865	finally
    //   857	862	865	finally
    //   956	1007	865	finally
    //   1007	1140	865	finally
    //   1140	1164	865	finally
    //   1164	1169	865	finally
    //   1682	1733	865	finally
    //   1733	1866	865	finally
    //   1866	1890	865	finally
    //   1890	1895	865	finally
    //   2113	2164	865	finally
    //   2164	2297	865	finally
    //   2297	2321	865	finally
    //   2321	2326	865	finally
    //   3413	3464	865	finally
    //   3464	3597	865	finally
    //   3597	3621	865	finally
    //   3621	3626	865	finally
    //   4149	4164	865	finally
    //   4170	4236	865	finally
    //   4242	4247	865	finally
    //   4247	4328	865	finally
    //   4336	4350	865	finally
    //   4353	4377	865	finally
    //   4380	4427	865	finally
    //   4430	4444	865	finally
    //   4447	4471	865	finally
    //   4474	4521	865	finally
    //   4524	4538	865	finally
    //   4541	4565	865	finally
    //   4568	4615	865	finally
    //   4618	4632	865	finally
    //   4635	4659	865	finally
    //   4662	4709	865	finally
    //   4712	4726	865	finally
    //   4729	4753	865	finally
    //   4756	4803	865	finally
    //   4806	4820	865	finally
    //   4823	4847	865	finally
    //   4850	4897	865	finally
    //   172	205	886	com/sleepycat/b/i/h/ae
    //   91	148	911	java/io/IOException
    //   153	160	911	java/io/IOException
    //   160	172	911	java/io/IOException
    //   172	205	911	java/io/IOException
    //   205	336	911	java/io/IOException
    //   608	621	911	java/io/IOException
    //   887	911	911	java/io/IOException
    //   1172	1177	911	java/io/IOException
    //   1180	1320	911	java/io/IOException
    //   1325	1403	911	java/io/IOException
    //   1411	1530	911	java/io/IOException
    //   1579	1666	911	java/io/IOException
    //   1898	2092	911	java/io/IOException
    //   2329	2380	911	java/io/IOException
    //   2432	2492	911	java/io/IOException
    //   2492	2498	911	java/io/IOException
    //   2498	2635	911	java/io/IOException
    //   2638	2757	911	java/io/IOException
    //   2920	3000	911	java/io/IOException
    //   3160	3413	911	java/io/IOException
    //   91	148	1177	com/sleepycat/b/i/c/b/an
    //   153	160	1177	com/sleepycat/b/i/c/b/an
    //   160	172	1177	com/sleepycat/b/i/c/b/an
    //   172	205	1177	com/sleepycat/b/i/c/b/an
    //   205	336	1177	com/sleepycat/b/i/c/b/an
    //   608	621	1177	com/sleepycat/b/i/c/b/an
    //   887	911	1177	com/sleepycat/b/i/c/b/an
    //   1172	1177	1177	com/sleepycat/b/i/c/b/an
    //   1180	1320	1177	com/sleepycat/b/i/c/b/an
    //   1325	1403	1177	com/sleepycat/b/i/c/b/an
    //   1411	1530	1177	com/sleepycat/b/i/c/b/an
    //   1579	1666	1177	com/sleepycat/b/i/c/b/an
    //   1898	2092	1177	com/sleepycat/b/i/c/b/an
    //   2329	2380	1177	com/sleepycat/b/i/c/b/an
    //   2432	2492	1177	com/sleepycat/b/i/c/b/an
    //   2492	2498	1177	com/sleepycat/b/i/c/b/an
    //   2498	2635	1177	com/sleepycat/b/i/c/b/an
    //   2638	2757	1177	com/sleepycat/b/i/c/b/an
    //   2920	3000	1177	com/sleepycat/b/i/c/b/an
    //   3160	3413	1177	com/sleepycat/b/i/c/b/an
    //   91	148	1403	com/sleepycat/b/i/d
    //   153	160	1403	com/sleepycat/b/i/d
    //   160	172	1403	com/sleepycat/b/i/d
    //   172	205	1403	com/sleepycat/b/i/d
    //   205	336	1403	com/sleepycat/b/i/d
    //   608	621	1403	com/sleepycat/b/i/d
    //   887	911	1403	com/sleepycat/b/i/d
    //   1172	1177	1403	com/sleepycat/b/i/d
    //   1180	1320	1403	com/sleepycat/b/i/d
    //   1325	1403	1403	com/sleepycat/b/i/d
    //   1411	1530	1403	com/sleepycat/b/i/d
    //   1579	1666	1403	com/sleepycat/b/i/d
    //   1898	2092	1403	com/sleepycat/b/i/d
    //   2329	2380	1403	com/sleepycat/b/i/d
    //   2432	2492	1403	com/sleepycat/b/i/d
    //   2492	2498	1403	com/sleepycat/b/i/d
    //   2498	2635	1403	com/sleepycat/b/i/d
    //   2638	2757	1403	com/sleepycat/b/i/d
    //   2920	3000	1403	com/sleepycat/b/i/d
    //   3160	3413	1403	com/sleepycat/b/i/d
    //   91	148	1530	java/lang/RuntimeException
    //   153	160	1530	java/lang/RuntimeException
    //   160	172	1530	java/lang/RuntimeException
    //   172	205	1530	java/lang/RuntimeException
    //   205	336	1530	java/lang/RuntimeException
    //   608	621	1530	java/lang/RuntimeException
    //   887	911	1530	java/lang/RuntimeException
    //   1172	1177	1530	java/lang/RuntimeException
    //   1180	1320	1530	java/lang/RuntimeException
    //   1325	1403	1530	java/lang/RuntimeException
    //   1411	1530	1530	java/lang/RuntimeException
    //   1579	1666	1530	java/lang/RuntimeException
    //   1898	2092	1530	java/lang/RuntimeException
    //   2329	2380	1530	java/lang/RuntimeException
    //   2432	2492	1530	java/lang/RuntimeException
    //   2492	2498	1530	java/lang/RuntimeException
    //   2498	2635	1530	java/lang/RuntimeException
    //   2638	2757	1530	java/lang/RuntimeException
    //   2920	3000	1530	java/lang/RuntimeException
    //   3160	3413	1530	java/lang/RuntimeException
    //   91	148	1666	com/sleepycat/b/i/e/o
    //   153	160	1666	com/sleepycat/b/i/e/o
    //   160	172	1666	com/sleepycat/b/i/e/o
    //   172	205	1666	com/sleepycat/b/i/e/o
    //   205	336	1666	com/sleepycat/b/i/e/o
    //   608	621	1666	com/sleepycat/b/i/e/o
    //   887	911	1666	com/sleepycat/b/i/e/o
    //   1172	1177	1666	com/sleepycat/b/i/e/o
    //   1180	1320	1666	com/sleepycat/b/i/e/o
    //   1325	1403	1666	com/sleepycat/b/i/e/o
    //   1411	1530	1666	com/sleepycat/b/i/e/o
    //   1579	1666	1666	com/sleepycat/b/i/e/o
    //   1898	2092	1666	com/sleepycat/b/i/e/o
    //   2329	2380	1666	com/sleepycat/b/i/e/o
    //   2432	2492	1666	com/sleepycat/b/i/e/o
    //   2492	2498	1666	com/sleepycat/b/i/e/o
    //   2498	2635	1666	com/sleepycat/b/i/e/o
    //   2638	2757	1666	com/sleepycat/b/i/e/o
    //   2920	3000	1666	com/sleepycat/b/i/e/o
    //   3160	3413	1666	com/sleepycat/b/i/e/o
    //   91	148	2092	com/sleepycat/b/i/c/b/aj
    //   153	160	2092	com/sleepycat/b/i/c/b/aj
    //   160	172	2092	com/sleepycat/b/i/c/b/aj
    //   172	205	2092	com/sleepycat/b/i/c/b/aj
    //   205	336	2092	com/sleepycat/b/i/c/b/aj
    //   608	621	2092	com/sleepycat/b/i/c/b/aj
    //   887	911	2092	com/sleepycat/b/i/c/b/aj
    //   1172	1177	2092	com/sleepycat/b/i/c/b/aj
    //   1180	1320	2092	com/sleepycat/b/i/c/b/aj
    //   1325	1403	2092	com/sleepycat/b/i/c/b/aj
    //   1411	1530	2092	com/sleepycat/b/i/c/b/aj
    //   1579	1666	2092	com/sleepycat/b/i/c/b/aj
    //   1898	2092	2092	com/sleepycat/b/i/c/b/aj
    //   2329	2380	2092	com/sleepycat/b/i/c/b/aj
    //   2432	2492	2092	com/sleepycat/b/i/c/b/aj
    //   2492	2498	2092	com/sleepycat/b/i/c/b/aj
    //   2498	2635	2092	com/sleepycat/b/i/c/b/aj
    //   2638	2757	2092	com/sleepycat/b/i/c/b/aj
    //   2920	3000	2092	com/sleepycat/b/i/c/b/aj
    //   3160	3413	2092	com/sleepycat/b/i/c/b/aj
    //   91	148	2380	java/lang/Exception
    //   153	160	2380	java/lang/Exception
    //   160	172	2380	java/lang/Exception
    //   172	205	2380	java/lang/Exception
    //   205	336	2380	java/lang/Exception
    //   608	621	2380	java/lang/Exception
    //   887	911	2380	java/lang/Exception
    //   1172	1177	2380	java/lang/Exception
    //   1180	1320	2380	java/lang/Exception
    //   1325	1403	2380	java/lang/Exception
    //   1411	1530	2380	java/lang/Exception
    //   1579	1666	2380	java/lang/Exception
    //   1898	2092	2380	java/lang/Exception
    //   2329	2380	2380	java/lang/Exception
    //   2432	2492	2380	java/lang/Exception
    //   2492	2498	2380	java/lang/Exception
    //   2498	2635	2380	java/lang/Exception
    //   2638	2757	2380	java/lang/Exception
    //   2920	3000	2380	java/lang/Exception
    //   3160	3413	2380	java/lang/Exception
    //   2757	2918	2918	finally
    //   3006	3020	2918	finally
    //   3020	3160	2918	finally
    //   3629	3677	2918	finally
    //   3677	3731	2918	finally
    //   3731	3801	2918	finally
    //   3804	3835	2918	finally
    //   3835	3891	2918	finally
    //   3891	3947	2918	finally
    //   3947	4036	2918	finally
    //   4036	4123	2918	finally
  }
  
  protected void b()
  {
    int i1 = this.a.i.u.a(an.O);
    this.c.a(i1);
    am localam = new am(this, this.j, "ReplayThread");
    localam.start();
    for (;;)
    {
      try
      {
        com.sleepycat.b.i.h.d locald = this.e.a(this.c);
        boolean bool = this.a.k();
        if ((bool) || (locald == null))
        {
          throw am.b(localam);
          this.r.f();
        }
        if (am.a(localam).offer(locald, 1000000000L, TimeUnit.NANOSECONDS)) {
          continue;
        }
        bool = localam.isAlive();
        if (bool) {
          continue;
        }
        throw am.b(localam);
      }
      catch (IOException localIOException)
      {
        localam.a = al.b;
        throw am.b(localam);
        localam.a = al.a;
        localam.join();
        throw localIOException;
        localam.a = al.a;
        localam.join();
        return;
      }
      finally
      {
        if (localam.a == al.b) {
          localam.join();
        }
        if (am.b(localam) == null) {
          continue;
        }
      }
      localam.a = al.a;
      continue;
      localam.a = al.a;
    }
  }
  
  final void c()
  {
    c localc = this.i;
    Iterator localIterator = localc.a.values().iterator();
    while (localIterator.hasNext()) {
      localc.a(((e)localIterator.next()).b);
    }
    localc.a.clear();
  }
  
  final void d()
  {
    if (this.j.ap.a() == u.c) {
      throw com.sleepycat.b.aa.a(this.j, "Should not be in MASTER state when converting from master to replica state");
    }
    Object localObject2 = this.j.y.b();
    Object localObject1 = new HashSet();
    localObject2 = ((Set)localObject2).iterator();
    while (((Iterator)localObject2).hasNext()) {
      ((Set)localObject1).add((b)((Iterator)localObject2).next());
    }
    w.c(this.q, this.j, "Transitioning node to replica state, " + ((Set)localObject1).size() + " txns to clean up");
    localObject2 = ((Set)localObject1).iterator();
    while (((Iterator)localObject2).hasNext()) {
      ((b)((Iterator)localObject2).next()).g = true;
    }
    this.j.Z();
    localObject1 = ((Set)localObject1).iterator();
    while (((Iterator)localObject1).hasNext())
    {
      localObject2 = (b)((Iterator)localObject1).next();
      com.sleepycat.b.i.f.e locale = ((b)localObject2).a(this.q, this.j.an);
      if (locale == null)
      {
        w.c(this.q, this.j, "Master Txn " + ((com.sleepycat.b.n.q)localObject2).k + " has no locks, nothing to transfer");
      }
      else
      {
        this.j.y.a(locale);
        w.c(this.q, this.j, "state for replay transaction " + locale.k + " = " + locale.u);
      }
    }
    this.a.i();
  }
}


/* Location:              E:\apk\xueqiu2\classes-dex2jar.jar!\com\sleepycat\b\i\c\b\ag.class
 * Java compiler version: 6 (50.0)
 * JD-Core Version:       0.7.1
 */