package com.sleepycat.b.i.c.b;

import com.sleepycat.b.c.ad;
import com.sleepycat.b.c.m;
import com.sleepycat.b.i.c.an;
import com.sleepycat.b.i.h.d;
import com.sleepycat.b.p.aj;
import com.sleepycat.b.p.w;
import java.util.concurrent.ArrayBlockingQueue;
import java.util.concurrent.BlockingQueue;
import java.util.logging.Logger;

final class am
  extends aj
{
  volatile int a = 0;
  private final BlockingQueue<d> d;
  private volatile Exception e;
  
  static
  {
    if (!ag.class.desiredAssertionStatus()) {}
    for (boolean bool = true;; bool = false)
    {
      b = bool;
      return;
    }
  }
  
  protected am(ag paramag, ad paramad, String paramString)
  {
    super(paramad, paramString);
    int i = ag.a(paramag).i.u.a(an.e);
    w.c(ag.b(paramag), ag.c(paramag), "Replay thread started. Message queue size:" + i);
    this.d = new ArrayBlockingQueue(i);
  }
  
  protected final Logger a()
  {
    return ag.b(this.c);
  }
  
  protected final int c()
  {
    this.a = al.a;
    return 0;
  }
  
  /* Error */
  public final void run()
  {
    // Byte code:
    //   0: aload_0
    //   1: getfield 32	com/sleepycat/b/i/c/b/am:c	Lcom/sleepycat/b/i/c/b/ag;
    //   4: invokestatic 40	com/sleepycat/b/i/c/b/ag:a	(Lcom/sleepycat/b/i/c/b/ag;)Lcom/sleepycat/b/i/c/b/aa;
    //   7: getfield 46	com/sleepycat/b/i/c/b/aa:i	Lcom/sleepycat/b/i/c/aj;
    //   10: getfield 52	com/sleepycat/b/c/ad:u	Lcom/sleepycat/b/c/m;
    //   13: getstatic 116	com/sleepycat/b/i/c/an:z	Lcom/sleepycat/b/b/e;
    //   16: invokevirtual 62	com/sleepycat/b/c/m:a	(Lcom/sleepycat/b/b/e;)I
    //   19: istore 14
    //   21: aload_0
    //   22: getfield 32	com/sleepycat/b/i/c/b/am:c	Lcom/sleepycat/b/i/c/b/ag;
    //   25: invokestatic 120	com/sleepycat/b/i/c/b/ag:f	(Lcom/sleepycat/b/i/c/b/ag;)Lcom/sleepycat/b/i/c/b/ac;
    //   28: astore_2
    //   29: aload_0
    //   30: getfield 32	com/sleepycat/b/i/c/b/am:c	Lcom/sleepycat/b/i/c/b/ag;
    //   33: invokestatic 123	com/sleepycat/b/i/c/b/ag:d	(Lcom/sleepycat/b/i/c/b/ag;)Lcom/sleepycat/b/i/h/p;
    //   36: astore_3
    //   37: aload_0
    //   38: getfield 32	com/sleepycat/b/i/c/b/am:c	Lcom/sleepycat/b/i/c/b/ag;
    //   41: invokestatic 126	com/sleepycat/b/i/c/b/ag:e	(Lcom/sleepycat/b/i/c/b/ag;)Lcom/sleepycat/b/i/e/t;
    //   44: astore 4
    //   46: aload_2
    //   47: aload_3
    //   48: putfield 132	com/sleepycat/b/i/c/b/ac:k	Lcom/sleepycat/b/i/h/o;
    //   51: aload_2
    //   52: aload 4
    //   54: putfield 136	com/sleepycat/b/i/c/b/ac:l	Lcom/sleepycat/b/i/e/t;
    //   57: lconst_0
    //   58: lstore 15
    //   60: aload_0
    //   61: getfield 32	com/sleepycat/b/i/c/b/am:c	Lcom/sleepycat/b/i/c/b/ag;
    //   64: invokestatic 120	com/sleepycat/b/i/c/b/ag:f	(Lcom/sleepycat/b/i/c/b/ag;)Lcom/sleepycat/b/i/c/b/ac;
    //   67: getfield 140	com/sleepycat/b/i/c/b/ac:m	Lcom/sleepycat/b/i/c/b/ad;
    //   70: astore_2
    //   71: aload_2
    //   72: getfield 144	com/sleepycat/b/i/c/b/ad:b	I
    //   75: ifne +89 -> 164
    //   78: ldc2_w 145
    //   81: lstore 17
    //   83: aload_0
    //   84: getfield 95	com/sleepycat/b/i/c/b/am:d	Ljava/util/concurrent/BlockingQueue;
    //   87: lload 17
    //   89: getstatic 152	java/util/concurrent/TimeUnit:NANOSECONDS	Ljava/util/concurrent/TimeUnit;
    //   92: invokeinterface 158 4 0
    //   97: checkcast 160	com/sleepycat/b/i/h/d
    //   100: astore 7
    //   102: aload_0
    //   103: getfield 37	com/sleepycat/b/i/c/b/am:a	I
    //   106: getstatic 104	com/sleepycat/b/i/c/b/al:a	I
    //   109: if_icmpeq +31 -> 140
    //   112: aload_0
    //   113: getfield 37	com/sleepycat/b/i/c/b/am:a	I
    //   116: getstatic 161	com/sleepycat/b/i/c/b/al:b	I
    //   119: if_icmpne +8 -> 127
    //   122: aload 7
    //   124: ifnull +16 -> 140
    //   127: aload_0
    //   128: getfield 32	com/sleepycat/b/i/c/b/am:c	Lcom/sleepycat/b/i/c/b/ag;
    //   131: invokestatic 40	com/sleepycat/b/i/c/b/ag:a	(Lcom/sleepycat/b/i/c/b/ag;)Lcom/sleepycat/b/i/c/b/aa;
    //   134: invokevirtual 163	com/sleepycat/b/i/c/b/aa:k	()Z
    //   137: ifeq +50 -> 187
    //   140: aload_0
    //   141: getfield 37	com/sleepycat/b/i/c/b/am:a	I
    //   144: getstatic 161	com/sleepycat/b/i/c/b/al:b	I
    //   147: if_icmpne +3344 -> 3491
    //   150: aload_0
    //   151: getfield 32	com/sleepycat/b/i/c/b/am:c	Lcom/sleepycat/b/i/c/b/ag;
    //   154: invokestatic 120	com/sleepycat/b/i/c/b/ag:f	(Lcom/sleepycat/b/i/c/b/ag;)Lcom/sleepycat/b/i/c/b/ac;
    //   157: ldc2_w 164
    //   160: invokevirtual 168	com/sleepycat/b/i/c/b/ac:a	(J)V
    //   163: return
    //   164: invokestatic 174	java/lang/System:nanoTime	()J
    //   167: lstore 17
    //   169: aload_2
    //   170: getfield 177	com/sleepycat/b/i/c/b/ad:c	J
    //   173: lload 17
    //   175: lsub
    //   176: ldc2_w 145
    //   179: invokestatic 183	java/lang/Math:min	(JJ)J
    //   182: lstore 17
    //   184: goto -101 -> 83
    //   187: invokestatic 174	java/lang/System:nanoTime	()J
    //   190: lstore 17
    //   192: aload_0
    //   193: getfield 32	com/sleepycat/b/i/c/b/am:c	Lcom/sleepycat/b/i/c/b/ag;
    //   196: invokestatic 120	com/sleepycat/b/i/c/b/ag:f	(Lcom/sleepycat/b/i/c/b/ag;)Lcom/sleepycat/b/i/c/b/ac;
    //   199: lload 17
    //   201: invokevirtual 168	com/sleepycat/b/i/c/b/ac:a	(J)V
    //   204: aload_0
    //   205: getfield 32	com/sleepycat/b/i/c/b/am:c	Lcom/sleepycat/b/i/c/b/ag;
    //   208: invokestatic 40	com/sleepycat/b/i/c/b/ag:a	(Lcom/sleepycat/b/i/c/b/ag;)Lcom/sleepycat/b/i/c/b/aa;
    //   211: getfield 187	com/sleepycat/b/i/c/b/aa:g	Lcom/sleepycat/b/i/e/n;
    //   214: invokevirtual 191	com/sleepycat/b/i/e/n:e	()V
    //   217: aload 7
    //   219: ifnull -159 -> 60
    //   222: aload 7
    //   224: invokevirtual 194	com/sleepycat/b/i/h/d:a	()Lcom/sleepycat/b/i/h/e;
    //   227: astore_2
    //   228: aload_2
    //   229: getstatic 200	com/sleepycat/b/i/e/t:w	Lcom/sleepycat/b/i/h/e;
    //   232: if_acmpne +78 -> 310
    //   235: aload_0
    //   236: getfield 32	com/sleepycat/b/i/c/b/am:c	Lcom/sleepycat/b/i/c/b/ag;
    //   239: aload 7
    //   241: checkcast 202	com/sleepycat/b/i/e/as
    //   244: invokestatic 205	com/sleepycat/b/i/c/b/ag:a	(Lcom/sleepycat/b/i/c/b/ag;Lcom/sleepycat/b/i/e/as;)Lcom/sleepycat/b/i/d;
    //   247: athrow
    //   248: astore_2
    //   249: aload_0
    //   250: aload_2
    //   251: putfield 99	com/sleepycat/b/i/c/b/am:e	Ljava/lang/Exception;
    //   254: aload_0
    //   255: getfield 95	com/sleepycat/b/i/c/b/am:d	Ljava/util/concurrent/BlockingQueue;
    //   258: invokeinterface 208 1 0
    //   263: aload_0
    //   264: getfield 32	com/sleepycat/b/i/c/b/am:c	Lcom/sleepycat/b/i/c/b/ag;
    //   267: invokestatic 123	com/sleepycat/b/i/c/b/ag:d	(Lcom/sleepycat/b/i/c/b/ag;)Lcom/sleepycat/b/i/h/p;
    //   270: invokestatic 213	com/sleepycat/b/i/h/q:a	(Lcom/sleepycat/b/i/h/o;)V
    //   273: aload_0
    //   274: getfield 32	com/sleepycat/b/i/c/b/am:c	Lcom/sleepycat/b/i/c/b/ag;
    //   277: invokestatic 65	com/sleepycat/b/i/c/b/ag:b	(Lcom/sleepycat/b/i/c/b/ag;)Ljava/util/logging/Logger;
    //   280: aload_0
    //   281: getfield 32	com/sleepycat/b/i/c/b/am:c	Lcom/sleepycat/b/i/c/b/ag;
    //   284: invokestatic 68	com/sleepycat/b/i/c/b/ag:c	(Lcom/sleepycat/b/i/c/b/ag;)Lcom/sleepycat/b/i/c/aj;
    //   287: new 70	java/lang/StringBuilder
    //   290: dup
    //   291: ldc -41
    //   293: invokespecial 75	java/lang/StringBuilder:<init>	(Ljava/lang/String;)V
    //   296: aload_2
    //   297: invokevirtual 218	java/lang/Exception:getMessage	()Ljava/lang/String;
    //   300: invokevirtual 221	java/lang/StringBuilder:append	(Ljava/lang/String;)Ljava/lang/StringBuilder;
    //   303: invokevirtual 83	java/lang/StringBuilder:toString	()Ljava/lang/String;
    //   306: invokestatic 88	com/sleepycat/b/p/w:c	(Ljava/util/logging/Logger;Lcom/sleepycat/b/c/ad;Ljava/lang/String;)V
    //   309: return
    //   310: aload_2
    //   311: getstatic 224	com/sleepycat/b/i/e/t:n	Lcom/sleepycat/b/i/h/e;
    //   314: if_acmpne +176 -> 490
    //   317: aload_0
    //   318: getfield 32	com/sleepycat/b/i/c/b/am:c	Lcom/sleepycat/b/i/c/b/ag;
    //   321: aload_0
    //   322: getfield 32	com/sleepycat/b/i/c/b/am:c	Lcom/sleepycat/b/i/c/b/ag;
    //   325: invokestatic 123	com/sleepycat/b/i/c/b/ag:d	(Lcom/sleepycat/b/i/c/b/ag;)Lcom/sleepycat/b/i/h/p;
    //   328: aload 7
    //   330: checkcast 226	com/sleepycat/b/i/e/ae
    //   333: invokestatic 229	com/sleepycat/b/i/c/b/ag:a	(Lcom/sleepycat/b/i/c/b/ag;Lcom/sleepycat/b/i/h/o;Lcom/sleepycat/b/i/e/ae;)V
    //   336: aload_0
    //   337: getfield 32	com/sleepycat/b/i/c/b/am:c	Lcom/sleepycat/b/i/c/b/ag;
    //   340: invokestatic 232	com/sleepycat/b/i/c/b/ag:g	(Lcom/sleepycat/b/i/c/b/ag;)Lcom/sleepycat/b/i/c/b/c;
    //   343: astore_2
    //   344: aload_2
    //   345: getfield 236	com/sleepycat/b/i/c/b/c:c	I
    //   348: ifle +20 -> 368
    //   351: invokestatic 239	java/lang/System:currentTimeMillis	()J
    //   354: aload_2
    //   355: getfield 241	com/sleepycat/b/i/c/b/c:e	J
    //   358: lsub
    //   359: aload_2
    //   360: getfield 236	com/sleepycat/b/i/c/b/c:c	I
    //   363: i2l
    //   364: lcmp
    //   365: ifle +83 -> 448
    //   368: aload_2
    //   369: getfield 244	com/sleepycat/b/i/c/b/c:a	Lcom/sleepycat/b/i/c/b/d;
    //   372: invokevirtual 250	com/sleepycat/b/i/c/b/d:values	()Ljava/util/Collection;
    //   375: invokeinterface 256 1 0
    //   380: astore_3
    //   381: aload_3
    //   382: invokeinterface 261 1 0
    //   387: ifeq +44 -> 431
    //   390: aload_3
    //   391: invokeinterface 265 1 0
    //   396: checkcast 267	com/sleepycat/b/i/c/b/e
    //   399: astore 4
    //   401: aload 4
    //   403: getfield 268	com/sleepycat/b/i/c/b/e:a	I
    //   406: aload_2
    //   407: getfield 270	com/sleepycat/b/i/c/b/c:d	I
    //   410: if_icmpge -29 -> 381
    //   413: aload_2
    //   414: aload 4
    //   416: getfield 273	com/sleepycat/b/i/c/b/e:b	Lcom/sleepycat/b/c/i;
    //   419: invokevirtual 276	com/sleepycat/b/i/c/b/c:a	(Lcom/sleepycat/b/c/i;)V
    //   422: aload_3
    //   423: invokeinterface 279 1 0
    //   428: goto -47 -> 381
    //   431: aload_2
    //   432: aload_2
    //   433: getfield 270	com/sleepycat/b/i/c/b/c:d	I
    //   436: iconst_1
    //   437: iadd
    //   438: putfield 270	com/sleepycat/b/i/c/b/c:d	I
    //   441: aload_2
    //   442: invokestatic 239	java/lang/System:currentTimeMillis	()J
    //   445: putfield 241	com/sleepycat/b/i/c/b/c:e	J
    //   448: aload_0
    //   449: getfield 32	com/sleepycat/b/i/c/b/am:c	Lcom/sleepycat/b/i/c/b/ag;
    //   452: invokestatic 283	com/sleepycat/b/i/c/b/ag:j	(Lcom/sleepycat/b/i/c/b/ag;)I
    //   455: ifle +14 -> 469
    //   458: aload_0
    //   459: getfield 32	com/sleepycat/b/i/c/b/am:c	Lcom/sleepycat/b/i/c/b/ag;
    //   462: invokestatic 283	com/sleepycat/b/i/c/b/ag:j	(Lcom/sleepycat/b/i/c/b/ag;)I
    //   465: i2l
    //   466: invokestatic 288	java/lang/Thread:sleep	(J)V
    //   469: lload 15
    //   471: iload 14
    //   473: i2l
    //   474: lrem
    //   475: lconst_0
    //   476: lcmp
    //   477: ifne +3015 -> 3492
    //   480: aload_0
    //   481: getfield 32	com/sleepycat/b/i/c/b/am:c	Lcom/sleepycat/b/i/c/b/ag;
    //   484: invokevirtual 290	com/sleepycat/b/i/c/b/ag:c	()V
    //   487: goto +3005 -> 3492
    //   490: aload_0
    //   491: getfield 32	com/sleepycat/b/i/c/b/am:c	Lcom/sleepycat/b/i/c/b/ag;
    //   494: invokestatic 294	com/sleepycat/b/i/c/b/ag:h	(Lcom/sleepycat/b/i/c/b/ag;)Z
    //   497: ifeq +41 -> 538
    //   500: aload_0
    //   501: getfield 32	com/sleepycat/b/i/c/b/am:c	Lcom/sleepycat/b/i/c/b/ag;
    //   504: invokestatic 65	com/sleepycat/b/i/c/b/ag:b	(Lcom/sleepycat/b/i/c/b/ag;)Ljava/util/logging/Logger;
    //   507: aload_0
    //   508: getfield 32	com/sleepycat/b/i/c/b/am:c	Lcom/sleepycat/b/i/c/b/ag;
    //   511: invokestatic 68	com/sleepycat/b/i/c/b/ag:c	(Lcom/sleepycat/b/i/c/b/ag;)Lcom/sleepycat/b/i/c/aj;
    //   514: new 70	java/lang/StringBuilder
    //   517: dup
    //   518: ldc_w 296
    //   521: invokespecial 75	java/lang/StringBuilder:<init>	(Ljava/lang/String;)V
    //   524: aload 7
    //   526: invokevirtual 299	java/lang/StringBuilder:append	(Ljava/lang/Object;)Ljava/lang/StringBuilder;
    //   529: invokevirtual 83	java/lang/StringBuilder:toString	()Ljava/lang/String;
    //   532: invokestatic 88	com/sleepycat/b/p/w:c	(Ljava/util/logging/Logger;Lcom/sleepycat/b/c/ad;Ljava/lang/String;)V
    //   535: goto -475 -> 60
    //   538: aload_0
    //   539: getfield 32	com/sleepycat/b/i/c/b/am:c	Lcom/sleepycat/b/i/c/b/ag;
    //   542: invokestatic 120	com/sleepycat/b/i/c/b/ag:f	(Lcom/sleepycat/b/i/c/b/ag;)Lcom/sleepycat/b/i/c/b/ac;
    //   545: astore 5
    //   547: aload 7
    //   549: checkcast 301	com/sleepycat/b/i/e/y
    //   552: astore_2
    //   553: aload_2
    //   554: invokevirtual 304	com/sleepycat/b/i/e/y:d	()Lcom/sleepycat/b/i/e/k;
    //   557: astore 6
    //   559: aload 6
    //   561: getfield 309	com/sleepycat/b/i/e/k:a	Lcom/sleepycat/b/g/a/m;
    //   564: astore 4
    //   566: aload 6
    //   568: getfield 312	com/sleepycat/b/i/e/k:d	Lcom/sleepycat/b/g/ae;
    //   571: getfield 317	com/sleepycat/b/g/ae:e	Lcom/sleepycat/b/p/au;
    //   574: astore_3
    //   575: aload 5
    //   577: getfield 319	com/sleepycat/b/i/c/b/ac:h	Lcom/sleepycat/b/p/au;
    //   580: astore 8
    //   582: aload 8
    //   584: invokevirtual 323	com/sleepycat/b/p/au:c	()Z
    //   587: ifeq +12 -> 599
    //   590: aload_3
    //   591: getfield 324	com/sleepycat/b/p/au:c	J
    //   594: lconst_1
    //   595: lcmp
    //   596: ifeq +2905 -> 3501
    //   599: aload 8
    //   601: invokevirtual 323	com/sleepycat/b/p/au:c	()Z
    //   604: ifne +2903 -> 3507
    //   607: aload 8
    //   609: getfield 324	com/sleepycat/b/p/au:c	J
    //   612: aload_3
    //   613: getfield 324	com/sleepycat/b/p/au:c	J
    //   616: lconst_1
    //   617: lsub
    //   618: lcmp
    //   619: ifne +2888 -> 3507
    //   622: goto +2879 -> 3501
    //   625: iload 13
    //   627: ifne +57 -> 684
    //   630: new 326	com/sleepycat/b/aa
    //   633: dup
    //   634: aload 5
    //   636: getfield 328	com/sleepycat/b/i/c/b/ac:d	Lcom/sleepycat/b/i/c/aj;
    //   639: getstatic 334	com/sleepycat/b/c/ac:B	Lcom/sleepycat/b/c/ac;
    //   642: new 70	java/lang/StringBuilder
    //   645: dup
    //   646: ldc_w 336
    //   649: invokespecial 75	java/lang/StringBuilder:<init>	(Ljava/lang/String;)V
    //   652: aload 5
    //   654: getfield 319	com/sleepycat/b/i/c/b/ac:h	Lcom/sleepycat/b/p/au;
    //   657: invokevirtual 299	java/lang/StringBuilder:append	(Ljava/lang/Object;)Ljava/lang/StringBuilder;
    //   660: ldc_w 338
    //   663: invokevirtual 221	java/lang/StringBuilder:append	(Ljava/lang/String;)Ljava/lang/StringBuilder;
    //   666: aload 6
    //   668: getfield 312	com/sleepycat/b/i/e/k:d	Lcom/sleepycat/b/g/ae;
    //   671: getfield 317	com/sleepycat/b/g/ae:e	Lcom/sleepycat/b/p/au;
    //   674: invokevirtual 299	java/lang/StringBuilder:append	(Ljava/lang/Object;)Ljava/lang/StringBuilder;
    //   677: invokevirtual 83	java/lang/StringBuilder:toString	()Ljava/lang/String;
    //   680: invokespecial 341	com/sleepycat/b/aa:<init>	(Lcom/sleepycat/b/c/ad;Lcom/sleepycat/b/c/ac;Ljava/lang/String;)V
    //   683: athrow
    //   684: aload 5
    //   686: getfield 345	com/sleepycat/b/i/c/b/ac:C	Ljava/util/logging/Logger;
    //   689: getstatic 351	java/util/logging/Level:FINEST	Ljava/util/logging/Level;
    //   692: invokevirtual 357	java/util/logging/Logger:isLoggable	(Ljava/util/logging/Level;)Z
    //   695: ifeq +34 -> 729
    //   698: aload 5
    //   700: getfield 345	com/sleepycat/b/i/c/b/ac:C	Ljava/util/logging/Logger;
    //   703: aload 5
    //   705: getfield 328	com/sleepycat/b/i/c/b/ac:d	Lcom/sleepycat/b/i/c/aj;
    //   708: new 70	java/lang/StringBuilder
    //   711: dup
    //   712: ldc_w 359
    //   715: invokespecial 75	java/lang/StringBuilder:<init>	(Ljava/lang/String;)V
    //   718: aload 6
    //   720: invokevirtual 299	java/lang/StringBuilder:append	(Ljava/lang/Object;)Ljava/lang/StringBuilder;
    //   723: invokevirtual 83	java/lang/StringBuilder:toString	()Ljava/lang/String;
    //   726: invokestatic 361	com/sleepycat/b/p/w:e	(Ljava/util/logging/Logger;Lcom/sleepycat/b/c/ad;Ljava/lang/String;)V
    //   729: aload 5
    //   731: aload 4
    //   733: invokeinterface 365 1 0
    //   738: iconst_1
    //   739: invokevirtual 368	com/sleepycat/b/i/c/b/ac:a	(JZ)Lcom/sleepycat/b/i/f/e;
    //   742: astore 8
    //   744: aload 5
    //   746: getfield 328	com/sleepycat/b/i/c/b/ac:d	Lcom/sleepycat/b/i/c/aj;
    //   749: getfield 372	com/sleepycat/b/c/ad:y	Lcom/sleepycat/b/n/aj;
    //   752: astore_3
    //   753: aload 4
    //   755: invokeinterface 365 1 0
    //   760: lstore 19
    //   762: getstatic 376	com/sleepycat/b/n/aj:m	Z
    //   765: ifne +21 -> 786
    //   768: aload_3
    //   769: getfield 379	com/sleepycat/b/n/aj:b	Lcom/sleepycat/b/c/ad;
    //   772: invokevirtual 382	com/sleepycat/b/c/ad:R	()Z
    //   775: ifeq +11 -> 786
    //   778: new 384	java/lang/AssertionError
    //   781: dup
    //   782: invokespecial 386	java/lang/AssertionError:<init>	()V
    //   785: athrow
    //   786: getstatic 376	com/sleepycat/b/n/aj:m	Z
    //   789: ifne +36 -> 825
    //   792: lload 19
    //   794: lconst_0
    //   795: lcmp
    //   796: iflt +29 -> 825
    //   799: new 384	java/lang/AssertionError
    //   802: dup
    //   803: new 70	java/lang/StringBuilder
    //   806: dup
    //   807: ldc_w 388
    //   810: invokespecial 75	java/lang/StringBuilder:<init>	(Ljava/lang/String;)V
    //   813: lload 19
    //   815: invokevirtual 391	java/lang/StringBuilder:append	(J)Ljava/lang/StringBuilder;
    //   818: invokevirtual 83	java/lang/StringBuilder:toString	()Ljava/lang/String;
    //   821: invokespecial 394	java/lang/AssertionError:<init>	(Ljava/lang/Object;)V
    //   824: athrow
    //   825: lload 19
    //   827: aload_3
    //   828: getfield 397	com/sleepycat/b/n/aj:h	Ljava/util/concurrent/atomic/AtomicLong;
    //   831: invokevirtual 402	java/util/concurrent/atomic/AtomicLong:get	()J
    //   834: lcmp
    //   835: ifge +12 -> 847
    //   838: aload_3
    //   839: getfield 397	com/sleepycat/b/n/aj:h	Ljava/util/concurrent/atomic/AtomicLong;
    //   842: lload 19
    //   844: invokevirtual 405	java/util/concurrent/atomic/AtomicLong:set	(J)V
    //   847: aload 4
    //   849: instanceof 407
    //   852: ifeq +131 -> 983
    //   855: aload 4
    //   857: checkcast 407	com/sleepycat/b/g/a/o
    //   860: astore_3
    //   861: aload_3
    //   862: iconst_0
    //   863: invokevirtual 410	com/sleepycat/b/g/a/o:b	(Z)V
    //   866: aload_3
    //   867: invokevirtual 413	com/sleepycat/b/g/a/o:j	()Lcom/sleepycat/b/l/y;
    //   870: checkcast 415	com/sleepycat/b/l/ab
    //   873: astore 9
    //   875: aload 5
    //   877: getfield 328	com/sleepycat/b/i/c/b/ac:d	Lcom/sleepycat/b/i/c/aj;
    //   880: getfield 419	com/sleepycat/b/c/ad:q	Lcom/sleepycat/b/c/p;
    //   883: astore_3
    //   884: aload 9
    //   886: getfield 422	com/sleepycat/b/l/ab:a	Lcom/sleepycat/b/c/h;
    //   889: astore 9
    //   891: getstatic 426	com/sleepycat/b/c/p:i	Z
    //   894: ifne +21 -> 915
    //   897: aload_3
    //   898: getfield 428	com/sleepycat/b/c/p:h	Lcom/sleepycat/b/c/ad;
    //   901: invokevirtual 382	com/sleepycat/b/c/ad:R	()Z
    //   904: ifeq +11 -> 915
    //   907: new 384	java/lang/AssertionError
    //   910: dup
    //   911: invokespecial 386	java/lang/AssertionError:<init>	()V
    //   914: athrow
    //   915: aload 9
    //   917: getfield 432	com/sleepycat/b/c/h:a	J
    //   920: lstore 19
    //   922: lload 19
    //   924: lconst_0
    //   925: lcmp
    //   926: ifle +35 -> 961
    //   929: aload_3
    //   930: getfield 428	com/sleepycat/b/c/p:h	Lcom/sleepycat/b/c/ad;
    //   933: invokevirtual 435	com/sleepycat/b/c/ad:N	()Z
    //   936: ifne +25 -> 961
    //   939: new 70	java/lang/StringBuilder
    //   942: dup
    //   943: ldc_w 437
    //   946: invokespecial 75	java/lang/StringBuilder:<init>	(Ljava/lang/String;)V
    //   949: aload 9
    //   951: invokevirtual 299	java/lang/StringBuilder:append	(Ljava/lang/Object;)Ljava/lang/StringBuilder;
    //   954: invokevirtual 83	java/lang/StringBuilder:toString	()Ljava/lang/String;
    //   957: invokestatic 440	com/sleepycat/b/aa:c	(Ljava/lang/String;)Lcom/sleepycat/b/aa;
    //   960: athrow
    //   961: lload 19
    //   963: aload_3
    //   964: getfield 442	com/sleepycat/b/c/p:d	Ljava/util/concurrent/atomic/AtomicLong;
    //   967: invokevirtual 402	java/util/concurrent/atomic/AtomicLong:get	()J
    //   970: lcmp
    //   971: ifge +12 -> 983
    //   974: aload_3
    //   975: getfield 442	com/sleepycat/b/c/p:d	Ljava/util/concurrent/atomic/AtomicLong;
    //   978: lload 19
    //   980: invokevirtual 405	java/util/concurrent/atomic/AtomicLong:set	(J)V
    //   983: aload 6
    //   985: getfield 312	com/sleepycat/b/i/e/k:d	Lcom/sleepycat/b/g/ae;
    //   988: getfield 444	com/sleepycat/b/g/ae:b	B
    //   991: istore_1
    //   992: aload 5
    //   994: aload 6
    //   996: getfield 312	com/sleepycat/b/i/e/k:d	Lcom/sleepycat/b/g/ae;
    //   999: getfield 317	com/sleepycat/b/g/ae:e	Lcom/sleepycat/b/p/au;
    //   1002: putfield 319	com/sleepycat/b/i/c/b/ac:h	Lcom/sleepycat/b/p/au;
    //   1005: getstatic 449	com/sleepycat/b/g/af:q	Lcom/sleepycat/b/g/af;
    //   1008: iload_1
    //   1009: invokevirtual 452	com/sleepycat/b/g/af:c	(B)Z
    //   1012: ifeq +910 -> 1922
    //   1015: aload_2
    //   1016: checkcast 454	com/sleepycat/b/i/e/w
    //   1019: astore_2
    //   1020: aload_2
    //   1021: getfield 456	com/sleepycat/b/i/e/w:a	Z
    //   1024: istore 25
    //   1026: aload_2
    //   1027: getfield 459	com/sleepycat/b/i/e/w:b	Lcom/sleepycat/b/w;
    //   1030: astore_3
    //   1031: iload 25
    //   1033: ifeq +713 -> 1746
    //   1036: aload 5
    //   1038: getfield 140	com/sleepycat/b/i/c/b/ac:m	Lcom/sleepycat/b/i/c/b/ad;
    //   1041: astore_2
    //   1042: aload_3
    //   1043: getstatic 463	com/sleepycat/b/w:a	Lcom/sleepycat/b/w;
    //   1046: if_acmpne +695 -> 1741
    //   1049: aload_2
    //   1050: invokevirtual 465	com/sleepycat/b/i/c/b/ad:a	()Z
    //   1053: ifeq +688 -> 1741
    //   1056: getstatic 466	com/sleepycat/b/w:b	Lcom/sleepycat/b/w;
    //   1059: astore_2
    //   1060: aload 5
    //   1062: getfield 345	com/sleepycat/b/i/c/b/ac:C	Ljava/util/logging/Logger;
    //   1065: getstatic 469	java/util/logging/Level:FINE	Ljava/util/logging/Level;
    //   1068: invokevirtual 357	java/util/logging/Logger:isLoggable	(Ljava/util/logging/Level;)Z
    //   1071: ifeq +66 -> 1137
    //   1074: iload 25
    //   1076: ifeq +679 -> 1755
    //   1079: aload 5
    //   1081: getfield 345	com/sleepycat/b/i/c/b/ac:C	Ljava/util/logging/Logger;
    //   1084: aload 5
    //   1086: getfield 328	com/sleepycat/b/i/c/b/ac:d	Lcom/sleepycat/b/i/c/aj;
    //   1089: new 70	java/lang/StringBuilder
    //   1092: dup
    //   1093: ldc_w 471
    //   1096: invokespecial 75	java/lang/StringBuilder:<init>	(Ljava/lang/String;)V
    //   1099: aload 8
    //   1101: getfield 475	com/sleepycat/b/n/q:k	J
    //   1104: invokevirtual 391	java/lang/StringBuilder:append	(J)Ljava/lang/StringBuilder;
    //   1107: ldc_w 477
    //   1110: invokevirtual 221	java/lang/StringBuilder:append	(Ljava/lang/String;)Ljava/lang/StringBuilder;
    //   1113: aload_2
    //   1114: invokevirtual 299	java/lang/StringBuilder:append	(Ljava/lang/Object;)Ljava/lang/StringBuilder;
    //   1117: ldc_w 479
    //   1120: invokevirtual 221	java/lang/StringBuilder:append	(Ljava/lang/String;)Ljava/lang/StringBuilder;
    //   1123: aload 5
    //   1125: getfield 319	com/sleepycat/b/i/c/b/ac:h	Lcom/sleepycat/b/p/au;
    //   1128: invokevirtual 299	java/lang/StringBuilder:append	(Ljava/lang/Object;)Ljava/lang/StringBuilder;
    //   1131: invokevirtual 83	java/lang/StringBuilder:toString	()Ljava/lang/String;
    //   1134: invokestatic 481	com/sleepycat/b/p/w:d	(Ljava/util/logging/Logger;Lcom/sleepycat/b/c/ad;Ljava/lang/String;)V
    //   1137: aload 4
    //   1139: invokeinterface 483 1 0
    //   1144: checkcast 485	com/sleepycat/b/n/ah
    //   1147: astore 4
    //   1149: iload 25
    //   1151: ifeq +32 -> 1183
    //   1154: aload 5
    //   1156: getfield 328	com/sleepycat/b/i/c/b/ac:d	Lcom/sleepycat/b/i/c/aj;
    //   1159: getfield 491	com/sleepycat/b/i/c/aj:am	Lcom/sleepycat/b/i/c/b/aa;
    //   1162: getfield 494	com/sleepycat/b/i/c/b/aa:l	Lcom/sleepycat/b/i/c/b/b;
    //   1165: invokevirtual 498	com/sleepycat/b/i/c/b/b:b	()Z
    //   1168: pop
    //   1169: aload 5
    //   1171: getfield 328	com/sleepycat/b/i/c/b/ac:d	Lcom/sleepycat/b/i/c/aj;
    //   1174: getfield 491	com/sleepycat/b/i/c/aj:am	Lcom/sleepycat/b/i/c/b/aa;
    //   1177: getfield 187	com/sleepycat/b/i/c/b/aa:g	Lcom/sleepycat/b/i/e/n;
    //   1180: invokevirtual 191	com/sleepycat/b/i/e/n:e	()V
    //   1183: aload 8
    //   1185: aload_2
    //   1186: new 500	com/sleepycat/b/g/av
    //   1189: dup
    //   1190: aload 5
    //   1192: getfield 319	com/sleepycat/b/i/c/b/ac:h	Lcom/sleepycat/b/p/au;
    //   1195: invokespecial 503	com/sleepycat/b/g/av:<init>	(Lcom/sleepycat/b/p/au;)V
    //   1198: aload 4
    //   1200: getfield 506	com/sleepycat/b/n/ai:c	I
    //   1203: invokevirtual 511	com/sleepycat/b/i/f/e:a	(Lcom/sleepycat/b/w;Lcom/sleepycat/b/g/av;I)J
    //   1206: pop2
    //   1207: aload 4
    //   1209: invokevirtual 514	com/sleepycat/b/n/ah:e	()Lcom/sleepycat/b/p/aq;
    //   1212: invokevirtual 519	com/sleepycat/b/p/aq:getTime	()J
    //   1215: lstore 19
    //   1217: aload 5
    //   1219: new 521	com/sleepycat/b/i/c/b/ae
    //   1222: dup
    //   1223: aload 5
    //   1225: getfield 319	com/sleepycat/b/i/c/b/ac:h	Lcom/sleepycat/b/p/au;
    //   1228: lload 19
    //   1230: iconst_0
    //   1231: invokespecial 524	com/sleepycat/b/i/c/b/ae:<init>	(Lcom/sleepycat/b/p/au;JB)V
    //   1234: putfield 527	com/sleepycat/b/i/c/b/ac:g	Lcom/sleepycat/b/i/c/b/ae;
    //   1237: aload 8
    //   1239: getfield 529	com/sleepycat/b/i/f/e:b	J
    //   1242: lstore 21
    //   1244: invokestatic 174	java/lang/System:nanoTime	()J
    //   1247: lload 17
    //   1249: lsub
    //   1250: lstore 23
    //   1252: lload 23
    //   1254: aload 5
    //   1256: getfield 530	com/sleepycat/b/i/c/b/ac:e	J
    //   1259: lcmp
    //   1260: ifle +70 -> 1330
    //   1263: aload 5
    //   1265: getfield 345	com/sleepycat/b/i/c/b/ac:C	Ljava/util/logging/Logger;
    //   1268: getstatic 533	java/util/logging/Level:INFO	Ljava/util/logging/Level;
    //   1271: invokevirtual 357	java/util/logging/Logger:isLoggable	(Ljava/util/logging/Level;)Z
    //   1274: ifeq +56 -> 1330
    //   1277: aload 5
    //   1279: getfield 345	com/sleepycat/b/i/c/b/ac:C	Ljava/util/logging/Logger;
    //   1282: aload 5
    //   1284: getfield 328	com/sleepycat/b/i/c/b/ac:d	Lcom/sleepycat/b/i/c/aj;
    //   1287: new 70	java/lang/StringBuilder
    //   1290: dup
    //   1291: ldc_w 535
    //   1294: invokespecial 75	java/lang/StringBuilder:<init>	(Ljava/lang/String;)V
    //   1297: lload 23
    //   1299: ldc2_w 536
    //   1302: ldiv
    //   1303: invokevirtual 391	java/lang/StringBuilder:append	(J)Ljava/lang/StringBuilder;
    //   1306: ldc_w 539
    //   1309: invokevirtual 221	java/lang/StringBuilder:append	(Ljava/lang/String;)Ljava/lang/StringBuilder;
    //   1312: aload 5
    //   1314: getfield 530	com/sleepycat/b/i/c/b/ac:e	J
    //   1317: ldc2_w 536
    //   1320: ldiv
    //   1321: invokevirtual 391	java/lang/StringBuilder:append	(J)Ljava/lang/StringBuilder;
    //   1324: invokevirtual 83	java/lang/StringBuilder:toString	()Ljava/lang/String;
    //   1327: invokestatic 88	com/sleepycat/b/p/w:c	(Ljava/util/logging/Logger;Lcom/sleepycat/b/c/ad;Ljava/lang/String;)V
    //   1330: aload 5
    //   1332: getfield 543	com/sleepycat/b/i/c/b/ac:o	Lcom/sleepycat/b/p/z;
    //   1335: invokevirtual 547	com/sleepycat/b/p/z:f	()V
    //   1338: iload 25
    //   1340: ifeq +11 -> 1351
    //   1343: aload 5
    //   1345: getfield 550	com/sleepycat/b/i/c/b/ac:p	Lcom/sleepycat/b/p/z;
    //   1348: invokevirtual 547	com/sleepycat/b/p/z:f	()V
    //   1351: aload_2
    //   1352: getstatic 463	com/sleepycat/b/w:a	Lcom/sleepycat/b/w;
    //   1355: if_acmpne +451 -> 1806
    //   1358: aload 5
    //   1360: getfield 552	com/sleepycat/b/i/c/b/ac:q	Lcom/sleepycat/b/p/z;
    //   1363: invokevirtual 547	com/sleepycat/b/p/z:f	()V
    //   1366: aload 5
    //   1368: getfield 555	com/sleepycat/b/i/c/b/ac:A	Lcom/sleepycat/b/p/z;
    //   1371: lload 23
    //   1373: invokevirtual 557	com/sleepycat/b/p/z:b	(J)V
    //   1376: aload 5
    //   1378: getfield 560	com/sleepycat/b/i/c/b/ac:y	Lcom/sleepycat/b/p/y;
    //   1381: lload 23
    //   1383: invokevirtual 563	com/sleepycat/b/p/y:a	(J)V
    //   1386: aload 5
    //   1388: getfield 566	com/sleepycat/b/i/c/b/ac:z	Lcom/sleepycat/b/p/x;
    //   1391: lload 23
    //   1393: invokevirtual 571	com/sleepycat/b/p/x:a	(J)Z
    //   1396: pop
    //   1397: lload 21
    //   1399: lload 19
    //   1401: lcmp
    //   1402: ifle +16 -> 1418
    //   1405: aload 5
    //   1407: getfield 573	com/sleepycat/b/i/c/b/ac:B	Lcom/sleepycat/b/p/z;
    //   1410: lload 21
    //   1412: lload 19
    //   1414: lsub
    //   1415: invokevirtual 557	com/sleepycat/b/p/z:b	(J)V
    //   1418: iload 25
    //   1420: ifeq +77 -> 1497
    //   1423: aload 5
    //   1425: getfield 140	com/sleepycat/b/i/c/b/ac:m	Lcom/sleepycat/b/i/c/b/ad;
    //   1428: astore_2
    //   1429: aload_2
    //   1430: invokevirtual 465	com/sleepycat/b/i/c/b/ad:a	()Z
    //   1433: ifeq +2080 -> 3513
    //   1436: aload_3
    //   1437: getstatic 463	com/sleepycat/b/w:a	Lcom/sleepycat/b/w;
    //   1440: if_acmpeq +423 -> 1863
    //   1443: aload_2
    //   1444: getfield 144	com/sleepycat/b/i/c/b/ad:b	I
    //   1447: ifgt +416 -> 1863
    //   1450: goto +2063 -> 3513
    //   1453: iload 13
    //   1455: ifne +42 -> 1497
    //   1458: aload 5
    //   1460: getfield 136	com/sleepycat/b/i/c/b/ac:l	Lcom/sleepycat/b/i/e/t;
    //   1463: astore_2
    //   1464: aload 5
    //   1466: getfield 136	com/sleepycat/b/i/c/b/ac:l	Lcom/sleepycat/b/i/e/t;
    //   1469: astore_3
    //   1470: aload_3
    //   1471: invokevirtual 579	java/lang/Object:getClass	()Ljava/lang/Class;
    //   1474: pop
    //   1475: aload_2
    //   1476: new 581	com/sleepycat/b/i/e/u
    //   1479: dup
    //   1480: aload_3
    //   1481: aload 8
    //   1483: getfield 475	com/sleepycat/b/n/q:k	J
    //   1486: invokespecial 584	com/sleepycat/b/i/e/u:<init>	(Lcom/sleepycat/b/i/e/t;J)V
    //   1489: aload 5
    //   1491: getfield 132	com/sleepycat/b/i/c/b/ac:k	Lcom/sleepycat/b/i/h/o;
    //   1494: invokevirtual 587	com/sleepycat/b/i/e/t:a	(Lcom/sleepycat/b/i/h/d;Lcom/sleepycat/b/i/h/o;)V
    //   1497: aload 8
    //   1499: getfield 589	com/sleepycat/b/i/f/e:d	Z
    //   1502: ifeq +36 -> 1538
    //   1505: aload 5
    //   1507: aload 8
    //   1509: invokevirtual 592	com/sleepycat/b/i/c/b/ac:a	(Lcom/sleepycat/b/i/f/e;)Z
    //   1512: ifeq +26 -> 1538
    //   1515: aload 5
    //   1517: getfield 328	com/sleepycat/b/i/c/b/ac:d	Lcom/sleepycat/b/i/c/aj;
    //   1520: getfield 491	com/sleepycat/b/i/c/aj:am	Lcom/sleepycat/b/i/c/b/aa;
    //   1523: invokevirtual 595	com/sleepycat/b/i/c/b/aa:h	()Lcom/sleepycat/b/i/c/t;
    //   1526: pop
    //   1527: aload 5
    //   1529: getfield 328	com/sleepycat/b/i/c/b/ac:d	Lcom/sleepycat/b/i/c/aj;
    //   1532: getfield 491	com/sleepycat/b/i/c/aj:am	Lcom/sleepycat/b/i/c/b/aa;
    //   1535: invokevirtual 597	com/sleepycat/b/i/c/b/aa:j	()V
    //   1538: aload 5
    //   1540: getfield 599	com/sleepycat/b/i/c/b/ac:w	Lcom/sleepycat/b/p/z;
    //   1543: aload 8
    //   1545: invokevirtual 602	com/sleepycat/b/i/f/e:g_	()J
    //   1548: invokevirtual 557	com/sleepycat/b/p/z:b	(J)V
    //   1551: aload 5
    //   1553: getfield 319	com/sleepycat/b/i/c/b/ac:h	Lcom/sleepycat/b/p/au;
    //   1556: astore_2
    //   1557: aload_2
    //   1558: aload 8
    //   1560: getfield 604	com/sleepycat/b/i/f/e:c	Lcom/sleepycat/b/p/au;
    //   1563: invokevirtual 607	com/sleepycat/b/p/au:b	(Lcom/sleepycat/b/p/au;)I
    //   1566: ifgt +1716 -> 3282
    //   1569: new 70	java/lang/StringBuilder
    //   1572: dup
    //   1573: ldc_w 609
    //   1576: invokespecial 75	java/lang/StringBuilder:<init>	(Ljava/lang/String;)V
    //   1579: aload 8
    //   1581: getfield 475	com/sleepycat/b/n/q:k	J
    //   1584: invokevirtual 391	java/lang/StringBuilder:append	(J)Ljava/lang/StringBuilder;
    //   1587: ldc_w 611
    //   1590: invokevirtual 221	java/lang/StringBuilder:append	(Ljava/lang/String;)Ljava/lang/StringBuilder;
    //   1593: aload_2
    //   1594: invokevirtual 299	java/lang/StringBuilder:append	(Ljava/lang/Object;)Ljava/lang/StringBuilder;
    //   1597: ldc_w 613
    //   1600: invokevirtual 221	java/lang/StringBuilder:append	(Ljava/lang/String;)Ljava/lang/StringBuilder;
    //   1603: aload 8
    //   1605: getfield 604	com/sleepycat/b/i/f/e:c	Lcom/sleepycat/b/p/au;
    //   1608: invokevirtual 299	java/lang/StringBuilder:append	(Ljava/lang/Object;)Ljava/lang/StringBuilder;
    //   1611: invokevirtual 83	java/lang/StringBuilder:toString	()Ljava/lang/String;
    //   1614: invokestatic 440	com/sleepycat/b/aa:c	(Ljava/lang/String;)Lcom/sleepycat/b/aa;
    //   1617: athrow
    //   1618: astore_2
    //   1619: aload_2
    //   1620: new 70	java/lang/StringBuilder
    //   1623: dup
    //   1624: ldc_w 615
    //   1627: invokespecial 75	java/lang/StringBuilder:<init>	(Ljava/lang/String;)V
    //   1630: aload 6
    //   1632: invokevirtual 299	java/lang/StringBuilder:append	(Ljava/lang/Object;)Ljava/lang/StringBuilder;
    //   1635: invokevirtual 83	java/lang/StringBuilder:toString	()Ljava/lang/String;
    //   1638: invokevirtual 617	com/sleepycat/b/n:a	(Ljava/lang/String;)V
    //   1641: aload_2
    //   1642: athrow
    //   1643: astore_2
    //   1644: invokestatic 174	java/lang/System:nanoTime	()J
    //   1647: lload 17
    //   1649: lsub
    //   1650: lstore 15
    //   1652: lload 15
    //   1654: aload 5
    //   1656: getfield 619	com/sleepycat/b/i/c/b/ac:j	J
    //   1659: lcmp
    //   1660: ifle +79 -> 1739
    //   1663: aload 5
    //   1665: getfield 345	com/sleepycat/b/i/c/b/ac:C	Ljava/util/logging/Logger;
    //   1668: aload 5
    //   1670: getfield 328	com/sleepycat/b/i/c/b/ac:d	Lcom/sleepycat/b/i/c/aj;
    //   1673: new 70	java/lang/StringBuilder
    //   1676: dup
    //   1677: ldc_w 621
    //   1680: invokespecial 75	java/lang/StringBuilder:<init>	(Ljava/lang/String;)V
    //   1683: iload_1
    //   1684: invokestatic 624	com/sleepycat/b/g/af:a	(B)Lcom/sleepycat/b/g/af;
    //   1687: invokevirtual 299	java/lang/StringBuilder:append	(Ljava/lang/Object;)Ljava/lang/StringBuilder;
    //   1690: ldc_w 626
    //   1693: invokevirtual 221	java/lang/StringBuilder:append	(Ljava/lang/String;)Ljava/lang/StringBuilder;
    //   1696: getstatic 152	java/util/concurrent/TimeUnit:NANOSECONDS	Ljava/util/concurrent/TimeUnit;
    //   1699: lload 15
    //   1701: invokevirtual 630	java/util/concurrent/TimeUnit:toMillis	(J)J
    //   1704: invokevirtual 391	java/lang/StringBuilder:append	(J)Ljava/lang/StringBuilder;
    //   1707: ldc_w 632
    //   1710: invokevirtual 221	java/lang/StringBuilder:append	(Ljava/lang/String;)Ljava/lang/StringBuilder;
    //   1713: getstatic 152	java/util/concurrent/TimeUnit:NANOSECONDS	Ljava/util/concurrent/TimeUnit;
    //   1716: aload 5
    //   1718: getfield 619	com/sleepycat/b/i/c/b/ac:j	J
    //   1721: invokevirtual 630	java/util/concurrent/TimeUnit:toMillis	(J)J
    //   1724: invokevirtual 391	java/lang/StringBuilder:append	(J)Ljava/lang/StringBuilder;
    //   1727: ldc_w 634
    //   1730: invokevirtual 221	java/lang/StringBuilder:append	(Ljava/lang/String;)Ljava/lang/StringBuilder;
    //   1733: invokevirtual 83	java/lang/StringBuilder:toString	()Ljava/lang/String;
    //   1736: invokestatic 88	com/sleepycat/b/p/w:c	(Ljava/util/logging/Logger;Lcom/sleepycat/b/c/ad;Ljava/lang/String;)V
    //   1739: aload_2
    //   1740: athrow
    //   1741: aload_3
    //   1742: astore_2
    //   1743: goto -683 -> 1060
    //   1746: aload 5
    //   1748: getfield 636	com/sleepycat/b/i/c/b/ac:i	Lcom/sleepycat/b/w;
    //   1751: astore_2
    //   1752: goto -692 -> 1060
    //   1755: aload 5
    //   1757: getfield 345	com/sleepycat/b/i/c/b/ac:C	Ljava/util/logging/Logger;
    //   1760: aload 5
    //   1762: getfield 328	com/sleepycat/b/i/c/b/ac:d	Lcom/sleepycat/b/i/c/aj;
    //   1765: new 70	java/lang/StringBuilder
    //   1768: dup
    //   1769: ldc_w 471
    //   1772: invokespecial 75	java/lang/StringBuilder:<init>	(Ljava/lang/String;)V
    //   1775: aload 8
    //   1777: getfield 475	com/sleepycat/b/n/q:k	J
    //   1780: invokevirtual 391	java/lang/StringBuilder:append	(J)Ljava/lang/StringBuilder;
    //   1783: ldc_w 638
    //   1786: invokevirtual 221	java/lang/StringBuilder:append	(Ljava/lang/String;)Ljava/lang/StringBuilder;
    //   1789: aload 5
    //   1791: getfield 319	com/sleepycat/b/i/c/b/ac:h	Lcom/sleepycat/b/p/au;
    //   1794: invokevirtual 299	java/lang/StringBuilder:append	(Ljava/lang/Object;)Ljava/lang/StringBuilder;
    //   1797: invokevirtual 83	java/lang/StringBuilder:toString	()Ljava/lang/String;
    //   1800: invokestatic 481	com/sleepycat/b/p/w:d	(Ljava/util/logging/Logger;Lcom/sleepycat/b/c/ad;Ljava/lang/String;)V
    //   1803: goto -666 -> 1137
    //   1806: aload_2
    //   1807: getstatic 466	com/sleepycat/b/w:b	Lcom/sleepycat/b/w;
    //   1810: if_acmpne +14 -> 1824
    //   1813: aload 5
    //   1815: getfield 641	com/sleepycat/b/i/c/b/ac:r	Lcom/sleepycat/b/p/z;
    //   1818: invokevirtual 547	com/sleepycat/b/p/z:f	()V
    //   1821: goto -455 -> 1366
    //   1824: aload_2
    //   1825: getstatic 643	com/sleepycat/b/w:c	Lcom/sleepycat/b/w;
    //   1828: if_acmpne +14 -> 1842
    //   1831: aload 5
    //   1833: getfield 646	com/sleepycat/b/i/c/b/ac:s	Lcom/sleepycat/b/p/z;
    //   1836: invokevirtual 547	com/sleepycat/b/p/z:f	()V
    //   1839: goto -473 -> 1366
    //   1842: new 70	java/lang/StringBuilder
    //   1845: dup
    //   1846: ldc_w 648
    //   1849: invokespecial 75	java/lang/StringBuilder:<init>	(Ljava/lang/String;)V
    //   1852: aload_2
    //   1853: invokevirtual 299	java/lang/StringBuilder:append	(Ljava/lang/Object;)Ljava/lang/StringBuilder;
    //   1856: invokevirtual 83	java/lang/StringBuilder:toString	()Ljava/lang/String;
    //   1859: invokestatic 440	com/sleepycat/b/aa:c	(Ljava/lang/String;)Lcom/sleepycat/b/aa;
    //   1862: athrow
    //   1863: aload_2
    //   1864: getfield 651	com/sleepycat/b/i/c/b/ad:a	[J
    //   1867: astore_3
    //   1868: aload_2
    //   1869: getfield 144	com/sleepycat/b/i/c/b/ad:b	I
    //   1872: istore 13
    //   1874: aload_2
    //   1875: iload 13
    //   1877: iconst_1
    //   1878: iadd
    //   1879: putfield 144	com/sleepycat/b/i/c/b/ad:b	I
    //   1882: aload_3
    //   1883: iload 13
    //   1885: aload 8
    //   1887: getfield 475	com/sleepycat/b/n/q:k	J
    //   1890: lastore
    //   1891: aload_2
    //   1892: getfield 144	com/sleepycat/b/i/c/b/ad:b	I
    //   1895: iconst_1
    //   1896: if_icmpne +17 -> 1913
    //   1899: aload_2
    //   1900: aload_2
    //   1901: getfield 653	com/sleepycat/b/i/c/b/ad:d	J
    //   1904: lload 17
    //   1906: ladd
    //   1907: putfield 177	com/sleepycat/b/i/c/b/ad:c	J
    //   1910: goto +1609 -> 3519
    //   1913: aload_2
    //   1914: lload 17
    //   1916: invokevirtual 654	com/sleepycat/b/i/c/b/ad:a	(J)V
    //   1919: goto +1600 -> 3519
    //   1922: getstatic 656	com/sleepycat/b/g/af:r	Lcom/sleepycat/b/g/af;
    //   1925: iload_1
    //   1926: invokevirtual 452	com/sleepycat/b/g/af:c	(B)Z
    //   1929: ifeq +191 -> 2120
    //   1932: aload 5
    //   1934: getfield 659	com/sleepycat/b/i/c/b/ac:t	Lcom/sleepycat/b/p/z;
    //   1937: invokevirtual 547	com/sleepycat/b/p/z:f	()V
    //   1940: aload 4
    //   1942: invokeinterface 483 1 0
    //   1947: checkcast 661	com/sleepycat/b/n/ac
    //   1950: astore_2
    //   1951: new 500	com/sleepycat/b/g/av
    //   1954: dup
    //   1955: aload 6
    //   1957: getfield 312	com/sleepycat/b/i/e/k:d	Lcom/sleepycat/b/g/ae;
    //   1960: getfield 317	com/sleepycat/b/g/ae:e	Lcom/sleepycat/b/p/au;
    //   1963: invokespecial 503	com/sleepycat/b/g/av:<init>	(Lcom/sleepycat/b/p/au;)V
    //   1966: astore_3
    //   1967: aload 5
    //   1969: getfield 345	com/sleepycat/b/i/c/b/ac:C	Ljava/util/logging/Logger;
    //   1972: getstatic 351	java/util/logging/Level:FINEST	Ljava/util/logging/Level;
    //   1975: invokevirtual 357	java/util/logging/Logger:isLoggable	(Ljava/util/logging/Level;)Z
    //   1978: ifeq +60 -> 2038
    //   1981: aload 5
    //   1983: getfield 345	com/sleepycat/b/i/c/b/ac:C	Ljava/util/logging/Logger;
    //   1986: aload 5
    //   1988: getfield 328	com/sleepycat/b/i/c/b/ac:d	Lcom/sleepycat/b/i/c/aj;
    //   1991: new 70	java/lang/StringBuilder
    //   1994: dup
    //   1995: ldc_w 663
    //   1998: invokespecial 75	java/lang/StringBuilder:<init>	(Ljava/lang/String;)V
    //   2001: aload 8
    //   2003: getfield 475	com/sleepycat/b/n/q:k	J
    //   2006: invokevirtual 391	java/lang/StringBuilder:append	(J)Ljava/lang/StringBuilder;
    //   2009: ldc_w 665
    //   2012: invokevirtual 221	java/lang/StringBuilder:append	(Ljava/lang/String;)Ljava/lang/StringBuilder;
    //   2015: aload_2
    //   2016: getfield 506	com/sleepycat/b/n/ai:c	I
    //   2019: invokevirtual 79	java/lang/StringBuilder:append	(I)Ljava/lang/StringBuilder;
    //   2022: ldc_w 667
    //   2025: invokevirtual 221	java/lang/StringBuilder:append	(Ljava/lang/String;)Ljava/lang/StringBuilder;
    //   2028: aload_3
    //   2029: invokevirtual 299	java/lang/StringBuilder:append	(Ljava/lang/Object;)Ljava/lang/StringBuilder;
    //   2032: invokevirtual 83	java/lang/StringBuilder:toString	()Ljava/lang/String;
    //   2035: invokestatic 361	com/sleepycat/b/p/w:e	(Ljava/util/logging/Logger;Lcom/sleepycat/b/c/ad;Ljava/lang/String;)V
    //   2038: aload 8
    //   2040: aload_3
    //   2041: aload_2
    //   2042: getfield 506	com/sleepycat/b/n/ai:c	I
    //   2045: invokevirtual 670	com/sleepycat/b/i/f/e:a	(Lcom/sleepycat/b/g/av;I)J
    //   2048: pop2
    //   2049: aload 5
    //   2051: new 521	com/sleepycat/b/i/c/b/ae
    //   2054: dup
    //   2055: aload 5
    //   2057: getfield 319	com/sleepycat/b/i/c/b/ac:h	Lcom/sleepycat/b/p/au;
    //   2060: aload_2
    //   2061: invokevirtual 671	com/sleepycat/b/n/ac:e	()Lcom/sleepycat/b/p/aq;
    //   2064: invokevirtual 519	com/sleepycat/b/p/aq:getTime	()J
    //   2067: iconst_0
    //   2068: invokespecial 524	com/sleepycat/b/i/c/b/ae:<init>	(Lcom/sleepycat/b/p/au;JB)V
    //   2071: putfield 527	com/sleepycat/b/i/c/b/ac:g	Lcom/sleepycat/b/i/c/b/ae;
    //   2074: aload 8
    //   2076: getfield 589	com/sleepycat/b/i/f/e:d	Z
    //   2079: ifeq +25 -> 2104
    //   2082: aload 5
    //   2084: aload 8
    //   2086: invokevirtual 592	com/sleepycat/b/i/c/b/ac:a	(Lcom/sleepycat/b/i/f/e;)Z
    //   2089: ifeq +15 -> 2104
    //   2092: aload 5
    //   2094: getfield 328	com/sleepycat/b/i/c/b/ac:d	Lcom/sleepycat/b/i/c/aj;
    //   2097: getfield 491	com/sleepycat/b/i/c/aj:am	Lcom/sleepycat/b/i/c/b/aa;
    //   2100: invokevirtual 595	com/sleepycat/b/i/c/b/aa:h	()Lcom/sleepycat/b/i/c/t;
    //   2103: pop
    //   2104: aload 5
    //   2106: getfield 599	com/sleepycat/b/i/c/b/ac:w	Lcom/sleepycat/b/p/z;
    //   2109: aload 8
    //   2111: invokevirtual 602	com/sleepycat/b/i/f/e:g_	()J
    //   2114: invokevirtual 557	com/sleepycat/b/p/z:b	(J)V
    //   2117: goto -566 -> 1551
    //   2120: getstatic 673	com/sleepycat/b/g/af:e	Lcom/sleepycat/b/g/af;
    //   2123: iload_1
    //   2124: invokevirtual 452	com/sleepycat/b/g/af:c	(B)Z
    //   2127: ifeq +767 -> 2894
    //   2130: aload 5
    //   2132: getfield 328	com/sleepycat/b/i/c/b/ac:d	Lcom/sleepycat/b/i/c/aj;
    //   2135: getfield 491	com/sleepycat/b/i/c/aj:am	Lcom/sleepycat/b/i/c/b/aa;
    //   2138: getfield 675	com/sleepycat/b/i/c/b/aa:e	Lcom/sleepycat/b/i/c/b/ag;
    //   2141: invokevirtual 290	com/sleepycat/b/i/c/b/ag:c	()V
    //   2144: aload 5
    //   2146: getfield 677	com/sleepycat/b/i/c/b/ac:u	Lcom/sleepycat/b/p/z;
    //   2149: invokevirtual 547	com/sleepycat/b/p/z:f	()V
    //   2152: aload 6
    //   2154: getfield 309	com/sleepycat/b/i/e/k:a	Lcom/sleepycat/b/g/a/m;
    //   2157: checkcast 407	com/sleepycat/b/g/a/o
    //   2160: astore_2
    //   2161: aload_2
    //   2162: invokevirtual 413	com/sleepycat/b/g/a/o:j	()Lcom/sleepycat/b/l/y;
    //   2165: checkcast 415	com/sleepycat/b/l/ab
    //   2168: astore 9
    //   2170: aload_2
    //   2171: invokevirtual 680	com/sleepycat/b/g/a/o:k	()[B
    //   2174: invokestatic 685	com/sleepycat/d/b:a	([B)Ljava/lang/String;
    //   2177: astore 10
    //   2179: new 687	com/sleepycat/b/g/g
    //   2182: dup
    //   2183: aload 6
    //   2185: getfield 312	com/sleepycat/b/i/e/k:d	Lcom/sleepycat/b/g/ae;
    //   2188: getfield 317	com/sleepycat/b/g/ae:e	Lcom/sleepycat/b/p/au;
    //   2191: aload_2
    //   2192: invokespecial 690	com/sleepycat/b/g/g:<init>	(Lcom/sleepycat/b/p/au;Lcom/sleepycat/b/g/a/o;)V
    //   2195: astore 11
    //   2197: aload 11
    //   2199: getfield 693	com/sleepycat/b/g/g:b	Lcom/sleepycat/b/g/a/f;
    //   2202: astore_2
    //   2203: getstatic 698	com/sleepycat/b/i/c/b/ac$2:a	[I
    //   2206: aload_2
    //   2207: invokevirtual 703	com/sleepycat/b/g/a/f:ordinal	()I
    //   2210: iaload
    //   2211: tableswitch	default:+1314->3525, 1:+100->2311, 2:+248->2459, 3:+377->2588, 4:+475->2686, 5:+600->2811
    //   2244: new 70	java/lang/StringBuilder
    //   2247: dup
    //   2248: ldc_w 705
    //   2251: invokespecial 75	java/lang/StringBuilder:<init>	(Ljava/lang/String;)V
    //   2254: aload_2
    //   2255: invokevirtual 706	com/sleepycat/b/g/a/f:toString	()Ljava/lang/String;
    //   2258: invokevirtual 221	java/lang/StringBuilder:append	(Ljava/lang/String;)Ljava/lang/StringBuilder;
    //   2261: ldc_w 708
    //   2264: invokevirtual 221	java/lang/StringBuilder:append	(Ljava/lang/String;)Ljava/lang/StringBuilder;
    //   2267: aload 6
    //   2269: invokevirtual 299	java/lang/StringBuilder:append	(Ljava/lang/Object;)Ljava/lang/StringBuilder;
    //   2272: ldc_w 710
    //   2275: invokevirtual 221	java/lang/StringBuilder:append	(Ljava/lang/String;)Ljava/lang/StringBuilder;
    //   2278: aload 10
    //   2280: invokevirtual 221	java/lang/StringBuilder:append	(Ljava/lang/String;)Ljava/lang/StringBuilder;
    //   2283: invokevirtual 83	java/lang/StringBuilder:toString	()Ljava/lang/String;
    //   2286: invokestatic 440	com/sleepycat/b/aa:c	(Ljava/lang/String;)Lcom/sleepycat/b/aa;
    //   2289: athrow
    //   2290: astore_2
    //   2291: aconst_null
    //   2292: astore_3
    //   2293: aload_3
    //   2294: ifnull +15 -> 2309
    //   2297: aload 5
    //   2299: getfield 328	com/sleepycat/b/i/c/b/ac:d	Lcom/sleepycat/b/i/c/aj;
    //   2302: getfield 419	com/sleepycat/b/c/ad:q	Lcom/sleepycat/b/c/p;
    //   2305: aload_3
    //   2306: invokevirtual 712	com/sleepycat/b/c/p:c	(Lcom/sleepycat/b/c/i;)V
    //   2309: aload_2
    //   2310: athrow
    //   2311: aload 11
    //   2313: invokevirtual 715	com/sleepycat/b/g/g:b	()Lcom/sleepycat/b/c/ax;
    //   2316: aload 5
    //   2318: getfield 328	com/sleepycat/b/i/c/b/ac:d	Lcom/sleepycat/b/i/c/aj;
    //   2321: invokevirtual 720	com/sleepycat/b/c/ax:a	(Lcom/sleepycat/b/c/ad;)Lcom/sleepycat/b/l;
    //   2324: astore_2
    //   2325: aload 5
    //   2327: getfield 328	com/sleepycat/b/i/c/b/ac:d	Lcom/sleepycat/b/i/c/aj;
    //   2330: getfield 419	com/sleepycat/b/c/ad:q	Lcom/sleepycat/b/c/p;
    //   2333: aload 8
    //   2335: aload 10
    //   2337: aload_2
    //   2338: aconst_null
    //   2339: aload 9
    //   2341: aload 11
    //   2343: invokevirtual 723	com/sleepycat/b/c/p:a	(Lcom/sleepycat/b/n/q;Ljava/lang/String;Lcom/sleepycat/b/l;Lcom/sleepycat/b/n/d;Lcom/sleepycat/b/l/ab;Lcom/sleepycat/b/g/av;)Lcom/sleepycat/b/c/i;
    //   2346: astore_3
    //   2347: aload_3
    //   2348: astore_2
    //   2349: aload_3
    //   2350: getfield 726	com/sleepycat/b/c/i:a	Lcom/sleepycat/b/c/h;
    //   2353: getfield 432	com/sleepycat/b/c/h:a	J
    //   2356: ldc2_w 727
    //   2359: lcmp
    //   2360: ifne +69 -> 2429
    //   2363: aload_3
    //   2364: astore_2
    //   2365: getstatic 733	com/sleepycat/b/c/w:d	Lcom/sleepycat/b/c/w;
    //   2368: invokevirtual 735	com/sleepycat/b/c/w:b	()Ljava/lang/String;
    //   2371: aload 10
    //   2373: invokevirtual 741	java/lang/String:equals	(Ljava/lang/Object;)Z
    //   2376: ifne +53 -> 2429
    //   2379: aload_3
    //   2380: astore_2
    //   2381: new 70	java/lang/StringBuilder
    //   2384: dup
    //   2385: ldc_w 743
    //   2388: invokespecial 75	java/lang/StringBuilder:<init>	(Ljava/lang/String;)V
    //   2391: getstatic 733	com/sleepycat/b/c/w:d	Lcom/sleepycat/b/c/w;
    //   2394: invokevirtual 735	com/sleepycat/b/c/w:b	()Ljava/lang/String;
    //   2397: invokevirtual 221	java/lang/StringBuilder:append	(Ljava/lang/String;)Ljava/lang/StringBuilder;
    //   2400: ldc_w 745
    //   2403: invokevirtual 221	java/lang/StringBuilder:append	(Ljava/lang/String;)Ljava/lang/StringBuilder;
    //   2406: aload_3
    //   2407: getfield 726	com/sleepycat/b/c/i:a	Lcom/sleepycat/b/c/h;
    //   2410: getfield 432	com/sleepycat/b/c/h:a	J
    //   2413: invokevirtual 391	java/lang/StringBuilder:append	(J)Ljava/lang/StringBuilder;
    //   2416: ldc_w 747
    //   2419: invokevirtual 221	java/lang/StringBuilder:append	(Ljava/lang/String;)Ljava/lang/StringBuilder;
    //   2422: invokevirtual 83	java/lang/StringBuilder:toString	()Ljava/lang/String;
    //   2425: invokestatic 440	com/sleepycat/b/aa:c	(Ljava/lang/String;)Lcom/sleepycat/b/aa;
    //   2428: athrow
    //   2429: aload_3
    //   2430: astore_2
    //   2431: aload 8
    //   2433: aload_3
    //   2434: iconst_1
    //   2435: invokestatic 752	com/sleepycat/b/c/bh:a	(Lcom/sleepycat/b/n/q;Lcom/sleepycat/b/c/i;Z)V
    //   2438: aload_3
    //   2439: astore_2
    //   2440: aload_2
    //   2441: ifnull -890 -> 1551
    //   2444: aload 5
    //   2446: getfield 328	com/sleepycat/b/i/c/b/ac:d	Lcom/sleepycat/b/i/c/aj;
    //   2449: getfield 419	com/sleepycat/b/c/ad:q	Lcom/sleepycat/b/c/p;
    //   2452: aload_2
    //   2453: invokevirtual 712	com/sleepycat/b/c/p:c	(Lcom/sleepycat/b/c/i;)V
    //   2456: goto -905 -> 1551
    //   2459: aload 5
    //   2461: getfield 328	com/sleepycat/b/i/c/b/ac:d	Lcom/sleepycat/b/i/c/aj;
    //   2464: getfield 419	com/sleepycat/b/c/ad:q	Lcom/sleepycat/b/c/p;
    //   2467: aload 9
    //   2469: getfield 422	com/sleepycat/b/l/ab:a	Lcom/sleepycat/b/c/h;
    //   2472: invokevirtual 755	com/sleepycat/b/c/p:b	(Lcom/sleepycat/b/c/h;)Lcom/sleepycat/b/c/i;
    //   2475: astore_3
    //   2476: aload_3
    //   2477: astore_2
    //   2478: aload 5
    //   2480: getfield 328	com/sleepycat/b/i/c/b/ac:d	Lcom/sleepycat/b/i/c/aj;
    //   2483: getfield 419	com/sleepycat/b/c/ad:q	Lcom/sleepycat/b/c/p;
    //   2486: astore 4
    //   2488: aload_3
    //   2489: astore_2
    //   2490: aload 9
    //   2492: getfield 422	com/sleepycat/b/l/ab:a	Lcom/sleepycat/b/c/h;
    //   2495: astore 12
    //   2497: aload_3
    //   2498: astore_2
    //   2499: aload 4
    //   2501: aload 8
    //   2503: aload 10
    //   2505: aload 12
    //   2507: aload 11
    //   2509: invokevirtual 758	com/sleepycat/b/c/p:a	(Lcom/sleepycat/b/n/q;Ljava/lang/String;Lcom/sleepycat/b/c/h;Lcom/sleepycat/b/g/g;)Lcom/sleepycat/b/c/i;
    //   2512: pop
    //   2513: aload_3
    //   2514: astore_2
    //   2515: aload 8
    //   2517: aload_3
    //   2518: invokestatic 761	com/sleepycat/b/c/bh:b	(Lcom/sleepycat/b/n/q;Lcom/sleepycat/b/c/i;)V
    //   2521: aload_3
    //   2522: astore_2
    //   2523: goto -83 -> 2440
    //   2526: astore_2
    //   2527: aload_3
    //   2528: astore_2
    //   2529: new 70	java/lang/StringBuilder
    //   2532: dup
    //   2533: ldc_w 743
    //   2536: invokespecial 75	java/lang/StringBuilder:<init>	(Ljava/lang/String;)V
    //   2539: aload_3
    //   2540: invokevirtual 764	com/sleepycat/b/c/i:x	()Ljava/lang/String;
    //   2543: invokevirtual 221	java/lang/StringBuilder:append	(Ljava/lang/String;)Ljava/lang/StringBuilder;
    //   2546: ldc_w 766
    //   2549: invokevirtual 221	java/lang/StringBuilder:append	(Ljava/lang/String;)Ljava/lang/StringBuilder;
    //   2552: aload 9
    //   2554: getfield 422	com/sleepycat/b/l/ab:a	Lcom/sleepycat/b/c/h;
    //   2557: invokevirtual 299	java/lang/StringBuilder:append	(Ljava/lang/Object;)Ljava/lang/StringBuilder;
    //   2560: ldc_w 768
    //   2563: invokevirtual 221	java/lang/StringBuilder:append	(Ljava/lang/String;)Ljava/lang/StringBuilder;
    //   2566: invokevirtual 83	java/lang/StringBuilder:toString	()Ljava/lang/String;
    //   2569: invokestatic 440	com/sleepycat/b/aa:c	(Ljava/lang/String;)Lcom/sleepycat/b/aa;
    //   2572: athrow
    //   2573: astore 7
    //   2575: aload_3
    //   2576: astore_2
    //   2577: aload 4
    //   2579: getfield 428	com/sleepycat/b/c/p:h	Lcom/sleepycat/b/c/ad;
    //   2582: aload 7
    //   2584: invokestatic 771	com/sleepycat/b/aa:a	(Lcom/sleepycat/b/c/ad;Ljava/lang/Exception;)Lcom/sleepycat/b/aa;
    //   2587: athrow
    //   2588: aload 5
    //   2590: getfield 328	com/sleepycat/b/i/c/b/ac:d	Lcom/sleepycat/b/i/c/aj;
    //   2593: getfield 419	com/sleepycat/b/c/ad:q	Lcom/sleepycat/b/c/p;
    //   2596: aload 11
    //   2598: invokevirtual 774	com/sleepycat/b/g/g:c	()Lcom/sleepycat/b/c/h;
    //   2601: invokevirtual 755	com/sleepycat/b/c/p:b	(Lcom/sleepycat/b/c/h;)Lcom/sleepycat/b/c/i;
    //   2604: astore_3
    //   2605: aload_3
    //   2606: astore_2
    //   2607: aload 8
    //   2609: aload 5
    //   2611: getfield 328	com/sleepycat/b/i/c/b/ac:d	Lcom/sleepycat/b/i/c/aj;
    //   2614: getfield 419	com/sleepycat/b/c/ad:q	Lcom/sleepycat/b/c/p;
    //   2617: aload 8
    //   2619: aload 10
    //   2621: aload 9
    //   2623: aload 11
    //   2625: invokevirtual 777	com/sleepycat/b/c/p:a	(Lcom/sleepycat/b/n/q;Ljava/lang/String;Lcom/sleepycat/b/l/ab;Lcom/sleepycat/b/g/g;)Lcom/sleepycat/b/c/v;
    //   2628: getfield 780	com/sleepycat/b/c/v:b	Lcom/sleepycat/b/c/i;
    //   2631: invokestatic 782	com/sleepycat/b/c/bh:c	(Lcom/sleepycat/b/n/q;Lcom/sleepycat/b/c/i;)V
    //   2634: aload_3
    //   2635: astore_2
    //   2636: goto -196 -> 2440
    //   2639: astore_2
    //   2640: aload_3
    //   2641: astore_2
    //   2642: new 70	java/lang/StringBuilder
    //   2645: dup
    //   2646: ldc_w 743
    //   2649: invokespecial 75	java/lang/StringBuilder:<init>	(Ljava/lang/String;)V
    //   2652: aload_3
    //   2653: invokevirtual 764	com/sleepycat/b/c/i:x	()Ljava/lang/String;
    //   2656: invokevirtual 221	java/lang/StringBuilder:append	(Ljava/lang/String;)Ljava/lang/StringBuilder;
    //   2659: ldc_w 766
    //   2662: invokevirtual 221	java/lang/StringBuilder:append	(Ljava/lang/String;)Ljava/lang/StringBuilder;
    //   2665: aload 9
    //   2667: getfield 422	com/sleepycat/b/l/ab:a	Lcom/sleepycat/b/c/h;
    //   2670: invokevirtual 299	java/lang/StringBuilder:append	(Ljava/lang/Object;)Ljava/lang/StringBuilder;
    //   2673: ldc_w 768
    //   2676: invokevirtual 221	java/lang/StringBuilder:append	(Ljava/lang/String;)Ljava/lang/StringBuilder;
    //   2679: invokevirtual 83	java/lang/StringBuilder:toString	()Ljava/lang/String;
    //   2682: invokestatic 440	com/sleepycat/b/aa:c	(Ljava/lang/String;)Lcom/sleepycat/b/aa;
    //   2685: athrow
    //   2686: aload 5
    //   2688: getfield 328	com/sleepycat/b/i/c/b/ac:d	Lcom/sleepycat/b/i/c/aj;
    //   2691: getfield 419	com/sleepycat/b/c/ad:q	Lcom/sleepycat/b/c/p;
    //   2694: aload 9
    //   2696: getfield 422	com/sleepycat/b/l/ab:a	Lcom/sleepycat/b/c/h;
    //   2699: invokevirtual 755	com/sleepycat/b/c/p:b	(Lcom/sleepycat/b/c/h;)Lcom/sleepycat/b/c/i;
    //   2702: astore 4
    //   2704: aload 4
    //   2706: astore_3
    //   2707: aload 4
    //   2709: astore_2
    //   2710: aload 5
    //   2712: getfield 328	com/sleepycat/b/i/c/b/ac:d	Lcom/sleepycat/b/i/c/aj;
    //   2715: getfield 419	com/sleepycat/b/c/ad:q	Lcom/sleepycat/b/c/p;
    //   2718: aload 8
    //   2720: aload 4
    //   2722: invokevirtual 764	com/sleepycat/b/c/i:x	()Ljava/lang/String;
    //   2725: aload 10
    //   2727: aload 9
    //   2729: aload 11
    //   2731: invokevirtual 785	com/sleepycat/b/c/p:a	(Lcom/sleepycat/b/n/q;Ljava/lang/String;Ljava/lang/String;Lcom/sleepycat/b/l/ab;Lcom/sleepycat/b/g/g;)Lcom/sleepycat/b/c/i;
    //   2734: astore 4
    //   2736: aload 4
    //   2738: astore_3
    //   2739: aload 4
    //   2741: astore_2
    //   2742: aload 8
    //   2744: aload 4
    //   2746: aload 10
    //   2748: invokestatic 788	com/sleepycat/b/c/bh:a	(Lcom/sleepycat/b/n/q;Lcom/sleepycat/b/c/i;Ljava/lang/String;)V
    //   2751: aload 4
    //   2753: astore_2
    //   2754: goto -314 -> 2440
    //   2757: astore_2
    //   2758: aload_3
    //   2759: astore_2
    //   2760: new 70	java/lang/StringBuilder
    //   2763: dup
    //   2764: ldc_w 790
    //   2767: invokespecial 75	java/lang/StringBuilder:<init>	(Ljava/lang/String;)V
    //   2770: aload_3
    //   2771: invokevirtual 764	com/sleepycat/b/c/i:x	()Ljava/lang/String;
    //   2774: invokevirtual 221	java/lang/StringBuilder:append	(Ljava/lang/String;)Ljava/lang/StringBuilder;
    //   2777: ldc_w 792
    //   2780: invokevirtual 221	java/lang/StringBuilder:append	(Ljava/lang/String;)Ljava/lang/StringBuilder;
    //   2783: aload 10
    //   2785: invokevirtual 221	java/lang/StringBuilder:append	(Ljava/lang/String;)Ljava/lang/StringBuilder;
    //   2788: ldc_w 794
    //   2791: invokevirtual 221	java/lang/StringBuilder:append	(Ljava/lang/String;)Ljava/lang/StringBuilder;
    //   2794: invokevirtual 83	java/lang/StringBuilder:toString	()Ljava/lang/String;
    //   2797: invokestatic 440	com/sleepycat/b/aa:c	(Ljava/lang/String;)Lcom/sleepycat/b/aa;
    //   2800: athrow
    //   2801: astore 4
    //   2803: aload_2
    //   2804: astore_3
    //   2805: aload 4
    //   2807: astore_2
    //   2808: goto -515 -> 2293
    //   2811: aload 11
    //   2813: invokevirtual 715	com/sleepycat/b/g/g:b	()Lcom/sleepycat/b/c/ax;
    //   2816: aload 5
    //   2818: getfield 328	com/sleepycat/b/i/c/b/ac:d	Lcom/sleepycat/b/i/c/aj;
    //   2821: invokevirtual 720	com/sleepycat/b/c/ax:a	(Lcom/sleepycat/b/c/ad;)Lcom/sleepycat/b/l;
    //   2824: astore_3
    //   2825: aload 5
    //   2827: getfield 328	com/sleepycat/b/i/c/b/ac:d	Lcom/sleepycat/b/i/c/aj;
    //   2830: getfield 419	com/sleepycat/b/c/ad:q	Lcom/sleepycat/b/c/p;
    //   2833: aload 9
    //   2835: getfield 422	com/sleepycat/b/l/ab:a	Lcom/sleepycat/b/c/h;
    //   2838: invokevirtual 755	com/sleepycat/b/c/p:b	(Lcom/sleepycat/b/c/h;)Lcom/sleepycat/b/c/i;
    //   2841: astore_2
    //   2842: aload_2
    //   2843: invokevirtual 764	com/sleepycat/b/c/i:x	()Ljava/lang/String;
    //   2846: astore 4
    //   2848: aload 5
    //   2850: getfield 328	com/sleepycat/b/i/c/b/ac:d	Lcom/sleepycat/b/i/c/aj;
    //   2853: getfield 419	com/sleepycat/b/c/ad:q	Lcom/sleepycat/b/c/p;
    //   2856: aload 8
    //   2858: aload 4
    //   2860: aload 11
    //   2862: invokevirtual 797	com/sleepycat/b/c/p:a	(Lcom/sleepycat/b/n/q;Ljava/lang/String;Lcom/sleepycat/b/g/g;)V
    //   2865: aload_2
    //   2866: aload 8
    //   2868: aload 4
    //   2870: aload_3
    //   2871: aload 5
    //   2873: getfield 328	com/sleepycat/b/i/c/b/ac:d	Lcom/sleepycat/b/i/c/aj;
    //   2876: invokevirtual 800	com/sleepycat/b/c/i:a	(Lcom/sleepycat/b/n/q;Ljava/lang/String;Lcom/sleepycat/b/l;Lcom/sleepycat/b/c/ad;)V
    //   2879: aload 5
    //   2881: getfield 328	com/sleepycat/b/i/c/b/ac:d	Lcom/sleepycat/b/i/c/aj;
    //   2884: getfield 419	com/sleepycat/b/c/ad:q	Lcom/sleepycat/b/c/p;
    //   2887: aload_2
    //   2888: invokevirtual 802	com/sleepycat/b/c/p:b	(Lcom/sleepycat/b/c/i;)V
    //   2891: goto -451 -> 2440
    //   2894: aload 5
    //   2896: getfield 805	com/sleepycat/b/i/c/b/ac:v	Lcom/sleepycat/b/p/z;
    //   2899: invokevirtual 547	com/sleepycat/b/p/z:f	()V
    //   2902: getstatic 808	com/sleepycat/b/i/c/b/ac:D	Z
    //   2905: ifne +22 -> 2927
    //   2908: aload 6
    //   2910: getfield 309	com/sleepycat/b/i/e/k:a	Lcom/sleepycat/b/g/a/m;
    //   2913: instanceof 810
    //   2916: ifne +11 -> 2927
    //   2919: new 384	java/lang/AssertionError
    //   2922: dup
    //   2923: invokespecial 386	java/lang/AssertionError:<init>	()V
    //   2926: athrow
    //   2927: aload 6
    //   2929: getfield 309	com/sleepycat/b/i/e/k:a	Lcom/sleepycat/b/g/a/m;
    //   2932: checkcast 810	com/sleepycat/b/g/a/k
    //   2935: astore 4
    //   2937: aload 4
    //   2939: getfield 812	com/sleepycat/b/g/a/k:d	Lcom/sleepycat/b/c/h;
    //   2942: astore 9
    //   2944: aload 9
    //   2946: getfield 432	com/sleepycat/b/c/h:a	J
    //   2949: ldc2_w 727
    //   2952: lcmp
    //   2953: ifne +9 -> 2962
    //   2956: aload 8
    //   2958: iconst_1
    //   2959: putfield 589	com/sleepycat/b/i/f/e:d	Z
    //   2962: aload 5
    //   2964: getfield 328	com/sleepycat/b/i/c/b/ac:d	Lcom/sleepycat/b/i/c/aj;
    //   2967: getfield 491	com/sleepycat/b/i/c/aj:am	Lcom/sleepycat/b/i/c/b/aa;
    //   2970: getfield 675	com/sleepycat/b/i/c/b/aa:e	Lcom/sleepycat/b/i/c/b/ag;
    //   2973: getfield 815	com/sleepycat/b/i/c/b/ag:i	Lcom/sleepycat/b/i/c/b/c;
    //   2976: astore 10
    //   2978: aload 10
    //   2980: getfield 244	com/sleepycat/b/i/c/b/c:a	Lcom/sleepycat/b/i/c/b/d;
    //   2983: aload 9
    //   2985: invokevirtual 818	com/sleepycat/b/i/c/b/d:get	(Ljava/lang/Object;)Ljava/lang/Object;
    //   2988: checkcast 267	com/sleepycat/b/i/c/b/e
    //   2991: astore_2
    //   2992: aload_2
    //   2993: ifnull +172 -> 3165
    //   2996: aload_2
    //   2997: aload 10
    //   2999: getfield 270	com/sleepycat/b/i/c/b/c:d	I
    //   3002: putfield 268	com/sleepycat/b/i/c/b/e:a	I
    //   3005: aload_2
    //   3006: getfield 273	com/sleepycat/b/i/c/b/e:b	Lcom/sleepycat/b/c/i;
    //   3009: astore_2
    //   3010: aload 4
    //   3012: aload_2
    //   3013: invokevirtual 819	com/sleepycat/b/g/a/k:c	(Lcom/sleepycat/b/c/i;)V
    //   3016: new 500	com/sleepycat/b/g/av
    //   3019: dup
    //   3020: aload 6
    //   3022: getfield 312	com/sleepycat/b/i/e/k:d	Lcom/sleepycat/b/g/ae;
    //   3025: getfield 317	com/sleepycat/b/g/ae:e	Lcom/sleepycat/b/p/au;
    //   3028: invokespecial 503	com/sleepycat/b/g/av:<init>	(Lcom/sleepycat/b/p/au;)V
    //   3031: astore 10
    //   3033: aload_2
    //   3034: aload 8
    //   3036: aconst_null
    //   3037: invokestatic 824	com/sleepycat/b/q:a	(Lcom/sleepycat/b/c/i;Lcom/sleepycat/b/n/q;Lcom/sleepycat/b/g;)Lcom/sleepycat/b/e;
    //   3040: astore 9
    //   3042: aload 4
    //   3044: invokevirtual 825	com/sleepycat/b/g/a/k:j	()Lcom/sleepycat/b/l/y;
    //   3047: astore_2
    //   3048: aload_2
    //   3049: invokevirtual 829	com/sleepycat/b/l/y:i	()Z
    //   3052: ifeq +180 -> 3232
    //   3055: aload 5
    //   3057: getfield 832	com/sleepycat/b/i/c/b/ac:a	Lcom/sleepycat/b/m;
    //   3060: aload 4
    //   3062: invokevirtual 833	com/sleepycat/b/g/a/k:k	()[B
    //   3065: invokevirtual 838	com/sleepycat/b/m:a	([B)V
    //   3068: aload 9
    //   3070: aload 5
    //   3072: getfield 832	com/sleepycat/b/i/c/b/ac:a	Lcom/sleepycat/b/m;
    //   3075: aload 5
    //   3077: getfield 840	com/sleepycat/b/i/c/b/ac:c	Lcom/sleepycat/b/m;
    //   3080: getstatic 845	com/sleepycat/b/ao:b	Lcom/sleepycat/b/ao;
    //   3083: getstatic 850	com/sleepycat/b/c/e:a	Lcom/sleepycat/b/c/e;
    //   3086: invokevirtual 855	com/sleepycat/b/e:b	(Lcom/sleepycat/b/m;Lcom/sleepycat/b/m;Lcom/sleepycat/b/ao;Lcom/sleepycat/b/c/e;)Lcom/sleepycat/b/av;
    //   3089: astore_3
    //   3090: aload_3
    //   3091: astore_2
    //   3092: aload_3
    //   3093: getstatic 860	com/sleepycat/b/av:a	Lcom/sleepycat/b/av;
    //   3096: if_acmpne +11 -> 3107
    //   3099: aload 9
    //   3101: aload 10
    //   3103: invokevirtual 863	com/sleepycat/b/e:a	(Lcom/sleepycat/b/g/av;)Lcom/sleepycat/b/av;
    //   3106: astore_2
    //   3107: aload_2
    //   3108: getstatic 860	com/sleepycat/b/av:a	Lcom/sleepycat/b/av;
    //   3111: if_acmpeq +362 -> 3473
    //   3114: new 326	com/sleepycat/b/aa
    //   3117: dup
    //   3118: aload 5
    //   3120: getfield 328	com/sleepycat/b/i/c/b/ac:d	Lcom/sleepycat/b/i/c/aj;
    //   3123: getstatic 865	com/sleepycat/b/c/ac:l	Lcom/sleepycat/b/c/ac;
    //   3126: new 70	java/lang/StringBuilder
    //   3129: dup
    //   3130: ldc_w 867
    //   3133: invokespecial 75	java/lang/StringBuilder:<init>	(Ljava/lang/String;)V
    //   3136: aload_2
    //   3137: invokevirtual 299	java/lang/StringBuilder:append	(Ljava/lang/Object;)Ljava/lang/StringBuilder;
    //   3140: bipush 32
    //   3142: invokevirtual 870	java/lang/StringBuilder:append	(C)Ljava/lang/StringBuilder;
    //   3145: aload 6
    //   3147: invokevirtual 299	java/lang/StringBuilder:append	(Ljava/lang/Object;)Ljava/lang/StringBuilder;
    //   3150: invokevirtual 83	java/lang/StringBuilder:toString	()Ljava/lang/String;
    //   3153: invokespecial 341	com/sleepycat/b/aa:<init>	(Lcom/sleepycat/b/c/ad;Lcom/sleepycat/b/c/ac;Ljava/lang/String;)V
    //   3156: athrow
    //   3157: astore_2
    //   3158: aload 9
    //   3160: invokevirtual 873	com/sleepycat/b/e:close	()V
    //   3163: aload_2
    //   3164: athrow
    //   3165: new 267	com/sleepycat/b/i/c/b/e
    //   3168: dup
    //   3169: aload 10
    //   3171: aload 10
    //   3173: getfield 875	com/sleepycat/b/i/c/b/c:b	Lcom/sleepycat/b/c/p;
    //   3176: aload 9
    //   3178: ldc2_w 876
    //   3181: aconst_null
    //   3182: invokevirtual 880	com/sleepycat/b/c/p:a	(Lcom/sleepycat/b/c/h;JLjava/lang/String;)Lcom/sleepycat/b/c/i;
    //   3185: invokespecial 883	com/sleepycat/b/i/c/b/e:<init>	(Lcom/sleepycat/b/i/c/b/c;Lcom/sleepycat/b/c/i;)V
    //   3188: astore_3
    //   3189: aload 10
    //   3191: getfield 244	com/sleepycat/b/i/c/b/c:a	Lcom/sleepycat/b/i/c/b/d;
    //   3194: aload 9
    //   3196: aload_3
    //   3197: invokevirtual 887	com/sleepycat/b/i/c/b/d:put	(Ljava/lang/Object;Ljava/lang/Object;)Ljava/lang/Object;
    //   3200: pop
    //   3201: aload_3
    //   3202: astore_2
    //   3203: aload_3
    //   3204: getfield 273	com/sleepycat/b/i/c/b/e:b	Lcom/sleepycat/b/c/i;
    //   3207: getfield 890	com/sleepycat/b/c/i:k	Ljava/util/concurrent/atomic/AtomicInteger;
    //   3210: invokevirtual 895	java/util/concurrent/atomic/AtomicInteger:incrementAndGet	()I
    //   3213: iconst_1
    //   3214: if_icmpne -209 -> 3005
    //   3217: aload 8
    //   3219: aload_3
    //   3220: getfield 273	com/sleepycat/b/i/c/b/e:b	Lcom/sleepycat/b/c/i;
    //   3223: iconst_0
    //   3224: invokestatic 752	com/sleepycat/b/c/bh:a	(Lcom/sleepycat/b/n/q;Lcom/sleepycat/b/c/i;Z)V
    //   3227: aload_3
    //   3228: astore_2
    //   3229: goto -224 -> 3005
    //   3232: aload 5
    //   3234: getfield 832	com/sleepycat/b/i/c/b/ac:a	Lcom/sleepycat/b/m;
    //   3237: aload 4
    //   3239: invokevirtual 833	com/sleepycat/b/g/a/k:k	()[B
    //   3242: invokevirtual 838	com/sleepycat/b/m:a	([B)V
    //   3245: aload 5
    //   3247: getfield 897	com/sleepycat/b/i/c/b/ac:b	Lcom/sleepycat/b/m;
    //   3250: aload_2
    //   3251: getfield 900	com/sleepycat/b/l/y:f	[B
    //   3254: invokevirtual 838	com/sleepycat/b/m:a	([B)V
    //   3257: aload 9
    //   3259: aload 5
    //   3261: getfield 832	com/sleepycat/b/i/c/b/ac:a	Lcom/sleepycat/b/m;
    //   3264: aload 5
    //   3266: getfield 897	com/sleepycat/b/i/c/b/ac:b	Lcom/sleepycat/b/m;
    //   3269: aload_2
    //   3270: getstatic 905	com/sleepycat/b/c/at:d	Lcom/sleepycat/b/c/at;
    //   3273: aload 10
    //   3275: invokevirtual 908	com/sleepycat/b/e:a	(Lcom/sleepycat/b/m;Lcom/sleepycat/b/m;Lcom/sleepycat/b/l/y;Lcom/sleepycat/b/c/at;Lcom/sleepycat/b/g/av;)Lcom/sleepycat/b/av;
    //   3278: astore_2
    //   3279: goto -172 -> 3107
    //   3282: aload 8
    //   3284: aload_2
    //   3285: putfield 604	com/sleepycat/b/i/f/e:c	Lcom/sleepycat/b/p/au;
    //   3288: invokestatic 174	java/lang/System:nanoTime	()J
    //   3291: lload 17
    //   3293: lsub
    //   3294: lstore 17
    //   3296: lload 17
    //   3298: aload 5
    //   3300: getfield 619	com/sleepycat/b/i/c/b/ac:j	J
    //   3303: lcmp
    //   3304: ifle +79 -> 3383
    //   3307: aload 5
    //   3309: getfield 345	com/sleepycat/b/i/c/b/ac:C	Ljava/util/logging/Logger;
    //   3312: aload 5
    //   3314: getfield 328	com/sleepycat/b/i/c/b/ac:d	Lcom/sleepycat/b/i/c/aj;
    //   3317: new 70	java/lang/StringBuilder
    //   3320: dup
    //   3321: ldc_w 621
    //   3324: invokespecial 75	java/lang/StringBuilder:<init>	(Ljava/lang/String;)V
    //   3327: iload_1
    //   3328: invokestatic 624	com/sleepycat/b/g/af:a	(B)Lcom/sleepycat/b/g/af;
    //   3331: invokevirtual 299	java/lang/StringBuilder:append	(Ljava/lang/Object;)Ljava/lang/StringBuilder;
    //   3334: ldc_w 626
    //   3337: invokevirtual 221	java/lang/StringBuilder:append	(Ljava/lang/String;)Ljava/lang/StringBuilder;
    //   3340: getstatic 152	java/util/concurrent/TimeUnit:NANOSECONDS	Ljava/util/concurrent/TimeUnit;
    //   3343: lload 17
    //   3345: invokevirtual 630	java/util/concurrent/TimeUnit:toMillis	(J)J
    //   3348: invokevirtual 391	java/lang/StringBuilder:append	(J)Ljava/lang/StringBuilder;
    //   3351: ldc_w 632
    //   3354: invokevirtual 221	java/lang/StringBuilder:append	(Ljava/lang/String;)Ljava/lang/StringBuilder;
    //   3357: getstatic 152	java/util/concurrent/TimeUnit:NANOSECONDS	Ljava/util/concurrent/TimeUnit;
    //   3360: aload 5
    //   3362: getfield 619	com/sleepycat/b/i/c/b/ac:j	J
    //   3365: invokevirtual 630	java/util/concurrent/TimeUnit:toMillis	(J)J
    //   3368: invokevirtual 391	java/lang/StringBuilder:append	(J)Ljava/lang/StringBuilder;
    //   3371: ldc_w 634
    //   3374: invokevirtual 221	java/lang/StringBuilder:append	(Ljava/lang/String;)Ljava/lang/StringBuilder;
    //   3377: invokevirtual 83	java/lang/StringBuilder:toString	()Ljava/lang/String;
    //   3380: invokestatic 88	com/sleepycat/b/p/w:c	(Ljava/util/logging/Logger;Lcom/sleepycat/b/c/ad;Ljava/lang/String;)V
    //   3383: aload 7
    //   3385: checkcast 301	com/sleepycat/b/i/e/y
    //   3388: invokevirtual 304	com/sleepycat/b/i/e/y:d	()Lcom/sleepycat/b/i/e/k;
    //   3391: getfield 312	com/sleepycat/b/i/e/k:d	Lcom/sleepycat/b/g/ae;
    //   3394: getfield 444	com/sleepycat/b/g/ae:b	B
    //   3397: istore_1
    //   3398: getstatic 449	com/sleepycat/b/g/af:q	Lcom/sleepycat/b/g/af;
    //   3401: iload_1
    //   3402: invokevirtual 452	com/sleepycat/b/g/af:c	(B)Z
    //   3405: ifne +133 -> 3538
    //   3408: getstatic 656	com/sleepycat/b/g/af:r	Lcom/sleepycat/b/g/af;
    //   3411: iload_1
    //   3412: invokevirtual 452	com/sleepycat/b/g/af:c	(B)Z
    //   3415: ifeq +52 -> 3467
    //   3418: goto +120 -> 3538
    //   3421: iload 13
    //   3423: ifeq +31 -> 3454
    //   3426: aload_0
    //   3427: getfield 32	com/sleepycat/b/i/c/b/am:c	Lcom/sleepycat/b/i/c/b/ag;
    //   3430: aload_0
    //   3431: getfield 32	com/sleepycat/b/i/c/b/am:c	Lcom/sleepycat/b/i/c/b/ag;
    //   3434: invokestatic 120	com/sleepycat/b/i/c/b/ag:f	(Lcom/sleepycat/b/i/c/b/ag;)Lcom/sleepycat/b/i/c/b/ac;
    //   3437: getfield 319	com/sleepycat/b/i/c/b/ac:h	Lcom/sleepycat/b/p/au;
    //   3440: invokestatic 911	com/sleepycat/b/i/c/b/ag:a	(Lcom/sleepycat/b/i/c/b/ag;Lcom/sleepycat/b/p/au;)Lcom/sleepycat/b/p/au;
    //   3443: pop
    //   3444: aload_0
    //   3445: getfield 32	com/sleepycat/b/i/c/b/am:c	Lcom/sleepycat/b/i/c/b/ag;
    //   3448: invokestatic 914	com/sleepycat/b/i/c/b/ag:i	(Lcom/sleepycat/b/i/c/b/ag;)Lcom/sleepycat/b/i/c/b/ai;
    //   3451: invokevirtual 918	com/sleepycat/b/i/c/b/ai:b	()V
    //   3454: aload_0
    //   3455: getfield 32	com/sleepycat/b/i/c/b/am:c	Lcom/sleepycat/b/i/c/b/ag;
    //   3458: invokestatic 914	com/sleepycat/b/i/c/b/ag:i	(Lcom/sleepycat/b/i/c/b/ag;)Lcom/sleepycat/b/i/c/b/ai;
    //   3461: invokevirtual 919	com/sleepycat/b/i/c/b/ai:c	()V
    //   3464: goto -3016 -> 448
    //   3467: iconst_0
    //   3468: istore 13
    //   3470: goto -49 -> 3421
    //   3473: aload 9
    //   3475: invokevirtual 873	com/sleepycat/b/e:close	()V
    //   3478: goto -1927 -> 1551
    //   3481: astore 4
    //   3483: aload_2
    //   3484: astore_3
    //   3485: aload 4
    //   3487: astore_2
    //   3488: goto -1195 -> 2293
    //   3491: return
    //   3492: lconst_1
    //   3493: lload 15
    //   3495: ladd
    //   3496: lstore 15
    //   3498: goto -3438 -> 60
    //   3501: iconst_1
    //   3502: istore 13
    //   3504: goto -2879 -> 625
    //   3507: iconst_0
    //   3508: istore 13
    //   3510: goto -2885 -> 625
    //   3513: iconst_0
    //   3514: istore 13
    //   3516: goto -2063 -> 1453
    //   3519: iconst_1
    //   3520: istore 13
    //   3522: goto -2069 -> 1453
    //   3525: goto -1281 -> 2244
    //   3528: astore 4
    //   3530: aload_2
    //   3531: astore_3
    //   3532: aload 4
    //   3534: astore_2
    //   3535: goto -1242 -> 2293
    //   3538: iconst_1
    //   3539: istore 13
    //   3541: goto -120 -> 3421
    // Local variable table:
    //   start	length	slot	name	signature
    //   0	3544	0	this	am
    //   991	2421	1	b1	byte
    //   28	201	2	localObject1	Object
    //   248	63	2	localException	Exception
    //   343	1251	2	localObject2	Object
    //   1618	24	2	localn	com.sleepycat.b.n
    //   1643	97	2	localObject3	Object
    //   1742	513	2	localObject4	Object
    //   2290	20	2	localObject5	Object
    //   2324	199	2	localObject6	Object
    //   2526	1	2	localp1	com.sleepycat.b.p
    //   2528	108	2	localObject7	Object
    //   2639	1	2	localp2	com.sleepycat.b.p
    //   2641	113	2	localObject8	Object
    //   2757	1	2	localp3	com.sleepycat.b.p
    //   2759	378	2	localObject9	Object
    //   3157	7	2	localObject10	Object
    //   3202	333	2	localObject11	Object
    //   36	3496	3	localObject12	Object
    //   44	2708	4	localObject13	Object
    //   2801	5	4	localObject14	Object
    //   2846	392	4	localObject15	Object
    //   3481	5	4	localObject16	Object
    //   3528	5	4	localObject17	Object
    //   545	2816	5	localac	ac
    //   557	2589	6	localk	com.sleepycat.b.i.e.k
    //   100	448	7	locald	d
    //   2573	811	7	locals	com.sleepycat.b.c.s
    //   580	2703	8	localObject18	Object
    //   873	2601	9	localObject19	Object
    //   2177	1097	10	localObject20	Object
    //   2195	666	11	localg	com.sleepycat.b.g.g
    //   2495	11	12	localh	com.sleepycat.b.c.h
    //   625	2915	13	i	int
    //   19	453	14	j	int
    //   58	3439	15	l1	long
    //   81	3263	17	l2	long
    //   760	653	19	l3	long
    //   1242	169	21	l4	long
    //   1250	142	23	l5	long
    //   1024	395	25	bool	boolean
    // Exception table:
    //   from	to	target	type
    //   60	78	248	java/lang/Exception
    //   83	122	248	java/lang/Exception
    //   127	140	248	java/lang/Exception
    //   140	163	248	java/lang/Exception
    //   164	184	248	java/lang/Exception
    //   187	217	248	java/lang/Exception
    //   222	248	248	java/lang/Exception
    //   310	368	248	java/lang/Exception
    //   368	381	248	java/lang/Exception
    //   381	428	248	java/lang/Exception
    //   431	448	248	java/lang/Exception
    //   448	469	248	java/lang/Exception
    //   480	487	248	java/lang/Exception
    //   490	535	248	java/lang/Exception
    //   538	599	248	java/lang/Exception
    //   599	622	248	java/lang/Exception
    //   630	684	248	java/lang/Exception
    //   684	729	248	java/lang/Exception
    //   729	786	248	java/lang/Exception
    //   786	792	248	java/lang/Exception
    //   799	825	248	java/lang/Exception
    //   825	847	248	java/lang/Exception
    //   847	915	248	java/lang/Exception
    //   915	922	248	java/lang/Exception
    //   929	961	248	java/lang/Exception
    //   961	983	248	java/lang/Exception
    //   983	1005	248	java/lang/Exception
    //   1644	1739	248	java/lang/Exception
    //   1739	1741	248	java/lang/Exception
    //   3288	3383	248	java/lang/Exception
    //   3383	3418	248	java/lang/Exception
    //   3426	3454	248	java/lang/Exception
    //   3454	3464	248	java/lang/Exception
    //   1005	1031	1618	com/sleepycat/b/n
    //   1036	1060	1618	com/sleepycat/b/n
    //   1060	1074	1618	com/sleepycat/b/n
    //   1079	1137	1618	com/sleepycat/b/n
    //   1137	1149	1618	com/sleepycat/b/n
    //   1154	1183	1618	com/sleepycat/b/n
    //   1183	1330	1618	com/sleepycat/b/n
    //   1330	1338	1618	com/sleepycat/b/n
    //   1343	1351	1618	com/sleepycat/b/n
    //   1351	1366	1618	com/sleepycat/b/n
    //   1366	1397	1618	com/sleepycat/b/n
    //   1405	1418	1618	com/sleepycat/b/n
    //   1423	1450	1618	com/sleepycat/b/n
    //   1458	1497	1618	com/sleepycat/b/n
    //   1497	1538	1618	com/sleepycat/b/n
    //   1538	1551	1618	com/sleepycat/b/n
    //   1551	1618	1618	com/sleepycat/b/n
    //   1746	1752	1618	com/sleepycat/b/n
    //   1755	1803	1618	com/sleepycat/b/n
    //   1806	1821	1618	com/sleepycat/b/n
    //   1824	1839	1618	com/sleepycat/b/n
    //   1842	1863	1618	com/sleepycat/b/n
    //   1863	1910	1618	com/sleepycat/b/n
    //   1913	1919	1618	com/sleepycat/b/n
    //   1922	2038	1618	com/sleepycat/b/n
    //   2038	2104	1618	com/sleepycat/b/n
    //   2104	2117	1618	com/sleepycat/b/n
    //   2120	2203	1618	com/sleepycat/b/n
    //   2297	2309	1618	com/sleepycat/b/n
    //   2309	2311	1618	com/sleepycat/b/n
    //   2444	2456	1618	com/sleepycat/b/n
    //   2894	2927	1618	com/sleepycat/b/n
    //   2927	2962	1618	com/sleepycat/b/n
    //   2962	2992	1618	com/sleepycat/b/n
    //   2996	3005	1618	com/sleepycat/b/n
    //   3005	3042	1618	com/sleepycat/b/n
    //   3158	3165	1618	com/sleepycat/b/n
    //   3165	3201	1618	com/sleepycat/b/n
    //   3203	3227	1618	com/sleepycat/b/n
    //   3282	3288	1618	com/sleepycat/b/n
    //   3473	3478	1618	com/sleepycat/b/n
    //   1005	1031	1643	finally
    //   1036	1060	1643	finally
    //   1060	1074	1643	finally
    //   1079	1137	1643	finally
    //   1137	1149	1643	finally
    //   1154	1183	1643	finally
    //   1183	1330	1643	finally
    //   1330	1338	1643	finally
    //   1343	1351	1643	finally
    //   1351	1366	1643	finally
    //   1366	1397	1643	finally
    //   1405	1418	1643	finally
    //   1423	1450	1643	finally
    //   1458	1497	1643	finally
    //   1497	1538	1643	finally
    //   1538	1551	1643	finally
    //   1551	1618	1643	finally
    //   1619	1643	1643	finally
    //   1746	1752	1643	finally
    //   1755	1803	1643	finally
    //   1806	1821	1643	finally
    //   1824	1839	1643	finally
    //   1842	1863	1643	finally
    //   1863	1910	1643	finally
    //   1913	1919	1643	finally
    //   1922	2038	1643	finally
    //   2038	2104	1643	finally
    //   2104	2117	1643	finally
    //   2120	2203	1643	finally
    //   2297	2309	1643	finally
    //   2309	2311	1643	finally
    //   2444	2456	1643	finally
    //   2894	2927	1643	finally
    //   2927	2962	1643	finally
    //   2962	2992	1643	finally
    //   2996	3005	1643	finally
    //   3005	3042	1643	finally
    //   3158	3165	1643	finally
    //   3165	3201	1643	finally
    //   3203	3227	1643	finally
    //   3282	3288	1643	finally
    //   3473	3478	1643	finally
    //   2203	2244	2290	finally
    //   2244	2290	2290	finally
    //   2311	2347	2290	finally
    //   2459	2476	2290	finally
    //   2588	2605	2290	finally
    //   2686	2704	2290	finally
    //   2811	2842	2290	finally
    //   2478	2488	2526	com/sleepycat/b/p
    //   2490	2497	2526	com/sleepycat/b/p
    //   2499	2513	2526	com/sleepycat/b/p
    //   2515	2521	2526	com/sleepycat/b/p
    //   2577	2588	2526	com/sleepycat/b/p
    //   2499	2513	2573	com/sleepycat/b/c/s
    //   2607	2634	2639	com/sleepycat/b/p
    //   2710	2736	2757	com/sleepycat/b/p
    //   2742	2751	2757	com/sleepycat/b/p
    //   2710	2736	2801	finally
    //   2742	2751	2801	finally
    //   2760	2801	2801	finally
    //   3042	3090	3157	finally
    //   3092	3107	3157	finally
    //   3107	3157	3157	finally
    //   3232	3279	3157	finally
    //   2842	2891	3481	finally
    //   2349	2363	3528	finally
    //   2365	2379	3528	finally
    //   2381	2429	3528	finally
    //   2431	2438	3528	finally
    //   2478	2488	3528	finally
    //   2490	2497	3528	finally
    //   2499	2513	3528	finally
    //   2515	2521	3528	finally
    //   2529	2573	3528	finally
    //   2577	2588	3528	finally
    //   2607	2634	3528	finally
    //   2642	2686	3528	finally
  }
}


/* Location:              E:\apk\xueqiu2\classes-dex2jar.jar!\com\sleepycat\b\i\c\b\am.class
 * Java compiler version: 6 (50.0)
 * JD-Core Version:       0.7.1
 */