package com.sleepycat.b.i.c.b;

import com.sleepycat.b.i.e.af;
import com.sleepycat.b.i.e.n;
import com.sleepycat.b.i.e.t;
import com.sleepycat.b.i.e.u;
import com.sleepycat.b.i.h.d;
import com.sleepycat.b.i.h.q;
import com.sleepycat.b.p.au;
import com.sleepycat.b.p.w;
import java.util.concurrent.atomic.AtomicBoolean;
import java.util.logging.Level;
import java.util.logging.Logger;

final class k
  extends com.sleepycat.b.p.aj
{
  t a = null;
  private r c;
  
  k(h paramh, com.sleepycat.b.i.c.aj paramaj)
  {
    super(paramaj, new j(paramh, (byte)0), "Feeder Input");
  }
  
  private void b()
  {
    Object localObject;
    while (!d())
    {
      localObject = this.a.a(h.b(this.b));
      if (!d())
      {
        h.i(this.b).e();
        h.a(this.b, System.currentTimeMillis());
        if (((d)localObject).a() == t.o)
        {
          localObject = (af)localObject;
          this.c.a(((af)localObject).a, "heartbeat");
          localObject = ((af)localObject).b;
          if (localObject != null)
          {
            h.a(this.b, (au)localObject);
            if (h.d(this.b).b(h.a(this.b).g()) >= 0)
            {
              h.e(this.b);
              this.b.a();
            }
          }
        }
        else if (((d)localObject).a() == t.q)
        {
          long l = ((u)localObject).a;
          if (h.k(this.b).isLoggable(Level.FINE)) {
            w.d(h.k(this.b), h.l(this.b), "Ack for: " + l);
          }
          h.b(this.b, l);
        }
        else
        {
          if (((d)localObject).a() != t.x) {
            break label268;
          }
          w.c(h.k(this.b), h.l(this.b), "Shutdown confirmed by replica " + h.c(this.b).a);
        }
      }
    }
    return;
    label268:
    throw com.sleepycat.b.aa.c("Unexpected message: " + localObject);
  }
  
  private boolean d()
  {
    return (h.m(this.b).get()) && (h.a(this.b).s < 0L);
  }
  
  protected final Logger a()
  {
    return h.k(this.b);
  }
  
  protected final int c()
  {
    q.a(h.b(this.b));
    return h.a(this.b).d() * 4;
  }
  
  /* Error */
  public final void run()
  {
    // Byte code:
    //   0: aconst_null
    //   1: astore_3
    //   2: new 229	com/sleepycat/b/i/e/c
    //   5: dup
    //   6: aload_0
    //   7: getfield 14	com/sleepycat/b/i/c/b/k:b	Lcom/sleepycat/b/i/c/b/h;
    //   10: invokestatic 94	com/sleepycat/b/i/c/b/h:a	(Lcom/sleepycat/b/i/c/b/h;)Lcom/sleepycat/b/i/c/b/aa;
    //   13: aload_0
    //   14: getfield 14	com/sleepycat/b/i/c/b/k:b	Lcom/sleepycat/b/i/c/b/h;
    //   17: invokestatic 37	com/sleepycat/b/i/c/b/h:b	(Lcom/sleepycat/b/i/c/b/h;)Lcom/sleepycat/b/i/h/p;
    //   20: invokespecial 232	com/sleepycat/b/i/e/c:<init>	(Lcom/sleepycat/b/i/c/b/aa;Lcom/sleepycat/b/i/h/o;)V
    //   23: astore 5
    //   25: aload 5
    //   27: getfield 236	com/sleepycat/b/i/e/c:f	Ljava/util/logging/Logger;
    //   30: aload 5
    //   32: getfield 239	com/sleepycat/b/i/e/c:a	Lcom/sleepycat/b/i/c/b/aa;
    //   35: getfield 242	com/sleepycat/b/i/c/b/aa:i	Lcom/sleepycat/b/i/c/aj;
    //   38: ldc -12
    //   40: invokestatic 179	com/sleepycat/b/p/w:c	(Ljava/util/logging/Logger;Lcom/sleepycat/b/c/ad;Ljava/lang/String;)V
    //   43: aload 5
    //   45: getfield 239	com/sleepycat/b/i/e/c:a	Lcom/sleepycat/b/i/c/b/aa;
    //   48: invokestatic 247	com/sleepycat/b/i/e/t:a	(Lcom/sleepycat/b/i/c/b/aa;)Lcom/sleepycat/b/i/e/t;
    //   51: astore_2
    //   52: aload_2
    //   53: aload 5
    //   55: getfield 250	com/sleepycat/b/i/e/c:b	Lcom/sleepycat/b/i/h/o;
    //   58: invokevirtual 42	com/sleepycat/b/i/e/t:a	(Ljava/nio/channels/ReadableByteChannel;)Lcom/sleepycat/b/i/h/d;
    //   61: checkcast 252	com/sleepycat/b/i/e/an
    //   64: astore_1
    //   65: aload 5
    //   67: aload_1
    //   68: getfield 257	com/sleepycat/b/i/e/al:d	Lcom/sleepycat/b/i/c/b/x;
    //   71: putfield 258	com/sleepycat/b/i/e/c:d	Lcom/sleepycat/b/i/c/b/x;
    //   74: aload 5
    //   76: getfield 239	com/sleepycat/b/i/e/c:a	Lcom/sleepycat/b/i/c/b/aa;
    //   79: getfield 261	com/sleepycat/b/i/c/b/aa:f	Lcom/sleepycat/b/i/c/b/m;
    //   82: astore 4
    //   84: aload 5
    //   86: getfield 258	com/sleepycat/b/i/e/c:d	Lcom/sleepycat/b/i/c/b/x;
    //   89: getfield 174	com/sleepycat/b/i/c/b/x:a	Ljava/lang/String;
    //   92: astore 6
    //   94: aload 4
    //   96: getfield 266	com/sleepycat/b/i/c/b/m:c	Lcom/sleepycat/b/i/h/af;
    //   99: aload 6
    //   101: invokevirtual 271	com/sleepycat/b/i/h/af:get	(Ljava/lang/Object;)Ljava/lang/Object;
    //   104: checkcast 34	com/sleepycat/b/i/c/b/h
    //   107: ifnonnull +24 -> 131
    //   110: aload_1
    //   111: getfield 257	com/sleepycat/b/i/e/al:d	Lcom/sleepycat/b/i/c/b/x;
    //   114: getfield 174	com/sleepycat/b/i/c/b/x:a	Ljava/lang/String;
    //   117: aload 5
    //   119: getfield 273	com/sleepycat/b/i/e/c:c	Lcom/sleepycat/b/i/c/b/x;
    //   122: getfield 174	com/sleepycat/b/i/c/b/x:a	Ljava/lang/String;
    //   125: invokevirtual 279	java/lang/String:equals	(Ljava/lang/Object;)Z
    //   128: ifeq +134 -> 262
    //   131: aload_2
    //   132: invokevirtual 285	java/lang/Object:getClass	()Ljava/lang/Class;
    //   135: pop
    //   136: aload_2
    //   137: new 287	com/sleepycat/b/i/e/x
    //   140: dup
    //   141: aload_2
    //   142: new 140	java/lang/StringBuilder
    //   145: dup
    //   146: ldc_w 289
    //   149: invokespecial 145	java/lang/StringBuilder:<init>	(Ljava/lang/String;)V
    //   152: aload 5
    //   154: getfield 258	com/sleepycat/b/i/e/c:d	Lcom/sleepycat/b/i/c/b/x;
    //   157: invokevirtual 184	java/lang/StringBuilder:append	(Ljava/lang/Object;)Ljava/lang/StringBuilder;
    //   160: ldc_w 291
    //   163: invokevirtual 177	java/lang/StringBuilder:append	(Ljava/lang/String;)Ljava/lang/StringBuilder;
    //   166: invokevirtual 153	java/lang/StringBuilder:toString	()Ljava/lang/String;
    //   169: invokespecial 294	com/sleepycat/b/i/e/x:<init>	(Lcom/sleepycat/b/i/e/t;Ljava/lang/String;)V
    //   172: aload 5
    //   174: getfield 250	com/sleepycat/b/i/e/c:b	Lcom/sleepycat/b/i/h/o;
    //   177: invokevirtual 297	com/sleepycat/b/i/e/t:a	(Lcom/sleepycat/b/i/h/d;Lcom/sleepycat/b/i/h/o;)V
    //   180: aload 5
    //   182: getfield 250	com/sleepycat/b/i/e/c:b	Lcom/sleepycat/b/i/h/o;
    //   185: invokevirtual 302	com/sleepycat/b/i/h/o:a	()Ljava/nio/channels/SocketChannel;
    //   188: invokevirtual 308	java/nio/channels/SocketChannel:socket	()Ljava/net/Socket;
    //   191: invokevirtual 314	java/net/Socket:getRemoteSocketAddress	()Ljava/net/SocketAddress;
    //   194: astore_1
    //   195: new 221	com/sleepycat/b/i/c/b/i
    //   198: dup
    //   199: new 140	java/lang/StringBuilder
    //   202: dup
    //   203: ldc_w 316
    //   206: invokespecial 145	java/lang/StringBuilder:<init>	(Ljava/lang/String;)V
    //   209: aload 5
    //   211: getfield 258	com/sleepycat/b/i/e/c:d	Lcom/sleepycat/b/i/c/b/x;
    //   214: invokevirtual 184	java/lang/StringBuilder:append	(Ljava/lang/Object;)Ljava/lang/StringBuilder;
    //   217: ldc_w 318
    //   220: invokevirtual 177	java/lang/StringBuilder:append	(Ljava/lang/String;)Ljava/lang/StringBuilder;
    //   223: aload_1
    //   224: invokevirtual 184	java/lang/StringBuilder:append	(Ljava/lang/Object;)Ljava/lang/StringBuilder;
    //   227: invokevirtual 153	java/lang/StringBuilder:toString	()Ljava/lang/String;
    //   230: invokespecial 319	com/sleepycat/b/i/c/b/i:<init>	(Ljava/lang/String;)V
    //   233: athrow
    //   234: astore_1
    //   235: aload_0
    //   236: getfield 14	com/sleepycat/b/i/c/b/k:b	Lcom/sleepycat/b/i/c/b/h;
    //   239: invokestatic 122	com/sleepycat/b/i/c/b/h:k	(Lcom/sleepycat/b/i/c/b/h;)Ljava/util/logging/Logger;
    //   242: aload_0
    //   243: getfield 14	com/sleepycat/b/i/c/b/k:b	Lcom/sleepycat/b/i/c/b/h;
    //   246: invokestatic 138	com/sleepycat/b/i/c/b/h:l	(Lcom/sleepycat/b/i/c/b/h;)Lcom/sleepycat/b/i/c/aj;
    //   249: aload_1
    //   250: invokevirtual 322	com/sleepycat/b/i/e/e:getMessage	()Ljava/lang/String;
    //   253: invokestatic 179	com/sleepycat/b/p/w:c	(Ljava/util/logging/Logger;Lcom/sleepycat/b/c/ad;Ljava/lang/String;)V
    //   256: iconst_0
    //   257: ifeq +1194 -> 1451
    //   260: aconst_null
    //   261: athrow
    //   262: aload_1
    //   263: getfield 325	com/sleepycat/b/i/e/al:c	I
    //   266: istore 8
    //   268: aload 5
    //   270: getfield 239	com/sleepycat/b/i/e/c:a	Lcom/sleepycat/b/i/c/b/aa;
    //   273: iload 8
    //   275: invokestatic 328	com/sleepycat/b/i/e/t:a	(Lcom/sleepycat/b/i/c/b/aa;I)Lcom/sleepycat/b/i/e/t;
    //   278: astore 4
    //   280: aload 4
    //   282: astore_1
    //   283: aload 4
    //   285: ifnonnull +5 -> 290
    //   288: aload_2
    //   289: astore_1
    //   290: aload_2
    //   291: invokevirtual 285	java/lang/Object:getClass	()Ljava/lang/Class;
    //   294: pop
    //   295: aload_2
    //   296: new 330	com/sleepycat/b/i/e/ac
    //   299: dup
    //   300: aload_2
    //   301: aload_1
    //   302: getfield 335	com/sleepycat/b/i/h/a:B	I
    //   305: invokespecial 338	com/sleepycat/b/i/e/ac:<init>	(Lcom/sleepycat/b/i/e/t;I)V
    //   308: aload 5
    //   310: getfield 250	com/sleepycat/b/i/e/c:b	Lcom/sleepycat/b/i/h/o;
    //   313: invokevirtual 297	com/sleepycat/b/i/e/t:a	(Lcom/sleepycat/b/i/h/d;Lcom/sleepycat/b/i/h/o;)V
    //   316: aload 5
    //   318: aload_1
    //   319: aload 5
    //   321: getfield 250	com/sleepycat/b/i/e/c:b	Lcom/sleepycat/b/i/h/o;
    //   324: invokevirtual 42	com/sleepycat/b/i/e/t:a	(Ljava/nio/channels/ReadableByteChannel;)Lcom/sleepycat/b/i/h/d;
    //   327: checkcast 340	com/sleepycat/b/i/e/am
    //   330: putfield 343	com/sleepycat/b/i/e/c:e	Lcom/sleepycat/b/i/e/am;
    //   333: aload 5
    //   335: getfield 236	com/sleepycat/b/i/e/c:f	Ljava/util/logging/Logger;
    //   338: aload 5
    //   340: getfield 239	com/sleepycat/b/i/e/c:a	Lcom/sleepycat/b/i/c/b/aa;
    //   343: getfield 242	com/sleepycat/b/i/c/b/aa:i	Lcom/sleepycat/b/i/c/aj;
    //   346: new 140	java/lang/StringBuilder
    //   349: dup
    //   350: ldc_w 345
    //   353: invokespecial 145	java/lang/StringBuilder:<init>	(Ljava/lang/String;)V
    //   356: aload 5
    //   358: getfield 258	com/sleepycat/b/i/e/c:d	Lcom/sleepycat/b/i/c/b/x;
    //   361: getfield 174	com/sleepycat/b/i/c/b/x:a	Ljava/lang/String;
    //   364: invokevirtual 177	java/lang/StringBuilder:append	(Ljava/lang/String;)Ljava/lang/StringBuilder;
    //   367: ldc_w 347
    //   370: invokevirtual 177	java/lang/StringBuilder:append	(Ljava/lang/String;)Ljava/lang/StringBuilder;
    //   373: aload 5
    //   375: getfield 343	com/sleepycat/b/i/e/c:e	Lcom/sleepycat/b/i/e/am;
    //   378: invokevirtual 350	com/sleepycat/b/i/e/am:d	()Lcom/sleepycat/b/am;
    //   381: invokevirtual 354	com/sleepycat/b/am:a	()Ljava/lang/String;
    //   384: invokevirtual 177	java/lang/StringBuilder:append	(Ljava/lang/String;)Ljava/lang/StringBuilder;
    //   387: ldc_w 356
    //   390: invokevirtual 177	java/lang/StringBuilder:append	(Ljava/lang/String;)Ljava/lang/StringBuilder;
    //   393: aload 5
    //   395: getfield 343	com/sleepycat/b/i/e/c:e	Lcom/sleepycat/b/i/e/am;
    //   398: invokevirtual 359	com/sleepycat/b/i/e/am:c	()B
    //   401: invokevirtual 362	java/lang/StringBuilder:append	(I)Ljava/lang/StringBuilder;
    //   404: invokevirtual 153	java/lang/StringBuilder:toString	()Ljava/lang/String;
    //   407: invokestatic 158	com/sleepycat/b/p/w:d	(Ljava/util/logging/Logger;Lcom/sleepycat/b/c/ad;Ljava/lang/String;)V
    //   410: aload 5
    //   412: getfield 343	com/sleepycat/b/i/e/c:e	Lcom/sleepycat/b/i/e/am;
    //   415: astore_2
    //   416: aload_2
    //   417: invokevirtual 365	com/sleepycat/b/i/e/ag:c	()B
    //   420: istore 10
    //   422: invokestatic 367	com/sleepycat/b/i/e/c:a	()I
    //   425: istore 9
    //   427: iload 9
    //   429: bipush 9
    //   431: if_icmplt +403 -> 834
    //   434: iload 9
    //   436: iconst_1
    //   437: isub
    //   438: istore 8
    //   440: goto +1113 -> 1553
    //   443: aload_2
    //   444: ifnull +475 -> 919
    //   447: aload 5
    //   449: getfield 236	com/sleepycat/b/i/e/c:f	Ljava/util/logging/Logger;
    //   452: aload 5
    //   454: getfield 239	com/sleepycat/b/i/e/c:a	Lcom/sleepycat/b/i/c/b/aa;
    //   457: getfield 242	com/sleepycat/b/i/c/b/aa:i	Lcom/sleepycat/b/i/c/aj;
    //   460: new 140	java/lang/StringBuilder
    //   463: dup
    //   464: ldc_w 369
    //   467: invokespecial 145	java/lang/StringBuilder:<init>	(Ljava/lang/String;)V
    //   470: aload_2
    //   471: getfield 373	com/sleepycat/b/i/h/i:b	Ljava/lang/String;
    //   474: invokevirtual 177	java/lang/StringBuilder:append	(Ljava/lang/String;)Ljava/lang/StringBuilder;
    //   477: ldc_w 375
    //   480: invokevirtual 177	java/lang/StringBuilder:append	(Ljava/lang/String;)Ljava/lang/StringBuilder;
    //   483: aload 5
    //   485: getfield 258	com/sleepycat/b/i/e/c:d	Lcom/sleepycat/b/i/c/b/x;
    //   488: getfield 174	com/sleepycat/b/i/c/b/x:a	Ljava/lang/String;
    //   491: invokevirtual 177	java/lang/StringBuilder:append	(Ljava/lang/String;)Ljava/lang/StringBuilder;
    //   494: invokevirtual 153	java/lang/StringBuilder:toString	()Ljava/lang/String;
    //   497: invokestatic 377	com/sleepycat/b/p/w:b	(Ljava/util/logging/Logger;Lcom/sleepycat/b/c/ad;Ljava/lang/String;)V
    //   500: aload_1
    //   501: aload_2
    //   502: aload 5
    //   504: getfield 250	com/sleepycat/b/i/e/c:b	Lcom/sleepycat/b/i/h/o;
    //   507: invokevirtual 297	com/sleepycat/b/i/e/t:a	(Lcom/sleepycat/b/i/h/d;Lcom/sleepycat/b/i/h/o;)V
    //   510: aload_0
    //   511: aload_1
    //   512: putfield 26	com/sleepycat/b/i/c/b/k:a	Lcom/sleepycat/b/i/e/t;
    //   515: aload_0
    //   516: getfield 14	com/sleepycat/b/i/c/b/k:b	Lcom/sleepycat/b/i/c/b/h;
    //   519: aload_0
    //   520: getfield 26	com/sleepycat/b/i/c/b/k:a	Lcom/sleepycat/b/i/e/t;
    //   523: getfield 335	com/sleepycat/b/i/h/a:B	I
    //   526: invokestatic 380	com/sleepycat/b/i/c/b/h:a	(Lcom/sleepycat/b/i/c/b/h;I)I
    //   529: pop
    //   530: aload_0
    //   531: getfield 14	com/sleepycat/b/i/c/b/k:b	Lcom/sleepycat/b/i/c/b/h;
    //   534: aload 5
    //   536: getfield 258	com/sleepycat/b/i/e/c:d	Lcom/sleepycat/b/i/c/b/x;
    //   539: invokestatic 383	com/sleepycat/b/i/c/b/h:a	(Lcom/sleepycat/b/i/c/b/h;Lcom/sleepycat/b/i/c/b/x;)Lcom/sleepycat/b/i/c/b/x;
    //   542: pop
    //   543: aload_0
    //   544: getfield 14	com/sleepycat/b/i/c/b/k:b	Lcom/sleepycat/b/i/c/b/h;
    //   547: astore_1
    //   548: aload 5
    //   550: getfield 343	com/sleepycat/b/i/e/c:e	Lcom/sleepycat/b/i/e/am;
    //   553: ifnull +470 -> 1023
    //   556: aload 5
    //   558: getfield 343	com/sleepycat/b/i/e/c:e	Lcom/sleepycat/b/i/e/am;
    //   561: invokevirtual 359	com/sleepycat/b/i/e/am:c	()B
    //   564: istore 8
    //   566: aload_1
    //   567: iload 8
    //   569: invokestatic 385	com/sleepycat/b/i/c/b/h:b	(Lcom/sleepycat/b/i/c/b/h;I)I
    //   572: pop
    //   573: invokestatic 391	java/lang/Thread:currentThread	()Ljava/lang/Thread;
    //   576: new 140	java/lang/StringBuilder
    //   579: dup
    //   580: ldc_w 393
    //   583: invokespecial 145	java/lang/StringBuilder:<init>	(Ljava/lang/String;)V
    //   586: aload_0
    //   587: getfield 14	com/sleepycat/b/i/c/b/k:b	Lcom/sleepycat/b/i/c/b/h;
    //   590: invokestatic 169	com/sleepycat/b/i/c/b/h:c	(Lcom/sleepycat/b/i/c/b/h;)Lcom/sleepycat/b/i/c/b/x;
    //   593: getfield 174	com/sleepycat/b/i/c/b/x:a	Ljava/lang/String;
    //   596: invokevirtual 177	java/lang/StringBuilder:append	(Ljava/lang/String;)Ljava/lang/StringBuilder;
    //   599: invokevirtual 153	java/lang/StringBuilder:toString	()Ljava/lang/String;
    //   602: invokevirtual 396	java/lang/Thread:setName	(Ljava/lang/String;)V
    //   605: new 398	com/sleepycat/b/i/e/d
    //   608: dup
    //   609: aload_0
    //   610: getfield 14	com/sleepycat/b/i/c/b/k:b	Lcom/sleepycat/b/i/c/b/h;
    //   613: aload_0
    //   614: getfield 14	com/sleepycat/b/i/c/b/k:b	Lcom/sleepycat/b/i/c/b/h;
    //   617: invokestatic 37	com/sleepycat/b/i/c/b/h:b	(Lcom/sleepycat/b/i/c/b/h;)Lcom/sleepycat/b/i/h/p;
    //   620: aload_0
    //   621: getfield 26	com/sleepycat/b/i/c/b/k:a	Lcom/sleepycat/b/i/e/t;
    //   624: invokespecial 401	com/sleepycat/b/i/e/d:<init>	(Lcom/sleepycat/b/i/c/b/h;Lcom/sleepycat/b/i/h/o;Lcom/sleepycat/b/i/e/t;)V
    //   627: astore_1
    //   628: aload_0
    //   629: new 80	com/sleepycat/b/i/c/b/r
    //   632: dup
    //   633: aload_0
    //   634: getfield 14	com/sleepycat/b/i/c/b/k:b	Lcom/sleepycat/b/i/c/b/h;
    //   637: invokestatic 169	com/sleepycat/b/i/c/b/h:c	(Lcom/sleepycat/b/i/c/b/h;)Lcom/sleepycat/b/i/c/b/x;
    //   640: aload_0
    //   641: getfield 14	com/sleepycat/b/i/c/b/k:b	Lcom/sleepycat/b/i/c/b/h;
    //   644: invokestatic 94	com/sleepycat/b/i/c/b/h:a	(Lcom/sleepycat/b/i/c/b/h;)Lcom/sleepycat/b/i/c/b/aa;
    //   647: invokespecial 404	com/sleepycat/b/i/c/b/r:<init>	(Lcom/sleepycat/b/i/c/b/x;Lcom/sleepycat/b/i/c/b/aa;)V
    //   650: putfield 73	com/sleepycat/b/i/c/b/k:c	Lcom/sleepycat/b/i/c/b/r;
    //   653: aload_1
    //   654: aload_0
    //   655: getfield 73	com/sleepycat/b/i/c/b/k:c	Lcom/sleepycat/b/i/c/b/r;
    //   658: invokevirtual 407	com/sleepycat/b/i/e/d:a	(Lcom/sleepycat/b/i/c/b/r;)Lcom/sleepycat/b/p/au;
    //   661: astore_1
    //   662: aload_0
    //   663: getfield 14	com/sleepycat/b/i/c/b/k:b	Lcom/sleepycat/b/i/c/b/h;
    //   666: aload_1
    //   667: invokevirtual 409	com/sleepycat/b/p/au:e	()Lcom/sleepycat/b/p/au;
    //   670: invokestatic 88	com/sleepycat/b/i/c/b/h:a	(Lcom/sleepycat/b/i/c/b/h;Lcom/sleepycat/b/p/au;)Lcom/sleepycat/b/p/au;
    //   673: pop
    //   674: aload_0
    //   675: getfield 14	com/sleepycat/b/i/c/b/k:b	Lcom/sleepycat/b/i/c/b/h;
    //   678: invokestatic 91	com/sleepycat/b/i/c/b/h:d	(Lcom/sleepycat/b/i/c/b/h;)Lcom/sleepycat/b/p/au;
    //   681: aload_0
    //   682: getfield 14	com/sleepycat/b/i/c/b/k:b	Lcom/sleepycat/b/i/c/b/h;
    //   685: invokestatic 94	com/sleepycat/b/i/c/b/h:a	(Lcom/sleepycat/b/i/c/b/h;)Lcom/sleepycat/b/i/c/b/aa;
    //   688: invokevirtual 100	com/sleepycat/b/i/c/b/aa:g	()Lcom/sleepycat/b/p/au;
    //   691: invokevirtual 105	com/sleepycat/b/p/au:b	(Lcom/sleepycat/b/p/au;)I
    //   694: iflt +11 -> 705
    //   697: aload_0
    //   698: getfield 14	com/sleepycat/b/i/c/b/k:b	Lcom/sleepycat/b/i/c/b/h;
    //   701: invokestatic 108	com/sleepycat/b/i/c/b/h:e	(Lcom/sleepycat/b/i/c/b/h;)Z
    //   704: pop
    //   705: aload_0
    //   706: getfield 14	com/sleepycat/b/i/c/b/k:b	Lcom/sleepycat/b/i/c/b/h;
    //   709: aload_1
    //   710: invokestatic 411	com/sleepycat/b/i/c/b/h:b	(Lcom/sleepycat/b/i/c/b/h;Lcom/sleepycat/b/p/au;)Lcom/sleepycat/b/p/au;
    //   713: pop
    //   714: aload_0
    //   715: getfield 14	com/sleepycat/b/i/c/b/k:b	Lcom/sleepycat/b/i/c/b/h;
    //   718: invokestatic 414	com/sleepycat/b/i/c/b/h:g	(Lcom/sleepycat/b/i/c/b/h;)Lcom/sleepycat/b/i/e/f;
    //   721: aload_0
    //   722: getfield 14	com/sleepycat/b/i/c/b/k:b	Lcom/sleepycat/b/i/c/b/h;
    //   725: invokestatic 416	com/sleepycat/b/i/c/b/h:f	(Lcom/sleepycat/b/i/c/b/h;)Lcom/sleepycat/b/p/au;
    //   728: invokeinterface 421 2 0
    //   733: aload_0
    //   734: getfield 14	com/sleepycat/b/i/c/b/k:b	Lcom/sleepycat/b/i/c/b/h;
    //   737: invokestatic 425	com/sleepycat/b/i/c/b/h:h	(Lcom/sleepycat/b/i/c/b/h;)Lcom/sleepycat/b/i/c/b/l;
    //   740: invokevirtual 430	com/sleepycat/b/i/c/b/l:start	()V
    //   743: aload_0
    //   744: getfield 14	com/sleepycat/b/i/c/b/k:b	Lcom/sleepycat/b/i/c/b/h;
    //   747: invokestatic 57	java/lang/System:currentTimeMillis	()J
    //   750: invokestatic 60	com/sleepycat/b/i/c/b/h:a	(Lcom/sleepycat/b/i/c/b/h;J)J
    //   753: pop2
    //   754: aload_0
    //   755: getfield 14	com/sleepycat/b/i/c/b/k:b	Lcom/sleepycat/b/i/c/b/h;
    //   758: invokestatic 46	com/sleepycat/b/i/c/b/h:i	(Lcom/sleepycat/b/i/c/b/h;)Lcom/sleepycat/b/i/e/n;
    //   761: invokevirtual 51	com/sleepycat/b/i/e/n:e	()V
    //   764: aload_0
    //   765: getfield 14	com/sleepycat/b/i/c/b/k:b	Lcom/sleepycat/b/i/c/b/h;
    //   768: invokestatic 434	com/sleepycat/b/i/c/b/h:j	(Lcom/sleepycat/b/i/c/b/h;)Lcom/sleepycat/b/i/c/b/m;
    //   771: astore 5
    //   773: aload_0
    //   774: getfield 14	com/sleepycat/b/i/c/b/k:b	Lcom/sleepycat/b/i/c/b/h;
    //   777: astore 4
    //   779: aload 5
    //   781: getfield 437	com/sleepycat/b/i/c/b/m:d	Ljava/util/Set;
    //   784: astore_1
    //   785: aload_1
    //   786: monitorenter
    //   787: aload 5
    //   789: getfield 266	com/sleepycat/b/i/c/b/m:c	Lcom/sleepycat/b/i/h/af;
    //   792: astore_2
    //   793: aload_2
    //   794: monitorenter
    //   795: aload 5
    //   797: getfield 437	com/sleepycat/b/i/c/b/m:d	Ljava/util/Set;
    //   800: aload 4
    //   802: invokeinterface 442 2 0
    //   807: istore 11
    //   809: aload 4
    //   811: getfield 445	com/sleepycat/b/i/c/b/h:h	Ljava/util/concurrent/atomic/AtomicBoolean;
    //   814: invokevirtual 198	java/util/concurrent/atomic/AtomicBoolean:get	()Z
    //   817: ifeq +212 -> 1029
    //   820: aload_2
    //   821: monitorexit
    //   822: aload_1
    //   823: monitorexit
    //   824: aload_0
    //   825: invokespecial 447	com/sleepycat/b/i/c/b/k:b	()V
    //   828: iconst_0
    //   829: ifeq +683 -> 1512
    //   832: aconst_null
    //   833: athrow
    //   834: iload 9
    //   836: istore 8
    //   838: goto +715 -> 1553
    //   841: aload_1
    //   842: invokevirtual 285	java/lang/Object:getClass	()Ljava/lang/Class;
    //   845: pop
    //   846: new 449	com/sleepycat/b/i/e/ah
    //   849: dup
    //   850: aload_1
    //   851: new 140	java/lang/StringBuilder
    //   854: dup
    //   855: ldc_w 451
    //   858: invokespecial 145	java/lang/StringBuilder:<init>	(Ljava/lang/String;)V
    //   861: iload 9
    //   863: invokevirtual 362	java/lang/StringBuilder:append	(I)Ljava/lang/StringBuilder;
    //   866: ldc_w 453
    //   869: invokevirtual 177	java/lang/StringBuilder:append	(Ljava/lang/String;)Ljava/lang/StringBuilder;
    //   872: getstatic 456	com/sleepycat/b/am:a	Lcom/sleepycat/b/am;
    //   875: invokevirtual 184	java/lang/StringBuilder:append	(Ljava/lang/Object;)Ljava/lang/StringBuilder;
    //   878: ldc_w 458
    //   881: invokevirtual 177	java/lang/StringBuilder:append	(Ljava/lang/String;)Ljava/lang/StringBuilder;
    //   884: iload 10
    //   886: invokevirtual 362	java/lang/StringBuilder:append	(I)Ljava/lang/StringBuilder;
    //   889: ldc_w 460
    //   892: invokevirtual 177	java/lang/StringBuilder:append	(Ljava/lang/String;)Ljava/lang/StringBuilder;
    //   895: aload_2
    //   896: invokevirtual 461	com/sleepycat/b/i/e/ag:d	()Lcom/sleepycat/b/am;
    //   899: invokevirtual 184	java/lang/StringBuilder:append	(Ljava/lang/Object;)Ljava/lang/StringBuilder;
    //   902: invokevirtual 153	java/lang/StringBuilder:toString	()Ljava/lang/String;
    //   905: invokespecial 462	com/sleepycat/b/i/e/ah:<init>	(Lcom/sleepycat/b/i/e/t;Ljava/lang/String;)V
    //   908: astore_2
    //   909: goto -466 -> 443
    //   912: astore_1
    //   913: iconst_0
    //   914: ifeq +548 -> 1462
    //   917: aconst_null
    //   918: athrow
    //   919: invokestatic 367	com/sleepycat/b/i/e/c:a	()I
    //   922: aload 5
    //   924: getfield 343	com/sleepycat/b/i/e/c:e	Lcom/sleepycat/b/i/e/am;
    //   927: invokevirtual 359	com/sleepycat/b/i/e/am:c	()B
    //   930: invokestatic 468	java/lang/Math:min	(II)I
    //   933: istore 8
    //   935: aload_1
    //   936: invokevirtual 285	java/lang/Object:getClass	()Ljava/lang/Class;
    //   939: pop
    //   940: aload_1
    //   941: new 470	com/sleepycat/b/i/e/ab
    //   944: dup
    //   945: aload_1
    //   946: getstatic 456	com/sleepycat/b/am:a	Lcom/sleepycat/b/am;
    //   949: iload 8
    //   951: invokespecial 473	com/sleepycat/b/i/e/ab:<init>	(Lcom/sleepycat/b/i/e/t;Lcom/sleepycat/b/am;I)V
    //   954: aload 5
    //   956: getfield 250	com/sleepycat/b/i/e/c:b	Lcom/sleepycat/b/i/h/o;
    //   959: invokevirtual 297	com/sleepycat/b/i/e/t:a	(Lcom/sleepycat/b/i/h/d;Lcom/sleepycat/b/i/h/o;)V
    //   962: aload 5
    //   964: aload_1
    //   965: invokevirtual 476	com/sleepycat/b/i/e/c:b	(Lcom/sleepycat/b/i/e/t;)V
    //   968: aload 5
    //   970: aload_1
    //   971: invokevirtual 478	com/sleepycat/b/i/e/c:a	(Lcom/sleepycat/b/i/e/t;)V
    //   974: aload 5
    //   976: getfield 236	com/sleepycat/b/i/e/c:f	Ljava/util/logging/Logger;
    //   979: aload 5
    //   981: getfield 239	com/sleepycat/b/i/e/c:a	Lcom/sleepycat/b/i/c/b/aa;
    //   984: getfield 242	com/sleepycat/b/i/c/b/aa:i	Lcom/sleepycat/b/i/c/aj;
    //   987: new 140	java/lang/StringBuilder
    //   990: dup
    //   991: ldc_w 480
    //   994: invokespecial 145	java/lang/StringBuilder:<init>	(Ljava/lang/String;)V
    //   997: aload 5
    //   999: getfield 258	com/sleepycat/b/i/e/c:d	Lcom/sleepycat/b/i/c/b/x;
    //   1002: getfield 174	com/sleepycat/b/i/c/b/x:a	Ljava/lang/String;
    //   1005: invokevirtual 177	java/lang/StringBuilder:append	(Ljava/lang/String;)Ljava/lang/StringBuilder;
    //   1008: ldc_w 482
    //   1011: invokevirtual 177	java/lang/StringBuilder:append	(Ljava/lang/String;)Ljava/lang/StringBuilder;
    //   1014: invokevirtual 153	java/lang/StringBuilder:toString	()Ljava/lang/String;
    //   1017: invokestatic 179	com/sleepycat/b/p/w:c	(Ljava/util/logging/Logger;Lcom/sleepycat/b/c/ad;Ljava/lang/String;)V
    //   1020: goto -510 -> 510
    //   1023: iconst_0
    //   1024: istore 8
    //   1026: goto -460 -> 566
    //   1029: getstatic 485	com/sleepycat/b/i/c/b/m:k	Z
    //   1032: ifne +35 -> 1067
    //   1035: iload 11
    //   1037: ifne +30 -> 1067
    //   1040: new 487	java/lang/AssertionError
    //   1043: dup
    //   1044: invokespecial 489	java/lang/AssertionError:<init>	()V
    //   1047: athrow
    //   1048: astore 4
    //   1050: aload_2
    //   1051: monitorexit
    //   1052: aload 4
    //   1054: athrow
    //   1055: astore_2
    //   1056: aload_1
    //   1057: monitorexit
    //   1058: aload_2
    //   1059: athrow
    //   1060: astore_1
    //   1061: iconst_0
    //   1062: ifeq +408 -> 1470
    //   1065: aconst_null
    //   1066: athrow
    //   1067: aload 4
    //   1069: getfield 491	com/sleepycat/b/i/c/b/h:i	Lcom/sleepycat/b/i/c/b/x;
    //   1072: getfield 174	com/sleepycat/b/i/c/b/x:a	Ljava/lang/String;
    //   1075: astore 6
    //   1077: getstatic 485	com/sleepycat/b/i/c/b/m:k	Z
    //   1080: ifne +25 -> 1105
    //   1083: aload 4
    //   1085: getfield 491	com/sleepycat/b/i/c/b/h:i	Lcom/sleepycat/b/i/c/b/x;
    //   1088: getstatic 492	com/sleepycat/b/i/c/b/x:c	Lcom/sleepycat/b/i/c/b/x;
    //   1091: invokevirtual 493	com/sleepycat/b/i/c/b/x:equals	(Ljava/lang/Object;)Z
    //   1094: ifeq +11 -> 1105
    //   1097: new 487	java/lang/AssertionError
    //   1100: dup
    //   1101: invokespecial 489	java/lang/AssertionError:<init>	()V
    //   1104: athrow
    //   1105: aload 5
    //   1107: getfield 266	com/sleepycat/b/i/c/b/m:c	Lcom/sleepycat/b/i/h/af;
    //   1110: aload 6
    //   1112: invokevirtual 271	com/sleepycat/b/i/h/af:get	(Ljava/lang/Object;)Ljava/lang/Object;
    //   1115: checkcast 34	com/sleepycat/b/i/c/b/h
    //   1118: astore 7
    //   1120: aload 7
    //   1122: ifnull +50 -> 1172
    //   1125: aload 7
    //   1127: getfield 445	com/sleepycat/b/i/c/b/h:h	Ljava/util/concurrent/atomic/AtomicBoolean;
    //   1130: invokevirtual 198	java/util/concurrent/atomic/AtomicBoolean:get	()Z
    //   1133: ifne +39 -> 1172
    //   1136: aload 5
    //   1138: getfield 494	com/sleepycat/b/i/c/b/m:a	Lcom/sleepycat/b/i/c/b/aa;
    //   1141: getfield 242	com/sleepycat/b/i/c/b/aa:i	Lcom/sleepycat/b/i/c/aj;
    //   1144: new 140	java/lang/StringBuilder
    //   1147: dup
    //   1148: invokespecial 495	java/lang/StringBuilder:<init>	()V
    //   1151: aload 4
    //   1153: getfield 491	com/sleepycat/b/i/c/b/h:i	Lcom/sleepycat/b/i/c/b/x;
    //   1156: invokevirtual 184	java/lang/StringBuilder:append	(Ljava/lang/Object;)Ljava/lang/StringBuilder;
    //   1159: ldc_w 497
    //   1162: invokevirtual 177	java/lang/StringBuilder:append	(Ljava/lang/String;)Ljava/lang/StringBuilder;
    //   1165: invokevirtual 153	java/lang/StringBuilder:toString	()Ljava/lang/String;
    //   1168: invokestatic 500	com/sleepycat/b/aa:a	(Lcom/sleepycat/b/c/ad;Ljava/lang/String;)Lcom/sleepycat/b/aa;
    //   1171: athrow
    //   1172: aload 5
    //   1174: getfield 266	com/sleepycat/b/i/c/b/m:c	Lcom/sleepycat/b/i/h/af;
    //   1177: aload 6
    //   1179: aload 4
    //   1181: invokevirtual 504	com/sleepycat/b/i/h/af:put	(Ljava/lang/Object;Ljava/lang/Object;)Ljava/lang/Object;
    //   1184: pop
    //   1185: aload 5
    //   1187: getfield 494	com/sleepycat/b/i/c/b/m:a	Lcom/sleepycat/b/i/c/b/aa;
    //   1190: getfield 507	com/sleepycat/b/i/c/b/aa:q	Lcom/sleepycat/b/i/c/b/u;
    //   1193: astore 5
    //   1195: aload 5
    //   1197: ifnull +88 -> 1285
    //   1200: aload 4
    //   1202: getfield 491	com/sleepycat/b/i/c/b/h:i	Lcom/sleepycat/b/i/c/b/x;
    //   1205: getfield 174	com/sleepycat/b/i/c/b/x:a	Ljava/lang/String;
    //   1208: astore 6
    //   1210: aload 5
    //   1212: getfield 511	com/sleepycat/b/i/c/b/u:a	Ljava/util/Set;
    //   1215: aload 6
    //   1217: invokeinterface 514 2 0
    //   1222: ifeq +63 -> 1285
    //   1225: aload 5
    //   1227: getfield 516	com/sleepycat/b/i/c/b/u:c	Ljava/util/logging/Logger;
    //   1230: aload 5
    //   1232: getfield 518	com/sleepycat/b/i/c/b/u:b	Lcom/sleepycat/b/i/c/b/aa;
    //   1235: getfield 242	com/sleepycat/b/i/c/b/aa:i	Lcom/sleepycat/b/i/c/aj;
    //   1238: new 140	java/lang/StringBuilder
    //   1241: dup
    //   1242: ldc_w 520
    //   1245: invokespecial 145	java/lang/StringBuilder:<init>	(Ljava/lang/String;)V
    //   1248: aload 6
    //   1250: invokevirtual 177	java/lang/StringBuilder:append	(Ljava/lang/String;)Ljava/lang/StringBuilder;
    //   1253: ldc_w 522
    //   1256: invokevirtual 177	java/lang/StringBuilder:append	(Ljava/lang/String;)Ljava/lang/StringBuilder;
    //   1259: invokevirtual 153	java/lang/StringBuilder:toString	()Ljava/lang/String;
    //   1262: invokestatic 179	com/sleepycat/b/p/w:c	(Ljava/util/logging/Logger;Lcom/sleepycat/b/c/ad;Ljava/lang/String;)V
    //   1265: aload 4
    //   1267: aload 5
    //   1269: putfield 524	com/sleepycat/b/i/c/b/h:f	Lcom/sleepycat/b/i/c/b/u;
    //   1272: aload 4
    //   1274: getfield 526	com/sleepycat/b/i/c/b/h:g	Z
    //   1277: ifeq +8 -> 1285
    //   1280: aload 4
    //   1282: invokevirtual 110	com/sleepycat/b/i/c/b/h:a	()V
    //   1285: aload_2
    //   1286: monitorexit
    //   1287: aload_1
    //   1288: monitorexit
    //   1289: goto -465 -> 824
    //   1292: astore_1
    //   1293: aload_0
    //   1294: getfield 14	com/sleepycat/b/i/c/b/k:b	Lcom/sleepycat/b/i/c/b/h;
    //   1297: invokestatic 122	com/sleepycat/b/i/c/b/h:k	(Lcom/sleepycat/b/i/c/b/h;)Ljava/util/logging/Logger;
    //   1300: aload_0
    //   1301: getfield 14	com/sleepycat/b/i/c/b/k:b	Lcom/sleepycat/b/i/c/b/h;
    //   1304: invokestatic 138	com/sleepycat/b/i/c/b/h:l	(Lcom/sleepycat/b/i/c/b/h;)Lcom/sleepycat/b/i/c/aj;
    //   1307: new 140	java/lang/StringBuilder
    //   1310: dup
    //   1311: ldc_w 528
    //   1314: invokespecial 145	java/lang/StringBuilder:<init>	(Ljava/lang/String;)V
    //   1317: aload_1
    //   1318: invokevirtual 529	com/sleepycat/b/i/c/b/i:getMessage	()Ljava/lang/String;
    //   1321: invokevirtual 177	java/lang/StringBuilder:append	(Ljava/lang/String;)Ljava/lang/StringBuilder;
    //   1324: invokevirtual 153	java/lang/StringBuilder:toString	()Ljava/lang/String;
    //   1327: invokestatic 377	com/sleepycat/b/p/w:b	(Ljava/util/logging/Logger;Lcom/sleepycat/b/c/ad;Ljava/lang/String;)V
    //   1330: iconst_0
    //   1331: ifeq +162 -> 1493
    //   1334: aconst_null
    //   1335: athrow
    //   1336: astore_3
    //   1337: aload_0
    //   1338: getfield 14	com/sleepycat/b/i/c/b/k:b	Lcom/sleepycat/b/i/c/b/h;
    //   1341: invokestatic 94	com/sleepycat/b/i/c/b/h:a	(Lcom/sleepycat/b/i/c/b/h;)Lcom/sleepycat/b/i/c/b/aa;
    //   1344: getfield 242	com/sleepycat/b/i/c/b/aa:i	Lcom/sleepycat/b/i/c/aj;
    //   1347: aload_3
    //   1348: invokevirtual 534	com/sleepycat/b/i/c/aj:a	(Ljava/lang/Error;)V
    //   1351: aload_3
    //   1352: ifnull +149 -> 1501
    //   1355: aload_3
    //   1356: athrow
    //   1357: goto +0 -> 1357
    //   1360: astore_2
    //   1361: new 186	com/sleepycat/b/aa
    //   1364: dup
    //   1365: aload_0
    //   1366: getfield 14	com/sleepycat/b/i/c/b/k:b	Lcom/sleepycat/b/i/c/b/h;
    //   1369: invokestatic 94	com/sleepycat/b/i/c/b/h:a	(Lcom/sleepycat/b/i/c/b/h;)Lcom/sleepycat/b/i/c/b/aa;
    //   1372: getfield 242	com/sleepycat/b/i/c/b/aa:i	Lcom/sleepycat/b/i/c/aj;
    //   1375: getstatic 539	com/sleepycat/b/c/ac:j	Lcom/sleepycat/b/c/ac;
    //   1378: aload_2
    //   1379: invokespecial 542	com/sleepycat/b/aa:<init>	(Lcom/sleepycat/b/c/ad;Lcom/sleepycat/b/c/ac;Ljava/lang/Throwable;)V
    //   1382: athrow
    //   1383: astore_1
    //   1384: aload_3
    //   1385: ifnull +56 -> 1441
    //   1388: aload_3
    //   1389: athrow
    //   1390: astore_2
    //   1391: aload_0
    //   1392: getfield 14	com/sleepycat/b/i/c/b/k:b	Lcom/sleepycat/b/i/c/b/h;
    //   1395: invokestatic 122	com/sleepycat/b/i/c/b/h:k	(Lcom/sleepycat/b/i/c/b/h;)Ljava/util/logging/Logger;
    //   1398: aload_0
    //   1399: getfield 14	com/sleepycat/b/i/c/b/k:b	Lcom/sleepycat/b/i/c/b/h;
    //   1402: invokestatic 138	com/sleepycat/b/i/c/b/h:l	(Lcom/sleepycat/b/i/c/b/h;)Lcom/sleepycat/b/i/c/aj;
    //   1405: new 140	java/lang/StringBuilder
    //   1408: dup
    //   1409: ldc_w 544
    //   1412: invokespecial 145	java/lang/StringBuilder:<init>	(Ljava/lang/String;)V
    //   1415: aload_2
    //   1416: invokevirtual 545	java/lang/RuntimeException:getMessage	()Ljava/lang/String;
    //   1419: invokevirtual 177	java/lang/StringBuilder:append	(Ljava/lang/String;)Ljava/lang/StringBuilder;
    //   1422: aload_2
    //   1423: invokestatic 548	com/sleepycat/b/p/w:a	(Ljava/lang/Throwable;)Ljava/lang/String;
    //   1426: invokevirtual 177	java/lang/StringBuilder:append	(Ljava/lang/String;)Ljava/lang/StringBuilder;
    //   1429: invokevirtual 153	java/lang/StringBuilder:toString	()Ljava/lang/String;
    //   1432: invokestatic 550	com/sleepycat/b/p/w:a	(Ljava/util/logging/Logger;Lcom/sleepycat/b/c/ad;Ljava/lang/String;)V
    //   1435: aload_2
    //   1436: athrow
    //   1437: astore_1
    //   1438: goto -54 -> 1384
    //   1441: aload_0
    //   1442: getfield 14	com/sleepycat/b/i/c/b/k:b	Lcom/sleepycat/b/i/c/b/h;
    //   1445: aload_2
    //   1446: invokevirtual 553	com/sleepycat/b/i/c/b/h:a	(Ljava/lang/Exception;)V
    //   1449: aload_1
    //   1450: athrow
    //   1451: aload_0
    //   1452: getfield 14	com/sleepycat/b/i/c/b/k:b	Lcom/sleepycat/b/i/c/b/h;
    //   1455: astore_2
    //   1456: aload_2
    //   1457: aload_1
    //   1458: invokevirtual 553	com/sleepycat/b/i/c/b/h:a	(Ljava/lang/Exception;)V
    //   1461: return
    //   1462: aload_0
    //   1463: getfield 14	com/sleepycat/b/i/c/b/k:b	Lcom/sleepycat/b/i/c/b/h;
    //   1466: astore_2
    //   1467: goto -11 -> 1456
    //   1470: aload_0
    //   1471: getfield 14	com/sleepycat/b/i/c/b/k:b	Lcom/sleepycat/b/i/c/b/h;
    //   1474: astore_2
    //   1475: goto -19 -> 1456
    //   1478: astore_1
    //   1479: iconst_0
    //   1480: ifeq +5 -> 1485
    //   1483: aconst_null
    //   1484: athrow
    //   1485: aload_0
    //   1486: getfield 14	com/sleepycat/b/i/c/b/k:b	Lcom/sleepycat/b/i/c/b/h;
    //   1489: astore_2
    //   1490: goto -34 -> 1456
    //   1493: aload_0
    //   1494: getfield 14	com/sleepycat/b/i/c/b/k:b	Lcom/sleepycat/b/i/c/b/h;
    //   1497: astore_2
    //   1498: goto -42 -> 1456
    //   1501: aload_0
    //   1502: getfield 14	com/sleepycat/b/i/c/b/k:b	Lcom/sleepycat/b/i/c/b/h;
    //   1505: aconst_null
    //   1506: invokevirtual 553	com/sleepycat/b/i/c/b/h:a	(Ljava/lang/Exception;)V
    //   1509: goto -152 -> 1357
    //   1512: aload_0
    //   1513: getfield 14	com/sleepycat/b/i/c/b/k:b	Lcom/sleepycat/b/i/c/b/h;
    //   1516: aconst_null
    //   1517: invokevirtual 553	com/sleepycat/b/i/c/b/h:a	(Ljava/lang/Exception;)V
    //   1520: return
    //   1521: astore_1
    //   1522: aconst_null
    //   1523: astore_2
    //   1524: goto -140 -> 1384
    //   1527: astore 4
    //   1529: aload_1
    //   1530: astore_2
    //   1531: aload 4
    //   1533: astore_1
    //   1534: goto -150 -> 1384
    //   1537: astore 4
    //   1539: aload_1
    //   1540: astore_2
    //   1541: aload 4
    //   1543: astore_1
    //   1544: goto -160 -> 1384
    //   1547: astore_1
    //   1548: aconst_null
    //   1549: astore_2
    //   1550: goto -166 -> 1384
    //   1553: iload 10
    //   1555: iload 8
    //   1557: if_icmplt -716 -> 841
    //   1560: aconst_null
    //   1561: astore_2
    //   1562: goto -1119 -> 443
    // Local variable table:
    //   start	length	slot	name	signature
    //   0	1565	0	this	k
    //   64	160	1	localObject1	Object
    //   234	29	1	locale	com.sleepycat.b.i.e.e
    //   282	569	1	localObject2	Object
    //   912	145	1	localIOException	java.io.IOException
    //   1060	228	1	localo	com.sleepycat.b.i.e.o
    //   1292	26	1	locali	i
    //   1383	1	1	localObject3	Object
    //   1437	21	1	localException	Exception
    //   1478	1	1	localInterruptedException	InterruptedException
    //   1521	9	1	localObject4	Object
    //   1533	11	1	localObject5	Object
    //   1547	1	1	localObject6	Object
    //   51	1000	2	localObject7	Object
    //   1055	231	2	localObject8	Object
    //   1360	19	2	localc	com.sleepycat.b.g.c
    //   1390	56	2	localRuntimeException	RuntimeException
    //   1455	107	2	localObject9	Object
    //   1	1	3	localObject10	Object
    //   1336	53	3	localError	Error
    //   82	728	4	localObject11	Object
    //   1048	233	4	localObject12	Object
    //   1527	5	4	localObject13	Object
    //   1537	5	4	localObject14	Object
    //   23	1245	5	localObject15	Object
    //   92	1157	6	str	String
    //   1118	8	7	localh	h
    //   266	1292	8	i	int
    //   425	437	9	j	int
    //   420	1138	10	k	int
    //   807	229	11	bool	boolean
    // Exception table:
    //   from	to	target	type
    //   2	131	234	com/sleepycat/b/i/e/e
    //   131	234	234	com/sleepycat/b/i/e/e
    //   262	280	234	com/sleepycat/b/i/e/e
    //   290	427	234	com/sleepycat/b/i/e/e
    //   447	510	234	com/sleepycat/b/i/e/e
    //   510	566	234	com/sleepycat/b/i/e/e
    //   566	705	234	com/sleepycat/b/i/e/e
    //   705	787	234	com/sleepycat/b/i/e/e
    //   824	828	234	com/sleepycat/b/i/e/e
    //   841	909	234	com/sleepycat/b/i/e/e
    //   919	1020	234	com/sleepycat/b/i/e/e
    //   1058	1060	234	com/sleepycat/b/i/e/e
    //   2	131	912	java/io/IOException
    //   131	234	912	java/io/IOException
    //   262	280	912	java/io/IOException
    //   290	427	912	java/io/IOException
    //   447	510	912	java/io/IOException
    //   510	566	912	java/io/IOException
    //   566	705	912	java/io/IOException
    //   705	787	912	java/io/IOException
    //   824	828	912	java/io/IOException
    //   841	909	912	java/io/IOException
    //   919	1020	912	java/io/IOException
    //   1058	1060	912	java/io/IOException
    //   795	822	1048	finally
    //   1029	1035	1048	finally
    //   1040	1048	1048	finally
    //   1050	1052	1048	finally
    //   1067	1105	1048	finally
    //   1105	1120	1048	finally
    //   1125	1172	1048	finally
    //   1172	1195	1048	finally
    //   1200	1285	1048	finally
    //   1285	1287	1048	finally
    //   787	795	1055	finally
    //   822	824	1055	finally
    //   1052	1055	1055	finally
    //   1056	1058	1055	finally
    //   1287	1289	1055	finally
    //   2	131	1060	com/sleepycat/b/i/e/o
    //   131	234	1060	com/sleepycat/b/i/e/o
    //   262	280	1060	com/sleepycat/b/i/e/o
    //   290	427	1060	com/sleepycat/b/i/e/o
    //   447	510	1060	com/sleepycat/b/i/e/o
    //   510	566	1060	com/sleepycat/b/i/e/o
    //   566	705	1060	com/sleepycat/b/i/e/o
    //   705	787	1060	com/sleepycat/b/i/e/o
    //   824	828	1060	com/sleepycat/b/i/e/o
    //   841	909	1060	com/sleepycat/b/i/e/o
    //   919	1020	1060	com/sleepycat/b/i/e/o
    //   1058	1060	1060	com/sleepycat/b/i/e/o
    //   2	131	1292	com/sleepycat/b/i/c/b/i
    //   131	234	1292	com/sleepycat/b/i/c/b/i
    //   262	280	1292	com/sleepycat/b/i/c/b/i
    //   290	427	1292	com/sleepycat/b/i/c/b/i
    //   447	510	1292	com/sleepycat/b/i/c/b/i
    //   510	566	1292	com/sleepycat/b/i/c/b/i
    //   566	705	1292	com/sleepycat/b/i/c/b/i
    //   705	787	1292	com/sleepycat/b/i/c/b/i
    //   824	828	1292	com/sleepycat/b/i/c/b/i
    //   841	909	1292	com/sleepycat/b/i/c/b/i
    //   919	1020	1292	com/sleepycat/b/i/c/b/i
    //   1058	1060	1292	com/sleepycat/b/i/c/b/i
    //   2	131	1336	java/lang/Error
    //   131	234	1336	java/lang/Error
    //   262	280	1336	java/lang/Error
    //   290	427	1336	java/lang/Error
    //   447	510	1336	java/lang/Error
    //   510	566	1336	java/lang/Error
    //   566	705	1336	java/lang/Error
    //   705	787	1336	java/lang/Error
    //   824	828	1336	java/lang/Error
    //   841	909	1336	java/lang/Error
    //   919	1020	1336	java/lang/Error
    //   1058	1060	1336	java/lang/Error
    //   2	131	1360	com/sleepycat/b/g/c
    //   131	234	1360	com/sleepycat/b/g/c
    //   262	280	1360	com/sleepycat/b/g/c
    //   290	427	1360	com/sleepycat/b/g/c
    //   447	510	1360	com/sleepycat/b/g/c
    //   510	566	1360	com/sleepycat/b/g/c
    //   566	705	1360	com/sleepycat/b/g/c
    //   705	787	1360	com/sleepycat/b/g/c
    //   824	828	1360	com/sleepycat/b/g/c
    //   841	909	1360	com/sleepycat/b/g/c
    //   919	1020	1360	com/sleepycat/b/g/c
    //   1058	1060	1360	com/sleepycat/b/g/c
    //   1361	1383	1383	finally
    //   2	131	1390	java/lang/RuntimeException
    //   131	234	1390	java/lang/RuntimeException
    //   262	280	1390	java/lang/RuntimeException
    //   290	427	1390	java/lang/RuntimeException
    //   447	510	1390	java/lang/RuntimeException
    //   510	566	1390	java/lang/RuntimeException
    //   566	705	1390	java/lang/RuntimeException
    //   705	787	1390	java/lang/RuntimeException
    //   824	828	1390	java/lang/RuntimeException
    //   841	909	1390	java/lang/RuntimeException
    //   919	1020	1390	java/lang/RuntimeException
    //   1058	1060	1390	java/lang/RuntimeException
    //   1391	1437	1437	finally
    //   2	131	1478	java/lang/InterruptedException
    //   131	234	1478	java/lang/InterruptedException
    //   262	280	1478	java/lang/InterruptedException
    //   290	427	1478	java/lang/InterruptedException
    //   447	510	1478	java/lang/InterruptedException
    //   510	566	1478	java/lang/InterruptedException
    //   566	705	1478	java/lang/InterruptedException
    //   705	787	1478	java/lang/InterruptedException
    //   824	828	1478	java/lang/InterruptedException
    //   841	909	1478	java/lang/InterruptedException
    //   919	1020	1478	java/lang/InterruptedException
    //   1058	1060	1478	java/lang/InterruptedException
    //   2	131	1521	finally
    //   131	234	1521	finally
    //   262	280	1521	finally
    //   290	427	1521	finally
    //   447	510	1521	finally
    //   510	566	1521	finally
    //   566	705	1521	finally
    //   705	787	1521	finally
    //   824	828	1521	finally
    //   841	909	1521	finally
    //   919	1020	1521	finally
    //   1058	1060	1521	finally
    //   235	256	1527	finally
    //   1293	1330	1537	finally
    //   1337	1351	1547	finally
  }
}


/* Location:              E:\apk\xueqiu2\classes-dex2jar.jar!\com\sleepycat\b\i\c\b\k.class
 * Java compiler version: 6 (50.0)
 * JD-Core Version:       0.7.1
 */