package com.sleepycat.b.i.c.b;

import com.sleepycat.b.c.ad;
import com.sleepycat.b.g.af;
import com.sleepycat.b.i.e.s;
import com.sleepycat.b.i.e.t;
import com.sleepycat.b.i.h.d;
import com.sleepycat.b.i.h.q;
import com.sleepycat.b.p.ai;
import com.sleepycat.b.p.au;
import com.sleepycat.b.p.w;
import java.util.logging.Logger;

final class l
  extends com.sleepycat.b.p.aj
{
  t a = null;
  private long d = 0L;
  private long e = 0L;
  private long f = 0L;
  private final com.sleepycat.b.i.c.aj g;
  private final boolean h;
  private final int i;
  private final com.sleepycat.b.i.h.n j;
  private final com.sleepycat.b.p.an k;
  
  static
  {
    if (!h.class.desiredAssertionStatus()) {}
    for (boolean bool = true;; bool = false)
    {
      b = bool;
      return;
    }
  }
  
  l(h paramh, com.sleepycat.b.i.c.aj paramaj)
  {
    super(paramaj, new j(paramh, (byte)0), "Feeder Output");
    this.g = paramaj;
    paramaj = h.a(paramh).i.u;
    this.h = paramaj.a(com.sleepycat.b.i.c.an.X);
    this.i = paramaj.a(com.sleepycat.b.i.c.an.V);
    if (h.j(paramh) != null)
    {
      this.j = h.j(paramh).i;
      this.k = h.j(paramh).j;
      return;
    }
    paramh = new ai("FeederManager", "A feeder is a replication stream connection between a master and replica nodes.");
    this.j = new com.sleepycat.b.i.h.n(paramh, n.c);
    this.k = new com.sleepycat.b.p.an(paramh, n.d);
  }
  
  private void a(d paramd, s params)
  {
    if (h.b() == 0L)
    {
      params = af.a(params.d.b);
      if ((!params.d()) || (!params.N.c)) {
        h.c();
      }
    }
    else
    {
      return;
    }
    w.c(h.k(this.c), this.g, "Initiating message spray: " + paramd);
    for (;;)
    {
      this.a.a(paramd, h.b(this.c));
    }
  }
  
  private void b()
  {
    long l1 = System.currentTimeMillis();
    if (l1 - this.d <= h.p(this.c)) {}
    long l2;
    do
    {
      return;
      au localau = h.a(this.c).g();
      t localt1 = this.a;
      t localt2 = this.a;
      localt2.getClass();
      localt1.a(new com.sleepycat.b.i.e.ae(localt2, l1, localau.c), h.b(this.c));
      this.d = l1;
      l1 = localau.c;
      l2 = h.f(this.c).c;
    } while (!this.j.a(l1 - l2));
    this.k.a = h.c(this.c).a;
  }
  
  protected final Logger a()
  {
    return h.k(this.c);
  }
  
  protected final int c()
  {
    q.a(h.b(this.c));
    return h.a(this.c).d() * 4;
  }
  
  /* Error */
  public final void run()
  {
    // Byte code:
    //   0: aload_0
    //   1: aload_0
    //   2: getfield 40	com/sleepycat/b/i/c/b/l:c	Lcom/sleepycat/b/i/c/b/h;
    //   5: invokestatic 63	com/sleepycat/b/i/c/b/h:a	(Lcom/sleepycat/b/i/c/b/h;)Lcom/sleepycat/b/i/c/b/aa;
    //   8: aload_0
    //   9: getfield 40	com/sleepycat/b/i/c/b/l:c	Lcom/sleepycat/b/i/c/b/h;
    //   12: invokestatic 259	com/sleepycat/b/i/c/b/h:n	(Lcom/sleepycat/b/i/c/b/h;)I
    //   15: aload_0
    //   16: getfield 40	com/sleepycat/b/i/c/b/l:c	Lcom/sleepycat/b/i/c/b/h;
    //   19: invokestatic 262	com/sleepycat/b/i/c/b/h:o	(Lcom/sleepycat/b/i/c/b/h;)I
    //   22: invokestatic 265	com/sleepycat/b/i/e/t:a	(Lcom/sleepycat/b/i/c/b/aa;II)Lcom/sleepycat/b/i/e/t;
    //   25: putfield 54	com/sleepycat/b/i/c/b/l:a	Lcom/sleepycat/b/i/e/t;
    //   28: invokestatic 271	java/lang/Thread:currentThread	()Ljava/lang/Thread;
    //   31: new 168	java/lang/StringBuilder
    //   34: dup
    //   35: ldc_w 273
    //   38: invokespecial 173	java/lang/StringBuilder:<init>	(Ljava/lang/String;)V
    //   41: aload_0
    //   42: getfield 40	com/sleepycat/b/i/c/b/l:c	Lcom/sleepycat/b/i/c/b/h;
    //   45: getfield 276	com/sleepycat/b/i/c/b/h:i	Lcom/sleepycat/b/i/c/b/x;
    //   48: getfield 235	com/sleepycat/b/i/c/b/x:a	Ljava/lang/String;
    //   51: invokevirtual 279	java/lang/StringBuilder:append	(Ljava/lang/String;)Ljava/lang/StringBuilder;
    //   54: invokevirtual 181	java/lang/StringBuilder:toString	()Ljava/lang/String;
    //   57: invokevirtual 282	java/lang/Thread:setName	(Ljava/lang/String;)V
    //   60: aload_0
    //   61: getfield 40	com/sleepycat/b/i/c/b/l:c	Lcom/sleepycat/b/i/c/b/h;
    //   64: invokestatic 98	com/sleepycat/b/i/c/b/h:j	(Lcom/sleepycat/b/i/c/b/h;)Lcom/sleepycat/b/i/c/b/m;
    //   67: getfield 284	com/sleepycat/b/i/c/b/m:e	I
    //   70: istore 5
    //   72: iload 5
    //   74: ifle +41 -> 115
    //   77: aload_0
    //   78: getfield 40	com/sleepycat/b/i/c/b/l:c	Lcom/sleepycat/b/i/c/b/h;
    //   81: invokestatic 166	com/sleepycat/b/i/c/b/h:k	(Lcom/sleepycat/b/i/c/b/h;)Ljava/util/logging/Logger;
    //   84: aload_0
    //   85: getfield 60	com/sleepycat/b/i/c/b/l:g	Lcom/sleepycat/b/i/c/aj;
    //   88: new 168	java/lang/StringBuilder
    //   91: dup
    //   92: ldc_w 286
    //   95: invokespecial 173	java/lang/StringBuilder:<init>	(Ljava/lang/String;)V
    //   98: iload 5
    //   100: invokevirtual 289	java/lang/StringBuilder:append	(I)Ljava/lang/StringBuilder;
    //   103: ldc_w 291
    //   106: invokevirtual 279	java/lang/StringBuilder:append	(Ljava/lang/String;)Ljava/lang/StringBuilder;
    //   109: invokevirtual 181	java/lang/StringBuilder:toString	()Ljava/lang/String;
    //   112: invokestatic 186	com/sleepycat/b/p/w:c	(Ljava/util/logging/Logger;Lcom/sleepycat/b/c/ad;Ljava/lang/String;)V
    //   115: aload_0
    //   116: getfield 40	com/sleepycat/b/i/c/b/l:c	Lcom/sleepycat/b/i/c/b/h;
    //   119: invokestatic 63	com/sleepycat/b/i/c/b/h:a	(Lcom/sleepycat/b/i/c/b/h;)Lcom/sleepycat/b/i/c/b/aa;
    //   122: getfield 67	com/sleepycat/b/i/c/b/aa:i	Lcom/sleepycat/b/i/c/aj;
    //   125: getfield 297	com/sleepycat/b/i/c/aj:aj	Lcom/sleepycat/b/i/i/f;
    //   128: getfield 302	com/sleepycat/b/i/i/f:h	Lcom/sleepycat/b/i/i/p;
    //   131: invokevirtual 307	com/sleepycat/b/i/i/p:b	()Lcom/sleepycat/b/i/i/m;
    //   134: astore_1
    //   135: aload_0
    //   136: getfield 40	com/sleepycat/b/i/c/b/l:c	Lcom/sleepycat/b/i/c/b/h;
    //   139: invokestatic 166	com/sleepycat/b/i/c/b/h:k	(Lcom/sleepycat/b/i/c/b/h;)Ljava/util/logging/Logger;
    //   142: aload_0
    //   143: getfield 60	com/sleepycat/b/i/c/b/l:g	Lcom/sleepycat/b/i/c/aj;
    //   146: ldc_w 309
    //   149: iconst_5
    //   150: anewarray 208	java/lang/Object
    //   153: dup
    //   154: iconst_0
    //   155: aload_0
    //   156: getfield 40	com/sleepycat/b/i/c/b/l:c	Lcom/sleepycat/b/i/c/b/h;
    //   159: invokestatic 230	com/sleepycat/b/i/c/b/h:c	(Lcom/sleepycat/b/i/c/b/h;)Lcom/sleepycat/b/i/c/b/x;
    //   162: getfield 235	com/sleepycat/b/i/c/b/x:a	Ljava/lang/String;
    //   165: aastore
    //   166: dup
    //   167: iconst_1
    //   168: aload_0
    //   169: getfield 40	com/sleepycat/b/i/c/b/l:c	Lcom/sleepycat/b/i/c/b/h;
    //   172: invokestatic 224	com/sleepycat/b/i/c/b/h:f	(Lcom/sleepycat/b/i/c/b/h;)Lcom/sleepycat/b/p/au;
    //   175: getfield 218	com/sleepycat/b/p/au:c	J
    //   178: invokestatic 315	java/lang/Long:valueOf	(J)Ljava/lang/Long;
    //   181: aastore
    //   182: dup
    //   183: iconst_2
    //   184: aload_1
    //   185: getfield 320	com/sleepycat/b/i/i/m:c	Lcom/sleepycat/b/p/au;
    //   188: getfield 218	com/sleepycat/b/p/au:c	J
    //   191: invokestatic 315	java/lang/Long:valueOf	(J)Ljava/lang/Long;
    //   194: aastore
    //   195: dup
    //   196: iconst_3
    //   197: aload_1
    //   198: getfield 320	com/sleepycat/b/i/i/m:c	Lcom/sleepycat/b/p/au;
    //   201: getfield 218	com/sleepycat/b/p/au:c	J
    //   204: aload_0
    //   205: getfield 40	com/sleepycat/b/i/c/b/l:c	Lcom/sleepycat/b/i/c/b/h;
    //   208: invokestatic 224	com/sleepycat/b/i/c/b/h:f	(Lcom/sleepycat/b/i/c/b/h;)Lcom/sleepycat/b/p/au;
    //   211: getfield 218	com/sleepycat/b/p/au:c	J
    //   214: lsub
    //   215: invokestatic 315	java/lang/Long:valueOf	(J)Ljava/lang/Long;
    //   218: aastore
    //   219: dup
    //   220: iconst_4
    //   221: aload_0
    //   222: getfield 40	com/sleepycat/b/i/c/b/l:c	Lcom/sleepycat/b/i/c/b/h;
    //   225: invokestatic 189	com/sleepycat/b/i/c/b/h:b	(Lcom/sleepycat/b/i/c/b/h;)Lcom/sleepycat/b/i/h/p;
    //   228: aastore
    //   229: invokestatic 326	java/lang/String:format	(Ljava/lang/String;[Ljava/lang/Object;)Ljava/lang/String;
    //   232: invokestatic 186	com/sleepycat/b/p/w:c	(Ljava/util/logging/Logger;Lcom/sleepycat/b/c/ad;Ljava/lang/String;)V
    //   235: aload_0
    //   236: invokespecial 328	com/sleepycat/b/i/c/b/l:b	()V
    //   239: aload_0
    //   240: getfield 40	com/sleepycat/b/i/c/b/l:c	Lcom/sleepycat/b/i/c/b/h;
    //   243: invokestatic 63	com/sleepycat/b/i/c/b/h:a	(Lcom/sleepycat/b/i/c/b/h;)Lcom/sleepycat/b/i/c/b/aa;
    //   246: getfield 67	com/sleepycat/b/i/c/b/aa:i	Lcom/sleepycat/b/i/c/aj;
    //   249: getfield 73	com/sleepycat/b/c/ad:u	Lcom/sleepycat/b/c/m;
    //   252: getstatic 331	com/sleepycat/b/i/c/an:U	Lcom/sleepycat/b/b/c;
    //   255: invokevirtual 93	com/sleepycat/b/c/m:a	(Lcom/sleepycat/b/b/c;)I
    //   258: istore 4
    //   260: aload_0
    //   261: getfield 40	com/sleepycat/b/i/c/b/l:c	Lcom/sleepycat/b/i/c/b/h;
    //   264: invokestatic 189	com/sleepycat/b/i/c/b/h:b	(Lcom/sleepycat/b/i/c/b/h;)Lcom/sleepycat/b/i/h/p;
    //   267: iload 4
    //   269: invokevirtual 336	com/sleepycat/b/i/h/p:a	(I)V
    //   272: aload_0
    //   273: getfield 40	com/sleepycat/b/i/c/b/l:c	Lcom/sleepycat/b/i/c/b/h;
    //   276: invokestatic 340	com/sleepycat/b/i/c/b/h:m	(Lcom/sleepycat/b/i/c/b/h;)Ljava/util/concurrent/atomic/AtomicBoolean;
    //   279: invokevirtual 345	java/util/concurrent/atomic/AtomicBoolean:get	()Z
    //   282: ifne +122 -> 404
    //   285: iconst_0
    //   286: istore 4
    //   288: iload 4
    //   290: ifne +1289 -> 1579
    //   293: aload_0
    //   294: getfield 40	com/sleepycat/b/i/c/b/l:c	Lcom/sleepycat/b/i/c/b/h;
    //   297: invokestatic 224	com/sleepycat/b/i/c/b/h:f	(Lcom/sleepycat/b/i/c/b/h;)Lcom/sleepycat/b/p/au;
    //   300: aload_0
    //   301: getfield 40	com/sleepycat/b/i/c/b/l:c	Lcom/sleepycat/b/i/c/b/h;
    //   304: invokestatic 63	com/sleepycat/b/i/c/b/h:a	(Lcom/sleepycat/b/i/c/b/h;)Lcom/sleepycat/b/i/c/b/aa;
    //   307: invokevirtual 206	com/sleepycat/b/i/c/b/aa:g	()Lcom/sleepycat/b/p/au;
    //   310: invokevirtual 348	com/sleepycat/b/p/au:b	(Lcom/sleepycat/b/p/au;)I
    //   313: iflt +25 -> 338
    //   316: aload_0
    //   317: getfield 40	com/sleepycat/b/i/c/b/l:c	Lcom/sleepycat/b/i/c/b/h;
    //   320: invokestatic 63	com/sleepycat/b/i/c/b/h:a	(Lcom/sleepycat/b/i/c/b/h;)Lcom/sleepycat/b/i/c/b/aa;
    //   323: getfield 352	com/sleepycat/b/i/c/b/aa:A	Lcom/sleepycat/b/i/a/a;
    //   326: astore_1
    //   327: aload_1
    //   328: monitorenter
    //   329: aload_1
    //   330: getfield 356	com/sleepycat/b/i/a/a:a	Z
    //   333: ifne +255 -> 588
    //   336: aload_1
    //   337: monitorexit
    //   338: aload_0
    //   339: getfield 40	com/sleepycat/b/i/c/b/l:c	Lcom/sleepycat/b/i/c/b/h;
    //   342: invokestatic 359	com/sleepycat/b/i/c/b/h:g	(Lcom/sleepycat/b/i/c/b/h;)Lcom/sleepycat/b/i/e/f;
    //   345: aload_0
    //   346: getfield 40	com/sleepycat/b/i/c/b/l:c	Lcom/sleepycat/b/i/c/b/h;
    //   349: invokestatic 224	com/sleepycat/b/i/c/b/h:f	(Lcom/sleepycat/b/i/c/b/h;)Lcom/sleepycat/b/p/au;
    //   352: aload_0
    //   353: getfield 40	com/sleepycat/b/i/c/b/l:c	Lcom/sleepycat/b/i/c/b/h;
    //   356: invokestatic 203	com/sleepycat/b/i/c/b/h:p	(Lcom/sleepycat/b/i/c/b/h;)I
    //   359: invokeinterface 364 3 0
    //   364: astore_2
    //   365: aload_0
    //   366: getfield 40	com/sleepycat/b/i/c/b/l:c	Lcom/sleepycat/b/i/c/b/h;
    //   369: invokestatic 367	com/sleepycat/b/i/c/b/h:i	(Lcom/sleepycat/b/i/c/b/h;)Lcom/sleepycat/b/i/e/n;
    //   372: invokevirtual 371	com/sleepycat/b/i/e/n:e	()V
    //   375: aload_2
    //   376: ifnonnull +255 -> 631
    //   379: aload_0
    //   380: invokespecial 328	com/sleepycat/b/i/c/b/l:b	()V
    //   383: iload 5
    //   385: ifle -113 -> 272
    //   388: iload 5
    //   390: i2l
    //   391: invokestatic 375	java/lang/Thread:sleep	(J)V
    //   394: goto -122 -> 272
    //   397: astore_1
    //   398: iconst_0
    //   399: ifeq +842 -> 1241
    //   402: aconst_null
    //   403: athrow
    //   404: aload_0
    //   405: getfield 40	com/sleepycat/b/i/c/b/l:c	Lcom/sleepycat/b/i/c/b/h;
    //   408: invokestatic 63	com/sleepycat/b/i/c/b/h:a	(Lcom/sleepycat/b/i/c/b/h;)Lcom/sleepycat/b/i/c/b/aa;
    //   411: getfield 378	com/sleepycat/b/i/c/b/aa:s	J
    //   414: lconst_0
    //   415: lcmp
    //   416: iflt +166 -> 582
    //   419: aload_0
    //   420: getfield 58	com/sleepycat/b/i/c/b/l:f	J
    //   423: lconst_0
    //   424: lcmp
    //   425: ifne +10 -> 435
    //   428: aload_0
    //   429: invokestatic 199	java/lang/System:currentTimeMillis	()J
    //   432: putfield 58	com/sleepycat/b/i/c/b/l:f	J
    //   435: invokestatic 199	java/lang/System:currentTimeMillis	()J
    //   438: aload_0
    //   439: getfield 58	com/sleepycat/b/i/c/b/l:f	J
    //   442: lsub
    //   443: aload_0
    //   444: getfield 40	com/sleepycat/b/i/c/b/l:c	Lcom/sleepycat/b/i/c/b/h;
    //   447: invokestatic 63	com/sleepycat/b/i/c/b/h:a	(Lcom/sleepycat/b/i/c/b/h;)Lcom/sleepycat/b/i/c/b/aa;
    //   450: getfield 378	com/sleepycat/b/i/c/b/aa:s	J
    //   453: lcmp
    //   454: ifle +1221 -> 1675
    //   457: iconst_1
    //   458: istore 4
    //   460: iload 4
    //   462: ifne +32 -> 494
    //   465: aload_0
    //   466: getfield 40	com/sleepycat/b/i/c/b/l:c	Lcom/sleepycat/b/i/c/b/h;
    //   469: invokestatic 224	com/sleepycat/b/i/c/b/h:f	(Lcom/sleepycat/b/i/c/b/h;)Lcom/sleepycat/b/p/au;
    //   472: aload_0
    //   473: getfield 40	com/sleepycat/b/i/c/b/l:c	Lcom/sleepycat/b/i/c/b/h;
    //   476: invokestatic 63	com/sleepycat/b/i/c/b/h:a	(Lcom/sleepycat/b/i/c/b/h;)Lcom/sleepycat/b/i/c/b/aa;
    //   479: invokevirtual 206	com/sleepycat/b/i/c/b/aa:g	()Lcom/sleepycat/b/p/au;
    //   482: invokevirtual 348	com/sleepycat/b/p/au:b	(Lcom/sleepycat/b/p/au;)I
    //   485: ifge +9 -> 494
    //   488: iconst_0
    //   489: istore 4
    //   491: goto -203 -> 288
    //   494: aload_0
    //   495: getfield 54	com/sleepycat/b/i/c/b/l:a	Lcom/sleepycat/b/i/e/t;
    //   498: astore_1
    //   499: aload_0
    //   500: getfield 54	com/sleepycat/b/i/c/b/l:a	Lcom/sleepycat/b/i/e/t;
    //   503: astore_2
    //   504: aload_2
    //   505: invokevirtual 212	java/lang/Object:getClass	()Ljava/lang/Class;
    //   508: pop
    //   509: aload_1
    //   510: new 380	com/sleepycat/b/i/e/as
    //   513: dup
    //   514: aload_2
    //   515: aload_0
    //   516: getfield 58	com/sleepycat/b/i/c/b/l:f	J
    //   519: invokespecial 383	com/sleepycat/b/i/e/as:<init>	(Lcom/sleepycat/b/i/e/t;J)V
    //   522: aload_0
    //   523: getfield 40	com/sleepycat/b/i/c/b/l:c	Lcom/sleepycat/b/i/c/b/h;
    //   526: invokestatic 189	com/sleepycat/b/i/c/b/h:b	(Lcom/sleepycat/b/i/c/b/h;)Lcom/sleepycat/b/i/h/p;
    //   529: invokevirtual 194	com/sleepycat/b/i/e/t:a	(Lcom/sleepycat/b/i/h/d;Lcom/sleepycat/b/i/h/o;)V
    //   532: ldc_w 385
    //   535: iconst_2
    //   536: anewarray 208	java/lang/Object
    //   539: dup
    //   540: iconst_0
    //   541: aload_0
    //   542: getfield 40	com/sleepycat/b/i/c/b/l:c	Lcom/sleepycat/b/i/c/b/h;
    //   545: invokestatic 230	com/sleepycat/b/i/c/b/h:c	(Lcom/sleepycat/b/i/c/b/h;)Lcom/sleepycat/b/i/c/b/x;
    //   548: aastore
    //   549: dup
    //   550: iconst_1
    //   551: invokestatic 199	java/lang/System:currentTimeMillis	()J
    //   554: aload_0
    //   555: getfield 58	com/sleepycat/b/i/c/b/l:f	J
    //   558: lsub
    //   559: invokestatic 315	java/lang/Long:valueOf	(J)Ljava/lang/Long;
    //   562: aastore
    //   563: invokestatic 326	java/lang/String:format	(Ljava/lang/String;[Ljava/lang/Object;)Ljava/lang/String;
    //   566: astore_1
    //   567: aload_0
    //   568: getfield 40	com/sleepycat/b/i/c/b/l:c	Lcom/sleepycat/b/i/c/b/h;
    //   571: invokestatic 166	com/sleepycat/b/i/c/b/h:k	(Lcom/sleepycat/b/i/c/b/h;)Ljava/util/logging/Logger;
    //   574: aload_0
    //   575: getfield 60	com/sleepycat/b/i/c/b/l:g	Lcom/sleepycat/b/i/c/aj;
    //   578: aload_1
    //   579: invokestatic 186	com/sleepycat/b/p/w:c	(Ljava/util/logging/Logger;Lcom/sleepycat/b/c/ad;Ljava/lang/String;)V
    //   582: iconst_1
    //   583: istore 4
    //   585: goto -297 -> 288
    //   588: aload_1
    //   589: iconst_0
    //   590: putfield 356	com/sleepycat/b/i/a/a:a	Z
    //   593: aload_1
    //   594: monitorexit
    //   595: aload_1
    //   596: getfield 388	com/sleepycat/b/i/a/a:d	Ljava/util/logging/Logger;
    //   599: aload_1
    //   600: getfield 390	com/sleepycat/b/i/a/a:c	Lcom/sleepycat/b/i/c/aj;
    //   603: ldc_w 392
    //   606: invokestatic 186	com/sleepycat/b/p/w:c	(Ljava/util/logging/Logger;Lcom/sleepycat/b/c/ad;Ljava/lang/String;)V
    //   609: goto -271 -> 338
    //   612: astore_1
    //   613: iconst_0
    //   614: ifeq +713 -> 1327
    //   617: aconst_null
    //   618: athrow
    //   619: astore_2
    //   620: aload_1
    //   621: monitorexit
    //   622: aload_2
    //   623: athrow
    //   624: astore_1
    //   625: iconst_0
    //   626: ifeq +784 -> 1410
    //   629: aconst_null
    //   630: athrow
    //   631: aload_2
    //   632: invokevirtual 393	com/sleepycat/b/i/e/s:b	()J
    //   635: lstore 8
    //   637: lload 8
    //   639: lconst_0
    //   640: lcmp
    //   641: ifne +139 -> 780
    //   644: aload_0
    //   645: getfield 54	com/sleepycat/b/i/c/b/l:a	Lcom/sleepycat/b/i/e/t;
    //   648: astore_1
    //   649: aload_1
    //   650: invokevirtual 212	java/lang/Object:getClass	()Ljava/lang/Class;
    //   653: pop
    //   654: new 395	com/sleepycat/b/i/e/y
    //   657: dup
    //   658: aload_1
    //   659: aload_2
    //   660: invokespecial 398	com/sleepycat/b/i/e/y:<init>	(Lcom/sleepycat/b/i/e/t;Lcom/sleepycat/b/i/e/s;)V
    //   663: astore_1
    //   664: aload_2
    //   665: getfield 141	com/sleepycat/b/i/e/s:d	Lcom/sleepycat/b/g/ae;
    //   668: getfield 400	com/sleepycat/b/g/ae:e	Lcom/sleepycat/b/p/au;
    //   671: aload_0
    //   672: getfield 40	com/sleepycat/b/i/c/b/l:c	Lcom/sleepycat/b/i/c/b/h;
    //   675: invokestatic 224	com/sleepycat/b/i/c/b/h:f	(Lcom/sleepycat/b/i/c/b/h;)Lcom/sleepycat/b/p/au;
    //   678: invokevirtual 403	com/sleepycat/b/p/au:a	(Lcom/sleepycat/b/p/au;)Z
    //   681: ifne +345 -> 1026
    //   684: new 168	java/lang/StringBuilder
    //   687: dup
    //   688: ldc_w 405
    //   691: invokespecial 173	java/lang/StringBuilder:<init>	(Ljava/lang/String;)V
    //   694: aload_0
    //   695: getfield 40	com/sleepycat/b/i/c/b/l:c	Lcom/sleepycat/b/i/c/b/h;
    //   698: invokestatic 224	com/sleepycat/b/i/c/b/h:f	(Lcom/sleepycat/b/i/c/b/h;)Lcom/sleepycat/b/p/au;
    //   701: invokevirtual 177	java/lang/StringBuilder:append	(Ljava/lang/Object;)Ljava/lang/StringBuilder;
    //   704: ldc_w 407
    //   707: invokevirtual 279	java/lang/StringBuilder:append	(Ljava/lang/String;)Ljava/lang/StringBuilder;
    //   710: aload_2
    //   711: getfield 141	com/sleepycat/b/i/e/s:d	Lcom/sleepycat/b/g/ae;
    //   714: getfield 400	com/sleepycat/b/g/ae:e	Lcom/sleepycat/b/p/au;
    //   717: invokevirtual 177	java/lang/StringBuilder:append	(Ljava/lang/Object;)Ljava/lang/StringBuilder;
    //   720: invokevirtual 181	java/lang/StringBuilder:toString	()Ljava/lang/String;
    //   723: invokestatic 412	com/sleepycat/b/aa:c	(Ljava/lang/String;)Lcom/sleepycat/b/aa;
    //   726: athrow
    //   727: astore_2
    //   728: aload_0
    //   729: getfield 40	com/sleepycat/b/i/c/b/l:c	Lcom/sleepycat/b/i/c/b/h;
    //   732: invokestatic 166	com/sleepycat/b/i/c/b/h:k	(Lcom/sleepycat/b/i/c/b/h;)Ljava/util/logging/Logger;
    //   735: aload_0
    //   736: getfield 60	com/sleepycat/b/i/c/b/l:g	Lcom/sleepycat/b/i/c/aj;
    //   739: new 168	java/lang/StringBuilder
    //   742: dup
    //   743: ldc_w 414
    //   746: invokespecial 173	java/lang/StringBuilder:<init>	(Ljava/lang/String;)V
    //   749: aload_2
    //   750: invokevirtual 417	java/lang/RuntimeException:getMessage	()Ljava/lang/String;
    //   753: invokevirtual 279	java/lang/StringBuilder:append	(Ljava/lang/String;)Ljava/lang/StringBuilder;
    //   756: aload_2
    //   757: invokestatic 420	com/sleepycat/b/p/w:a	(Ljava/lang/Throwable;)Ljava/lang/String;
    //   760: invokevirtual 279	java/lang/StringBuilder:append	(Ljava/lang/String;)Ljava/lang/StringBuilder;
    //   763: invokevirtual 181	java/lang/StringBuilder:toString	()Ljava/lang/String;
    //   766: invokestatic 422	com/sleepycat/b/p/w:a	(Ljava/util/logging/Logger;Lcom/sleepycat/b/c/ad;Ljava/lang/String;)V
    //   769: aload_2
    //   770: athrow
    //   771: astore_1
    //   772: aconst_null
    //   773: astore_3
    //   774: aload_3
    //   775: ifnull +381 -> 1156
    //   778: aload_3
    //   779: athrow
    //   780: aload_0
    //   781: getfield 40	com/sleepycat/b/i/c/b/l:c	Lcom/sleepycat/b/i/c/b/h;
    //   784: invokestatic 63	com/sleepycat/b/i/c/b/h:a	(Lcom/sleepycat/b/i/c/b/h;)Lcom/sleepycat/b/i/c/b/aa;
    //   787: getfield 67	com/sleepycat/b/i/c/b/aa:i	Lcom/sleepycat/b/i/c/aj;
    //   790: getfield 426	com/sleepycat/b/i/c/aj:al	Lcom/sleepycat/b/i/e/i;
    //   793: getfield 431	com/sleepycat/b/i/e/i:a	Ljava/util/Map;
    //   796: lload 8
    //   798: invokestatic 315	java/lang/Long:valueOf	(J)Ljava/lang/Long;
    //   801: invokeinterface 436 2 0
    //   806: checkcast 438	com/sleepycat/b/i/e/j
    //   809: astore_1
    //   810: aload_1
    //   811: ifnonnull +197 -> 1008
    //   814: aconst_null
    //   815: astore_1
    //   816: getstatic 443	com/sleepycat/b/w:b	Lcom/sleepycat/b/w;
    //   819: astore_3
    //   820: aload_1
    //   821: ifnull +195 -> 1016
    //   824: aload_1
    //   825: invokestatic 199	java/lang/System:currentTimeMillis	()J
    //   828: aload_1
    //   829: getfield 446	com/sleepycat/b/i/f/b:c	J
    //   832: lsub
    //   833: l2i
    //   834: putfield 447	com/sleepycat/b/i/f/b:e	I
    //   837: aload_1
    //   838: getfield 447	com/sleepycat/b/i/f/b:e	I
    //   841: ifle +840 -> 1681
    //   844: aload_1
    //   845: getfield 447	com/sleepycat/b/i/f/b:e	I
    //   848: aload_1
    //   849: getfield 449	com/sleepycat/b/i/f/b:d	I
    //   852: isub
    //   853: i2l
    //   854: lstore 6
    //   856: aload_0
    //   857: aload_0
    //   858: getfield 56	com/sleepycat/b/i/c/b/l:e	J
    //   861: lload 6
    //   863: ladd
    //   864: putfield 56	com/sleepycat/b/i/c/b/l:e	J
    //   867: lload 6
    //   869: aload_0
    //   870: getfield 95	com/sleepycat/b/i/c/b/l:i	I
    //   873: i2l
    //   874: lcmp
    //   875: ifle +68 -> 943
    //   878: ldc_w 451
    //   881: iconst_4
    //   882: anewarray 208	java/lang/Object
    //   885: dup
    //   886: iconst_0
    //   887: aload_0
    //   888: getfield 40	com/sleepycat/b/i/c/b/l:c	Lcom/sleepycat/b/i/c/b/h;
    //   891: invokestatic 230	com/sleepycat/b/i/c/b/h:c	(Lcom/sleepycat/b/i/c/b/h;)Lcom/sleepycat/b/i/c/b/x;
    //   894: getfield 235	com/sleepycat/b/i/c/b/x:a	Ljava/lang/String;
    //   897: aastore
    //   898: dup
    //   899: iconst_1
    //   900: lload 8
    //   902: invokestatic 315	java/lang/Long:valueOf	(J)Ljava/lang/Long;
    //   905: aastore
    //   906: dup
    //   907: iconst_2
    //   908: lload 6
    //   910: invokestatic 315	java/lang/Long:valueOf	(J)Ljava/lang/Long;
    //   913: aastore
    //   914: dup
    //   915: iconst_3
    //   916: aload_0
    //   917: getfield 56	com/sleepycat/b/i/c/b/l:e	J
    //   920: invokestatic 315	java/lang/Long:valueOf	(J)Ljava/lang/Long;
    //   923: aastore
    //   924: invokestatic 326	java/lang/String:format	(Ljava/lang/String;[Ljava/lang/Object;)Ljava/lang/String;
    //   927: astore_3
    //   928: aload_0
    //   929: getfield 40	com/sleepycat/b/i/c/b/l:c	Lcom/sleepycat/b/i/c/b/h;
    //   932: invokestatic 166	com/sleepycat/b/i/c/b/h:k	(Lcom/sleepycat/b/i/c/b/h;)Ljava/util/logging/Logger;
    //   935: aload_0
    //   936: getfield 60	com/sleepycat/b/i/c/b/l:g	Lcom/sleepycat/b/i/c/aj;
    //   939: aload_3
    //   940: invokestatic 186	com/sleepycat/b/p/w:c	(Ljava/util/logging/Logger;Lcom/sleepycat/b/c/ad;Ljava/lang/String;)V
    //   943: aload_0
    //   944: getfield 86	com/sleepycat/b/i/c/b/l:h	Z
    //   947: ifne +740 -> 1687
    //   950: iconst_1
    //   951: istore 10
    //   953: aload_1
    //   954: getfield 457	com/sleepycat/b/n/z:D	Lcom/sleepycat/b/u;
    //   957: getfield 461	com/sleepycat/b/u:f	Lcom/sleepycat/b/w;
    //   960: astore_1
    //   961: aload_0
    //   962: getfield 54	com/sleepycat/b/i/c/b/l:a	Lcom/sleepycat/b/i/e/t;
    //   965: astore_3
    //   966: aload_3
    //   967: invokevirtual 212	java/lang/Object:getClass	()Ljava/lang/Class;
    //   970: pop
    //   971: new 463	com/sleepycat/b/i/e/w
    //   974: dup
    //   975: aload_3
    //   976: iload 10
    //   978: aload_1
    //   979: aload_2
    //   980: invokespecial 466	com/sleepycat/b/i/e/w:<init>	(Lcom/sleepycat/b/i/e/t;ZLcom/sleepycat/b/w;Lcom/sleepycat/b/i/e/s;)V
    //   983: astore_1
    //   984: goto -320 -> 664
    //   987: astore_3
    //   988: aload_0
    //   989: getfield 40	com/sleepycat/b/i/c/b/l:c	Lcom/sleepycat/b/i/c/b/h;
    //   992: invokestatic 63	com/sleepycat/b/i/c/b/h:a	(Lcom/sleepycat/b/i/c/b/h;)Lcom/sleepycat/b/i/c/b/aa;
    //   995: getfield 67	com/sleepycat/b/i/c/b/aa:i	Lcom/sleepycat/b/i/c/aj;
    //   998: aload_3
    //   999: invokevirtual 469	com/sleepycat/b/i/c/aj:a	(Ljava/lang/Error;)V
    //   1002: aload_3
    //   1003: ifnull +490 -> 1493
    //   1006: aload_3
    //   1007: athrow
    //   1008: aload_1
    //   1009: getfield 472	com/sleepycat/b/i/e/j:b	Lcom/sleepycat/b/i/f/b;
    //   1012: astore_1
    //   1013: goto -197 -> 816
    //   1016: getstatic 443	com/sleepycat/b/w:b	Lcom/sleepycat/b/w;
    //   1019: astore_1
    //   1020: iconst_0
    //   1021: istore 10
    //   1023: goto -62 -> 961
    //   1026: aload_0
    //   1027: getfield 60	com/sleepycat/b/i/c/b/l:g	Lcom/sleepycat/b/i/c/aj;
    //   1030: invokevirtual 474	com/sleepycat/b/i/c/aj:N	()Z
    //   1033: ifne +37 -> 1070
    //   1036: getstatic 35	com/sleepycat/b/i/c/b/l:b	Z
    //   1039: ifne +31 -> 1070
    //   1042: aload_2
    //   1043: new 168	java/lang/StringBuilder
    //   1046: dup
    //   1047: ldc_w 476
    //   1050: invokespecial 173	java/lang/StringBuilder:<init>	(Ljava/lang/String;)V
    //   1053: aload_0
    //   1054: getfield 40	com/sleepycat/b/i/c/b/l:c	Lcom/sleepycat/b/i/c/b/h;
    //   1057: invokestatic 479	com/sleepycat/b/i/c/b/h:q	(Lcom/sleepycat/b/i/c/b/h;)Lcom/sleepycat/b/i/c/b/x;
    //   1060: invokevirtual 177	java/lang/StringBuilder:append	(Ljava/lang/Object;)Ljava/lang/StringBuilder;
    //   1063: invokevirtual 181	java/lang/StringBuilder:toString	()Ljava/lang/String;
    //   1066: invokevirtual 482	com/sleepycat/b/i/e/s:a	(Ljava/lang/String;)Z
    //   1069: pop
    //   1070: aload_0
    //   1071: aload_1
    //   1072: aload_2
    //   1073: invokespecial 484	com/sleepycat/b/i/c/b/l:a	(Lcom/sleepycat/b/i/h/d;Lcom/sleepycat/b/i/e/s;)V
    //   1076: aload_0
    //   1077: getfield 54	com/sleepycat/b/i/c/b/l:a	Lcom/sleepycat/b/i/e/t;
    //   1080: aload_1
    //   1081: aload_0
    //   1082: getfield 40	com/sleepycat/b/i/c/b/l:c	Lcom/sleepycat/b/i/c/b/h;
    //   1085: invokestatic 189	com/sleepycat/b/i/c/b/h:b	(Lcom/sleepycat/b/i/c/b/h;)Lcom/sleepycat/b/i/h/p;
    //   1088: invokevirtual 194	com/sleepycat/b/i/e/t:a	(Lcom/sleepycat/b/i/h/d;Lcom/sleepycat/b/i/h/o;)V
    //   1091: aload_0
    //   1092: getfield 86	com/sleepycat/b/i/c/b/l:h	Z
    //   1095: ifeq +25 -> 1120
    //   1098: aload_2
    //   1099: invokevirtual 393	com/sleepycat/b/i/e/s:b	()J
    //   1102: lstore 6
    //   1104: lload 6
    //   1106: lconst_0
    //   1107: lcmp
    //   1108: ifeq +12 -> 1120
    //   1111: aload_0
    //   1112: getfield 40	com/sleepycat/b/i/c/b/l:c	Lcom/sleepycat/b/i/c/b/h;
    //   1115: lload 6
    //   1117: invokestatic 487	com/sleepycat/b/i/c/b/h:b	(Lcom/sleepycat/b/i/c/b/h;J)V
    //   1120: aload_0
    //   1121: invokespecial 328	com/sleepycat/b/i/c/b/l:b	()V
    //   1124: aload_0
    //   1125: getfield 40	com/sleepycat/b/i/c/b/l:c	Lcom/sleepycat/b/i/c/b/h;
    //   1128: aload_0
    //   1129: getfield 40	com/sleepycat/b/i/c/b/l:c	Lcom/sleepycat/b/i/c/b/h;
    //   1132: invokestatic 224	com/sleepycat/b/i/c/b/h:f	(Lcom/sleepycat/b/i/c/b/h;)Lcom/sleepycat/b/p/au;
    //   1135: invokevirtual 489	com/sleepycat/b/p/au:d	()Lcom/sleepycat/b/p/au;
    //   1138: invokestatic 492	com/sleepycat/b/i/c/b/h:b	(Lcom/sleepycat/b/i/c/b/h;Lcom/sleepycat/b/p/au;)Lcom/sleepycat/b/p/au;
    //   1141: pop
    //   1142: goto -759 -> 383
    //   1145: astore_1
    //   1146: aconst_null
    //   1147: astore_2
    //   1148: aconst_null
    //   1149: astore_3
    //   1150: goto -376 -> 774
    //   1153: goto +0 -> 1153
    //   1156: aload_0
    //   1157: getfield 40	com/sleepycat/b/i/c/b/l:c	Lcom/sleepycat/b/i/c/b/h;
    //   1160: invokestatic 166	com/sleepycat/b/i/c/b/h:k	(Lcom/sleepycat/b/i/c/b/h;)Ljava/util/logging/Logger;
    //   1163: aload_0
    //   1164: getfield 60	com/sleepycat/b/i/c/b/l:g	Lcom/sleepycat/b/i/c/aj;
    //   1167: new 168	java/lang/StringBuilder
    //   1170: dup
    //   1171: ldc_w 494
    //   1174: invokespecial 173	java/lang/StringBuilder:<init>	(Ljava/lang/String;)V
    //   1177: aload_0
    //   1178: getfield 40	com/sleepycat/b/i/c/b/l:c	Lcom/sleepycat/b/i/c/b/h;
    //   1181: invokestatic 230	com/sleepycat/b/i/c/b/h:c	(Lcom/sleepycat/b/i/c/b/h;)Lcom/sleepycat/b/i/c/b/x;
    //   1184: getfield 235	com/sleepycat/b/i/c/b/x:a	Ljava/lang/String;
    //   1187: invokevirtual 279	java/lang/StringBuilder:append	(Ljava/lang/String;)Ljava/lang/StringBuilder;
    //   1190: ldc_w 496
    //   1193: invokevirtual 279	java/lang/StringBuilder:append	(Ljava/lang/String;)Ljava/lang/StringBuilder;
    //   1196: aload_0
    //   1197: getfield 40	com/sleepycat/b/i/c/b/l:c	Lcom/sleepycat/b/i/c/b/h;
    //   1200: invokestatic 224	com/sleepycat/b/i/c/b/h:f	(Lcom/sleepycat/b/i/c/b/h;)Lcom/sleepycat/b/p/au;
    //   1203: invokevirtual 177	java/lang/StringBuilder:append	(Ljava/lang/Object;)Ljava/lang/StringBuilder;
    //   1206: ldc_w 498
    //   1209: invokevirtual 279	java/lang/StringBuilder:append	(Ljava/lang/String;)Ljava/lang/StringBuilder;
    //   1212: aload_0
    //   1213: getfield 40	com/sleepycat/b/i/c/b/l:c	Lcom/sleepycat/b/i/c/b/h;
    //   1216: invokestatic 63	com/sleepycat/b/i/c/b/h:a	(Lcom/sleepycat/b/i/c/b/h;)Lcom/sleepycat/b/i/c/b/aa;
    //   1219: invokevirtual 206	com/sleepycat/b/i/c/b/aa:g	()Lcom/sleepycat/b/p/au;
    //   1222: invokevirtual 177	java/lang/StringBuilder:append	(Ljava/lang/Object;)Ljava/lang/StringBuilder;
    //   1225: invokevirtual 181	java/lang/StringBuilder:toString	()Ljava/lang/String;
    //   1228: invokestatic 186	com/sleepycat/b/p/w:c	(Ljava/util/logging/Logger;Lcom/sleepycat/b/c/ad;Ljava/lang/String;)V
    //   1231: aload_0
    //   1232: getfield 40	com/sleepycat/b/i/c/b/l:c	Lcom/sleepycat/b/i/c/b/h;
    //   1235: aload_2
    //   1236: invokevirtual 501	com/sleepycat/b/i/c/b/h:a	(Ljava/lang/Exception;)V
    //   1239: aload_1
    //   1240: athrow
    //   1241: aload_0
    //   1242: getfield 40	com/sleepycat/b/i/c/b/l:c	Lcom/sleepycat/b/i/c/b/h;
    //   1245: invokestatic 166	com/sleepycat/b/i/c/b/h:k	(Lcom/sleepycat/b/i/c/b/h;)Ljava/util/logging/Logger;
    //   1248: aload_0
    //   1249: getfield 60	com/sleepycat/b/i/c/b/l:g	Lcom/sleepycat/b/i/c/aj;
    //   1252: new 168	java/lang/StringBuilder
    //   1255: dup
    //   1256: ldc_w 494
    //   1259: invokespecial 173	java/lang/StringBuilder:<init>	(Ljava/lang/String;)V
    //   1262: aload_0
    //   1263: getfield 40	com/sleepycat/b/i/c/b/l:c	Lcom/sleepycat/b/i/c/b/h;
    //   1266: invokestatic 230	com/sleepycat/b/i/c/b/h:c	(Lcom/sleepycat/b/i/c/b/h;)Lcom/sleepycat/b/i/c/b/x;
    //   1269: getfield 235	com/sleepycat/b/i/c/b/x:a	Ljava/lang/String;
    //   1272: invokevirtual 279	java/lang/StringBuilder:append	(Ljava/lang/String;)Ljava/lang/StringBuilder;
    //   1275: ldc_w 496
    //   1278: invokevirtual 279	java/lang/StringBuilder:append	(Ljava/lang/String;)Ljava/lang/StringBuilder;
    //   1281: aload_0
    //   1282: getfield 40	com/sleepycat/b/i/c/b/l:c	Lcom/sleepycat/b/i/c/b/h;
    //   1285: invokestatic 224	com/sleepycat/b/i/c/b/h:f	(Lcom/sleepycat/b/i/c/b/h;)Lcom/sleepycat/b/p/au;
    //   1288: invokevirtual 177	java/lang/StringBuilder:append	(Ljava/lang/Object;)Ljava/lang/StringBuilder;
    //   1291: ldc_w 498
    //   1294: invokevirtual 279	java/lang/StringBuilder:append	(Ljava/lang/String;)Ljava/lang/StringBuilder;
    //   1297: aload_0
    //   1298: getfield 40	com/sleepycat/b/i/c/b/l:c	Lcom/sleepycat/b/i/c/b/h;
    //   1301: invokestatic 63	com/sleepycat/b/i/c/b/h:a	(Lcom/sleepycat/b/i/c/b/h;)Lcom/sleepycat/b/i/c/b/aa;
    //   1304: invokevirtual 206	com/sleepycat/b/i/c/b/aa:g	()Lcom/sleepycat/b/p/au;
    //   1307: invokevirtual 177	java/lang/StringBuilder:append	(Ljava/lang/Object;)Ljava/lang/StringBuilder;
    //   1310: invokevirtual 181	java/lang/StringBuilder:toString	()Ljava/lang/String;
    //   1313: invokestatic 186	com/sleepycat/b/p/w:c	(Ljava/util/logging/Logger;Lcom/sleepycat/b/c/ad;Ljava/lang/String;)V
    //   1316: aload_0
    //   1317: getfield 40	com/sleepycat/b/i/c/b/l:c	Lcom/sleepycat/b/i/c/b/h;
    //   1320: astore_2
    //   1321: aload_2
    //   1322: aload_1
    //   1323: invokevirtual 501	com/sleepycat/b/i/c/b/h:a	(Ljava/lang/Exception;)V
    //   1326: return
    //   1327: aload_0
    //   1328: getfield 40	com/sleepycat/b/i/c/b/l:c	Lcom/sleepycat/b/i/c/b/h;
    //   1331: invokestatic 166	com/sleepycat/b/i/c/b/h:k	(Lcom/sleepycat/b/i/c/b/h;)Ljava/util/logging/Logger;
    //   1334: aload_0
    //   1335: getfield 60	com/sleepycat/b/i/c/b/l:g	Lcom/sleepycat/b/i/c/aj;
    //   1338: new 168	java/lang/StringBuilder
    //   1341: dup
    //   1342: ldc_w 494
    //   1345: invokespecial 173	java/lang/StringBuilder:<init>	(Ljava/lang/String;)V
    //   1348: aload_0
    //   1349: getfield 40	com/sleepycat/b/i/c/b/l:c	Lcom/sleepycat/b/i/c/b/h;
    //   1352: invokestatic 230	com/sleepycat/b/i/c/b/h:c	(Lcom/sleepycat/b/i/c/b/h;)Lcom/sleepycat/b/i/c/b/x;
    //   1355: getfield 235	com/sleepycat/b/i/c/b/x:a	Ljava/lang/String;
    //   1358: invokevirtual 279	java/lang/StringBuilder:append	(Ljava/lang/String;)Ljava/lang/StringBuilder;
    //   1361: ldc_w 496
    //   1364: invokevirtual 279	java/lang/StringBuilder:append	(Ljava/lang/String;)Ljava/lang/StringBuilder;
    //   1367: aload_0
    //   1368: getfield 40	com/sleepycat/b/i/c/b/l:c	Lcom/sleepycat/b/i/c/b/h;
    //   1371: invokestatic 224	com/sleepycat/b/i/c/b/h:f	(Lcom/sleepycat/b/i/c/b/h;)Lcom/sleepycat/b/p/au;
    //   1374: invokevirtual 177	java/lang/StringBuilder:append	(Ljava/lang/Object;)Ljava/lang/StringBuilder;
    //   1377: ldc_w 498
    //   1380: invokevirtual 279	java/lang/StringBuilder:append	(Ljava/lang/String;)Ljava/lang/StringBuilder;
    //   1383: aload_0
    //   1384: getfield 40	com/sleepycat/b/i/c/b/l:c	Lcom/sleepycat/b/i/c/b/h;
    //   1387: invokestatic 63	com/sleepycat/b/i/c/b/h:a	(Lcom/sleepycat/b/i/c/b/h;)Lcom/sleepycat/b/i/c/b/aa;
    //   1390: invokevirtual 206	com/sleepycat/b/i/c/b/aa:g	()Lcom/sleepycat/b/p/au;
    //   1393: invokevirtual 177	java/lang/StringBuilder:append	(Ljava/lang/Object;)Ljava/lang/StringBuilder;
    //   1396: invokevirtual 181	java/lang/StringBuilder:toString	()Ljava/lang/String;
    //   1399: invokestatic 186	com/sleepycat/b/p/w:c	(Ljava/util/logging/Logger;Lcom/sleepycat/b/c/ad;Ljava/lang/String;)V
    //   1402: aload_0
    //   1403: getfield 40	com/sleepycat/b/i/c/b/l:c	Lcom/sleepycat/b/i/c/b/h;
    //   1406: astore_2
    //   1407: goto -86 -> 1321
    //   1410: aload_0
    //   1411: getfield 40	com/sleepycat/b/i/c/b/l:c	Lcom/sleepycat/b/i/c/b/h;
    //   1414: invokestatic 166	com/sleepycat/b/i/c/b/h:k	(Lcom/sleepycat/b/i/c/b/h;)Ljava/util/logging/Logger;
    //   1417: aload_0
    //   1418: getfield 60	com/sleepycat/b/i/c/b/l:g	Lcom/sleepycat/b/i/c/aj;
    //   1421: new 168	java/lang/StringBuilder
    //   1424: dup
    //   1425: ldc_w 494
    //   1428: invokespecial 173	java/lang/StringBuilder:<init>	(Ljava/lang/String;)V
    //   1431: aload_0
    //   1432: getfield 40	com/sleepycat/b/i/c/b/l:c	Lcom/sleepycat/b/i/c/b/h;
    //   1435: invokestatic 230	com/sleepycat/b/i/c/b/h:c	(Lcom/sleepycat/b/i/c/b/h;)Lcom/sleepycat/b/i/c/b/x;
    //   1438: getfield 235	com/sleepycat/b/i/c/b/x:a	Ljava/lang/String;
    //   1441: invokevirtual 279	java/lang/StringBuilder:append	(Ljava/lang/String;)Ljava/lang/StringBuilder;
    //   1444: ldc_w 496
    //   1447: invokevirtual 279	java/lang/StringBuilder:append	(Ljava/lang/String;)Ljava/lang/StringBuilder;
    //   1450: aload_0
    //   1451: getfield 40	com/sleepycat/b/i/c/b/l:c	Lcom/sleepycat/b/i/c/b/h;
    //   1454: invokestatic 224	com/sleepycat/b/i/c/b/h:f	(Lcom/sleepycat/b/i/c/b/h;)Lcom/sleepycat/b/p/au;
    //   1457: invokevirtual 177	java/lang/StringBuilder:append	(Ljava/lang/Object;)Ljava/lang/StringBuilder;
    //   1460: ldc_w 498
    //   1463: invokevirtual 279	java/lang/StringBuilder:append	(Ljava/lang/String;)Ljava/lang/StringBuilder;
    //   1466: aload_0
    //   1467: getfield 40	com/sleepycat/b/i/c/b/l:c	Lcom/sleepycat/b/i/c/b/h;
    //   1470: invokestatic 63	com/sleepycat/b/i/c/b/h:a	(Lcom/sleepycat/b/i/c/b/h;)Lcom/sleepycat/b/i/c/b/aa;
    //   1473: invokevirtual 206	com/sleepycat/b/i/c/b/aa:g	()Lcom/sleepycat/b/p/au;
    //   1476: invokevirtual 177	java/lang/StringBuilder:append	(Ljava/lang/Object;)Ljava/lang/StringBuilder;
    //   1479: invokevirtual 181	java/lang/StringBuilder:toString	()Ljava/lang/String;
    //   1482: invokestatic 186	com/sleepycat/b/p/w:c	(Ljava/util/logging/Logger;Lcom/sleepycat/b/c/ad;Ljava/lang/String;)V
    //   1485: aload_0
    //   1486: getfield 40	com/sleepycat/b/i/c/b/l:c	Lcom/sleepycat/b/i/c/b/h;
    //   1489: astore_2
    //   1490: goto -169 -> 1321
    //   1493: aload_0
    //   1494: getfield 40	com/sleepycat/b/i/c/b/l:c	Lcom/sleepycat/b/i/c/b/h;
    //   1497: invokestatic 166	com/sleepycat/b/i/c/b/h:k	(Lcom/sleepycat/b/i/c/b/h;)Ljava/util/logging/Logger;
    //   1500: aload_0
    //   1501: getfield 60	com/sleepycat/b/i/c/b/l:g	Lcom/sleepycat/b/i/c/aj;
    //   1504: new 168	java/lang/StringBuilder
    //   1507: dup
    //   1508: ldc_w 494
    //   1511: invokespecial 173	java/lang/StringBuilder:<init>	(Ljava/lang/String;)V
    //   1514: aload_0
    //   1515: getfield 40	com/sleepycat/b/i/c/b/l:c	Lcom/sleepycat/b/i/c/b/h;
    //   1518: invokestatic 230	com/sleepycat/b/i/c/b/h:c	(Lcom/sleepycat/b/i/c/b/h;)Lcom/sleepycat/b/i/c/b/x;
    //   1521: getfield 235	com/sleepycat/b/i/c/b/x:a	Ljava/lang/String;
    //   1524: invokevirtual 279	java/lang/StringBuilder:append	(Ljava/lang/String;)Ljava/lang/StringBuilder;
    //   1527: ldc_w 496
    //   1530: invokevirtual 279	java/lang/StringBuilder:append	(Ljava/lang/String;)Ljava/lang/StringBuilder;
    //   1533: aload_0
    //   1534: getfield 40	com/sleepycat/b/i/c/b/l:c	Lcom/sleepycat/b/i/c/b/h;
    //   1537: invokestatic 224	com/sleepycat/b/i/c/b/h:f	(Lcom/sleepycat/b/i/c/b/h;)Lcom/sleepycat/b/p/au;
    //   1540: invokevirtual 177	java/lang/StringBuilder:append	(Ljava/lang/Object;)Ljava/lang/StringBuilder;
    //   1543: ldc_w 498
    //   1546: invokevirtual 279	java/lang/StringBuilder:append	(Ljava/lang/String;)Ljava/lang/StringBuilder;
    //   1549: aload_0
    //   1550: getfield 40	com/sleepycat/b/i/c/b/l:c	Lcom/sleepycat/b/i/c/b/h;
    //   1553: invokestatic 63	com/sleepycat/b/i/c/b/h:a	(Lcom/sleepycat/b/i/c/b/h;)Lcom/sleepycat/b/i/c/b/aa;
    //   1556: invokevirtual 206	com/sleepycat/b/i/c/b/aa:g	()Lcom/sleepycat/b/p/au;
    //   1559: invokevirtual 177	java/lang/StringBuilder:append	(Ljava/lang/Object;)Ljava/lang/StringBuilder;
    //   1562: invokevirtual 181	java/lang/StringBuilder:toString	()Ljava/lang/String;
    //   1565: invokestatic 186	com/sleepycat/b/p/w:c	(Ljava/util/logging/Logger;Lcom/sleepycat/b/c/ad;Ljava/lang/String;)V
    //   1568: aload_0
    //   1569: getfield 40	com/sleepycat/b/i/c/b/l:c	Lcom/sleepycat/b/i/c/b/h;
    //   1572: aconst_null
    //   1573: invokevirtual 501	com/sleepycat/b/i/c/b/h:a	(Ljava/lang/Exception;)V
    //   1576: goto -423 -> 1153
    //   1579: iconst_0
    //   1580: ifeq +5 -> 1585
    //   1583: aconst_null
    //   1584: athrow
    //   1585: aload_0
    //   1586: getfield 40	com/sleepycat/b/i/c/b/l:c	Lcom/sleepycat/b/i/c/b/h;
    //   1589: invokestatic 166	com/sleepycat/b/i/c/b/h:k	(Lcom/sleepycat/b/i/c/b/h;)Ljava/util/logging/Logger;
    //   1592: aload_0
    //   1593: getfield 60	com/sleepycat/b/i/c/b/l:g	Lcom/sleepycat/b/i/c/aj;
    //   1596: new 168	java/lang/StringBuilder
    //   1599: dup
    //   1600: ldc_w 494
    //   1603: invokespecial 173	java/lang/StringBuilder:<init>	(Ljava/lang/String;)V
    //   1606: aload_0
    //   1607: getfield 40	com/sleepycat/b/i/c/b/l:c	Lcom/sleepycat/b/i/c/b/h;
    //   1610: invokestatic 230	com/sleepycat/b/i/c/b/h:c	(Lcom/sleepycat/b/i/c/b/h;)Lcom/sleepycat/b/i/c/b/x;
    //   1613: getfield 235	com/sleepycat/b/i/c/b/x:a	Ljava/lang/String;
    //   1616: invokevirtual 279	java/lang/StringBuilder:append	(Ljava/lang/String;)Ljava/lang/StringBuilder;
    //   1619: ldc_w 496
    //   1622: invokevirtual 279	java/lang/StringBuilder:append	(Ljava/lang/String;)Ljava/lang/StringBuilder;
    //   1625: aload_0
    //   1626: getfield 40	com/sleepycat/b/i/c/b/l:c	Lcom/sleepycat/b/i/c/b/h;
    //   1629: invokestatic 224	com/sleepycat/b/i/c/b/h:f	(Lcom/sleepycat/b/i/c/b/h;)Lcom/sleepycat/b/p/au;
    //   1632: invokevirtual 177	java/lang/StringBuilder:append	(Ljava/lang/Object;)Ljava/lang/StringBuilder;
    //   1635: ldc_w 498
    //   1638: invokevirtual 279	java/lang/StringBuilder:append	(Ljava/lang/String;)Ljava/lang/StringBuilder;
    //   1641: aload_0
    //   1642: getfield 40	com/sleepycat/b/i/c/b/l:c	Lcom/sleepycat/b/i/c/b/h;
    //   1645: invokestatic 63	com/sleepycat/b/i/c/b/h:a	(Lcom/sleepycat/b/i/c/b/h;)Lcom/sleepycat/b/i/c/b/aa;
    //   1648: invokevirtual 206	com/sleepycat/b/i/c/b/aa:g	()Lcom/sleepycat/b/p/au;
    //   1651: invokevirtual 177	java/lang/StringBuilder:append	(Ljava/lang/Object;)Ljava/lang/StringBuilder;
    //   1654: invokevirtual 181	java/lang/StringBuilder:toString	()Ljava/lang/String;
    //   1657: invokestatic 186	com/sleepycat/b/p/w:c	(Ljava/util/logging/Logger;Lcom/sleepycat/b/c/ad;Ljava/lang/String;)V
    //   1660: aload_0
    //   1661: getfield 40	com/sleepycat/b/i/c/b/l:c	Lcom/sleepycat/b/i/c/b/h;
    //   1664: aconst_null
    //   1665: invokevirtual 501	com/sleepycat/b/i/c/b/h:a	(Ljava/lang/Exception;)V
    //   1668: return
    //   1669: astore_1
    //   1670: aconst_null
    //   1671: astore_2
    //   1672: goto -898 -> 774
    //   1675: iconst_0
    //   1676: istore 4
    //   1678: goto -1218 -> 460
    //   1681: lconst_0
    //   1682: lstore 6
    //   1684: goto -828 -> 856
    //   1687: iconst_0
    //   1688: istore 10
    //   1690: goto -737 -> 953
    // Local variable table:
    //   start	length	slot	name	signature
    //   0	1693	0	this	l
    //   397	1	1	localIOException	java.io.IOException
    //   498	102	1	localObject2	Object
    //   612	9	1	localo	com.sleepycat.b.i.e.o
    //   624	1	1	localInterruptedException	InterruptedException
    //   648	16	1	localObject3	Object
    //   771	1	1	localObject4	Object
    //   809	272	1	localObject5	Object
    //   1145	178	1	localException	Exception
    //   1669	1	1	localObject6	Object
    //   364	151	2	localObject7	Object
    //   619	92	2	locals	s
    //   727	372	2	localRuntimeException	RuntimeException
    //   1147	525	2	localObject8	Object
    //   773	203	3	localObject9	Object
    //   987	20	3	localError	Error
    //   1149	1	3	localObject10	Object
    //   258	1419	4	m	int
    //   70	319	5	n	int
    //   854	829	6	l1	long
    //   635	266	8	l2	long
    //   951	738	10	bool	boolean
    // Exception table:
    //   from	to	target	type
    //   235	272	397	java/io/IOException
    //   272	285	397	java/io/IOException
    //   293	329	397	java/io/IOException
    //   338	375	397	java/io/IOException
    //   379	383	397	java/io/IOException
    //   388	394	397	java/io/IOException
    //   404	435	397	java/io/IOException
    //   435	457	397	java/io/IOException
    //   465	488	397	java/io/IOException
    //   494	582	397	java/io/IOException
    //   595	609	397	java/io/IOException
    //   622	624	397	java/io/IOException
    //   631	637	397	java/io/IOException
    //   644	664	397	java/io/IOException
    //   664	727	397	java/io/IOException
    //   780	810	397	java/io/IOException
    //   816	820	397	java/io/IOException
    //   824	856	397	java/io/IOException
    //   856	943	397	java/io/IOException
    //   943	950	397	java/io/IOException
    //   953	961	397	java/io/IOException
    //   961	984	397	java/io/IOException
    //   1008	1013	397	java/io/IOException
    //   1016	1020	397	java/io/IOException
    //   1026	1070	397	java/io/IOException
    //   1070	1104	397	java/io/IOException
    //   1111	1120	397	java/io/IOException
    //   1120	1142	397	java/io/IOException
    //   235	272	612	com/sleepycat/b/i/e/o
    //   272	285	612	com/sleepycat/b/i/e/o
    //   293	329	612	com/sleepycat/b/i/e/o
    //   338	375	612	com/sleepycat/b/i/e/o
    //   379	383	612	com/sleepycat/b/i/e/o
    //   388	394	612	com/sleepycat/b/i/e/o
    //   404	435	612	com/sleepycat/b/i/e/o
    //   435	457	612	com/sleepycat/b/i/e/o
    //   465	488	612	com/sleepycat/b/i/e/o
    //   494	582	612	com/sleepycat/b/i/e/o
    //   595	609	612	com/sleepycat/b/i/e/o
    //   622	624	612	com/sleepycat/b/i/e/o
    //   631	637	612	com/sleepycat/b/i/e/o
    //   644	664	612	com/sleepycat/b/i/e/o
    //   664	727	612	com/sleepycat/b/i/e/o
    //   780	810	612	com/sleepycat/b/i/e/o
    //   816	820	612	com/sleepycat/b/i/e/o
    //   824	856	612	com/sleepycat/b/i/e/o
    //   856	943	612	com/sleepycat/b/i/e/o
    //   943	950	612	com/sleepycat/b/i/e/o
    //   953	961	612	com/sleepycat/b/i/e/o
    //   961	984	612	com/sleepycat/b/i/e/o
    //   1008	1013	612	com/sleepycat/b/i/e/o
    //   1016	1020	612	com/sleepycat/b/i/e/o
    //   1026	1070	612	com/sleepycat/b/i/e/o
    //   1070	1104	612	com/sleepycat/b/i/e/o
    //   1111	1120	612	com/sleepycat/b/i/e/o
    //   1120	1142	612	com/sleepycat/b/i/e/o
    //   329	338	619	finally
    //   588	595	619	finally
    //   620	622	619	finally
    //   235	272	624	java/lang/InterruptedException
    //   272	285	624	java/lang/InterruptedException
    //   293	329	624	java/lang/InterruptedException
    //   338	375	624	java/lang/InterruptedException
    //   379	383	624	java/lang/InterruptedException
    //   388	394	624	java/lang/InterruptedException
    //   404	435	624	java/lang/InterruptedException
    //   435	457	624	java/lang/InterruptedException
    //   465	488	624	java/lang/InterruptedException
    //   494	582	624	java/lang/InterruptedException
    //   595	609	624	java/lang/InterruptedException
    //   622	624	624	java/lang/InterruptedException
    //   631	637	624	java/lang/InterruptedException
    //   644	664	624	java/lang/InterruptedException
    //   664	727	624	java/lang/InterruptedException
    //   780	810	624	java/lang/InterruptedException
    //   816	820	624	java/lang/InterruptedException
    //   824	856	624	java/lang/InterruptedException
    //   856	943	624	java/lang/InterruptedException
    //   943	950	624	java/lang/InterruptedException
    //   953	961	624	java/lang/InterruptedException
    //   961	984	624	java/lang/InterruptedException
    //   1008	1013	624	java/lang/InterruptedException
    //   1016	1020	624	java/lang/InterruptedException
    //   1026	1070	624	java/lang/InterruptedException
    //   1070	1104	624	java/lang/InterruptedException
    //   1111	1120	624	java/lang/InterruptedException
    //   1120	1142	624	java/lang/InterruptedException
    //   235	272	727	java/lang/RuntimeException
    //   272	285	727	java/lang/RuntimeException
    //   293	329	727	java/lang/RuntimeException
    //   338	375	727	java/lang/RuntimeException
    //   379	383	727	java/lang/RuntimeException
    //   388	394	727	java/lang/RuntimeException
    //   404	435	727	java/lang/RuntimeException
    //   435	457	727	java/lang/RuntimeException
    //   465	488	727	java/lang/RuntimeException
    //   494	582	727	java/lang/RuntimeException
    //   595	609	727	java/lang/RuntimeException
    //   622	624	727	java/lang/RuntimeException
    //   631	637	727	java/lang/RuntimeException
    //   644	664	727	java/lang/RuntimeException
    //   664	727	727	java/lang/RuntimeException
    //   780	810	727	java/lang/RuntimeException
    //   816	820	727	java/lang/RuntimeException
    //   824	856	727	java/lang/RuntimeException
    //   856	943	727	java/lang/RuntimeException
    //   943	950	727	java/lang/RuntimeException
    //   953	961	727	java/lang/RuntimeException
    //   961	984	727	java/lang/RuntimeException
    //   1008	1013	727	java/lang/RuntimeException
    //   1016	1020	727	java/lang/RuntimeException
    //   1026	1070	727	java/lang/RuntimeException
    //   1070	1104	727	java/lang/RuntimeException
    //   1111	1120	727	java/lang/RuntimeException
    //   1120	1142	727	java/lang/RuntimeException
    //   728	771	771	finally
    //   235	272	987	java/lang/Error
    //   272	285	987	java/lang/Error
    //   293	329	987	java/lang/Error
    //   338	375	987	java/lang/Error
    //   379	383	987	java/lang/Error
    //   388	394	987	java/lang/Error
    //   404	435	987	java/lang/Error
    //   435	457	987	java/lang/Error
    //   465	488	987	java/lang/Error
    //   494	582	987	java/lang/Error
    //   595	609	987	java/lang/Error
    //   622	624	987	java/lang/Error
    //   631	637	987	java/lang/Error
    //   644	664	987	java/lang/Error
    //   664	727	987	java/lang/Error
    //   780	810	987	java/lang/Error
    //   816	820	987	java/lang/Error
    //   824	856	987	java/lang/Error
    //   856	943	987	java/lang/Error
    //   943	950	987	java/lang/Error
    //   953	961	987	java/lang/Error
    //   961	984	987	java/lang/Error
    //   1008	1013	987	java/lang/Error
    //   1016	1020	987	java/lang/Error
    //   1026	1070	987	java/lang/Error
    //   1070	1104	987	java/lang/Error
    //   1111	1120	987	java/lang/Error
    //   1120	1142	987	java/lang/Error
    //   235	272	1145	finally
    //   272	285	1145	finally
    //   293	329	1145	finally
    //   338	375	1145	finally
    //   379	383	1145	finally
    //   388	394	1145	finally
    //   404	435	1145	finally
    //   435	457	1145	finally
    //   465	488	1145	finally
    //   494	582	1145	finally
    //   595	609	1145	finally
    //   622	624	1145	finally
    //   631	637	1145	finally
    //   644	664	1145	finally
    //   664	727	1145	finally
    //   780	810	1145	finally
    //   816	820	1145	finally
    //   824	856	1145	finally
    //   856	943	1145	finally
    //   943	950	1145	finally
    //   953	961	1145	finally
    //   961	984	1145	finally
    //   1008	1013	1145	finally
    //   1016	1020	1145	finally
    //   1026	1070	1145	finally
    //   1070	1104	1145	finally
    //   1111	1120	1145	finally
    //   1120	1142	1145	finally
    //   988	1002	1669	finally
  }
}


/* Location:              E:\apk\xueqiu2\classes-dex2jar.jar!\com\sleepycat\b\i\c\b\l.class
 * Java compiler version: 6 (50.0)
 * JD-Core Version:       0.7.1
 */