package com.xueqiu.android.base.util;

import java.io.File;
import java.util.LinkedList;
import java.util.List;

public final class y
{
  public List<z> a = new LinkedList();
  private File b;
  
  public y(File paramFile)
  {
    this.b = paramFile;
  }
  
  /* Error */
  public final void a(String paramString1, String paramString2, int paramInt, long paramLong)
  {
    // Byte code:
    //   0: aload_0
    //   1: monitorenter
    //   2: aload_0
    //   3: getfield 19	com/xueqiu/android/base/util/y:a	Ljava/util/List;
    //   6: new 27	com/xueqiu/android/base/util/z
    //   9: dup
    //   10: aload_0
    //   11: aload_1
    //   12: aload_2
    //   13: iload_3
    //   14: lload 4
    //   16: invokespecial 30	com/xueqiu/android/base/util/z:<init>	(Lcom/xueqiu/android/base/util/y;Ljava/lang/String;Ljava/lang/String;IJ)V
    //   19: invokeinterface 36 2 0
    //   24: pop
    //   25: aload_0
    //   26: getfield 19	com/xueqiu/android/base/util/y:a	Ljava/util/List;
    //   29: invokeinterface 40 1 0
    //   34: bipush 10
    //   36: if_icmplt +132 -> 168
    //   39: aload_0
    //   40: getfield 19	com/xueqiu/android/base/util/y:a	Ljava/util/List;
    //   43: astore_1
    //   44: new 42	java/io/BufferedWriter
    //   47: dup
    //   48: new 44	java/io/OutputStreamWriter
    //   51: dup
    //   52: new 46	java/io/FileOutputStream
    //   55: dup
    //   56: aload_0
    //   57: getfield 21	com/xueqiu/android/base/util/y:b	Ljava/io/File;
    //   60: iconst_1
    //   61: invokespecial 49	java/io/FileOutputStream:<init>	(Ljava/io/File;Z)V
    //   64: ldc 51
    //   66: invokespecial 54	java/io/OutputStreamWriter:<init>	(Ljava/io/OutputStream;Ljava/lang/String;)V
    //   69: invokespecial 57	java/io/BufferedWriter:<init>	(Ljava/io/Writer;)V
    //   72: astore_2
    //   73: aload_1
    //   74: invokeinterface 61 1 0
    //   79: astore 6
    //   81: aload 6
    //   83: invokeinterface 67 1 0
    //   88: ifeq +83 -> 171
    //   91: aload 6
    //   93: invokeinterface 71 1 0
    //   98: checkcast 27	com/xueqiu/android/base/util/z
    //   101: astore 7
    //   103: aload_2
    //   104: ldc 73
    //   106: iconst_4
    //   107: anewarray 4	java/lang/Object
    //   110: dup
    //   111: iconst_0
    //   112: aload 7
    //   114: getfield 76	com/xueqiu/android/base/util/z:a	Ljava/lang/String;
    //   117: aastore
    //   118: dup
    //   119: iconst_1
    //   120: aload 7
    //   122: getfield 78	com/xueqiu/android/base/util/z:b	Ljava/lang/String;
    //   125: aastore
    //   126: dup
    //   127: iconst_2
    //   128: aload 7
    //   130: getfield 82	com/xueqiu/android/base/util/z:c	I
    //   133: invokestatic 88	java/lang/Integer:valueOf	(I)Ljava/lang/Integer;
    //   136: aastore
    //   137: dup
    //   138: iconst_3
    //   139: aload 7
    //   141: getfield 92	com/xueqiu/android/base/util/z:d	J
    //   144: invokestatic 97	java/lang/Long:valueOf	(J)Ljava/lang/Long;
    //   147: aastore
    //   148: invokestatic 103	java/lang/String:format	(Ljava/lang/String;[Ljava/lang/Object;)Ljava/lang/String;
    //   151: invokevirtual 107	java/io/BufferedWriter:write	(Ljava/lang/String;)V
    //   154: goto -73 -> 81
    //   157: astore_2
    //   158: aload_2
    //   159: invokevirtual 110	java/io/IOException:printStackTrace	()V
    //   162: aload_1
    //   163: invokeinterface 113 1 0
    //   168: aload_0
    //   169: monitorexit
    //   170: return
    //   171: aload_2
    //   172: invokevirtual 116	java/io/BufferedWriter:flush	()V
    //   175: aload_2
    //   176: invokevirtual 119	java/io/BufferedWriter:close	()V
    //   179: aload_1
    //   180: invokeinterface 113 1 0
    //   185: goto -17 -> 168
    //   188: astore_1
    //   189: aload_0
    //   190: monitorexit
    //   191: aload_1
    //   192: athrow
    //   193: astore_2
    //   194: aload_1
    //   195: invokeinterface 113 1 0
    //   200: aload_2
    //   201: athrow
    // Local variable table:
    //   start	length	slot	name	signature
    //   0	202	0	this	y
    //   0	202	1	paramString1	String
    //   0	202	2	paramString2	String
    //   0	202	3	paramInt	int
    //   0	202	4	paramLong	long
    //   79	13	6	localIterator	java.util.Iterator
    //   101	39	7	localz	z
    // Exception table:
    //   from	to	target	type
    //   44	81	157	java/io/IOException
    //   81	154	157	java/io/IOException
    //   171	179	157	java/io/IOException
    //   2	44	188	finally
    //   162	168	188	finally
    //   179	185	188	finally
    //   194	202	188	finally
    //   44	81	193	finally
    //   81	154	193	finally
    //   158	162	193	finally
    //   171	179	193	finally
  }
}


/* Location:              E:\apk\xueqiu2\classes-dex2jar.jar!\com\xueqiu\android\base\util\y.class
 * Java compiler version: 6 (50.0)
 * JD-Core Version:       0.7.1
 */