package com.d.a.b;

import android.content.res.Resources;
import android.graphics.Bitmap;
import android.graphics.drawable.Drawable;
import android.os.Handler;
import com.d.a.b.a.f;
import com.d.a.b.a.g;
import com.d.a.b.a.i;
import java.io.File;
import java.io.IOException;
import java.io.InputStream;
import java.util.concurrent.Executor;
import java.util.concurrent.atomic.AtomicBoolean;

final class n
  implements com.d.a.c.c, Runnable
{
  final h a;
  final String b;
  final com.d.a.b.e.a c;
  final d d;
  final com.d.a.b.f.a e;
  final com.d.a.b.f.b f;
  private final l g;
  private final m h;
  private final Handler i;
  private final com.d.a.b.d.b j;
  private final com.d.a.b.d.b k;
  private final com.d.a.b.d.b l;
  private final com.d.a.b.b.d m;
  private final String n;
  private final f o;
  private final boolean p;
  private g q = g.a;
  
  public n(l paraml, m paramm, Handler paramHandler)
  {
    this.g = paraml;
    this.h = paramm;
    this.i = paramHandler;
    this.a = paraml.a;
    this.j = this.a.p;
    this.k = this.a.s;
    this.l = this.a.t;
    this.m = this.a.q;
    this.b = paramm.a;
    this.n = paramm.b;
    this.c = paramm.c;
    this.o = paramm.d;
    this.d = paramm.e;
    this.e = paramm.f;
    this.f = paramm.g;
    this.p = this.d.s;
  }
  
  private Bitmap a(String paramString)
  {
    int i1 = this.c.c();
    paramString = new com.d.a.b.b.e(this.n, paramString, this.b, this.o, i1, e(), this.d);
    return this.m.a(paramString);
  }
  
  private void a(final int paramInt, final Throwable paramThrowable)
  {
    if ((this.p) || (k()) || (g())) {
      return;
    }
    a(new Runnable()
    {
      public final void run()
      {
        Object localObject = n.this.d;
        int i;
        com.d.a.b.e.a locala;
        Resources localResources;
        if ((((d)localObject).f != null) || (((d)localObject).c != 0))
        {
          i = 1;
          if (i != 0)
          {
            locala = n.this.c;
            localObject = n.this.d;
            localResources = n.this.a.a;
            if (((d)localObject).c == 0) {
              break label130;
            }
          }
        }
        label130:
        for (localObject = localResources.getDrawable(((d)localObject).c);; localObject = ((d)localObject).f)
        {
          locala.a((Drawable)localObject);
          localObject = n.this.e;
          n.this.c.d();
          ((com.d.a.b.f.a)localObject).a(new com.d.a.b.a.b(paramInt, paramThrowable));
          return;
          i = 0;
          break;
        }
      }
    }, false, this.i, this.g);
  }
  
  static void a(Runnable paramRunnable, boolean paramBoolean, Handler paramHandler, l paraml)
  {
    if (paramBoolean)
    {
      paramRunnable.run();
      return;
    }
    if (paramHandler == null)
    {
      paraml.d.execute(paramRunnable);
      return;
    }
    paramHandler.post(paramRunnable);
  }
  
  private boolean a()
  {
    AtomicBoolean localAtomicBoolean = this.g.f;
    if (localAtomicBoolean.get()) {}
    synchronized (this.g.i)
    {
      if (localAtomicBoolean.get()) {
        com.d.a.c.d.a("ImageLoader is paused. Waiting...  [%s]", new Object[] { this.n });
      }
      try
      {
        this.g.i.wait();
        com.d.a.c.d.a(".. Resume loading [%s]", new Object[] { this.n });
        return g();
      }
      catch (InterruptedException localInterruptedException)
      {
        com.d.a.c.d.d("Task was interrupted [%s]", new Object[] { this.n });
        return true;
      }
    }
  }
  
  private boolean b()
  {
    if (this.d.l > 0) {}
    for (int i1 = 1; i1 != 0; i1 = 0)
    {
      com.d.a.c.d.a("Delay %d ms before loading...  [%s]", new Object[] { Integer.valueOf(this.d.l), this.n });
      try
      {
        Thread.sleep(this.d.l);
        return g();
      }
      catch (InterruptedException localInterruptedException)
      {
        com.d.a.c.d.d("Task was interrupted [%s]", new Object[] { this.n });
        return true;
      }
    }
    return false;
  }
  
  private Bitmap c()
  {
    for (;;)
    {
      try
      {
        Object localObject1 = this.a.o.a(this.b);
        Object localObject3;
        Object localObject4;
        Object localObject5;
        Object localObject6;
        if ((localObject1 != null) && (((File)localObject1).exists()))
        {
          com.d.a.c.d.a("Load image from disk cache [%s]", new Object[] { this.n });
          this.q = g.b;
          f();
          localObject1 = a(com.d.a.b.d.c.c.b(((File)localObject1).getAbsolutePath()));
          if (localObject1 != null)
          {
            localObject3 = localObject1;
            localObject4 = localObject1;
            localObject5 = localObject1;
            localObject6 = localObject1;
          }
        }
        Object localObject7;
        String str;
        File localFile;
        Object localObject2 = null;
      }
      catch (IllegalStateException localIllegalStateException1)
      {
        try
        {
          if (((Bitmap)localObject1).getWidth() > 0)
          {
            localObject7 = localObject1;
            localObject3 = localObject1;
            localObject4 = localObject1;
            localObject5 = localObject1;
            localObject6 = localObject1;
            if (((Bitmap)localObject1).getHeight() > 0) {}
          }
          else
          {
            localObject3 = localObject1;
            localObject4 = localObject1;
            localObject5 = localObject1;
            localObject6 = localObject1;
            com.d.a.c.d.a("Load image from network [%s]", new Object[] { this.n });
            localObject3 = localObject1;
            localObject4 = localObject1;
            localObject5 = localObject1;
            localObject6 = localObject1;
            this.q = g.a;
            localObject3 = localObject1;
            localObject4 = localObject1;
            localObject5 = localObject1;
            localObject6 = localObject1;
            str = this.b;
            localObject7 = str;
            localObject3 = localObject1;
            localObject4 = localObject1;
            localObject5 = localObject1;
            localObject6 = localObject1;
            if (this.d.i)
            {
              localObject7 = str;
              localObject3 = localObject1;
              localObject4 = localObject1;
              localObject5 = localObject1;
              localObject6 = localObject1;
              if (d())
              {
                localObject3 = localObject1;
                localObject4 = localObject1;
                localObject5 = localObject1;
                localObject6 = localObject1;
                localFile = this.a.o.a(this.b);
                localObject7 = str;
                if (localFile != null)
                {
                  localObject3 = localObject1;
                  localObject4 = localObject1;
                  localObject5 = localObject1;
                  localObject6 = localObject1;
                  localObject7 = com.d.a.b.d.c.c.b(localFile.getAbsolutePath());
                }
              }
            }
            localObject3 = localObject1;
            localObject4 = localObject1;
            localObject5 = localObject1;
            localObject6 = localObject1;
            f();
            localObject3 = localObject1;
            localObject4 = localObject1;
            localObject5 = localObject1;
            localObject6 = localObject1;
            localObject1 = a((String)localObject7);
            if (localObject1 != null)
            {
              localObject3 = localObject1;
              localObject4 = localObject1;
              localObject5 = localObject1;
              localObject6 = localObject1;
              if (((Bitmap)localObject1).getWidth() > 0)
              {
                localObject7 = localObject1;
                localObject3 = localObject1;
                localObject4 = localObject1;
                localObject5 = localObject1;
                localObject6 = localObject1;
                if (((Bitmap)localObject1).getHeight() > 0) {
                  continue;
                }
              }
            }
            localObject3 = localObject1;
            localObject4 = localObject1;
            localObject5 = localObject1;
            localObject6 = localObject1;
            a(com.d.a.b.a.c.b, null);
            localObject7 = localObject1;
          }
          return (Bitmap)localObject7;
        }
        catch (Throwable localThrowable2)
        {
          continue;
        }
        catch (OutOfMemoryError localOutOfMemoryError2)
        {
          continue;
        }
        catch (IOException localIOException2)
        {
          continue;
        }
        catch (IllegalStateException localIllegalStateException2)
        {
          continue;
        }
        localIllegalStateException1 = localIllegalStateException1;
        localObject6 = null;
        a(com.d.a.b.a.c.c, null);
        return (Bitmap)localObject6;
      }
      catch (o localo)
      {
        throw localo;
      }
      catch (IOException localIOException1)
      {
        localObject5 = null;
        com.d.a.c.d.a(localIOException1);
        a(com.d.a.b.a.c.a, localIOException1);
        return (Bitmap)localObject5;
      }
      catch (OutOfMemoryError localOutOfMemoryError1)
      {
        localObject4 = null;
        com.d.a.c.d.a(localOutOfMemoryError1);
        a(com.d.a.b.a.c.d, localOutOfMemoryError1);
        return (Bitmap)localObject4;
      }
      catch (Throwable localThrowable1)
      {
        localObject3 = null;
        com.d.a.c.d.a(localThrowable1);
        a(com.d.a.b.a.c.e, localThrowable1);
        return (Bitmap)localObject3;
      }
    }
  }
  
  private boolean d()
  {
    com.d.a.c.d.a("Cache image on disk [%s]", new Object[] { this.n });
    try
    {
      Object localObject1 = e().a(this.b, this.d.n);
      boolean bool = this.a.o.a(this.b, (InputStream)localObject1, this);
      if (bool)
      {
        int i1 = this.a.d;
        int i2 = this.a.e;
        if ((i1 > 0) || (i2 > 0))
        {
          com.d.a.c.d.a("Resize image in disk cache [%s]", new Object[] { this.n });
          localObject1 = this.a.o.a(this.b);
          if ((localObject1 != null) && (((File)localObject1).exists()))
          {
            Object localObject2 = new f(i1, i2);
            Object localObject3 = new e().a(this.d);
            ((e)localObject3).j = com.d.a.b.a.e.d;
            localObject3 = ((e)localObject3).b();
            localObject1 = new com.d.a.b.b.e(this.n, com.d.a.b.d.c.c.b(((File)localObject1).getAbsolutePath()), this.b, (f)localObject2, i.a, e(), (d)localObject3);
            localObject2 = this.m.a((com.d.a.b.b.e)localObject1);
            localObject1 = localObject2;
            if (localObject2 != null)
            {
              localObject1 = localObject2;
              if (this.a.f != null)
              {
                com.d.a.c.d.a("Process image before cache on disk [%s]", new Object[] { this.n });
                localObject2 = this.a.f.a();
                localObject1 = localObject2;
                if (localObject2 == null)
                {
                  com.d.a.c.d.d("Bitmap processor for disk cache returned null [%s]", new Object[] { this.n });
                  localObject1 = localObject2;
                }
              }
            }
            if (localObject1 != null)
            {
              this.a.o.a(this.b, (Bitmap)localObject1);
              ((Bitmap)localObject1).recycle();
            }
          }
        }
      }
      return bool;
    }
    catch (IOException localIOException)
    {
      com.d.a.c.d.a(localIOException);
    }
    return false;
  }
  
  private com.d.a.b.d.b e()
  {
    if (this.g.g.get()) {
      return this.k;
    }
    if (this.g.h.get()) {
      return this.l;
    }
    return this.j;
  }
  
  private void f()
  {
    if (h()) {
      throw new o(this);
    }
    if (i()) {
      throw new o(this);
    }
  }
  
  private boolean g()
  {
    return (h()) || (i());
  }
  
  private boolean h()
  {
    if (this.c.e())
    {
      com.d.a.c.d.a("ImageAware was collected by GC. Task is cancelled. [%s]", new Object[] { this.n });
      return true;
    }
    return false;
  }
  
  private boolean i()
  {
    String str = this.g.a(this.c);
    if (!this.n.equals(str)) {}
    for (int i1 = 1; i1 != 0; i1 = 0)
    {
      com.d.a.c.d.a("ImageAware is reused for another image. Task is cancelled. [%s]", new Object[] { this.n });
      return true;
    }
    return false;
  }
  
  private void j()
  {
    if (k()) {
      throw new o(this);
    }
  }
  
  private boolean k()
  {
    if (Thread.interrupted())
    {
      com.d.a.c.d.a("Task was interrupted [%s]", new Object[] { this.n });
      return true;
    }
    return false;
  }
  
  public final boolean a(final int paramInt1, final int paramInt2)
  {
    boolean bool = false;
    if (!this.p) {
      if ((!k()) && (!g())) {
        break label33;
      }
    }
    for (paramInt1 = 0;; paramInt1 = 1)
    {
      if (paramInt1 != 0) {
        bool = true;
      }
      return bool;
      label33:
      if (this.f != null) {
        a(new Runnable()
        {
          public final void run()
          {
            n.this.c.d();
          }
        }, false, this.i, this.g);
      }
    }
  }
  
  /* Error */
  public final void run()
  {
    // Byte code:
    //   0: iconst_1
    //   1: istore 4
    //   3: aload_0
    //   4: invokespecial 382	com/d/a/b/n:a	()Z
    //   7: ifeq +4 -> 11
    //   10: return
    //   11: aload_0
    //   12: invokespecial 384	com/d/a/b/n:b	()Z
    //   15: ifne -5 -> 10
    //   18: aload_0
    //   19: getfield 60	com/d/a/b/n:h	Lcom/d/a/b/m;
    //   22: getfield 387	com/d/a/b/m:h	Ljava/util/concurrent/locks/ReentrantLock;
    //   25: astore_3
    //   26: ldc_w 389
    //   29: iconst_1
    //   30: anewarray 4	java/lang/Object
    //   33: dup
    //   34: iconst_0
    //   35: aload_0
    //   36: getfield 96	com/d/a/b/n:n	Ljava/lang/String;
    //   39: aastore
    //   40: invokestatic 191	com/d/a/c/d:a	(Ljava/lang/String;[Ljava/lang/Object;)V
    //   43: aload_3
    //   44: invokevirtual 394	java/util/concurrent/locks/ReentrantLock:isLocked	()Z
    //   47: ifeq +20 -> 67
    //   50: ldc_w 396
    //   53: iconst_1
    //   54: anewarray 4	java/lang/Object
    //   57: dup
    //   58: iconst_0
    //   59: aload_0
    //   60: getfield 96	com/d/a/b/n:n	Ljava/lang/String;
    //   63: aastore
    //   64: invokestatic 191	com/d/a/c/d:a	(Ljava/lang/String;[Ljava/lang/Object;)V
    //   67: aload_3
    //   68: invokevirtual 399	java/util/concurrent/locks/ReentrantLock:lock	()V
    //   71: aload_0
    //   72: invokespecial 247	com/d/a/b/n:f	()V
    //   75: aload_0
    //   76: getfield 67	com/d/a/b/n:a	Lcom/d/a/b/h;
    //   79: getfield 402	com/d/a/b/h:n	Lcom/d/a/a/b/c;
    //   82: aload_0
    //   83: getfield 96	com/d/a/b/n:n	Ljava/lang/String;
    //   86: invokeinterface 407 2 0
    //   91: checkcast 263	android/graphics/Bitmap
    //   94: astore_2
    //   95: aload_2
    //   96: ifnull +10 -> 106
    //   99: aload_2
    //   100: invokevirtual 410	android/graphics/Bitmap:isRecycled	()Z
    //   103: ifeq +277 -> 380
    //   106: aload_0
    //   107: invokespecial 412	com/d/a/b/n:c	()Landroid/graphics/Bitmap;
    //   110: astore_1
    //   111: aload_1
    //   112: ifnonnull +8 -> 120
    //   115: aload_3
    //   116: invokevirtual 415	java/util/concurrent/locks/ReentrantLock:unlock	()V
    //   119: return
    //   120: aload_0
    //   121: invokespecial 247	com/d/a/b/n:f	()V
    //   124: aload_0
    //   125: invokespecial 417	com/d/a/b/n:j	()V
    //   128: aload_0
    //   129: getfield 107	com/d/a/b/n:d	Lcom/d/a/b/d;
    //   132: getfield 419	com/d/a/b/d:o	Lcom/d/a/b/g/a;
    //   135: ifnull +239 -> 374
    //   138: iload 4
    //   140: ifeq +58 -> 198
    //   143: ldc_w 421
    //   146: iconst_1
    //   147: anewarray 4	java/lang/Object
    //   150: dup
    //   151: iconst_0
    //   152: aload_0
    //   153: getfield 96	com/d/a/b/n:n	Ljava/lang/String;
    //   156: aastore
    //   157: invokestatic 191	com/d/a/c/d:a	(Ljava/lang/String;[Ljava/lang/Object;)V
    //   160: aload_0
    //   161: getfield 107	com/d/a/b/n:d	Lcom/d/a/b/d;
    //   164: getfield 419	com/d/a/b/d:o	Lcom/d/a/b/g/a;
    //   167: invokeinterface 339 1 0
    //   172: astore_2
    //   173: aload_2
    //   174: astore_1
    //   175: aload_2
    //   176: ifnonnull +22 -> 198
    //   179: ldc_w 423
    //   182: iconst_1
    //   183: anewarray 4	java/lang/Object
    //   186: dup
    //   187: iconst_0
    //   188: aload_0
    //   189: getfield 96	com/d/a/b/n:n	Ljava/lang/String;
    //   192: aastore
    //   193: invokestatic 200	com/d/a/c/d:d	(Ljava/lang/String;[Ljava/lang/Object;)V
    //   196: aload_2
    //   197: astore_1
    //   198: aload_1
    //   199: astore_2
    //   200: aload_1
    //   201: ifnull +52 -> 253
    //   204: aload_1
    //   205: astore_2
    //   206: aload_0
    //   207: getfield 107	com/d/a/b/n:d	Lcom/d/a/b/d;
    //   210: getfield 425	com/d/a/b/d:h	Z
    //   213: ifeq +40 -> 253
    //   216: ldc_w 427
    //   219: iconst_1
    //   220: anewarray 4	java/lang/Object
    //   223: dup
    //   224: iconst_0
    //   225: aload_0
    //   226: getfield 96	com/d/a/b/n:n	Ljava/lang/String;
    //   229: aastore
    //   230: invokestatic 191	com/d/a/c/d:a	(Ljava/lang/String;[Ljava/lang/Object;)V
    //   233: aload_0
    //   234: getfield 67	com/d/a/b/n:a	Lcom/d/a/b/h;
    //   237: getfield 402	com/d/a/b/h:n	Lcom/d/a/a/b/c;
    //   240: aload_0
    //   241: getfield 96	com/d/a/b/n:n	Ljava/lang/String;
    //   244: aload_1
    //   245: invokeinterface 430 3 0
    //   250: pop
    //   251: aload_1
    //   252: astore_2
    //   253: aload_2
    //   254: astore_1
    //   255: aload_2
    //   256: ifnull +70 -> 326
    //   259: aload_2
    //   260: astore_1
    //   261: aload_0
    //   262: getfield 107	com/d/a/b/n:d	Lcom/d/a/b/d;
    //   265: invokevirtual 431	com/d/a/b/d:a	()Z
    //   268: ifeq +58 -> 326
    //   271: ldc_w 433
    //   274: iconst_1
    //   275: anewarray 4	java/lang/Object
    //   278: dup
    //   279: iconst_0
    //   280: aload_0
    //   281: getfield 96	com/d/a/b/n:n	Ljava/lang/String;
    //   284: aastore
    //   285: invokestatic 191	com/d/a/c/d:a	(Ljava/lang/String;[Ljava/lang/Object;)V
    //   288: aload_0
    //   289: getfield 107	com/d/a/b/n:d	Lcom/d/a/b/d;
    //   292: getfield 435	com/d/a/b/d:p	Lcom/d/a/b/g/a;
    //   295: invokeinterface 339 1 0
    //   300: astore_2
    //   301: aload_2
    //   302: astore_1
    //   303: aload_2
    //   304: ifnonnull +22 -> 326
    //   307: ldc_w 437
    //   310: iconst_1
    //   311: anewarray 4	java/lang/Object
    //   314: dup
    //   315: iconst_0
    //   316: aload_0
    //   317: getfield 96	com/d/a/b/n:n	Ljava/lang/String;
    //   320: aastore
    //   321: invokestatic 200	com/d/a/c/d:d	(Ljava/lang/String;[Ljava/lang/Object;)V
    //   324: aload_2
    //   325: astore_1
    //   326: aload_0
    //   327: invokespecial 247	com/d/a/b/n:f	()V
    //   330: aload_0
    //   331: invokespecial 417	com/d/a/b/n:j	()V
    //   334: aload_3
    //   335: invokevirtual 415	java/util/concurrent/locks/ReentrantLock:unlock	()V
    //   338: new 439	com/d/a/b/c
    //   341: dup
    //   342: aload_1
    //   343: aload_0
    //   344: getfield 60	com/d/a/b/n:h	Lcom/d/a/b/m;
    //   347: aload_0
    //   348: getfield 58	com/d/a/b/n:g	Lcom/d/a/b/l;
    //   351: aload_0
    //   352: getfield 56	com/d/a/b/n:q	Lcom/d/a/b/a/g;
    //   355: invokespecial 442	com/d/a/b/c:<init>	(Landroid/graphics/Bitmap;Lcom/d/a/b/m;Lcom/d/a/b/l;Lcom/d/a/b/a/g;)V
    //   358: aload_0
    //   359: getfield 121	com/d/a/b/n:p	Z
    //   362: aload_0
    //   363: getfield 62	com/d/a/b/n:i	Landroid/os/Handler;
    //   366: aload_0
    //   367: getfield 58	com/d/a/b/n:g	Lcom/d/a/b/l;
    //   370: invokestatic 153	com/d/a/b/n:a	(Ljava/lang/Runnable;ZLandroid/os/Handler;Lcom/d/a/b/l;)V
    //   373: return
    //   374: iconst_0
    //   375: istore 4
    //   377: goto -239 -> 138
    //   380: aload_0
    //   381: getstatic 444	com/d/a/b/a/g:c	Lcom/d/a/b/a/g;
    //   384: putfield 56	com/d/a/b/n:q	Lcom/d/a/b/a/g;
    //   387: ldc_w 446
    //   390: iconst_1
    //   391: anewarray 4	java/lang/Object
    //   394: dup
    //   395: iconst_0
    //   396: aload_0
    //   397: getfield 96	com/d/a/b/n:n	Ljava/lang/String;
    //   400: aastore
    //   401: invokestatic 191	com/d/a/c/d:a	(Ljava/lang/String;[Ljava/lang/Object;)V
    //   404: goto -151 -> 253
    //   407: astore_1
    //   408: aload_0
    //   409: getfield 121	com/d/a/b/n:p	Z
    //   412: ifne +14 -> 426
    //   415: aload_0
    //   416: invokespecial 145	com/d/a/b/n:k	()Z
    //   419: istore 5
    //   421: iload 5
    //   423: ifeq +8 -> 431
    //   426: aload_3
    //   427: invokevirtual 415	java/util/concurrent/locks/ReentrantLock:unlock	()V
    //   430: return
    //   431: new 14	com/d/a/b/n$3
    //   434: dup
    //   435: aload_0
    //   436: invokespecial 447	com/d/a/b/n$3:<init>	(Lcom/d/a/b/n;)V
    //   439: iconst_0
    //   440: aload_0
    //   441: getfield 62	com/d/a/b/n:i	Landroid/os/Handler;
    //   444: aload_0
    //   445: getfield 58	com/d/a/b/n:g	Lcom/d/a/b/l;
    //   448: invokestatic 153	com/d/a/b/n:a	(Ljava/lang/Runnable;ZLandroid/os/Handler;Lcom/d/a/b/l;)V
    //   451: goto -25 -> 426
    //   454: astore_1
    //   455: aload_3
    //   456: invokevirtual 415	java/util/concurrent/locks/ReentrantLock:unlock	()V
    //   459: aload_1
    //   460: athrow
    // Local variable table:
    //   start	length	slot	name	signature
    //   0	461	0	this	n
    //   110	233	1	localObject1	Object
    //   407	1	1	localo	o
    //   454	6	1	localObject2	Object
    //   94	231	2	localObject3	Object
    //   25	431	3	localReentrantLock	java.util.concurrent.locks.ReentrantLock
    //   1	375	4	i1	int
    //   419	3	5	bool	boolean
    // Exception table:
    //   from	to	target	type
    //   71	95	407	com/d/a/b/o
    //   99	106	407	com/d/a/b/o
    //   106	111	407	com/d/a/b/o
    //   120	138	407	com/d/a/b/o
    //   143	173	407	com/d/a/b/o
    //   179	196	407	com/d/a/b/o
    //   206	251	407	com/d/a/b/o
    //   261	301	407	com/d/a/b/o
    //   307	324	407	com/d/a/b/o
    //   326	334	407	com/d/a/b/o
    //   380	404	407	com/d/a/b/o
    //   71	95	454	finally
    //   99	106	454	finally
    //   106	111	454	finally
    //   120	138	454	finally
    //   143	173	454	finally
    //   179	196	454	finally
    //   206	251	454	finally
    //   261	301	454	finally
    //   307	324	454	finally
    //   326	334	454	finally
    //   380	404	454	finally
    //   408	421	454	finally
    //   431	451	454	finally
  }
}


/* Location:              E:\apk\xueqiu2\classes-dex2jar.jar!\com\d\a\b\n.class
 * Java compiler version: 6 (50.0)
 * JD-Core Version:       0.7.1
 */