package com.alipay.android.app;

import android.os.IBinder;
import android.os.Parcel;

final class IAlixPay$Stub$a
  implements IAlixPay
{
  private IBinder a;
  
  IAlixPay$Stub$a(IBinder paramIBinder)
  {
    this.a = paramIBinder;
  }
  
  private static String a()
  {
    return "com.alipay.android.app.IAlixPay";
  }
  
  public final String Pay(String paramString)
  {
    Parcel localParcel1 = Parcel.obtain();
    Parcel localParcel2 = Parcel.obtain();
    try
    {
      localParcel1.writeInterfaceToken("com.alipay.android.app.IAlixPay");
      localParcel1.writeString(paramString);
      this.a.transact(1, localParcel1, localParcel2, 0);
      localParcel2.readException();
      paramString = localParcel2.readString();
      return paramString;
    }
    finally
    {
      localParcel2.recycle();
      localParcel1.recycle();
    }
  }
  
  public final IBinder asBinder()
  {
    return this.a;
  }
  
  public final String prePay(String paramString)
  {
    Parcel localParcel1 = Parcel.obtain();
    Parcel localParcel2 = Parcel.obtain();
    try
    {
      localParcel1.writeInterfaceToken("com.alipay.android.app.IAlixPay");
      localParcel1.writeString(paramString);
      this.a.transact(5, localParcel1, localParcel2, 0);
      localParcel2.readException();
      paramString = localParcel2.readString();
      return paramString;
    }
    finally
    {
      localParcel2.recycle();
      localParcel1.recycle();
    }
  }
  
  /* Error */
  public final void registerCallback(IRemoteServiceCallback paramIRemoteServiceCallback)
  {
    // Byte code:
    //   0: invokestatic 27	android/os/Parcel:obtain	()Landroid/os/Parcel;
    //   3: astore_2
    //   4: invokestatic 27	android/os/Parcel:obtain	()Landroid/os/Parcel;
    //   7: astore_3
    //   8: aload_2
    //   9: ldc 19
    //   11: invokevirtual 31	android/os/Parcel:writeInterfaceToken	(Ljava/lang/String;)V
    //   14: aload_1
    //   15: ifnull +42 -> 57
    //   18: aload_1
    //   19: invokeinterface 58 1 0
    //   24: astore_1
    //   25: aload_2
    //   26: aload_1
    //   27: invokevirtual 61	android/os/Parcel:writeStrongBinder	(Landroid/os/IBinder;)V
    //   30: aload_0
    //   31: getfield 15	com/alipay/android/app/IAlixPay$Stub$a:a	Landroid/os/IBinder;
    //   34: iconst_3
    //   35: aload_2
    //   36: aload_3
    //   37: iconst_0
    //   38: invokeinterface 40 5 0
    //   43: pop
    //   44: aload_3
    //   45: invokevirtual 43	android/os/Parcel:readException	()V
    //   48: aload_3
    //   49: invokevirtual 49	android/os/Parcel:recycle	()V
    //   52: aload_2
    //   53: invokevirtual 49	android/os/Parcel:recycle	()V
    //   56: return
    //   57: aconst_null
    //   58: astore_1
    //   59: goto -34 -> 25
    //   62: astore_1
    //   63: aload_3
    //   64: invokevirtual 49	android/os/Parcel:recycle	()V
    //   67: aload_2
    //   68: invokevirtual 49	android/os/Parcel:recycle	()V
    //   71: aload_1
    //   72: athrow
    // Local variable table:
    //   start	length	slot	name	signature
    //   0	73	0	this	a
    //   0	73	1	paramIRemoteServiceCallback	IRemoteServiceCallback
    //   3	65	2	localParcel1	Parcel
    //   7	57	3	localParcel2	Parcel
    // Exception table:
    //   from	to	target	type
    //   8	14	62	finally
    //   18	25	62	finally
    //   25	48	62	finally
  }
  
  public final String test()
  {
    Parcel localParcel1 = Parcel.obtain();
    Parcel localParcel2 = Parcel.obtain();
    try
    {
      localParcel1.writeInterfaceToken("com.alipay.android.app.IAlixPay");
      this.a.transact(2, localParcel1, localParcel2, 0);
      localParcel2.readException();
      String str = localParcel2.readString();
      return str;
    }
    finally
    {
      localParcel2.recycle();
      localParcel1.recycle();
    }
  }
  
  /* Error */
  public final void unregisterCallback(IRemoteServiceCallback paramIRemoteServiceCallback)
  {
    // Byte code:
    //   0: invokestatic 27	android/os/Parcel:obtain	()Landroid/os/Parcel;
    //   3: astore_2
    //   4: invokestatic 27	android/os/Parcel:obtain	()Landroid/os/Parcel;
    //   7: astore_3
    //   8: aload_2
    //   9: ldc 19
    //   11: invokevirtual 31	android/os/Parcel:writeInterfaceToken	(Ljava/lang/String;)V
    //   14: aload_1
    //   15: ifnull +42 -> 57
    //   18: aload_1
    //   19: invokeinterface 58 1 0
    //   24: astore_1
    //   25: aload_2
    //   26: aload_1
    //   27: invokevirtual 61	android/os/Parcel:writeStrongBinder	(Landroid/os/IBinder;)V
    //   30: aload_0
    //   31: getfield 15	com/alipay/android/app/IAlixPay$Stub$a:a	Landroid/os/IBinder;
    //   34: iconst_4
    //   35: aload_2
    //   36: aload_3
    //   37: iconst_0
    //   38: invokeinterface 40 5 0
    //   43: pop
    //   44: aload_3
    //   45: invokevirtual 43	android/os/Parcel:readException	()V
    //   48: aload_3
    //   49: invokevirtual 49	android/os/Parcel:recycle	()V
    //   52: aload_2
    //   53: invokevirtual 49	android/os/Parcel:recycle	()V
    //   56: return
    //   57: aconst_null
    //   58: astore_1
    //   59: goto -34 -> 25
    //   62: astore_1
    //   63: aload_3
    //   64: invokevirtual 49	android/os/Parcel:recycle	()V
    //   67: aload_2
    //   68: invokevirtual 49	android/os/Parcel:recycle	()V
    //   71: aload_1
    //   72: athrow
    // Local variable table:
    //   start	length	slot	name	signature
    //   0	73	0	this	a
    //   0	73	1	paramIRemoteServiceCallback	IRemoteServiceCallback
    //   3	65	2	localParcel1	Parcel
    //   7	57	3	localParcel2	Parcel
    // Exception table:
    //   from	to	target	type
    //   8	14	62	finally
    //   18	25	62	finally
    //   25	48	62	finally
  }
}


/* Location:              E:\apk\xueqiu2\classes-dex2jar.jar!\com\alipay\android\app\IAlixPay$Stub$a.class
 * Java compiler version: 6 (50.0)
 * JD-Core Version:       0.7.1
 */